package bigname.zprestige.webhack.features.modules.Movement;

import Perryc;

public enum Strafe$Mode {
  NCP, NONE, STRAFE;
  
  public static Strafe$Mode[] $VALUES;
  
  static {
    // Byte code:
    //   0: new bigname/zprestige/webhack/features/modules/Movement/Strafe$Mode
    //   3: dup
    //   4: ldc '혤㌼홆ㅉ'
    //   6: getstatic Perryc.c : I
    //   9: iflt -> 22
    //   12: ldc2_w 835200165
    //   15: l2i
    //   16: ldc -670534200
    //   18: ixor
    //   19: goto -> 29
    //   22: ldc2_w 1626294211
    //   25: l2i
    //   26: ldc 1217806095
    //   28: ixor
    //   29: ldc2_w 724094059
    //   32: l2i
    //   33: ldc -1042757469
    //   35: ixor
    //   36: ixor
    //   37: lookupswitch default -> 64, 53499301 -> 896, 963085021 -> 22
    //   64: invokestatic 0 : (Ljava/lang/String;)Ljava/lang/String;
    //   67: ldc2_w -1052712445
    //   70: l2i
    //   71: ldc -1052712445
    //   73: ixor
    //   74: getstatic Perryc.0 : I
    //   77: ifle -> 90
    //   80: ldc2_w 1905453597
    //   83: l2i
    //   84: ldc 2096133781
    //   86: ixor
    //   87: goto -> 97
    //   90: ldc2_w -445739689
    //   93: l2i
    //   94: ldc -2016004150
    //   96: ixor
    //   97: ldc2_w 1196909970
    //   100: l2i
    //   101: ldc 208763063
    //   103: ixor
    //   104: ixor
    //   105: lookupswitch default -> 886, 698263480 -> 132, 1178894765 -> 90
    //   132: invokespecial <init> : (Ljava/lang/String;I)V
    //   135: getstatic Perryc.0 : I
    //   138: ifle -> 151
    //   141: ldc2_w -779373674
    //   144: l2i
    //   145: ldc 654081415
    //   147: ixor
    //   148: goto -> 158
    //   151: ldc2_w 552354457
    //   154: l2i
    //   155: ldc 1526799073
    //   157: ixor
    //   158: ldc2_w -41950028
    //   161: l2i
    //   162: ldc 373322543
    //   164: ixor
    //   165: ixor
    //   166: lookupswitch default -> 192, -356294869 -> 151, 474503562 -> 878
    //   192: putstatic bigname/zprestige/webhack/features/modules/Movement/Strafe$Mode.NONE : Lbigname/zprestige/webhack/features/modules/Movement/Strafe$Mode;
    //   195: new bigname/zprestige/webhack/features/modules/Movement/Strafe$Mode
    //   198: dup
    //   199: ldc '혤㌰환'
    //   201: getstatic Perryc.0 : I
    //   204: ifle -> 217
    //   207: ldc2_w 1214885786
    //   210: l2i
    //   211: ldc 900662173
    //   213: ixor
    //   214: goto -> 224
    //   217: ldc2_w 1806729385
    //   220: l2i
    //   221: ldc -1456493152
    //   223: ixor
    //   224: ldc2_w 1627312674
    //   227: l2i
    //   228: ldc 1989574620
    //   230: ixor
    //   231: ixor
    //   232: lookupswitch default -> 260, -1175115322 -> 217, 1806565881 -> 874
    //   260: invokestatic 0 : (Ljava/lang/String;)Ljava/lang/String;
    //   263: ldc2_w -169439699
    //   266: l2i
    //   267: ldc -169439700
    //   269: ixor
    //   270: getstatic Perryc.1 : I
    //   273: ifeq -> 286
    //   276: ldc2_w -1159607570
    //   279: l2i
    //   280: ldc -1483535150
    //   282: ixor
    //   283: goto -> 293
    //   286: ldc2_w -527636248
    //   289: l2i
    //   290: ldc 101987125
    //   292: ixor
    //   293: ldc2_w 1770617583
    //   296: l2i
    //   297: ldc 98847582
    //   299: ixor
    //   300: ixor
    //   301: lookupswitch default -> 880, -1963595156 -> 328, 1897920397 -> 286
    //   328: invokespecial <init> : (Ljava/lang/String;I)V
    //   331: getstatic Perryc.c : I
    //   334: iflt -> 347
    //   337: ldc2_w -2021442299
    //   340: l2i
    //   341: ldc -270163995
    //   343: ixor
    //   344: goto -> 354
    //   347: ldc2_w -1299248529
    //   350: l2i
    //   351: ldc 14020065
    //   353: ixor
    //   354: ldc2_w 151440027
    //   357: l2i
    //   358: ldc 1794510656
    //   360: ixor
    //   361: ixor
    //   362: lookupswitch default -> 388, -611146942 -> 347, 194406203 -> 882
    //   388: putstatic bigname/zprestige/webhack/features/modules/Movement/Strafe$Mode.NCP : Lbigname/zprestige/webhack/features/modules/Movement/Strafe$Mode;
    //   391: new bigname/zprestige/webhack/features/modules/Movement/Strafe$Mode
    //   394: dup
    //   395: ldc '혹㌧홚ㅍ馜㢓'
    //   397: getstatic Perryc.0 : I
    //   400: ifle -> 413
    //   403: ldc2_w -1605155145
    //   406: l2i
    //   407: ldc -632461237
    //   409: ixor
    //   410: goto -> 420
    //   413: ldc2_w -2030425345
    //   416: l2i
    //   417: ldc 356635508
    //   419: ixor
    //   420: ldc2_w -750893307
    //   423: l2i
    //   424: ldc -2065641468
    //   426: ixor
    //   427: ixor
    //   428: lookupswitch default -> 892, -999985526 -> 456, 767605245 -> 413
    //   456: invokestatic 0 : (Ljava/lang/String;)Ljava/lang/String;
    //   459: ldc2_w 383945609
    //   462: l2i
    //   463: ldc 383945611
    //   465: ixor
    //   466: getstatic Perryc.c : I
    //   469: iflt -> 482
    //   472: ldc2_w -2095160119
    //   475: l2i
    //   476: ldc -1907719033
    //   478: ixor
    //   479: goto -> 489
    //   482: ldc2_w 1847892537
    //   485: l2i
    //   486: ldc 1159232879
    //   488: ixor
    //   489: ldc2_w -1548635221
    //   492: l2i
    //   493: ldc -2012504998
    //   495: ixor
    //   496: ixor
    //   497: lookupswitch default -> 888, 8833191 -> 524, 653184959 -> 482
    //   524: invokespecial <init> : (Ljava/lang/String;I)V
    //   527: getstatic Perryc.0 : I
    //   530: ifle -> 543
    //   533: ldc2_w -935736121
    //   536: l2i
    //   537: ldc -790736313
    //   539: ixor
    //   540: goto -> 550
    //   543: ldc2_w 1899336152
    //   546: l2i
    //   547: ldc -729386519
    //   549: ixor
    //   550: ldc2_w -253245590
    //   553: l2i
    //   554: ldc -301022841
    //   556: ixor
    //   557: ixor
    //   558: lookupswitch default -> 890, -1151670564 -> 584, 101619821 -> 543
    //   584: putstatic bigname/zprestige/webhack/features/modules/Movement/Strafe$Mode.STRAFE : Lbigname/zprestige/webhack/features/modules/Movement/Strafe$Mode;
    //   587: ldc2_w -440914243
    //   590: l2i
    //   591: ldc -440914242
    //   593: ixor
    //   594: anewarray bigname/zprestige/webhack/features/modules/Movement/Strafe$Mode
    //   597: dup
    //   598: ldc2_w -665715176
    //   601: l2i
    //   602: ldc -665715176
    //   604: ixor
    //   605: getstatic Perryc.0 : I
    //   608: ifle -> 621
    //   611: ldc2_w 1118214583
    //   614: l2i
    //   615: ldc -1787111708
    //   617: ixor
    //   618: goto -> 628
    //   621: ldc2_w 1266832563
    //   624: l2i
    //   625: ldc 566680769
    //   627: ixor
    //   628: ldc2_w 1535579722
    //   631: l2i
    //   632: ldc 924110310
    //   634: ixor
    //   635: ixor
    //   636: lookupswitch default -> 894, -1152412417 -> 621, 114775006 -> 664
    //   664: getstatic bigname/zprestige/webhack/features/modules/Movement/Strafe$Mode.NONE : Lbigname/zprestige/webhack/features/modules/Movement/Strafe$Mode;
    //   667: aastore
    //   668: dup
    //   669: ldc2_w -2047571016
    //   672: l2i
    //   673: ldc -2047571015
    //   675: ixor
    //   676: getstatic Perryc.c : I
    //   679: iflt -> 692
    //   682: ldc2_w 348652744
    //   685: l2i
    //   686: ldc -610801032
    //   688: ixor
    //   689: goto -> 699
    //   692: ldc2_w 1472028941
    //   695: l2i
    //   696: ldc -182151493
    //   698: ixor
    //   699: ldc2_w 674945949
    //   702: l2i
    //   703: ldc 1349820860
    //   705: ixor
    //   706: ixor
    //   707: lookupswitch default -> 872, -1223584623 -> 692, -623407721 -> 732
    //   732: getstatic bigname/zprestige/webhack/features/modules/Movement/Strafe$Mode.NCP : Lbigname/zprestige/webhack/features/modules/Movement/Strafe$Mode;
    //   735: aastore
    //   736: dup
    //   737: ldc2_w -708291312
    //   740: l2i
    //   741: ldc -708291310
    //   743: ixor
    //   744: getstatic Perryc.c : I
    //   747: iflt -> 760
    //   750: ldc2_w 461561465
    //   753: l2i
    //   754: ldc -1637245723
    //   756: ixor
    //   757: goto -> 767
    //   760: ldc2_w 1174817021
    //   763: l2i
    //   764: ldc -167177505
    //   766: ixor
    //   767: ldc2_w 1856695383
    //   770: l2i
    //   771: ldc_w -885124301
    //   774: ixor
    //   775: ixor
    //   776: lookupswitch default -> 884, 362521926 -> 804, 545242616 -> 760
    //   804: getstatic bigname/zprestige/webhack/features/modules/Movement/Strafe$Mode.STRAFE : Lbigname/zprestige/webhack/features/modules/Movement/Strafe$Mode;
    //   807: aastore
    //   808: getstatic Perryc.c : I
    //   811: iflt -> 825
    //   814: ldc2_w 148334709
    //   817: l2i
    //   818: ldc_w 83503857
    //   821: ixor
    //   822: goto -> 833
    //   825: ldc2_w 1444930565
    //   828: l2i
    //   829: ldc_w 1068168697
    //   832: ixor
    //   833: ldc2_w -2104837354
    //   836: l2i
    //   837: ldc_w -560713043
    //   840: ixor
    //   841: ixor
    //   842: lookupswitch default -> 868, -1159022315 -> 825, 1345571647 -> 876
    //   868: putstatic bigname/zprestige/webhack/features/modules/Movement/Strafe$Mode.$VALUES : [Lbigname/zprestige/webhack/features/modules/Movement/Strafe$Mode;
    //   871: return
    //   872: aconst_null
    //   873: athrow
    //   874: aconst_null
    //   875: athrow
    //   876: aconst_null
    //   877: athrow
    //   878: aconst_null
    //   879: athrow
    //   880: aconst_null
    //   881: athrow
    //   882: aconst_null
    //   883: athrow
    //   884: aconst_null
    //   885: athrow
    //   886: aconst_null
    //   887: athrow
    //   888: aconst_null
    //   889: athrow
    //   890: aconst_null
    //   891: athrow
    //   892: aconst_null
    //   893: athrow
    //   894: aconst_null
    //   895: athrow
    //   896: aconst_null
    //   897: athrow
  }
}


/* Location:              C:\Users\alex\Desktop\webhack\WebHack-0.8-obf_sussy_1.jar!\bigname\zprestige\webhack\features\modules\Movement\Strafe$Mode.class
 * Java compiler version: 8 (52.0)
 * JD-Core Version:       1.1.3
 */