package bigname.zprestige.webhack.event.events;

import bigname.zprestige.webhack.event.EventStage;
import net.minecraft.entity.player.EntityPlayer;

public class DeathEvent extends EventStage {
  public EntityPlayer player;
  
  static {
    throw SYNTHETIC_LOCAL_VARIABLE_0;
  }
  
  public DeathEvent(EntityPlayer player) {
    // Byte code:
    //   0: getstatic Perryc.c : I
    //   3: iflt -> 16
    //   6: ldc2_w -2142189157
    //   9: l2i
    //   10: ldc -1390662097
    //   12: ixor
    //   13: goto -> 23
    //   16: ldc2_w 249514280
    //   19: l2i
    //   20: ldc -553275933
    //   22: ixor
    //   23: ldc2_w -1419234625
    //   26: l2i
    //   27: ldc 1057355424
    //   29: ixor
    //   30: ixor
    //   31: lookupswitch default -> 306, -1189010517 -> 16, 1169629396 -> 56
    //   56: aload_0
    //   57: getstatic Perryc.1 : I
    //   60: ifeq -> 73
    //   63: ldc2_w 497366704
    //   66: l2i
    //   67: ldc 933691683
    //   69: ixor
    //   70: goto -> 80
    //   73: ldc2_w -1443366385
    //   76: l2i
    //   77: ldc -1606020821
    //   79: ixor
    //   80: ldc2_w -1651375975
    //   83: l2i
    //   84: ldc -178279617
    //   86: ixor
    //   87: ixor
    //   88: lookupswitch default -> 116, -750332554 -> 73, 1120902197 -> 308
    //   116: invokespecial <init> : ()V
    //   119: getstatic Perryc.c : I
    //   122: iflt -> 135
    //   125: ldc2_w -1536088019
    //   128: l2i
    //   129: ldc -1715371840
    //   131: ixor
    //   132: goto -> 142
    //   135: ldc2_w -1720104931
    //   138: l2i
    //   139: ldc -658352248
    //   141: ixor
    //   142: ldc2_w -138603207
    //   145: l2i
    //   146: ldc -1604434370
    //   148: ixor
    //   149: ixor
    //   150: lookupswitch default -> 302, 374885522 -> 176, 1783888874 -> 135
    //   176: aload_0
    //   177: getstatic Perryc.0 : I
    //   180: ifle -> 193
    //   183: ldc2_w 32625478
    //   186: l2i
    //   187: ldc -972249505
    //   189: ixor
    //   190: goto -> 200
    //   193: ldc2_w 1790800861
    //   196: l2i
    //   197: ldc -1585532122
    //   199: ixor
    //   200: ldc2_w 1829424861
    //   203: l2i
    //   204: ldc 1136807606
    //   206: ixor
    //   207: ixor
    //   208: lookupswitch default -> 236, -382339726 -> 304, 824901638 -> 193
    //   236: aload_1
    //   237: getstatic Perryc.c : I
    //   240: iflt -> 253
    //   243: ldc2_w -1489766045
    //   246: l2i
    //   247: ldc 2093074499
    //   249: ixor
    //   250: goto -> 260
    //   253: ldc2_w -1790975844
    //   256: l2i
    //   257: ldc -90361456
    //   259: ixor
    //   260: ldc2_w 1364298474
    //   263: l2i
    //   264: ldc 418244875
    //   266: ixor
    //   267: ixor
    //   268: lookupswitch default -> 296, -2128359175 -> 253, -1840360767 -> 300
    //   296: putfield player : Lnet/minecraft/entity/player/EntityPlayer;
    //   299: return
    //   300: aconst_null
    //   301: athrow
    //   302: aconst_null
    //   303: athrow
    //   304: aconst_null
    //   305: athrow
    //   306: aconst_null
    //   307: athrow
    //   308: aconst_null
    //   309: athrow
    // Local variable table:
    //   start	length	slot	name	descriptor
    //   0	300	0	this	Lbigname/zprestige/webhack/event/events/DeathEvent;
    //   0	300	1	player	Lnet/minecraft/entity/player/EntityPlayer;
  }
}


/* Location:              C:\Users\alex\Desktop\webhack\WebHack-0.8-obf_sussy_1.jar!\bigname\zprestige\webhack\event\events\DeathEvent.class
 * Java compiler version: 8 (52.0)
 * JD-Core Version:       1.1.3
 */