package bigname.zprestige.webhack.event.events;

import net.minecraft.network.Packet;
import net.minecraftforge.fml.common.eventhandler.Cancelable;

@Cancelable
public class PacketEvent$Send extends PacketEvent {
  static {
    throw SYNTHETIC_LOCAL_VARIABLE_0;
  }
  
  public PacketEvent$Send(int stage, Packet<?> packet) {
    // Byte code:
    //   0: getstatic Perryc.1 : I
    //   3: ifeq -> 16
    //   6: ldc2_w 274515353
    //   9: l2i
    //   10: ldc -1149403844
    //   12: ixor
    //   13: goto -> 23
    //   16: ldc2_w -615394968
    //   19: l2i
    //   20: ldc 670658956
    //   22: ixor
    //   23: ldc2_w -2000627964
    //   26: l2i
    //   27: ldc 37086294
    //   29: ixor
    //   30: ixor
    //   31: lookupswitch default -> 56, 567577591 -> 244, 1094637779 -> 16
    //   56: aload_0
    //   57: getstatic Perryc.0 : I
    //   60: ifle -> 73
    //   63: ldc2_w 2073918252
    //   66: l2i
    //   67: ldc 1295604940
    //   69: ixor
    //   70: goto -> 80
    //   73: ldc2_w 1537165502
    //   76: l2i
    //   77: ldc -1584846666
    //   79: ixor
    //   80: ldc2_w 1718074006
    //   83: l2i
    //   84: ldc -2066661805
    //   86: ixor
    //   87: ixor
    //   88: lookupswitch default -> 242, -736976091 -> 73, 413197517 -> 116
    //   116: iload_1
    //   117: getstatic Perryc.0 : I
    //   120: ifle -> 133
    //   123: ldc2_w 695970108
    //   126: l2i
    //   127: ldc 1613956523
    //   129: ixor
    //   130: goto -> 140
    //   133: ldc2_w 2062452492
    //   136: l2i
    //   137: ldc 165410305
    //   139: ixor
    //   140: ldc2_w -2089464871
    //   143: l2i
    //   144: ldc 186697819
    //   146: ixor
    //   147: ixor
    //   148: lookupswitch default -> 176, -1055052011 -> 246, 148269669 -> 133
    //   176: aload_2
    //   177: getstatic Perryc.0 : I
    //   180: ifle -> 193
    //   183: ldc2_w 1185015784
    //   186: l2i
    //   187: ldc 868951937
    //   189: ixor
    //   190: goto -> 200
    //   193: ldc2_w -1241391804
    //   196: l2i
    //   197: ldc -2014956184
    //   199: ixor
    //   200: ldc2_w -103843105
    //   203: l2i
    //   204: ldc -1197084044
    //   206: ixor
    //   207: ixor
    //   208: lookupswitch default -> 236, 662535812 -> 193, 872433858 -> 240
    //   236: invokespecial <init> : (ILnet/minecraft/network/Packet;)V
    //   239: return
    //   240: aconst_null
    //   241: athrow
    //   242: aconst_null
    //   243: athrow
    //   244: aconst_null
    //   245: athrow
    //   246: aconst_null
    //   247: athrow
    // Local variable table:
    //   start	length	slot	name	descriptor
    //   0	240	0	this	Lbigname/zprestige/webhack/event/events/PacketEvent$Send;
    //   0	240	1	stage	I
    //   0	240	2	packet	Lnet/minecraft/network/Packet;
    // Local variable type table:
    //   start	length	slot	name	signature
    //   0	240	2	packet	Lnet/minecraft/network/Packet<*>;
  }
}


/* Location:              C:\Users\alex\Desktop\webhack\WebHack-0.8-obf_sussy_1.jar!\bigname\zprestige\webhack\event\events\PacketEvent$Send.class
 * Java compiler version: 8 (52.0)
 * JD-Core Version:       1.1.3
 */