package bigname.zprestige.webhack.event.events;

import net.minecraft.network.Packet;
import net.minecraftforge.fml.common.eventhandler.Cancelable;

@Cancelable
public class PacketEvent$Receive extends PacketEvent {
  static {
    throw SYNTHETIC_LOCAL_VARIABLE_0;
  }
  
  public PacketEvent$Receive(int stage, Packet<?> packet) {
    // Byte code:
    //   0: getstatic Perryc.0 : I
    //   3: ifle -> 16
    //   6: ldc2_w 879578989
    //   9: l2i
    //   10: ldc 1437471147
    //   12: ixor
    //   13: goto -> 23
    //   16: ldc2_w -824677828
    //   19: l2i
    //   20: ldc 572077382
    //   22: ixor
    //   23: ldc2_w -15070956
    //   26: l2i
    //   27: ldc 1654387542
    //   29: ixor
    //   30: ixor
    //   31: lookupswitch default -> 246, -62741372 -> 16, 1900062008 -> 56
    //   56: aload_0
    //   57: getstatic Perryc.1 : I
    //   60: ifeq -> 73
    //   63: ldc2_w -1729122901
    //   66: l2i
    //   67: ldc -134836391
    //   69: ixor
    //   70: goto -> 80
    //   73: ldc2_w -448539611
    //   76: l2i
    //   77: ldc -1392793667
    //   79: ixor
    //   80: ldc2_w -1167593579
    //   83: l2i
    //   84: ldc -790593265
    //   86: ixor
    //   87: ixor
    //   88: lookupswitch default -> 244, 94260328 -> 73, 591338754 -> 116
    //   116: iload_1
    //   117: getstatic Perryc.c : I
    //   120: iflt -> 133
    //   123: ldc2_w 1194036478
    //   126: l2i
    //   127: ldc 1471798406
    //   129: ixor
    //   130: goto -> 140
    //   133: ldc2_w -289575855
    //   136: l2i
    //   137: ldc 1434537208
    //   139: ixor
    //   140: ldc2_w 192015007
    //   143: l2i
    //   144: ldc 789384790
    //   146: ixor
    //   147: ixor
    //   148: lookupswitch default -> 240, -1623145376 -> 176, 888059057 -> 133
    //   176: aload_2
    //   177: getstatic Perryc.1 : I
    //   180: ifeq -> 193
    //   183: ldc2_w 748628575
    //   186: l2i
    //   187: ldc 1452874090
    //   189: ixor
    //   190: goto -> 200
    //   193: ldc2_w -211313990
    //   196: l2i
    //   197: ldc 746632770
    //   199: ixor
    //   200: ldc2_w -1647710866
    //   203: l2i
    //   204: ldc 697021771
    //   206: ixor
    //   207: ixor
    //   208: lookupswitch default -> 242, -834376944 -> 193, 1806005469 -> 236
    //   236: invokespecial <init> : (ILnet/minecraft/network/Packet;)V
    //   239: return
    //   240: aconst_null
    //   241: athrow
    //   242: aconst_null
    //   243: athrow
    //   244: aconst_null
    //   245: athrow
    //   246: aconst_null
    //   247: athrow
    // Local variable table:
    //   start	length	slot	name	descriptor
    //   0	240	0	this	Lbigname/zprestige/webhack/event/events/PacketEvent$Receive;
    //   0	240	1	stage	I
    //   0	240	2	packet	Lnet/minecraft/network/Packet;
    // Local variable type table:
    //   start	length	slot	name	signature
    //   0	240	2	packet	Lnet/minecraft/network/Packet<*>;
  }
}


/* Location:              C:\Users\alex\Desktop\webhack\WebHack-0.8-obf_sussy_1.jar!\bigname\zprestige\webhack\event\events\PacketEvent$Receive.class
 * Java compiler version: 8 (52.0)
 * JD-Core Version:       1.1.3
 */