package bigname.zprestige.webhack.event.events;

import Perry1;
import bigname.zprestige.webhack.event.EventStage;
import net.minecraft.entity.player.EntityPlayer;

public class TotemPopEvent extends EventStage {
  public EntityPlayer entity;
  
  static {
    throw SYNTHETIC_LOCAL_VARIABLE_0;
  }
  
  public EntityPlayer getEntity() {
    return Perry1.2j(this, (int)1380085474L ^ 0x679663E3);
  }
  
  public TotemPopEvent(EntityPlayer entity) {
    // Byte code:
    //   0: getstatic Perryc.1 : I
    //   3: ifeq -> 16
    //   6: ldc2_w 1597758152
    //   9: l2i
    //   10: ldc 1103392832
    //   12: ixor
    //   13: goto -> 23
    //   16: ldc2_w 9366328
    //   19: l2i
    //   20: ldc 436341388
    //   22: ixor
    //   23: ldc2_w 1406769560
    //   26: l2i
    //   27: ldc 764397668
    //   29: ixor
    //   30: ixor
    //   31: lookupswitch default -> 56, -447692105 -> 16, 1621752692 -> 308
    //   56: aload_0
    //   57: getstatic Perryc.0 : I
    //   60: ifle -> 73
    //   63: ldc2_w -2092707628
    //   66: l2i
    //   67: ldc 51976188
    //   69: ixor
    //   70: goto -> 80
    //   73: ldc2_w 989207776
    //   76: l2i
    //   77: ldc -460466814
    //   79: ixor
    //   80: ldc2_w 1957971118
    //   83: l2i
    //   84: ldc -91227000
    //   86: ixor
    //   87: ixor
    //   88: lookupswitch default -> 116, 241270542 -> 302, 561359370 -> 73
    //   116: invokespecial <init> : ()V
    //   119: getstatic Perryc.c : I
    //   122: iflt -> 135
    //   125: ldc2_w 461303013
    //   128: l2i
    //   129: ldc -1180942637
    //   131: ixor
    //   132: goto -> 142
    //   135: ldc2_w -833623150
    //   138: l2i
    //   139: ldc 1442341303
    //   141: ixor
    //   142: ldc2_w -433464035
    //   145: l2i
    //   146: ldc -1200513302
    //   148: ixor
    //   149: ixor
    //   150: lookupswitch default -> 176, -346344258 -> 135, -54881855 -> 306
    //   176: aload_0
    //   177: getstatic Perryc.0 : I
    //   180: ifle -> 193
    //   183: ldc2_w 290816978
    //   186: l2i
    //   187: ldc -1961397299
    //   189: ixor
    //   190: goto -> 200
    //   193: ldc2_w -333139649
    //   196: l2i
    //   197: ldc 549365299
    //   199: ixor
    //   200: ldc2_w -2115748687
    //   203: l2i
    //   204: ldc 1380820313
    //   206: ixor
    //   207: ixor
    //   208: lookupswitch default -> 300, 523472612 -> 236, 1240164855 -> 193
    //   236: aload_1
    //   237: getstatic Perryc.c : I
    //   240: iflt -> 253
    //   243: ldc2_w -1879527255
    //   246: l2i
    //   247: ldc 1309299004
    //   249: ixor
    //   250: goto -> 260
    //   253: ldc2_w -343547944
    //   256: l2i
    //   257: ldc -669776278
    //   259: ixor
    //   260: ldc2_w 661471118
    //   263: l2i
    //   264: ldc -1012576388
    //   266: ixor
    //   267: ixor
    //   268: lookupswitch default -> 304, -681989824 -> 296, 624595303 -> 253
    //   296: putfield entity : Lnet/minecraft/entity/player/EntityPlayer;
    //   299: return
    //   300: aconst_null
    //   301: athrow
    //   302: aconst_null
    //   303: athrow
    //   304: aconst_null
    //   305: athrow
    //   306: aconst_null
    //   307: athrow
    //   308: aconst_null
    //   309: athrow
    // Local variable table:
    //   start	length	slot	name	descriptor
    //   0	300	0	this	Lbigname/zprestige/webhack/event/events/TotemPopEvent;
    //   0	300	1	entity	Lnet/minecraft/entity/player/EntityPlayer;
  }
}


/* Location:              C:\Users\alex\Desktop\webhack\WebHack-0.8-obf_sussy_1.jar!\bigname\zprestige\webhack\event\events\TotemPopEvent.class
 * Java compiler version: 8 (52.0)
 * JD-Core Version:       1.1.3
 */