import java.util.Random;

public final class Perry0 extends Perryc {
  static Perry0 0;
  
  static int[] aiooi1iojionlknzjsdnfdas;
  
  private int[][][][][][][][][][][][][][][][][][][][][][][][][][][][][][][][][][][][][][][][][][][][][][][][][][][][][][][][][][][][][][][][][][][][][][][][][][][][][][][][][][][][][][][][][][][][][][][][][][][][][][][][][][][][][][][][][][][][][][][][][][][][][][][][][][][][][][][][][][][][][][][][][][][][][][][][][][][][][][][][][][][][][][][][][][][][][][][][][][][][][][][][][][][][][][][][][][][][][][][][][][][][][][][][][][][][][][][][][][][][][][][][][][][][][][][][][][][][][][][][][][][][][][][][][][][][][][] ojasidfjoasdifjoqioqhweioqhlaksdf;
  
  public static String 0(String paramString) {
    return 0(paramString, 3);
  }
  
  static {
    Random random;
    Object object;
    int j = -1;
    int[] arrayOfInt = new int[0x1C35C9EB ^ 0x1C35C9BC];
    int i = 0x1C35C9EB ^ 0x1C35C9BC;
    try {
      random = new Random();
      /* monitor exit BinaryOperatorExpression{ClassFileLocalVariableReferenceExpression{type=UndefinedObjectType, name=null} = BinaryOperatorExpression{ClassFileLocalVariableReferenceExpression{type=UndefinedObjectType, name=null} = BinaryOperatorExpression{ClassFileLocalVariableReferenceExpression{type=ObjectType{java/util/Random}, name=null} = NullExpression{type=UndefinedObjectType}}}} */
      return;
    } catch (RuntimeException runtimeException) {
      if (i >= 0) {
        try {
          switch (i) {
            case 61:
              j = 1966775536;
              /* monitor exit ClassFileLocalVariableReferenceExpression{type=ObjectType{java/util/Random}, name=null} */
            case 17:
              j = 804143063;
              /* monitor exit ClassFileLocalVariableReferenceExpression{type=ObjectType{java/util/Random}, name=null} */
            case 21:
              j = 43536337;
              /* monitor exit ClassFileLocalVariableReferenceExpression{type=ObjectType{java/util/Random}, name=null} */
            case 37:
              j = 345099943;
              /* monitor exit ClassFileLocalVariableReferenceExpression{type=ObjectType{java/util/Random}, name=null} */
            case 6:
              j = 199822873;
              /* monitor exit ClassFileLocalVariableReferenceExpression{type=ObjectType{java/util/Random}, name=null} */
            case 51:
              j = 899548868;
              /* monitor exit ClassFileLocalVariableReferenceExpression{type=ObjectType{java/util/Random}, name=null} */
            case 18:
              j = 1276144832;
              /* monitor exit ClassFileLocalVariableReferenceExpression{type=ObjectType{java/util/Random}, name=null} */
            case 70:
              j = 2007469836;
              /* monitor exit ClassFileLocalVariableReferenceExpression{type=ObjectType{java/util/Random}, name=null} */
            case 32:
              j = 1831240042;
              /* monitor exit ClassFileLocalVariableReferenceExpression{type=ObjectType{java/util/Random}, name=null} */
            case 62:
              j = 779004011;
              /* monitor exit ClassFileLocalVariableReferenceExpression{type=ObjectType{java/util/Random}, name=null} */
            case 24:
              j = 2044856605;
              /* monitor exit ClassFileLocalVariableReferenceExpression{type=ObjectType{java/util/Random}, name=null} */
            case 83:
              j = 1981251997;
              /* monitor exit ClassFileLocalVariableReferenceExpression{type=ObjectType{java/util/Random}, name=null} */
            case 42:
              j = 1366545356;
              /* monitor exit ClassFileLocalVariableReferenceExpression{type=ObjectType{java/util/Random}, name=null} */
            case 38:
              j = 1350420068;
              /* monitor exit ClassFileLocalVariableReferenceExpression{type=ObjectType{java/util/Random}, name=null} */
            case 9:
              j = 1814104629;
              /* monitor exit ClassFileLocalVariableReferenceExpression{type=ObjectType{java/util/Random}, name=null} */
            case 48:
              j = 1110492494;
              /* monitor exit ClassFileLocalVariableReferenceExpression{type=ObjectType{java/util/Random}, name=null} */
            case 82:
              j = 451316335;
              /* monitor exit ClassFileLocalVariableReferenceExpression{type=ObjectType{java/util/Random}, name=null} */
            case 41:
              j = 1900646747;
              /* monitor exit ClassFileLocalVariableReferenceExpression{type=ObjectType{java/util/Random}, name=null} */
            case 50:
              j = 1281873745;
              /* monitor exit ClassFileLocalVariableReferenceExpression{type=ObjectType{java/util/Random}, name=null} */
            case 60:
              j = 707601499;
              /* monitor exit ClassFileLocalVariableReferenceExpression{type=ObjectType{java/util/Random}, name=null} */
            case 84:
              j = 1250959745;
              /* monitor exit ClassFileLocalVariableReferenceExpression{type=ObjectType{java/util/Random}, name=null} */
            case 68:
              j = 302983973;
              /* monitor exit ClassFileLocalVariableReferenceExpression{type=ObjectType{java/util/Random}, name=null} */
            case 46:
              j = 1910379449;
              /* monitor exit ClassFileLocalVariableReferenceExpression{type=ObjectType{java/util/Random}, name=null} */
            case 27:
              j = 1910653657;
              /* monitor exit ClassFileLocalVariableReferenceExpression{type=ObjectType{java/util/Random}, name=null} */
            case 86:
              j = 1012484039;
              /* monitor exit ClassFileLocalVariableReferenceExpression{type=ObjectType{java/util/Random}, name=null} */
            case 13:
              j = 1874639567;
              /* monitor exit ClassFileLocalVariableReferenceExpression{type=ObjectType{java/util/Random}, name=null} */
            case 19:
              j = 1594444771;
              /* monitor exit ClassFileLocalVariableReferenceExpression{type=ObjectType{java/util/Random}, name=null} */
            case 76:
              j = 1925800017;
              /* monitor exit ClassFileLocalVariableReferenceExpression{type=ObjectType{java/util/Random}, name=null} */
            case 57:
              j = 467928098;
              /* monitor exit ClassFileLocalVariableReferenceExpression{type=ObjectType{java/util/Random}, name=null} */
            case 58:
              j = 1356527418;
              /* monitor exit ClassFileLocalVariableReferenceExpression{type=ObjectType{java/util/Random}, name=null} */
            case 26:
              j = 690100398;
              /* monitor exit ClassFileLocalVariableReferenceExpression{type=ObjectType{java/util/Random}, name=null} */
            case 15:
              j = 1350597307;
              /* monitor exit ClassFileLocalVariableReferenceExpression{type=ObjectType{java/util/Random}, name=null} */
            case 85:
              j = 162523417;
              /* monitor exit ClassFileLocalVariableReferenceExpression{type=ObjectType{java/util/Random}, name=null} */
            case 25:
              j = 1973203939;
              /* monitor exit ClassFileLocalVariableReferenceExpression{type=ObjectType{java/util/Random}, name=null} */
            case 35:
              j = 1405258293;
              /* monitor exit ClassFileLocalVariableReferenceExpression{type=ObjectType{java/util/Random}, name=null} */
            case 77:
              j = 1087820158;
              /* monitor exit ClassFileLocalVariableReferenceExpression{type=ObjectType{java/util/Random}, name=null} */
            case 2:
              j = 1221912496;
              /* monitor exit ClassFileLocalVariableReferenceExpression{type=ObjectType{java/util/Random}, name=null} */
            case 71:
              j = 1643989253;
              /* monitor exit ClassFileLocalVariableReferenceExpression{type=ObjectType{java/util/Random}, name=null} */
            case 4:
              j = 674518731;
              /* monitor exit ClassFileLocalVariableReferenceExpression{type=ObjectType{java/util/Random}, name=null} */
            case 59:
              j = 1289761534;
              /* monitor exit ClassFileLocalVariableReferenceExpression{type=ObjectType{java/util/Random}, name=null} */
            case 16:
              j = 82677759;
              /* monitor exit ClassFileLocalVariableReferenceExpression{type=ObjectType{java/util/Random}, name=null} */
            case 34:
              j = 1752328981;
              /* monitor exit ClassFileLocalVariableReferenceExpression{type=ObjectType{java/util/Random}, name=null} */
            case 45:
              j = 1256617562;
              /* monitor exit ClassFileLocalVariableReferenceExpression{type=ObjectType{java/util/Random}, name=null} */
            case 3:
              j = 518845977;
              /* monitor exit ClassFileLocalVariableReferenceExpression{type=ObjectType{java/util/Random}, name=null} */
            case 69:
              j = 1606376260;
              /* monitor exit ClassFileLocalVariableReferenceExpression{type=ObjectType{java/util/Random}, name=null} */
            case 7:
              j = 1872271991;
              /* monitor exit ClassFileLocalVariableReferenceExpression{type=ObjectType{java/util/Random}, name=null} */
            case 1:
              j = 65614707;
              /* monitor exit ClassFileLocalVariableReferenceExpression{type=ObjectType{java/util/Random}, name=null} */
            case 39:
              j = 1777734932;
              /* monitor exit ClassFileLocalVariableReferenceExpression{type=ObjectType{java/util/Random}, name=null} */
            case 43:
              j = 1232761405;
              /* monitor exit ClassFileLocalVariableReferenceExpression{type=ObjectType{java/util/Random}, name=null} */
            case 29:
              j = 1614120252;
              /* monitor exit ClassFileLocalVariableReferenceExpression{type=ObjectType{java/util/Random}, name=null} */
            case 23:
              j = 91196688;
              /* monitor exit ClassFileLocalVariableReferenceExpression{type=ObjectType{java/util/Random}, name=null} */
            case 47:
              j = 180096364;
              /* monitor exit ClassFileLocalVariableReferenceExpression{type=ObjectType{java/util/Random}, name=null} */
            case 0:
              j = 682747870;
              /* monitor exit ClassFileLocalVariableReferenceExpression{type=ObjectType{java/util/Random}, name=null} */
            case 44:
              j = 71327777;
              /* monitor exit ClassFileLocalVariableReferenceExpression{type=ObjectType{java/util/Random}, name=null} */
            case 56:
              j = 427963511;
              /* monitor exit ClassFileLocalVariableReferenceExpression{type=ObjectType{java/util/Random}, name=null} */
            case 80:
              j = 118989109;
              /* monitor exit ClassFileLocalVariableReferenceExpression{type=ObjectType{java/util/Random}, name=null} */
            case 33:
              j = 1206386073;
              /* monitor exit ClassFileLocalVariableReferenceExpression{type=ObjectType{java/util/Random}, name=null} */
            case 73:
              j = 1368628354;
              /* monitor exit ClassFileLocalVariableReferenceExpression{type=ObjectType{java/util/Random}, name=null} */
            case 22:
              j = 1484328269;
              /* monitor exit ClassFileLocalVariableReferenceExpression{type=ObjectType{java/util/Random}, name=null} */
            case 30:
              j = 1769046681;
              /* monitor exit ClassFileLocalVariableReferenceExpression{type=ObjectType{java/util/Random}, name=null} */
            case 31:
              j = 1985111061;
              /* monitor exit ClassFileLocalVariableReferenceExpression{type=ObjectType{java/util/Random}, name=null} */
            case 20:
              j = 1037920309;
              /* monitor exit ClassFileLocalVariableReferenceExpression{type=ObjectType{java/util/Random}, name=null} */
            case 79:
              j = 1734665545;
              /* monitor exit ClassFileLocalVariableReferenceExpression{type=ObjectType{java/util/Random}, name=null} */
            case 40:
              j = 2005487439;
              /* monitor exit ClassFileLocalVariableReferenceExpression{type=ObjectType{java/util/Random}, name=null} */
            case 49:
              j = 691171507;
              /* monitor exit ClassFileLocalVariableReferenceExpression{type=ObjectType{java/util/Random}, name=null} */
            case 74:
              j = 698754440;
              /* monitor exit ClassFileLocalVariableReferenceExpression{type=ObjectType{java/util/Random}, name=null} */
            case 10:
              j = 1222270725;
              /* monitor exit ClassFileLocalVariableReferenceExpression{type=ObjectType{java/util/Random}, name=null} */
            case 8:
              j = 606946765;
              /* monitor exit ClassFileLocalVariableReferenceExpression{type=ObjectType{java/util/Random}, name=null} */
            case 81:
              j = 1239730631;
              /* monitor exit ClassFileLocalVariableReferenceExpression{type=ObjectType{java/util/Random}, name=null} */
            case 78:
              j = 79872787;
              /* monitor exit ClassFileLocalVariableReferenceExpression{type=ObjectType{java/util/Random}, name=null} */
            case 14:
              j = 2100268739;
              /* monitor exit ClassFileLocalVariableReferenceExpression{type=ObjectType{java/util/Random}, name=null} */
            case 63:
              j = 2028924401;
              /* monitor exit ClassFileLocalVariableReferenceExpression{type=ObjectType{java/util/Random}, name=null} */
            case 75:
              j = 534659572;
              /* monitor exit ClassFileLocalVariableReferenceExpression{type=ObjectType{java/util/Random}, name=null} */
            case 66:
              j = 1294521169;
              /* monitor exit ClassFileLocalVariableReferenceExpression{type=ObjectType{java/util/Random}, name=null} */
            case 64:
              j = 217446012;
              /* monitor exit ClassFileLocalVariableReferenceExpression{type=ObjectType{java/util/Random}, name=null} */
            case 52:
              j = 971611403;
              /* monitor exit ClassFileLocalVariableReferenceExpression{type=ObjectType{java/util/Random}, name=null} */
            case 28:
              j = 1060102907;
              /* monitor exit ClassFileLocalVariableReferenceExpression{type=ObjectType{java/util/Random}, name=null} */
            case 5:
              j = 1541278050;
              /* monitor exit ClassFileLocalVariableReferenceExpression{type=ObjectType{java/util/Random}, name=null} */
            case 54:
              j = 594677801;
              /* monitor exit ClassFileLocalVariableReferenceExpression{type=ObjectType{java/util/Random}, name=null} */
            case 11:
              j = 78056007;
              /* monitor exit ClassFileLocalVariableReferenceExpression{type=ObjectType{java/util/Random}, name=null} */
            case 72:
              j = 310810071;
              /* monitor exit ClassFileLocalVariableReferenceExpression{type=ObjectType{java/util/Random}, name=null} */
            case 53:
              j = 1913614807;
              /* monitor exit ClassFileLocalVariableReferenceExpression{type=ObjectType{java/util/Random}, name=null} */
            case 36:
              j = 1621842176;
              /* monitor exit ClassFileLocalVariableReferenceExpression{type=ObjectType{java/util/Random}, name=null} */
            case 12:
              j = 1786718722;
              /* monitor exit ClassFileLocalVariableReferenceExpression{type=ObjectType{java/util/Random}, name=null} */
            case 65:
              j = 1661355303;
              /* monitor exit ClassFileLocalVariableReferenceExpression{type=ObjectType{java/util/Random}, name=null} */
            case 67:
              j = 174282575;
              /* monitor exit ClassFileLocalVariableReferenceExpression{type=ObjectType{java/util/Random}, name=null} */
            case 55:
              j = 1573427995;
              /* monitor exit ClassFileLocalVariableReferenceExpression{type=ObjectType{java/util/Random}, name=null} */
              return;
          } 
        } catch (IllegalMonitorStateException illegalMonitorStateException) {
          arrayOfInt[i] = j ^ 0x1C35C9BC;
        } 
        i--;
        /* monitor exit ClassFileLocalVariableReferenceExpression{type=UndefinedObjectType, name=null} */
      } 
      return;
    } 
  }
  
  static {
    throw SYNTHETIC_LOCAL_VARIABLE_0;
  }
  
  public static String 0(String paramString, int paramInt) {
    // Byte code:
    //   0: aload_0
    //   1: astore #12
    //   3: aload_0
    //   4: astore #14
    //   6: aload_0
    //   7: astore_3
    //   8: iconst_1
    //   9: getstatic Perry0.aiooi1iojionlknzjsdnfdas : [I
    //   12: astore #16
    //   14: istore #13
    //   16: aload #16
    //   18: astore #12
    //   20: aload #16
    //   22: astore #14
    //   24: aload #16
    //   26: astore_3
    //   27: goto -> 44
    //   30: aload_0
    //   31: ifnonnull -> 44
    //   34: new java/lang/NullPointerException
    //   37: dup
    //   38: ldc 'String deobfuscation parameter should not be null'
    //   40: invokespecial <init> : (Ljava/lang/String;)V
    //   43: athrow
    //   44: new java/lang/Exception
    //   47: iconst_m1
    //   48: aconst_null
    //   49: aconst_null
    //   50: astore #4
    //   52: astore #8
    //   54: aconst_null
    //   55: astore #5
    //   57: iconst_m1
    //   58: iload_1
    //   59: istore #11
    //   61: ldc 473287100
    //   63: istore_1
    //   64: istore_2
    //   65: iconst_m1
    //   66: aconst_null
    //   67: astore #9
    //   69: istore #10
    //   71: iconst_0
    //   72: istore #15
    //   74: istore #6
    //   76: getstatic Perryc.c : I
    //   79: iflt -> 98
    //   82: <illegal opcode> while : ()V
    //   87: <illegal opcode> fuck : ()V
    //   92: <illegal opcode> yayeet : ()Ljava/lang/YaYeet;
    //   97: pop
    //   98: iconst_m1
    //   99: istore #7
    //   101: pop
    //   102: iload #13
    //   104: ifeq -> 30
    //   107: iconst_0
    //   108: istore #13
    //   110: goto -> 155
    //   113: aconst_null
    //   114: checkcast java/lang/YourMum
    //   117: pop
    //   118: aload #8
    //   120: iload #10
    //   122: caload
    //   123: iload #10
    //   125: iload #7
    //   127: iadd
    //   128: ixor
    //   129: istore #15
    //   131: invokestatic a : ()V
    //   134: goto -> 172
    //   137: iload #10
    //   139: aload #8
    //   141: arraylength
    //   142: if_icmpge -> 233
    //   145: iload #10
    //   147: iconst_5
    //   148: irem
    //   149: bipush #9
    //   151: iadd
    //   152: goto -> 499
    //   155: aconst_null
    //   156: getstatic Perryc.c : I
    //   159: iflt -> 168
    //   162: pop
    //   163: aconst_null
    //   164: goto -> 439
    //   167: athrow
    //   168: pop
    //   169: goto -> 462
    //   172: invokestatic currentThread : ()Ljava/lang/Thread;
    //   175: astore #4
    //   177: iconst_3
    //   178: istore_2
    //   179: aload #14
    //   181: monitorexit
    //   182: goto -> 172
    //   185: aload_0
    //   186: invokevirtual toCharArray : ()[C
    //   189: astore #8
    //   191: aload #8
    //   193: arraylength
    //   194: newarray char
    //   196: astore #9
    //   198: bipush #8
    //   200: istore_2
    //   201: aload #14
    //   203: monitorexit
    //   204: goto -> 137
    //   207: pop
    //   208: iload #15
    //   210: i2c
    //   211: aload #16
    //   213: iload #10
    //   215: bipush #87
    //   217: irem
    //   218: iaload
    //   219: ixor
    //   220: aload #9
    //   222: swap
    //   223: iload #10
    //   225: swap
    //   226: castore
    //   227: iinc #10, 1
    //   230: goto -> 137
    //   233: iconst_1
    //   234: istore_2
    //   235: aload #14
    //   237: monitorexit
    //   238: goto -> 257
    //   241: aload #8
    //   243: iload #10
    //   245: caload
    //   246: iload #7
    //   248: ixor
    //   249: istore #15
    //   251: invokestatic a : ()V
    //   254: goto -> 44
    //   257: iconst_0
    //   258: istore #10
    //   260: goto -> 137
    //   263: aload #8
    //   265: iload #10
    //   267: caload
    //   268: iconst_4
    //   269: iload #6
    //   271: iadd
    //   272: ixor
    //   273: istore #15
    //   275: invokestatic a : ()V
    //   278: goto -> 281
    //   281: aload #8
    //   283: iload #10
    //   285: caload
    //   286: iload #7
    //   288: iload #6
    //   290: iadd
    //   291: ixor
    //   292: istore #15
    //   294: invokestatic a : ()V
    //   297: goto -> 257
    //   300: <illegal opcode> ________ : ()V
    //   305: goto -> 44
    //   308: pop
    //   309: getstatic Perry0.0 : LPerry0;
    //   312: aload_0
    //   313: new java/lang/String
    //   316: dup
    //   317: aload #9
    //   319: invokespecial <init> : ([C)V
    //   322: dup_x2
    //   323: invokevirtual put : (Ljava/lang/Object;Ljava/lang/Object;)Ljava/lang/Object;
    //   326: swap
    //   327: areturn
    //   328: aload #8
    //   330: iload #10
    //   332: caload
    //   333: iload #6
    //   335: ixor
    //   336: istore #15
    //   338: invokestatic a : ()V
    //   341: goto -> 172
    //   344: pop
    //   345: aload #5
    //   347: iload #11
    //   349: aaload
    //   350: invokevirtual getMethodName : ()Ljava/lang/String;
    //   353: invokevirtual hashCode : ()I
    //   356: istore #7
    //   358: bipush #7
    //   360: istore_2
    //   361: aload #14
    //   363: monitorexit
    //   364: getstatic Perry0.0 : LPerry0;
    //   367: aload_0
    //   368: invokevirtual get : (Ljava/lang/Object;)Ljava/lang/Object;
    //   371: dup
    //   372: ifnull -> 379
    //   375: checkcast java/lang/String
    //   378: areturn
    //   379: new java/lang/IllegalStateException
    //   382: dup
    //   383: invokespecial <init> : ()V
    //   386: athrow
    //   387: pop
    //   388: iconst_2
    //   389: istore_2
    //   390: goto -> 498
    //   393: aload #4
    //   395: invokevirtual getStackTrace : ()[Ljava/lang/StackTraceElement;
    //   398: astore #5
    //   400: iconst_4
    //   401: istore_2
    //   402: aload #14
    //   404: monitorexit
    //   405: aconst_null
    //   406: goto -> 387
    //   409: aload #5
    //   411: iload #11
    //   413: aaload
    //   414: invokevirtual getClassName : ()Ljava/lang/String;
    //   417: invokevirtual hashCode : ()I
    //   420: istore #6
    //   422: iconst_5
    //   423: istore_2
    //   424: aload #14
    //   426: dup
    //   427: ifnull -> 461
    //   430: monitorexit
    //   431: <illegal opcode> fuck : ()V
    //   436: aconst_null
    //   437: athrow
    //   438: athrow
    //   439: pop
    //   440: aconst_null
    //   441: goto -> 167
    //   444: aload #8
    //   446: iload #10
    //   448: caload
    //   449: iload_1
    //   450: ixor
    //   451: istore #15
    //   453: invokestatic a : ()V
    //   456: goto -> 172
    //   459: nop
    //   460: athrow
    //   461: pop
    //   462: ldc 473287100
    //   464: istore_1
    //   465: aconst_null
    //   466: astore_3
    //   467: aconst_null
    //   468: astore #4
    //   470: aconst_null
    //   471: astore #5
    //   473: iconst_0
    //   474: istore #6
    //   476: iconst_0
    //   477: istore #7
    //   479: aconst_null
    //   480: astore #8
    //   482: aconst_null
    //   483: astore #9
    //   485: iconst_0
    //   486: istore #10
    //   488: iconst_0
    //   489: istore_2
    //   490: goto -> 498
    //   493: ifnonnull -> 498
    //   496: aconst_null
    //   497: athrow
    //   498: iload_2
    //   499: tableswitch default -> 113, 0 -> 364, 1 -> 300, 2 -> 172, 3 -> 393, 4 -> 409, 5 -> 345, 6 -> 364, 7 -> 185, 8 -> 257, 9 -> 263, 10 -> 444, 11 -> 328, 12 -> 241, 13 -> 281, 14 -> 118
    // Exception table:
    //   from	to	target	type
    //   155	169	439	finally
    //   167	169	168	finally
    //   172	207	493	java/lang/IllegalMonitorStateException
    //   172	207	308	java/lang/BootstrapMethodError
    //   172	207	387	java/lang/IllegalStateException
    //   172	207	439	java/lang/IllegalArgumentException
    //   172	207	438	java/lang/NoClassDefFoundError
    //   172	257	168	finally
    //   172	300	493	java/lang/IllegalMonitorStateException
    //   172	300	308	java/lang/BootstrapMethodError
    //   172	300	387	java/lang/IllegalStateException
    //   172	300	439	java/lang/IllegalArgumentException
    //   172	300	438	java/lang/NoClassDefFoundError
    //   172	300	438	java/lang/Throwable
    //   172	459	207	java/lang/NoClassDefFoundError
    //   172	459	493	java/lang/IllegalMonitorStateException
    //   172	459	308	java/lang/BootstrapMethodError
    //   172	459	387	java/lang/IllegalStateException
    //   172	459	439	java/lang/IllegalArgumentException
    //   241	257	168	java/lang/Throwable
    //   300	308	308	java/lang/Throwable
    //   345	364	438	java/lang/Exception
    //   393	409	438	finally
    //   409	438	344	java/lang/BootstrapMethodError
    //   461	498	207	java/lang/NoClassDefFoundError
    //   461	498	493	java/lang/IllegalMonitorStateException
    //   461	498	308	java/lang/BootstrapMethodError
    //   461	498	387	java/lang/IllegalStateException
    //   461	498	439	java/lang/IllegalArgumentException
  }
  
  Perry0() {
    0 = this;
  }
}


/* Location:              C:\Users\alex\Desktop\webhack\WebHack-0.8-obf_sussy_1.jar!\Perry0.class
 * Java compiler version: 8 (52.0)
 * JD-Core Version:       1.1.3
 */