package bigname.zprestige.webhack.features.command.commands;

import bigname.zprestige.webhack.features.command.Command;

public class BindCommand extends Command {
  public BindCommand() {
    // Byte code:
    //   0: getstatic Perryc.1 : I
    //   3: ifeq -> 16
    //   6: ldc2_w 1060101440
    //   9: l2i
    //   10: ldc -1582792773
    //   12: ixor
    //   13: goto -> 23
    //   16: ldc2_w -1002227458
    //   19: l2i
    //   20: ldc 1893642665
    //   22: ixor
    //   23: ldc2_w 40108074
    //   26: l2i
    //   27: ldc -1247172927
    //   29: ixor
    //   30: ixor
    //   31: lookupswitch default -> 334, 55586748 -> 56, 692716560 -> 16
    //   56: aload_0
    //   57: ldc 'ﴓ㌚ﵭ㶳'
    //   59: getstatic Perryc.c : I
    //   62: iflt -> 75
    //   65: ldc2_w 1554614297
    //   68: l2i
    //   69: ldc 1674511007
    //   71: ixor
    //   72: goto -> 82
    //   75: ldc2_w -541826860
    //   78: l2i
    //   79: ldc -1802047575
    //   81: ixor
    //   82: ldc2_w 2001600605
    //   85: l2i
    //   86: ldc -529792934
    //   88: ixor
    //   89: ixor
    //   90: lookupswitch default -> 116, -1471903103 -> 338, 1290240130 -> 75
    //   116: invokestatic 0 : (Ljava/lang/String;)Ljava/lang/String;
    //   119: ldc2_w 1979347742
    //   122: l2i
    //   123: ldc 1979347740
    //   125: ixor
    //   126: anewarray java/lang/String
    //   129: dup
    //   130: ldc2_w -1850156387
    //   133: l2i
    //   134: ldc -1850156387
    //   136: ixor
    //   137: ldc '﵍㌞ﵬ㶳䪃Ꭱ๼胺'
    //   139: getstatic Perryc.c : I
    //   142: iflt -> 155
    //   145: ldc2_w 1527185556
    //   148: l2i
    //   149: ldc 945222636
    //   151: ixor
    //   152: goto -> 162
    //   155: ldc2_w 1844609173
    //   158: l2i
    //   159: ldc -864878427
    //   161: ixor
    //   162: ldc2_w -637597595
    //   165: l2i
    //   166: ldc -99961911
    //   168: ixor
    //   169: ixor
    //   170: lookupswitch default -> 340, -2106311780 -> 196, 1084508372 -> 155
    //   196: invokestatic 0 : (Ljava/lang/String;)Ljava/lang/String;
    //   199: aastore
    //   200: dup
    //   201: ldc2_w -689607123
    //   204: l2i
    //   205: ldc -689607124
    //   207: ixor
    //   208: ldc '﵍㌑ﵪ㶹䪒Ᏻ'
    //   210: getstatic Perryc.1 : I
    //   213: ifeq -> 226
    //   216: ldc2_w 1427532964
    //   219: l2i
    //   220: ldc 384369744
    //   222: ixor
    //   223: goto -> 233
    //   226: ldc2_w -529202167
    //   229: l2i
    //   230: ldc -1260922129
    //   232: ixor
    //   233: ldc2_w 476993857
    //   236: l2i
    //   237: ldc 1070816769
    //   239: ixor
    //   240: ixor
    //   241: lookupswitch default -> 268, -776668471 -> 226, 1614966708 -> 332
    //   268: invokestatic 0 : (Ljava/lang/String;)Ljava/lang/String;
    //   271: aastore
    //   272: getstatic Perryc.0 : I
    //   275: ifle -> 288
    //   278: ldc2_w -64367307
    //   281: l2i
    //   282: ldc -1881876412
    //   284: ixor
    //   285: goto -> 295
    //   288: ldc2_w 45902667
    //   291: l2i
    //   292: ldc -1825923641
    //   294: ixor
    //   295: ldc2_w -565636496
    //   298: l2i
    //   299: ldc 1055459979
    //   301: ixor
    //   302: ixor
    //   303: lookupswitch default -> 328, -1822616182 -> 336, 750402158 -> 288
    //   328: invokespecial <init> : (Ljava/lang/String;[Ljava/lang/String;)V
    //   331: return
    //   332: aconst_null
    //   333: athrow
    //   334: aconst_null
    //   335: athrow
    //   336: aconst_null
    //   337: athrow
    //   338: aconst_null
    //   339: athrow
    //   340: aconst_null
    //   341: athrow
    // Local variable table:
    //   start	length	slot	name	descriptor
    //   0	332	0	this	Lbigname/zprestige/webhack/features/command/commands/BindCommand;
  }
  
  static {
    throw SYNTHETIC_LOCAL_VARIABLE_0;
  }
  
  public void execute(String[] commands) {
    // Byte code:
    //   0: goto -> 8
    //   3: dup
    //   4: ifnull -> 5885
    //   7: athrow
    //   8: aconst_null
    //   9: getstatic Perryc.1 : I
    //   12: ifgt -> 5877
    //   15: pop
    //   16: aconst_null
    //   17: goto -> 5869
    //   20: nop
    //   21: nop
    //   22: nop
    //   23: athrow
    //   24: getstatic Perryc.c : I
    //   27: iflt -> 40
    //   30: ldc2_w -31984616
    //   33: l2i
    //   34: ldc 2029956288
    //   36: ixor
    //   37: goto -> 47
    //   40: ldc2_w 2038074135
    //   43: l2i
    //   44: ldc -1327114547
    //   46: ixor
    //   47: ldc2_w 26731222
    //   50: l2i
    //   51: ldc 86059227
    //   53: ixor
    //   54: ixor
    //   55: lookupswitch default -> 5852, -2107665707 -> 40, -852912169 -> 80
    //   80: aload_1
    //   81: arraylength
    //   82: ldc2_w 872461573
    //   85: l2i
    //   86: ldc 872461572
    //   88: ixor
    //   89: if_icmpne -> 102
    //   92: ldc2_w 923578008
    //   95: l2i
    //   96: ldc 1453761517
    //   98: ixor
    //   99: goto -> 109
    //   102: ldc2_w -2075857388
    //   105: l2i
    //   106: ldc -437329054
    //   108: ixor
    //   109: ldc2_w -757107717
    //   112: l2i
    //   113: ldc -204991521
    //   115: ixor
    //   116: ixor
    //   117: tableswitch default -> 92, 1086156113 -> 140, 1086156114 -> 280
    //   140: ldc 'ﴡ㌟ﵦ좱喀Ꭸู肷筴२䗉ਮプ葿跛恵迟┉剦䢿狯侽ល돷'
    //   142: getstatic Perryc.c : I
    //   145: iflt -> 158
    //   148: ldc2_w -1897010082
    //   151: l2i
    //   152: ldc 1753817
    //   154: ixor
    //   155: goto -> 165
    //   158: ldc2_w 1382512643
    //   161: l2i
    //   162: ldc -458176538
    //   164: ixor
    //   165: ldc2_w -797969024
    //   168: l2i
    //   169: ldc 1525627177
    //   171: ixor
    //   172: ixor
    //   173: lookupswitch default -> 200, -758452328 -> 158, 74965550 -> 5716
    //   200: goto -> 204
    //   203: athrow
    //   204: invokestatic 0 : (Ljava/lang/String;)Ljava/lang/String;
    //   207: goto -> 211
    //   210: athrow
    //   211: getstatic Perryc.c : I
    //   214: iflt -> 227
    //   217: ldc2_w 1794951084
    //   220: l2i
    //   221: ldc -493210517
    //   223: ixor
    //   224: goto -> 234
    //   227: ldc2_w -467097866
    //   230: l2i
    //   231: ldc -2096882743
    //   233: ixor
    //   234: ldc2_w 1810049906
    //   237: l2i
    //   238: ldc -427430404
    //   240: ixor
    //   241: ixor
    //   242: lookupswitch default -> 268, 83899721 -> 5832, 1482171115 -> 227
    //   268: goto -> 272
    //   271: athrow
    //   272: invokestatic sendMessage : (Ljava/lang/String;)V
    //   275: goto -> 279
    //   278: athrow
    //   279: return
    //   280: getstatic Perryc.1 : I
    //   283: ifeq -> 296
    //   286: ldc2_w -1060923864
    //   289: l2i
    //   290: ldc -1880089245
    //   292: ixor
    //   293: goto -> 303
    //   296: ldc2_w 179655094
    //   299: l2i
    //   300: ldc -1262823968
    //   302: ixor
    //   303: ldc2_w -1227569221
    //   306: l2i
    //   307: ldc 1123881736
    //   309: ixor
    //   310: ixor
    //   311: lookupswitch default -> 336, -1155899400 -> 5840, 768446633 -> 296
    //   336: aload_1
    //   337: ldc2_w 869759538
    //   340: l2i
    //   341: ldc 869759539
    //   343: ixor
    //   344: aaload
    //   345: getstatic Perryc.c : I
    //   348: iflt -> 361
    //   351: ldc2_w 1162999502
    //   354: l2i
    //   355: ldc 686542962
    //   357: ixor
    //   358: goto -> 368
    //   361: ldc2_w -1295529732
    //   364: l2i
    //   365: ldc 1153553773
    //   367: ixor
    //   368: ldc2_w -600928108
    //   371: l2i
    //   372: ldc -1448481620
    //   374: ixor
    //   375: ixor
    //   376: lookupswitch default -> 5732, -2088672855 -> 404, 406674052 -> 361
    //   404: astore_2
    //   405: getstatic Perryc.1 : I
    //   408: ifeq -> 421
    //   411: ldc2_w 1152885298
    //   414: l2i
    //   415: ldc 378226535
    //   417: ixor
    //   418: goto -> 428
    //   421: ldc2_w 2063097931
    //   424: l2i
    //   425: ldc -824914654
    //   427: ixor
    //   428: ldc2_w -798923982
    //   431: l2i
    //   432: ldc -496715311
    //   434: ixor
    //   435: ixor
    //   436: lookupswitch default -> 5816, -2044102774 -> 464, 1614364598 -> 421
    //   464: aload_1
    //   465: ldc2_w -1297177698
    //   468: l2i
    //   469: ldc -1297177698
    //   471: ixor
    //   472: aaload
    //   473: getstatic Perryc.c : I
    //   476: iflt -> 489
    //   479: ldc2_w 665276627
    //   482: l2i
    //   483: ldc -688574043
    //   485: ixor
    //   486: goto -> 496
    //   489: ldc2_w 2067339365
    //   492: l2i
    //   493: ldc 1240268963
    //   495: ixor
    //   496: ldc2_w -93156516
    //   499: l2i
    //   500: ldc 450300631
    //   502: ixor
    //   503: ixor
    //   504: lookupswitch default -> 532, -1309161192 -> 489, 301457661 -> 5800
    //   532: astore_3
    //   533: getstatic Perryc.1 : I
    //   536: ifeq -> 549
    //   539: ldc2_w -1135045575
    //   542: l2i
    //   543: ldc 1256645619
    //   545: ixor
    //   546: goto -> 556
    //   549: ldc2_w -1168457915
    //   552: l2i
    //   553: ldc -1392988340
    //   555: ixor
    //   556: ldc2_w -2005365751
    //   559: l2i
    //   560: ldc 2057070278
    //   562: ixor
    //   563: ixor
    //   564: lookupswitch default -> 5850, -465110330 -> 592, 73047301 -> 549
    //   592: getstatic bigname/zprestige/webhack/WebHack.moduleManager : Lbigname/zprestige/webhack/manager/ModuleManager;
    //   595: getstatic Perryc.0 : I
    //   598: ifle -> 611
    //   601: ldc2_w -612171871
    //   604: l2i
    //   605: ldc -132839886
    //   607: ixor
    //   608: goto -> 618
    //   611: ldc2_w -763900529
    //   614: l2i
    //   615: ldc -404284226
    //   617: ixor
    //   618: ldc2_w -422659381
    //   621: l2i
    //   622: ldc -155882265
    //   624: ixor
    //   625: ixor
    //   626: lookupswitch default -> 5842, 636159773 -> 652, 871116735 -> 611
    //   652: aload_3
    //   653: getstatic Perryc.0 : I
    //   656: ifle -> 669
    //   659: ldc2_w 1964932752
    //   662: l2i
    //   663: ldc 1643293443
    //   665: ixor
    //   666: goto -> 676
    //   669: ldc2_w 1186454151
    //   672: l2i
    //   673: ldc -525262514
    //   675: ixor
    //   676: ldc2_w 1540992668
    //   679: l2i
    //   680: ldc 1889056899
    //   682: ixor
    //   683: ixor
    //   684: lookupswitch default -> 5854, -1924665898 -> 712, 1068352396 -> 669
    //   712: goto -> 716
    //   715: athrow
    //   716: invokevirtual getModuleByName : (Ljava/lang/String;)Lbigname/zprestige/webhack/features/modules/Module;
    //   719: goto -> 723
    //   722: athrow
    //   723: getstatic Perryc.c : I
    //   726: iflt -> 740
    //   729: ldc2_w -455303581
    //   732: l2i
    //   733: ldc_w -1592366140
    //   736: ixor
    //   737: goto -> 748
    //   740: ldc2_w -6060664
    //   743: l2i
    //   744: ldc_w -2044223597
    //   747: ixor
    //   748: ldc2_w -507993967
    //   751: l2i
    //   752: ldc_w 1628675186
    //   755: ixor
    //   756: ixor
    //   757: lookupswitch default -> 784, -983447228 -> 5714, -821297220 -> 740
    //   784: astore #4
    //   786: getstatic Perryc.1 : I
    //   789: ifeq -> 803
    //   792: ldc2_w 273085317
    //   795: l2i
    //   796: ldc_w -196278884
    //   799: ixor
    //   800: goto -> 811
    //   803: ldc2_w 782408046
    //   806: l2i
    //   807: ldc_w -1576014833
    //   810: ixor
    //   811: ldc2_w 1626614563
    //   814: l2i
    //   815: ldc_w -476631388
    //   818: ixor
    //   819: ixor
    //   820: lookupswitch default -> 848, -425894764 -> 803, 1734931358 -> 5746
    //   848: aload #4
    //   850: ifnonnull -> 864
    //   853: ldc2_w 1709239868
    //   856: l2i
    //   857: ldc_w 840005798
    //   860: ixor
    //   861: goto -> 872
    //   864: ldc2_w -874825875
    //   867: l2i
    //   868: ldc_w -1674927628
    //   871: ixor
    //   872: ldc2_w -1536752258
    //   875: l2i
    //   876: ldc_w -1556768879
    //   879: ixor
    //   880: ixor
    //   881: tableswitch default -> 853, 1352860789 -> 904, 1352860790 -> 1556
    //   904: new java/lang/StringBuilder
    //   907: dup
    //   908: getstatic Perryc.c : I
    //   911: iflt -> 925
    //   914: ldc2_w 1768602614
    //   917: l2i
    //   918: ldc_w 871261333
    //   921: ixor
    //   922: goto -> 933
    //   925: ldc2_w -559315650
    //   928: l2i
    //   929: ldc_w 1716021151
    //   932: ixor
    //   933: ldc2_w -174123225
    //   936: l2i
    //   937: ldc_w -824828686
    //   940: ixor
    //   941: ixor
    //   942: lookupswitch default -> 5736, -2086082188 -> 968, 1640879286 -> 925
    //   968: goto -> 972
    //   971: athrow
    //   972: invokespecial <init> : ()V
    //   975: goto -> 979
    //   978: athrow
    //   979: ldc_w 'ﴤ㌝ﵨ좾喜Ꮊ๷胤筩ॢ䗎ਲポ董跛怳'
    //   982: getstatic Perryc.0 : I
    //   985: ifle -> 999
    //   988: ldc2_w -542375762
    //   991: l2i
    //   992: ldc_w 879280639
    //   995: ixor
    //   996: goto -> 1007
    //   999: ldc2_w 924531857
    //   1002: l2i
    //   1003: ldc_w -2065886904
    //   1006: ixor
    //   1007: ldc2_w 1976642518
    //   1010: l2i
    //   1011: ldc_w -5451041
    //   1014: ixor
    //   1015: ixor
    //   1016: lookupswitch default -> 5856, 968611024 -> 1044, 1639528536 -> 999
    //   1044: goto -> 1048
    //   1047: athrow
    //   1048: invokestatic 0 : (Ljava/lang/String;)Ljava/lang/String;
    //   1051: goto -> 1055
    //   1054: athrow
    //   1055: getstatic Perryc.1 : I
    //   1058: ifeq -> 1072
    //   1061: ldc2_w 2035119354
    //   1064: l2i
    //   1065: ldc_w -1478759701
    //   1068: ixor
    //   1069: goto -> 1080
    //   1072: ldc2_w 2064718935
    //   1075: l2i
    //   1076: ldc_w -1198810444
    //   1079: ixor
    //   1080: ldc2_w -2067475736
    //   1083: l2i
    //   1084: ldc_w -952108662
    //   1087: ixor
    //   1088: ixor
    //   1089: lookupswitch default -> 5782, -2141082239 -> 1116, -1653754509 -> 1072
    //   1116: goto -> 1120
    //   1119: athrow
    //   1120: invokevirtual append : (Ljava/lang/String;)Ljava/lang/StringBuilder;
    //   1123: goto -> 1127
    //   1126: athrow
    //   1127: getstatic Perryc.1 : I
    //   1130: ifeq -> 1144
    //   1133: ldc2_w -1678312502
    //   1136: l2i
    //   1137: ldc_w -1609421456
    //   1140: ixor
    //   1141: goto -> 1152
    //   1144: ldc2_w 1143223541
    //   1147: l2i
    //   1148: ldc_w -967150234
    //   1151: ixor
    //   1152: ldc2_w -866044335
    //   1155: l2i
    //   1156: ldc_w -444442418
    //   1159: ixor
    //   1160: ixor
    //   1161: lookupswitch default -> 5786, -1415762164 -> 1188, 302495781 -> 1144
    //   1188: aload #4
    //   1190: getstatic Perryc.c : I
    //   1193: iflt -> 1207
    //   1196: ldc2_w -1969086428
    //   1199: l2i
    //   1200: ldc_w 330542800
    //   1203: ixor
    //   1204: goto -> 1215
    //   1207: ldc2_w 1652079935
    //   1210: l2i
    //   1211: ldc_w 700802552
    //   1214: ixor
    //   1215: ldc2_w 1111024718
    //   1218: l2i
    //   1219: ldc_w 1131790696
    //   1222: ixor
    //   1223: ixor
    //   1224: lookupswitch default -> 1252, -1738757166 -> 5734, -1472840732 -> 1207
    //   1252: goto -> 1256
    //   1255: athrow
    //   1256: invokevirtual append : (Ljava/lang/Object;)Ljava/lang/StringBuilder;
    //   1259: goto -> 1263
    //   1262: athrow
    //   1263: ldc_w 'ﵖ㍒'
    //   1266: getstatic Perryc.0 : I
    //   1269: ifle -> 1283
    //   1272: ldc2_w -844218124
    //   1275: l2i
    //   1276: ldc_w -1380314237
    //   1279: ixor
    //   1280: goto -> 1291
    //   1283: ldc2_w 735265838
    //   1286: l2i
    //   1287: ldc_w -1307265705
    //   1290: ixor
    //   1291: ldc2_w 337681971
    //   1294: l2i
    //   1295: ldc_w 574846884
    //   1298: ixor
    //   1299: ixor
    //   1300: lookupswitch default -> 5820, -1348200210 -> 1328, 1450687200 -> 1283
    //   1328: goto -> 1332
    //   1331: athrow
    //   1332: invokestatic 0 : (Ljava/lang/String;)Ljava/lang/String;
    //   1335: goto -> 1339
    //   1338: athrow
    //   1339: getstatic Perryc.0 : I
    //   1342: ifle -> 1356
    //   1345: ldc2_w 1662584556
    //   1348: l2i
    //   1349: ldc_w -2010777910
    //   1352: ixor
    //   1353: goto -> 1364
    //   1356: ldc2_w 82971683
    //   1359: l2i
    //   1360: ldc_w 1322152614
    //   1363: ixor
    //   1364: ldc2_w 251337641
    //   1367: l2i
    //   1368: ldc_w 1693564756
    //   1371: ixor
    //   1372: ixor
    //   1373: lookupswitch default -> 5824, -2127145765 -> 1356, 540465784 -> 1400
    //   1400: goto -> 1404
    //   1403: athrow
    //   1404: invokevirtual append : (Ljava/lang/String;)Ljava/lang/StringBuilder;
    //   1407: goto -> 1411
    //   1410: athrow
    //   1411: getstatic Perryc.c : I
    //   1414: iflt -> 1428
    //   1417: ldc2_w -1253958355
    //   1420: l2i
    //   1421: ldc_w -882920871
    //   1424: ixor
    //   1425: goto -> 1436
    //   1428: ldc2_w 904738720
    //   1431: l2i
    //   1432: ldc_w -1063281223
    //   1435: ixor
    //   1436: ldc2_w 1427828735
    //   1439: l2i
    //   1440: ldc_w -1549724848
    //   1443: ixor
    //   1444: ixor
    //   1445: lookupswitch default -> 5768, -2002365477 -> 1428, 63526582 -> 1472
    //   1472: goto -> 1476
    //   1475: athrow
    //   1476: invokevirtual toString : ()Ljava/lang/String;
    //   1479: goto -> 1483
    //   1482: athrow
    //   1483: getstatic Perryc.1 : I
    //   1486: ifeq -> 1500
    //   1489: ldc2_w 88540266
    //   1492: l2i
    //   1493: ldc_w -81276919
    //   1496: ixor
    //   1497: goto -> 1508
    //   1500: ldc2_w 60981972
    //   1503: l2i
    //   1504: ldc_w -431229373
    //   1507: ixor
    //   1508: ldc2_w -312376029
    //   1511: l2i
    //   1512: ldc_w -1377585758
    //   1515: ixor
    //   1516: ixor
    //   1517: lookupswitch default -> 5830, -1519696874 -> 1544, -1092426526 -> 1500
    //   1544: goto -> 1548
    //   1547: athrow
    //   1548: invokestatic sendMessage : (Ljava/lang/String;)V
    //   1551: goto -> 1555
    //   1554: athrow
    //   1555: return
    //   1556: getstatic Perryc.0 : I
    //   1559: ifle -> 1573
    //   1562: ldc2_w -552822435
    //   1565: l2i
    //   1566: ldc_w -550100020
    //   1569: ixor
    //   1570: goto -> 1581
    //   1573: ldc2_w 2100942572
    //   1576: l2i
    //   1577: ldc_w 448567110
    //   1580: ixor
    //   1581: ldc2_w -74009772
    //   1584: l2i
    //   1585: ldc_w -1835231890
    //   1588: ixor
    //   1589: ixor
    //   1590: lookupswitch default -> 5720, 244279184 -> 1616, 1764793515 -> 1573
    //   1616: aload_2
    //   1617: ifnonnull -> 1631
    //   1620: ldc2_w -1092213230
    //   1623: l2i
    //   1624: ldc_w 1965231621
    //   1627: ixor
    //   1628: goto -> 1639
    //   1631: ldc2_w 1351518055
    //   1634: l2i
    //   1635: ldc_w -1689538703
    //   1638: ixor
    //   1639: ldc2_w -1750760649
    //   1642: l2i
    //   1643: ldc_w 855412756
    //   1646: ixor
    //   1647: ixor
    //   1648: tableswitch default -> 1620, 1855732532 -> 1672, 1855732533 -> 2664
    //   1672: new java/lang/StringBuilder
    //   1675: dup
    //   1676: getstatic Perryc.1 : I
    //   1679: ifeq -> 1693
    //   1682: ldc2_w -1164144004
    //   1685: l2i
    //   1686: ldc_w 1646590595
    //   1689: ixor
    //   1690: goto -> 1701
    //   1693: ldc2_w 1345000618
    //   1696: l2i
    //   1697: ldc_w -126577184
    //   1700: ixor
    //   1701: ldc2_w -583895384
    //   1704: l2i
    //   1705: ldc_w -1615211200
    //   1708: ixor
    //   1709: ixor
    //   1710: lookupswitch default -> 5802, -1707881705 -> 1693, -355196254 -> 1736
    //   1736: goto -> 1740
    //   1739: athrow
    //   1740: invokespecial <init> : ()V
    //   1743: goto -> 1747
    //   1746: athrow
    //   1747: getstatic Perryc.0 : I
    //   1750: ifle -> 1764
    //   1753: ldc2_w -1021420984
    //   1756: l2i
    //   1757: ldc_w -1079560284
    //   1760: ixor
    //   1761: goto -> 1772
    //   1764: ldc2_w -1082889442
    //   1767: l2i
    //   1768: ldc_w 298929467
    //   1771: ixor
    //   1772: ldc2_w -842837165
    //   1775: l2i
    //   1776: ldc_w -1926939075
    //   1779: ixor
    //   1780: ixor
    //   1781: lookupswitch default -> 5740, -297579701 -> 1808, 1012859010 -> 1764
    //   1808: aload #4
    //   1810: getstatic Perryc.1 : I
    //   1813: ifeq -> 1827
    //   1816: ldc2_w -611617479
    //   1819: l2i
    //   1820: ldc_w -442533975
    //   1823: ixor
    //   1824: goto -> 1835
    //   1827: ldc2_w -1029806600
    //   1830: l2i
    //   1831: ldc_w -1186964098
    //   1834: ixor
    //   1835: ldc2_w -31958950
    //   1838: l2i
    //   1839: ldc_w -1548852910
    //   1842: ixor
    //   1843: ixor
    //   1844: lookupswitch default -> 1872, -155519168 -> 1827, 1671576472 -> 5718
    //   1872: goto -> 1876
    //   1875: athrow
    //   1876: invokevirtual getName : ()Ljava/lang/String;
    //   1879: goto -> 1883
    //   1882: athrow
    //   1883: getstatic Perryc.0 : I
    //   1886: ifle -> 1900
    //   1889: ldc2_w 152413574
    //   1892: l2i
    //   1893: ldc_w -1247749587
    //   1896: ixor
    //   1897: goto -> 1908
    //   1900: ldc2_w -1666746285
    //   1903: l2i
    //   1904: ldc_w 963242054
    //   1907: ixor
    //   1908: ldc2_w 378700326
    //   1911: l2i
    //   1912: ldc_w -726476116
    //   1915: ixor
    //   1916: ixor
    //   1917: lookupswitch default -> 1944, -1898596128 -> 1900, 2123704097 -> 5748
    //   1944: goto -> 1948
    //   1947: athrow
    //   1948: invokevirtual append : (Ljava/lang/String;)Ljava/lang/StringBuilder;
    //   1951: goto -> 1955
    //   1954: athrow
    //   1955: ldc_w 'ﵑ㌚ﵰ죰喑Ꭲ๬肪筠भ䗞ਨゑ'
    //   1958: getstatic Perryc.0 : I
    //   1961: ifle -> 1975
    //   1964: ldc2_w 1848177238
    //   1967: l2i
    //   1968: ldc_w 2061508379
    //   1971: ixor
    //   1972: goto -> 1983
    //   1975: ldc2_w -701835249
    //   1978: l2i
    //   1979: ldc_w 1181809746
    //   1982: ixor
    //   1983: ldc2_w -37876451
    //   1986: l2i
    //   1987: ldc_w 1823695966
    //   1990: ixor
    //   1991: ixor
    //   1992: lookupswitch default -> 5750, -2050653170 -> 1975, 22498590 -> 2020
    //   2020: goto -> 2024
    //   2023: athrow
    //   2024: invokestatic 0 : (Ljava/lang/String;)Ljava/lang/String;
    //   2027: goto -> 2031
    //   2030: athrow
    //   2031: getstatic Perryc.1 : I
    //   2034: ifeq -> 2048
    //   2037: ldc2_w -1902991217
    //   2040: l2i
    //   2041: ldc_w 1050245695
    //   2044: ixor
    //   2045: goto -> 2056
    //   2048: ldc2_w 1297746763
    //   2051: l2i
    //   2052: ldc_w -793492498
    //   2055: ixor
    //   2056: ldc2_w 1824327970
    //   2059: l2i
    //   2060: ldc_w 1255398769
    //   2063: ixor
    //   2064: ixor
    //   2065: lookupswitch default -> 2092, -2120620896 -> 2048, -1771763997 -> 5724
    //   2092: goto -> 2096
    //   2095: athrow
    //   2096: invokevirtual append : (Ljava/lang/String;)Ljava/lang/StringBuilder;
    //   2099: goto -> 2103
    //   2102: athrow
    //   2103: getstatic Perryc.0 : I
    //   2106: ifle -> 2120
    //   2109: ldc2_w -293981295
    //   2112: l2i
    //   2113: ldc_w -1964751125
    //   2116: ixor
    //   2117: goto -> 2128
    //   2120: ldc2_w -1189648941
    //   2123: l2i
    //   2124: ldc_w 79105343
    //   2127: ixor
    //   2128: ldc2_w 440363450
    //   2131: l2i
    //   2132: ldc_w -1107829173
    //   2135: ixor
    //   2136: ixor
    //   2137: lookupswitch default -> 2164, -1017724277 -> 5822, 1157334386 -> 2120
    //   2164: getstatic com/mojang/realmsclient/gui/ChatFormatting.GRAY : Lcom/mojang/realmsclient/gui/ChatFormatting;
    //   2167: getstatic Perryc.c : I
    //   2170: iflt -> 2184
    //   2173: ldc2_w -557199640
    //   2176: l2i
    //   2177: ldc_w -368637000
    //   2180: ixor
    //   2181: goto -> 2192
    //   2184: ldc2_w -821216298
    //   2187: l2i
    //   2188: ldc_w -1502323069
    //   2191: ixor
    //   2192: ldc2_w -303132355
    //   2195: l2i
    //   2196: ldc_w 1663806626
    //   2199: ixor
    //   2200: ixor
    //   2201: lookupswitch default -> 5846, -1173620529 -> 2184, -407086902 -> 2228
    //   2228: goto -> 2232
    //   2231: athrow
    //   2232: invokevirtual append : (Ljava/lang/Object;)Ljava/lang/StringBuilder;
    //   2235: goto -> 2239
    //   2238: athrow
    //   2239: getstatic Perryc.0 : I
    //   2242: ifle -> 2256
    //   2245: ldc2_w -2096766224
    //   2248: l2i
    //   2249: ldc_w -1350071260
    //   2252: ixor
    //   2253: goto -> 2264
    //   2256: ldc2_w 789908587
    //   2259: l2i
    //   2260: ldc_w -801364292
    //   2263: ixor
    //   2264: ldc2_w 1710500485
    //   2267: l2i
    //   2268: ldc_w -183756539
    //   2271: ixor
    //   2272: ixor
    //   2273: lookupswitch default -> 5728, -1132831404 -> 2256, 1875974487 -> 2300
    //   2300: aload #4
    //   2302: getstatic Perryc.c : I
    //   2305: iflt -> 2319
    //   2308: ldc2_w 1514409014
    //   2311: l2i
    //   2312: ldc_w -84871563
    //   2315: ixor
    //   2316: goto -> 2327
    //   2319: ldc2_w -1086848423
    //   2322: l2i
    //   2323: ldc_w 1782870056
    //   2326: ixor
    //   2327: ldc2_w -518713878
    //   2330: l2i
    //   2331: ldc_w -1999021504
    //   2334: ixor
    //   2335: ixor
    //   2336: lookupswitch default -> 2364, -914838039 -> 5752, 1896256511 -> 2319
    //   2364: goto -> 2368
    //   2367: athrow
    //   2368: invokevirtual getBind : ()Lbigname/zprestige/webhack/features/setting/Bind;
    //   2371: goto -> 2375
    //   2374: athrow
    //   2375: getstatic Perryc.0 : I
    //   2378: ifle -> 2392
    //   2381: ldc2_w -1324366052
    //   2384: l2i
    //   2385: ldc_w -529641307
    //   2388: ixor
    //   2389: goto -> 2400
    //   2392: ldc2_w -1373722389
    //   2395: l2i
    //   2396: ldc_w -1587586625
    //   2399: ixor
    //   2400: ldc2_w -1548394082
    //   2403: l2i
    //   2404: ldc_w -111855591
    //   2407: ixor
    //   2408: ixor
    //   2409: lookupswitch default -> 2436, 193056318 -> 5726, 662182158 -> 2392
    //   2436: goto -> 2440
    //   2439: athrow
    //   2440: invokevirtual toString : ()Ljava/lang/String;
    //   2443: goto -> 2447
    //   2446: athrow
    //   2447: getstatic Perryc.0 : I
    //   2450: ifle -> 2464
    //   2453: ldc2_w -1506304370
    //   2456: l2i
    //   2457: ldc_w -1249664682
    //   2460: ixor
    //   2461: goto -> 2472
    //   2464: ldc2_w -281283948
    //   2467: l2i
    //   2468: ldc_w 1554952836
    //   2471: ixor
    //   2472: ldc2_w 245978705
    //   2475: l2i
    //   2476: ldc_w 1982293053
    //   2479: ixor
    //   2480: ixor
    //   2481: lookupswitch default -> 2508, -1204483627 -> 2464, 1798966708 -> 5712
    //   2508: goto -> 2512
    //   2511: athrow
    //   2512: invokevirtual append : (Ljava/lang/String;)Ljava/lang/StringBuilder;
    //   2515: goto -> 2519
    //   2518: athrow
    //   2519: getstatic Perryc.0 : I
    //   2522: ifle -> 2536
    //   2525: ldc2_w 110584374
    //   2528: l2i
    //   2529: ldc_w -703895352
    //   2532: ixor
    //   2533: goto -> 2544
    //   2536: ldc2_w 545700414
    //   2539: l2i
    //   2540: ldc_w -212516673
    //   2543: ixor
    //   2544: ldc2_w 86028830
    //   2547: l2i
    //   2548: ldc_w 1855923212
    //   2551: ixor
    //   2552: ixor
    //   2553: lookupswitch default -> 2580, -1155293972 -> 5788, 796117159 -> 2536
    //   2580: goto -> 2584
    //   2583: athrow
    //   2584: invokevirtual toString : ()Ljava/lang/String;
    //   2587: goto -> 2591
    //   2590: athrow
    //   2591: getstatic Perryc.c : I
    //   2594: iflt -> 2608
    //   2597: ldc2_w -837562355
    //   2600: l2i
    //   2601: ldc_w 1745274217
    //   2604: ixor
    //   2605: goto -> 2616
    //   2608: ldc2_w -433635998
    //   2611: l2i
    //   2612: ldc_w -377890067
    //   2615: ixor
    //   2616: ldc2_w 1260238056
    //   2619: l2i
    //   2620: ldc_w -514198189
    //   2623: ixor
    //   2624: ixor
    //   2625: lookupswitch default -> 5844, -1524980172 -> 2652, 206656735 -> 2608
    //   2652: goto -> 2656
    //   2655: athrow
    //   2656: invokestatic sendMessage : (Ljava/lang/String;)V
    //   2659: goto -> 2663
    //   2662: athrow
    //   2663: return
    //   2664: getstatic Perryc.0 : I
    //   2667: ifle -> 2681
    //   2670: ldc2_w -2127263866
    //   2673: l2i
    //   2674: ldc_w -339147925
    //   2677: ixor
    //   2678: goto -> 2689
    //   2681: ldc2_w -1190477079
    //   2684: l2i
    //   2685: ldc_w -2049900693
    //   2688: ixor
    //   2689: ldc2_w -2124380333
    //   2692: l2i
    //   2693: ldc_w -1405287341
    //   2696: ixor
    //   2697: ixor
    //   2698: lookupswitch default -> 5760, 294108802 -> 2724, 1201670125 -> 2681
    //   2724: aload_2
    //   2725: getstatic Perryc.1 : I
    //   2728: ifeq -> 2742
    //   2731: ldc2_w -134567192
    //   2734: l2i
    //   2735: ldc_w -782740745
    //   2738: ixor
    //   2739: goto -> 2750
    //   2742: ldc2_w -1249167551
    //   2745: l2i
    //   2746: ldc_w 1889709711
    //   2749: ixor
    //   2750: ldc2_w -292500610
    //   2753: l2i
    //   2754: ldc_w 1813645145
    //   2757: ixor
    //   2758: ixor
    //   2759: lookupswitch default -> 2784, -1540869064 -> 5836, 1761294121 -> 2742
    //   2784: goto -> 2788
    //   2787: athrow
    //   2788: invokevirtual toUpperCase : ()Ljava/lang/String;
    //   2791: goto -> 2795
    //   2794: athrow
    //   2795: getstatic Perryc.1 : I
    //   2798: ifeq -> 2812
    //   2801: ldc2_w 227939016
    //   2804: l2i
    //   2805: ldc_w 576453364
    //   2808: ixor
    //   2809: goto -> 2820
    //   2812: ldc2_w -1423605173
    //   2815: l2i
    //   2816: ldc_w -41177263
    //   2819: ixor
    //   2820: ldc2_w -1387393909
    //   2823: l2i
    //   2824: ldc_w 1403383278
    //   2827: ixor
    //   2828: ixor
    //   2829: lookupswitch default -> 5774, -1471820673 -> 2856, -786036391 -> 2812
    //   2856: goto -> 2860
    //   2859: athrow
    //   2860: invokestatic getKeyIndex : (Ljava/lang/String;)I
    //   2863: goto -> 2867
    //   2866: athrow
    //   2867: getstatic Perryc.0 : I
    //   2870: ifle -> 2884
    //   2873: ldc2_w 2039060806
    //   2876: l2i
    //   2877: ldc_w -345373381
    //   2880: ixor
    //   2881: goto -> 2892
    //   2884: ldc2_w -879228239
    //   2887: l2i
    //   2888: ldc_w -1656172840
    //   2891: ixor
    //   2892: ldc2_w -497813204
    //   2895: l2i
    //   2896: ldc_w 399158399
    //   2899: ixor
    //   2900: ixor
    //   2901: lookupswitch default -> 5810, -1555459782 -> 2928, 1736100142 -> 2884
    //   2928: istore #5
    //   2930: getstatic Perryc.c : I
    //   2933: iflt -> 2947
    //   2936: ldc2_w 1995013276
    //   2939: l2i
    //   2940: ldc_w -173083156
    //   2943: ixor
    //   2944: goto -> 2955
    //   2947: ldc2_w -172499100
    //   2950: l2i
    //   2951: ldc_w -1169033681
    //   2954: ixor
    //   2955: ldc2_w 1474251836
    //   2958: l2i
    //   2959: ldc_w -1901623622
    //   2962: ixor
    //   2963: ixor
    //   2964: lookupswitch default -> 2992, 565826525 -> 2947, 1514095606 -> 5794
    //   2992: aload_2
    //   2993: ldc_w 'ﴟ㌜ﵭ좵'
    //   2996: getstatic Perryc.0 : I
    //   2999: ifle -> 3013
    //   3002: ldc2_w 1052917419
    //   3005: l2i
    //   3006: ldc_w 660832833
    //   3009: ixor
    //   3010: goto -> 3021
    //   3013: ldc2_w 424717898
    //   3016: l2i
    //   3017: ldc_w 2065020836
    //   3020: ixor
    //   3021: ldc2_w 647826096
    //   3024: l2i
    //   3025: ldc_w -46060844
    //   3028: ixor
    //   3029: ixor
    //   3030: lookupswitch default -> 3056, -1876867588 -> 3013, -1031955314 -> 5758
    //   3056: goto -> 3060
    //   3059: athrow
    //   3060: invokestatic 0 : (Ljava/lang/String;)Ljava/lang/String;
    //   3063: goto -> 3067
    //   3066: athrow
    //   3067: getstatic Perryc.c : I
    //   3070: iflt -> 3084
    //   3073: ldc2_w -1630942724
    //   3076: l2i
    //   3077: ldc_w 1190646690
    //   3080: ixor
    //   3081: goto -> 3092
    //   3084: ldc2_w -479427458
    //   3087: l2i
    //   3088: ldc_w -493710316
    //   3091: ixor
    //   3092: ldc2_w 443795204
    //   3095: l2i
    //   3096: ldc_w -1694084249
    //   3099: ixor
    //   3100: ixor
    //   3101: lookupswitch default -> 3128, -889480947 -> 3084, 1498123837 -> 5776
    //   3128: goto -> 3132
    //   3131: athrow
    //   3132: invokevirtual equalsIgnoreCase : (Ljava/lang/String;)Z
    //   3135: goto -> 3139
    //   3138: athrow
    //   3139: ifeq -> 3153
    //   3142: ldc2_w 845924657
    //   3145: l2i
    //   3146: ldc_w 675787825
    //   3149: ixor
    //   3150: goto -> 3161
    //   3153: ldc2_w -593977300
    //   3156: l2i
    //   3157: ldc_w -961225425
    //   3160: ixor
    //   3161: ldc2_w 81414020
    //   3164: l2i
    //   3165: ldc_w 541455917
    //   3168: ixor
    //   3169: ixor
    //   3170: tableswitch default -> 3142, 1051970729 -> 3192, 1051970730 -> 3262
    //   3192: ldc2_w 154727442
    //   3195: l2i
    //   3196: ldc_w -154727443
    //   3199: ixor
    //   3200: getstatic Perryc.0 : I
    //   3203: ifle -> 3217
    //   3206: ldc2_w -1481414031
    //   3209: l2i
    //   3210: ldc_w 1322069611
    //   3213: ixor
    //   3214: goto -> 3225
    //   3217: ldc2_w 544107403
    //   3220: l2i
    //   3221: ldc_w -1243249748
    //   3224: ixor
    //   3225: ldc2_w 1004145778
    //   3228: l2i
    //   3229: ldc_w 1678130774
    //   3232: ixor
    //   3233: ixor
    //   3234: lookupswitch default -> 5754, -1230866882 -> 3217, -900212221 -> 3260
    //   3260: istore #5
    //   3262: getstatic Perryc.0 : I
    //   3265: ifle -> 3279
    //   3268: ldc2_w 252032970
    //   3271: l2i
    //   3272: ldc_w -1199276776
    //   3275: ixor
    //   3276: goto -> 3287
    //   3279: ldc2_w -1475994257
    //   3282: l2i
    //   3283: ldc_w -1183289516
    //   3286: ixor
    //   3287: ldc2_w -2097905965
    //   3290: l2i
    //   3291: ldc_w 1034089836
    //   3294: ixor
    //   3295: ixor
    //   3296: lookupswitch default -> 3324, -1235464287 -> 3279, 148324717 -> 5808
    //   3324: iload #5
    //   3326: ifne -> 3340
    //   3329: ldc2_w -73934267
    //   3332: l2i
    //   3333: ldc_w -50393539
    //   3336: ixor
    //   3337: goto -> 3348
    //   3340: ldc2_w 801878899
    //   3343: l2i
    //   3344: ldc_w 681797384
    //   3347: ixor
    //   3348: ldc2_w 1910573950
    //   3351: l2i
    //   3352: ldc_w -1497182885
    //   3355: ixor
    //   3356: ixor
    //   3357: tableswitch default -> 3329, -800386467 -> 3380, -800386466 -> 4028
    //   3380: new java/lang/StringBuilder
    //   3383: dup
    //   3384: getstatic Perryc.c : I
    //   3387: iflt -> 3401
    //   3390: ldc2_w -53361429
    //   3393: l2i
    //   3394: ldc_w 1105469558
    //   3397: ixor
    //   3398: goto -> 3409
    //   3401: ldc2_w 1516203070
    //   3404: l2i
    //   3405: ldc_w 1949241977
    //   3408: ixor
    //   3409: ldc2_w 2069376383
    //   3412: l2i
    //   3413: ldc_w 987778827
    //   3416: ixor
    //   3417: ixor
    //   3418: lookupswitch default -> 5766, -57833751 -> 3401, 1875385395 -> 3444
    //   3444: goto -> 3448
    //   3447: athrow
    //   3448: invokespecial <init> : ()V
    //   3451: goto -> 3455
    //   3454: athrow
    //   3455: ldc_w 'ﴤ㌝ﵨ좾喜Ꮊ๷胤筯२䗓੧ゖ'
    //   3458: getstatic Perryc.1 : I
    //   3461: ifeq -> 3475
    //   3464: ldc2_w -670449084
    //   3467: l2i
    //   3468: ldc_w -1888406638
    //   3471: ixor
    //   3472: goto -> 3483
    //   3475: ldc2_w -307084725
    //   3478: l2i
    //   3479: ldc_w -2029480060
    //   3482: ixor
    //   3483: ldc2_w 522495315
    //   3486: l2i
    //   3487: ldc_w 1596694841
    //   3490: ixor
    //   3491: ixor
    //   3492: lookupswitch default -> 3520, -2034728713 -> 3475, 393737660 -> 5778
    //   3520: goto -> 3524
    //   3523: athrow
    //   3524: invokestatic 0 : (Ljava/lang/String;)Ljava/lang/String;
    //   3527: goto -> 3531
    //   3530: athrow
    //   3531: getstatic Perryc.0 : I
    //   3534: ifle -> 3548
    //   3537: ldc2_w -709349579
    //   3540: l2i
    //   3541: ldc_w 1754039189
    //   3544: ixor
    //   3545: goto -> 3556
    //   3548: ldc2_w 1819230638
    //   3551: l2i
    //   3552: ldc_w -38416759
    //   3555: ixor
    //   3556: ldc2_w -2043963095
    //   3559: l2i
    //   3560: ldc_w -1161355343
    //   3563: ixor
    //   3564: ixor
    //   3565: lookupswitch default -> 5812, -2116539848 -> 3548, -1388967489 -> 3592
    //   3592: goto -> 3596
    //   3595: athrow
    //   3596: invokevirtual append : (Ljava/lang/String;)Ljava/lang/StringBuilder;
    //   3599: goto -> 3603
    //   3602: athrow
    //   3603: getstatic Perryc.1 : I
    //   3606: ifeq -> 3620
    //   3609: ldc2_w 1858852746
    //   3612: l2i
    //   3613: ldc_w -387183312
    //   3616: ixor
    //   3617: goto -> 3628
    //   3620: ldc2_w 1287485352
    //   3623: l2i
    //   3624: ldc_w -1370320717
    //   3627: ixor
    //   3628: ldc2_w 1671694234
    //   3631: l2i
    //   3632: ldc_w -445839289
    //   3635: ixor
    //   3636: ixor
    //   3637: lookupswitch default -> 5706, 15652199 -> 3620, 1680271558 -> 3664
    //   3664: aload_2
    //   3665: getstatic Perryc.1 : I
    //   3668: ifeq -> 3682
    //   3671: ldc2_w -1353376540
    //   3674: l2i
    //   3675: ldc_w -1547603678
    //   3678: ixor
    //   3679: goto -> 3690
    //   3682: ldc2_w 418766803
    //   3685: l2i
    //   3686: ldc_w 1234943436
    //   3689: ixor
    //   3690: ldc2_w 876722738
    //   3693: l2i
    //   3694: ldc_w -914228153
    //   3697: ixor
    //   3698: ixor
    //   3699: lookupswitch default -> 5838, -1397873558 -> 3724, -246142029 -> 3682
    //   3724: goto -> 3728
    //   3727: athrow
    //   3728: invokevirtual append : (Ljava/lang/String;)Ljava/lang/StringBuilder;
    //   3731: goto -> 3735
    //   3734: athrow
    //   3735: ldc_w 'ﵖ㍒'
    //   3738: getstatic Perryc.c : I
    //   3741: iflt -> 3755
    //   3744: ldc2_w -2124439228
    //   3747: l2i
    //   3748: ldc_w 225611252
    //   3751: ixor
    //   3752: goto -> 3763
    //   3755: ldc2_w 538979773
    //   3758: l2i
    //   3759: ldc_w -223534511
    //   3762: ixor
    //   3763: ldc2_w 895478828
    //   3766: l2i
    //   3767: ldc_w -197995986
    //   3770: ixor
    //   3771: ixor
    //   3772: lookupswitch default -> 3800, -1876436781 -> 3755, 1296044722 -> 5710
    //   3800: goto -> 3804
    //   3803: athrow
    //   3804: invokestatic 0 : (Ljava/lang/String;)Ljava/lang/String;
    //   3807: goto -> 3811
    //   3810: athrow
    //   3811: getstatic Perryc.1 : I
    //   3814: ifeq -> 3828
    //   3817: ldc2_w 152856645
    //   3820: l2i
    //   3821: ldc_w -290597082
    //   3824: ixor
    //   3825: goto -> 3836
    //   3828: ldc2_w 437509790
    //   3831: l2i
    //   3832: ldc_w -219802452
    //   3835: ixor
    //   3836: ldc2_w 526452253
    //   3839: l2i
    //   3840: ldc_w -325754175
    //   3843: ixor
    //   3844: ixor
    //   3845: lookupswitch default -> 3872, 155988374 -> 3828, 340122559 -> 5806
    //   3872: goto -> 3876
    //   3875: athrow
    //   3876: invokevirtual append : (Ljava/lang/String;)Ljava/lang/StringBuilder;
    //   3879: goto -> 3883
    //   3882: athrow
    //   3883: getstatic Perryc.c : I
    //   3886: iflt -> 3900
    //   3889: ldc2_w -418993995
    //   3892: l2i
    //   3893: ldc_w 480646955
    //   3896: ixor
    //   3897: goto -> 3908
    //   3900: ldc2_w -1261897868
    //   3903: l2i
    //   3904: ldc_w 1798135351
    //   3907: ixor
    //   3908: ldc2_w -1806964226
    //   3911: l2i
    //   3912: ldc_w -462955088
    //   3915: ixor
    //   3916: ixor
    //   3917: lookupswitch default -> 3944, -1953723440 -> 5722, 1697530445 -> 3900
    //   3944: goto -> 3948
    //   3947: athrow
    //   3948: invokevirtual toString : ()Ljava/lang/String;
    //   3951: goto -> 3955
    //   3954: athrow
    //   3955: getstatic Perryc.c : I
    //   3958: iflt -> 3972
    //   3961: ldc2_w -2006092914
    //   3964: l2i
    //   3965: ldc_w 276721717
    //   3968: ixor
    //   3969: goto -> 3980
    //   3972: ldc2_w -949611613
    //   3975: l2i
    //   3976: ldc_w 587434412
    //   3979: ixor
    //   3980: ldc2_w 1310437054
    //   3983: l2i
    //   3984: ldc_w -2070487400
    //   3987: ixor
    //   3988: ixor
    //   3989: lookupswitch default -> 5756, 787016233 -> 4016, 1386115997 -> 3972
    //   4016: goto -> 4020
    //   4019: athrow
    //   4020: invokestatic sendMessage : (Ljava/lang/String;)V
    //   4023: goto -> 4027
    //   4026: athrow
    //   4027: return
    //   4028: getstatic Perryc.1 : I
    //   4031: ifeq -> 4045
    //   4034: ldc2_w -1332553607
    //   4037: l2i
    //   4038: ldc_w 1314290909
    //   4041: ixor
    //   4042: goto -> 4053
    //   4045: ldc2_w 1053556564
    //   4048: l2i
    //   4049: ldc_w -1519884907
    //   4052: ixor
    //   4053: ldc2_w 1935295448
    //   4056: l2i
    //   4057: ldc_w 1709524379
    //   4060: ixor
    //   4061: ixor
    //   4062: lookupswitch default -> 4088, -637316162 -> 4045, -394550553 -> 5858
    //   4088: aload #4
    //   4090: getstatic Perryc.c : I
    //   4093: iflt -> 4107
    //   4096: ldc2_w -1255288020
    //   4099: l2i
    //   4100: ldc_w 848483379
    //   4103: ixor
    //   4104: goto -> 4115
    //   4107: ldc2_w 292661810
    //   4110: l2i
    //   4111: ldc_w -916694281
    //   4114: ixor
    //   4115: ldc2_w 392480247
    //   4118: l2i
    //   4119: ldc_w -980825503
    //   4122: ixor
    //   4123: ixor
    //   4124: lookupswitch default -> 4152, -2064376906 -> 4107, 1431439497 -> 5770
    //   4152: getfield bind : Lbigname/zprestige/webhack/features/setting/Setting;
    //   4155: new bigname/zprestige/webhack/features/setting/Bind
    //   4158: dup
    //   4159: getstatic Perryc.1 : I
    //   4162: ifeq -> 4176
    //   4165: ldc2_w -1573651730
    //   4168: l2i
    //   4169: ldc_w -174885967
    //   4172: ixor
    //   4173: goto -> 4184
    //   4176: ldc2_w -1296444144
    //   4179: l2i
    //   4180: ldc_w 2003400610
    //   4183: ixor
    //   4184: ldc2_w -790735632
    //   4187: l2i
    //   4188: ldc_w 1561947738
    //   4191: ixor
    //   4192: ixor
    //   4193: lookupswitch default -> 4220, -630737931 -> 5804, 1998443861 -> 4176
    //   4220: iload #5
    //   4222: getstatic Perryc.1 : I
    //   4225: ifeq -> 4239
    //   4228: ldc2_w 501435167
    //   4231: l2i
    //   4232: ldc_w -299087879
    //   4235: ixor
    //   4236: goto -> 4247
    //   4239: ldc2_w -967970226
    //   4242: l2i
    //   4243: ldc_w 1205503884
    //   4246: ixor
    //   4247: ldc2_w -1108656284
    //   4250: l2i
    //   4251: ldc_w 1185355643
    //   4254: ixor
    //   4255: ixor
    //   4256: lookupswitch default -> 5704, 142812409 -> 4239, 2061196765 -> 4284
    //   4284: goto -> 4288
    //   4287: athrow
    //   4288: invokespecial <init> : (I)V
    //   4291: goto -> 4295
    //   4294: athrow
    //   4295: getstatic Perryc.0 : I
    //   4298: ifle -> 4312
    //   4301: ldc2_w 908070502
    //   4304: l2i
    //   4305: ldc_w -103422106
    //   4308: ixor
    //   4309: goto -> 4320
    //   4312: ldc2_w 1221495118
    //   4315: l2i
    //   4316: ldc_w -1156947137
    //   4319: ixor
    //   4320: ldc2_w -117756641
    //   4323: l2i
    //   4324: ldc_w 157001804
    //   4327: ixor
    //   4328: ixor
    //   4329: lookupswitch default -> 4356, 1045785683 -> 5848, 1963509628 -> 4312
    //   4356: goto -> 4360
    //   4359: athrow
    //   4360: invokevirtual setValue : (Ljava/lang/Object;)V
    //   4363: goto -> 4367
    //   4366: athrow
    //   4367: new java/lang/StringBuilder
    //   4370: dup
    //   4371: getstatic Perryc.1 : I
    //   4374: ifeq -> 4388
    //   4377: ldc2_w -668421456
    //   4380: l2i
    //   4381: ldc_w -708867358
    //   4384: ixor
    //   4385: goto -> 4396
    //   4388: ldc2_w 1635750169
    //   4391: l2i
    //   4392: ldc_w 1535373757
    //   4395: ixor
    //   4396: ldc2_w 1503437609
    //   4399: l2i
    //   4400: ldc_w -611799517
    //   4403: ixor
    //   4404: ixor
    //   4405: lookupswitch default -> 5796, -1887226536 -> 4388, -1192727122 -> 4432
    //   4432: goto -> 4436
    //   4435: athrow
    //   4436: invokespecial <init> : ()V
    //   4439: goto -> 4443
    //   4442: athrow
    //   4443: ldc_w 'ﴳ㌚ﵭ좴嗓Ꭻ๶肶笤'
    //   4446: getstatic Perryc.1 : I
    //   4449: ifeq -> 4463
    //   4452: ldc2_w 867142420
    //   4455: l2i
    //   4456: ldc_w 997574916
    //   4459: ixor
    //   4460: goto -> 4471
    //   4463: ldc2_w 1971478746
    //   4466: l2i
    //   4467: ldc_w -489674874
    //   4470: ixor
    //   4471: ldc2_w 1323969116
    //   4474: l2i
    //   4475: ldc_w 475894546
    //   4478: ixor
    //   4479: ixor
    //   4480: lookupswitch default -> 5826, -974782958 -> 4508, 1517157214 -> 4463
    //   4508: goto -> 4512
    //   4511: athrow
    //   4512: invokestatic 0 : (Ljava/lang/String;)Ljava/lang/String;
    //   4515: goto -> 4519
    //   4518: athrow
    //   4519: getstatic Perryc.1 : I
    //   4522: ifeq -> 4536
    //   4525: ldc2_w 721483663
    //   4528: l2i
    //   4529: ldc_w 656347408
    //   4532: ixor
    //   4533: goto -> 4544
    //   4536: ldc2_w 1473513376
    //   4539: l2i
    //   4540: ldc_w 1689057102
    //   4543: ixor
    //   4544: ldc2_w -435315602
    //   4547: l2i
    //   4548: ldc_w -331611157
    //   4551: ixor
    //   4552: ixor
    //   4553: lookupswitch default -> 5730, 103708954 -> 4536, 961113963 -> 4580
    //   4580: goto -> 4584
    //   4583: athrow
    //   4584: invokevirtual append : (Ljava/lang/String;)Ljava/lang/StringBuilder;
    //   4587: goto -> 4591
    //   4590: athrow
    //   4591: getstatic Perryc.c : I
    //   4594: iflt -> 4608
    //   4597: ldc2_w -494912613
    //   4600: l2i
    //   4601: ldc_w -1636829587
    //   4604: ixor
    //   4605: goto -> 4616
    //   4608: ldc2_w -1842383754
    //   4611: l2i
    //   4612: ldc_w 1953890900
    //   4615: ixor
    //   4616: ldc2_w -1374034287
    //   4619: l2i
    //   4620: ldc_w -1379632810
    //   4623: ixor
    //   4624: ixor
    //   4625: lookupswitch default -> 4652, -1330278414 -> 4608, 2134004273 -> 5834
    //   4652: getstatic com/mojang/realmsclient/gui/ChatFormatting.GREEN : Lcom/mojang/realmsclient/gui/ChatFormatting;
    //   4655: getstatic Perryc.c : I
    //   4658: iflt -> 4672
    //   4661: ldc2_w -842557465
    //   4664: l2i
    //   4665: ldc_w -312368691
    //   4668: ixor
    //   4669: goto -> 4680
    //   4672: ldc2_w 1683352341
    //   4675: l2i
    //   4676: ldc_w -626958488
    //   4679: ixor
    //   4680: ldc2_w -188349981
    //   4683: l2i
    //   4684: ldc_w 413432741
    //   4687: ixor
    //   4688: ixor
    //   4689: lookupswitch default -> 4716, -1737573496 -> 4672, -859550612 -> 5780
    //   4716: goto -> 4720
    //   4719: athrow
    //   4720: invokevirtual append : (Ljava/lang/Object;)Ljava/lang/StringBuilder;
    //   4723: goto -> 4727
    //   4726: athrow
    //   4727: getstatic Perryc.c : I
    //   4730: iflt -> 4744
    //   4733: ldc2_w 1935629573
    //   4736: l2i
    //   4737: ldc_w -1692654664
    //   4740: ixor
    //   4741: goto -> 4752
    //   4744: ldc2_w -1668127503
    //   4747: l2i
    //   4748: ldc_w -229369753
    //   4751: ixor
    //   4752: ldc2_w 274695057
    //   4755: l2i
    //   4756: ldc_w 1002781226
    //   4759: ixor
    //   4760: ixor
    //   4761: lookupswitch default -> 5784, -1009137914 -> 4744, 1163707693 -> 4788
    //   4788: aload #4
    //   4790: getstatic Perryc.1 : I
    //   4793: ifeq -> 4807
    //   4796: ldc2_w -961943192
    //   4799: l2i
    //   4800: ldc_w 246631604
    //   4803: ixor
    //   4804: goto -> 4815
    //   4807: ldc2_w 1576832002
    //   4810: l2i
    //   4811: ldc_w 141152191
    //   4814: ixor
    //   4815: ldc2_w -310908056
    //   4818: l2i
    //   4819: ldc_w -970189092
    //   4822: ixor
    //   4823: ixor
    //   4824: lookupswitch default -> 5772, -482256792 -> 4807, 2127478281 -> 4852
    //   4852: goto -> 4856
    //   4855: athrow
    //   4856: invokevirtual getName : ()Ljava/lang/String;
    //   4859: goto -> 4863
    //   4862: athrow
    //   4863: getstatic Perryc.c : I
    //   4866: iflt -> 4880
    //   4869: ldc2_w -1079044598
    //   4872: l2i
    //   4873: ldc_w -144778473
    //   4876: ixor
    //   4877: goto -> 4888
    //   4880: ldc2_w -968906318
    //   4883: l2i
    //   4884: ldc_w 1248585780
    //   4887: ixor
    //   4888: ldc2_w -1989592580
    //   4891: l2i
    //   4892: ldc_w -1691432058
    //   4895: ixor
    //   4896: ixor
    //   4897: lookupswitch default -> 4924, -2017553588 -> 4880, 1521893223 -> 5744
    //   4924: goto -> 4928
    //   4927: athrow
    //   4928: invokevirtual append : (Ljava/lang/String;)Ljava/lang/StringBuilder;
    //   4931: goto -> 4935
    //   4934: athrow
    //   4935: getstatic Perryc.1 : I
    //   4938: ifeq -> 4952
    //   4941: ldc2_w -1647237991
    //   4944: l2i
    //   4945: ldc_w 1983413405
    //   4948: ixor
    //   4949: goto -> 4960
    //   4952: ldc2_w -1579974222
    //   4955: l2i
    //   4956: ldc_w 1828560512
    //   4959: ixor
    //   4960: ldc2_w 1982046875
    //   4963: l2i
    //   4964: ldc_w 537811707
    //   4967: ixor
    //   4968: ixor
    //   4969: lookupswitch default -> 5708, -1694242990 -> 4996, -1111187356 -> 4952
    //   4996: getstatic com/mojang/realmsclient/gui/ChatFormatting.WHITE : Lcom/mojang/realmsclient/gui/ChatFormatting;
    //   4999: getstatic Perryc.c : I
    //   5002: iflt -> 5016
    //   5005: ldc2_w 12099599
    //   5008: l2i
    //   5009: ldc_w -596042673
    //   5012: ixor
    //   5013: goto -> 5024
    //   5016: ldc2_w 308804938
    //   5019: l2i
    //   5020: ldc_w -353546473
    //   5023: ixor
    //   5024: ldc2_w -441318120
    //   5027: l2i
    //   5028: ldc_w -1306053559
    //   5031: ixor
    //   5032: ixor
    //   5033: lookupswitch default -> 5742, -1957393135 -> 5016, -1356889332 -> 5060
    //   5060: goto -> 5064
    //   5063: athrow
    //   5064: invokevirtual append : (Ljava/lang/Object;)Ljava/lang/StringBuilder;
    //   5067: goto -> 5071
    //   5070: athrow
    //   5071: ldc_w 'ﵑ㌀ﵦ좤嗓Ꮉ๶胤'
    //   5074: getstatic Perryc.0 : I
    //   5077: ifle -> 5091
    //   5080: ldc2_w 465157640
    //   5083: l2i
    //   5084: ldc_w 953712796
    //   5087: ixor
    //   5088: goto -> 5099
    //   5091: ldc2_w 669671956
    //   5094: l2i
    //   5095: ldc_w -365361353
    //   5098: ixor
    //   5099: ldc2_w 1482918794
    //   5102: l2i
    //   5103: ldc_w 1039454257
    //   5106: ixor
    //   5107: ixor
    //   5108: lookupswitch default -> 5136, -1150910210 -> 5091, 1190552879 -> 5828
    //   5136: goto -> 5140
    //   5139: athrow
    //   5140: invokestatic 0 : (Ljava/lang/String;)Ljava/lang/String;
    //   5143: goto -> 5147
    //   5146: athrow
    //   5147: getstatic Perryc.0 : I
    //   5150: ifle -> 5164
    //   5153: ldc2_w -1161455801
    //   5156: l2i
    //   5157: ldc_w 1655455798
    //   5160: ixor
    //   5161: goto -> 5172
    //   5164: ldc2_w 1171281522
    //   5167: l2i
    //   5168: ldc_w -381193737
    //   5171: ixor
    //   5172: ldc2_w 1282021565
    //   5175: l2i
    //   5176: ldc_w -1912346282
    //   5179: ixor
    //   5180: ixor
    //   5181: lookupswitch default -> 5208, 124153988 -> 5164, 436217498 -> 5738
    //   5208: goto -> 5212
    //   5211: athrow
    //   5212: invokevirtual append : (Ljava/lang/String;)Ljava/lang/StringBuilder;
    //   5215: goto -> 5219
    //   5218: athrow
    //   5219: getstatic Perryc.1 : I
    //   5222: ifeq -> 5236
    //   5225: ldc2_w 574543308
    //   5228: l2i
    //   5229: ldc_w -1145258509
    //   5232: ixor
    //   5233: goto -> 5244
    //   5236: ldc2_w 1313746733
    //   5239: l2i
    //   5240: ldc_w 137587340
    //   5243: ixor
    //   5244: ldc2_w 1780388575
    //   5247: l2i
    //   5248: ldc_w -1509801279
    //   5251: ixor
    //   5252: ixor
    //   5253: lookupswitch default -> 5814, -1973316161 -> 5280, 1436465185 -> 5236
    //   5280: getstatic com/mojang/realmsclient/gui/ChatFormatting.GRAY : Lcom/mojang/realmsclient/gui/ChatFormatting;
    //   5283: getstatic Perryc.c : I
    //   5286: iflt -> 5300
    //   5289: ldc2_w 2115452762
    //   5292: l2i
    //   5293: ldc_w 1712627189
    //   5296: ixor
    //   5297: goto -> 5308
    //   5300: ldc2_w -2065129898
    //   5303: l2i
    //   5304: ldc_w 467542659
    //   5307: ixor
    //   5308: ldc2_w -1778186540
    //   5311: l2i
    //   5312: ldc_w 1342609867
    //   5315: ixor
    //   5316: ixor
    //   5317: lookupswitch default -> 5818, -570016336 -> 5300, 1496523722 -> 5344
    //   5344: goto -> 5348
    //   5347: athrow
    //   5348: invokevirtual append : (Ljava/lang/Object;)Ljava/lang/StringBuilder;
    //   5351: goto -> 5355
    //   5354: athrow
    //   5355: getstatic Perryc.c : I
    //   5358: iflt -> 5372
    //   5361: ldc2_w -1628725297
    //   5364: l2i
    //   5365: ldc_w -1244677887
    //   5368: ixor
    //   5369: goto -> 5380
    //   5372: ldc2_w -691555795
    //   5375: l2i
    //   5376: ldc_w 89472930
    //   5379: ixor
    //   5380: ldc2_w 2050506098
    //   5383: l2i
    //   5384: ldc_w 267277542
    //   5387: ixor
    //   5388: ixor
    //   5389: lookupswitch default -> 5416, -464344137 -> 5372, 1592938330 -> 5762
    //   5416: aload_2
    //   5417: getstatic Perryc.1 : I
    //   5420: ifeq -> 5434
    //   5423: ldc2_w 541298195
    //   5426: l2i
    //   5427: ldc_w -1644796616
    //   5430: ixor
    //   5431: goto -> 5442
    //   5434: ldc2_w 64837065
    //   5437: l2i
    //   5438: ldc_w 1244842664
    //   5441: ixor
    //   5442: ldc2_w -1079435556
    //   5445: l2i
    //   5446: ldc_w -1021619289
    //   5449: ixor
    //   5450: ixor
    //   5451: lookupswitch default -> 5790, -1056463280 -> 5434, 895341082 -> 5476
    //   5476: goto -> 5480
    //   5479: athrow
    //   5480: invokevirtual toUpperCase : ()Ljava/lang/String;
    //   5483: goto -> 5487
    //   5486: athrow
    //   5487: getstatic Perryc.0 : I
    //   5490: ifle -> 5504
    //   5493: ldc2_w 315176867
    //   5496: l2i
    //   5497: ldc_w -578726495
    //   5500: ixor
    //   5501: goto -> 5512
    //   5504: ldc2_w -1797578166
    //   5507: l2i
    //   5508: ldc_w -761040074
    //   5511: ixor
    //   5512: ldc2_w -1447911110
    //   5515: l2i
    //   5516: ldc_w -10303493
    //   5519: ixor
    //   5520: ixor
    //   5521: lookupswitch default -> 5548, -1718090557 -> 5764, 872789300 -> 5504
    //   5548: goto -> 5552
    //   5551: athrow
    //   5552: invokevirtual append : (Ljava/lang/String;)Ljava/lang/StringBuilder;
    //   5555: goto -> 5559
    //   5558: athrow
    //   5559: getstatic Perryc.0 : I
    //   5562: ifle -> 5576
    //   5565: ldc2_w -1843348075
    //   5568: l2i
    //   5569: ldc_w -916063039
    //   5572: ixor
    //   5573: goto -> 5584
    //   5576: ldc2_w -1368603817
    //   5579: l2i
    //   5580: ldc_w -1507550678
    //   5583: ixor
    //   5584: ldc2_w 1235433157
    //   5587: l2i
    //   5588: ldc_w 1150326402
    //   5591: ixor
    //   5592: ixor
    //   5593: lookupswitch default -> 5620, 1380307942 -> 5576, 1450631443 -> 5792
    //   5620: goto -> 5624
    //   5623: athrow
    //   5624: invokevirtual toString : ()Ljava/lang/String;
    //   5627: goto -> 5631
    //   5630: athrow
    //   5631: getstatic Perryc.0 : I
    //   5634: ifle -> 5648
    //   5637: ldc2_w -1252658543
    //   5640: l2i
    //   5641: ldc_w 1577560204
    //   5644: ixor
    //   5645: goto -> 5656
    //   5648: ldc2_w 2001440765
    //   5651: l2i
    //   5652: ldc_w -552980632
    //   5655: ixor
    //   5656: ldc2_w 997011663
    //   5659: l2i
    //   5660: ldc_w 1183598430
    //   5663: ixor
    //   5664: ixor
    //   5665: lookupswitch default -> 5692, -1766642292 -> 5798, 578719327 -> 5648
    //   5692: goto -> 5696
    //   5695: athrow
    //   5696: invokestatic sendMessage : (Ljava/lang/String;)V
    //   5699: goto -> 5703
    //   5702: athrow
    //   5703: return
    //   5704: aconst_null
    //   5705: athrow
    //   5706: aconst_null
    //   5707: athrow
    //   5708: aconst_null
    //   5709: athrow
    //   5710: aconst_null
    //   5711: athrow
    //   5712: aconst_null
    //   5713: athrow
    //   5714: aconst_null
    //   5715: athrow
    //   5716: aconst_null
    //   5717: athrow
    //   5718: aconst_null
    //   5719: athrow
    //   5720: aconst_null
    //   5721: athrow
    //   5722: aconst_null
    //   5723: athrow
    //   5724: aconst_null
    //   5725: athrow
    //   5726: aconst_null
    //   5727: athrow
    //   5728: aconst_null
    //   5729: athrow
    //   5730: aconst_null
    //   5731: athrow
    //   5732: aconst_null
    //   5733: athrow
    //   5734: aconst_null
    //   5735: athrow
    //   5736: aconst_null
    //   5737: athrow
    //   5738: aconst_null
    //   5739: athrow
    //   5740: aconst_null
    //   5741: athrow
    //   5742: aconst_null
    //   5743: athrow
    //   5744: aconst_null
    //   5745: athrow
    //   5746: aconst_null
    //   5747: athrow
    //   5748: aconst_null
    //   5749: athrow
    //   5750: aconst_null
    //   5751: athrow
    //   5752: aconst_null
    //   5753: athrow
    //   5754: aconst_null
    //   5755: athrow
    //   5756: aconst_null
    //   5757: athrow
    //   5758: aconst_null
    //   5759: athrow
    //   5760: aconst_null
    //   5761: athrow
    //   5762: aconst_null
    //   5763: athrow
    //   5764: aconst_null
    //   5765: athrow
    //   5766: aconst_null
    //   5767: athrow
    //   5768: aconst_null
    //   5769: athrow
    //   5770: aconst_null
    //   5771: athrow
    //   5772: aconst_null
    //   5773: athrow
    //   5774: aconst_null
    //   5775: athrow
    //   5776: aconst_null
    //   5777: athrow
    //   5778: aconst_null
    //   5779: athrow
    //   5780: aconst_null
    //   5781: athrow
    //   5782: aconst_null
    //   5783: athrow
    //   5784: aconst_null
    //   5785: athrow
    //   5786: aconst_null
    //   5787: athrow
    //   5788: aconst_null
    //   5789: athrow
    //   5790: aconst_null
    //   5791: athrow
    //   5792: aconst_null
    //   5793: athrow
    //   5794: aconst_null
    //   5795: athrow
    //   5796: aconst_null
    //   5797: athrow
    //   5798: aconst_null
    //   5799: athrow
    //   5800: aconst_null
    //   5801: athrow
    //   5802: aconst_null
    //   5803: athrow
    //   5804: aconst_null
    //   5805: athrow
    //   5806: aconst_null
    //   5807: athrow
    //   5808: aconst_null
    //   5809: athrow
    //   5810: aconst_null
    //   5811: athrow
    //   5812: aconst_null
    //   5813: athrow
    //   5814: aconst_null
    //   5815: athrow
    //   5816: aconst_null
    //   5817: athrow
    //   5818: aconst_null
    //   5819: athrow
    //   5820: aconst_null
    //   5821: athrow
    //   5822: aconst_null
    //   5823: athrow
    //   5824: aconst_null
    //   5825: athrow
    //   5826: aconst_null
    //   5827: athrow
    //   5828: aconst_null
    //   5829: athrow
    //   5830: aconst_null
    //   5831: athrow
    //   5832: aconst_null
    //   5833: athrow
    //   5834: aconst_null
    //   5835: athrow
    //   5836: aconst_null
    //   5837: athrow
    //   5838: aconst_null
    //   5839: athrow
    //   5840: aconst_null
    //   5841: athrow
    //   5842: aconst_null
    //   5843: athrow
    //   5844: aconst_null
    //   5845: athrow
    //   5846: aconst_null
    //   5847: athrow
    //   5848: aconst_null
    //   5849: athrow
    //   5850: aconst_null
    //   5851: athrow
    //   5852: aconst_null
    //   5853: athrow
    //   5854: aconst_null
    //   5855: athrow
    //   5856: aconst_null
    //   5857: athrow
    //   5858: aconst_null
    //   5859: athrow
    //   5860: pop
    //   5861: goto -> 24
    //   5864: pop
    //   5865: aconst_null
    //   5866: goto -> 5860
    //   5869: dup
    //   5870: ifnull -> 5860
    //   5873: checkcast java/lang/Throwable
    //   5876: athrow
    //   5877: dup
    //   5878: ifnull -> 5864
    //   5881: checkcast java/lang/Throwable
    //   5884: athrow
    //   5885: aconst_null
    //   5886: athrow
    // Local variable table:
    //   start	length	slot	name	descriptor
    //   24	5680	0	this	Lbigname/zprestige/webhack/features/command/commands/BindCommand;
    //   24	5680	1	commands	[Ljava/lang/String;
    //   405	5299	2	rkey	Ljava/lang/String;
    //   533	5171	3	moduleName	Ljava/lang/String;
    //   786	4918	4	module	Lbigname/zprestige/webhack/features/modules/Module;
    //   2930	2774	5	key	I
    // Exception table:
    //   from	to	target	type
    //   8	20	5869	java/lang/IllegalArgumentException
    //   203	210	210	finally
    //   203	210	203	java/lang/StringIndexOutOfBoundsException
    //   203	210	203	java/lang/AssertionError
    //   203	210	210	finally
    //   204	210	203	finally
    //   271	278	278	finally
    //   271	278	3	finally
    //   271	278	3	finally
    //   272	278	271	java/lang/RuntimeException
    //   272	278	278	finally
    //   715	722	722	finally
    //   715	722	715	java/lang/IllegalStateException
    //   715	722	3	finally
    //   715	722	3	finally
    //   715	722	722	java/lang/NumberFormatException
    //   971	978	978	finally
    //   971	978	971	finally
    //   971	978	3	java/lang/ArrayIndexOutOfBoundsException
    //   971	978	978	java/lang/UnsupportedOperationException
    //   972	978	978	finally
    //   1048	1054	1054	finally
    //   1048	1054	3	finally
    //   1048	1054	1054	finally
    //   1048	1054	1054	java/lang/UnsupportedOperationException
    //   1048	1054	1054	finally
    //   1119	1126	1126	finally
    //   1119	1126	1119	finally
    //   1119	1126	1126	finally
    //   1119	1126	1119	finally
    //   1120	1126	3	java/lang/IllegalArgumentException
    //   1255	1262	1262	finally
    //   1255	1262	1262	java/lang/ArithmeticException
    //   1256	1262	1255	finally
    //   1256	1262	3	finally
    //   1256	1262	1262	java/util/NoSuchElementException
    //   1331	1338	1338	finally
    //   1331	1338	1331	finally
    //   1331	1338	1331	java/lang/IndexOutOfBoundsException
    //   1332	1338	1331	java/lang/IndexOutOfBoundsException
    //   1332	1338	3	java/lang/UnsupportedOperationException
    //   1403	1410	1410	finally
    //   1403	1410	1410	java/lang/IllegalStateException
    //   1403	1410	1403	finally
    //   1403	1410	1410	finally
    //   1404	1410	3	finally
    //   1475	1482	1482	finally
    //   1476	1482	1475	java/lang/ClassCastException
    //   1476	1482	1482	java/lang/NegativeArraySizeException
    //   1476	1482	1482	java/lang/StringIndexOutOfBoundsException
    //   1476	1482	3	finally
    //   1547	1554	1554	finally
    //   1547	1554	1554	finally
    //   1547	1554	1554	finally
    //   1548	1554	1547	finally
    //   1548	1554	1554	java/util/ConcurrentModificationException
    //   1740	1746	1746	finally
    //   1740	1746	1746	finally
    //   1740	1746	1746	finally
    //   1740	1746	1746	java/lang/NumberFormatException
    //   1740	1746	1746	finally
    //   1875	1882	1882	finally
    //   1875	1882	3	finally
    //   1875	1882	1875	finally
    //   1875	1882	1875	finally
    //   1876	1882	1875	java/lang/IllegalStateException
    //   1947	1954	1954	finally
    //   1948	1954	1954	finally
    //   1948	1954	1947	java/lang/UnsupportedOperationException
    //   1948	1954	3	finally
    //   1948	1954	1954	finally
    //   2023	2030	2030	finally
    //   2023	2030	2030	finally
    //   2023	2030	2023	java/lang/IllegalStateException
    //   2023	2030	2030	java/lang/IndexOutOfBoundsException
    //   2024	2030	3	finally
    //   2095	2102	2102	finally
    //   2096	2102	2102	java/lang/NullPointerException
    //   2096	2102	2095	java/lang/IllegalStateException
    //   2096	2102	3	finally
    //   2096	2102	2095	java/lang/NullPointerException
    //   2231	2238	2238	finally
    //   2232	2238	3	finally
    //   2232	2238	2238	java/lang/StringIndexOutOfBoundsException
    //   2232	2238	2231	finally
    //   2232	2238	2231	java/lang/UnsupportedOperationException
    //   2368	2374	2374	finally
    //   2368	2374	2374	finally
    //   2368	2374	2374	finally
    //   2368	2374	3	finally
    //   2368	2374	3	java/lang/AssertionError
    //   2439	2446	2446	finally
    //   2440	2446	2439	finally
    //   2440	2446	2439	java/lang/IllegalArgumentException
    //   2440	2446	2446	finally
    //   2440	2446	2446	java/lang/IndexOutOfBoundsException
    //   2512	2518	2518	finally
    //   2512	2518	3	java/lang/ArrayIndexOutOfBoundsException
    //   2512	2518	3	finally
    //   2512	2518	3	finally
    //   2512	2518	3	finally
    //   2583	2590	2590	finally
    //   2583	2590	3	java/lang/ClassCastException
    //   2584	2590	3	java/lang/IllegalStateException
    //   2584	2590	2590	java/lang/StringIndexOutOfBoundsException
    //   2584	2590	2583	java/lang/NegativeArraySizeException
    //   2655	2662	2662	finally
    //   2655	2662	2662	java/lang/IllegalArgumentException
    //   2655	2662	3	finally
    //   2656	2662	2655	java/lang/NullPointerException
    //   2656	2662	2655	finally
    //   2787	2794	2794	finally
    //   2787	2794	2787	finally
    //   2787	2794	3	java/lang/IndexOutOfBoundsException
    //   2788	2794	2787	java/lang/IndexOutOfBoundsException
    //   2788	2794	2787	java/lang/IllegalStateException
    //   2860	2866	2866	finally
    //   2860	2866	2866	finally
    //   2860	2866	3	finally
    //   2860	2866	2866	finally
    //   2860	2866	3	finally
    //   3059	3066	3066	finally
    //   3059	3066	3	finally
    //   3059	3066	3059	finally
    //   3060	3066	3059	finally
    //   3060	3066	3059	java/lang/ArithmeticException
    //   3131	3138	3138	finally
    //   3131	3138	3	java/lang/IllegalStateException
    //   3131	3138	3131	java/lang/RuntimeException
    //   3131	3138	3	finally
    //   3132	3138	3	finally
    //   3447	3454	3454	finally
    //   3447	3454	3454	finally
    //   3447	3454	3	java/lang/UnsupportedOperationException
    //   3448	3454	3447	java/lang/ClassCastException
    //   3448	3454	3454	java/lang/IndexOutOfBoundsException
    //   3524	3530	3530	finally
    //   3524	3530	3530	finally
    //   3524	3530	3	finally
    //   3524	3530	3530	finally
    //   3524	3530	3	finally
    //   3595	3602	3602	finally
    //   3595	3602	3	finally
    //   3595	3602	3595	finally
    //   3595	3602	3	finally
    //   3595	3602	3595	finally
    //   3728	3734	3734	finally
    //   3728	3734	3734	java/lang/NumberFormatException
    //   3728	3734	3	java/util/ConcurrentModificationException
    //   3728	3734	3	finally
    //   3728	3734	3	finally
    //   3803	3810	3810	finally
    //   3803	3810	3	java/lang/EnumConstantNotPresentException
    //   3803	3810	3803	finally
    //   3803	3810	3	finally
    //   3804	3810	3810	java/lang/UnsupportedOperationException
    //   3875	3882	3882	finally
    //   3875	3882	3875	java/lang/IndexOutOfBoundsException
    //   3875	3882	3882	java/lang/ArrayIndexOutOfBoundsException
    //   3876	3882	3882	java/lang/RuntimeException
    //   3876	3882	3882	finally
    //   3947	3954	3954	finally
    //   3947	3954	3954	java/lang/IllegalArgumentException
    //   3947	3954	3947	java/lang/IndexOutOfBoundsException
    //   3948	3954	3947	java/lang/EnumConstantNotPresentException
    //   3948	3954	3954	java/util/ConcurrentModificationException
    //   4019	4026	4026	finally
    //   4019	4026	4019	java/util/NoSuchElementException
    //   4019	4026	3	finally
    //   4019	4026	3	finally
    //   4020	4026	3	java/lang/UnsupportedOperationException
    //   4288	4294	4294	finally
    //   4288	4294	3	java/util/ConcurrentModificationException
    //   4288	4294	3	java/lang/AssertionError
    //   4288	4294	3	java/lang/NegativeArraySizeException
    //   4288	4294	3	java/lang/ArithmeticException
    //   4359	4366	4366	finally
    //   4359	4366	4359	finally
    //   4359	4366	4359	finally
    //   4360	4366	4366	finally
    //   4360	4366	4366	java/lang/ClassCastException
    //   4435	4442	4442	finally
    //   4435	4442	4435	finally
    //   4435	4442	3	finally
    //   4436	4442	3	java/lang/NullPointerException
    //   4436	4442	3	finally
    //   4511	4518	4518	finally
    //   4511	4518	3	finally
    //   4511	4518	3	finally
    //   4512	4518	4511	finally
    //   4512	4518	4511	java/lang/StringIndexOutOfBoundsException
    //   4583	4590	4590	finally
    //   4583	4590	4583	java/lang/ArithmeticException
    //   4584	4590	4590	finally
    //   4584	4590	4583	java/lang/AssertionError
    //   4584	4590	4590	java/lang/IllegalArgumentException
    //   4720	4726	4726	finally
    //   4720	4726	3	finally
    //   4720	4726	3	finally
    //   4720	4726	3	java/lang/NullPointerException
    //   4720	4726	3	java/lang/NumberFormatException
    //   4855	4862	4862	finally
    //   4855	4862	4855	java/lang/IllegalStateException
    //   4856	4862	4862	finally
    //   4856	4862	4855	finally
    //   4856	4862	3	finally
    //   4927	4934	4934	finally
    //   4927	4934	4927	finally
    //   4927	4934	4934	finally
    //   4928	4934	4927	finally
    //   4928	4934	4934	finally
    //   5063	5070	5070	finally
    //   5063	5070	5063	finally
    //   5064	5070	5063	java/lang/NegativeArraySizeException
    //   5064	5070	5063	finally
    //   5064	5070	5070	java/lang/NumberFormatException
    //   5139	5146	5146	finally
    //   5139	5146	3	finally
    //   5139	5146	5146	java/lang/AssertionError
    //   5140	5146	5139	finally
    //   5140	5146	3	java/lang/ArrayIndexOutOfBoundsException
    //   5211	5218	5218	finally
    //   5211	5218	5211	finally
    //   5212	5218	5211	finally
    //   5212	5218	5218	java/util/NoSuchElementException
    //   5212	5218	3	finally
    //   5348	5354	5354	finally
    //   5348	5354	3	java/lang/StringIndexOutOfBoundsException
    //   5348	5354	3	java/lang/AssertionError
    //   5348	5354	5354	java/lang/IllegalArgumentException
    //   5348	5354	5354	java/lang/RuntimeException
    //   5479	5486	5486	finally
    //   5479	5486	3	finally
    //   5479	5486	5486	java/lang/ArrayIndexOutOfBoundsException
    //   5480	5486	5479	java/lang/IndexOutOfBoundsException
    //   5480	5486	3	java/lang/RuntimeException
    //   5551	5558	5558	finally
    //   5551	5558	5551	finally
    //   5551	5558	5551	java/lang/IllegalArgumentException
    //   5552	5558	3	finally
    //   5552	5558	5551	finally
    //   5623	5630	5630	finally
    //   5623	5630	5623	finally
    //   5623	5630	3	finally
    //   5624	5630	3	java/lang/StringIndexOutOfBoundsException
    //   5624	5630	5630	java/lang/ArithmeticException
    //   5695	5702	5702	finally
    //   5695	5702	5702	finally
    //   5695	5702	3	finally
    //   5695	5702	5695	finally
    //   5696	5702	5702	finally
    //   5869	5877	5869	finally
    //   5885	5887	3	java/lang/IllegalStateException
  }
}


/* Location:              C:\Users\alex\Desktop\webhack\WebHack-0.8-obf_sussy_1.jar!\bigname\zprestige\webhack\features\command\commands\BindCommand.class
 * Java compiler version: 8 (52.0)
 * JD-Core Version:       1.1.3
 */