package bigname.zprestige.webhack.features.command.commands;

import Perryc;
import bigname.zprestige.webhack.features.command.Command;
import java.io.File;

public class ConfigCommand extends Command {
  public void execute(String[] commands) {
    if (Perryc.1 <= 0) {
      null;
    } else {
      if (null != null)
        throw (Throwable)null; 
      null;
    } 
    if (null != null)
      throw (Throwable)null; 
    null;
  }
  
  public ConfigCommand() {
    // Byte code:
    //   0: getstatic Perryc.c : I
    //   3: iflt -> 17
    //   6: ldc2_w -2017186727
    //   9: l2i
    //   10: ldc_w -1901328159
    //   13: ixor
    //   14: goto -> 25
    //   17: ldc2_w 2112145805
    //   20: l2i
    //   21: ldc_w -270616612
    //   24: ixor
    //   25: ldc2_w -332831929
    //   28: l2i
    //   29: ldc_w -1336025365
    //   32: ixor
    //   33: ixor
    //   34: lookupswitch default -> 286, -833698819 -> 60, 1427937556 -> 17
    //   60: aload_0
    //   61: ldc_w '㌜㶱喂ࢗ'
    //   64: getstatic Perryc.c : I
    //   67: iflt -> 81
    //   70: ldc2_w 1426428334
    //   73: l2i
    //   74: ldc_w -901414677
    //   77: ixor
    //   78: goto -> 89
    //   81: ldc2_w 2102833913
    //   84: l2i
    //   85: ldc_w 947932123
    //   88: ixor
    //   89: ldc2_w 621519876
    //   92: l2i
    //   93: ldc_w 85604065
    //   96: ixor
    //   97: ixor
    //   98: lookupswitch default -> 124, -1199955391 -> 81, -1085176928 -> 280
    //   124: invokestatic 0 : (Ljava/lang/String;)Ljava/lang/String;
    //   127: ldc2_w -1222517475
    //   130: l2i
    //   131: ldc_w -1222517476
    //   134: ixor
    //   135: anewarray java/lang/String
    //   138: dup
    //   139: ldc2_w -1883431716
    //   142: l2i
    //   143: ldc_w -1883431716
    //   146: ixor
    //   147: ldc_w '㌀㶡喎ࣟ๵鮎蹢ॱ庩'
    //   150: getstatic Perryc.1 : I
    //   153: ifeq -> 167
    //   156: ldc2_w 993266602
    //   159: l2i
    //   160: ldc_w 383626672
    //   163: ixor
    //   164: goto -> 175
    //   167: ldc2_w -1715643035
    //   170: l2i
    //   171: ldc_w 1128857369
    //   174: ixor
    //   175: ldc2_w -233605867
    //   178: l2i
    //   179: ldc_w -1722031066
    //   182: ixor
    //   183: ixor
    //   184: lookupswitch default -> 212, 560359671 -> 167, 1184970537 -> 284
    //   212: invokestatic 0 : (Ljava/lang/String;)Ljava/lang/String;
    //   215: aastore
    //   216: getstatic Perryc.1 : I
    //   219: ifeq -> 233
    //   222: ldc2_w -897146601
    //   225: l2i
    //   226: ldc_w 1865692994
    //   229: ixor
    //   230: goto -> 241
    //   233: ldc2_w 1497895679
    //   236: l2i
    //   237: ldc_w -1272138528
    //   240: ixor
    //   241: ldc2_w 1198850273
    //   244: l2i
    //   245: ldc_w 1688771361
    //   248: ixor
    //   249: ixor
    //   250: lookupswitch default -> 276, -2039542379 -> 282, -1360156941 -> 233
    //   276: invokespecial <init> : (Ljava/lang/String;[Ljava/lang/String;)V
    //   279: return
    //   280: aconst_null
    //   281: athrow
    //   282: aconst_null
    //   283: athrow
    //   284: aconst_null
    //   285: athrow
    //   286: aconst_null
    //   287: athrow
    // Local variable table:
    //   start	length	slot	name	descriptor
    //   0	280	0	this	Lbigname/zprestige/webhack/features/command/commands/ConfigCommand;
  }
  
  static {
    throw SYNTHETIC_LOCAL_VARIABLE_0;
  }
  
  public static boolean lambda$execute$0(File f) {
    // Byte code:
    //   0: goto -> 8
    //   3: dup
    //   4: ifnull -> 409
    //   7: athrow
    //   8: aconst_null
    //   9: getstatic Perryc.0 : I
    //   12: ifgt -> 401
    //   15: pop
    //   16: aconst_null
    //   17: goto -> 393
    //   20: nop
    //   21: nop
    //   22: nop
    //   23: athrow
    //   24: getstatic Perryc.c : I
    //   27: iflt -> 41
    //   30: ldc2_w 1204167299
    //   33: l2i
    //   34: ldc_w 1434913779
    //   37: ixor
    //   38: goto -> 49
    //   41: ldc2_w 12323330
    //   44: l2i
    //   45: ldc_w -1836052918
    //   48: ixor
    //   49: ldc2_w 899872560
    //   52: l2i
    //   53: ldc_w 1029511411
    //   56: ixor
    //   57: ixor
    //   58: lookupswitch default -> 84, -1192723820 -> 41, 448710323 -> 380
    //   84: aload_0
    //   85: getstatic Perryc.c : I
    //   88: iflt -> 102
    //   91: ldc2_w -805058308
    //   94: l2i
    //   95: ldc_w 1936667363
    //   98: ixor
    //   99: goto -> 110
    //   102: ldc2_w -1037007549
    //   105: l2i
    //   106: ldc_w 1236272612
    //   109: ixor
    //   110: ldc2_w 1572056621
    //   113: l2i
    //   114: ldc_w 962401855
    //   117: ixor
    //   118: ixor
    //   119: lookupswitch default -> 144, -947764723 -> 378, 339343056 -> 102
    //   144: goto -> 148
    //   147: athrow
    //   148: invokevirtual getName : ()Ljava/lang/String;
    //   151: goto -> 155
    //   154: athrow
    //   155: ldc_w '㌇巭'
    //   158: getstatic Perryc.1 : I
    //   161: ifeq -> 175
    //   164: ldc2_w 2053713943
    //   167: l2i
    //   168: ldc_w -1972894032
    //   171: ixor
    //   172: goto -> 183
    //   175: ldc2_w -1462029649
    //   178: l2i
    //   179: ldc_w -1349015633
    //   182: ixor
    //   183: ldc2_w 1762918023
    //   186: l2i
    //   187: ldc_w 1971013936
    //   190: ixor
    //   191: ixor
    //   192: lookupswitch default -> 220, -328630000 -> 376, 157867769 -> 175
    //   220: goto -> 224
    //   223: athrow
    //   224: invokestatic 0 : (Ljava/lang/String;)Ljava/lang/String;
    //   227: goto -> 231
    //   230: athrow
    //   231: getstatic Perryc.0 : I
    //   234: ifle -> 248
    //   237: ldc2_w 288834495
    //   240: l2i
    //   241: ldc_w 1115972699
    //   244: ixor
    //   245: goto -> 256
    //   248: ldc2_w 1117574011
    //   251: l2i
    //   252: ldc_w 2089543983
    //   255: ixor
    //   256: ldc2_w 369923634
    //   259: l2i
    //   260: ldc_w -734619253
    //   263: ixor
    //   264: ixor
    //   265: lookupswitch default -> 382, -1853282211 -> 248, -64145939 -> 292
    //   292: goto -> 296
    //   295: athrow
    //   296: invokevirtual equals : (Ljava/lang/Object;)Z
    //   299: goto -> 303
    //   302: athrow
    //   303: ifne -> 317
    //   306: ldc2_w 161336103
    //   309: l2i
    //   310: ldc_w -1732584154
    //   313: ixor
    //   314: goto -> 325
    //   317: ldc2_w -1557429343
    //   320: l2i
    //   321: ldc_w 839685543
    //   324: ixor
    //   325: ldc2_w 187930506
    //   328: l2i
    //   329: ldc_w -2090978352
    //   332: ixor
    //   333: ixor
    //   334: tableswitch default -> 306, 424325723 -> 356, 424325724 -> 367
    //   356: ldc2_w 1390094492
    //   359: l2i
    //   360: ldc_w 1390094493
    //   363: ixor
    //   364: goto -> 375
    //   367: ldc2_w -1458260145
    //   370: l2i
    //   371: ldc_w -1458260145
    //   374: ixor
    //   375: ireturn
    //   376: aconst_null
    //   377: athrow
    //   378: aconst_null
    //   379: athrow
    //   380: aconst_null
    //   381: athrow
    //   382: aconst_null
    //   383: athrow
    //   384: pop
    //   385: goto -> 24
    //   388: pop
    //   389: aconst_null
    //   390: goto -> 384
    //   393: dup
    //   394: ifnull -> 384
    //   397: checkcast java/lang/Throwable
    //   400: athrow
    //   401: dup
    //   402: ifnull -> 388
    //   405: checkcast java/lang/Throwable
    //   408: athrow
    //   409: aconst_null
    //   410: athrow
    // Local variable table:
    //   start	length	slot	name	descriptor
    //   24	352	0	f	Ljava/io/File;
    // Exception table:
    //   from	to	target	type
    //   8	20	393	finally
    //   147	154	154	finally
    //   147	154	3	finally
    //   147	154	154	java/lang/RuntimeException
    //   148	154	147	java/lang/NegativeArraySizeException
    //   148	154	154	java/util/NoSuchElementException
    //   223	230	230	finally
    //   223	230	223	finally
    //   223	230	230	finally
    //   224	230	3	java/lang/ClassCastException
    //   224	230	223	java/lang/ClassCastException
    //   295	302	302	finally
    //   295	302	3	java/lang/AssertionError
    //   295	302	3	finally
    //   296	302	295	finally
    //   296	302	295	finally
    //   393	401	393	finally
    //   409	411	3	java/lang/NullPointerException
  }
}


/* Location:              C:\Users\alex\Desktop\webhack\WebHack-0.8-obf_sussy_1.jar!\bigname\zprestige\webhack\features\command\commands\ConfigCommand.class
 * Java compiler version: 8 (52.0)
 * JD-Core Version:       1.1.3
 */