package bigname.zprestige.webhack.features.command.commands;

import Perryc;
import bigname.zprestige.webhack.features.command.Command;

public class FriendCommand extends Command {
  public FriendCommand() {
    // Byte code:
    //   0: getstatic Perryc.c : I
    //   3: iflt -> 16
    //   6: ldc2_w 778598307
    //   9: l2i
    //   10: ldc 1430142732
    //   12: ixor
    //   13: goto -> 23
    //   16: ldc2_w -1662027274
    //   19: l2i
    //   20: ldc 620635496
    //   22: ixor
    //   23: ldc2_w 1977301122
    //   26: l2i
    //   27: ldc -1682178836
    //   29: ixor
    //   30: ixor
    //   31: lookupswitch default -> 56, -1791587135 -> 334, 1289538064 -> 16
    //   56: aload_0
    //   57: ldc '꽖㌁꼫㶲᳙䇨'
    //   59: getstatic Perryc.0 : I
    //   62: ifle -> 75
    //   65: ldc2_w -2083971544
    //   68: l2i
    //   69: ldc 1988697614
    //   71: ixor
    //   72: goto -> 82
    //   75: ldc2_w -1833407446
    //   78: l2i
    //   79: ldc -786124778
    //   81: ixor
    //   82: ldc2_w 725886427
    //   85: l2i
    //   86: ldc 1881637866
    //   88: ixor
    //   89: ixor
    //   90: lookupswitch default -> 116, -1601677404 -> 75, -1373395433 -> 332
    //   116: invokestatic 0 : (Ljava/lang/String;)Ljava/lang/String;
    //   119: ldc2_w 2053491052
    //   122: l2i
    //   123: ldc 2053491054
    //   125: ixor
    //   126: anewarray java/lang/String
    //   129: dup
    //   130: ldc2_w -496370192
    //   133: l2i
    //   134: ldc -496370192
    //   136: ixor
    //   137: ldc '꼌㌒꼦㶳Ი䇨๼틩踬䀧ដਪ投焮쓜㈹辚睄ꝼơ'
    //   139: getstatic Perryc.c : I
    //   142: iflt -> 155
    //   145: ldc2_w -356737252
    //   148: l2i
    //   149: ldc -619995507
    //   151: ixor
    //   152: goto -> 162
    //   155: ldc2_w -1789942970
    //   158: l2i
    //   159: ldc -297612063
    //   161: ixor
    //   162: ldc2_w 1388522961
    //   165: l2i
    //   166: ldc 348864684
    //   168: ixor
    //   169: ixor
    //   170: lookupswitch default -> 196, -573787282 -> 155, 2009033964 -> 338
    //   196: invokestatic 0 : (Ljava/lang/String;)Ljava/lang/String;
    //   199: aastore
    //   200: dup
    //   201: ldc2_w 2095946689
    //   204: l2i
    //   205: ldc 2095946688
    //   207: ixor
    //   208: ldc '꼌㌝꼣㶺᳒䆲'
    //   210: getstatic Perryc.1 : I
    //   213: ifeq -> 226
    //   216: ldc2_w -1224454266
    //   219: l2i
    //   220: ldc 1030673069
    //   222: ixor
    //   223: goto -> 233
    //   226: ldc2_w -581950916
    //   229: l2i
    //   230: ldc -2094650780
    //   232: ixor
    //   233: ldc2_w -1742876660
    //   236: l2i
    //   237: ldc 862524590
    //   239: ixor
    //   240: ixor
    //   241: lookupswitch default -> 336, -184365830 -> 268, 555637129 -> 226
    //   268: invokestatic 0 : (Ljava/lang/String;)Ljava/lang/String;
    //   271: aastore
    //   272: getstatic Perryc.0 : I
    //   275: ifle -> 288
    //   278: ldc2_w -1777603424
    //   281: l2i
    //   282: ldc 557858532
    //   284: ixor
    //   285: goto -> 295
    //   288: ldc2_w -1143256898
    //   291: l2i
    //   292: ldc 564143920
    //   294: ixor
    //   295: ldc2_w 1883514100
    //   298: l2i
    //   299: ldc -1771215570
    //   301: ixor
    //   302: ixor
    //   303: lookupswitch default -> 328, -1944897005 -> 288, 1365414814 -> 340
    //   328: invokespecial <init> : (Ljava/lang/String;[Ljava/lang/String;)V
    //   331: return
    //   332: aconst_null
    //   333: athrow
    //   334: aconst_null
    //   335: athrow
    //   336: aconst_null
    //   337: athrow
    //   338: aconst_null
    //   339: athrow
    //   340: aconst_null
    //   341: athrow
    // Local variable table:
    //   start	length	slot	name	descriptor
    //   0	332	0	this	Lbigname/zprestige/webhack/features/command/commands/FriendCommand;
  }
  
  public void execute(String[] commands) {
    if (Perryc.1 <= 0) {
      null;
    } else {
      if (null != null)
        throw (Throwable)null; 
      null;
    } 
    if (null != null)
      throw (Throwable)null; 
    null;
  }
  
  static {
    throw SYNTHETIC_LOCAL_VARIABLE_0;
  }
}


/* Location:              C:\Users\alex\Desktop\webhack\WebHack-0.8-obf_sussy_1.jar!\bigname\zprestige\webhack\features\command\commands\FriendCommand.class
 * Java compiler version: 8 (52.0)
 * JD-Core Version:       1.1.3
 */