package bigname.zprestige.webhack.features.command.commands;

import Perryc;
import bigname.zprestige.webhack.features.command.Command;

public class HelpCommand extends Command {
  public HelpCommand() {
    // Byte code:
    //   0: getstatic Perryc.c : I
    //   3: iflt -> 16
    //   6: ldc2_w -291003306
    //   9: l2i
    //   10: ldc -1468856779
    //   12: ixor
    //   13: goto -> 23
    //   16: ldc2_w 1294405601
    //   19: l2i
    //   20: ldc 754894448
    //   22: ixor
    //   23: ldc2_w 1614037928
    //   26: l2i
    //   27: ldc -1581678540
    //   29: ixor
    //   30: ixor
    //   31: lookupswitch default -> 180, -2024185345 -> 16, -1605105139 -> 56
    //   56: aload_0
    //   57: ldc '喅㌖嗫㶧'
    //   59: getstatic Perryc.0 : I
    //   62: ifle -> 75
    //   65: ldc2_w -1180403644
    //   68: l2i
    //   69: ldc -1345542112
    //   71: ixor
    //   72: goto -> 82
    //   75: ldc2_w -2025821255
    //   78: l2i
    //   79: ldc 2070952186
    //   81: ixor
    //   82: ldc2_w -899183711
    //   85: l2i
    //   86: ldc 49925680
    //   88: ixor
    //   89: ixor
    //   90: lookupswitch default -> 116, -554265099 -> 184, 2096327577 -> 75
    //   116: invokestatic 0 : (Ljava/lang/String;)Ljava/lang/String;
    //   119: getstatic Perryc.1 : I
    //   122: ifeq -> 135
    //   125: ldc2_w 1846422887
    //   128: l2i
    //   129: ldc 1919022570
    //   131: ixor
    //   132: goto -> 142
    //   135: ldc2_w 633520030
    //   138: l2i
    //   139: ldc 523021814
    //   141: ixor
    //   142: ldc2_w 1077993754
    //   145: l2i
    //   146: ldc -1888581343
    //   148: ixor
    //   149: ixor
    //   150: lookupswitch default -> 182, -750669642 -> 135, -171935149 -> 176
    //   176: invokespecial <init> : (Ljava/lang/String;)V
    //   179: return
    //   180: aconst_null
    //   181: athrow
    //   182: aconst_null
    //   183: athrow
    //   184: aconst_null
    //   185: athrow
    // Local variable table:
    //   start	length	slot	name	descriptor
    //   0	180	0	this	Lbigname/zprestige/webhack/features/command/commands/HelpCommand;
  }
  
  public void execute(String[] commands) {
    if (Perryc.c < 0) {
      null;
    } else {
      if (null != null)
        throw (Throwable)null; 
      null;
    } 
    if (null != null)
      throw (Throwable)null; 
    null;
  }
  
  static {
    throw SYNTHETIC_LOCAL_VARIABLE_0;
  }
}


/* Location:              C:\Users\alex\Desktop\webhack\WebHack-0.8-obf_sussy_1.jar!\bigname\zprestige\webhack\features\command\commands\HelpCommand.class
 * Java compiler version: 8 (52.0)
 * JD-Core Version:       1.1.3
 */