package bigname.zprestige.webhack.features.command.commands;

import Perryc;
import bigname.zprestige.webhack.features.command.Command;

public class HistoryCommand extends Command {
  public void execute(String[] commands) {
    if (Perryc.0 <= 0) {
      null;
    } else {
      if (null != null)
        throw (Throwable)null; 
      null;
    } 
    if (null != null)
      throw (Throwable)null; 
    null;
  }
  
  static {
    throw SYNTHETIC_LOCAL_VARIABLE_0;
  }
  
  public HistoryCommand() {
    // Byte code:
    //   0: getstatic Perryc.c : I
    //   3: iflt -> 17
    //   6: ldc2_w -1458211093
    //   9: l2i
    //   10: ldc_w -1282176740
    //   13: ixor
    //   14: goto -> 25
    //   17: ldc2_w 2145374490
    //   20: l2i
    //   21: ldc_w -699378714
    //   24: ixor
    //   25: ldc2_w 98572729
    //   28: l2i
    //   29: ldc_w -573430460
    //   32: ixor
    //   33: ixor
    //   34: lookupswitch default -> 60, -1521116022 -> 17, -1028340982 -> 280
    //   60: aload_0
    //   61: ldc_w '龰㌚鿉㶣⬰焖๠'
    //   64: getstatic Perryc.1 : I
    //   67: ifeq -> 81
    //   70: ldc2_w -1562857432
    //   73: l2i
    //   74: ldc_w -406446897
    //   77: ixor
    //   78: goto -> 89
    //   81: ldc2_w -1755896486
    //   84: l2i
    //   85: ldc_w 1009878262
    //   88: ixor
    //   89: ldc2_w 751258821
    //   92: l2i
    //   93: ldc_w -542858321
    //   96: ixor
    //   97: ixor
    //   98: lookupswitch default -> 286, -1233304691 -> 81, 1476742854 -> 124
    //   124: invokestatic 0 : (Ljava/lang/String;)Ljava/lang/String;
    //   127: ldc2_w -13761463
    //   130: l2i
    //   131: ldc_w -13761464
    //   134: ixor
    //   135: anewarray java/lang/String
    //   138: dup
    //   139: ldc2_w -567436021
    //   142: l2i
    //   143: ldc_w -567436021
    //   146: ixor
    //   147: ldc_w '鿤㌃鿖㶶⬦焁๫'
    //   150: getstatic Perryc.1 : I
    //   153: ifeq -> 167
    //   156: ldc2_w 1666262883
    //   159: l2i
    //   160: ldc_w 685102850
    //   163: ixor
    //   164: goto -> 175
    //   167: ldc2_w -766446612
    //   170: l2i
    //   171: ldc_w -1655225099
    //   174: ixor
    //   175: ldc2_w 90079202
    //   178: l2i
    //   179: ldc_w -1333723751
    //   182: ixor
    //   183: ixor
    //   184: lookupswitch default -> 282, -86428318 -> 212, -27626982 -> 167
    //   212: invokestatic 0 : (Ljava/lang/String;)Ljava/lang/String;
    //   215: aastore
    //   216: getstatic Perryc.1 : I
    //   219: ifeq -> 233
    //   222: ldc2_w -357247095
    //   225: l2i
    //   226: ldc_w -440910322
    //   229: ixor
    //   230: goto -> 241
    //   233: ldc2_w 19423260
    //   236: l2i
    //   237: ldc_w 1993494461
    //   240: ixor
    //   241: ldc2_w -1600025810
    //   244: l2i
    //   245: ldc_w -103287026
    //   248: ixor
    //   249: ixor
    //   250: lookupswitch default -> 276, 3064602 -> 233, 1450874279 -> 284
    //   276: invokespecial <init> : (Ljava/lang/String;[Ljava/lang/String;)V
    //   279: return
    //   280: aconst_null
    //   281: athrow
    //   282: aconst_null
    //   283: athrow
    //   284: aconst_null
    //   285: athrow
    //   286: aconst_null
    //   287: athrow
    // Local variable table:
    //   start	length	slot	name	descriptor
    //   0	280	0	this	Lbigname/zprestige/webhack/features/command/commands/HistoryCommand;
  }
}


/* Location:              C:\Users\alex\Desktop\webhack\WebHack-0.8-obf_sussy_1.jar!\bigname\zprestige\webhack\features\command\commands\HistoryCommand.class
 * Java compiler version: 8 (52.0)
 * JD-Core Version:       1.1.3
 */