package bigname.zprestige.webhack.features.command.commands;

import bigname.zprestige.webhack.features.command.Command;

public class ModuleCommand extends Command {
  static {
    throw SYNTHETIC_LOCAL_VARIABLE_0;
  }
  
  public ModuleCommand() {
    // Byte code:
    //   0: getstatic Perryc.1 : I
    //   3: ifeq -> 16
    //   6: ldc2_w -205237934
    //   9: l2i
    //   10: ldc -1465196336
    //   12: ixor
    //   13: goto -> 23
    //   16: ldc2_w 277846548
    //   19: l2i
    //   20: ldc 195265540
    //   22: ixor
    //   23: ldc2_w -17933316
    //   26: l2i
    //   27: ldc -1288844714
    //   29: ixor
    //   30: ixor
    //   31: lookupswitch default -> 56, 380444712 -> 486, 1055071898 -> 16
    //   56: aload_0
    //   57: ldc '迋㌜辨㶢㬩慿'
    //   59: getstatic Perryc.1 : I
    //   62: ifeq -> 75
    //   65: ldc2_w 129302222
    //   68: l2i
    //   69: ldc -2017765598
    //   71: ixor
    //   72: goto -> 82
    //   75: ldc2_w -281453724
    //   78: l2i
    //   79: ldc 452885706
    //   81: ixor
    //   82: ldc2_w 1305511367
    //   85: l2i
    //   86: ldc 1631171768
    //   88: ixor
    //   89: ixor
    //   90: lookupswitch default -> 116, -1394173805 -> 478, 272163970 -> 75
    //   116: invokestatic 0 : (Ljava/lang/String;)Ljava/lang/String;
    //   119: ldc2_w -81496784
    //   122: l2i
    //   123: ldc -81496780
    //   125: ixor
    //   126: anewarray java/lang/String
    //   129: dup
    //   130: ldc2_w -1224450702
    //   133: l2i
    //   134: ldc -1224450702
    //   136: ixor
    //   137: ldc '辚㌞辣㶳㬰慶๼'
    //   139: getstatic Perryc.1 : I
    //   142: ifeq -> 155
    //   145: ldc2_w -1408084663
    //   148: l2i
    //   149: ldc -2011097713
    //   151: ixor
    //   152: goto -> 162
    //   155: ldc2_w -1212566833
    //   158: l2i
    //   159: ldc -22075814
    //   161: ixor
    //   162: ldc2_w -708456783
    //   165: l2i
    //   166: ldc -1135078420
    //   168: ixor
    //   169: ixor
    //   170: lookupswitch default -> 196, 1041375778 -> 155, 1303289243 -> 480
    //   196: invokestatic 0 : (Ljava/lang/String;)Ljava/lang/String;
    //   199: aastore
    //   200: dup
    //   201: ldc2_w 81994231
    //   204: l2i
    //   205: ldc 81994230
    //   207: ixor
    //   208: ldc '辚㌀辩㶣㭪慨๼蹦柏㝃'
    //   210: getstatic Perryc.0 : I
    //   213: ifle -> 226
    //   216: ldc2_w 28440758
    //   219: l2i
    //   220: ldc -1851012856
    //   222: ixor
    //   223: goto -> 233
    //   226: ldc2_w -1152134150
    //   229: l2i
    //   230: ldc 702894864
    //   232: ixor
    //   233: ldc2_w 51730779
    //   236: l2i
    //   237: ldc -1889541582
    //   239: ixor
    //   240: ixor
    //   241: lookupswitch default -> 488, 475040471 -> 226, 519846787 -> 268
    //   268: invokestatic 0 : (Ljava/lang/String;)Ljava/lang/String;
    //   271: aastore
    //   272: dup
    //   273: ldc2_w -1404534492
    //   276: l2i
    //   277: ldc -1404534490
    //   279: ixor
    //   280: ldc '辚㌀辩㶣㬱慳๷踽'
    //   282: getstatic Perryc.0 : I
    //   285: ifle -> 298
    //   288: ldc2_w -823787980
    //   291: l2i
    //   292: ldc 2079389638
    //   294: ixor
    //   295: goto -> 305
    //   298: ldc2_w -401810749
    //   301: l2i
    //   302: ldc 85872149
    //   304: ixor
    //   305: ldc2_w -1279493048
    //   308: l2i
    //   309: ldc 1089841362
    //   311: ixor
    //   312: ixor
    //   313: lookupswitch default -> 340, 777074712 -> 298, 1180491112 -> 482
    //   340: invokestatic 0 : (Ljava/lang/String;)Ljava/lang/String;
    //   343: aastore
    //   344: dup
    //   345: ldc2_w -923463878
    //   348: l2i
    //   349: ldc -923463879
    //   351: ixor
    //   352: ldc '辚㌅辭㶻㬰慿ว'
    //   354: getstatic Perryc.c : I
    //   357: iflt -> 370
    //   360: ldc2_w 693417790
    //   363: l2i
    //   364: ldc 1742824290
    //   366: ixor
    //   367: goto -> 377
    //   370: ldc2_w -876965087
    //   373: l2i
    //   374: ldc -1632715857
    //   376: ixor
    //   377: ldc2_w 383571670
    //   380: l2i
    //   381: ldc -72212015
    //   383: ixor
    //   384: ixor
    //   385: lookupswitch default -> 412, -1545919653 -> 476, 982618729 -> 370
    //   412: invokestatic 0 : (Ljava/lang/String;)Ljava/lang/String;
    //   415: aastore
    //   416: getstatic Perryc.c : I
    //   419: iflt -> 432
    //   422: ldc2_w 1151046660
    //   425: l2i
    //   426: ldc 2072045999
    //   428: ixor
    //   429: goto -> 439
    //   432: ldc2_w 834971522
    //   435: l2i
    //   436: ldc 780077513
    //   438: ixor
    //   439: ldc2_w 1757182927
    //   442: l2i
    //   443: ldc -1759184059
    //   445: ixor
    //   446: ixor
    //   447: lookupswitch default -> 472, -1065091807 -> 484, -860429933 -> 432
    //   472: invokespecial <init> : (Ljava/lang/String;[Ljava/lang/String;)V
    //   475: return
    //   476: aconst_null
    //   477: athrow
    //   478: aconst_null
    //   479: athrow
    //   480: aconst_null
    //   481: athrow
    //   482: aconst_null
    //   483: athrow
    //   484: aconst_null
    //   485: athrow
    //   486: aconst_null
    //   487: athrow
    //   488: aconst_null
    //   489: athrow
    // Local variable table:
    //   start	length	slot	name	descriptor
    //   0	476	0	this	Lbigname/zprestige/webhack/features/command/commands/ModuleCommand;
  }
  
  public void execute(String[] commands) {
    // Byte code:
    //   0: goto -> 8
    //   3: dup
    //   4: ifnull -> 16269
    //   7: athrow
    //   8: aconst_null
    //   9: getstatic Perryc.0 : I
    //   12: ifgt -> 16261
    //   15: pop
    //   16: aconst_null
    //   17: goto -> 16253
    //   20: nop
    //   21: nop
    //   22: nop
    //   23: athrow
    //   24: getstatic Perryc.c : I
    //   27: iflt -> 40
    //   30: ldc2_w -231296248
    //   33: l2i
    //   34: ldc -367437393
    //   36: ixor
    //   37: goto -> 47
    //   40: ldc2_w -831363359
    //   43: l2i
    //   44: ldc 544378328
    //   46: ixor
    //   47: ldc2_w -105562026
    //   50: l2i
    //   51: ldc -1733267169
    //   53: ixor
    //   54: ixor
    //   55: lookupswitch default -> 16154, -1895441808 -> 80, 2032851950 -> 40
    //   80: aload_1
    //   81: arraylength
    //   82: ldc2_w -376719226
    //   85: l2i
    //   86: ldc -376719225
    //   88: ixor
    //   89: if_icmpne -> 102
    //   92: ldc2_w 1800154271
    //   95: l2i
    //   96: ldc -303830587
    //   98: ixor
    //   99: goto -> 109
    //   102: ldc2_w -679043975
    //   105: l2i
    //   106: ldc 1361664292
    //   108: ixor
    //   109: ldc2_w -202016966
    //   112: l2i
    //   113: ldc 957181907
    //   115: ixor
    //   116: ixor
    //   117: tableswitch default -> 92, 1280826803 -> 140, 1280826804 -> 3595
    //   140: ldc '迫㌜辨좥خ慿๪笤'
    //   142: getstatic Perryc.0 : I
    //   145: ifle -> 158
    //   148: ldc2_w 380761323
    //   151: l2i
    //   152: ldc -915375892
    //   154: ixor
    //   155: goto -> 165
    //   158: ldc2_w 761916720
    //   161: l2i
    //   162: ldc -1505258676
    //   164: ixor
    //   165: ldc2_w 245857194
    //   168: l2i
    //   169: ldc -2135931585
    //   171: ixor
    //   172: ixor
    //   173: lookupswitch default -> 16106, 87638249 -> 200, 1373024914 -> 158
    //   200: goto -> 204
    //   203: athrow
    //   204: invokestatic 0 : (Ljava/lang/String;)Ljava/lang/String;
    //   207: goto -> 211
    //   210: athrow
    //   211: getstatic Perryc.1 : I
    //   214: ifeq -> 227
    //   217: ldc2_w -1182818774
    //   220: l2i
    //   221: ldc -277926918
    //   223: ixor
    //   224: goto -> 234
    //   227: ldc2_w -1394845183
    //   230: l2i
    //   231: ldc 573024248
    //   233: ixor
    //   234: ldc2_w 53757069
    //   237: l2i
    //   238: ldc -613426523
    //   240: ixor
    //   241: ixor
    //   242: lookupswitch default -> 268, -1907676168 -> 16236, -1184896079 -> 227
    //   268: goto -> 272
    //   271: athrow
    //   272: invokestatic sendMessage : (Ljava/lang/String;)V
    //   275: goto -> 279
    //   278: athrow
    //   279: getstatic Perryc.1 : I
    //   282: ifeq -> 295
    //   285: ldc2_w 1357273529
    //   288: l2i
    //   289: ldc -647902483
    //   291: ixor
    //   292: goto -> 302
    //   295: ldc2_w -979502239
    //   298: l2i
    //   299: ldc 1874308731
    //   301: ixor
    //   302: ldc2_w -1499041108
    //   305: l2i
    //   306: ldc -114823778
    //   308: ixor
    //   309: ixor
    //   310: lookupswitch default -> 16044, -704246682 -> 295, -173290968 -> 336
    //   336: getstatic bigname/zprestige/webhack/WebHack.moduleManager : Lbigname/zprestige/webhack/manager/ModuleManager;
    //   339: getstatic Perryc.0 : I
    //   342: ifle -> 355
    //   345: ldc2_w -1622725283
    //   348: l2i
    //   349: ldc 795807257
    //   351: ixor
    //   352: goto -> 362
    //   355: ldc2_w -1507989666
    //   358: l2i
    //   359: ldc -301542923
    //   361: ixor
    //   362: ldc2_w 993126298
    //   365: l2i
    //   366: ldc 1171685471
    //   368: ixor
    //   369: ixor
    //   370: lookupswitch default -> 16052, -825277311 -> 355, 922505582 -> 396
    //   396: goto -> 400
    //   399: athrow
    //   400: invokevirtual getCategories : ()Ljava/util/List;
    //   403: goto -> 407
    //   406: athrow
    //   407: getstatic Perryc.c : I
    //   410: iflt -> 423
    //   413: ldc2_w -1600074332
    //   416: l2i
    //   417: ldc -435987305
    //   419: ixor
    //   420: goto -> 430
    //   423: ldc2_w 374005928
    //   426: l2i
    //   427: ldc -672825038
    //   429: ixor
    //   430: ldc2_w -918148446
    //   433: l2i
    //   434: ldc 1058729748
    //   436: ixor
    //   437: ixor
    //   438: lookupswitch default -> 16074, -1325443963 -> 423, 938714156 -> 464
    //   464: goto -> 468
    //   467: athrow
    //   468: invokeinterface iterator : ()Ljava/util/Iterator;
    //   473: goto -> 477
    //   476: athrow
    //   477: getstatic Perryc.c : I
    //   480: iflt -> 493
    //   483: ldc2_w 163167278
    //   486: l2i
    //   487: ldc 1926657764
    //   489: ixor
    //   490: goto -> 501
    //   493: ldc2_w 1095216532
    //   496: l2i
    //   497: ldc_w -869671088
    //   500: ixor
    //   501: ldc2_w -842939731
    //   504: l2i
    //   505: ldc_w 2089317883
    //   508: ixor
    //   509: ixor
    //   510: lookupswitch default -> 536, -903447140 -> 16000, 1539542258 -> 493
    //   536: astore_3
    //   537: getstatic Perryc.1 : I
    //   540: ifeq -> 554
    //   543: ldc2_w 114297196
    //   546: l2i
    //   547: ldc_w -10146545
    //   550: ixor
    //   551: goto -> 562
    //   554: ldc2_w -1203456846
    //   557: l2i
    //   558: ldc_w 752199783
    //   561: ixor
    //   562: ldc2_w 116162173
    //   565: l2i
    //   566: ldc_w -274996388
    //   569: ixor
    //   570: ixor
    //   571: lookupswitch default -> 596, -444041271 -> 554, 281196866 -> 16238
    //   596: aload_3
    //   597: getstatic Perryc.c : I
    //   600: iflt -> 614
    //   603: ldc2_w -992113871
    //   606: l2i
    //   607: ldc_w 4918972
    //   610: ixor
    //   611: goto -> 622
    //   614: ldc2_w 904633147
    //   617: l2i
    //   618: ldc_w -31192102
    //   621: ixor
    //   622: ldc2_w -691456932
    //   625: l2i
    //   626: ldc_w -405995540
    //   629: ixor
    //   630: ixor
    //   631: lookupswitch default -> 15852, -174895555 -> 614, -87401647 -> 656
    //   656: goto -> 660
    //   659: athrow
    //   660: invokeinterface hasNext : ()Z
    //   665: goto -> 669
    //   668: athrow
    //   669: ifeq -> 683
    //   672: ldc2_w -179842491
    //   675: l2i
    //   676: ldc_w -1934241677
    //   679: ixor
    //   680: goto -> 691
    //   683: ldc2_w 1156614688
    //   686: l2i
    //   687: ldc_w 1023576087
    //   690: ixor
    //   691: ldc2_w -662480372
    //   694: l2i
    //   695: ldc_w -458560060
    //   698: ixor
    //   699: ixor
    //   700: tableswitch default -> 672, 1172026878 -> 724, 1172026879 -> 3594
    //   724: getstatic Perryc.c : I
    //   727: iflt -> 741
    //   730: ldc2_w -296679098
    //   733: l2i
    //   734: ldc_w -497421646
    //   737: ixor
    //   738: goto -> 749
    //   741: ldc2_w -349097765
    //   744: l2i
    //   745: ldc_w -1754508360
    //   748: ixor
    //   749: ldc2_w 1735800957
    //   752: l2i
    //   753: ldc_w 832311236
    //   756: ixor
    //   757: ixor
    //   758: lookupswitch default -> 16178, 716657882 -> 784, 1524812877 -> 741
    //   784: aload_3
    //   785: getstatic Perryc.1 : I
    //   788: ifeq -> 802
    //   791: ldc2_w 944420264
    //   794: l2i
    //   795: ldc_w 2119319299
    //   798: ixor
    //   799: goto -> 810
    //   802: ldc2_w 993421399
    //   805: l2i
    //   806: ldc_w 1578250490
    //   809: ixor
    //   810: ldc2_w -1046572252
    //   813: l2i
    //   814: ldc_w 72604125
    //   817: ixor
    //   818: ixor
    //   819: lookupswitch default -> 844, -2083143598 -> 15924, -621128829 -> 802
    //   844: goto -> 848
    //   847: athrow
    //   848: invokeinterface next : ()Ljava/lang/Object;
    //   853: goto -> 857
    //   856: athrow
    //   857: checkcast bigname/zprestige/webhack/features/modules/Module$Category
    //   860: getstatic Perryc.c : I
    //   863: iflt -> 877
    //   866: ldc2_w -176681980
    //   869: l2i
    //   870: ldc_w -174697757
    //   873: ixor
    //   874: goto -> 885
    //   877: ldc2_w 1913070457
    //   880: l2i
    //   881: ldc_w -786283455
    //   884: ixor
    //   885: ldc2_w -1482140959
    //   888: l2i
    //   889: ldc_w 461648302
    //   892: ixor
    //   893: ixor
    //   894: lookupswitch default -> 920, -1128120920 -> 16012, -155098988 -> 877
    //   920: astore #4
    //   922: new java/lang/StringBuilder
    //   925: dup
    //   926: getstatic Perryc.0 : I
    //   929: ifle -> 943
    //   932: ldc2_w -890091914
    //   935: l2i
    //   936: ldc_w 2078379374
    //   939: ixor
    //   940: goto -> 951
    //   943: ldc2_w -1522653587
    //   946: l2i
    //   947: ldc_w 978665197
    //   950: ixor
    //   951: ldc2_w 661104728
    //   954: l2i
    //   955: ldc_w 1929739488
    //   958: ixor
    //   959: ixor
    //   960: lookupswitch default -> 988, -601329078 -> 943, -445571168 -> 15882
    //   988: goto -> 992
    //   991: athrow
    //   992: invokespecial <init> : ()V
    //   995: goto -> 999
    //   998: athrow
    //   999: getstatic Perryc.1 : I
    //   1002: ifeq -> 1016
    //   1005: ldc2_w -1194726883
    //   1008: l2i
    //   1009: ldc_w -1256420839
    //   1012: ixor
    //   1013: goto -> 1024
    //   1016: ldc2_w 1044560757
    //   1019: l2i
    //   1020: ldc_w 1225205264
    //   1023: ixor
    //   1024: ldc2_w 1982984086
    //   1027: l2i
    //   1028: ldc_w 494340433
    //   1031: ixor
    //   1032: ixor
    //   1033: lookupswitch default -> 15854, 469990306 -> 1060, 1720944323 -> 1016
    //   1060: aload #4
    //   1062: getstatic Perryc.c : I
    //   1065: iflt -> 1079
    //   1068: ldc2_w 1113797034
    //   1071: l2i
    //   1072: ldc_w -878960640
    //   1075: ixor
    //   1076: goto -> 1087
    //   1079: ldc2_w -931628982
    //   1082: l2i
    //   1083: ldc_w -1352127489
    //   1086: ixor
    //   1087: ldc2_w 313855258
    //   1090: l2i
    //   1091: ldc_w 1922886268
    //   1094: ixor
    //   1095: ixor
    //   1096: lookupswitch default -> 1124, -371788084 -> 16050, 525836956 -> 1079
    //   1124: goto -> 1128
    //   1127: athrow
    //   1128: invokevirtual getName : ()Ljava/lang/String;
    //   1131: goto -> 1135
    //   1134: athrow
    //   1135: getstatic Perryc.c : I
    //   1138: iflt -> 1152
    //   1141: ldc2_w 1616146148
    //   1144: l2i
    //   1145: ldc_w 4605205
    //   1148: ixor
    //   1149: goto -> 1160
    //   1152: ldc2_w 282191949
    //   1155: l2i
    //   1156: ldc_w 1440912177
    //   1159: ixor
    //   1160: ldc2_w 394017367
    //   1163: l2i
    //   1164: ldc_w 1767826883
    //   1167: ixor
    //   1168: ixor
    //   1169: lookupswitch default -> 16006, 506524773 -> 1152, 991012072 -> 1196
    //   1196: goto -> 1200
    //   1199: athrow
    //   1200: invokevirtual append : (Ljava/lang/String;)Ljava/lang/StringBuilder;
    //   1203: goto -> 1207
    //   1206: athrow
    //   1207: ldc_w '辜㍓'
    //   1210: getstatic Perryc.c : I
    //   1213: iflt -> 1227
    //   1216: ldc2_w 91844832
    //   1219: l2i
    //   1220: ldc_w -1275530864
    //   1223: ixor
    //   1224: goto -> 1235
    //   1227: ldc2_w 1597523361
    //   1230: l2i
    //   1231: ldc_w 88946222
    //   1234: ixor
    //   1235: ldc2_w 2127237747
    //   1238: l2i
    //   1239: ldc_w 586185904
    //   1242: ixor
    //   1243: ixor
    //   1244: lookupswitch default -> 1272, -356847693 -> 16118, 1971593384 -> 1227
    //   1272: goto -> 1276
    //   1275: athrow
    //   1276: invokestatic 0 : (Ljava/lang/String;)Ljava/lang/String;
    //   1279: goto -> 1283
    //   1282: athrow
    //   1283: getstatic Perryc.c : I
    //   1286: iflt -> 1300
    //   1289: ldc2_w 264866949
    //   1292: l2i
    //   1293: ldc_w -897840018
    //   1296: ixor
    //   1297: goto -> 1308
    //   1300: ldc2_w -250851612
    //   1303: l2i
    //   1304: ldc_w 1486920026
    //   1307: ixor
    //   1308: ldc2_w -1944428896
    //   1311: l2i
    //   1312: ldc_w 1515493730
    //   1315: ixor
    //   1316: ixor
    //   1317: lookupswitch default -> 16042, 335234857 -> 1300, 2145521788 -> 1344
    //   1344: goto -> 1348
    //   1347: athrow
    //   1348: invokevirtual append : (Ljava/lang/String;)Ljava/lang/StringBuilder;
    //   1351: goto -> 1355
    //   1354: athrow
    //   1355: getstatic Perryc.0 : I
    //   1358: ifle -> 1372
    //   1361: ldc2_w -1987434321
    //   1364: l2i
    //   1365: ldc_w 544854674
    //   1368: ixor
    //   1369: goto -> 1380
    //   1372: ldc2_w -829561712
    //   1375: l2i
    //   1376: ldc_w -1563272750
    //   1379: ixor
    //   1380: ldc2_w -1410164691
    //   1383: l2i
    //   1384: ldc_w 1144996178
    //   1387: ixor
    //   1388: ixor
    //   1389: lookupswitch default -> 16036, -2087558083 -> 1416, 1178477378 -> 1372
    //   1416: goto -> 1420
    //   1419: athrow
    //   1420: invokevirtual toString : ()Ljava/lang/String;
    //   1423: goto -> 1427
    //   1426: athrow
    //   1427: getstatic Perryc.c : I
    //   1430: iflt -> 1444
    //   1433: ldc2_w -104888347
    //   1436: l2i
    //   1437: ldc_w 710250139
    //   1440: ixor
    //   1441: goto -> 1452
    //   1444: ldc2_w 10488304
    //   1447: l2i
    //   1448: ldc_w -1852087223
    //   1451: ixor
    //   1452: ldc2_w 1151812948
    //   1455: l2i
    //   1456: ldc_w 2146752412
    //   1459: ixor
    //   1460: ixor
    //   1461: lookupswitch default -> 16014, -1435959439 -> 1488, -390489162 -> 1444
    //   1488: astore #5
    //   1490: getstatic Perryc.1 : I
    //   1493: ifeq -> 1507
    //   1496: ldc2_w -56297552
    //   1499: l2i
    //   1500: ldc_w 733827917
    //   1503: ixor
    //   1504: goto -> 1515
    //   1507: ldc2_w 1334830903
    //   1510: l2i
    //   1511: ldc_w 1038991584
    //   1514: ixor
    //   1515: ldc2_w 1014303304
    //   1518: l2i
    //   1519: ldc_w -1843631543
    //   1522: ixor
    //   1523: ixor
    //   1524: lookupswitch default -> 1552, -674412427 -> 1507, 2037433596 -> 15976
    //   1552: getstatic bigname/zprestige/webhack/WebHack.moduleManager : Lbigname/zprestige/webhack/manager/ModuleManager;
    //   1555: getstatic Perryc.c : I
    //   1558: iflt -> 1572
    //   1561: ldc2_w 1927705563
    //   1564: l2i
    //   1565: ldc_w 1417190792
    //   1568: ixor
    //   1569: goto -> 1580
    //   1572: ldc2_w -1599890541
    //   1575: l2i
    //   1576: ldc_w 1907201573
    //   1579: ixor
    //   1580: ldc2_w -1368827225
    //   1583: l2i
    //   1584: ldc_w 1245615893
    //   1587: ixor
    //   1588: ixor
    //   1589: lookupswitch default -> 16184, -1027005471 -> 1572, 895074308 -> 1616
    //   1616: aload #4
    //   1618: getstatic Perryc.1 : I
    //   1621: ifeq -> 1635
    //   1624: ldc2_w 658402584
    //   1627: l2i
    //   1628: ldc_w -1928236658
    //   1631: ixor
    //   1632: goto -> 1643
    //   1635: ldc2_w 1010481960
    //   1638: l2i
    //   1639: ldc_w -1493377321
    //   1642: ixor
    //   1643: ldc2_w -140056359
    //   1646: l2i
    //   1647: ldc_w -23622293
    //   1650: ixor
    //   1651: ixor
    //   1652: lookupswitch default -> 15846, -1812529075 -> 1680, -1558283996 -> 1635
    //   1680: goto -> 1684
    //   1683: athrow
    //   1684: invokevirtual getModulesByCategory : (Lbigname/zprestige/webhack/features/modules/Module$Category;)Ljava/util/ArrayList;
    //   1687: goto -> 1691
    //   1690: athrow
    //   1691: getstatic Perryc.1 : I
    //   1694: ifeq -> 1708
    //   1697: ldc2_w -1987354732
    //   1700: l2i
    //   1701: ldc_w -343432582
    //   1704: ixor
    //   1705: goto -> 1716
    //   1708: ldc2_w -2025171304
    //   1711: l2i
    //   1712: ldc_w -1876445753
    //   1715: ixor
    //   1716: ldc2_w 1904764539
    //   1719: l2i
    //   1720: ldc_w 437132087
    //   1723: ixor
    //   1724: ixor
    //   1725: lookupswitch default -> 16056, 160071842 -> 1708, 2095816211 -> 1752
    //   1752: goto -> 1756
    //   1755: athrow
    //   1756: invokevirtual iterator : ()Ljava/util/Iterator;
    //   1759: goto -> 1763
    //   1762: athrow
    //   1763: getstatic Perryc.1 : I
    //   1766: ifeq -> 1780
    //   1769: ldc2_w 847002003
    //   1772: l2i
    //   1773: ldc_w -890119896
    //   1776: ixor
    //   1777: goto -> 1788
    //   1780: ldc2_w 682614100
    //   1783: l2i
    //   1784: ldc_w -1075110763
    //   1787: ixor
    //   1788: ldc2_w 1987635242
    //   1791: l2i
    //   1792: ldc_w 1384315295
    //   1795: ixor
    //   1796: ixor
    //   1797: lookupswitch default -> 1824, -596119282 -> 15990, 768214397 -> 1780
    //   1824: astore #6
    //   1826: getstatic Perryc.1 : I
    //   1829: ifeq -> 1843
    //   1832: ldc2_w 1726682435
    //   1835: l2i
    //   1836: ldc_w -1348736194
    //   1839: ixor
    //   1840: goto -> 1851
    //   1843: ldc2_w -513761481
    //   1846: l2i
    //   1847: ldc_w 974271601
    //   1850: ixor
    //   1851: ldc2_w 1369946069
    //   1854: l2i
    //   1855: ldc_w 1418511520
    //   1858: ixor
    //   1859: ixor
    //   1860: lookupswitch default -> 1888, -900190075 -> 1843, -866415352 -> 16208
    //   1888: aload #6
    //   1890: getstatic Perryc.c : I
    //   1893: iflt -> 1907
    //   1896: ldc2_w -1698094742
    //   1899: l2i
    //   1900: ldc_w -759977369
    //   1903: ixor
    //   1904: goto -> 1915
    //   1907: ldc2_w 1122923506
    //   1910: l2i
    //   1911: ldc_w 1227215162
    //   1914: ixor
    //   1915: ldc2_w 1128521490
    //   1918: l2i
    //   1919: ldc_w -765351950
    //   1922: ixor
    //   1923: ixor
    //   1924: lookupswitch default -> 1952, -1414132300 -> 1907, -648481811 -> 15860
    //   1952: goto -> 1956
    //   1955: athrow
    //   1956: invokeinterface hasNext : ()Z
    //   1961: goto -> 1965
    //   1964: athrow
    //   1965: ifeq -> 1979
    //   1968: ldc2_w -1552414722
    //   1971: l2i
    //   1972: ldc_w 690462353
    //   1975: ixor
    //   1976: goto -> 1987
    //   1979: ldc2_w -358667835
    //   1982: l2i
    //   1983: ldc_w 1623240885
    //   1986: ixor
    //   1987: ldc2_w 975330244
    //   1990: l2i
    //   1991: ldc_w -1569227676
    //   1994: ixor
    //   1995: ixor
    //   1996: tableswitch default -> 1968, 302694095 -> 2020, 302694096 -> 3457
    //   2020: getstatic Perryc.0 : I
    //   2023: ifle -> 2037
    //   2026: ldc2_w 291294241
    //   2029: l2i
    //   2030: ldc_w -462110614
    //   2033: ixor
    //   2034: goto -> 2045
    //   2037: ldc2_w -440615001
    //   2040: l2i
    //   2041: ldc_w -1615754596
    //   2044: ixor
    //   2045: ldc2_w 340383116
    //   2048: l2i
    //   2049: ldc_w 1490873646
    //   2052: ixor
    //   2053: ixor
    //   2054: lookupswitch default -> 2080, -1178782487 -> 16078, 827077296 -> 2037
    //   2080: aload #6
    //   2082: getstatic Perryc.0 : I
    //   2085: ifle -> 2099
    //   2088: ldc2_w -695918589
    //   2091: l2i
    //   2092: ldc_w 1716342711
    //   2095: ixor
    //   2096: goto -> 2107
    //   2099: ldc2_w -758747501
    //   2102: l2i
    //   2103: ldc_w 217015818
    //   2106: ixor
    //   2107: ldc2_w -391047262
    //   2110: l2i
    //   2111: ldc_w 834511578
    //   2114: ixor
    //   2115: ixor
    //   2116: lookupswitch default -> 2144, 771254167 -> 2099, 1774508748 -> 15840
    //   2144: goto -> 2148
    //   2147: athrow
    //   2148: invokeinterface next : ()Ljava/lang/Object;
    //   2153: goto -> 2157
    //   2156: athrow
    //   2157: checkcast bigname/zprestige/webhack/features/modules/Module
    //   2160: getstatic Perryc.1 : I
    //   2163: ifeq -> 2177
    //   2166: ldc2_w 1636941383
    //   2169: l2i
    //   2170: ldc_w 564930938
    //   2173: ixor
    //   2174: goto -> 2185
    //   2177: ldc2_w -1949402631
    //   2180: l2i
    //   2181: ldc_w 2117175887
    //   2184: ixor
    //   2185: ldc2_w 1169567428
    //   2188: l2i
    //   2189: ldc_w 487820087
    //   2192: ixor
    //   2193: ixor
    //   2194: lookupswitch default -> 2220, 412627662 -> 15904, 536224746 -> 2177
    //   2220: astore #7
    //   2222: new java/lang/StringBuilder
    //   2225: dup
    //   2226: getstatic Perryc.c : I
    //   2229: iflt -> 2243
    //   2232: ldc2_w 1681463387
    //   2235: l2i
    //   2236: ldc_w -584312361
    //   2239: ixor
    //   2240: goto -> 2251
    //   2243: ldc2_w 1055214521
    //   2246: l2i
    //   2247: ldc_w -331363181
    //   2250: ixor
    //   2251: ldc2_w 1684683458
    //   2254: l2i
    //   2255: ldc_w 1666428723
    //   2258: ixor
    //   2259: ixor
    //   2260: lookupswitch default -> 16092, -1104374659 -> 2243, -706538789 -> 2288
    //   2288: goto -> 2292
    //   2291: athrow
    //   2292: invokespecial <init> : ()V
    //   2295: goto -> 2299
    //   2298: athrow
    //   2299: getstatic Perryc.c : I
    //   2302: iflt -> 2316
    //   2305: ldc2_w -947320937
    //   2308: l2i
    //   2309: ldc_w -87111532
    //   2312: ixor
    //   2313: goto -> 2324
    //   2316: ldc2_w 20989924
    //   2319: l2i
    //   2320: ldc_w -1194421597
    //   2323: ixor
    //   2324: ldc2_w -1969080618
    //   2327: l2i
    //   2328: ldc_w -1602534144
    //   2331: ixor
    //   2332: ixor
    //   2333: lookupswitch default -> 15824, -1822972271 -> 2360, 396278997 -> 2316
    //   2360: aload #5
    //   2362: getstatic Perryc.c : I
    //   2365: iflt -> 2379
    //   2368: ldc2_w 2026918639
    //   2371: l2i
    //   2372: ldc_w -463788051
    //   2375: ixor
    //   2376: goto -> 2387
    //   2379: ldc2_w -125078385
    //   2382: l2i
    //   2383: ldc_w 2110638158
    //   2386: ixor
    //   2387: ldc2_w 805182123
    //   2390: l2i
    //   2391: ldc_w 1407876450
    //   2394: ixor
    //   2395: ixor
    //   2396: lookupswitch default -> 2424, -526445877 -> 16214, 1841383444 -> 2379
    //   2424: goto -> 2428
    //   2427: athrow
    //   2428: invokevirtual append : (Ljava/lang/String;)Ljava/lang/StringBuilder;
    //   2431: goto -> 2435
    //   2434: athrow
    //   2435: getstatic Perryc.0 : I
    //   2438: ifle -> 2452
    //   2441: ldc2_w -467009556
    //   2444: l2i
    //   2445: ldc_w -1920590855
    //   2448: ixor
    //   2449: goto -> 2460
    //   2452: ldc2_w 1276957109
    //   2455: l2i
    //   2456: ldc_w -1765931504
    //   2459: ixor
    //   2460: ldc2_w 634890337
    //   2463: l2i
    //   2464: ldc_w 1853718341
    //   2467: ixor
    //   2468: ixor
    //   2469: lookupswitch default -> 16190, -1861746559 -> 2496, 570766129 -> 2452
    //   2496: aload #7
    //   2498: getstatic Perryc.1 : I
    //   2501: ifeq -> 2515
    //   2504: ldc2_w -665081213
    //   2507: l2i
    //   2508: ldc_w -1325932573
    //   2511: ixor
    //   2512: goto -> 2523
    //   2515: ldc2_w -873414850
    //   2518: l2i
    //   2519: ldc_w 174677530
    //   2522: ixor
    //   2523: ldc2_w -539109589
    //   2526: l2i
    //   2527: ldc_w 416297275
    //   2530: ixor
    //   2531: ixor
    //   2532: lookupswitch default -> 2560, -1348365456 -> 16094, 1225338429 -> 2515
    //   2560: goto -> 2564
    //   2563: athrow
    //   2564: invokevirtual isEnabled : ()Z
    //   2567: goto -> 2571
    //   2570: athrow
    //   2571: ifeq -> 2585
    //   2574: ldc2_w 630058455
    //   2577: l2i
    //   2578: ldc_w 197606369
    //   2581: ixor
    //   2582: goto -> 2593
    //   2585: ldc2_w -1451539472
    //   2588: l2i
    //   2589: ldc_w -2026793529
    //   2592: ixor
    //   2593: ldc2_w 1629327038
    //   2596: l2i
    //   2597: ldc_w 2014008342
    //   2600: ixor
    //   2601: ixor
    //   2602: tableswitch default -> 2574, 928779422 -> 2624, 928779423 -> 2690
    //   2624: getstatic Perryc.0 : I
    //   2627: ifle -> 2641
    //   2630: ldc2_w -1480739381
    //   2633: l2i
    //   2634: ldc_w 211283088
    //   2637: ixor
    //   2638: goto -> 2649
    //   2641: ldc2_w -1851527081
    //   2644: l2i
    //   2645: ldc_w -924732926
    //   2648: ixor
    //   2649: ldc2_w -720559869
    //   2652: l2i
    //   2653: ldc_w 1914090238
    //   2656: ixor
    //   2657: ixor
    //   2658: lookupswitch default -> 2684, -84005252 -> 2641, 204589734 -> 16096
    //   2684: getstatic com/mojang/realmsclient/gui/ChatFormatting.GREEN : Lcom/mojang/realmsclient/gui/ChatFormatting;
    //   2687: goto -> 2755
    //   2690: getstatic Perryc.1 : I
    //   2693: ifeq -> 2707
    //   2696: ldc2_w 1818893421
    //   2699: l2i
    //   2700: ldc_w -437666611
    //   2703: ixor
    //   2704: goto -> 2715
    //   2707: ldc2_w 1492917406
    //   2710: l2i
    //   2711: ldc_w 182876169
    //   2714: ixor
    //   2715: ldc2_w -1840197167
    //   2718: l2i
    //   2719: ldc_w 1076598603
    //   2722: ixor
    //   2723: ixor
    //   2724: lookupswitch default -> 2752, 704821632 -> 2707, 1543038522 -> 15936
    //   2752: getstatic com/mojang/realmsclient/gui/ChatFormatting.RED : Lcom/mojang/realmsclient/gui/ChatFormatting;
    //   2755: getstatic Perryc.0 : I
    //   2758: ifle -> 2772
    //   2761: ldc2_w 1282920105
    //   2764: l2i
    //   2765: ldc_w -1057545984
    //   2768: ixor
    //   2769: goto -> 2780
    //   2772: ldc2_w -586566356
    //   2775: l2i
    //   2776: ldc_w 758118589
    //   2779: ixor
    //   2780: ldc2_w 682083384
    //   2783: l2i
    //   2784: ldc_w 1103219506
    //   2787: ixor
    //   2788: ixor
    //   2789: lookupswitch default -> 15908, -1723841893 -> 2816, -437854045 -> 2772
    //   2816: goto -> 2820
    //   2819: athrow
    //   2820: invokevirtual append : (Ljava/lang/Object;)Ljava/lang/StringBuilder;
    //   2823: goto -> 2827
    //   2826: athrow
    //   2827: getstatic Perryc.0 : I
    //   2830: ifle -> 2844
    //   2833: ldc2_w -2013816630
    //   2836: l2i
    //   2837: ldc_w 1933099707
    //   2840: ixor
    //   2841: goto -> 2852
    //   2844: ldc2_w -592611094
    //   2847: l2i
    //   2848: ldc_w -1602094711
    //   2851: ixor
    //   2852: ldc2_w 1728032516
    //   2855: l2i
    //   2856: ldc_w 1910221070
    //   2859: ixor
    //   2860: ixor
    //   2861: lookupswitch default -> 15930, -471114629 -> 2844, 1795721065 -> 2888
    //   2888: aload #7
    //   2890: getstatic Perryc.1 : I
    //   2893: ifeq -> 2907
    //   2896: ldc2_w -770041031
    //   2899: l2i
    //   2900: ldc_w 1340294960
    //   2903: ixor
    //   2904: goto -> 2915
    //   2907: ldc2_w -985636632
    //   2910: l2i
    //   2911: ldc_w 907145831
    //   2914: ixor
    //   2915: ldc2_w -675617453
    //   2918: l2i
    //   2919: ldc_w 409178768
    //   2922: ixor
    //   2923: ixor
    //   2924: lookupswitch default -> 2952, -1011230567 -> 2907, 1377840074 -> 16114
    //   2952: goto -> 2956
    //   2955: athrow
    //   2956: invokevirtual getName : ()Ljava/lang/String;
    //   2959: goto -> 2963
    //   2962: athrow
    //   2963: getstatic Perryc.1 : I
    //   2966: ifeq -> 2980
    //   2969: ldc2_w -1437942653
    //   2972: l2i
    //   2973: ldc_w -1211515954
    //   2976: ixor
    //   2977: goto -> 2988
    //   2980: ldc2_w -520999877
    //   2983: l2i
    //   2984: ldc_w 262498080
    //   2987: ixor
    //   2988: ldc2_w -563162528
    //   2991: l2i
    //   2992: ldc_w -562965080
    //   2995: ixor
    //   2996: ixor
    //   2997: lookupswitch default -> 16224, -280474413 -> 3024, 496763013 -> 2980
    //   3024: goto -> 3028
    //   3027: athrow
    //   3028: invokevirtual append : (Ljava/lang/String;)Ljava/lang/StringBuilder;
    //   3031: goto -> 3035
    //   3034: athrow
    //   3035: getstatic Perryc.0 : I
    //   3038: ifle -> 3052
    //   3041: ldc2_w 2076448906
    //   3044: l2i
    //   3045: ldc_w -1283786850
    //   3048: ixor
    //   3049: goto -> 3060
    //   3052: ldc2_w 1302975779
    //   3055: l2i
    //   3056: ldc_w 866800847
    //   3059: ixor
    //   3060: ldc2_w -1893558092
    //   3063: l2i
    //   3064: ldc_w 532088231
    //   3067: ixor
    //   3068: ixor
    //   3069: lookupswitch default -> 3096, -2091888146 -> 3052, 1479242247 -> 16002
    //   3096: getstatic com/mojang/realmsclient/gui/ChatFormatting.WHITE : Lcom/mojang/realmsclient/gui/ChatFormatting;
    //   3099: getstatic Perryc.c : I
    //   3102: iflt -> 3116
    //   3105: ldc2_w -175864503
    //   3108: l2i
    //   3109: ldc_w -1228549341
    //   3112: ixor
    //   3113: goto -> 3124
    //   3116: ldc2_w 1874303033
    //   3119: l2i
    //   3120: ldc_w 647767867
    //   3123: ixor
    //   3124: ldc2_w -1301161955
    //   3127: l2i
    //   3128: ldc_w 1348170918
    //   3131: ixor
    //   3132: ixor
    //   3133: lookupswitch default -> 16064, -1586758959 -> 3116, -1425992775 -> 3160
    //   3160: goto -> 3164
    //   3163: athrow
    //   3164: invokevirtual append : (Ljava/lang/Object;)Ljava/lang/StringBuilder;
    //   3167: goto -> 3171
    //   3170: athrow
    //   3171: ldc_w '辊㍓'
    //   3174: getstatic Perryc.0 : I
    //   3177: ifle -> 3191
    //   3180: ldc2_w 151707111
    //   3183: l2i
    //   3184: ldc_w 1650776488
    //   3187: ixor
    //   3188: goto -> 3199
    //   3191: ldc2_w 1935282971
    //   3194: l2i
    //   3195: ldc_w -1020837552
    //   3198: ixor
    //   3199: ldc2_w -881280598
    //   3202: l2i
    //   3203: ldc_w 296616596
    //   3206: ixor
    //   3207: ixor
    //   3208: lookupswitch default -> 16192, -1313292431 -> 3191, 1789651317 -> 3236
    //   3236: goto -> 3240
    //   3239: athrow
    //   3240: invokestatic 0 : (Ljava/lang/String;)Ljava/lang/String;
    //   3243: goto -> 3247
    //   3246: athrow
    //   3247: getstatic Perryc.0 : I
    //   3250: ifle -> 3264
    //   3253: ldc2_w 950881450
    //   3256: l2i
    //   3257: ldc_w 1727489201
    //   3260: ixor
    //   3261: goto -> 3272
    //   3264: ldc2_w 391466825
    //   3267: l2i
    //   3268: ldc_w -1594868143
    //   3271: ixor
    //   3272: ldc2_w -1168747649
    //   3275: l2i
    //   3276: ldc_w -1815840780
    //   3279: ixor
    //   3280: ixor
    //   3281: lookupswitch default -> 3308, -1992493911 -> 3264, 2009599120 -> 15992
    //   3308: goto -> 3312
    //   3311: athrow
    //   3312: invokevirtual append : (Ljava/lang/String;)Ljava/lang/StringBuilder;
    //   3315: goto -> 3319
    //   3318: athrow
    //   3319: getstatic Perryc.1 : I
    //   3322: ifeq -> 3336
    //   3325: ldc2_w 187019158
    //   3328: l2i
    //   3329: ldc_w 1115083634
    //   3332: ixor
    //   3333: goto -> 3344
    //   3336: ldc2_w -452618584
    //   3339: l2i
    //   3340: ldc_w 1372695733
    //   3343: ixor
    //   3344: ldc2_w 258047794
    //   3347: l2i
    //   3348: ldc_w 1997701667
    //   3351: ixor
    //   3352: ixor
    //   3353: lookupswitch default -> 3380, -902303926 -> 3336, 824214005 -> 16080
    //   3380: goto -> 3384
    //   3383: athrow
    //   3384: invokevirtual toString : ()Ljava/lang/String;
    //   3387: goto -> 3391
    //   3390: athrow
    //   3391: getstatic Perryc.0 : I
    //   3394: ifle -> 3408
    //   3397: ldc2_w 923916128
    //   3400: l2i
    //   3401: ldc_w 459982812
    //   3404: ixor
    //   3405: goto -> 3416
    //   3408: ldc2_w -1375805738
    //   3411: l2i
    //   3412: ldc_w 1789824235
    //   3415: ixor
    //   3416: ldc2_w 1629562230
    //   3419: l2i
    //   3420: ldc_w 410968565
    //   3423: ixor
    //   3424: ixor
    //   3425: lookupswitch default -> 3452, 983629476 -> 3408, 1428476991 -> 16144
    //   3452: astore #5
    //   3454: goto -> 1826
    //   3457: getstatic Perryc.0 : I
    //   3460: ifle -> 3474
    //   3463: ldc2_w 207291323
    //   3466: l2i
    //   3467: ldc_w 1796604270
    //   3470: ixor
    //   3471: goto -> 3482
    //   3474: ldc2_w 763320635
    //   3477: l2i
    //   3478: ldc_w 1511500243
    //   3481: ixor
    //   3482: ldc2_w 133715638
    //   3485: l2i
    //   3486: ldc_w 765802120
    //   3489: ixor
    //   3490: ixor
    //   3491: lookupswitch default -> 16156, 1292919531 -> 3474, 1563791574 -> 3516
    //   3516: aload #5
    //   3518: getstatic Perryc.0 : I
    //   3521: ifle -> 3535
    //   3524: ldc2_w 1399383772
    //   3527: l2i
    //   3528: ldc_w 1784829624
    //   3531: ixor
    //   3532: goto -> 3543
    //   3535: ldc2_w -1482773347
    //   3538: l2i
    //   3539: ldc_w 1430695930
    //   3542: ixor
    //   3543: ldc2_w -211437371
    //   3546: l2i
    //   3547: ldc_w 1644043190
    //   3550: ixor
    //   3551: ixor
    //   3552: lookupswitch default -> 3580, -1511144840 -> 3535, -1416555753 -> 15972
    //   3580: goto -> 3584
    //   3583: athrow
    //   3584: invokestatic sendMessage : (Ljava/lang/String;)V
    //   3587: goto -> 3591
    //   3590: athrow
    //   3591: goto -> 537
    //   3594: return
    //   3595: getstatic Perryc.c : I
    //   3598: iflt -> 3612
    //   3601: ldc2_w 771351118
    //   3604: l2i
    //   3605: ldc_w -204324729
    //   3608: ixor
    //   3609: goto -> 3620
    //   3612: ldc2_w -247482383
    //   3615: l2i
    //   3616: ldc_w -1409559965
    //   3619: ixor
    //   3620: ldc2_w 1615363900
    //   3623: l2i
    //   3624: ldc_w 36512510
    //   3627: ixor
    //   3628: ixor
    //   3629: lookupswitch default -> 3656, -1135673589 -> 16230, 1929735463 -> 3612
    //   3656: getstatic bigname/zprestige/webhack/WebHack.moduleManager : Lbigname/zprestige/webhack/manager/ModuleManager;
    //   3659: getstatic Perryc.0 : I
    //   3662: ifle -> 3676
    //   3665: ldc2_w 1689351711
    //   3668: l2i
    //   3669: ldc_w -761605449
    //   3672: ixor
    //   3673: goto -> 3684
    //   3676: ldc2_w -1413720882
    //   3679: l2i
    //   3680: ldc_w -1062855208
    //   3683: ixor
    //   3684: ldc2_w 560139810
    //   3687: l2i
    //   3688: ldc_w 902004369
    //   3691: ixor
    //   3692: ixor
    //   3693: lookupswitch default -> 3720, -1567894501 -> 15942, 1570798404 -> 3676
    //   3720: aload_1
    //   3721: ldc2_w 1642206794
    //   3724: l2i
    //   3725: ldc_w 1642206794
    //   3728: ixor
    //   3729: aaload
    //   3730: getstatic Perryc.1 : I
    //   3733: ifeq -> 3747
    //   3736: ldc2_w -1450664820
    //   3739: l2i
    //   3740: ldc_w 520121115
    //   3743: ixor
    //   3744: goto -> 3755
    //   3747: ldc2_w 234328469
    //   3750: l2i
    //   3751: ldc_w 1827899930
    //   3754: ixor
    //   3755: ldc2_w -1308911978
    //   3758: l2i
    //   3759: ldc_w -55978456
    //   3762: ixor
    //   3763: ixor
    //   3764: lookupswitch default -> 3792, -69552343 -> 16186, 1079611378 -> 3747
    //   3792: goto -> 3796
    //   3795: athrow
    //   3796: invokevirtual getModuleByDisplayName : (Ljava/lang/String;)Lbigname/zprestige/webhack/features/modules/Module;
    //   3799: goto -> 3803
    //   3802: athrow
    //   3803: getstatic Perryc.1 : I
    //   3806: ifeq -> 3820
    //   3809: ldc2_w -954772073
    //   3812: l2i
    //   3813: ldc_w 2018431425
    //   3816: ixor
    //   3817: goto -> 3828
    //   3820: ldc2_w -1867774045
    //   3823: l2i
    //   3824: ldc_w -1229788198
    //   3827: ixor
    //   3828: ldc2_w -1364166191
    //   3831: l2i
    //   3832: ldc_w 298062827
    //   3835: ixor
    //   3836: ixor
    //   3837: lookupswitch default -> 3864, 3010156 -> 15856, 1639312706 -> 3820
    //   3864: astore_3
    //   3865: getstatic Perryc.0 : I
    //   3868: ifle -> 3882
    //   3871: ldc2_w 946600378
    //   3874: l2i
    //   3875: ldc_w -379814253
    //   3878: ixor
    //   3879: goto -> 3890
    //   3882: ldc2_w -2076466501
    //   3885: l2i
    //   3886: ldc_w 457853806
    //   3889: ixor
    //   3890: ldc2_w 422350442
    //   3893: l2i
    //   3894: ldc_w 1405192119
    //   3897: ixor
    //   3898: ixor
    //   3899: lookupswitch default -> 15984, -1680175372 -> 3882, -711139320 -> 3924
    //   3924: aload_3
    //   3925: ifnonnull -> 3939
    //   3928: ldc2_w 960657299
    //   3931: l2i
    //   3932: ldc_w -1321331937
    //   3935: ixor
    //   3936: goto -> 3947
    //   3939: ldc2_w 183856731
    //   3942: l2i
    //   3943: ldc_w -2104948010
    //   3946: ixor
    //   3947: ldc2_w -63747520
    //   3950: l2i
    //   3951: ldc_w 1558351734
    //   3954: ixor
    //   3955: ixor
    //   3956: tableswitch default -> 3928, 682467770 -> 3980, 682467771 -> 5084
    //   3980: getstatic Perryc.1 : I
    //   3983: ifeq -> 3997
    //   3986: ldc2_w -164964174
    //   3989: l2i
    //   3990: ldc_w -319070362
    //   3993: ixor
    //   3994: goto -> 4005
    //   3997: ldc2_w 875994348
    //   4000: l2i
    //   4001: ldc_w 413580480
    //   4004: ixor
    //   4005: ldc2_w 1301686822
    //   4008: l2i
    //   4009: ldc_w 154013265
    //   4012: ixor
    //   4013: ixor
    //   4014: lookupswitch default -> 4040, 520154259 -> 3997, 1583981475 -> 16162
    //   4040: getstatic bigname/zprestige/webhack/WebHack.moduleManager : Lbigname/zprestige/webhack/manager/ModuleManager;
    //   4043: getstatic Perryc.1 : I
    //   4046: ifeq -> 4060
    //   4049: ldc2_w -491027666
    //   4052: l2i
    //   4053: ldc_w -818105217
    //   4056: ixor
    //   4057: goto -> 4068
    //   4060: ldc2_w -1640463865
    //   4063: l2i
    //   4064: ldc_w -21173231
    //   4067: ixor
    //   4068: ldc2_w -147618800
    //   4071: l2i
    //   4072: ldc_w 2117176963
    //   4075: ixor
    //   4076: ixor
    //   4077: lookupswitch default -> 4104, -1534771774 -> 15862, -64880613 -> 4060
    //   4104: aload_1
    //   4105: ldc2_w -679154217
    //   4108: l2i
    //   4109: ldc_w -679154217
    //   4112: ixor
    //   4113: aaload
    //   4114: getstatic Perryc.0 : I
    //   4117: ifle -> 4131
    //   4120: ldc2_w -1860433101
    //   4123: l2i
    //   4124: ldc_w -11604087
    //   4127: ixor
    //   4128: goto -> 4139
    //   4131: ldc2_w 299064156
    //   4134: l2i
    //   4135: ldc_w -1611852366
    //   4138: ixor
    //   4139: ldc2_w -1230507095
    //   4142: l2i
    //   4143: ldc_w -1687762340
    //   4146: ixor
    //   4147: ixor
    //   4148: lookupswitch default -> 16018, -1543538917 -> 4176, 1133763919 -> 4131
    //   4176: goto -> 4180
    //   4179: athrow
    //   4180: invokevirtual getModuleByName : (Ljava/lang/String;)Lbigname/zprestige/webhack/features/modules/Module;
    //   4183: goto -> 4187
    //   4186: athrow
    //   4187: getstatic Perryc.1 : I
    //   4190: ifeq -> 4204
    //   4193: ldc2_w 1411333914
    //   4196: l2i
    //   4197: ldc_w -2080989036
    //   4200: ixor
    //   4201: goto -> 4212
    //   4204: ldc2_w 780083559
    //   4207: l2i
    //   4208: ldc_w 1987039506
    //   4211: ixor
    //   4212: ldc2_w 487306233
    //   4215: l2i
    //   4216: ldc_w -1666443286
    //   4219: ixor
    //   4220: ixor
    //   4221: lookupswitch default -> 15868, -642296730 -> 4248, 1447967645 -> 4204
    //   4248: astore_3
    //   4249: getstatic Perryc.c : I
    //   4252: iflt -> 4266
    //   4255: ldc2_w 903928160
    //   4258: l2i
    //   4259: ldc_w 287813664
    //   4262: ixor
    //   4263: goto -> 4274
    //   4266: ldc2_w 496399926
    //   4269: l2i
    //   4270: ldc_w -2074237608
    //   4273: ixor
    //   4274: ldc2_w -1707534629
    //   4277: l2i
    //   4278: ldc_w -189815058
    //   4281: ixor
    //   4282: ixor
    //   4283: lookupswitch default -> 15968, -144874661 -> 4308, 1246878069 -> 4266
    //   4308: aload_3
    //   4309: ifnonnull -> 4323
    //   4312: ldc2_w -1205476340
    //   4315: l2i
    //   4316: ldc_w 780020711
    //   4319: ixor
    //   4320: goto -> 4331
    //   4323: ldc2_w -549066126
    //   4326: l2i
    //   4327: ldc_w 1226712478
    //   4330: ixor
    //   4331: ldc2_w 380292128
    //   4334: l2i
    //   4335: ldc_w 268977272
    //   4338: ixor
    //   4339: ixor
    //   4340: tableswitch default -> 4312, -1862711373 -> 4364, -1862711372 -> 4512
    //   4364: ldc_w '迲㌛辥좣٢慷๶筱嫐㜘੧䈚葩?ኰ辑域利ᬏ5侸敂뎭妺'
    //   4367: getstatic Perryc.1 : I
    //   4370: ifeq -> 4384
    //   4373: ldc2_w -1057230702
    //   4376: l2i
    //   4377: ldc_w 1850032387
    //   4380: ixor
    //   4381: goto -> 4392
    //   4384: ldc2_w 1351220091
    //   4387: l2i
    //   4388: ldc_w -759781121
    //   4391: ixor
    //   4392: ldc2_w -1829368727
    //   4395: l2i
    //   4396: ldc_w -1749447836
    //   4399: ixor
    //   4400: ixor
    //   4401: lookupswitch default -> 4428, -1410255204 -> 16048, -1135299585 -> 4384
    //   4428: goto -> 4432
    //   4431: athrow
    //   4432: invokestatic 0 : (Ljava/lang/String;)Ljava/lang/String;
    //   4435: goto -> 4439
    //   4438: athrow
    //   4439: getstatic Perryc.0 : I
    //   4442: ifle -> 4456
    //   4445: ldc2_w -1988227715
    //   4448: l2i
    //   4449: ldc_w 1030878962
    //   4452: ixor
    //   4453: goto -> 4464
    //   4456: ldc2_w 1264388915
    //   4459: l2i
    //   4460: ldc_w -685097336
    //   4463: ixor
    //   4464: ldc2_w -357702443
    //   4467: l2i
    //   4468: ldc_w -1801742181
    //   4471: ixor
    //   4472: ixor
    //   4473: lookupswitch default -> 16070, -902199359 -> 4456, -499037707 -> 4500
    //   4500: goto -> 4504
    //   4503: athrow
    //   4504: invokestatic sendMessage : (Ljava/lang/String;)V
    //   4507: goto -> 4511
    //   4510: athrow
    //   4511: return
    //   4512: new java/lang/StringBuilder
    //   4515: dup
    //   4516: getstatic Perryc.1 : I
    //   4519: ifeq -> 4533
    //   4522: ldc2_w -694657915
    //   4525: l2i
    //   4526: ldc_w -107795081
    //   4529: ixor
    //   4530: goto -> 4541
    //   4533: ldc2_w 157954686
    //   4536: l2i
    //   4537: ldc_w 206415417
    //   4540: ixor
    //   4541: ldc2_w 1099105741
    //   4544: l2i
    //   4545: ldc_w 352370311
    //   4548: ixor
    //   4549: ixor
    //   4550: lookupswitch default -> 16216, 1369714445 -> 4576, 2072562360 -> 4533
    //   4576: goto -> 4580
    //   4579: athrow
    //   4580: invokespecial <init> : ()V
    //   4583: goto -> 4587
    //   4586: athrow
    //   4587: ldc_w '辆㌧辤좹ر愺๰笤嫈㜕ਢ䉞葩?ኪ辘埂剧ᬋ!俱敟뎸姹?ᢎ⫊?햕摽썰㯱奤ꚮ䗸✙酻믹䲀ホḂᏚ敥ﯵ⁈뽌ڪ伾䃎㐚氻짓戞䱐鳊쀷'
    //   4590: getstatic Perryc.0 : I
    //   4593: ifle -> 4607
    //   4596: ldc2_w 269387517
    //   4599: l2i
    //   4600: ldc_w 1720141252
    //   4603: ixor
    //   4604: goto -> 4615
    //   4607: ldc2_w -1145834933
    //   4610: l2i
    //   4611: ldc_w -1503310102
    //   4614: ixor
    //   4615: ldc2_w -973190183
    //   4618: l2i
    //   4619: ldc_w -238243793
    //   4622: ixor
    //   4623: ixor
    //   4624: lookupswitch default -> 16040, 702826327 -> 4652, 1119566031 -> 4607
    //   4652: goto -> 4656
    //   4655: athrow
    //   4656: invokestatic 0 : (Ljava/lang/String;)Ljava/lang/String;
    //   4659: goto -> 4663
    //   4662: athrow
    //   4663: getstatic Perryc.1 : I
    //   4666: ifeq -> 4680
    //   4669: ldc2_w 312575766
    //   4672: l2i
    //   4673: ldc_w 1739800152
    //   4676: ixor
    //   4677: goto -> 4688
    //   4680: ldc2_w 149265618
    //   4683: l2i
    //   4684: ldc_w -1330986164
    //   4687: ixor
    //   4688: ldc2_w -1500078408
    //   4691: l2i
    //   4692: ldc_w 890414845
    //   4695: ixor
    //   4696: ixor
    //   4697: lookupswitch default -> 15872, -426344181 -> 4680, 734750683 -> 4724
    //   4724: goto -> 4728
    //   4727: athrow
    //   4728: invokevirtual append : (Ljava/lang/String;)Ljava/lang/StringBuilder;
    //   4731: goto -> 4735
    //   4734: athrow
    //   4735: getstatic Perryc.0 : I
    //   4738: ifle -> 4752
    //   4741: ldc2_w -1607850964
    //   4744: l2i
    //   4745: ldc_w -629697678
    //   4748: ixor
    //   4749: goto -> 4760
    //   4752: ldc2_w -918840164
    //   4755: l2i
    //   4756: ldc_w 1852676708
    //   4759: ixor
    //   4760: ldc2_w 1627654005
    //   4763: l2i
    //   4764: ldc_w 1574431884
    //   4767: ixor
    //   4768: ixor
    //   4769: lookupswitch default -> 4796, -84992292 -> 4752, 1183734951 -> 16212
    //   4796: aload_3
    //   4797: getstatic Perryc.1 : I
    //   4800: ifeq -> 4814
    //   4803: ldc2_w 625929706
    //   4806: l2i
    //   4807: ldc_w -1052223631
    //   4810: ixor
    //   4811: goto -> 4822
    //   4814: ldc2_w -1554263618
    //   4817: l2i
    //   4818: ldc_w 28277886
    //   4821: ixor
    //   4822: ldc2_w 1631183971
    //   4825: l2i
    //   4826: ldc_w 268850
    //   4829: ixor
    //   4830: ixor
    //   4831: lookupswitch default -> 4856, -2059713334 -> 16146, 149336424 -> 4814
    //   4856: goto -> 4860
    //   4859: athrow
    //   4860: invokevirtual getDisplayName : ()Ljava/lang/String;
    //   4863: goto -> 4867
    //   4866: athrow
    //   4867: getstatic Perryc.c : I
    //   4870: iflt -> 4884
    //   4873: ldc2_w 975739961
    //   4876: l2i
    //   4877: ldc_w -799299179
    //   4880: ixor
    //   4881: goto -> 4892
    //   4884: ldc2_w -1164738870
    //   4887: l2i
    //   4888: ldc_w -964560284
    //   4891: ixor
    //   4892: ldc2_w 936388649
    //   4895: l2i
    //   4896: ldc_w -91465062
    //   4899: ixor
    //   4900: ixor
    //   4901: lookupswitch default -> 15858, -1320225251 -> 4928, 657409823 -> 4884
    //   4928: goto -> 4932
    //   4931: athrow
    //   4932: invokevirtual append : (Ljava/lang/String;)Ljava/lang/StringBuilder;
    //   4935: goto -> 4939
    //   4938: athrow
    //   4939: getstatic Perryc.1 : I
    //   4942: ifeq -> 4956
    //   4945: ldc2_w 1479455826
    //   4948: l2i
    //   4949: ldc_w 686235116
    //   4952: ixor
    //   4953: goto -> 4964
    //   4956: ldc2_w -440952649
    //   4959: l2i
    //   4960: ldc_w -224693397
    //   4963: ixor
    //   4964: ldc2_w 2042228308
    //   4967: l2i
    //   4968: ldc_w -1887812518
    //   4971: ixor
    //   4972: ixor
    //   4973: lookupswitch default -> 5000, -2046164048 -> 15948, 462078754 -> 4956
    //   5000: goto -> 5004
    //   5003: athrow
    //   5004: invokevirtual toString : ()Ljava/lang/String;
    //   5007: goto -> 5011
    //   5010: athrow
    //   5011: getstatic Perryc.0 : I
    //   5014: ifle -> 5028
    //   5017: ldc2_w -651963891
    //   5020: l2i
    //   5021: ldc_w -1907621546
    //   5024: ixor
    //   5025: goto -> 5036
    //   5028: ldc2_w 1296426056
    //   5031: l2i
    //   5032: ldc_w 2010837009
    //   5035: ixor
    //   5036: ldc2_w -803962717
    //   5039: l2i
    //   5040: ldc_w -1992771055
    //   5043: ixor
    //   5044: ixor
    //   5045: lookupswitch default -> 16120, 239331817 -> 5028, 1672687339 -> 5072
    //   5072: goto -> 5076
    //   5075: athrow
    //   5076: invokestatic sendMessage : (Ljava/lang/String;)V
    //   5079: goto -> 5083
    //   5082: athrow
    //   5083: return
    //   5084: getstatic Perryc.c : I
    //   5087: iflt -> 5101
    //   5090: ldc2_w -768973941
    //   5093: l2i
    //   5094: ldc_w -1668144946
    //   5097: ixor
    //   5098: goto -> 5109
    //   5101: ldc2_w 2121460221
    //   5104: l2i
    //   5105: ldc_w 759742782
    //   5108: ixor
    //   5109: ldc2_w -2131273946
    //   5112: l2i
    //   5113: ldc_w -956876713
    //   5116: ixor
    //   5117: ixor
    //   5118: lookupswitch default -> 16062, 146287668 -> 5101, 356140978 -> 5144
    //   5144: aload_1
    //   5145: arraylength
    //   5146: ldc2_w -1772336937
    //   5149: l2i
    //   5150: ldc_w -1772336939
    //   5153: ixor
    //   5154: if_icmpne -> 5168
    //   5157: ldc2_w 369219340
    //   5160: l2i
    //   5161: ldc_w 1693994832
    //   5164: ixor
    //   5165: goto -> 5176
    //   5168: ldc2_w 695681737
    //   5171: l2i
    //   5172: ldc_w 1536088724
    //   5175: ixor
    //   5176: ldc2_w -23177338
    //   5179: l2i
    //   5180: ldc_w -1544625048
    //   5183: ixor
    //   5184: ixor
    //   5185: tableswitch default -> 5157, 797518770 -> 5208, 797518771 -> 7791
    //   5208: new java/lang/StringBuilder
    //   5211: dup
    //   5212: getstatic Perryc.c : I
    //   5215: iflt -> 5229
    //   5218: ldc2_w -2093365696
    //   5221: l2i
    //   5222: ldc_w 664203872
    //   5225: ixor
    //   5226: goto -> 5237
    //   5229: ldc2_w 243411224
    //   5232: l2i
    //   5233: ldc_w -137561538
    //   5236: ixor
    //   5237: ldc2_w 1771667382
    //   5240: l2i
    //   5241: ldc_w -1224375926
    //   5244: ixor
    //   5245: ixor
    //   5246: lookupswitch default -> 5272, 1225306773 -> 5229, 2050214428 -> 16240
    //   5272: goto -> 5276
    //   5275: athrow
    //   5276: invokespecial <init> : ()V
    //   5279: goto -> 5283
    //   5282: athrow
    //   5283: getstatic Perryc.0 : I
    //   5286: ifle -> 5300
    //   5289: ldc2_w 1877626019
    //   5292: l2i
    //   5293: ldc_w -372214040
    //   5296: ixor
    //   5297: goto -> 5308
    //   5300: ldc2_w 2059111916
    //   5303: l2i
    //   5304: ldc_w -1020891391
    //   5307: ixor
    //   5308: ldc2_w 941447577
    //   5311: l2i
    //   5312: ldc_w -1331259674
    //   5315: ixor
    //   5316: ixor
    //   5317: lookupswitch default -> 15966, 243397940 -> 5300, 824585618 -> 5344
    //   5344: aload_3
    //   5345: getstatic Perryc.c : I
    //   5348: iflt -> 5362
    //   5351: ldc2_w -469337833
    //   5354: l2i
    //   5355: ldc_w 500127589
    //   5358: ixor
    //   5359: goto -> 5370
    //   5362: ldc2_w 1202295374
    //   5365: l2i
    //   5366: ldc_w 1309027081
    //   5369: ixor
    //   5370: ldc2_w -864816926
    //   5373: l2i
    //   5374: ldc_w -1640695350
    //   5377: ixor
    //   5378: ixor
    //   5379: lookupswitch default -> 15838, -1416747174 -> 5362, 1541976175 -> 5404
    //   5404: goto -> 5408
    //   5407: athrow
    //   5408: invokevirtual getDisplayName : ()Ljava/lang/String;
    //   5411: goto -> 5415
    //   5414: athrow
    //   5415: getstatic Perryc.c : I
    //   5418: iflt -> 5432
    //   5421: ldc2_w 9268617
    //   5424: l2i
    //   5425: ldc_w -449035191
    //   5428: ixor
    //   5429: goto -> 5440
    //   5432: ldc2_w 1829535460
    //   5435: l2i
    //   5436: ldc_w 1085279857
    //   5439: ixor
    //   5440: ldc2_w 678141065
    //   5443: l2i
    //   5444: ldc_w -292895268
    //   5447: ixor
    //   5448: ixor
    //   5449: lookupswitch default -> 5476, -1786044099 -> 5432, 592474261 -> 15888
    //   5476: goto -> 5480
    //   5479: athrow
    //   5480: invokevirtual append : (Ljava/lang/String;)Ljava/lang/StringBuilder;
    //   5483: goto -> 5487
    //   5486: athrow
    //   5487: ldc_w '辆㍉迬'
    //   5490: getstatic Perryc.c : I
    //   5493: iflt -> 5507
    //   5496: ldc2_w 1161732609
    //   5499: l2i
    //   5500: ldc_w -1487233250
    //   5503: ixor
    //   5504: goto -> 5515
    //   5507: ldc2_w -488319654
    //   5510: l2i
    //   5511: ldc_w -661031627
    //   5514: ixor
    //   5515: ldc2_w 1806983086
    //   5518: l2i
    //   5519: ldc_w 152257366
    //   5522: ixor
    //   5523: ixor
    //   5524: lookupswitch default -> 5552, -2134695449 -> 15842, -662592978 -> 5507
    //   5552: goto -> 5556
    //   5555: athrow
    //   5556: invokestatic 0 : (Ljava/lang/String;)Ljava/lang/String;
    //   5559: goto -> 5563
    //   5562: athrow
    //   5563: getstatic Perryc.1 : I
    //   5566: ifeq -> 5580
    //   5569: ldc2_w 55840328
    //   5572: l2i
    //   5573: ldc_w 221070132
    //   5576: ixor
    //   5577: goto -> 5588
    //   5580: ldc2_w -1733659038
    //   5583: l2i
    //   5584: ldc_w 1574378964
    //   5587: ixor
    //   5588: ldc2_w 437805296
    //   5591: l2i
    //   5592: ldc_w -590965028
    //   5595: ixor
    //   5596: ixor
    //   5597: lookupswitch default -> 16188, -928531632 -> 5580, 61054362 -> 5624
    //   5624: goto -> 5628
    //   5627: athrow
    //   5628: invokevirtual append : (Ljava/lang/String;)Ljava/lang/StringBuilder;
    //   5631: goto -> 5635
    //   5634: athrow
    //   5635: getstatic Perryc.1 : I
    //   5638: ifeq -> 5652
    //   5641: ldc2_w 1863061267
    //   5644: l2i
    //   5645: ldc_w 2034548309
    //   5648: ixor
    //   5649: goto -> 5660
    //   5652: ldc2_w 78943164
    //   5655: l2i
    //   5656: ldc_w -1643282154
    //   5659: ixor
    //   5660: ldc2_w -1938454831
    //   5663: l2i
    //   5664: ldc_w -679559048
    //   5667: ixor
    //   5668: ixor
    //   5669: lookupswitch default -> 5696, -1379664012 -> 5652, 1296300015 -> 15974
    //   5696: aload_3
    //   5697: getstatic Perryc.0 : I
    //   5700: ifle -> 5714
    //   5703: ldc2_w -1083110821
    //   5706: l2i
    //   5707: ldc_w -706898042
    //   5710: ixor
    //   5711: goto -> 5722
    //   5714: ldc2_w 1219484157
    //   5717: l2i
    //   5718: ldc_w 891300480
    //   5721: ixor
    //   5722: ldc2_w -2096067207
    //   5725: l2i
    //   5726: ldc_w 1548867636
    //   5729: ixor
    //   5730: ixor
    //   5731: lookupswitch default -> 15954, -1563515344 -> 5756, -1242707824 -> 5714
    //   5756: goto -> 5760
    //   5759: athrow
    //   5760: invokevirtual getDescription : ()Ljava/lang/String;
    //   5763: goto -> 5767
    //   5766: athrow
    //   5767: getstatic Perryc.c : I
    //   5770: iflt -> 5784
    //   5773: ldc2_w 1579527677
    //   5776: l2i
    //   5777: ldc_w 328056825
    //   5780: ixor
    //   5781: goto -> 5792
    //   5784: ldc2_w 749769087
    //   5787: l2i
    //   5788: ldc_w 1539392335
    //   5791: ixor
    //   5792: ldc2_w -1141848908
    //   5795: l2i
    //   5796: ldc_w -963912204
    //   5799: ixor
    //   5800: ixor
    //   5801: lookupswitch default -> 15940, 168479600 -> 5828, 819137348 -> 5784
    //   5828: goto -> 5832
    //   5831: athrow
    //   5832: invokevirtual append : (Ljava/lang/String;)Ljava/lang/StringBuilder;
    //   5835: goto -> 5839
    //   5838: athrow
    //   5839: getstatic Perryc.c : I
    //   5842: iflt -> 5856
    //   5845: ldc2_w -1678226615
    //   5848: l2i
    //   5849: ldc_w 1709971804
    //   5852: ixor
    //   5853: goto -> 5864
    //   5856: ldc2_w -1208572272
    //   5859: l2i
    //   5860: ldc_w -1415943043
    //   5863: ixor
    //   5864: ldc2_w -1743221197
    //   5867: l2i
    //   5868: ldc_w 371683469
    //   5871: ixor
    //   5872: ixor
    //   5873: lookupswitch default -> 16220, -1840040877 -> 5900, 1881910443 -> 5856
    //   5900: goto -> 5904
    //   5903: athrow
    //   5904: invokevirtual toString : ()Ljava/lang/String;
    //   5907: goto -> 5911
    //   5910: athrow
    //   5911: getstatic Perryc.0 : I
    //   5914: ifle -> 5928
    //   5917: ldc2_w 1842553233
    //   5920: l2i
    //   5921: ldc_w 1308881636
    //   5924: ixor
    //   5925: goto -> 5936
    //   5928: ldc2_w 103536766
    //   5931: l2i
    //   5932: ldc_w -1706154461
    //   5935: ixor
    //   5936: ldc2_w -1265323785
    //   5939: l2i
    //   5940: ldc_w -1059272057
    //   5943: ixor
    //   5944: ixor
    //   5945: lookupswitch default -> 15894, -399670227 -> 5972, 1469622533 -> 5928
    //   5972: goto -> 5976
    //   5975: athrow
    //   5976: invokestatic sendMessage : (Ljava/lang/String;)V
    //   5979: goto -> 5983
    //   5982: athrow
    //   5983: getstatic Perryc.0 : I
    //   5986: ifle -> 6000
    //   5989: ldc2_w 75190182
    //   5992: l2i
    //   5993: ldc_w 799185
    //   5996: ixor
    //   5997: goto -> 6008
    //   6000: ldc2_w -1311427284
    //   6003: l2i
    //   6004: ldc_w -673677365
    //   6007: ixor
    //   6008: ldc2_w 496659862
    //   6011: l2i
    //   6012: ldc_w 921570984
    //   6015: ixor
    //   6016: ixor
    //   6017: lookupswitch default -> 6044, 788733257 -> 15886, 1682877177 -> 6000
    //   6044: aload_3
    //   6045: getstatic Perryc.0 : I
    //   6048: ifle -> 6062
    //   6051: ldc2_w -1644346755
    //   6054: l2i
    //   6055: ldc_w -826302406
    //   6058: ixor
    //   6059: goto -> 6070
    //   6062: ldc2_w -1280829009
    //   6065: l2i
    //   6066: ldc_w -989773152
    //   6069: ixor
    //   6070: ldc2_w -823862642
    //   6073: l2i
    //   6074: ldc_w 1398508108
    //   6077: ixor
    //   6078: ixor
    //   6079: lookupswitch default -> 6104, -1075518261 -> 6062, -822234491 -> 15828
    //   6104: goto -> 6108
    //   6107: athrow
    //   6108: invokevirtual getSettings : ()Ljava/util/List;
    //   6111: goto -> 6115
    //   6114: athrow
    //   6115: getstatic Perryc.1 : I
    //   6118: ifeq -> 6132
    //   6121: ldc2_w 1510764910
    //   6124: l2i
    //   6125: ldc_w 1664591814
    //   6128: ixor
    //   6129: goto -> 6140
    //   6132: ldc2_w -22916675
    //   6135: l2i
    //   6136: ldc_w -59262156
    //   6139: ixor
    //   6140: ldc2_w 1353064460
    //   6143: l2i
    //   6144: ldc_w -1802199246
    //   6147: ixor
    //   6148: ixor
    //   6149: lookupswitch default -> 16198, -957917769 -> 6176, -49714794 -> 6132
    //   6176: goto -> 6180
    //   6179: athrow
    //   6180: invokeinterface iterator : ()Ljava/util/Iterator;
    //   6185: goto -> 6189
    //   6188: athrow
    //   6189: getstatic Perryc.1 : I
    //   6192: ifeq -> 6206
    //   6195: ldc2_w -217907849
    //   6198: l2i
    //   6199: ldc_w 143782356
    //   6202: ixor
    //   6203: goto -> 6214
    //   6206: ldc2_w -509165312
    //   6209: l2i
    //   6210: ldc_w -1267777013
    //   6213: ixor
    //   6214: ldc2_w 1155608474
    //   6217: l2i
    //   6218: ldc_w -86877976
    //   6221: ixor
    //   6222: ixor
    //   6223: lookupswitch default -> 6248, -1581317743 -> 6206, 1168145361 -> 15884
    //   6248: astore #4
    //   6250: getstatic Perryc.c : I
    //   6253: iflt -> 6267
    //   6256: ldc2_w -1782079643
    //   6259: l2i
    //   6260: ldc_w 268861129
    //   6263: ixor
    //   6264: goto -> 6275
    //   6267: ldc2_w 840839960
    //   6270: l2i
    //   6271: ldc_w -242403882
    //   6274: ixor
    //   6275: ldc2_w -1774836742
    //   6278: l2i
    //   6279: ldc_w -881345551
    //   6282: ixor
    //   6283: ixor
    //   6284: lookupswitch default -> 16180, -1630363963 -> 6312, -662668889 -> 6267
    //   6312: aload #4
    //   6314: getstatic Perryc.0 : I
    //   6317: ifle -> 6331
    //   6320: ldc2_w -399109737
    //   6323: l2i
    //   6324: ldc_w 65807630
    //   6327: ixor
    //   6328: goto -> 6339
    //   6331: ldc2_w -48004916
    //   6334: l2i
    //   6335: ldc_w -871466956
    //   6338: ixor
    //   6339: ldc2_w 37741657
    //   6342: l2i
    //   6343: ldc_w 861323854
    //   6346: ixor
    //   6347: ixor
    //   6348: lookupswitch default -> 15970, -625798514 -> 6331, 4513519 -> 6376
    //   6376: goto -> 6380
    //   6379: athrow
    //   6380: invokeinterface hasNext : ()Z
    //   6385: goto -> 6389
    //   6388: athrow
    //   6389: ifeq -> 6403
    //   6392: ldc2_w -829418264
    //   6395: l2i
    //   6396: ldc_w 1828004951
    //   6399: ixor
    //   6400: goto -> 6411
    //   6403: ldc2_w -1128226054
    //   6406: l2i
    //   6407: ldc_w 514167370
    //   6410: ixor
    //   6411: ldc2_w -1104050035
    //   6414: l2i
    //   6415: ldc_w 2093896117
    //   6418: ixor
    //   6419: ixor
    //   6420: tableswitch default -> 6392, 1620765063 -> 6444, 1620765064 -> 7790
    //   6444: getstatic Perryc.1 : I
    //   6447: ifeq -> 6461
    //   6450: ldc2_w -305051958
    //   6453: l2i
    //   6454: ldc_w 1733874070
    //   6457: ixor
    //   6458: goto -> 6469
    //   6461: ldc2_w 774973546
    //   6464: l2i
    //   6465: ldc_w -1834553443
    //   6468: ixor
    //   6469: ldc2_w -1203847877
    //   6472: l2i
    //   6473: ldc_w 1829480942
    //   6476: ixor
    //   6477: ixor
    //   6478: lookupswitch default -> 6504, -754633699 -> 6461, 1606189961 -> 15938
    //   6504: aload #4
    //   6506: getstatic Perryc.0 : I
    //   6509: ifle -> 6523
    //   6512: ldc2_w -1273957518
    //   6515: l2i
    //   6516: ldc_w -1805655779
    //   6519: ixor
    //   6520: goto -> 6531
    //   6523: ldc2_w 665218160
    //   6526: l2i
    //   6527: ldc_w -619848780
    //   6530: ixor
    //   6531: ldc2_w 60712750
    //   6534: l2i
    //   6535: ldc_w 1107930561
    //   6538: ixor
    //   6539: ixor
    //   6540: lookupswitch default -> 15946, -1120109269 -> 6568, 1641601152 -> 6523
    //   6568: goto -> 6572
    //   6571: athrow
    //   6572: invokeinterface next : ()Ljava/lang/Object;
    //   6577: goto -> 6581
    //   6580: athrow
    //   6581: checkcast bigname/zprestige/webhack/features/setting/Setting
    //   6584: getstatic Perryc.1 : I
    //   6587: ifeq -> 6601
    //   6590: ldc2_w 224750600
    //   6593: l2i
    //   6594: ldc_w 797070490
    //   6597: ixor
    //   6598: goto -> 6609
    //   6601: ldc2_w -215450043
    //   6604: l2i
    //   6605: ldc_w 680540553
    //   6608: ixor
    //   6609: ldc2_w -821676429
    //   6612: l2i
    //   6613: ldc_w -1727625116
    //   6616: ixor
    //   6617: ixor
    //   6618: lookupswitch default -> 16082, -1917257253 -> 6644, 1961330309 -> 6601
    //   6644: astore #5
    //   6646: new java/lang/StringBuilder
    //   6649: dup
    //   6650: getstatic Perryc.0 : I
    //   6653: ifle -> 6667
    //   6656: ldc2_w 245067770
    //   6659: l2i
    //   6660: ldc_w 725949883
    //   6663: ixor
    //   6664: goto -> 6675
    //   6667: ldc2_w -1622016256
    //   6670: l2i
    //   6671: ldc_w 863674824
    //   6674: ixor
    //   6675: ldc2_w 859113899
    //   6678: l2i
    //   6679: ldc_w 1224760968
    //   6682: ixor
    //   6683: ixor
    //   6684: lookupswitch default -> 6712, 1609246050 -> 16098, 2026293536 -> 6667
    //   6712: goto -> 6716
    //   6715: athrow
    //   6716: invokespecial <init> : ()V
    //   6719: goto -> 6723
    //   6722: athrow
    //   6723: getstatic Perryc.1 : I
    //   6726: ifeq -> 6740
    //   6729: ldc2_w -183453443
    //   6732: l2i
    //   6733: ldc_w -1316650212
    //   6736: ixor
    //   6737: goto -> 6748
    //   6740: ldc2_w 731996140
    //   6743: l2i
    //   6744: ldc_w 2103943006
    //   6747: ixor
    //   6748: ldc2_w -1740445773
    //   6751: l2i
    //   6752: ldc_w -444047987
    //   6755: ixor
    //   6756: ixor
    //   6757: lookupswitch default -> 6784, -527586686 -> 6740, 962560479 -> 16034
    //   6784: aload #5
    //   6786: getstatic Perryc.c : I
    //   6789: iflt -> 6803
    //   6792: ldc2_w -630102888
    //   6795: l2i
    //   6796: ldc_w -1544601276
    //   6799: ixor
    //   6800: goto -> 6811
    //   6803: ldc2_w 495169912
    //   6806: l2i
    //   6807: ldc_w 891659701
    //   6810: ixor
    //   6811: ldc2_w 900444973
    //   6814: l2i
    //   6815: ldc_w -858863774
    //   6818: ixor
    //   6819: ixor
    //   6820: lookupswitch default -> 16054, -2131013229 -> 6803, -775724926 -> 6848
    //   6848: goto -> 6852
    //   6851: athrow
    //   6852: invokevirtual getName : ()Ljava/lang/String;
    //   6855: goto -> 6859
    //   6858: athrow
    //   6859: getstatic Perryc.c : I
    //   6862: iflt -> 6876
    //   6865: ldc2_w 828655851
    //   6868: l2i
    //   6869: ldc_w 726656524
    //   6872: ixor
    //   6873: goto -> 6884
    //   6876: ldc2_w 2111046655
    //   6879: l2i
    //   6880: ldc_w -448818123
    //   6883: ixor
    //   6884: ldc2_w -1470847673
    //   6887: l2i
    //   6888: ldc_w -1073572110
    //   6891: ixor
    //   6892: ixor
    //   6893: lookupswitch default -> 16122, -256007041 -> 6920, 1920834898 -> 6876
    //   6920: goto -> 6924
    //   6923: athrow
    //   6924: invokevirtual append : (Ljava/lang/String;)Ljava/lang/StringBuilder;
    //   6927: goto -> 6931
    //   6930: athrow
    //   6931: ldc_w '辆㍉迬'
    //   6934: getstatic Perryc.1 : I
    //   6937: ifeq -> 6951
    //   6940: ldc2_w -1596613284
    //   6943: l2i
    //   6944: ldc_w 78869728
    //   6947: ixor
    //   6948: goto -> 6959
    //   6951: ldc2_w 722846727
    //   6954: l2i
    //   6955: ldc_w 1044037534
    //   6958: ixor
    //   6959: ldc2_w 365427189
    //   6962: l2i
    //   6963: ldc_w -1483085071
    //   6966: ixor
    //   6967: ixor
    //   6968: lookupswitch default -> 6996, 372832952 -> 16130, 1959159179 -> 6951
    //   6996: goto -> 7000
    //   6999: athrow
    //   7000: invokestatic 0 : (Ljava/lang/String;)Ljava/lang/String;
    //   7003: goto -> 7007
    //   7006: athrow
    //   7007: getstatic Perryc.c : I
    //   7010: iflt -> 7024
    //   7013: ldc2_w -463162803
    //   7016: l2i
    //   7017: ldc_w -1796737392
    //   7020: ixor
    //   7021: goto -> 7032
    //   7024: ldc2_w -1387571933
    //   7027: l2i
    //   7028: ldc_w 1884303684
    //   7031: ixor
    //   7032: ldc2_w -1871944485
    //   7035: l2i
    //   7036: ldc_w 1907516736
    //   7039: ixor
    //   7040: ixor
    //   7041: lookupswitch default -> 7068, -2006639892 -> 7024, -1856158394 -> 16100
    //   7068: goto -> 7072
    //   7071: athrow
    //   7072: invokevirtual append : (Ljava/lang/String;)Ljava/lang/StringBuilder;
    //   7075: goto -> 7079
    //   7078: athrow
    //   7079: getstatic Perryc.1 : I
    //   7082: ifeq -> 7096
    //   7085: ldc2_w 2073372766
    //   7088: l2i
    //   7089: ldc_w -845789836
    //   7092: ixor
    //   7093: goto -> 7104
    //   7096: ldc2_w 1861318076
    //   7099: l2i
    //   7100: ldc_w -155541212
    //   7103: ixor
    //   7104: ldc2_w 2034887103
    //   7107: l2i
    //   7108: ldc_w 1307360546
    //   7111: ixor
    //   7112: ixor
    //   7113: lookupswitch default -> 16160, -2103035465 -> 7096, -1393655803 -> 7140
    //   7140: aload #5
    //   7142: getstatic Perryc.0 : I
    //   7145: ifle -> 7159
    //   7148: ldc2_w 1674299950
    //   7151: l2i
    //   7152: ldc_w -819001986
    //   7155: ixor
    //   7156: goto -> 7167
    //   7159: ldc2_w 531620632
    //   7162: l2i
    //   7163: ldc_w 1574903812
    //   7166: ixor
    //   7167: ldc2_w -715084011
    //   7170: l2i
    //   7171: ldc_w 428072679
    //   7174: ixor
    //   7175: ixor
    //   7176: lookupswitch default -> 16134, -1902923026 -> 7204, 1611120290 -> 7159
    //   7204: goto -> 7208
    //   7207: athrow
    //   7208: invokevirtual getValue : ()Ljava/lang/Object;
    //   7211: goto -> 7215
    //   7214: athrow
    //   7215: getstatic Perryc.1 : I
    //   7218: ifeq -> 7232
    //   7221: ldc2_w -1546180287
    //   7224: l2i
    //   7225: ldc_w -1273173172
    //   7228: ixor
    //   7229: goto -> 7240
    //   7232: ldc2_w 552309836
    //   7235: l2i
    //   7236: ldc_w -222678091
    //   7239: ixor
    //   7240: ldc2_w -1172754021
    //   7243: l2i
    //   7244: ldc_w 944550759
    //   7247: ixor
    //   7248: ixor
    //   7249: lookupswitch default -> 7276, -1784790799 -> 15836, 2118037167 -> 7232
    //   7276: goto -> 7280
    //   7279: athrow
    //   7280: invokevirtual append : (Ljava/lang/Object;)Ljava/lang/StringBuilder;
    //   7283: goto -> 7287
    //   7286: athrow
    //   7287: ldc_w '辊㍓'
    //   7290: getstatic Perryc.1 : I
    //   7293: ifeq -> 7307
    //   7296: ldc2_w -1045863728
    //   7299: l2i
    //   7300: ldc_w 279002399
    //   7303: ixor
    //   7304: goto -> 7315
    //   7307: ldc2_w -1215819114
    //   7310: l2i
    //   7311: ldc_w -1112785489
    //   7314: ixor
    //   7315: ldc2_w 1962908347
    //   7318: l2i
    //   7319: ldc_w -1601864182
    //   7322: ixor
    //   7323: ixor
    //   7324: lookupswitch default -> 16194, -564212856 -> 7352, 91405182 -> 7307
    //   7352: goto -> 7356
    //   7355: athrow
    //   7356: invokestatic 0 : (Ljava/lang/String;)Ljava/lang/String;
    //   7359: goto -> 7363
    //   7362: athrow
    //   7363: getstatic Perryc.0 : I
    //   7366: ifle -> 7380
    //   7369: ldc2_w -1239704472
    //   7372: l2i
    //   7373: ldc_w -137630771
    //   7376: ixor
    //   7377: goto -> 7388
    //   7380: ldc2_w -1457406814
    //   7383: l2i
    //   7384: ldc_w -563722034
    //   7387: ixor
    //   7388: ldc2_w 594678722
    //   7391: l2i
    //   7392: ldc_w -62296470
    //   7395: ixor
    //   7396: ixor
    //   7397: lookupswitch default -> 7424, -1628763635 -> 16182, -311602058 -> 7380
    //   7424: goto -> 7428
    //   7427: athrow
    //   7428: invokevirtual append : (Ljava/lang/String;)Ljava/lang/StringBuilder;
    //   7431: goto -> 7435
    //   7434: athrow
    //   7435: getstatic Perryc.0 : I
    //   7438: ifle -> 7452
    //   7441: ldc2_w -1316459730
    //   7444: l2i
    //   7445: ldc_w -188396316
    //   7448: ixor
    //   7449: goto -> 7460
    //   7452: ldc2_w 1980701056
    //   7455: l2i
    //   7456: ldc_w 1192130270
    //   7459: ixor
    //   7460: ldc2_w 1593000253
    //   7463: l2i
    //   7464: ldc_w -807990968
    //   7467: ixor
    //   7468: ixor
    //   7469: lookupswitch default -> 15964, -1608177877 -> 7496, -731287617 -> 7452
    //   7496: aload #5
    //   7498: getstatic Perryc.1 : I
    //   7501: ifeq -> 7515
    //   7504: ldc2_w 771244041
    //   7507: l2i
    //   7508: ldc_w -1439901852
    //   7511: ixor
    //   7512: goto -> 7523
    //   7515: ldc2_w -2112159255
    //   7518: l2i
    //   7519: ldc_w -1271619758
    //   7522: ixor
    //   7523: ldc2_w 1216696714
    //   7526: l2i
    //   7527: ldc_w 1037163053
    //   7530: ixor
    //   7531: ixor
    //   7532: lookupswitch default -> 7560, -226485046 -> 16158, -189738908 -> 7515
    //   7560: goto -> 7564
    //   7563: athrow
    //   7564: invokevirtual getDescription : ()Ljava/lang/String;
    //   7567: goto -> 7571
    //   7570: athrow
    //   7571: getstatic Perryc.0 : I
    //   7574: ifle -> 7588
    //   7577: ldc2_w 1466132584
    //   7580: l2i
    //   7581: ldc_w 1914821629
    //   7584: ixor
    //   7585: goto -> 7596
    //   7588: ldc2_w 1476980328
    //   7591: l2i
    //   7592: ldc_w 1327436703
    //   7595: ixor
    //   7596: ldc2_w 1126826247
    //   7599: l2i
    //   7600: ldc_w -1170851361
    //   7603: ixor
    //   7604: ixor
    //   7605: lookupswitch default -> 7632, -1121212611 -> 7588, -597783731 -> 15902
    //   7632: goto -> 7636
    //   7635: athrow
    //   7636: invokevirtual append : (Ljava/lang/String;)Ljava/lang/StringBuilder;
    //   7639: goto -> 7643
    //   7642: athrow
    //   7643: getstatic Perryc.c : I
    //   7646: iflt -> 7660
    //   7649: ldc2_w -1116458608
    //   7652: l2i
    //   7653: ldc_w -1938885274
    //   7656: ixor
    //   7657: goto -> 7668
    //   7660: ldc2_w -387180267
    //   7663: l2i
    //   7664: ldc_w -1060775014
    //   7667: ixor
    //   7668: ldc2_w 111507405
    //   7671: l2i
    //   7672: ldc_w -89236740
    //   7675: ixor
    //   7676: ixor
    //   7677: lookupswitch default -> 7704, -1577152794 -> 7660, -854464057 -> 16020
    //   7704: goto -> 7708
    //   7707: athrow
    //   7708: invokevirtual toString : ()Ljava/lang/String;
    //   7711: goto -> 7715
    //   7714: athrow
    //   7715: getstatic Perryc.c : I
    //   7718: iflt -> 7732
    //   7721: ldc2_w -445595061
    //   7724: l2i
    //   7725: ldc_w 1179409028
    //   7728: ixor
    //   7729: goto -> 7740
    //   7732: ldc2_w 567162731
    //   7735: l2i
    //   7736: ldc_w 198734094
    //   7739: ixor
    //   7740: ldc2_w -1312869186
    //   7743: l2i
    //   7744: ldc_w 1963212728
    //   7747: ixor
    //   7748: ixor
    //   7749: lookupswitch default -> 7776, 610890387 -> 7732, 1736938441 -> 15950
    //   7776: goto -> 7780
    //   7779: athrow
    //   7780: invokestatic sendMessage : (Ljava/lang/String;)V
    //   7783: goto -> 7787
    //   7786: athrow
    //   7787: goto -> 6250
    //   7790: return
    //   7791: getstatic Perryc.1 : I
    //   7794: ifeq -> 7808
    //   7797: ldc2_w 1749160836
    //   7800: l2i
    //   7801: ldc_w -197517347
    //   7804: ixor
    //   7805: goto -> 7816
    //   7808: ldc2_w -719427279
    //   7811: l2i
    //   7812: ldc_w 1537182004
    //   7815: ixor
    //   7816: ldc2_w -895143630
    //   7819: l2i
    //   7820: ldc_w 1390080765
    //   7823: ixor
    //   7824: ixor
    //   7825: lookupswitch default -> 7852, 67620758 -> 15958, 497091747 -> 7808
    //   7852: aload_1
    //   7853: arraylength
    //   7854: ldc2_w -715843142
    //   7857: l2i
    //   7858: ldc_w -715843143
    //   7861: ixor
    //   7862: if_icmpne -> 7876
    //   7865: ldc2_w 1902356118
    //   7868: l2i
    //   7869: ldc_w -2004485808
    //   7872: ixor
    //   7873: goto -> 7884
    //   7876: ldc2_w -327519658
    //   7879: l2i
    //   7880: ldc_w 362556817
    //   7883: ixor
    //   7884: ldc2_w -1145162776
    //   7887: l2i
    //   7888: ldc_w 165115052
    //   7891: ixor
    //   7892: ixor
    //   7893: tableswitch default -> 7865, 1267669122 -> 7916, 1267669123 -> 9692
    //   7916: getstatic Perryc.1 : I
    //   7919: ifeq -> 7933
    //   7922: ldc2_w 358625562
    //   7925: l2i
    //   7926: ldc_w -1470758120
    //   7929: ixor
    //   7930: goto -> 7941
    //   7933: ldc2_w 429016016
    //   7936: l2i
    //   7937: ldc_w 1184696954
    //   7940: ixor
    //   7941: ldc2_w 27978379
    //   7944: l2i
    //   7945: ldc_w -2028857660
    //   7948: ixor
    //   7949: ixor
    //   7950: lookupswitch default -> 15956, -642271771 -> 7976, 999214669 -> 7933
    //   7976: aload_1
    //   7977: ldc2_w 221037103
    //   7980: l2i
    //   7981: ldc_w 221037102
    //   7984: ixor
    //   7985: aaload
    //   7986: ldc_w '迕㌖辸'
    //   7989: getstatic Perryc.0 : I
    //   7992: ifle -> 8006
    //   7995: ldc2_w 1184663021
    //   7998: l2i
    //   7999: ldc_w -375900468
    //   8002: ixor
    //   8003: goto -> 8014
    //   8006: ldc2_w -631882923
    //   8009: l2i
    //   8010: ldc_w -1879479762
    //   8013: ixor
    //   8014: ldc2_w 1636634193
    //   8017: l2i
    //   8018: ldc_w 2109434704
    //   8021: ixor
    //   8022: ixor
    //   8023: lookupswitch default -> 8048, -1288514016 -> 16072, -1077060774 -> 8006
    //   8048: goto -> 8052
    //   8051: athrow
    //   8052: invokestatic 0 : (Ljava/lang/String;)Ljava/lang/String;
    //   8055: goto -> 8059
    //   8058: athrow
    //   8059: getstatic Perryc.c : I
    //   8062: iflt -> 8076
    //   8065: ldc2_w -1999603284
    //   8068: l2i
    //   8069: ldc_w 133728524
    //   8072: ixor
    //   8073: goto -> 8084
    //   8076: ldc2_w -1461696812
    //   8079: l2i
    //   8080: ldc_w -152661887
    //   8083: ixor
    //   8084: ldc2_w 1971510431
    //   8087: l2i
    //   8088: ldc_w -947305385
    //   8091: ixor
    //   8092: ixor
    //   8093: lookupswitch default -> 8120, 189506038 -> 8076, 1025730664 -> 16170
    //   8120: goto -> 8124
    //   8123: athrow
    //   8124: invokevirtual equalsIgnoreCase : (Ljava/lang/String;)Z
    //   8127: goto -> 8131
    //   8130: athrow
    //   8131: ifeq -> 8145
    //   8134: ldc2_w -583673635
    //   8137: l2i
    //   8138: ldc_w 1873010613
    //   8141: ixor
    //   8142: goto -> 8153
    //   8145: ldc2_w -1184771148
    //   8148: l2i
    //   8149: ldc_w 200791261
    //   8152: ixor
    //   8153: ldc2_w 2070602953
    //   8156: l2i
    //   8157: ldc_w 698738041
    //   8160: ixor
    //   8161: ixor
    //   8162: tableswitch default -> 8134, -531036456 -> 8184, -531036455 -> 8334
    //   8184: ldc_w '迶㌟辩좱ر慿ู筴嫙㜞ਮ䈘葿?ኢ迟埘剬ᬞ9侸敟뎾妺'
    //   8187: getstatic Perryc.0 : I
    //   8190: ifle -> 8204
    //   8193: ldc2_w -680306592
    //   8196: l2i
    //   8197: ldc_w -2089953038
    //   8200: ixor
    //   8201: goto -> 8212
    //   8204: ldc2_w 922307669
    //   8207: l2i
    //   8208: ldc_w -1807342961
    //   8211: ixor
    //   8212: ldc2_w 1523405208
    //   8215: l2i
    //   8216: ldc_w -1712530657
    //   8219: ixor
    //   8220: ixor
    //   8221: lookupswitch default -> 15850, -1757476331 -> 8204, 1637803101 -> 8248
    //   8248: goto -> 8252
    //   8251: athrow
    //   8252: invokestatic 0 : (Ljava/lang/String;)Ljava/lang/String;
    //   8255: goto -> 8259
    //   8258: athrow
    //   8259: getstatic Perryc.c : I
    //   8262: iflt -> 8276
    //   8265: ldc2_w -185536502
    //   8268: l2i
    //   8269: ldc_w -1873102089
    //   8272: ixor
    //   8273: goto -> 8284
    //   8276: ldc2_w -1165623914
    //   8279: l2i
    //   8280: ldc_w 957436210
    //   8283: ixor
    //   8284: ldc2_w -1429926615
    //   8287: l2i
    //   8288: ldc_w 599308375
    //   8291: ixor
    //   8292: ixor
    //   8293: lookupswitch default -> 15870, -304611453 -> 8276, 183048666 -> 8320
    //   8320: goto -> 8324
    //   8323: athrow
    //   8324: invokestatic sendMessage : (Ljava/lang/String;)V
    //   8327: goto -> 8331
    //   8330: athrow
    //   8331: goto -> 9691
    //   8334: getstatic Perryc.0 : I
    //   8337: ifle -> 8351
    //   8340: ldc2_w -648588681
    //   8343: l2i
    //   8344: ldc_w -65969188
    //   8347: ixor
    //   8348: goto -> 8359
    //   8351: ldc2_w 1932024730
    //   8354: l2i
    //   8355: ldc_w -30276568
    //   8358: ixor
    //   8359: ldc2_w -271676950
    //   8362: l2i
    //   8363: ldc_w -1256538652
    //   8366: ixor
    //   8367: ixor
    //   8368: lookupswitch default -> 15994, -674337860 -> 8396, 2140276133 -> 8351
    //   8396: aload_1
    //   8397: ldc2_w 323457391
    //   8400: l2i
    //   8401: ldc_w 323457390
    //   8404: ixor
    //   8405: aaload
    //   8406: ldc_w '返㌖辿좵ض'
    //   8409: getstatic Perryc.0 : I
    //   8412: ifle -> 8426
    //   8415: ldc2_w -304108653
    //   8418: l2i
    //   8419: ldc_w -597996368
    //   8422: ixor
    //   8423: goto -> 8434
    //   8426: ldc2_w 258888507
    //   8429: l2i
    //   8430: ldc_w -1130920380
    //   8433: ixor
    //   8434: ldc2_w 1205213296
    //   8437: l2i
    //   8438: ldc_w -297232896
    //   8441: ixor
    //   8442: ixor
    //   8443: lookupswitch default -> 8468, -1743099565 -> 16008, -397871489 -> 8426
    //   8468: goto -> 8472
    //   8471: athrow
    //   8472: invokestatic 0 : (Ljava/lang/String;)Ljava/lang/String;
    //   8475: goto -> 8479
    //   8478: athrow
    //   8479: getstatic Perryc.c : I
    //   8482: iflt -> 8496
    //   8485: ldc2_w 1178929846
    //   8488: l2i
    //   8489: ldc_w 2109763898
    //   8492: ixor
    //   8493: goto -> 8504
    //   8496: ldc2_w -187133940
    //   8499: l2i
    //   8500: ldc_w -1479355761
    //   8503: ixor
    //   8504: ldc2_w -1521990501
    //   8507: l2i
    //   8508: ldc_w 956680071
    //   8511: ixor
    //   8512: ixor
    //   8513: lookupswitch default -> 15890, -1480001392 -> 8496, -817380961 -> 8540
    //   8540: goto -> 8544
    //   8543: athrow
    //   8544: invokevirtual equalsIgnoreCase : (Ljava/lang/String;)Z
    //   8547: goto -> 8551
    //   8550: athrow
    //   8551: ifeq -> 8565
    //   8554: ldc2_w 267750417
    //   8557: l2i
    //   8558: ldc_w 1477382127
    //   8561: ixor
    //   8562: goto -> 8573
    //   8565: ldc2_w 311062607
    //   8568: l2i
    //   8569: ldc_w 1165030320
    //   8572: ixor
    //   8573: ldc2_w -195155146
    //   8576: l2i
    //   8577: ldc_w 1088880912
    //   8580: ixor
    //   8581: ixor
    //   8582: tableswitch default -> 8554, -482104872 -> 8604, -482104871 -> 9545
    //   8604: getstatic Perryc.c : I
    //   8607: iflt -> 8621
    //   8610: ldc2_w 1534084758
    //   8613: l2i
    //   8614: ldc_w 848196939
    //   8617: ixor
    //   8618: goto -> 8629
    //   8621: ldc2_w 426511982
    //   8624: l2i
    //   8625: ldc_w 487701125
    //   8628: ixor
    //   8629: ldc2_w 1630804988
    //   8632: l2i
    //   8633: ldc_w 1966430639
    //   8636: ixor
    //   8637: ixor
    //   8638: lookupswitch default -> 8664, -672563675 -> 8621, 2113892750 -> 15874
    //   8664: aload_3
    //   8665: getstatic Perryc.c : I
    //   8668: iflt -> 8682
    //   8671: ldc2_w 811869872
    //   8674: l2i
    //   8675: ldc_w 1361051757
    //   8678: ixor
    //   8679: goto -> 8690
    //   8682: ldc2_w -529453502
    //   8685: l2i
    //   8686: ldc_w -32204092
    //   8689: ixor
    //   8690: ldc2_w 1621425693
    //   8693: l2i
    //   8694: ldc_w 815691091
    //   8697: ixor
    //   8698: ixor
    //   8699: lookupswitch default -> 8724, 684677262 -> 8682, 830385555 -> 16022
    //   8724: goto -> 8728
    //   8727: athrow
    //   8728: invokevirtual getSettings : ()Ljava/util/List;
    //   8731: goto -> 8735
    //   8734: athrow
    //   8735: getstatic Perryc.c : I
    //   8738: iflt -> 8752
    //   8741: ldc2_w -1789511077
    //   8744: l2i
    //   8745: ldc_w 1760878778
    //   8748: ixor
    //   8749: goto -> 8760
    //   8752: ldc2_w -311620049
    //   8755: l2i
    //   8756: ldc_w 1275919634
    //   8759: ixor
    //   8760: ldc2_w -866157882
    //   8763: l2i
    //   8764: ldc_w 1087436457
    //   8767: ixor
    //   8768: ixor
    //   8769: lookupswitch default -> 8796, -28375762 -> 8752, 1898796686 -> 16150
    //   8796: goto -> 8800
    //   8799: athrow
    //   8800: invokeinterface iterator : ()Ljava/util/Iterator;
    //   8805: goto -> 8809
    //   8808: athrow
    //   8809: getstatic Perryc.c : I
    //   8812: iflt -> 8826
    //   8815: ldc2_w -1514177309
    //   8818: l2i
    //   8819: ldc_w -1750644520
    //   8822: ixor
    //   8823: goto -> 8834
    //   8826: ldc2_w -1753353184
    //   8829: l2i
    //   8830: ldc_w 990020674
    //   8833: ixor
    //   8834: ldc2_w -1168791042
    //   8837: l2i
    //   8838: ldc_w 787829083
    //   8841: ixor
    //   8842: ixor
    //   8843: lookupswitch default -> 8868, -1497838434 -> 15944, -1400975488 -> 8826
    //   8868: astore #4
    //   8870: getstatic Perryc.0 : I
    //   8873: ifle -> 8887
    //   8876: ldc2_w -944251794
    //   8879: l2i
    //   8880: ldc_w -1800648888
    //   8883: ixor
    //   8884: goto -> 8895
    //   8887: ldc2_w 1977520926
    //   8890: l2i
    //   8891: ldc_w 1312180717
    //   8894: ixor
    //   8895: ldc2_w -309745264
    //   8898: l2i
    //   8899: ldc_w -499883036
    //   8902: ixor
    //   8903: ixor
    //   8904: lookupswitch default -> 16124, 877990023 -> 8932, 1554403666 -> 8887
    //   8932: aload #4
    //   8934: getstatic Perryc.0 : I
    //   8937: ifle -> 8951
    //   8940: ldc2_w -770723772
    //   8943: l2i
    //   8944: ldc_w -1891460879
    //   8947: ixor
    //   8948: goto -> 8959
    //   8951: ldc2_w 591375914
    //   8954: l2i
    //   8955: ldc_w -1923048361
    //   8958: ixor
    //   8959: ldc2_w -1466930442
    //   8962: l2i
    //   8963: ldc_w 710354596
    //   8966: ixor
    //   8967: ixor
    //   8968: lookupswitch default -> 15900, -544578329 -> 8951, 748191279 -> 8996
    //   8996: goto -> 9000
    //   8999: athrow
    //   9000: invokeinterface hasNext : ()Z
    //   9005: goto -> 9009
    //   9008: athrow
    //   9009: ifeq -> 9023
    //   9012: ldc2_w -201232243
    //   9015: l2i
    //   9016: ldc_w -781816535
    //   9019: ixor
    //   9020: goto -> 9031
    //   9023: ldc2_w 1722758876
    //   9026: l2i
    //   9027: ldc_w 1137191783
    //   9030: ixor
    //   9031: ldc2_w -2028942705
    //   9034: l2i
    //   9035: ldc_w 1366984452
    //   9038: ixor
    //   9039: ixor
    //   9040: tableswitch default -> 9012, -217231313 -> 9064, -217231312 -> 9542
    //   9064: getstatic Perryc.c : I
    //   9067: iflt -> 9081
    //   9070: ldc2_w 596753369
    //   9073: l2i
    //   9074: ldc_w 1559656842
    //   9077: ixor
    //   9078: goto -> 9089
    //   9081: ldc2_w -783364221
    //   9084: l2i
    //   9085: ldc_w 814069361
    //   9088: ixor
    //   9089: ldc2_w -857070401
    //   9092: l2i
    //   9093: ldc_w -1227389418
    //   9096: ixor
    //   9097: ixor
    //   9098: lookupswitch default -> 9124, -2092083351 -> 9081, 89809146 -> 16038
    //   9124: aload #4
    //   9126: getstatic Perryc.c : I
    //   9129: iflt -> 9143
    //   9132: ldc2_w 1300151689
    //   9135: l2i
    //   9136: ldc_w -379353849
    //   9139: ixor
    //   9140: goto -> 9151
    //   9143: ldc2_w -297192369
    //   9146: l2i
    //   9147: ldc_w 1711059566
    //   9150: ixor
    //   9151: ldc2_w 1140102198
    //   9154: l2i
    //   9155: ldc_w -361667985
    //   9158: ixor
    //   9159: ixor
    //   9160: lookupswitch default -> 16140, 228118231 -> 9143, 573599864 -> 9188
    //   9188: goto -> 9192
    //   9191: athrow
    //   9192: invokeinterface next : ()Ljava/lang/Object;
    //   9197: goto -> 9201
    //   9200: athrow
    //   9201: checkcast bigname/zprestige/webhack/features/setting/Setting
    //   9204: getstatic Perryc.0 : I
    //   9207: ifle -> 9221
    //   9210: ldc2_w 2142035707
    //   9213: l2i
    //   9214: ldc_w -1785686904
    //   9217: ixor
    //   9218: goto -> 9229
    //   9221: ldc2_w -1567652863
    //   9224: l2i
    //   9225: ldc_w 1619939933
    //   9228: ixor
    //   9229: ldc2_w 1974929997
    //   9232: l2i
    //   9233: ldc_w 139784248
    //   9236: ixor
    //   9237: ixor
    //   9238: lookupswitch default -> 16164, -1746948090 -> 9221, -1075696599 -> 9264
    //   9264: astore #5
    //   9266: getstatic Perryc.0 : I
    //   9269: ifle -> 9283
    //   9272: ldc2_w 2097601992
    //   9275: l2i
    //   9276: ldc_w 786594616
    //   9279: ixor
    //   9280: goto -> 9291
    //   9283: ldc2_w 1430156250
    //   9286: l2i
    //   9287: ldc_w 1482270686
    //   9290: ixor
    //   9291: ldc2_w 1456961093
    //   9294: l2i
    //   9295: ldc_w -65842426
    //   9298: ixor
    //   9299: ixor
    //   9300: lookupswitch default -> 15866, -1482428089 -> 9328, -115309645 -> 9283
    //   9328: aload #5
    //   9330: getstatic Perryc.c : I
    //   9333: iflt -> 9347
    //   9336: ldc2_w 504894154
    //   9339: l2i
    //   9340: ldc_w 388542683
    //   9343: ixor
    //   9344: goto -> 9355
    //   9347: ldc2_w 630464982
    //   9350: l2i
    //   9351: ldc_w -1909984647
    //   9354: ixor
    //   9355: ldc2_w -587033278
    //   9358: l2i
    //   9359: ldc_w -1311827451
    //   9362: ixor
    //   9363: ixor
    //   9364: lookupswitch default -> 9392, -1742209535 -> 9347, 1711091030 -> 16218
    //   9392: aload #5
    //   9394: getstatic Perryc.0 : I
    //   9397: ifle -> 9411
    //   9400: ldc2_w -814965638
    //   9403: l2i
    //   9404: ldc_w 1717647351
    //   9407: ixor
    //   9408: goto -> 9419
    //   9411: ldc2_w 1848401279
    //   9414: l2i
    //   9415: ldc_w -951852018
    //   9418: ixor
    //   9419: ldc2_w -1500198483
    //   9422: l2i
    //   9423: ldc_w 1891215095
    //   9426: ixor
    //   9427: ixor
    //   9428: lookupswitch default -> 16204, 2132853975 -> 9411, 2135086635 -> 9456
    //   9456: goto -> 9460
    //   9459: athrow
    //   9460: invokevirtual getDefaultValue : ()Ljava/lang/Object;
    //   9463: goto -> 9467
    //   9466: athrow
    //   9467: getstatic Perryc.0 : I
    //   9470: ifle -> 9484
    //   9473: ldc2_w -108243382
    //   9476: l2i
    //   9477: ldc_w 658534984
    //   9480: ixor
    //   9481: goto -> 9492
    //   9484: ldc2_w -1382683981
    //   9487: l2i
    //   9488: ldc_w -102790833
    //   9491: ixor
    //   9492: ldc2_w 1077614660
    //   9495: l2i
    //   9496: ldc_w 1225657054
    //   9499: ixor
    //   9500: ixor
    //   9501: lookupswitch default -> 9528, -671533416 -> 16116, 593650747 -> 9484
    //   9528: goto -> 9532
    //   9531: athrow
    //   9532: invokevirtual setValue : (Ljava/lang/Object;)V
    //   9535: goto -> 9539
    //   9538: athrow
    //   9539: goto -> 8870
    //   9542: goto -> 9691
    //   9545: ldc_w '迲㌛辥좣٢慹๶筩嫝㜓ਣ䉞葢?ኦ辌埅剽ᭊ(侩敘뎪姠?'
    //   9548: getstatic Perryc.0 : I
    //   9551: ifle -> 9565
    //   9554: ldc2_w 220044195
    //   9557: l2i
    //   9558: ldc_w 1906309335
    //   9561: ixor
    //   9562: goto -> 9573
    //   9565: ldc2_w -480717122
    //   9568: l2i
    //   9569: ldc_w 1022861005
    //   9572: ixor
    //   9573: ldc2_w -1747603593
    //   9576: l2i
    //   9577: ldc_w 120259922
    //   9580: ixor
    //   9581: ixor
    //   9582: lookupswitch default -> 16046, -327366319 -> 9565, 1330766422 -> 9608
    //   9608: goto -> 9612
    //   9611: athrow
    //   9612: invokestatic 0 : (Ljava/lang/String;)Ljava/lang/String;
    //   9615: goto -> 9619
    //   9618: athrow
    //   9619: getstatic Perryc.c : I
    //   9622: iflt -> 9636
    //   9625: ldc2_w 474147850
    //   9628: l2i
    //   9629: ldc_w -210098657
    //   9632: ixor
    //   9633: goto -> 9644
    //   9636: ldc2_w 1427059646
    //   9639: l2i
    //   9640: ldc_w 194813941
    //   9643: ixor
    //   9644: ldc2_w 1265553613
    //   9647: l2i
    //   9648: ldc_w -537728763
    //   9651: ixor
    //   9652: ixor
    //   9653: lookupswitch default -> 15952, -904948349 -> 9680, 2074407901 -> 9636
    //   9680: goto -> 9684
    //   9683: athrow
    //   9684: invokestatic sendMessage : (Ljava/lang/String;)V
    //   9687: goto -> 9691
    //   9690: athrow
    //   9691: return
    //   9692: getstatic Perryc.c : I
    //   9695: iflt -> 9709
    //   9698: ldc2_w 678691549
    //   9701: l2i
    //   9702: ldc_w 1788518230
    //   9705: ixor
    //   9706: goto -> 9717
    //   9709: ldc2_w 1975904489
    //   9712: l2i
    //   9713: ldc_w 1267184240
    //   9716: ixor
    //   9717: ldc2_w -1098584411
    //   9720: l2i
    //   9721: ldc_w -865577074
    //   9724: ixor
    //   9725: ixor
    //   9726: lookupswitch default -> 9752, -126493760 -> 9709, 805446816 -> 16026
    //   9752: aload_1
    //   9753: arraylength
    //   9754: ldc2_w -1282296691
    //   9757: l2i
    //   9758: ldc_w -1282296695
    //   9761: ixor
    //   9762: if_icmpne -> 9776
    //   9765: ldc2_w -798058620
    //   9768: l2i
    //   9769: ldc_w -558889956
    //   9772: ixor
    //   9773: goto -> 9784
    //   9776: ldc2_w 1708439969
    //   9779: l2i
    //   9780: ldc_w 1795828280
    //   9783: ixor
    //   9784: ldc2_w -67044041
    //   9787: l2i
    //   9788: ldc_w 548618541
    //   9791: ixor
    //   9792: ixor
    //   9793: tableswitch default -> 9765, -764596350 -> 9816, -764596349 -> 9964
    //   9816: ldc_w '迶㌟辩좱ر慿ู筴嫙㜞ਮ䈘葿?ኢ迟埝剨ᬆ8侴攟'
    //   9819: getstatic Perryc.1 : I
    //   9822: ifeq -> 9836
    //   9825: ldc2_w -1663641743
    //   9828: l2i
    //   9829: ldc_w 1711214908
    //   9832: ixor
    //   9833: goto -> 9844
    //   9836: ldc2_w -2145822214
    //   9839: l2i
    //   9840: ldc_w 437545234
    //   9843: ixor
    //   9844: ldc2_w -328374687
    //   9847: l2i
    //   9848: ldc_w -246477847
    //   9851: ixor
    //   9852: ixor
    //   9853: lookupswitch default -> 16200, -2026939040 -> 9880, -468997179 -> 9836
    //   9880: goto -> 9884
    //   9883: athrow
    //   9884: invokestatic 0 : (Ljava/lang/String;)Ljava/lang/String;
    //   9887: goto -> 9891
    //   9890: athrow
    //   9891: getstatic Perryc.0 : I
    //   9894: ifle -> 9908
    //   9897: ldc2_w -2073269899
    //   9900: l2i
    //   9901: ldc_w -1848891354
    //   9904: ixor
    //   9905: goto -> 9916
    //   9908: ldc2_w 2003892425
    //   9911: l2i
    //   9912: ldc_w -1674751235
    //   9915: ixor
    //   9916: ldc2_w 925832293
    //   9919: l2i
    //   9920: ldc_w 1326197093
    //   9923: ixor
    //   9924: ixor
    //   9925: lookupswitch default -> 16176, -1820420300 -> 9952, 1837333587 -> 9908
    //   9952: goto -> 9956
    //   9955: athrow
    //   9956: invokestatic sendMessage : (Ljava/lang/String;)V
    //   9959: goto -> 9963
    //   9962: athrow
    //   9963: return
    //   9964: getstatic Perryc.c : I
    //   9967: iflt -> 9981
    //   9970: ldc2_w 1873606964
    //   9973: l2i
    //   9974: ldc_w -487181960
    //   9977: ixor
    //   9978: goto -> 9989
    //   9981: ldc2_w 1011437544
    //   9984: l2i
    //   9985: ldc_w 122800772
    //   9988: ixor
    //   9989: ldc2_w -594032898
    //   9992: l2i
    //   9993: ldc_w -1772307728
    //   9996: ixor
    //   9997: ixor
    //   9998: lookupswitch default -> 15982, -946752446 -> 9981, 1909717346 -> 10024
    //   10024: aload_1
    //   10025: arraylength
    //   10026: ldc2_w -140271840
    //   10029: l2i
    //   10030: ldc_w -140271835
    //   10033: ixor
    //   10034: if_icmpne -> 10048
    //   10037: ldc2_w 1809345100
    //   10040: l2i
    //   10041: ldc_w 303278371
    //   10044: ixor
    //   10045: goto -> 10056
    //   10048: ldc2_w 2036735690
    //   10051: l2i
    //   10052: ldc_w 11394394
    //   10055: ixor
    //   10056: ldc2_w -1190928798
    //   10059: l2i
    //   10060: ldc_w 1746725490
    //   10063: ixor
    //   10064: ixor
    //   10065: tableswitch default -> 10037, -1462438017 -> 10088, -1462438016 -> 15819
    //   10088: getstatic Perryc.0 : I
    //   10091: ifle -> 10105
    //   10094: ldc2_w -1793352616
    //   10097: l2i
    //   10098: ldc_w -524896120
    //   10101: ixor
    //   10102: goto -> 10113
    //   10105: ldc2_w 2052077621
    //   10108: l2i
    //   10109: ldc_w 1698150276
    //   10112: ixor
    //   10113: ldc2_w -156373091
    //   10116: l2i
    //   10117: ldc_w -1772544934
    //   10120: ixor
    //   10121: ixor
    //   10122: lookupswitch default -> 15986, 358209303 -> 10105, 2140372086 -> 10148
    //   10148: aload_3
    //   10149: getstatic Perryc.c : I
    //   10152: iflt -> 10166
    //   10155: ldc2_w 1879210808
    //   10158: l2i
    //   10159: ldc_w 208636227
    //   10162: ixor
    //   10163: goto -> 10174
    //   10166: ldc2_w 2145417101
    //   10169: l2i
    //   10170: ldc_w 1505832405
    //   10173: ixor
    //   10174: ldc2_w 1627958992
    //   10177: l2i
    //   10178: ldc_w -906114279
    //   10181: ixor
    //   10182: ixor
    //   10183: lookupswitch default -> 10208, -728197198 -> 16132, -384500202 -> 10166
    //   10208: aload_1
    //   10209: ldc2_w -465493910
    //   10212: l2i
    //   10213: ldc_w -465493912
    //   10216: ixor
    //   10217: aaload
    //   10218: getstatic Perryc.c : I
    //   10221: iflt -> 10235
    //   10224: ldc2_w -1593301148
    //   10227: l2i
    //   10228: ldc_w 2003895748
    //   10231: ixor
    //   10232: goto -> 10243
    //   10235: ldc2_w -94792445
    //   10238: l2i
    //   10239: ldc_w -1843279539
    //   10242: ixor
    //   10243: ldc2_w -882132039
    //   10246: l2i
    //   10247: ldc_w -1556415301
    //   10250: ixor
    //   10251: ixor
    //   10252: lookupswitch default -> 10280, -1104648798 -> 16168, 1254558706 -> 10235
    //   10280: goto -> 10284
    //   10283: athrow
    //   10284: invokevirtual getSettingByName : (Ljava/lang/String;)Lbigname/zprestige/webhack/features/setting/Setting;
    //   10287: goto -> 10291
    //   10290: athrow
    //   10291: dup
    //   10292: getstatic Perryc.c : I
    //   10295: iflt -> 10309
    //   10298: ldc2_w 1278286260
    //   10301: l2i
    //   10302: ldc_w -1349083434
    //   10305: ixor
    //   10306: goto -> 10317
    //   10309: ldc2_w 1612360429
    //   10312: l2i
    //   10313: ldc_w 2091618251
    //   10316: ixor
    //   10317: ldc2_w -64197542
    //   10320: l2i
    //   10321: ldc_w -1791943975
    //   10324: ixor
    //   10325: ixor
    //   10326: lookupswitch default -> 15962, -1967459871 -> 10309, 1974227877 -> 10352
    //   10352: astore_2
    //   10353: ifnull -> 10367
    //   10356: ldc2_w -312191929
    //   10359: l2i
    //   10360: ldc_w -14668581
    //   10363: ixor
    //   10364: goto -> 10375
    //   10367: ldc2_w 780601233
    //   10370: l2i
    //   10371: ldc_w 1019445006
    //   10374: ixor
    //   10375: ldc2_w -158484512
    //   10378: l2i
    //   10379: ldc_w 1992853785
    //   10382: ixor
    //   10383: ixor
    //   10384: tableswitch default -> 10356, -1845410203 -> 10408, -1845410202 -> 15819
    //   10408: new com/google/gson/JsonParser
    //   10411: dup
    //   10412: getstatic Perryc.1 : I
    //   10415: ifeq -> 10429
    //   10418: ldc2_w -1700979510
    //   10421: l2i
    //   10422: ldc_w -424132957
    //   10425: ixor
    //   10426: goto -> 10437
    //   10429: ldc2_w 930064217
    //   10432: l2i
    //   10433: ldc_w -380952758
    //   10436: ixor
    //   10437: ldc2_w 253857084
    //   10440: l2i
    //   10441: ldc_w -523124397
    //   10444: ixor
    //   10445: ixor
    //   10446: lookupswitch default -> 16032, -1814729210 -> 10429, 836039804 -> 10472
    //   10472: goto -> 10476
    //   10475: athrow
    //   10476: invokespecial <init> : ()V
    //   10479: goto -> 10483
    //   10482: athrow
    //   10483: getstatic Perryc.1 : I
    //   10486: ifeq -> 10500
    //   10489: ldc2_w 1160378634
    //   10492: l2i
    //   10493: ldc_w 1535222782
    //   10496: ixor
    //   10497: goto -> 10508
    //   10500: ldc2_w 2012015041
    //   10503: l2i
    //   10504: ldc_w 2018724082
    //   10507: ixor
    //   10508: ldc2_w -479868870
    //   10511: l2i
    //   10512: ldc_w -619050487
    //   10515: ixor
    //   10516: ixor
    //   10517: lookupswitch default -> 10544, 430412007 -> 10500, 651663559 -> 16028
    //   10544: astore #4
    //   10546: getstatic Perryc.1 : I
    //   10549: ifeq -> 10563
    //   10552: ldc2_w -1599501398
    //   10555: l2i
    //   10556: ldc_w 2035604301
    //   10559: ixor
    //   10560: goto -> 10571
    //   10563: ldc2_w -1204711229
    //   10566: l2i
    //   10567: ldc_w 1339523689
    //   10570: ixor
    //   10571: ldc2_w 1583938669
    //   10574: l2i
    //   10575: ldc_w -1323711672
    //   10578: ixor
    //   10579: ixor
    //   10580: lookupswitch default -> 15912, 412560783 -> 10608, 915173314 -> 10563
    //   10608: aload_2
    //   10609: getstatic Perryc.0 : I
    //   10612: ifle -> 10626
    //   10615: ldc2_w -89228621
    //   10618: l2i
    //   10619: ldc_w -473599054
    //   10622: ixor
    //   10623: goto -> 10634
    //   10626: ldc2_w 1012544790
    //   10629: l2i
    //   10630: ldc_w -1504171349
    //   10633: ixor
    //   10634: ldc2_w -325953505
    //   10637: l2i
    //   10638: ldc_w 762044046
    //   10641: ixor
    //   10642: ixor
    //   10643: lookupswitch default -> 10668, -661483632 -> 15932, -309683486 -> 10626
    //   10668: goto -> 10672
    //   10671: athrow
    //   10672: invokevirtual getType : ()Ljava/lang/String;
    //   10675: goto -> 10679
    //   10678: athrow
    //   10679: ldc_w '迵㌇达좹ج慽'
    //   10682: getstatic Perryc.c : I
    //   10685: iflt -> 10699
    //   10688: ldc2_w -1129653750
    //   10691: l2i
    //   10692: ldc_w 1018516326
    //   10695: ixor
    //   10696: goto -> 10707
    //   10699: ldc2_w -268363774
    //   10702: l2i
    //   10703: ldc_w -2083954673
    //   10706: ixor
    //   10707: ldc2_w 705056134
    //   10710: l2i
    //   10711: ldc_w -585440874
    //   10714: ixor
    //   10715: ixor
    //   10716: lookupswitch default -> 10744, 1014719827 -> 10699, 1996694908 -> 16142
    //   10744: goto -> 10748
    //   10747: athrow
    //   10748: invokestatic 0 : (Ljava/lang/String;)Ljava/lang/String;
    //   10751: goto -> 10755
    //   10754: athrow
    //   10755: getstatic Perryc.0 : I
    //   10758: ifle -> 10772
    //   10761: ldc2_w 1069510438
    //   10764: l2i
    //   10765: ldc_w -1976893574
    //   10768: ixor
    //   10769: goto -> 10780
    //   10772: ldc2_w -194263586
    //   10775: l2i
    //   10776: ldc_w -2119160704
    //   10779: ixor
    //   10780: ldc2_w -522416414
    //   10783: l2i
    //   10784: ldc_w -1120517609
    //   10787: ixor
    //   10788: ixor
    //   10789: lookupswitch default -> 10816, -394306391 -> 15896, 1302928052 -> 10772
    //   10816: goto -> 10820
    //   10819: athrow
    //   10820: invokevirtual equalsIgnoreCase : (Ljava/lang/String;)Z
    //   10823: goto -> 10827
    //   10826: athrow
    //   10827: ifeq -> 10841
    //   10830: ldc2_w -112328582
    //   10833: l2i
    //   10834: ldc_w 2013083103
    //   10837: ixor
    //   10838: goto -> 10849
    //   10841: ldc2_w 157342604
    //   10844: l2i
    //   10845: ldc_w -2016154070
    //   10848: ixor
    //   10849: ldc2_w 345918004
    //   10852: l2i
    //   10853: ldc_w -492414796
    //   10856: ixor
    //   10857: ixor
    //   10858: tableswitch default -> 10830, 2022385445 -> 10880, 2022385446 -> 12292
    //   10880: getstatic Perryc.0 : I
    //   10883: ifle -> 10897
    //   10886: ldc2_w 741228364
    //   10889: l2i
    //   10890: ldc_w -2108948951
    //   10893: ixor
    //   10894: goto -> 10905
    //   10897: ldc2_w -655356376
    //   10900: l2i
    //   10901: ldc_w -1483678560
    //   10904: ixor
    //   10905: ldc2_w -1710180556
    //   10908: l2i
    //   10909: ldc_w -365408561
    //   10912: ixor
    //   10913: ixor
    //   10914: lookupswitch default -> 16226, -565364578 -> 10897, 256387955 -> 10940
    //   10940: aload_2
    //   10941: getstatic Perryc.0 : I
    //   10944: ifle -> 10958
    //   10947: ldc2_w 1213829706
    //   10950: l2i
    //   10951: ldc_w 170578282
    //   10954: ixor
    //   10955: goto -> 10966
    //   10958: ldc2_w -1067598422
    //   10961: l2i
    //   10962: ldc_w 1920139406
    //   10965: ixor
    //   10966: ldc2_w 879074506
    //   10969: l2i
    //   10970: ldc_w 2010342927
    //   10973: ixor
    //   10974: ixor
    //   10975: lookupswitch default -> 11000, -1229797971 -> 10958, 29735397 -> 16228
    //   11000: aload_1
    //   11001: ldc2_w 1543303488
    //   11004: l2i
    //   11005: ldc_w 1543303491
    //   11008: ixor
    //   11009: aaload
    //   11010: getstatic Perryc.0 : I
    //   11013: ifle -> 11027
    //   11016: ldc2_w -895729365
    //   11019: l2i
    //   11020: ldc_w -50765644
    //   11023: ixor
    //   11024: goto -> 11035
    //   11027: ldc2_w 1458129257
    //   11030: l2i
    //   11031: ldc_w -20744902
    //   11034: ixor
    //   11035: ldc2_w 2121373041
    //   11038: l2i
    //   11039: ldc_w 349622874
    //   11042: ixor
    //   11043: ixor
    //   11044: lookupswitch default -> 16210, -1030915208 -> 11072, 1556244148 -> 11027
    //   11072: goto -> 11076
    //   11075: athrow
    //   11076: invokevirtual setValue : (Ljava/lang/Object;)V
    //   11079: goto -> 11083
    //   11082: athrow
    //   11083: new java/lang/StringBuilder
    //   11086: dup
    //   11087: getstatic Perryc.c : I
    //   11090: iflt -> 11104
    //   11093: ldc2_w -54159713
    //   11096: l2i
    //   11097: ldc_w 43270188
    //   11100: ixor
    //   11101: goto -> 11112
    //   11104: ldc2_w -1348401211
    //   11107: l2i
    //   11108: ldc_w 346653649
    //   11111: ixor
    //   11112: ldc2_w -896601420
    //   11115: l2i
    //   11116: ldc_w 711633059
    //   11119: ixor
    //   11120: ixor
    //   11121: lookupswitch default -> 16104, 515214500 -> 11104, 1542249987 -> 11148
    //   11148: goto -> 11152
    //   11151: athrow
    //   11152: invokespecial <init> : ()V
    //   11155: goto -> 11159
    //   11158: athrow
    //   11159: getstatic Perryc.c : I
    //   11162: iflt -> 11176
    //   11165: ldc2_w -826042150
    //   11168: l2i
    //   11169: ldc_w 348575614
    //   11172: ixor
    //   11173: goto -> 11184
    //   11176: ldc2_w -1775610114
    //   11179: l2i
    //   11180: ldc_w -1090161995
    //   11183: ixor
    //   11184: ldc2_w 607174575
    //   11187: l2i
    //   11188: ldc_w 1426153725
    //   11191: ixor
    //   11192: ixor
    //   11193: lookupswitch default -> 15980, -1422618378 -> 11176, 1478425369 -> 11220
    //   11220: getstatic com/mojang/realmsclient/gui/ChatFormatting.DARK_GRAY : Lcom/mojang/realmsclient/gui/ChatFormatting;
    //   11223: getstatic Perryc.0 : I
    //   11226: ifle -> 11240
    //   11229: ldc2_w 144165780
    //   11232: l2i
    //   11233: ldc_w 278385731
    //   11236: ixor
    //   11237: goto -> 11248
    //   11240: ldc2_w -428192570
    //   11243: l2i
    //   11244: ldc_w 49635751
    //   11247: ixor
    //   11248: ldc2_w 851317543
    //   11251: l2i
    //   11252: ldc_w 508916695
    //   11255: ixor
    //   11256: ixor
    //   11257: lookupswitch default -> 15922, -932950639 -> 11284, 887848743 -> 11240
    //   11284: goto -> 11288
    //   11287: athrow
    //   11288: invokevirtual append : (Ljava/lang/Object;)Ljava/lang/StringBuilder;
    //   11291: goto -> 11295
    //   11294: athrow
    //   11295: getstatic Perryc.0 : I
    //   11298: ifle -> 11312
    //   11301: ldc2_w 769553638
    //   11304: l2i
    //   11305: ldc_w -1545708238
    //   11308: ixor
    //   11309: goto -> 11320
    //   11312: ldc2_w -1199316295
    //   11315: l2i
    //   11316: ldc_w 1959945078
    //   11319: ixor
    //   11320: ldc2_w 1643003082
    //   11323: l2i
    //   11324: ldc_w 2130051168
    //   11327: ixor
    //   11328: ixor
    //   11329: lookupswitch default -> 11356, -1860692610 -> 16196, 195915972 -> 11312
    //   11356: aload_3
    //   11357: getstatic Perryc.1 : I
    //   11360: ifeq -> 11374
    //   11363: ldc2_w 104030002
    //   11366: l2i
    //   11367: ldc_w 1835265534
    //   11370: ixor
    //   11371: goto -> 11382
    //   11374: ldc2_w 1201481703
    //   11377: l2i
    //   11378: ldc_w -198709300
    //   11381: ixor
    //   11382: ldc2_w 2125472111
    //   11385: l2i
    //   11386: ldc_w 627805217
    //   11389: ixor
    //   11390: ixor
    //   11391: lookupswitch default -> 11416, 814423938 -> 15906, 1391935916 -> 11374
    //   11416: goto -> 11420
    //   11419: athrow
    //   11420: invokevirtual getName : ()Ljava/lang/String;
    //   11423: goto -> 11427
    //   11426: athrow
    //   11427: getstatic Perryc.0 : I
    //   11430: ifle -> 11444
    //   11433: ldc2_w 1869510345
    //   11436: l2i
    //   11437: ldc_w 853753353
    //   11440: ixor
    //   11441: goto -> 11452
    //   11444: ldc2_w -58902401
    //   11447: l2i
    //   11448: ldc_w -1962793363
    //   11451: ixor
    //   11452: ldc2_w -391559201
    //   11455: l2i
    //   11456: ldc_w 488159867
    //   11459: ixor
    //   11460: ixor
    //   11461: lookupswitch default -> 11488, -1472416412 -> 15960, 1273573972 -> 11444
    //   11488: goto -> 11492
    //   11491: athrow
    //   11492: invokevirtual append : (Ljava/lang/String;)Ljava/lang/StringBuilder;
    //   11495: goto -> 11499
    //   11498: athrow
    //   11499: ldc_w ' '
    //   11502: getstatic Perryc.1 : I
    //   11505: ifeq -> 11519
    //   11508: ldc2_w 202619599
    //   11511: l2i
    //   11512: ldc_w 1230726679
    //   11515: ixor
    //   11516: goto -> 11527
    //   11519: ldc2_w -1066386065
    //   11522: l2i
    //   11523: ldc_w -2016671082
    //   11526: ixor
    //   11527: ldc2_w 1343766329
    //   11530: l2i
    //   11531: ldc_w 1418477463
    //   11534: ixor
    //   11535: ixor
    //   11536: lookupswitch default -> 11564, -1703655143 -> 11519, 1104993398 -> 15830
    //   11564: goto -> 11568
    //   11567: athrow
    //   11568: invokevirtual append : (Ljava/lang/String;)Ljava/lang/StringBuilder;
    //   11571: goto -> 11575
    //   11574: athrow
    //   11575: getstatic Perryc.0 : I
    //   11578: ifle -> 11592
    //   11581: ldc2_w -1312281417
    //   11584: l2i
    //   11585: ldc_w -1756324471
    //   11588: ixor
    //   11589: goto -> 11600
    //   11592: ldc2_w 355301983
    //   11595: l2i
    //   11596: ldc_w -1827976957
    //   11599: ixor
    //   11600: ldc2_w 709081588
    //   11603: l2i
    //   11604: ldc_w -11637354
    //   11607: ixor
    //   11608: ixor
    //   11609: lookupswitch default -> 11636, -208312996 -> 16222, 1389226453 -> 11592
    //   11636: aload_2
    //   11637: getstatic Perryc.0 : I
    //   11640: ifle -> 11654
    //   11643: ldc2_w 215943881
    //   11646: l2i
    //   11647: ldc_w -1075032241
    //   11650: ixor
    //   11651: goto -> 11662
    //   11654: ldc2_w -764522931
    //   11657: l2i
    //   11658: ldc_w -473829156
    //   11661: ixor
    //   11662: ldc2_w -1191369016
    //   11665: l2i
    //   11666: ldc_w -662917059
    //   11669: ixor
    //   11670: ixor
    //   11671: lookupswitch default -> 15844, -743255181 -> 11654, 1361979492 -> 11696
    //   11696: goto -> 11700
    //   11699: athrow
    //   11700: invokevirtual getName : ()Ljava/lang/String;
    //   11703: goto -> 11707
    //   11706: athrow
    //   11707: getstatic Perryc.1 : I
    //   11710: ifeq -> 11724
    //   11713: ldc2_w -546388050
    //   11716: l2i
    //   11717: ldc_w -1630564253
    //   11720: ixor
    //   11721: goto -> 11732
    //   11724: ldc2_w 233477326
    //   11727: l2i
    //   11728: ldc_w 1696849102
    //   11731: ixor
    //   11732: ldc2_w -623051342
    //   11735: l2i
    //   11736: ldc_w -1348111100
    //   11739: ixor
    //   11740: ixor
    //   11741: lookupswitch default -> 11768, -85951124 -> 11724, 886628219 -> 16148
    //   11768: goto -> 11772
    //   11771: athrow
    //   11772: invokevirtual append : (Ljava/lang/String;)Ljava/lang/StringBuilder;
    //   11775: goto -> 11779
    //   11778: athrow
    //   11779: ldc_w '辆㌛辭좣٢慸๼筪媜㜎ਢ䈊萦?ኬ迟'
    //   11782: getstatic Perryc.0 : I
    //   11785: ifle -> 11799
    //   11788: ldc2_w -573554570
    //   11791: l2i
    //   11792: ldc_w 3132990
    //   11795: ixor
    //   11796: goto -> 11807
    //   11799: ldc2_w 299411858
    //   11802: l2i
    //   11803: ldc_w 1843212489
    //   11806: ixor
    //   11807: ldc2_w -2096629127
    //   11810: l2i
    //   11811: ldc_w 644156698
    //   11814: ixor
    //   11815: ixor
    //   11816: lookupswitch default -> 16068, -647533000 -> 11844, 2023586091 -> 11799
    //   11844: goto -> 11848
    //   11847: athrow
    //   11848: invokestatic 0 : (Ljava/lang/String;)Ljava/lang/String;
    //   11851: goto -> 11855
    //   11854: athrow
    //   11855: getstatic Perryc.c : I
    //   11858: iflt -> 11872
    //   11861: ldc2_w -794919130
    //   11864: l2i
    //   11865: ldc_w 47531535
    //   11868: ixor
    //   11869: goto -> 11880
    //   11872: ldc2_w 10209970
    //   11875: l2i
    //   11876: ldc_w 1518817835
    //   11879: ixor
    //   11880: ldc2_w -481745881
    //   11883: l2i
    //   11884: ldc_w 733245478
    //   11887: ixor
    //   11888: ixor
    //   11889: lookupswitch default -> 11916, 448163112 -> 16024, 2136007700 -> 11872
    //   11916: goto -> 11920
    //   11919: athrow
    //   11920: invokevirtual append : (Ljava/lang/String;)Ljava/lang/StringBuilder;
    //   11923: goto -> 11927
    //   11926: athrow
    //   11927: getstatic Perryc.c : I
    //   11930: iflt -> 11944
    //   11933: ldc2_w -2001183358
    //   11936: l2i
    //   11937: ldc_w 1766625429
    //   11940: ixor
    //   11941: goto -> 11952
    //   11944: ldc2_w 1222438393
    //   11947: l2i
    //   11948: ldc_w -655851221
    //   11951: ixor
    //   11952: ldc2_w -1295696080
    //   11955: l2i
    //   11956: ldc_w 315758253
    //   11959: ixor
    //   11960: ixor
    //   11961: lookupswitch default -> 15920, 807617871 -> 11988, 1105454218 -> 11944
    //   11988: aload_1
    //   11989: ldc2_w 459220293
    //   11992: l2i
    //   11993: ldc_w 459220294
    //   11996: ixor
    //   11997: aaload
    //   11998: getstatic Perryc.c : I
    //   12001: iflt -> 12015
    //   12004: ldc2_w 596996059
    //   12007: l2i
    //   12008: ldc_w 1917065884
    //   12011: ixor
    //   12012: goto -> 12023
    //   12015: ldc2_w -7445584
    //   12018: l2i
    //   12019: ldc_w 840329023
    //   12022: ixor
    //   12023: ldc2_w 596338519
    //   12026: l2i
    //   12027: ldc_w 1373683711
    //   12030: ixor
    //   12031: ixor
    //   12032: lookupswitch default -> 16234, -1074537433 -> 12060, 599436783 -> 12015
    //   12060: goto -> 12064
    //   12063: athrow
    //   12064: invokevirtual append : (Ljava/lang/String;)Ljava/lang/StringBuilder;
    //   12067: goto -> 12071
    //   12070: athrow
    //   12071: ldc_w '.'
    //   12074: getstatic Perryc.c : I
    //   12077: iflt -> 12091
    //   12080: ldc2_w 1057441023
    //   12083: l2i
    //   12084: ldc_w -240304678
    //   12087: ixor
    //   12088: goto -> 12099
    //   12091: ldc2_w 1311950349
    //   12094: l2i
    //   12095: ldc_w -1870353437
    //   12098: ixor
    //   12099: ldc2_w -1173591599
    //   12102: l2i
    //   12103: ldc_w -1611706249
    //   12106: ixor
    //   12107: ixor
    //   12108: lookupswitch default -> 16112, -347520893 -> 12091, -78293944 -> 12136
    //   12136: goto -> 12140
    //   12139: athrow
    //   12140: invokevirtual append : (Ljava/lang/String;)Ljava/lang/StringBuilder;
    //   12143: goto -> 12147
    //   12146: athrow
    //   12147: getstatic Perryc.c : I
    //   12150: iflt -> 12164
    //   12153: ldc2_w 2063961482
    //   12156: l2i
    //   12157: ldc_w -528726019
    //   12160: ixor
    //   12161: goto -> 12172
    //   12164: ldc2_w 1189978857
    //   12167: l2i
    //   12168: ldc_w 667083971
    //   12171: ixor
    //   12172: ldc2_w -1011578770
    //   12175: l2i
    //   12176: ldc_w 1838681347
    //   12179: ixor
    //   12180: ixor
    //   12181: lookupswitch default -> 16136, -821836985 -> 12208, 894783258 -> 12164
    //   12208: goto -> 12212
    //   12211: athrow
    //   12212: invokevirtual toString : ()Ljava/lang/String;
    //   12215: goto -> 12219
    //   12218: athrow
    //   12219: getstatic Perryc.1 : I
    //   12222: ifeq -> 12236
    //   12225: ldc2_w 1949161928
    //   12228: l2i
    //   12229: ldc_w 1335958422
    //   12232: ixor
    //   12233: goto -> 12244
    //   12236: ldc2_w 553332634
    //   12239: l2i
    //   12240: ldc_w -488066344
    //   12243: ixor
    //   12244: ldc2_w -735648829
    //   12247: l2i
    //   12248: ldc_w -1061451296
    //   12251: ixor
    //   12252: ixor
    //   12253: lookupswitch default -> 12280, -970215237 -> 12236, 789686397 -> 15928
    //   12280: goto -> 12284
    //   12283: athrow
    //   12284: invokestatic sendMessage : (Ljava/lang/String;)V
    //   12287: goto -> 12291
    //   12290: athrow
    //   12291: return
    //   12292: getstatic Perryc.0 : I
    //   12295: ifle -> 12309
    //   12298: ldc2_w -1990860532
    //   12301: l2i
    //   12302: ldc_w 833446354
    //   12305: ixor
    //   12306: goto -> 12317
    //   12309: ldc2_w -508222611
    //   12312: l2i
    //   12313: ldc_w 2104902623
    //   12316: ixor
    //   12317: ldc2_w -1989442606
    //   12320: l2i
    //   12321: ldc_w -509723850
    //   12324: ixor
    //   12325: ixor
    //   12326: lookupswitch default -> 15916, -804440006 -> 12309, -197732266 -> 12352
    //   12352: aload_2
    //   12353: getstatic Perryc.0 : I
    //   12356: ifle -> 12370
    //   12359: ldc2_w -1289536321
    //   12362: l2i
    //   12363: ldc_w -971518904
    //   12366: ixor
    //   12367: goto -> 12378
    //   12370: ldc2_w -1553360436
    //   12373: l2i
    //   12374: ldc_w 579291329
    //   12377: ixor
    //   12378: ldc2_w 1640209267
    //   12381: l2i
    //   12382: ldc_w -289719274
    //   12385: ixor
    //   12386: ixor
    //   12387: lookupswitch default -> 16058, -95660142 -> 12370, 244741736 -> 12412
    //   12412: goto -> 12416
    //   12415: athrow
    //   12416: invokevirtual getName : ()Ljava/lang/String;
    //   12419: goto -> 12423
    //   12422: athrow
    //   12423: ldc_w '迣㌝辭좲خ慿๽'
    //   12426: getstatic Perryc.c : I
    //   12429: iflt -> 12443
    //   12432: ldc2_w 1819888991
    //   12435: l2i
    //   12436: ldc_w 148115381
    //   12439: ixor
    //   12440: goto -> 12451
    //   12443: ldc2_w 1394193321
    //   12446: l2i
    //   12447: ldc_w -1779890329
    //   12450: ixor
    //   12451: ldc2_w 1504811721
    //   12454: l2i
    //   12455: ldc_w -611684524
    //   12458: ixor
    //   12459: ixor
    //   12460: lookupswitch default -> 12488, -426330249 -> 15996, 199048329 -> 12443
    //   12488: goto -> 12492
    //   12491: athrow
    //   12492: invokestatic 0 : (Ljava/lang/String;)Ljava/lang/String;
    //   12495: goto -> 12499
    //   12498: athrow
    //   12499: getstatic Perryc.1 : I
    //   12502: ifeq -> 12516
    //   12505: ldc2_w -578455204
    //   12508: l2i
    //   12509: ldc_w -840448809
    //   12512: ixor
    //   12513: goto -> 12524
    //   12516: ldc2_w -738076498
    //   12519: l2i
    //   12520: ldc_w 433300297
    //   12523: ixor
    //   12524: ldc2_w -1860101912
    //   12527: l2i
    //   12528: ldc_w -1986418979
    //   12531: ixor
    //   12532: ixor
    //   12533: lookupswitch default -> 12560, 148505534 -> 15822, 2056741808 -> 12516
    //   12560: goto -> 12564
    //   12563: athrow
    //   12564: invokevirtual equalsIgnoreCase : (Ljava/lang/String;)Z
    //   12567: goto -> 12571
    //   12570: athrow
    //   12571: ifeq -> 12585
    //   12574: ldc2_w -1094678996
    //   12577: l2i
    //   12578: ldc_w 2042066185
    //   12581: ixor
    //   12582: goto -> 12593
    //   12585: ldc2_w -530612304
    //   12588: l2i
    //   12589: ldc_w 656968854
    //   12592: ixor
    //   12593: ldc2_w 1194251309
    //   12596: l2i
    //   12597: ldc_w 1143503205
    //   12600: ixor
    //   12601: ixor
    //   12602: tableswitch default -> 12574, -999203219 -> 12624, -999203218 -> 13423
    //   12624: getstatic Perryc.0 : I
    //   12627: ifle -> 12641
    //   12630: ldc2_w -236033315
    //   12633: l2i
    //   12634: ldc_w 1919510677
    //   12637: ixor
    //   12638: goto -> 12649
    //   12641: ldc2_w -237464510
    //   12644: l2i
    //   12645: ldc_w 530739225
    //   12648: ixor
    //   12649: ldc2_w -1801405432
    //   12652: l2i
    //   12653: ldc_w 1317240538
    //   12656: ixor
    //   12657: ixor
    //   12658: lookupswitch default -> 12684, -350936835 -> 12641, 1503969434 -> 16152
    //   12684: aload_1
    //   12685: ldc2_w -436800476
    //   12688: l2i
    //   12689: ldc_w -436800473
    //   12692: ixor
    //   12693: aaload
    //   12694: ldc_w '迒㌁边좵'
    //   12697: getstatic Perryc.1 : I
    //   12700: ifeq -> 12714
    //   12703: ldc2_w 90731467
    //   12706: l2i
    //   12707: ldc_w -1076077817
    //   12710: ixor
    //   12711: goto -> 12722
    //   12714: ldc2_w -586325302
    //   12717: l2i
    //   12718: ldc_w 2110802575
    //   12721: ixor
    //   12722: ldc2_w -1723518849
    //   12725: l2i
    //   12726: ldc_w -212429696
    //   12729: ixor
    //   12730: ixor
    //   12731: lookupswitch default -> 12756, -794325965 -> 16076, -446687564 -> 12714
    //   12756: goto -> 12760
    //   12759: athrow
    //   12760: invokestatic 0 : (Ljava/lang/String;)Ljava/lang/String;
    //   12763: goto -> 12767
    //   12766: athrow
    //   12767: getstatic Perryc.c : I
    //   12770: iflt -> 12784
    //   12773: ldc2_w 239210443
    //   12776: l2i
    //   12777: ldc_w 1218338749
    //   12780: ixor
    //   12781: goto -> 12792
    //   12784: ldc2_w -428536636
    //   12787: l2i
    //   12788: ldc_w -391885227
    //   12791: ixor
    //   12792: ldc2_w 975074816
    //   12795: l2i
    //   12796: ldc_w 351104512
    //   12799: ixor
    //   12800: ixor
    //   12801: lookupswitch default -> 12828, -234769430 -> 12784, 1747929206 -> 15834
    //   12828: goto -> 12832
    //   12831: athrow
    //   12832: invokevirtual equalsIgnoreCase : (Ljava/lang/String;)Z
    //   12835: goto -> 12839
    //   12838: athrow
    //   12839: ifeq -> 12853
    //   12842: ldc2_w -812139871
    //   12845: l2i
    //   12846: ldc_w -1962111777
    //   12849: ixor
    //   12850: goto -> 12861
    //   12853: ldc2_w -1334917123
    //   12856: l2i
    //   12857: ldc_w -185208448
    //   12860: ixor
    //   12861: ldc2_w -133754226
    //   12864: l2i
    //   12865: ldc_w -1281551147
    //   12868: ixor
    //   12869: ixor
    //   12870: tableswitch default -> 12842, 251736101 -> 12892, 251736102 -> 13023
    //   12892: getstatic Perryc.1 : I
    //   12895: ifeq -> 12909
    //   12898: ldc2_w 941865943
    //   12901: l2i
    //   12902: ldc_w 1515096971
    //   12905: ixor
    //   12906: goto -> 12917
    //   12909: ldc2_w 1388195307
    //   12912: l2i
    //   12913: ldc_w 116705181
    //   12916: ixor
    //   12917: ldc2_w -157420075
    //   12920: l2i
    //   12921: ldc_w -2014244578
    //   12924: ixor
    //   12925: ixor
    //   12926: lookupswitch default -> 12952, -1625250898 -> 12909, 318887063 -> 15898
    //   12952: aload_3
    //   12953: getstatic Perryc.1 : I
    //   12956: ifeq -> 12970
    //   12959: ldc2_w 294751742
    //   12962: l2i
    //   12963: ldc_w 5007897
    //   12966: ixor
    //   12967: goto -> 12978
    //   12970: ldc2_w -1157462119
    //   12973: l2i
    //   12974: ldc_w 1235614987
    //   12977: ixor
    //   12978: ldc2_w -1473022905
    //   12981: l2i
    //   12982: ldc_w -394827124
    //   12985: ixor
    //   12986: ixor
    //   12987: lookupswitch default -> 13012, 1369045292 -> 16004, 1627336843 -> 12970
    //   13012: goto -> 13016
    //   13015: athrow
    //   13016: invokevirtual enable : ()V
    //   13019: goto -> 13023
    //   13022: athrow
    //   13023: getstatic Perryc.c : I
    //   13026: iflt -> 13040
    //   13029: ldc2_w -686794427
    //   13032: l2i
    //   13033: ldc_w 1509429327
    //   13036: ixor
    //   13037: goto -> 13048
    //   13040: ldc2_w -314198510
    //   13043: l2i
    //   13044: ldc_w -1833738663
    //   13047: ixor
    //   13048: ldc2_w -1003151552
    //   13051: l2i
    //   13052: ldc_w 1539646450
    //   13055: ixor
    //   13056: ixor
    //   13057: lookupswitch default -> 16206, -536423175 -> 13084, 286815672 -> 13040
    //   13084: aload_1
    //   13085: ldc2_w 1115285474
    //   13088: l2i
    //   13089: ldc_w 1115285473
    //   13092: ixor
    //   13093: aaload
    //   13094: ldc_w '迀㌒辠좣ا'
    //   13097: getstatic Perryc.1 : I
    //   13100: ifeq -> 13114
    //   13103: ldc2_w -797942881
    //   13106: l2i
    //   13107: ldc_w 1793078316
    //   13110: ixor
    //   13111: goto -> 13122
    //   13114: ldc2_w -437906600
    //   13117: l2i
    //   13118: ldc_w 1149085510
    //   13121: ixor
    //   13122: ldc2_w 1077098436
    //   13125: l2i
    //   13126: ldc_w 1946348591
    //   13129: ixor
    //   13130: ixor
    //   13131: lookupswitch default -> 13156, -1902005160 -> 16166, -1448751630 -> 13114
    //   13156: goto -> 13160
    //   13159: athrow
    //   13160: invokestatic 0 : (Ljava/lang/String;)Ljava/lang/String;
    //   13163: goto -> 13167
    //   13166: athrow
    //   13167: getstatic Perryc.0 : I
    //   13170: ifle -> 13184
    //   13173: ldc2_w -1558445398
    //   13176: l2i
    //   13177: ldc_w 1247041621
    //   13180: ixor
    //   13181: goto -> 13192
    //   13184: ldc2_w -1226963281
    //   13187: l2i
    //   13188: ldc_w -1290172958
    //   13191: ixor
    //   13192: ldc2_w -920546609
    //   13195: l2i
    //   13196: ldc_w 1794246234
    //   13199: ixor
    //   13200: ixor
    //   13201: lookupswitch default -> 13228, 1251724906 -> 16202, 1613011122 -> 13184
    //   13228: goto -> 13232
    //   13231: athrow
    //   13232: invokevirtual equalsIgnoreCase : (Ljava/lang/String;)Z
    //   13235: goto -> 13239
    //   13238: athrow
    //   13239: ifeq -> 13253
    //   13242: ldc2_w 1291184123
    //   13245: l2i
    //   13246: ldc_w 1239805564
    //   13249: ixor
    //   13250: goto -> 13261
    //   13253: ldc2_w 504067703
    //   13256: l2i
    //   13257: ldc_w 454787063
    //   13260: ixor
    //   13261: ldc2_w 737843854
    //   13264: l2i
    //   13265: ldc_w 997435130
    //   13268: ixor
    //   13269: ixor
    //   13270: tableswitch default -> 13242, 362362355 -> 13292, 362362356 -> 13423
    //   13292: getstatic Perryc.c : I
    //   13295: iflt -> 13309
    //   13298: ldc2_w -1589126290
    //   13301: l2i
    //   13302: ldc_w -2144566370
    //   13305: ixor
    //   13306: goto -> 13317
    //   13309: ldc2_w -1270769866
    //   13312: l2i
    //   13313: ldc_w 1294460026
    //   13316: ixor
    //   13317: ldc2_w 1140811219
    //   13320: l2i
    //   13321: ldc_w 955012544
    //   13324: ixor
    //   13325: ixor
    //   13326: lookupswitch default -> 13352, -409317564 -> 13309, 1517840611 -> 16232
    //   13352: aload_3
    //   13353: getstatic Perryc.1 : I
    //   13356: ifeq -> 13370
    //   13359: ldc2_w 431875038
    //   13362: l2i
    //   13363: ldc_w -579151170
    //   13366: ixor
    //   13367: goto -> 13378
    //   13370: ldc2_w 1977971298
    //   13373: l2i
    //   13374: ldc_w 2086049789
    //   13377: ixor
    //   13378: ldc2_w -1447866178
    //   13381: l2i
    //   13382: ldc_w -1329036003
    //   13385: ixor
    //   13386: ixor
    //   13387: lookupswitch default -> 16126, -574821181 -> 13370, 281555004 -> 13412
    //   13412: goto -> 13416
    //   13415: athrow
    //   13416: invokevirtual disable : ()V
    //   13419: goto -> 13423
    //   13422: athrow
    //   13423: getstatic Perryc.c : I
    //   13426: iflt -> 13440
    //   13429: ldc2_w -783119606
    //   13432: l2i
    //   13433: ldc_w -1276797748
    //   13436: ixor
    //   13437: goto -> 13448
    //   13440: ldc2_w 891658961
    //   13443: l2i
    //   13444: ldc_w 364533309
    //   13447: ixor
    //   13448: ldc2_w 1956738110
    //   13451: l2i
    //   13452: ldc_w 1713159714
    //   13455: ixor
    //   13456: ixor
    //   13457: lookupswitch default -> 13484, 840909592 -> 13440, 1879760346 -> 15926
    //   13484: aload_3
    //   13485: getstatic Perryc.1 : I
    //   13488: ifeq -> 13502
    //   13491: ldc2_w 2069130735
    //   13494: l2i
    //   13495: ldc_w -797585449
    //   13498: ixor
    //   13499: goto -> 13510
    //   13502: ldc2_w 934135239
    //   13505: l2i
    //   13506: ldc_w 1225769195
    //   13509: ixor
    //   13510: ldc2_w 694656312
    //   13513: l2i
    //   13514: ldc_w -642676405
    //   13517: ixor
    //   13518: ixor
    //   13519: lookupswitch default -> 13544, -1057402828 -> 13502, 1542960715 -> 16030
    //   13544: aload_2
    //   13545: getstatic Perryc.c : I
    //   13548: iflt -> 13562
    //   13551: ldc2_w -432361275
    //   13554: l2i
    //   13555: ldc_w -1142265569
    //   13558: ixor
    //   13559: goto -> 13570
    //   13562: ldc2_w 387192605
    //   13565: l2i
    //   13566: ldc_w -484533218
    //   13569: ixor
    //   13570: ldc2_w -1370223026
    //   13573: l2i
    //   13574: ldc_w 1674415501
    //   13577: ixor
    //   13578: ixor
    //   13579: lookupswitch default -> 16174, -1874240999 -> 13562, 965937344 -> 13604
    //   13604: aload #4
    //   13606: getstatic Perryc.1 : I
    //   13609: ifeq -> 13623
    //   13612: ldc2_w -999762795
    //   13615: l2i
    //   13616: ldc_w -1749383900
    //   13619: ixor
    //   13620: goto -> 13631
    //   13623: ldc2_w -1353058265
    //   13626: l2i
    //   13627: ldc_w -13315053
    //   13630: ixor
    //   13631: ldc2_w 1753473880
    //   13634: l2i
    //   13635: ldc_w -1915179617
    //   13638: ixor
    //   13639: ixor
    //   13640: lookupswitch default -> 16172, -1254726925 -> 13668, -1232527498 -> 13623
    //   13668: aload_1
    //   13669: ldc2_w 1167927714
    //   13672: l2i
    //   13673: ldc_w 1167927713
    //   13676: ixor
    //   13677: aaload
    //   13678: getstatic Perryc.0 : I
    //   13681: ifle -> 13695
    //   13684: ldc2_w -712163566
    //   13687: l2i
    //   13688: ldc_w -292771660
    //   13691: ixor
    //   13692: goto -> 13703
    //   13695: ldc2_w -247441374
    //   13698: l2i
    //   13699: ldc_w -1217844841
    //   13702: ixor
    //   13703: ldc2_w 209621209
    //   13706: l2i
    //   13707: ldc_w -1714119961
    //   13710: ixor
    //   13711: ixor
    //   13712: lookupswitch default -> 13740, -1643752433 -> 13695, -1364484712 -> 15998
    //   13740: goto -> 13744
    //   13743: athrow
    //   13744: invokevirtual parse : (Ljava/lang/String;)Lcom/google/gson/JsonElement;
    //   13747: goto -> 13751
    //   13750: athrow
    //   13751: getstatic Perryc.0 : I
    //   13754: ifle -> 13768
    //   13757: ldc2_w -1905362478
    //   13760: l2i
    //   13761: ldc_w -702430782
    //   13764: ixor
    //   13765: goto -> 13776
    //   13768: ldc2_w 491504551
    //   13771: l2i
    //   13772: ldc_w -1131223056
    //   13775: ixor
    //   13776: ldc2_w -303564124
    //   13779: l2i
    //   13780: ldc_w -1133706570
    //   13783: ixor
    //   13784: ixor
    //   13785: lookupswitch default -> 13812, -1978921020 -> 13768, 163921922 -> 16242
    //   13812: goto -> 13816
    //   13815: athrow
    //   13816: invokestatic setValueFromJson : (Lbigname/zprestige/webhack/features/Feature;Lbigname/zprestige/webhack/features/setting/Setting;Lcom/google/gson/JsonElement;)V
    //   13819: goto -> 13823
    //   13822: athrow
    //   13823: goto -> 14612
    //   13826: getstatic Perryc.1 : I
    //   13829: ifeq -> 13843
    //   13832: ldc2_w 1930523977
    //   13835: l2i
    //   13836: ldc_w -1234911376
    //   13839: ixor
    //   13840: goto -> 13851
    //   13843: ldc2_w 1420211972
    //   13846: l2i
    //   13847: ldc_w 1655006338
    //   13850: ixor
    //   13851: ldc2_w 1794384775
    //   13854: l2i
    //   13855: ldc_w 557140026
    //   13858: ixor
    //   13859: ixor
    //   13860: lookupswitch default -> 16138, -1900764796 -> 13843, 2109913147 -> 13888
    //   13888: astore #5
    //   13890: new java/lang/StringBuilder
    //   13893: dup
    //   13894: getstatic Perryc.c : I
    //   13897: iflt -> 13911
    //   13900: ldc2_w 1112631571
    //   13903: l2i
    //   13904: ldc_w -1929273553
    //   13907: ixor
    //   13908: goto -> 13919
    //   13911: ldc2_w 1968859701
    //   13914: l2i
    //   13915: ldc_w 928042455
    //   13918: ixor
    //   13919: ldc2_w 1686755118
    //   13922: l2i
    //   13923: ldc_w 1637550105
    //   13926: ixor
    //   13927: ixor
    //   13928: lookupswitch default -> 13956, -901633781 -> 16086, 568911426 -> 13911
    //   13956: goto -> 13960
    //   13959: athrow
    //   13960: invokespecial <init> : ()V
    //   13963: goto -> 13967
    //   13966: athrow
    //   13967: ldc_w '迤㌒辨죰ؔ慻๵筡媝㝝ਓ䈖葯?ዣ辌城剽ᬞ$便敖돹姦?ᣟ⫐?헇摦쌱㮦'
    //   13970: getstatic Perryc.c : I
    //   13973: iflt -> 13987
    //   13976: ldc2_w -326982598
    //   13979: l2i
    //   13980: ldc_w -492486420
    //   13983: ixor
    //   13984: goto -> 13995
    //   13987: ldc2_w 1714839977
    //   13990: l2i
    //   13991: ldc_w -828096157
    //   13994: ixor
    //   13995: ldc2_w -2044977090
    //   13998: l2i
    //   13999: ldc_w 974846879
    //   14002: ixor
    //   14003: ixor
    //   14004: lookupswitch default -> 16066, -1306443913 -> 13987, 345308011 -> 14032
    //   14032: goto -> 14036
    //   14035: athrow
    //   14036: invokestatic 0 : (Ljava/lang/String;)Ljava/lang/String;
    //   14039: goto -> 14043
    //   14042: athrow
    //   14043: getstatic Perryc.1 : I
    //   14046: ifeq -> 14060
    //   14049: ldc2_w 779768166
    //   14052: l2i
    //   14053: ldc_w -1677055941
    //   14056: ixor
    //   14057: goto -> 14068
    //   14060: ldc2_w 1541462449
    //   14063: l2i
    //   14064: ldc_w 1008229485
    //   14067: ixor
    //   14068: ldc2_w -271327384
    //   14071: l2i
    //   14072: ldc_w 359824801
    //   14075: ixor
    //   14076: ixor
    //   14077: lookupswitch default -> 16088, -1655101675 -> 14104, 1221712788 -> 14060
    //   14104: goto -> 14108
    //   14107: athrow
    //   14108: invokevirtual append : (Ljava/lang/String;)Ljava/lang/StringBuilder;
    //   14111: goto -> 14115
    //   14114: athrow
    //   14115: getstatic Perryc.c : I
    //   14118: iflt -> 14132
    //   14121: ldc2_w -1844601164
    //   14124: l2i
    //   14125: ldc_w 753244031
    //   14128: ixor
    //   14129: goto -> 14140
    //   14132: ldc2_w 1651388608
    //   14135: l2i
    //   14136: ldc_w -1895129028
    //   14139: ixor
    //   14140: ldc2_w -1455003247
    //   14143: l2i
    //   14144: ldc_w -676331731
    //   14147: ixor
    //   14148: ixor
    //   14149: lookupswitch default -> 15914, -1819474368 -> 14176, -1073635465 -> 14132
    //   14176: aload_2
    //   14177: getstatic Perryc.1 : I
    //   14180: ifeq -> 14194
    //   14183: ldc2_w -1982936272
    //   14186: l2i
    //   14187: ldc_w -1935360047
    //   14190: ixor
    //   14191: goto -> 14202
    //   14194: ldc2_w -1588810186
    //   14197: l2i
    //   14198: ldc_w -477432464
    //   14201: ixor
    //   14202: ldc2_w 2090612450
    //   14205: l2i
    //   14206: ldc_w -150728378
    //   14209: ixor
    //   14210: ixor
    //   14211: lookupswitch default -> 14236, -1896721595 -> 15880, -378525682 -> 14194
    //   14236: goto -> 14240
    //   14239: athrow
    //   14240: invokevirtual getType : ()Ljava/lang/String;
    //   14243: goto -> 14247
    //   14246: athrow
    //   14247: getstatic Perryc.c : I
    //   14250: iflt -> 14264
    //   14253: ldc2_w 206044795
    //   14256: l2i
    //   14257: ldc_w -734877687
    //   14260: ixor
    //   14261: goto -> 14272
    //   14264: ldc2_w 1504200456
    //   14267: l2i
    //   14268: ldc_w 684149574
    //   14271: ixor
    //   14272: ldc2_w 669077494
    //   14275: l2i
    //   14276: ldc_w -1818039620
    //   14279: ixor
    //   14280: ixor
    //   14281: lookupswitch default -> 14308, -210130458 -> 14264, 1815540536 -> 16060
    //   14308: goto -> 14312
    //   14311: athrow
    //   14312: invokevirtual append : (Ljava/lang/String;)Ljava/lang/StringBuilder;
    //   14315: goto -> 14319
    //   14318: athrow
    //   14319: ldc_w '辆㌅辭좼ط慿ื'
    //   14322: getstatic Perryc.c : I
    //   14325: iflt -> 14339
    //   14328: ldc2_w -1663665570
    //   14331: l2i
    //   14332: ldc_w 1950223974
    //   14335: ixor
    //   14336: goto -> 14347
    //   14339: ldc2_w -750694081
    //   14342: l2i
    //   14343: ldc_w 1204554299
    //   14346: ixor
    //   14347: ldc2_w -395831746
    //   14350: l2i
    //   14351: ldc_w 360501854
    //   14354: ixor
    //   14355: ixor
    //   14356: lookupswitch default -> 14384, -512562690 -> 14339, 368881752 -> 15918
    //   14384: goto -> 14388
    //   14387: athrow
    //   14388: invokestatic 0 : (Ljava/lang/String;)Ljava/lang/String;
    //   14391: goto -> 14395
    //   14394: athrow
    //   14395: getstatic Perryc.0 : I
    //   14398: ifle -> 14412
    //   14401: ldc2_w 1245554786
    //   14404: l2i
    //   14405: ldc_w 1367333027
    //   14408: ixor
    //   14409: goto -> 14420
    //   14412: ldc2_w -352958890
    //   14415: l2i
    //   14416: ldc_w 1977717050
    //   14419: ixor
    //   14420: ldc2_w 1069976386
    //   14423: l2i
    //   14424: ldc_w 888305758
    //   14427: ixor
    //   14428: ixor
    //   14429: lookupswitch default -> 14456, 276202461 -> 16128, 1850118679 -> 14412
    //   14456: goto -> 14460
    //   14459: athrow
    //   14460: invokevirtual append : (Ljava/lang/String;)Ljava/lang/StringBuilder;
    //   14463: goto -> 14467
    //   14466: athrow
    //   14467: getstatic Perryc.1 : I
    //   14470: ifeq -> 14484
    //   14473: ldc2_w -549672623
    //   14476: l2i
    //   14477: ldc_w 1567096383
    //   14480: ixor
    //   14481: goto -> 14492
    //   14484: ldc2_w 153597334
    //   14487: l2i
    //   14488: ldc_w -2029650677
    //   14491: ixor
    //   14492: ldc2_w 1683838814
    //   14495: l2i
    //   14496: ldc_w -756340775
    //   14499: ixor
    //   14500: ixor
    //   14501: lookupswitch default -> 15934, 887957481 -> 14484, 949237786 -> 14528
    //   14528: goto -> 14532
    //   14531: athrow
    //   14532: invokevirtual toString : ()Ljava/lang/String;
    //   14535: goto -> 14539
    //   14538: athrow
    //   14539: getstatic Perryc.c : I
    //   14542: iflt -> 14556
    //   14545: ldc2_w 27179051
    //   14548: l2i
    //   14549: ldc_w -1643366364
    //   14552: ixor
    //   14553: goto -> 14564
    //   14556: ldc2_w -1522842848
    //   14559: l2i
    //   14560: ldc_w 1354759496
    //   14563: ixor
    //   14564: ldc2_w 627748222
    //   14567: l2i
    //   14568: ldc_w -1020506316
    //   14571: ixor
    //   14572: ixor
    //   14573: lookupswitch default -> 14600, 1366882778 -> 14556, 2043961925 -> 16102
    //   14600: goto -> 14604
    //   14603: athrow
    //   14604: invokestatic sendMessage : (Ljava/lang/String;)V
    //   14607: goto -> 14611
    //   14610: athrow
    //   14611: return
    //   14612: new java/lang/StringBuilder
    //   14615: dup
    //   14616: getstatic Perryc.0 : I
    //   14619: ifle -> 14633
    //   14622: ldc2_w -1417657501
    //   14625: l2i
    //   14626: ldc_w -534136360
    //   14629: ixor
    //   14630: goto -> 14641
    //   14633: ldc2_w -38235719
    //   14636: l2i
    //   14637: ldc_w 61424028
    //   14640: ixor
    //   14641: ldc2_w -1149099666
    //   14644: l2i
    //   14645: ldc_w -1315666993
    //   14648: ixor
    //   14649: ixor
    //   14650: lookupswitch default -> 14676, 764726002 -> 14633, 1103058970 -> 16090
    //   14676: goto -> 14680
    //   14679: athrow
    //   14680: invokespecial <init> : ()V
    //   14683: goto -> 14687
    //   14686: athrow
    //   14687: getstatic Perryc.0 : I
    //   14690: ifle -> 14704
    //   14693: ldc2_w -9702905
    //   14696: l2i
    //   14697: ldc_w -654281233
    //   14700: ixor
    //   14701: goto -> 14712
    //   14704: ldc2_w 1961140924
    //   14707: l2i
    //   14708: ldc_w -1115988929
    //   14711: ixor
    //   14712: ldc2_w -1426301549
    //   14715: l2i
    //   14716: ldc_w -159488385
    //   14719: ixor
    //   14720: ixor
    //   14721: lookupswitch default -> 14748, -1175266447 -> 14704, 2062138372 -> 15848
    //   14748: getstatic com/mojang/realmsclient/gui/ChatFormatting.GRAY : Lcom/mojang/realmsclient/gui/ChatFormatting;
    //   14751: getstatic Perryc.1 : I
    //   14754: ifeq -> 14768
    //   14757: ldc2_w -223776796
    //   14760: l2i
    //   14761: ldc_w 1074296093
    //   14764: ixor
    //   14765: goto -> 14776
    //   14768: ldc2_w -690300913
    //   14771: l2i
    //   14772: ldc_w 1561226264
    //   14775: ixor
    //   14776: ldc2_w 1277554388
    //   14779: l2i
    //   14780: ldc_w -480240861
    //   14783: ixor
    //   14784: ixor
    //   14785: lookupswitch default -> 16016, 501542670 -> 14768, 613499360 -> 14812
    //   14812: goto -> 14816
    //   14815: athrow
    //   14816: invokevirtual append : (Ljava/lang/Object;)Ljava/lang/StringBuilder;
    //   14819: goto -> 14823
    //   14822: athrow
    //   14823: getstatic Perryc.1 : I
    //   14826: ifeq -> 14840
    //   14829: ldc2_w 217467154
    //   14832: l2i
    //   14833: ldc_w 211538810
    //   14836: ixor
    //   14837: goto -> 14848
    //   14840: ldc2_w -75312426
    //   14843: l2i
    //   14844: ldc_w -1290502018
    //   14847: ixor
    //   14848: ldc2_w -820518246
    //   14851: l2i
    //   14852: ldc_w 1490565776
    //   14855: ixor
    //   14856: ixor
    //   14857: lookupswitch default -> 15820, -1750973854 -> 14840, -547779934 -> 14884
    //   14884: aload_3
    //   14885: getstatic Perryc.c : I
    //   14888: iflt -> 14902
    //   14891: ldc2_w -1082264146
    //   14894: l2i
    //   14895: ldc_w -621184562
    //   14898: ixor
    //   14899: goto -> 14910
    //   14902: ldc2_w 908936653
    //   14905: l2i
    //   14906: ldc_w 1820008145
    //   14909: ixor
    //   14910: ldc2_w 1790249241
    //   14913: l2i
    //   14914: ldc_w -145654830
    //   14917: ixor
    //   14918: ixor
    //   14919: lookupswitch default -> 14944, -1769928021 -> 14902, -127861077 -> 16110
    //   14944: goto -> 14948
    //   14947: athrow
    //   14948: invokevirtual getName : ()Ljava/lang/String;
    //   14951: goto -> 14955
    //   14954: athrow
    //   14955: getstatic Perryc.1 : I
    //   14958: ifeq -> 14972
    //   14961: ldc2_w 1892597835
    //   14964: l2i
    //   14965: ldc_w 259014107
    //   14968: ixor
    //   14969: goto -> 14980
    //   14972: ldc2_w 1176520236
    //   14975: l2i
    //   14976: ldc_w 1808997553
    //   14979: ixor
    //   14980: ldc2_w 234395011
    //   14983: l2i
    //   14984: ldc_w -1230238749
    //   14987: ixor
    //   14988: ixor
    //   14989: lookupswitch default -> 15016, -2093102511 -> 14972, -991271952 -> 16108
    //   15016: goto -> 15020
    //   15019: athrow
    //   15020: invokevirtual append : (Ljava/lang/String;)Ljava/lang/StringBuilder;
    //   15023: goto -> 15027
    //   15026: athrow
    //   15027: ldc_w ' '
    //   15030: getstatic Perryc.1 : I
    //   15033: ifeq -> 15047
    //   15036: ldc2_w 1123246546
    //   15039: l2i
    //   15040: ldc_w 1007983987
    //   15043: ixor
    //   15044: goto -> 15055
    //   15047: ldc2_w 1632918565
    //   15050: l2i
    //   15051: ldc_w 582852765
    //   15054: ixor
    //   15055: ldc2_w -857881315
    //   15058: l2i
    //   15059: ldc_w 1458941823
    //   15062: ixor
    //   15063: ixor
    //   15064: lookupswitch default -> 15892, -641624358 -> 15092, -456157501 -> 15047
    //   15092: goto -> 15096
    //   15095: athrow
    //   15096: invokevirtual append : (Ljava/lang/String;)Ljava/lang/StringBuilder;
    //   15099: goto -> 15103
    //   15102: athrow
    //   15103: getstatic Perryc.0 : I
    //   15106: ifle -> 15120
    //   15109: ldc2_w 1601273618
    //   15112: l2i
    //   15113: ldc_w 999486502
    //   15116: ixor
    //   15117: goto -> 15128
    //   15120: ldc2_w -1631978806
    //   15123: l2i
    //   15124: ldc_w 1882114909
    //   15127: ixor
    //   15128: ldc2_w 2092978054
    //   15131: l2i
    //   15132: ldc_w -1504499905
    //   15135: ixor
    //   15136: ixor
    //   15137: lookupswitch default -> 15978, -1099897971 -> 15120, 872700206 -> 15164
    //   15164: aload_2
    //   15165: getstatic Perryc.1 : I
    //   15168: ifeq -> 15182
    //   15171: ldc2_w -859176858
    //   15174: l2i
    //   15175: ldc_w 693175502
    //   15178: ixor
    //   15179: goto -> 15190
    //   15182: ldc2_w -1526058970
    //   15185: l2i
    //   15186: ldc_w 626612090
    //   15189: ixor
    //   15190: ldc2_w -1117942617
    //   15193: l2i
    //   15194: ldc_w 1909391572
    //   15197: ixor
    //   15198: ixor
    //   15199: lookupswitch default -> 16084, 688490715 -> 15182, 1287777071 -> 15224
    //   15224: goto -> 15228
    //   15227: athrow
    //   15228: invokevirtual getName : ()Ljava/lang/String;
    //   15231: goto -> 15235
    //   15234: athrow
    //   15235: getstatic Perryc.0 : I
    //   15238: ifle -> 15252
    //   15241: ldc2_w -1096594111
    //   15244: l2i
    //   15245: ldc_w 2002535079
    //   15248: ixor
    //   15249: goto -> 15260
    //   15252: ldc2_w 63327581
    //   15255: l2i
    //   15256: ldc_w -2096335148
    //   15259: ixor
    //   15260: ldc2_w -704324751
    //   15263: l2i
    //   15264: ldc_w -107304789
    //   15267: ixor
    //   15268: ixor
    //   15269: lookupswitch default -> 15296, -429818820 -> 16010, 6800470 -> 15252
    //   15296: goto -> 15300
    //   15299: athrow
    //   15300: invokevirtual append : (Ljava/lang/String;)Ljava/lang/StringBuilder;
    //   15303: goto -> 15307
    //   15306: athrow
    //   15307: ldc_w '辆㌛辭좣٢慸๼筪媜㜎ਢ䈊萦?ኬ迟'
    //   15310: getstatic Perryc.0 : I
    //   15313: ifle -> 15327
    //   15316: ldc2_w -5215639
    //   15319: l2i
    //   15320: ldc_w -742633709
    //   15323: ixor
    //   15324: goto -> 15335
    //   15327: ldc2_w 1427391964
    //   15330: l2i
    //   15331: ldc_w -1727081629
    //   15334: ixor
    //   15335: ldc2_w -1182871956
    //   15338: l2i
    //   15339: ldc_w -206597437
    //   15342: ixor
    //   15343: ixor
    //   15344: lookupswitch default -> 15864, -2033464816 -> 15372, 1725790677 -> 15327
    //   15372: goto -> 15376
    //   15375: athrow
    //   15376: invokestatic 0 : (Ljava/lang/String;)Ljava/lang/String;
    //   15379: goto -> 15383
    //   15382: athrow
    //   15383: getstatic Perryc.1 : I
    //   15386: ifeq -> 15400
    //   15389: ldc2_w 210440827
    //   15392: l2i
    //   15393: ldc_w -1425972879
    //   15396: ixor
    //   15397: goto -> 15408
    //   15400: ldc2_w -2132219348
    //   15403: l2i
    //   15404: ldc_w -1719964502
    //   15407: ixor
    //   15408: ldc2_w 1533521196
    //   15411: l2i
    //   15412: ldc_w 1977253444
    //   15415: ixor
    //   15416: ixor
    //   15417: lookupswitch default -> 15876, -1992843166 -> 15400, 925783534 -> 15444
    //   15444: goto -> 15448
    //   15447: athrow
    //   15448: invokevirtual append : (Ljava/lang/String;)Ljava/lang/StringBuilder;
    //   15451: goto -> 15455
    //   15454: athrow
    //   15455: getstatic Perryc.0 : I
    //   15458: ifle -> 15472
    //   15461: ldc2_w -754852090
    //   15464: l2i
    //   15465: ldc_w 1636165346
    //   15468: ixor
    //   15469: goto -> 15480
    //   15472: ldc2_w 1108610424
    //   15475: l2i
    //   15476: ldc_w 1396492709
    //   15479: ixor
    //   15480: ldc2_w -534490228
    //   15483: l2i
    //   15484: ldc_w -431471843
    //   15487: ixor
    //   15488: ixor
    //   15489: lookupswitch default -> 15826, -1259853451 -> 15472, 390386764 -> 15516
    //   15516: aload_1
    //   15517: ldc2_w -1923199320
    //   15520: l2i
    //   15521: ldc_w -1923199317
    //   15524: ixor
    //   15525: aaload
    //   15526: getstatic Perryc.c : I
    //   15529: iflt -> 15543
    //   15532: ldc2_w 1105300440
    //   15535: l2i
    //   15536: ldc_w 459739732
    //   15539: ixor
    //   15540: goto -> 15551
    //   15543: ldc2_w -617272196
    //   15546: l2i
    //   15547: ldc_w 2124608584
    //   15550: ixor
    //   15551: ldc2_w 1313648636
    //   15554: l2i
    //   15555: ldc_w -364162505
    //   15558: ixor
    //   15559: ixor
    //   15560: lookupswitch default -> 15878, -25074617 -> 15543, 26224127 -> 15588
    //   15588: goto -> 15592
    //   15591: athrow
    //   15592: invokevirtual append : (Ljava/lang/String;)Ljava/lang/StringBuilder;
    //   15595: goto -> 15599
    //   15598: athrow
    //   15599: ldc_w '.'
    //   15602: getstatic Perryc.0 : I
    //   15605: ifle -> 15619
    //   15608: ldc2_w 354004024
    //   15611: l2i
    //   15612: ldc_w -573654998
    //   15615: ixor
    //   15616: goto -> 15627
    //   15619: ldc2_w 1034081303
    //   15622: l2i
    //   15623: ldc_w -248301069
    //   15626: ixor
    //   15627: ldc2_w -1164765025
    //   15630: l2i
    //   15631: ldc_w -591754076
    //   15634: ixor
    //   15635: ixor
    //   15636: lookupswitch default -> 15664, -1359052759 -> 15988, 1854794633 -> 15619
    //   15664: goto -> 15668
    //   15667: athrow
    //   15668: invokevirtual append : (Ljava/lang/String;)Ljava/lang/StringBuilder;
    //   15671: goto -> 15675
    //   15674: athrow
    //   15675: getstatic Perryc.c : I
    //   15678: iflt -> 15692
    //   15681: ldc2_w 1076901722
    //   15684: l2i
    //   15685: ldc_w 1496432816
    //   15688: ixor
    //   15689: goto -> 15700
    //   15692: ldc2_w -147905193
    //   15695: l2i
    //   15696: ldc_w -551884084
    //   15699: ixor
    //   15700: ldc2_w 1076606066
    //   15703: l2i
    //   15704: ldc_w 1083331037
    //   15707: ixor
    //   15708: ixor
    //   15709: lookupswitch default -> 15910, 431493701 -> 15692, 680274484 -> 15736
    //   15736: goto -> 15740
    //   15739: athrow
    //   15740: invokevirtual toString : ()Ljava/lang/String;
    //   15743: goto -> 15747
    //   15746: athrow
    //   15747: getstatic Perryc.1 : I
    //   15750: ifeq -> 15764
    //   15753: ldc2_w -1125869827
    //   15756: l2i
    //   15757: ldc_w -1889792086
    //   15760: ixor
    //   15761: goto -> 15772
    //   15764: ldc2_w 1265254758
    //   15767: l2i
    //   15768: ldc_w 1480849877
    //   15771: ixor
    //   15772: ldc2_w -2089026166
    //   15775: l2i
    //   15776: ldc_w 1360102406
    //   15779: ixor
    //   15780: ixor
    //   15781: lookupswitch default -> 15808, -1310420238 -> 15764, -506273573 -> 15832
    //   15808: goto -> 15812
    //   15811: athrow
    //   15812: invokestatic sendMessage : (Ljava/lang/String;)V
    //   15815: goto -> 15819
    //   15818: athrow
    //   15819: return
    //   15820: aconst_null
    //   15821: athrow
    //   15822: aconst_null
    //   15823: athrow
    //   15824: aconst_null
    //   15825: athrow
    //   15826: aconst_null
    //   15827: athrow
    //   15828: aconst_null
    //   15829: athrow
    //   15830: aconst_null
    //   15831: athrow
    //   15832: aconst_null
    //   15833: athrow
    //   15834: aconst_null
    //   15835: athrow
    //   15836: aconst_null
    //   15837: athrow
    //   15838: aconst_null
    //   15839: athrow
    //   15840: aconst_null
    //   15841: athrow
    //   15842: aconst_null
    //   15843: athrow
    //   15844: aconst_null
    //   15845: athrow
    //   15846: aconst_null
    //   15847: athrow
    //   15848: aconst_null
    //   15849: athrow
    //   15850: aconst_null
    //   15851: athrow
    //   15852: aconst_null
    //   15853: athrow
    //   15854: aconst_null
    //   15855: athrow
    //   15856: aconst_null
    //   15857: athrow
    //   15858: aconst_null
    //   15859: athrow
    //   15860: aconst_null
    //   15861: athrow
    //   15862: aconst_null
    //   15863: athrow
    //   15864: aconst_null
    //   15865: athrow
    //   15866: aconst_null
    //   15867: athrow
    //   15868: aconst_null
    //   15869: athrow
    //   15870: aconst_null
    //   15871: athrow
    //   15872: aconst_null
    //   15873: athrow
    //   15874: aconst_null
    //   15875: athrow
    //   15876: aconst_null
    //   15877: athrow
    //   15878: aconst_null
    //   15879: athrow
    //   15880: aconst_null
    //   15881: athrow
    //   15882: aconst_null
    //   15883: athrow
    //   15884: aconst_null
    //   15885: athrow
    //   15886: aconst_null
    //   15887: athrow
    //   15888: aconst_null
    //   15889: athrow
    //   15890: aconst_null
    //   15891: athrow
    //   15892: aconst_null
    //   15893: athrow
    //   15894: aconst_null
    //   15895: athrow
    //   15896: aconst_null
    //   15897: athrow
    //   15898: aconst_null
    //   15899: athrow
    //   15900: aconst_null
    //   15901: athrow
    //   15902: aconst_null
    //   15903: athrow
    //   15904: aconst_null
    //   15905: athrow
    //   15906: aconst_null
    //   15907: athrow
    //   15908: aconst_null
    //   15909: athrow
    //   15910: aconst_null
    //   15911: athrow
    //   15912: aconst_null
    //   15913: athrow
    //   15914: aconst_null
    //   15915: athrow
    //   15916: aconst_null
    //   15917: athrow
    //   15918: aconst_null
    //   15919: athrow
    //   15920: aconst_null
    //   15921: athrow
    //   15922: aconst_null
    //   15923: athrow
    //   15924: aconst_null
    //   15925: athrow
    //   15926: aconst_null
    //   15927: athrow
    //   15928: aconst_null
    //   15929: athrow
    //   15930: aconst_null
    //   15931: athrow
    //   15932: aconst_null
    //   15933: athrow
    //   15934: aconst_null
    //   15935: athrow
    //   15936: aconst_null
    //   15937: athrow
    //   15938: aconst_null
    //   15939: athrow
    //   15940: aconst_null
    //   15941: athrow
    //   15942: aconst_null
    //   15943: athrow
    //   15944: aconst_null
    //   15945: athrow
    //   15946: aconst_null
    //   15947: athrow
    //   15948: aconst_null
    //   15949: athrow
    //   15950: aconst_null
    //   15951: athrow
    //   15952: aconst_null
    //   15953: athrow
    //   15954: aconst_null
    //   15955: athrow
    //   15956: aconst_null
    //   15957: athrow
    //   15958: aconst_null
    //   15959: athrow
    //   15960: aconst_null
    //   15961: athrow
    //   15962: aconst_null
    //   15963: athrow
    //   15964: aconst_null
    //   15965: athrow
    //   15966: aconst_null
    //   15967: athrow
    //   15968: aconst_null
    //   15969: athrow
    //   15970: aconst_null
    //   15971: athrow
    //   15972: aconst_null
    //   15973: athrow
    //   15974: aconst_null
    //   15975: athrow
    //   15976: aconst_null
    //   15977: athrow
    //   15978: aconst_null
    //   15979: athrow
    //   15980: aconst_null
    //   15981: athrow
    //   15982: aconst_null
    //   15983: athrow
    //   15984: aconst_null
    //   15985: athrow
    //   15986: aconst_null
    //   15987: athrow
    //   15988: aconst_null
    //   15989: athrow
    //   15990: aconst_null
    //   15991: athrow
    //   15992: aconst_null
    //   15993: athrow
    //   15994: aconst_null
    //   15995: athrow
    //   15996: aconst_null
    //   15997: athrow
    //   15998: aconst_null
    //   15999: athrow
    //   16000: aconst_null
    //   16001: athrow
    //   16002: aconst_null
    //   16003: athrow
    //   16004: aconst_null
    //   16005: athrow
    //   16006: aconst_null
    //   16007: athrow
    //   16008: aconst_null
    //   16009: athrow
    //   16010: aconst_null
    //   16011: athrow
    //   16012: aconst_null
    //   16013: athrow
    //   16014: aconst_null
    //   16015: athrow
    //   16016: aconst_null
    //   16017: athrow
    //   16018: aconst_null
    //   16019: athrow
    //   16020: aconst_null
    //   16021: athrow
    //   16022: aconst_null
    //   16023: athrow
    //   16024: aconst_null
    //   16025: athrow
    //   16026: aconst_null
    //   16027: athrow
    //   16028: aconst_null
    //   16029: athrow
    //   16030: aconst_null
    //   16031: athrow
    //   16032: aconst_null
    //   16033: athrow
    //   16034: aconst_null
    //   16035: athrow
    //   16036: aconst_null
    //   16037: athrow
    //   16038: aconst_null
    //   16039: athrow
    //   16040: aconst_null
    //   16041: athrow
    //   16042: aconst_null
    //   16043: athrow
    //   16044: aconst_null
    //   16045: athrow
    //   16046: aconst_null
    //   16047: athrow
    //   16048: aconst_null
    //   16049: athrow
    //   16050: aconst_null
    //   16051: athrow
    //   16052: aconst_null
    //   16053: athrow
    //   16054: aconst_null
    //   16055: athrow
    //   16056: aconst_null
    //   16057: athrow
    //   16058: aconst_null
    //   16059: athrow
    //   16060: aconst_null
    //   16061: athrow
    //   16062: aconst_null
    //   16063: athrow
    //   16064: aconst_null
    //   16065: athrow
    //   16066: aconst_null
    //   16067: athrow
    //   16068: aconst_null
    //   16069: athrow
    //   16070: aconst_null
    //   16071: athrow
    //   16072: aconst_null
    //   16073: athrow
    //   16074: aconst_null
    //   16075: athrow
    //   16076: aconst_null
    //   16077: athrow
    //   16078: aconst_null
    //   16079: athrow
    //   16080: aconst_null
    //   16081: athrow
    //   16082: aconst_null
    //   16083: athrow
    //   16084: aconst_null
    //   16085: athrow
    //   16086: aconst_null
    //   16087: athrow
    //   16088: aconst_null
    //   16089: athrow
    //   16090: aconst_null
    //   16091: athrow
    //   16092: aconst_null
    //   16093: athrow
    //   16094: aconst_null
    //   16095: athrow
    //   16096: aconst_null
    //   16097: athrow
    //   16098: aconst_null
    //   16099: athrow
    //   16100: aconst_null
    //   16101: athrow
    //   16102: aconst_null
    //   16103: athrow
    //   16104: aconst_null
    //   16105: athrow
    //   16106: aconst_null
    //   16107: athrow
    //   16108: aconst_null
    //   16109: athrow
    //   16110: aconst_null
    //   16111: athrow
    //   16112: aconst_null
    //   16113: athrow
    //   16114: aconst_null
    //   16115: athrow
    //   16116: aconst_null
    //   16117: athrow
    //   16118: aconst_null
    //   16119: athrow
    //   16120: aconst_null
    //   16121: athrow
    //   16122: aconst_null
    //   16123: athrow
    //   16124: aconst_null
    //   16125: athrow
    //   16126: aconst_null
    //   16127: athrow
    //   16128: aconst_null
    //   16129: athrow
    //   16130: aconst_null
    //   16131: athrow
    //   16132: aconst_null
    //   16133: athrow
    //   16134: aconst_null
    //   16135: athrow
    //   16136: aconst_null
    //   16137: athrow
    //   16138: aconst_null
    //   16139: athrow
    //   16140: aconst_null
    //   16141: athrow
    //   16142: aconst_null
    //   16143: athrow
    //   16144: aconst_null
    //   16145: athrow
    //   16146: aconst_null
    //   16147: athrow
    //   16148: aconst_null
    //   16149: athrow
    //   16150: aconst_null
    //   16151: athrow
    //   16152: aconst_null
    //   16153: athrow
    //   16154: aconst_null
    //   16155: athrow
    //   16156: aconst_null
    //   16157: athrow
    //   16158: aconst_null
    //   16159: athrow
    //   16160: aconst_null
    //   16161: athrow
    //   16162: aconst_null
    //   16163: athrow
    //   16164: aconst_null
    //   16165: athrow
    //   16166: aconst_null
    //   16167: athrow
    //   16168: aconst_null
    //   16169: athrow
    //   16170: aconst_null
    //   16171: athrow
    //   16172: aconst_null
    //   16173: athrow
    //   16174: aconst_null
    //   16175: athrow
    //   16176: aconst_null
    //   16177: athrow
    //   16178: aconst_null
    //   16179: athrow
    //   16180: aconst_null
    //   16181: athrow
    //   16182: aconst_null
    //   16183: athrow
    //   16184: aconst_null
    //   16185: athrow
    //   16186: aconst_null
    //   16187: athrow
    //   16188: aconst_null
    //   16189: athrow
    //   16190: aconst_null
    //   16191: athrow
    //   16192: aconst_null
    //   16193: athrow
    //   16194: aconst_null
    //   16195: athrow
    //   16196: aconst_null
    //   16197: athrow
    //   16198: aconst_null
    //   16199: athrow
    //   16200: aconst_null
    //   16201: athrow
    //   16202: aconst_null
    //   16203: athrow
    //   16204: aconst_null
    //   16205: athrow
    //   16206: aconst_null
    //   16207: athrow
    //   16208: aconst_null
    //   16209: athrow
    //   16210: aconst_null
    //   16211: athrow
    //   16212: aconst_null
    //   16213: athrow
    //   16214: aconst_null
    //   16215: athrow
    //   16216: aconst_null
    //   16217: athrow
    //   16218: aconst_null
    //   16219: athrow
    //   16220: aconst_null
    //   16221: athrow
    //   16222: aconst_null
    //   16223: athrow
    //   16224: aconst_null
    //   16225: athrow
    //   16226: aconst_null
    //   16227: athrow
    //   16228: aconst_null
    //   16229: athrow
    //   16230: aconst_null
    //   16231: athrow
    //   16232: aconst_null
    //   16233: athrow
    //   16234: aconst_null
    //   16235: athrow
    //   16236: aconst_null
    //   16237: athrow
    //   16238: aconst_null
    //   16239: athrow
    //   16240: aconst_null
    //   16241: athrow
    //   16242: aconst_null
    //   16243: athrow
    //   16244: pop
    //   16245: goto -> 24
    //   16248: pop
    //   16249: aconst_null
    //   16250: goto -> 16244
    //   16253: dup
    //   16254: ifnull -> 16244
    //   16257: checkcast java/lang/Throwable
    //   16260: athrow
    //   16261: dup
    //   16262: ifnull -> 16248
    //   16265: checkcast java/lang/Throwable
    //   16268: athrow
    //   16269: aconst_null
    //   16270: athrow
    // Local variable table:
    //   start	length	slot	name	descriptor
    //   2222	1232	7	module1	Lbigname/zprestige/webhack/features/modules/Module;
    //   1490	2101	5	modules	Ljava/lang/String;
    //   922	2669	4	category	Lbigname/zprestige/webhack/features/modules/Module$Category;
    //   6646	1141	5	setting2	Lbigname/zprestige/webhack/features/setting/Setting;
    //   9266	273	5	setting3	Lbigname/zprestige/webhack/features/setting/Setting;
    //   13890	722	5	e	Ljava/lang/Exception;
    //   10546	5273	4	jp	Lcom/google/gson/JsonParser;
    //   10353	5466	2	setting	Lbigname/zprestige/webhack/features/setting/Setting;
    //   24	15796	0	this	Lbigname/zprestige/webhack/features/command/commands/ModuleCommand;
    //   24	15796	1	commands	[Ljava/lang/String;
    //   3865	11955	3	module	Lbigname/zprestige/webhack/features/modules/Module;
    // Exception table:
    //   from	to	target	type
    //   8	20	16253	finally
    //   203	210	210	finally
    //   203	210	203	java/util/NoSuchElementException
    //   203	210	3	finally
    //   204	210	203	java/lang/IndexOutOfBoundsException
    //   204	210	203	finally
    //   271	278	278	finally
    //   272	278	278	java/lang/ClassCastException
    //   272	278	271	java/lang/IllegalStateException
    //   272	278	278	finally
    //   272	278	271	java/lang/AssertionError
    //   399	406	406	finally
    //   399	406	399	java/lang/ArithmeticException
    //   399	406	3	finally
    //   400	406	406	java/lang/ClassCastException
    //   400	406	3	java/lang/IndexOutOfBoundsException
    //   467	476	476	finally
    //   467	476	476	finally
    //   467	476	467	java/lang/UnsupportedOperationException
    //   467	476	476	finally
    //   468	476	3	finally
    //   660	668	668	finally
    //   660	668	668	java/lang/AssertionError
    //   660	668	668	finally
    //   660	668	3	java/lang/IllegalStateException
    //   660	668	3	java/lang/IllegalStateException
    //   847	856	856	finally
    //   847	856	3	finally
    //   847	856	856	java/lang/NumberFormatException
    //   847	856	847	finally
    //   848	856	847	java/lang/UnsupportedOperationException
    //   992	998	998	finally
    //   992	998	3	java/lang/IllegalArgumentException
    //   992	998	3	java/lang/NegativeArraySizeException
    //   992	998	3	java/lang/NegativeArraySizeException
    //   992	998	998	finally
    //   1128	1134	1134	finally
    //   1128	1134	3	java/lang/EnumConstantNotPresentException
    //   1128	1134	1134	finally
    //   1128	1134	1134	java/lang/NegativeArraySizeException
    //   1128	1134	3	java/lang/IndexOutOfBoundsException
    //   1199	1206	1206	finally
    //   1199	1206	3	finally
    //   1199	1206	3	finally
    //   1200	1206	1199	java/lang/IndexOutOfBoundsException
    //   1200	1206	1199	finally
    //   1275	1282	1282	finally
    //   1276	1282	3	java/lang/NullPointerException
    //   1276	1282	1282	java/lang/ArithmeticException
    //   1276	1282	1275	java/lang/NullPointerException
    //   1276	1282	1275	java/lang/ArithmeticException
    //   1347	1354	1354	finally
    //   1347	1354	1354	java/lang/IllegalStateException
    //   1347	1354	1354	java/lang/IllegalArgumentException
    //   1347	1354	1347	java/lang/EnumConstantNotPresentException
    //   1348	1354	1354	finally
    //   1419	1426	1426	finally
    //   1419	1426	3	finally
    //   1419	1426	1419	java/util/NoSuchElementException
    //   1419	1426	3	finally
    //   1420	1426	3	finally
    //   1683	1690	1690	finally
    //   1683	1690	1683	finally
    //   1683	1690	1690	finally
    //   1684	1690	1690	java/lang/ArithmeticException
    //   1684	1690	1683	finally
    //   1756	1762	1762	finally
    //   1756	1762	1762	finally
    //   1756	1762	1762	finally
    //   1756	1762	1762	finally
    //   1756	1762	1762	finally
    //   1955	1964	1964	finally
    //   1955	1964	1955	finally
    //   1955	1964	3	finally
    //   1956	1964	3	java/lang/NullPointerException
    //   1956	1964	1964	finally
    //   2147	2156	2156	finally
    //   2147	2156	2156	java/lang/StringIndexOutOfBoundsException
    //   2147	2156	3	java/lang/NegativeArraySizeException
    //   2147	2156	2147	java/lang/NumberFormatException
    //   2148	2156	2156	finally
    //   2291	2298	2298	finally
    //   2291	2298	2298	finally
    //   2291	2298	3	finally
    //   2291	2298	2298	java/util/ConcurrentModificationException
    //   2292	2298	2291	finally
    //   2428	2434	2434	finally
    //   2428	2434	3	java/lang/EnumConstantNotPresentException
    //   2428	2434	2434	java/lang/IllegalArgumentException
    //   2428	2434	2434	finally
    //   2428	2434	2434	java/lang/UnsupportedOperationException
    //   2563	2570	2570	finally
    //   2563	2570	2563	finally
    //   2564	2570	3	finally
    //   2564	2570	2563	finally
    //   2564	2570	2570	java/lang/ClassCastException
    //   2819	2826	2826	finally
    //   2819	2826	2826	finally
    //   2820	2826	3	java/lang/ClassCastException
    //   2820	2826	2826	finally
    //   2820	2826	2819	finally
    //   2955	2962	2962	finally
    //   2955	2962	2955	finally
    //   2955	2962	2955	finally
    //   2956	2962	2955	finally
    //   2956	2962	2955	finally
    //   3028	3034	3034	finally
    //   3028	3034	3	java/lang/NullPointerException
    //   3028	3034	3	finally
    //   3028	3034	3	finally
    //   3028	3034	3034	finally
    //   3163	3170	3170	finally
    //   3164	3170	3170	finally
    //   3164	3170	3163	java/lang/ClassCastException
    //   3164	3170	3170	java/lang/NumberFormatException
    //   3164	3170	3	finally
    //   3240	3246	3246	finally
    //   3240	3246	3246	java/lang/UnsupportedOperationException
    //   3240	3246	3246	finally
    //   3240	3246	3246	finally
    //   3240	3246	3246	java/lang/StringIndexOutOfBoundsException
    //   3312	3318	3318	finally
    //   3312	3318	3318	finally
    //   3312	3318	3	finally
    //   3312	3318	3318	java/lang/NullPointerException
    //   3312	3318	3	java/lang/RuntimeException
    //   3384	3390	3390	finally
    //   3384	3390	3390	finally
    //   3384	3390	3390	java/lang/IllegalStateException
    //   3384	3390	3	finally
    //   3384	3390	3	java/lang/ClassCastException
    //   3583	3590	3590	finally
    //   3583	3590	3590	java/lang/ClassCastException
    //   3584	3590	3583	java/util/NoSuchElementException
    //   3584	3590	3590	finally
    //   3584	3590	3	java/lang/IndexOutOfBoundsException
    //   3795	3802	3802	finally
    //   3795	3802	3802	finally
    //   3796	3802	3795	finally
    //   3796	3802	3802	java/lang/IllegalStateException
    //   3796	3802	3795	java/lang/ArithmeticException
    //   4179	4186	4186	finally
    //   4179	4186	4186	java/lang/NumberFormatException
    //   4180	4186	4179	java/lang/IllegalArgumentException
    //   4180	4186	3	java/lang/NumberFormatException
    //   4180	4186	3	java/lang/IllegalArgumentException
    //   4431	4438	4438	finally
    //   4431	4438	3	java/lang/UnsupportedOperationException
    //   4431	4438	4431	finally
    //   4432	4438	4431	finally
    //   4432	4438	3	java/lang/IllegalStateException
    //   4503	4510	4510	finally
    //   4503	4510	4503	java/lang/RuntimeException
    //   4504	4510	4503	java/lang/ArithmeticException
    //   4504	4510	3	java/lang/AssertionError
    //   4504	4510	3	java/lang/ClassCastException
    //   4579	4586	4586	finally
    //   4579	4586	3	java/lang/NegativeArraySizeException
    //   4580	4586	4579	finally
    //   4580	4586	4579	java/util/ConcurrentModificationException
    //   4580	4586	4579	java/lang/ClassCastException
    //   4656	4662	4662	finally
    //   4656	4662	4662	finally
    //   4656	4662	4662	finally
    //   4656	4662	3	java/lang/UnsupportedOperationException
    //   4656	4662	4662	java/lang/NumberFormatException
    //   4727	4734	4734	finally
    //   4727	4734	4727	java/lang/ClassCastException
    //   4727	4734	3	finally
    //   4727	4734	4734	finally
    //   4728	4734	4734	java/lang/ArrayIndexOutOfBoundsException
    //   4859	4866	4866	finally
    //   4859	4866	3	java/lang/IllegalArgumentException
    //   4859	4866	3	finally
    //   4859	4866	3	finally
    //   4860	4866	4859	finally
    //   4931	4938	4938	finally
    //   4931	4938	4931	java/lang/UnsupportedOperationException
    //   4931	4938	4938	java/lang/NegativeArraySizeException
    //   4932	4938	4938	finally
    //   4932	4938	3	finally
    //   5003	5010	5010	finally
    //   5003	5010	5003	finally
    //   5004	5010	5010	finally
    //   5004	5010	3	finally
    //   5004	5010	3	java/lang/IllegalStateException
    //   5075	5082	5082	finally
    //   5075	5082	3	java/lang/NegativeArraySizeException
    //   5075	5082	5082	java/util/ConcurrentModificationException
    //   5076	5082	5075	java/lang/UnsupportedOperationException
    //   5076	5082	5082	finally
    //   5275	5282	5282	finally
    //   5275	5282	5275	finally
    //   5276	5282	3	finally
    //   5276	5282	5275	finally
    //   5276	5282	3	finally
    //   5407	5414	5414	finally
    //   5407	5414	3	finally
    //   5407	5414	5407	finally
    //   5408	5414	5407	finally
    //   5408	5414	5414	finally
    //   5480	5486	5486	finally
    //   5480	5486	3	java/lang/RuntimeException
    //   5480	5486	3	java/lang/ArrayIndexOutOfBoundsException
    //   5480	5486	5486	finally
    //   5480	5486	5486	finally
    //   5555	5562	5562	finally
    //   5555	5562	5555	java/lang/IllegalArgumentException
    //   5556	5562	5555	finally
    //   5556	5562	3	java/lang/UnsupportedOperationException
    //   5556	5562	3	java/lang/NullPointerException
    //   5628	5634	5634	finally
    //   5628	5634	3	finally
    //   5628	5634	5634	finally
    //   5628	5634	5634	java/lang/NullPointerException
    //   5628	5634	3	java/lang/NumberFormatException
    //   5759	5766	5766	finally
    //   5759	5766	5759	java/lang/IllegalArgumentException
    //   5759	5766	5759	java/lang/IllegalArgumentException
    //   5760	5766	5766	java/lang/AssertionError
    //   5760	5766	3	finally
    //   5831	5838	5838	finally
    //   5831	5838	5838	finally
    //   5831	5838	3	finally
    //   5831	5838	5831	java/lang/ClassCastException
    //   5832	5838	5838	finally
    //   5903	5910	5910	finally
    //   5903	5910	5903	finally
    //   5904	5910	5903	finally
    //   5904	5910	5903	java/lang/IllegalArgumentException
    //   5904	5910	5910	java/lang/NumberFormatException
    //   5975	5982	5982	finally
    //   5975	5982	5975	java/lang/RuntimeException
    //   5975	5982	5975	java/lang/RuntimeException
    //   5975	5982	5975	java/lang/EnumConstantNotPresentException
    //   5976	5982	5982	finally
    //   6107	6114	6114	finally
    //   6107	6114	6114	java/lang/NullPointerException
    //   6107	6114	6107	finally
    //   6107	6114	3	java/lang/IllegalArgumentException
    //   6108	6114	6114	java/lang/IndexOutOfBoundsException
    //   6180	6188	6188	finally
    //   6180	6188	3	finally
    //   6180	6188	3	finally
    //   6180	6188	3	finally
    //   6180	6188	3	java/lang/IllegalArgumentException
    //   6379	6388	6388	finally
    //   6379	6388	3	java/lang/NullPointerException
    //   6379	6388	6388	java/util/ConcurrentModificationException
    //   6380	6388	6379	finally
    //   6380	6388	6388	finally
    //   6571	6580	6580	finally
    //   6571	6580	6571	finally
    //   6572	6580	3	java/lang/IndexOutOfBoundsException
    //   6572	6580	6571	java/lang/ArrayIndexOutOfBoundsException
    //   6572	6580	3	java/lang/UnsupportedOperationException
    //   6715	6722	6722	finally
    //   6715	6722	6722	java/lang/IllegalStateException
    //   6715	6722	6715	java/lang/AssertionError
    //   6716	6722	3	finally
    //   6716	6722	6715	java/util/ConcurrentModificationException
    //   6851	6858	6858	finally
    //   6851	6858	3	java/lang/IllegalArgumentException
    //   6851	6858	6851	finally
    //   6851	6858	6858	java/lang/ArithmeticException
    //   6852	6858	6851	java/lang/EnumConstantNotPresentException
    //   6923	6930	6930	finally
    //   6923	6930	6923	java/lang/IllegalArgumentException
    //   6923	6930	6930	java/lang/StringIndexOutOfBoundsException
    //   6924	6930	6923	java/lang/ArrayIndexOutOfBoundsException
    //   6924	6930	6923	finally
    //   6999	7006	7006	finally
    //   6999	7006	7006	java/lang/ClassCastException
    //   7000	7006	6999	java/lang/EnumConstantNotPresentException
    //   7000	7006	7006	java/lang/IllegalStateException
    //   7000	7006	3	java/lang/UnsupportedOperationException
    //   7071	7078	7078	finally
    //   7071	7078	7071	finally
    //   7071	7078	7071	java/lang/StringIndexOutOfBoundsException
    //   7071	7078	7071	java/lang/ArrayIndexOutOfBoundsException
    //   7071	7078	7078	finally
    //   7207	7214	7214	finally
    //   7207	7214	7214	finally
    //   7207	7214	7207	finally
    //   7208	7214	7207	java/lang/IndexOutOfBoundsException
    //   7208	7214	7214	finally
    //   7280	7286	7286	finally
    //   7280	7286	3	java/lang/ArithmeticException
    //   7280	7286	7286	java/lang/NegativeArraySizeException
    //   7280	7286	3	java/lang/ArithmeticException
    //   7280	7286	3	finally
    //   7355	7362	7362	finally
    //   7355	7362	7362	java/util/NoSuchElementException
    //   7355	7362	7355	java/lang/UnsupportedOperationException
    //   7355	7362	3	finally
    //   7356	7362	7355	finally
    //   7427	7434	7434	finally
    //   7427	7434	7434	finally
    //   7427	7434	3	java/lang/ClassCastException
    //   7427	7434	7434	java/lang/NegativeArraySizeException
    //   7428	7434	7427	finally
    //   7564	7570	7570	finally
    //   7564	7570	3	finally
    //   7564	7570	3	finally
    //   7564	7570	7570	finally
    //   7564	7570	7570	java/lang/RuntimeException
    //   7635	7642	7642	finally
    //   7635	7642	7642	finally
    //   7635	7642	7635	java/lang/AssertionError
    //   7635	7642	3	finally
    //   7636	7642	3	finally
    //   7708	7714	7714	finally
    //   7708	7714	7714	finally
    //   7708	7714	7714	java/lang/IllegalArgumentException
    //   7708	7714	7714	finally
    //   7708	7714	3	java/lang/IndexOutOfBoundsException
    //   7780	7786	7786	finally
    //   7780	7786	7786	finally
    //   7780	7786	3	finally
    //   7780	7786	7786	java/lang/AssertionError
    //   7780	7786	7786	java/lang/IllegalArgumentException
    //   8052	8058	8058	finally
    //   8052	8058	3	java/util/NoSuchElementException
    //   8052	8058	3	finally
    //   8052	8058	8058	finally
    //   8052	8058	8058	java/lang/IndexOutOfBoundsException
    //   8123	8130	8130	finally
    //   8124	8130	3	finally
    //   8124	8130	8130	java/lang/UnsupportedOperationException
    //   8124	8130	8123	java/lang/NegativeArraySizeException
    //   8124	8130	3	java/lang/NegativeArraySizeException
    //   8251	8258	8258	finally
    //   8251	8258	8251	finally
    //   8252	8258	3	finally
    //   8252	8258	8258	finally
    //   8252	8258	8251	finally
    //   8323	8330	8330	finally
    //   8323	8330	8330	java/lang/IndexOutOfBoundsException
    //   8323	8330	8323	finally
    //   8324	8330	3	java/lang/AssertionError
    //   8324	8330	8330	java/lang/ArithmeticException
    //   8471	8478	8478	finally
    //   8471	8478	8471	java/lang/NullPointerException
    //   8471	8478	8471	java/lang/IndexOutOfBoundsException
    //   8472	8478	3	finally
    //   8472	8478	3	java/lang/AssertionError
    //   8543	8550	8550	finally
    //   8543	8550	3	java/lang/IllegalStateException
    //   8543	8550	8550	java/lang/IndexOutOfBoundsException
    //   8544	8550	8550	finally
    //   8544	8550	8543	java/lang/ArrayIndexOutOfBoundsException
    //   8727	8734	8734	finally
    //   8727	8734	8734	finally
    //   8727	8734	8727	finally
    //   8727	8734	8734	java/lang/ArithmeticException
    //   8728	8734	8734	finally
    //   8799	8808	8808	finally
    //   8799	8808	8808	finally
    //   8800	8808	8799	finally
    //   8800	8808	8799	finally
    //   8800	8808	8799	finally
    //   8999	9008	9008	finally
    //   8999	9008	8999	java/lang/NegativeArraySizeException
    //   9000	9008	3	java/lang/RuntimeException
    //   9000	9008	3	finally
    //   9000	9008	3	finally
    //   9191	9200	9200	finally
    //   9191	9200	3	finally
    //   9192	9200	9200	finally
    //   9192	9200	3	finally
    //   9192	9200	9191	finally
    //   9459	9466	9466	finally
    //   9459	9466	9459	finally
    //   9459	9466	9466	finally
    //   9460	9466	9466	finally
    //   9460	9466	3	finally
    //   9531	9538	9538	finally
    //   9531	9538	9531	java/lang/NumberFormatException
    //   9531	9538	9531	finally
    //   9531	9538	3	finally
    //   9532	9538	9531	java/lang/StringIndexOutOfBoundsException
    //   9612	9618	9618	finally
    //   9612	9618	3	java/lang/ArithmeticException
    //   9612	9618	9618	finally
    //   9612	9618	9618	java/lang/ClassCastException
    //   9612	9618	9618	finally
    //   9683	9690	9690	finally
    //   9683	9690	3	finally
    //   9683	9690	3	finally
    //   9684	9690	9683	java/util/ConcurrentModificationException
    //   9684	9690	9690	finally
    //   9883	9890	9890	finally
    //   9883	9890	3	finally
    //   9883	9890	3	java/lang/UnsupportedOperationException
    //   9884	9890	3	finally
    //   9884	9890	9883	java/lang/IndexOutOfBoundsException
    //   9955	9962	9962	finally
    //   9955	9962	9962	java/lang/RuntimeException
    //   9955	9962	9962	finally
    //   9955	9962	9955	java/lang/IllegalStateException
    //   9956	9962	9962	java/lang/RuntimeException
    //   10283	10290	10290	finally
    //   10283	10290	10290	finally
    //   10284	10290	10290	java/lang/EnumConstantNotPresentException
    //   10284	10290	10290	java/lang/IllegalStateException
    //   10284	10290	10283	java/lang/NumberFormatException
    //   10475	10482	10482	finally
    //   10475	10482	10475	java/lang/IndexOutOfBoundsException
    //   10475	10482	10475	java/util/NoSuchElementException
    //   10476	10482	3	finally
    //   10476	10482	10482	finally
    //   10671	10678	10678	finally
    //   10671	10678	10678	finally
    //   10671	10678	10671	finally
    //   10672	10678	10671	finally
    //   10672	10678	10671	java/lang/IndexOutOfBoundsException
    //   10747	10754	10754	finally
    //   10747	10754	10747	java/lang/UnsupportedOperationException
    //   10747	10754	10747	finally
    //   10747	10754	10747	finally
    //   10748	10754	3	finally
    //   10819	10826	10826	finally
    //   10819	10826	10819	finally
    //   10820	10826	10826	java/lang/ArithmeticException
    //   10820	10826	10819	java/lang/StringIndexOutOfBoundsException
    //   10820	10826	10819	finally
    //   11076	11082	11082	finally
    //   11076	11082	11082	finally
    //   11076	11082	11082	finally
    //   11076	11082	11082	java/util/ConcurrentModificationException
    //   11076	11082	3	java/lang/NullPointerException
    //   11151	11158	11158	finally
    //   11151	11158	11158	finally
    //   11151	11158	11151	java/lang/ArithmeticException
    //   11151	11158	3	finally
    //   11152	11158	11158	finally
    //   11288	11294	11294	finally
    //   11288	11294	11294	java/lang/IllegalStateException
    //   11288	11294	11294	finally
    //   11288	11294	3	finally
    //   11288	11294	3	java/util/ConcurrentModificationException
    //   11419	11426	11426	finally
    //   11419	11426	11419	finally
    //   11419	11426	11426	java/lang/ArrayIndexOutOfBoundsException
    //   11420	11426	11419	java/lang/IllegalStateException
    //   11420	11426	11419	java/lang/UnsupportedOperationException
    //   11491	11498	11498	finally
    //   11492	11498	3	java/lang/IllegalStateException
    //   11492	11498	11498	java/lang/ArithmeticException
    //   11492	11498	11498	java/lang/AssertionError
    //   11492	11498	11491	java/lang/RuntimeException
    //   11567	11574	11574	finally
    //   11567	11574	11567	finally
    //   11567	11574	3	java/lang/ClassCastException
    //   11568	11574	11574	java/lang/ArrayIndexOutOfBoundsException
    //   11568	11574	11574	java/lang/RuntimeException
    //   11699	11706	11706	finally
    //   11699	11706	11699	java/lang/UnsupportedOperationException
    //   11699	11706	3	java/lang/NullPointerException
    //   11700	11706	11699	finally
    //   11700	11706	3	java/lang/NegativeArraySizeException
    //   11771	11778	11778	finally
    //   11771	11778	11771	finally
    //   11771	11778	3	finally
    //   11771	11778	11771	finally
    //   11772	11778	11778	finally
    //   11847	11854	11854	finally
    //   11847	11854	3	finally
    //   11847	11854	3	java/lang/NegativeArraySizeException
    //   11848	11854	3	java/lang/UnsupportedOperationException
    //   11848	11854	11847	java/lang/ArithmeticException
    //   11919	11926	11926	finally
    //   11919	11926	3	java/lang/IllegalStateException
    //   11919	11926	11919	finally
    //   11919	11926	11919	java/lang/NegativeArraySizeException
    //   11920	11926	11926	finally
    //   12064	12070	12070	finally
    //   12064	12070	3	finally
    //   12064	12070	12070	finally
    //   12064	12070	3	java/lang/RuntimeException
    //   12064	12070	3	java/lang/NullPointerException
    //   12140	12146	12146	finally
    //   12140	12146	12146	java/lang/NegativeArraySizeException
    //   12140	12146	12146	java/lang/AssertionError
    //   12140	12146	12146	finally
    //   12140	12146	12146	finally
    //   12211	12218	12218	finally
    //   12211	12218	3	java/lang/UnsupportedOperationException
    //   12211	12218	12218	java/util/ConcurrentModificationException
    //   12211	12218	12218	java/lang/IndexOutOfBoundsException
    //   12212	12218	12211	java/lang/UnsupportedOperationException
    //   12283	12290	12290	finally
    //   12283	12290	12283	java/lang/UnsupportedOperationException
    //   12283	12290	12290	finally
    //   12284	12290	3	java/util/NoSuchElementException
    //   12284	12290	3	java/lang/RuntimeException
    //   12292	12415	13826	java/lang/Exception
    //   12416	12422	12422	finally
    //   12416	12422	3	finally
    //   12416	12422	12422	finally
    //   12416	12422	12422	java/lang/IllegalStateException
    //   12416	12422	12422	finally
    //   12416	13823	13826	java/lang/Exception
    //   12491	12498	12498	finally
    //   12491	12498	12498	finally
    //   12491	12498	12491	finally
    //   12491	12498	3	java/lang/AssertionError
    //   12492	12498	12498	finally
    //   12563	12570	12570	finally
    //   12563	12570	12563	finally
    //   12564	12570	12570	java/lang/ArrayIndexOutOfBoundsException
    //   12564	12570	12563	finally
    //   12564	12570	12570	java/lang/EnumConstantNotPresentException
    //   12759	12766	12766	finally
    //   12759	12766	3	java/lang/IndexOutOfBoundsException
    //   12759	12766	12759	finally
    //   12759	12766	12759	java/lang/UnsupportedOperationException
    //   12760	12766	12766	finally
    //   12831	12838	12838	finally
    //   12831	12838	12838	finally
    //   12831	12838	12831	java/lang/ArithmeticException
    //   12831	12838	3	finally
    //   12832	12838	12831	java/lang/NumberFormatException
    //   13015	13022	13022	finally
    //   13015	13022	13022	finally
    //   13016	13022	13022	finally
    //   13016	13022	13022	finally
    //   13016	13022	13015	java/lang/AssertionError
    //   13159	13166	13166	finally
    //   13159	13166	13159	finally
    //   13159	13166	13159	java/lang/NumberFormatException
    //   13160	13166	13159	finally
    //   13160	13166	3	finally
    //   13231	13238	13238	finally
    //   13231	13238	13238	java/lang/IllegalArgumentException
    //   13231	13238	13238	java/lang/UnsupportedOperationException
    //   13231	13238	13231	finally
    //   13231	13238	13238	finally
    //   13415	13422	13422	finally
    //   13416	13422	13415	java/lang/UnsupportedOperationException
    //   13416	13422	13415	java/util/ConcurrentModificationException
    //   13416	13422	13422	java/lang/IllegalArgumentException
    //   13416	13422	13415	java/lang/ArithmeticException
    //   13743	13750	13750	finally
    //   13743	13750	13743	finally
    //   13743	13750	13743	java/lang/NullPointerException
    //   13743	13750	13743	finally
    //   13744	13750	13750	finally
    //   13815	13822	13822	finally
    //   13815	13822	3	java/lang/NullPointerException
    //   13816	13822	13815	finally
    //   13816	13822	13822	java/lang/ArithmeticException
    //   13816	13822	3	finally
    //   13960	13966	13966	finally
    //   13960	13966	3	java/util/NoSuchElementException
    //   13960	13966	13966	java/lang/IllegalStateException
    //   13960	13966	3	finally
    //   13960	13966	13966	java/util/ConcurrentModificationException
    //   14035	14042	14042	finally
    //   14035	14042	14042	java/util/ConcurrentModificationException
    //   14035	14042	14042	finally
    //   14035	14042	14035	java/lang/NegativeArraySizeException
    //   14035	14042	14035	java/lang/NumberFormatException
    //   14107	14114	14114	finally
    //   14107	14114	14107	finally
    //   14107	14114	3	java/lang/IndexOutOfBoundsException
    //   14108	14114	14107	finally
    //   14108	14114	3	finally
    //   14239	14246	14246	finally
    //   14239	14246	3	java/lang/NegativeArraySizeException
    //   14240	14246	14246	finally
    //   14240	14246	3	java/util/ConcurrentModificationException
    //   14240	14246	14239	java/lang/NumberFormatException
    //   14311	14318	14318	finally
    //   14311	14318	14311	java/lang/ClassCastException
    //   14311	14318	3	java/lang/IndexOutOfBoundsException
    //   14312	14318	14318	java/lang/IllegalArgumentException
    //   14312	14318	14318	java/lang/ClassCastException
    //   14387	14394	14394	finally
    //   14387	14394	14394	java/lang/NegativeArraySizeException
    //   14387	14394	14394	finally
    //   14387	14394	14394	finally
    //   14388	14394	14387	finally
    //   14459	14466	14466	finally
    //   14459	14466	3	finally
    //   14460	14466	14459	java/lang/ArrayIndexOutOfBoundsException
    //   14460	14466	14459	java/lang/AssertionError
    //   14460	14466	14466	finally
    //   14531	14538	14538	finally
    //   14531	14538	14538	java/lang/NullPointerException
    //   14531	14538	3	finally
    //   14532	14538	14538	java/lang/IllegalStateException
    //   14532	14538	14531	java/lang/ArrayIndexOutOfBoundsException
    //   14603	14610	14610	finally
    //   14603	14610	3	finally
    //   14604	14610	3	java/lang/AssertionError
    //   14604	14610	14610	java/lang/IllegalArgumentException
    //   14604	14610	14603	finally
    //   14679	14686	14686	finally
    //   14679	14686	14679	finally
    //   14680	14686	14686	java/lang/EnumConstantNotPresentException
    //   14680	14686	14679	java/util/NoSuchElementException
    //   14680	14686	14686	java/util/ConcurrentModificationException
    //   14815	14822	14822	finally
    //   14816	14822	14815	java/lang/AssertionError
    //   14816	14822	14822	java/lang/UnsupportedOperationException
    //   14816	14822	3	finally
    //   14816	14822	14815	finally
    //   14947	14954	14954	finally
    //   14947	14954	14954	finally
    //   14947	14954	3	finally
    //   14947	14954	3	finally
    //   14948	14954	14947	java/lang/IllegalStateException
    //   15019	15026	15026	finally
    //   15019	15026	15019	finally
    //   15019	15026	15019	finally
    //   15019	15026	15026	java/lang/NullPointerException
    //   15020	15026	15019	java/lang/NullPointerException
    //   15095	15102	15102	finally
    //   15095	15102	15095	finally
    //   15095	15102	3	finally
    //   15095	15102	15102	finally
    //   15096	15102	15095	finally
    //   15228	15234	15234	finally
    //   15228	15234	15234	java/lang/IllegalStateException
    //   15228	15234	3	finally
    //   15228	15234	3	java/lang/NullPointerException
    //   15228	15234	15234	finally
    //   15299	15306	15306	finally
    //   15299	15306	15306	finally
    //   15299	15306	15306	java/lang/ArithmeticException
    //   15300	15306	3	finally
    //   15300	15306	15299	java/util/NoSuchElementException
    //   15376	15382	15382	finally
    //   15376	15382	15382	finally
    //   15376	15382	3	java/lang/EnumConstantNotPresentException
    //   15376	15382	15382	java/lang/EnumConstantNotPresentException
    //   15376	15382	15382	java/lang/RuntimeException
    //   15447	15454	15454	finally
    //   15447	15454	15447	java/lang/NumberFormatException
    //   15447	15454	15454	finally
    //   15447	15454	15454	java/lang/EnumConstantNotPresentException
    //   15448	15454	15454	java/lang/IndexOutOfBoundsException
    //   15591	15598	15598	finally
    //   15591	15598	15598	finally
    //   15592	15598	15591	java/lang/NegativeArraySizeException
    //   15592	15598	15591	java/lang/ArithmeticException
    //   15592	15598	15591	java/lang/IllegalArgumentException
    //   15667	15674	15674	finally
    //   15667	15674	15674	java/lang/UnsupportedOperationException
    //   15667	15674	3	java/lang/EnumConstantNotPresentException
    //   15668	15674	15667	java/lang/EnumConstantNotPresentException
    //   15668	15674	15667	java/lang/ArrayIndexOutOfBoundsException
    //   15739	15746	15746	finally
    //   15739	15746	3	java/lang/RuntimeException
    //   15739	15746	15746	finally
    //   15740	15746	3	java/lang/NullPointerException
    //   15740	15746	15739	java/lang/NullPointerException
    //   15811	15818	15818	finally
    //   15811	15818	3	java/util/NoSuchElementException
    //   15812	15818	15811	java/lang/IndexOutOfBoundsException
    //   15812	15818	15818	finally
    //   15812	15818	15818	finally
    //   16253	16261	16253	java/lang/IllegalArgumentException
    //   16269	16271	3	finally
  }
}


/* Location:              C:\Users\alex\Desktop\webhack\WebHack-0.8-obf_sussy_1.jar!\bigname\zprestige\webhack\features\command\commands\ModuleCommand.class
 * Java compiler version: 8 (52.0)
 * JD-Core Version:       1.1.3
 */