package bigname.zprestige.webhack.features.command.commands;

import Perryc;
import bigname.zprestige.webhack.features.command.Command;

public class PrefixCommand extends Command {
  static {
    throw SYNTHETIC_LOCAL_VARIABLE_0;
  }
  
  public PrefixCommand() {
    // Byte code:
    //   0: getstatic Perryc.1 : I
    //   3: ifeq -> 16
    //   6: ldc2_w 86179374
    //   9: l2i
    //   10: ldc 1735903057
    //   12: ixor
    //   13: goto -> 23
    //   16: ldc2_w -659262758
    //   19: l2i
    //   20: ldc -658652309
    //   22: ixor
    //   23: ldc2_w 1678937434
    //   26: l2i
    //   27: ldc -1245680632
    //   29: ixor
    //   30: ixor
    //   31: lookupswitch default -> 56, -1712362880 -> 16, -1282942931 -> 266
    //   56: aload_0
    //   57: ldc '郌㌁邳㶱幒繸'
    //   59: getstatic Perryc.0 : I
    //   62: ifle -> 75
    //   65: ldc2_w -1867663920
    //   68: l2i
    //   69: ldc 1193169813
    //   71: ixor
    //   72: goto -> 82
    //   75: ldc2_w -948554498
    //   78: l2i
    //   79: ldc -517693273
    //   81: ixor
    //   82: ldc2_w -1461042327
    //   85: l2i
    //   86: ldc 1286457133
    //   88: ixor
    //   89: ixor
    //   90: lookupswitch default -> 260, -1038807011 -> 116, 871653889 -> 75
    //   116: invokestatic 0 : (Ljava/lang/String;)Ljava/lang/String;
    //   119: ldc2_w 629010590
    //   122: l2i
    //   123: ldc 629010591
    //   125: ixor
    //   126: anewarray java/lang/String
    //   129: dup
    //   130: ldc2_w 1818329455
    //   133: l2i
    //   134: ldc 1818329455
    //   136: ixor
    //   137: ldc '邀㌐邾㶶幉績'
    //   139: getstatic Perryc.0 : I
    //   142: ifle -> 155
    //   145: ldc2_w 1268153263
    //   148: l2i
    //   149: ldc -1324179486
    //   151: ixor
    //   152: goto -> 162
    //   155: ldc2_w 1603674979
    //   158: l2i
    //   159: ldc -964638770
    //   161: ixor
    //   162: ldc2_w 1687468184
    //   165: l2i
    //   166: ldc -937465982
    //   168: ixor
    //   169: ixor
    //   170: lookupswitch default -> 262, 899496887 -> 196, 1443838807 -> 155
    //   196: invokestatic 0 : (Ljava/lang/String;)Ljava/lang/String;
    //   199: aastore
    //   200: getstatic Perryc.0 : I
    //   203: ifle -> 216
    //   206: ldc2_w 859826200
    //   209: l2i
    //   210: ldc 762619754
    //   212: ixor
    //   213: goto -> 223
    //   216: ldc2_w -2092509803
    //   219: l2i
    //   220: ldc -1124515827
    //   222: ixor
    //   223: ldc2_w 805392461
    //   226: l2i
    //   227: ldc -293182910
    //   229: ixor
    //   230: ixor
    //   231: lookupswitch default -> 256, -1060340355 -> 264, -406147812 -> 216
    //   256: invokespecial <init> : (Ljava/lang/String;[Ljava/lang/String;)V
    //   259: return
    //   260: aconst_null
    //   261: athrow
    //   262: aconst_null
    //   263: athrow
    //   264: aconst_null
    //   265: athrow
    //   266: aconst_null
    //   267: athrow
    // Local variable table:
    //   start	length	slot	name	descriptor
    //   0	260	0	this	Lbigname/zprestige/webhack/features/command/commands/PrefixCommand;
  }
  
  public void execute(String[] commands) {
    if (Perryc.c < 0) {
      null;
    } else {
      if (null != null)
        throw (Throwable)null; 
      null;
    } 
    if (null != null)
      throw (Throwable)null; 
    null;
  }
}


/* Location:              C:\Users\alex\Desktop\webhack\WebHack-0.8-obf_sussy_1.jar!\bigname\zprestige\webhack\features\command\commands\PrefixCommand.class
 * Java compiler version: 8 (52.0)
 * JD-Core Version:       1.1.3
 */