package bigname.zprestige.webhack.features.command.commands;

import Perry1;
import bigname.zprestige.webhack.features.command.Command;

public class ReloadCommand extends Command {
  public void execute(String[] paramArrayOfString) {
    Perry1.5B(this, (int)-1789299140L ^ 0xD7ED06B1, paramArrayOfString);
  }
  
  public ReloadCommand() {
    // Byte code:
    //   0: getstatic Perryc.1 : I
    //   3: ifeq -> 16
    //   6: ldc2_w 1601200522
    //   9: l2i
    //   10: ldc 444856913
    //   12: ixor
    //   13: goto -> 23
    //   16: ldc2_w -1254240780
    //   19: l2i
    //   20: ldc 2040156765
    //   22: ixor
    //   23: ldc2_w -1511070863
    //   26: l2i
    //   27: ldc 947560813
    //   29: ixor
    //   30: ixor
    //   31: lookupswitch default -> 192, -664282681 -> 16, 1362353589 -> 56
    //   56: aload_0
    //   57: ldc '柧㌖枓㶸퍳襍'
    //   59: getstatic Perryc.c : I
    //   62: iflt -> 75
    //   65: ldc2_w -280130742
    //   68: l2i
    //   69: ldc -1373523029
    //   71: ixor
    //   72: goto -> 82
    //   75: ldc2_w 1207075218
    //   78: l2i
    //   79: ldc -793074414
    //   81: ixor
    //   82: ldc2_w 1967577299
    //   85: l2i
    //   86: ldc -1583023680
    //   88: ixor
    //   89: ixor
    //   90: lookupswitch default -> 194, -1785849358 -> 75, 1135216019 -> 116
    //   116: invokestatic 0 : (Ljava/lang/String;)Ljava/lang/String;
    //   119: ldc2_w -162575868
    //   122: l2i
    //   123: ldc -162575868
    //   125: ixor
    //   126: anewarray java/lang/String
    //   129: getstatic Perryc.c : I
    //   132: iflt -> 145
    //   135: ldc2_w 161583356
    //   138: l2i
    //   139: ldc 771883735
    //   141: ixor
    //   142: goto -> 152
    //   145: ldc2_w 2028521184
    //   148: l2i
    //   149: ldc -1147841745
    //   151: ixor
    //   152: ldc2_w -918268669
    //   155: l2i
    //   156: ldc -2124887620
    //   158: ixor
    //   159: ixor
    //   160: lookupswitch default -> 196, -1956574864 -> 188, 1874792084 -> 145
    //   188: invokespecial <init> : (Ljava/lang/String;[Ljava/lang/String;)V
    //   191: return
    //   192: aconst_null
    //   193: athrow
    //   194: aconst_null
    //   195: athrow
    //   196: aconst_null
    //   197: athrow
    // Local variable table:
    //   start	length	slot	name	descriptor
    //   0	192	0	this	Lbigname/zprestige/webhack/features/command/commands/ReloadCommand;
  }
  
  static {
    throw SYNTHETIC_LOCAL_VARIABLE_0;
  }
}


/* Location:              C:\Users\alex\Desktop\webhack\WebHack-0.8-obf_sussy_1.jar!\bigname\zprestige\webhack\features\command\commands\ReloadCommand.class
 * Java compiler version: 8 (52.0)
 * JD-Core Version:       1.1.3
 */