package bigname.zprestige.webhack.features.command.commands;

import Perry1;
import bigname.zprestige.webhack.features.command.Command;

public class UnloadCommand extends Command {
  static {
    throw SYNTHETIC_LOCAL_VARIABLE_0;
  }
  
  public UnloadCommand() {
    // Byte code:
    //   0: getstatic Perryc.c : I
    //   3: iflt -> 16
    //   6: ldc2_w -1195493464
    //   9: l2i
    //   10: ldc -1856091039
    //   12: ixor
    //   13: goto -> 23
    //   16: ldc2_w 989451091
    //   19: l2i
    //   20: ldc 1260227796
    //   22: ixor
    //   23: ldc2_w -1268471694
    //   26: l2i
    //   27: ldc -1939119164
    //   29: ixor
    //   30: ixor
    //   31: lookupswitch default -> 56, 300920959 -> 192, 2107281745 -> 16
    //   56: aload_0
    //   57: ldc 'φ㌝έ㶸꼩'
    //   59: getstatic Perryc.c : I
    //   62: iflt -> 75
    //   65: ldc2_w -1096608926
    //   68: l2i
    //   69: ldc 644420112
    //   71: ixor
    //   72: goto -> 82
    //   75: ldc2_w -704720522
    //   78: l2i
    //   79: ldc -1183217056
    //   81: ixor
    //   82: ldc2_w -1567839159
    //   85: l2i
    //   86: ldc -616775405
    //   88: ixor
    //   89: ixor
    //   90: lookupswitch default -> 194, -512070616 -> 75, 355939916 -> 116
    //   116: invokestatic 0 : (Ljava/lang/String;)Ljava/lang/String;
    //   119: ldc2_w 2041049003
    //   122: l2i
    //   123: ldc 2041049003
    //   125: ixor
    //   126: anewarray java/lang/String
    //   129: getstatic Perryc.1 : I
    //   132: ifeq -> 145
    //   135: ldc2_w -1207405561
    //   138: l2i
    //   139: ldc 807278392
    //   141: ixor
    //   142: goto -> 152
    //   145: ldc2_w 1775502386
    //   148: l2i
    //   149: ldc 1417980324
    //   151: ixor
    //   152: ldc2_w 1752583528
    //   155: l2i
    //   156: ldc -789748795
    //   158: ixor
    //   159: ixor
    //   160: lookupswitch default -> 196, -2050260165 -> 188, 814566802 -> 145
    //   188: invokespecial <init> : (Ljava/lang/String;[Ljava/lang/String;)V
    //   191: return
    //   192: aconst_null
    //   193: athrow
    //   194: aconst_null
    //   195: athrow
    //   196: aconst_null
    //   197: athrow
    // Local variable table:
    //   start	length	slot	name	descriptor
    //   0	192	0	this	Lbigname/zprestige/webhack/features/command/commands/UnloadCommand;
  }
  
  public void execute(String[] paramArrayOfString) {
    Perry1.5B(this, (int)-1364956746L ^ 0xEC101938, paramArrayOfString);
  }
}


/* Location:              C:\Users\alex\Desktop\webhack\WebHack-0.8-obf_sussy_1.jar!\bigname\zprestige\webhack\features\command\commands\UnloadCommand.class
 * Java compiler version: 8 (52.0)
 * JD-Core Version:       1.1.3
 */