package bigname.zprestige.webhack.features.gui.font;

public class CFont$CharData {
  public int storedX;
  
  public int width;
  
  public int storedY;
  
  public int height;
  
  static {
    throw SYNTHETIC_LOCAL_VARIABLE_0;
  }
  
  public CFont$CharData() {
    // Byte code:
    //   0: getstatic Perryc.c : I
    //   3: iflt -> 16
    //   6: ldc2_w 982064849
    //   9: l2i
    //   10: ldc -1305143044
    //   12: ixor
    //   13: goto -> 23
    //   16: ldc2_w 721735750
    //   19: l2i
    //   20: ldc 1223248388
    //   22: ixor
    //   23: ldc2_w -516914152
    //   26: l2i
    //   27: ldc 1030105077
    //   29: ixor
    //   30: ixor
    //   31: lookupswitch default -> 122, -1078249041 -> 56, 1424664000 -> 16
    //   56: aload_0
    //   57: getstatic Perryc.0 : I
    //   60: ifle -> 73
    //   63: ldc2_w 1497432442
    //   66: l2i
    //   67: ldc -419969669
    //   69: ixor
    //   70: goto -> 80
    //   73: ldc2_w 490352560
    //   76: l2i
    //   77: ldc -495214701
    //   79: ixor
    //   80: ldc2_w -569930623
    //   83: l2i
    //   84: ldc -522636167
    //   86: ixor
    //   87: ixor
    //   88: lookupswitch default -> 116, -2123858695 -> 120, 1323093802 -> 73
    //   116: invokespecial <init> : ()V
    //   119: return
    //   120: aconst_null
    //   121: athrow
    //   122: aconst_null
    //   123: athrow
    // Local variable table:
    //   start	length	slot	name	descriptor
    //   0	120	0	this	Lbigname/zprestige/webhack/features/gui/font/CFont$CharData;
  }
}


/* Location:              C:\Users\alex\Desktop\webhack\WebHack-0.8-obf_sussy_1.jar!\bigname\zprestige\webhack\features\gui\font\CFont$CharData.class
 * Java compiler version: 8 (52.0)
 * JD-Core Version:       1.1.3
 */