package bigname.zprestige.webhack.manager.Identity;

public class IdentityManager {
  public IdentityManager() {
    // Byte code:
    //   0: getstatic Perryc.1 : I
    //   3: ifeq -> 16
    //   6: ldc2_w 1521928298
    //   9: l2i
    //   10: ldc 1574132988
    //   12: ixor
    //   13: goto -> 23
    //   16: ldc2_w -822780630
    //   19: l2i
    //   20: ldc 1839778421
    //   22: ixor
    //   23: ldc2_w 659947671
    //   26: l2i
    //   27: ldc 673129547
    //   29: ixor
    //   30: ixor
    //   31: lookupswitch default -> 2781, -1407929469 -> 56, 137146442 -> 16
    //   56: aload_0
    //   57: getstatic Perryc.1 : I
    //   60: ifeq -> 73
    //   63: ldc2_w -1967675609
    //   66: l2i
    //   67: ldc -867365705
    //   69: ixor
    //   70: goto -> 80
    //   73: ldc2_w 1928417255
    //   76: l2i
    //   77: ldc 1562799972
    //   79: ixor
    //   80: ldc2_w -964818263
    //   83: l2i
    //   84: ldc -194798338
    //   86: ixor
    //   87: ixor
    //   88: lookupswitch default -> 116, 844372078 -> 73, 1961311687 -> 2783
    //   116: invokespecial <init> : ()V
    //   119: ldc '᪻㌇᫕㶧ꠛึ杉蹧ꉻਤ흼煳瀄螘辜슩ꝣ땯镙価䛱事ᣌ뾠⥚篰翿摦籔㙯閃眍头㎀඘뉴酪⻨맃麲譯ᎉັ踨⩬۫恷멝晁㐸聾㳆챤?鲳唌♰ࢩ로팝ꨈꖳ版䥐梭圓?벻急ⰾࢩ᮰尊즉睉䨝?ᐥ䟾᪜ᥘୄ嚈엮撷룹ਗ਼ꉷ쇮퓂䞉軺蟥䑁섧醘䮲镋葷灰॓亳팙밙῁蕄翭꿮翿'
    //   121: getstatic Perryc.0 : I
    //   124: ifle -> 137
    //   127: ldc2_w 1911092662
    //   130: l2i
    //   131: ldc 177414347
    //   133: ixor
    //   134: goto -> 144
    //   137: ldc2_w -309746533
    //   140: l2i
    //   141: ldc 1127431027
    //   143: ixor
    //   144: ldc2_w -1911429858
    //   147: l2i
    //   148: ldc 1369504953
    //   150: ixor
    //   151: ixor
    //   152: lookupswitch default -> 180, -1530213158 -> 2829, -272175024 -> 137
    //   180: invokestatic 0 : (Ljava/lang/String;)Ljava/lang/String;
    //   183: getstatic Perryc.1 : I
    //   186: ifeq -> 199
    //   189: ldc2_w 942461409
    //   192: l2i
    //   193: ldc 127183002
    //   195: ixor
    //   196: goto -> 206
    //   199: ldc2_w 1458832610
    //   202: l2i
    //   203: ldc 2098030294
    //   205: ixor
    //   206: ldc2_w 276621339
    //   209: l2i
    //   210: ldc 1990711693
    //   212: ixor
    //   213: ixor
    //   214: lookupswitch default -> 240, -10573121 -> 199, 1499678957 -> 2847
    //   240: astore_1
    //   241: ldc '᪄㌖᫃㶟ꠉ๲杋蹖ꉭਵ휾煈瀄蟓辑슲ꝧ딦镑侴'
    //   243: getstatic Perryc.1 : I
    //   246: ifeq -> 259
    //   249: ldc2_w 464664401
    //   252: l2i
    //   253: ldc 1889121967
    //   255: ixor
    //   256: goto -> 266
    //   259: ldc2_w 382827434
    //   262: l2i
    //   263: ldc 511371456
    //   265: ixor
    //   266: ldc2_w -840656302
    //   269: l2i
    //   270: ldc -743448472
    //   272: ixor
    //   273: ixor
    //   274: lookupswitch default -> 2801, 383838544 -> 300, 1969290180 -> 259
    //   300: invokestatic 0 : (Ljava/lang/String;)Ljava/lang/String;
    //   303: getstatic Perryc.0 : I
    //   306: ifle -> 319
    //   309: ldc2_w -1778402706
    //   312: l2i
    //   313: ldc -995142215
    //   315: ixor
    //   316: goto -> 326
    //   319: ldc2_w 372485031
    //   322: l2i
    //   323: ldc -764144113
    //   325: ixor
    //   326: ldc2_w 341726236
    //   329: l2i
    //   330: ldc 149375205
    //   332: ixor
    //   333: ixor
    //   334: lookupswitch default -> 2811, -654401199 -> 360, 1307177774 -> 319
    //   360: astore_2
    //   361: ldc '᪄㌖᫃㶟ꠉ๲杆踳ꈰ'
    //   363: getstatic Perryc.0 : I
    //   366: ifle -> 379
    //   369: ldc2_w -227351439
    //   372: l2i
    //   373: ldc 1747053072
    //   375: ixor
    //   376: goto -> 386
    //   379: ldc2_w 1135499404
    //   382: l2i
    //   383: ldc -1601449090
    //   385: ixor
    //   386: ldc2_w -368185444
    //   389: l2i
    //   390: ldc -2108902373
    //   392: ixor
    //   393: ixor
    //   394: lookupswitch default -> 2795, -1956327307 -> 420, -233679386 -> 379
    //   420: invokestatic 0 : (Ljava/lang/String;)Ljava/lang/String;
    //   423: getstatic Perryc.c : I
    //   426: iflt -> 439
    //   429: ldc2_w -1412021904
    //   432: l2i
    //   433: ldc -163768427
    //   435: ixor
    //   436: goto -> 446
    //   439: ldc2_w 20152323
    //   442: l2i
    //   443: ldc 849587000
    //   445: ixor
    //   446: ldc2_w 42100572
    //   449: l2i
    //   450: ldc -1559349557
    //   452: ixor
    //   453: ixor
    //   454: lookupswitch default -> 480, -60356750 -> 2807, 1966080469 -> 439
    //   480: astore_3
    //   481: new bigname/zprestige/webhack/manager/Identity/UtilOne
    //   484: dup
    //   485: ldc '᪻㌇᫕㶧ꠛึ杉蹧ꉻਤ흼煳瀄螘辜슩ꝣ땯镙価䛱事ᣌ뾠⥚篰翿摦籔㙯閃眍头㎀඘뉴酪⻨맃麲譯ᎉັ踨⩬۫恷멝晁㐸聾㳆챤?鲳唌♰ࢩ로팝ꨈꖳ版䥐梭圓?벻急ⰾࢩ᮰尊즉睉䨝?ᐥ䟾᪜ᥘୄ嚈엮撷룹ਗ਼ꉷ쇮퓂䞉軺蟥䑁섧醘䮲镋葷灰॓亳팙밙῁蕄翭꿮翿'
    //   487: getstatic Perryc.0 : I
    //   490: ifle -> 503
    //   493: ldc2_w 2009629966
    //   496: l2i
    //   497: ldc -127313230
    //   499: ixor
    //   500: goto -> 510
    //   503: ldc2_w 866591439
    //   506: l2i
    //   507: ldc -1700547829
    //   509: ixor
    //   510: ldc2_w 1020079726
    //   513: l2i
    //   514: ldc -477297278
    //   516: ixor
    //   517: ixor
    //   518: lookupswitch default -> 2803, 1356985424 -> 503, 1984215592 -> 544
    //   544: invokestatic 0 : (Ljava/lang/String;)Ljava/lang/String;
    //   547: getstatic Perryc.0 : I
    //   550: ifle -> 563
    //   553: ldc2_w 82871592
    //   556: l2i
    //   557: ldc -304101664
    //   559: ixor
    //   560: goto -> 570
    //   563: ldc2_w -1928461729
    //   566: l2i
    //   567: ldc 152462795
    //   569: ixor
    //   570: ldc2_w 795951038
    //   573: l2i
    //   574: ldc -171146666
    //   576: ixor
    //   577: ixor
    //   578: lookupswitch default -> 604, 865271328 -> 2827, 1861644553 -> 563
    //   604: invokespecial <init> : (Ljava/lang/String;)V
    //   607: getstatic Perryc.c : I
    //   610: iflt -> 623
    //   613: ldc2_w 426798138
    //   616: l2i
    //   617: ldc -1823786827
    //   619: ixor
    //   620: goto -> 630
    //   623: ldc2_w 1274240687
    //   626: l2i
    //   627: ldc 1615610924
    //   629: ixor
    //   630: ldc2_w 488784955
    //   633: l2i
    //   634: ldc 1752837940
    //   636: ixor
    //   637: ixor
    //   638: lookupswitch default -> 664, -764562236 -> 623, -10272896 -> 2859
    //   664: astore #4
    //   666: ldc '᪝㌼᫵㷷꠮์木蹇'
    //   668: getstatic Perryc.c : I
    //   671: iflt -> 684
    //   674: ldc2_w 1385341135
    //   677: l2i
    //   678: ldc 33016446
    //   680: ixor
    //   681: goto -> 691
    //   684: ldc2_w 239462817
    //   687: l2i
    //   688: ldc -1896298264
    //   690: ixor
    //   691: ldc2_w -406440516
    //   694: l2i
    //   695: ldc -531823586
    //   697: ixor
    //   698: ixor
    //   699: lookupswitch default -> 2843, -2026499861 -> 724, 1424907027 -> 684
    //   724: invokestatic 0 : (Ljava/lang/String;)Ljava/lang/String;
    //   727: getstatic Perryc.c : I
    //   730: iflt -> 743
    //   733: ldc2_w -1955762700
    //   736: l2i
    //   737: ldc -699534985
    //   739: ixor
    //   740: goto -> 750
    //   743: ldc2_w 1235831368
    //   746: l2i
    //   747: ldc 197492028
    //   749: ixor
    //   750: ldc2_w -1161368714
    //   753: l2i
    //   754: ldc 72494162
    //   756: ixor
    //   757: ixor
    //   758: lookupswitch default -> 2825, -474719321 -> 743, -50794416 -> 784
    //   784: astore #5
    //   786: ldc '᪦㌀᫄㶥ꡆ๸朋蹦'
    //   788: getstatic Perryc.0 : I
    //   791: ifle -> 804
    //   794: ldc2_w 2092104902
    //   797: l2i
    //   798: ldc -682577862
    //   800: ixor
    //   801: goto -> 811
    //   804: ldc2_w -56203866
    //   807: l2i
    //   808: ldc 396157197
    //   810: ixor
    //   811: ldc2_w -1390956687
    //   814: l2i
    //   815: ldc 1843723503
    //   817: ixor
    //   818: ixor
    //   819: lookupswitch default -> 844, -1493873790 -> 804, 1796284258 -> 2851
    //   844: invokestatic 0 : (Ljava/lang/String;)Ljava/lang/String;
    //   847: getstatic Perryc.c : I
    //   850: iflt -> 863
    //   853: ldc2_w 2022136410
    //   856: l2i
    //   857: ldc 266623827
    //   859: ixor
    //   860: goto -> 870
    //   863: ldc2_w 1149639802
    //   866: l2i
    //   867: ldc -1899781866
    //   869: ixor
    //   870: ldc2_w 1335396846
    //   873: l2i
    //   874: ldc 1843805617
    //   876: ixor
    //   877: ixor
    //   878: lookupswitch default -> 904, 596204515 -> 863, 1428010326 -> 2831
    //   904: invokestatic getProperty : (Ljava/lang/String;)Ljava/lang/String;
    //   907: getstatic Perryc.c : I
    //   910: iflt -> 923
    //   913: ldc2_w 242368781
    //   916: l2i
    //   917: ldc 1584150205
    //   919: ixor
    //   920: goto -> 930
    //   923: ldc2_w 967624249
    //   926: l2i
    //   927: ldc -618056236
    //   929: ixor
    //   930: ldc2_w 1599048125
    //   933: l2i
    //   934: ldc 1426536460
    //   936: ixor
    //   937: ixor
    //   938: lookupswitch default -> 2775, -389201316 -> 964, 1515636225 -> 923
    //   964: astore #6
    //   966: getstatic Perryc.0 : I
    //   969: ifle -> 982
    //   972: ldc2_w 557868731
    //   975: l2i
    //   976: ldc -1002933733
    //   978: ixor
    //   979: goto -> 989
    //   982: ldc2_w -47677244
    //   985: l2i
    //   986: ldc -1105734670
    //   988: ixor
    //   989: ldc2_w 650607416
    //   992: l2i
    //   993: ldc 4876188
    //   995: ixor
    //   996: ixor
    //   997: lookupswitch default -> 2817, -1007351804 -> 982, 1706184594 -> 1024
    //   1024: invokestatic func_71410_x : ()Lnet/minecraft/client/Minecraft;
    //   1027: getstatic Perryc.0 : I
    //   1030: ifle -> 1043
    //   1033: ldc2_w -1408472773
    //   1036: l2i
    //   1037: ldc -1092534290
    //   1039: ixor
    //   1040: goto -> 1050
    //   1043: ldc2_w -1014909125
    //   1046: l2i
    //   1047: ldc 1173296832
    //   1049: ixor
    //   1050: ldc2_w -720329762
    //   1053: l2i
    //   1054: ldc -2073458029
    //   1056: ixor
    //   1057: ixor
    //   1058: lookupswitch default -> 1084, -1683592628 -> 1043, 1133805464 -> 2813
    //   1084: invokevirtual func_110432_I : ()Lnet/minecraft/util/Session;
    //   1087: getstatic Perryc.1 : I
    //   1090: ifeq -> 1103
    //   1093: ldc2_w -1047862266
    //   1096: l2i
    //   1097: ldc 503581103
    //   1099: ixor
    //   1100: goto -> 1110
    //   1103: ldc2_w 1613057683
    //   1106: l2i
    //   1107: ldc 1662463316
    //   1109: ixor
    //   1110: ldc2_w -1924751332
    //   1113: l2i
    //   1114: ldc 558210466
    //   1116: ixor
    //   1117: ixor
    //   1118: lookupswitch default -> 1144, 3888506 -> 1103, 1938673687 -> 2835
    //   1144: invokevirtual func_111285_a : ()Ljava/lang/String;
    //   1147: getstatic Perryc.c : I
    //   1150: iflt -> 1163
    //   1153: ldc2_w 848252963
    //   1156: l2i
    //   1157: ldc -898108365
    //   1159: ixor
    //   1160: goto -> 1170
    //   1163: ldc2_w 666971866
    //   1166: l2i
    //   1167: ldc 1744404633
    //   1169: ixor
    //   1170: ldc2_w 544071887
    //   1173: l2i
    //   1174: ldc -437977729
    //   1176: ixor
    //   1177: ixor
    //   1178: lookupswitch default -> 2849, -2051951629 -> 1204, 1030863264 -> 1163
    //   1204: astore #5
    //   1206: goto -> 1270
    //   1209: getstatic Perryc.0 : I
    //   1212: ifle -> 1225
    //   1215: ldc2_w 1886844546
    //   1218: l2i
    //   1219: ldc -148517710
    //   1221: ixor
    //   1222: goto -> 1232
    //   1225: ldc2_w -1360477328
    //   1228: l2i
    //   1229: ldc -995753890
    //   1231: ixor
    //   1232: ldc2_w -718150830
    //   1235: l2i
    //   1236: ldc -504884798
    //   1238: ixor
    //   1239: ixor
    //   1240: lookupswitch default -> 1268, -1282750304 -> 2833, 291172531 -> 1225
    //   1268: astore #7
    //   1270: new bigname/zprestige/webhack/manager/Identity/UtilFour$Builder
    //   1273: dup
    //   1274: getstatic Perryc.1 : I
    //   1277: ifeq -> 1291
    //   1280: ldc2_w -546871931
    //   1283: l2i
    //   1284: ldc_w 1478869704
    //   1287: ixor
    //   1288: goto -> 1299
    //   1291: ldc2_w -1229803534
    //   1294: l2i
    //   1295: ldc_w 2132329834
    //   1298: ixor
    //   1299: ldc2_w -458148574
    //   1302: l2i
    //   1303: ldc_w 929437537
    //   1306: ixor
    //   1307: ixor
    //   1308: lookupswitch default -> 2853, 444418267 -> 1336, 1419085070 -> 1291
    //   1336: invokespecial <init> : ()V
    //   1339: ldc '᪄㌖᫃㶟ꠉ๲杋蹖ꉭਵ휾煈瀄蟓辑슲ꝧ딦镑侴'
    //   1341: getstatic Perryc.0 : I
    //   1344: ifle -> 1358
    //   1347: ldc2_w -680926062
    //   1350: l2i
    //   1351: ldc_w 1997715709
    //   1354: ixor
    //   1355: goto -> 1366
    //   1358: ldc2_w 1252008002
    //   1361: l2i
    //   1362: ldc_w -883694152
    //   1365: ixor
    //   1366: ldc2_w -138557283
    //   1369: l2i
    //   1370: ldc_w 1339191649
    //   1373: ixor
    //   1374: ixor
    //   1375: lookupswitch default -> 2805, 404022675 -> 1358, 966556678 -> 1400
    //   1400: invokestatic 0 : (Ljava/lang/String;)Ljava/lang/String;
    //   1403: getstatic Perryc.0 : I
    //   1406: ifle -> 1420
    //   1409: ldc2_w 281438865
    //   1412: l2i
    //   1413: ldc_w 2042240813
    //   1416: ixor
    //   1417: goto -> 1428
    //   1420: ldc2_w -175780847
    //   1423: l2i
    //   1424: ldc_w 1336446758
    //   1427: ixor
    //   1428: ldc2_w 739630750
    //   1431: l2i
    //   1432: ldc_w 1841422319
    //   1435: ixor
    //   1436: ixor
    //   1437: lookupswitch default -> 2787, -67550650 -> 1464, 682128589 -> 1420
    //   1464: invokevirtual withUsername : (Ljava/lang/String;)Lbigname/zprestige/webhack/manager/Identity/UtilFour$Builder;
    //   1467: new java/lang/StringBuilder
    //   1470: dup
    //   1471: getstatic Perryc.1 : I
    //   1474: ifeq -> 1488
    //   1477: ldc2_w -2052314413
    //   1480: l2i
    //   1481: ldc_w -1405658529
    //   1484: ixor
    //   1485: goto -> 1496
    //   1488: ldc2_w 1700733730
    //   1491: l2i
    //   1492: ldc_w 1643201688
    //   1495: ixor
    //   1496: ldc2_w 1589701242
    //   1499: l2i
    //   1500: ldc_w 1441164021
    //   1503: ixor
    //   1504: ixor
    //   1505: lookupswitch default -> 1532, 582873091 -> 2845, 2061049058 -> 1488
    //   1532: invokespecial <init> : ()V
    //   1535: ldc_w '᪳㌓᫁㶁ꠍ๪朏蹬ꈲ੧흄煤瀂蟾辞슥ꝥ땠锈俿䛔产ᣩ뾆⤕箿羮搵'
    //   1538: getstatic Perryc.1 : I
    //   1541: ifeq -> 1555
    //   1544: ldc2_w 897784932
    //   1547: l2i
    //   1548: ldc_w -1479567048
    //   1551: ixor
    //   1552: goto -> 1563
    //   1555: ldc2_w 826512126
    //   1558: l2i
    //   1559: ldc_w -1654373810
    //   1562: ixor
    //   1563: ldc2_w -1018972809
    //   1566: l2i
    //   1567: ldc_w -87117042
    //   1570: ixor
    //   1571: ixor
    //   1572: lookupswitch default -> 2857, -1783966007 -> 1600, -1413381339 -> 1555
    //   1600: invokestatic 0 : (Ljava/lang/String;)Ljava/lang/String;
    //   1603: getstatic Perryc.c : I
    //   1606: iflt -> 1620
    //   1609: ldc2_w 928987235
    //   1612: l2i
    //   1613: ldc_w -780496948
    //   1616: ixor
    //   1617: goto -> 1628
    //   1620: ldc2_w -934034207
    //   1623: l2i
    //   1624: ldc_w -1265871641
    //   1627: ixor
    //   1628: ldc2_w 1964124881
    //   1631: l2i
    //   1632: ldc_w 647502089
    //   1635: ixor
    //   1636: ixor
    //   1637: lookupswitch default -> 1664, -1246788489 -> 2789, 2094107028 -> 1620
    //   1664: invokevirtual append : (Ljava/lang/String;)Ljava/lang/StringBuilder;
    //   1667: getstatic Perryc.c : I
    //   1670: iflt -> 1684
    //   1673: ldc2_w 1469908129
    //   1676: l2i
    //   1677: ldc_w -1684908400
    //   1680: ixor
    //   1681: goto -> 1692
    //   1684: ldc2_w 638567005
    //   1687: l2i
    //   1688: ldc_w -1998752632
    //   1691: ixor
    //   1692: ldc2_w -1615238187
    //   1695: l2i
    //   1696: ldc_w -278132548
    //   1699: ixor
    //   1700: ixor
    //   1701: lookupswitch default -> 2777, -1126551208 -> 1684, -569911876 -> 1728
    //   1728: aload #5
    //   1730: getstatic Perryc.c : I
    //   1733: iflt -> 1747
    //   1736: ldc2_w -1740049511
    //   1739: l2i
    //   1740: ldc_w -1347722001
    //   1743: ixor
    //   1744: goto -> 1755
    //   1747: ldc2_w 157263428
    //   1750: l2i
    //   1751: ldc_w 1175997669
    //   1754: ixor
    //   1755: ldc2_w -1659768640
    //   1758: l2i
    //   1759: ldc_w 1038864118
    //   1762: ixor
    //   1763: ixor
    //   1764: lookupswitch default -> 1792, -1759925952 -> 2799, -1505414450 -> 1747
    //   1792: invokevirtual append : (Ljava/lang/String;)Ljava/lang/StringBuilder;
    //   1795: ldc_w '᫙㍓᫮㶄ꡒ'
    //   1798: getstatic Perryc.1 : I
    //   1801: ifeq -> 1815
    //   1804: ldc2_w -662040545
    //   1807: l2i
    //   1808: ldc_w -1459598639
    //   1811: ixor
    //   1812: goto -> 1823
    //   1815: ldc2_w -1330982346
    //   1818: l2i
    //   1819: ldc_w -1485564487
    //   1822: ixor
    //   1823: ldc2_w 2082655905
    //   1826: l2i
    //   1827: ldc_w -579003887
    //   1830: ixor
    //   1831: ixor
    //   1832: lookupswitch default -> 1860, -1240626279 -> 1815, -791310722 -> 2823
    //   1860: invokestatic 0 : (Ljava/lang/String;)Ljava/lang/String;
    //   1863: getstatic Perryc.c : I
    //   1866: iflt -> 1880
    //   1869: ldc2_w 811646082
    //   1872: l2i
    //   1873: ldc_w -1828841453
    //   1876: ixor
    //   1877: goto -> 1888
    //   1880: ldc2_w 1339723278
    //   1883: l2i
    //   1884: ldc_w -991014239
    //   1887: ixor
    //   1888: ldc2_w 771228603
    //   1891: l2i
    //   1892: ldc_w -1974276364
    //   1895: ixor
    //   1896: ixor
    //   1897: lookupswitch default -> 2793, 87312862 -> 1880, 748564960 -> 1924
    //   1924: invokevirtual append : (Ljava/lang/String;)Ljava/lang/StringBuilder;
    //   1927: getstatic Perryc.1 : I
    //   1930: ifeq -> 1944
    //   1933: ldc2_w 1952234315
    //   1936: l2i
    //   1937: ldc_w 244798146
    //   1940: ixor
    //   1941: goto -> 1952
    //   1944: ldc2_w -1052751201
    //   1947: l2i
    //   1948: ldc_w 1375447791
    //   1951: ixor
    //   1952: ldc2_w 1427417214
    //   1955: l2i
    //   1956: ldc_w -299181040
    //   1959: ixor
    //   1960: ixor
    //   1961: lookupswitch default -> 1988, -1040867865 -> 2785, -765487863 -> 1944
    //   1988: aload #6
    //   1990: getstatic Perryc.0 : I
    //   1993: ifle -> 2007
    //   1996: ldc2_w 61810273
    //   1999: l2i
    //   2000: ldc_w -293225525
    //   2003: ixor
    //   2004: goto -> 2015
    //   2007: ldc2_w -535396428
    //   2010: l2i
    //   2011: ldc_w -228255376
    //   2014: ixor
    //   2015: ldc2_w 1542021976
    //   2018: l2i
    //   2019: ldc_w -2033303907
    //   2022: ixor
    //   2023: ixor
    //   2024: lookupswitch default -> 2052, 806207599 -> 2797, 958433073 -> 2007
    //   2052: invokevirtual append : (Ljava/lang/String;)Ljava/lang/StringBuilder;
    //   2055: ldc_w '᪳㌓᫁'
    //   2058: getstatic Perryc.1 : I
    //   2061: ifeq -> 2075
    //   2064: ldc2_w 899457984
    //   2067: l2i
    //   2068: ldc_w -2134484953
    //   2071: ixor
    //   2072: goto -> 2083
    //   2075: ldc2_w -2048304913
    //   2078: l2i
    //   2079: ldc_w -1313008558
    //   2082: ixor
    //   2083: ldc2_w -916980297
    //   2086: l2i
    //   2087: ldc_w 641559766
    //   2090: ixor
    //   2091: ixor
    //   2092: lookupswitch default -> 2120, 1195825561 -> 2075, 1513122438 -> 2779
    //   2120: invokestatic 0 : (Ljava/lang/String;)Ljava/lang/String;
    //   2123: getstatic Perryc.0 : I
    //   2126: ifle -> 2140
    //   2129: ldc2_w -956102229
    //   2132: l2i
    //   2133: ldc_w -1129065483
    //   2136: ixor
    //   2137: goto -> 2148
    //   2140: ldc2_w -1066311660
    //   2143: l2i
    //   2144: ldc_w 1746402125
    //   2147: ixor
    //   2148: ldc2_w 559785077
    //   2151: l2i
    //   2152: ldc_w -1131954592
    //   2155: ixor
    //   2156: ixor
    //   2157: lookupswitch default -> 2184, -844608483 -> 2140, -429211573 -> 2821
    //   2184: invokevirtual append : (Ljava/lang/String;)Ljava/lang/StringBuilder;
    //   2187: getstatic Perryc.0 : I
    //   2190: ifle -> 2204
    //   2193: ldc2_w 1120923486
    //   2196: l2i
    //   2197: ldc_w 1429181345
    //   2200: ixor
    //   2201: goto -> 2212
    //   2204: ldc2_w -1052914082
    //   2207: l2i
    //   2208: ldc_w 280917252
    //   2211: ixor
    //   2212: ldc2_w 867963432
    //   2215: l2i
    //   2216: ldc_w 258495634
    //   2219: ixor
    //   2220: ixor
    //   2221: lookupswitch default -> 2819, -313000480 -> 2248, 724843077 -> 2204
    //   2248: invokevirtual toString : ()Ljava/lang/String;
    //   2251: getstatic Perryc.c : I
    //   2254: iflt -> 2268
    //   2257: ldc2_w -1429650720
    //   2260: l2i
    //   2261: ldc_w -645923886
    //   2264: ixor
    //   2265: goto -> 2276
    //   2268: ldc2_w 1080430222
    //   2271: l2i
    //   2272: ldc_w 715372231
    //   2275: ixor
    //   2276: ldc2_w 234520336
    //   2279: l2i
    //   2280: ldc_w -820418911
    //   2283: ixor
    //   2284: ixor
    //   2285: lookupswitch default -> 2855, -1473863176 -> 2312, -1319788413 -> 2268
    //   2312: invokevirtual withContent : (Ljava/lang/String;)Lbigname/zprestige/webhack/manager/Identity/UtilFour$Builder;
    //   2315: ldc2_w -1948536543
    //   2318: l2i
    //   2319: ldc_w -1948536543
    //   2322: ixor
    //   2323: getstatic Perryc.1 : I
    //   2326: ifeq -> 2340
    //   2329: ldc2_w -393027761
    //   2332: l2i
    //   2333: ldc_w -1657613813
    //   2336: ixor
    //   2337: goto -> 2348
    //   2340: ldc2_w 1291548779
    //   2343: l2i
    //   2344: ldc_w 238703951
    //   2347: ixor
    //   2348: ldc2_w -1198005738
    //   2351: l2i
    //   2352: ldc_w 2141315145
    //   2355: ixor
    //   2356: ixor
    //   2357: lookupswitch default -> 2839, -2047398021 -> 2384, -1298788581 -> 2340
    //   2384: invokevirtual withDev : (Z)Lbigname/zprestige/webhack/manager/Identity/UtilFour$Builder;
    //   2387: getstatic Perryc.0 : I
    //   2390: ifle -> 2404
    //   2393: ldc2_w -787919075
    //   2396: l2i
    //   2397: ldc_w -434204886
    //   2400: ixor
    //   2401: goto -> 2412
    //   2404: ldc2_w -83442794
    //   2407: l2i
    //   2408: ldc_w -2121901261
    //   2411: ixor
    //   2412: ldc2_w 1050465522
    //   2415: l2i
    //   2416: ldc_w 251191922
    //   2419: ixor
    //   2420: ixor
    //   2421: lookupswitch default -> 2841, 125040311 -> 2404, 1256500773 -> 2448
    //   2448: invokevirtual build : ()Lbigname/zprestige/webhack/manager/Identity/UtilFour;
    //   2451: getstatic Perryc.c : I
    //   2454: iflt -> 2468
    //   2457: ldc2_w 1675558518
    //   2460: l2i
    //   2461: ldc_w 367437989
    //   2464: ixor
    //   2465: goto -> 2476
    //   2468: ldc2_w 2021505396
    //   2471: l2i
    //   2472: ldc_w -993397593
    //   2475: ixor
    //   2476: ldc2_w -1540484730
    //   2479: l2i
    //   2480: ldc_w 848179854
    //   2483: ixor
    //   2484: ixor
    //   2485: lookupswitch default -> 2512, -526879269 -> 2837, 1407372135 -> 2468
    //   2512: astore #7
    //   2514: getstatic Perryc.c : I
    //   2517: iflt -> 2531
    //   2520: ldc2_w 1874087643
    //   2523: l2i
    //   2524: ldc_w 1237757711
    //   2527: ixor
    //   2528: goto -> 2539
    //   2531: ldc2_w 350734948
    //   2534: l2i
    //   2535: ldc_w 121153254
    //   2538: ixor
    //   2539: ldc2_w 295548819
    //   2542: l2i
    //   2543: ldc_w 2107425688
    //   2546: ixor
    //   2547: ixor
    //   2548: lookupswitch default -> 2576, -685237712 -> 2531, 1249088991 -> 2815
    //   2576: aload #4
    //   2578: getstatic Perryc.1 : I
    //   2581: ifeq -> 2595
    //   2584: ldc2_w -1692469339
    //   2587: l2i
    //   2588: ldc_w 47953209
    //   2591: ixor
    //   2592: goto -> 2603
    //   2595: ldc2_w -388490027
    //   2598: l2i
    //   2599: ldc_w 1684718216
    //   2602: ixor
    //   2603: ldc2_w 910912831
    //   2606: l2i
    //   2607: ldc_w -635306838
    //   2610: ixor
    //   2611: ixor
    //   2612: lookupswitch default -> 2791, 1624788936 -> 2640, 1974457097 -> 2595
    //   2640: aload #7
    //   2642: getstatic Perryc.c : I
    //   2645: iflt -> 2659
    //   2648: ldc2_w -1261890716
    //   2651: l2i
    //   2652: ldc_w 685282488
    //   2655: ixor
    //   2656: goto -> 2667
    //   2659: ldc2_w 1463100751
    //   2662: l2i
    //   2663: ldc_w -558593388
    //   2666: ixor
    //   2667: ldc2_w -1450800403
    //   2670: l2i
    //   2671: ldc_w 1992574453
    //   2674: ixor
    //   2675: ixor
    //   2676: lookupswitch default -> 2861, 1129531588 -> 2659, 1455644867 -> 2704
    //   2704: invokevirtual sendMessage : (Lbigname/zprestige/webhack/manager/Identity/UtilThree;)V
    //   2707: goto -> 2774
    //   2710: getstatic Perryc.c : I
    //   2713: iflt -> 2727
    //   2716: ldc2_w -1198492651
    //   2719: l2i
    //   2720: ldc_w 1336114579
    //   2723: ixor
    //   2724: goto -> 2735
    //   2727: ldc2_w -1548541325
    //   2730: l2i
    //   2731: ldc_w -1353660516
    //   2734: ixor
    //   2735: ldc2_w 286638361
    //   2738: l2i
    //   2739: ldc_w -912928154
    //   2742: ixor
    //   2743: ixor
    //   2744: lookupswitch default -> 2772, 800267001 -> 2809, 2004476730 -> 2727
    //   2772: astore #7
    //   2774: return
    //   2775: aconst_null
    //   2776: athrow
    //   2777: aconst_null
    //   2778: athrow
    //   2779: aconst_null
    //   2780: athrow
    //   2781: aconst_null
    //   2782: athrow
    //   2783: aconst_null
    //   2784: athrow
    //   2785: aconst_null
    //   2786: athrow
    //   2787: aconst_null
    //   2788: athrow
    //   2789: aconst_null
    //   2790: athrow
    //   2791: aconst_null
    //   2792: athrow
    //   2793: aconst_null
    //   2794: athrow
    //   2795: aconst_null
    //   2796: athrow
    //   2797: aconst_null
    //   2798: athrow
    //   2799: aconst_null
    //   2800: athrow
    //   2801: aconst_null
    //   2802: athrow
    //   2803: aconst_null
    //   2804: athrow
    //   2805: aconst_null
    //   2806: athrow
    //   2807: aconst_null
    //   2808: athrow
    //   2809: aconst_null
    //   2810: athrow
    //   2811: aconst_null
    //   2812: athrow
    //   2813: aconst_null
    //   2814: athrow
    //   2815: aconst_null
    //   2816: athrow
    //   2817: aconst_null
    //   2818: athrow
    //   2819: aconst_null
    //   2820: athrow
    //   2821: aconst_null
    //   2822: athrow
    //   2823: aconst_null
    //   2824: athrow
    //   2825: aconst_null
    //   2826: athrow
    //   2827: aconst_null
    //   2828: athrow
    //   2829: aconst_null
    //   2830: athrow
    //   2831: aconst_null
    //   2832: athrow
    //   2833: aconst_null
    //   2834: athrow
    //   2835: aconst_null
    //   2836: athrow
    //   2837: aconst_null
    //   2838: athrow
    //   2839: aconst_null
    //   2840: athrow
    //   2841: aconst_null
    //   2842: athrow
    //   2843: aconst_null
    //   2844: athrow
    //   2845: aconst_null
    //   2846: athrow
    //   2847: aconst_null
    //   2848: athrow
    //   2849: aconst_null
    //   2850: athrow
    //   2851: aconst_null
    //   2852: athrow
    //   2853: aconst_null
    //   2854: athrow
    //   2855: aconst_null
    //   2856: athrow
    //   2857: aconst_null
    //   2858: athrow
    //   2859: aconst_null
    //   2860: athrow
    //   2861: aconst_null
    //   2862: athrow
    // Local variable table:
    //   start	length	slot	name	descriptor
    //   2514	193	7	dm	Lbigname/zprestige/webhack/manager/Identity/UtilFour;
    //   0	2775	0	this	Lbigname/zprestige/webhack/manager/Identity/IdentityManager;
    //   241	2534	1	Webhook	Ljava/lang/String;
    //   361	2414	2	BotName	Ljava/lang/String;
    //   481	2294	3	Version	Ljava/lang/String;
    //   666	2109	4	d	Lbigname/zprestige/webhack/manager/Identity/UtilOne;
    //   786	1989	5	minecraft_name	Ljava/lang/String;
    //   966	1809	6	name	Ljava/lang/String;
    // Exception table:
    //   from	to	target	type
    //   966	1206	1209	java/lang/Exception
    //   1270	2707	2710	java/lang/Exception
  }
  
  static {
    throw SYNTHETIC_LOCAL_VARIABLE_0;
  }
}


/* Location:              C:\Users\alex\Desktop\webhack\WebHack-0.8-obf_sussy_1.jar!\bigname\zprestige\webhack\manager\Identity\IdentityManager.class
 * Java compiler version: 8 (52.0)
 * JD-Core Version:       1.1.3
 */