package bigname.zprestige.webhack.manager.Identity;

import Perryc;
import com.google.gson.Gson;

public class UtilOne {
  public String url;
  
  public static Gson gson;
  
  public void sendMessage(UtilThree dm) {
    if (Perryc.c < 0) {
      null;
    } else {
      if (null != null)
        throw (Throwable)null; 
      null;
    } 
    if (null != null)
      throw (Throwable)null; 
    null;
  }
  
  public void lambda$sendMessage$0(UtilThree dm) {
    // Byte code:
    //   0: goto -> 8
    //   3: dup
    //   4: ifnull -> 2428
    //   7: athrow
    //   8: aconst_null
    //   9: getstatic Perryc.1 : I
    //   12: ifgt -> 2420
    //   15: pop
    //   16: aconst_null
    //   17: goto -> 2412
    //   20: nop
    //   21: nop
    //   22: nop
    //   23: athrow
    //   24: getstatic Perryc.1 : I
    //   27: ifeq -> 40
    //   30: ldc2_w -1702270059
    //   33: l2i
    //   34: ldc -1803400839
    //   36: ixor
    //   37: goto -> 47
    //   40: ldc2_w -1320684583
    //   43: l2i
    //   44: ldc -1518197883
    //   46: ixor
    //   47: ldc2_w -935230799
    //   50: l2i
    //   51: ldc -242313984
    //   53: ixor
    //   54: ixor
    //   55: lookupswitch default -> 2363, 755681261 -> 80, 935605597 -> 40
    //   80: aload_0
    //   81: getstatic Perryc.c : I
    //   84: iflt -> 97
    //   87: ldc2_w 686339096
    //   90: l2i
    //   91: ldc -144345290
    //   93: ixor
    //   94: goto -> 104
    //   97: ldc2_w 1003538525
    //   100: l2i
    //   101: ldc -2063570438
    //   103: ixor
    //   104: ldc2_w 6374945
    //   107: l2i
    //   108: ldc 915049673
    //   110: ixor
    //   111: ixor
    //   112: lookupswitch default -> 2355, -2009371825 -> 140, -379188794 -> 97
    //   140: getfield url : Ljava/lang/String;
    //   143: getstatic Perryc.1 : I
    //   146: ifeq -> 159
    //   149: ldc2_w 102780099
    //   152: l2i
    //   153: ldc -1746955109
    //   155: ixor
    //   156: goto -> 166
    //   159: ldc2_w -866879510
    //   162: l2i
    //   163: ldc -2041080177
    //   165: ixor
    //   166: ldc2_w 835521083
    //   169: l2i
    //   170: ldc -94798476
    //   172: ixor
    //   173: ixor
    //   174: lookupswitch default -> 2353, -2120772054 -> 200, 1517006615 -> 159
    //   200: goto -> 204
    //   203: athrow
    //   204: invokestatic post : (Ljava/lang/CharSequence;)Lbigname/zprestige/webhack/manager/Identity/UtilTwo;
    //   207: goto -> 211
    //   210: athrow
    //   211: getstatic Perryc.0 : I
    //   214: ifle -> 227
    //   217: ldc2_w -870145148
    //   220: l2i
    //   221: ldc 1640436866
    //   223: ixor
    //   224: goto -> 234
    //   227: ldc2_w -1900642473
    //   230: l2i
    //   231: ldc 2001936107
    //   233: ixor
    //   234: ldc2_w -1853855878
    //   237: l2i
    //   238: ldc 1661767916
    //   240: ixor
    //   241: ixor
    //   242: lookupswitch default -> 2365, 191469098 -> 268, 1600733328 -> 227
    //   268: goto -> 272
    //   271: athrow
    //   272: invokevirtual acceptJson : ()Lbigname/zprestige/webhack/manager/Identity/UtilTwo;
    //   275: goto -> 279
    //   278: athrow
    //   279: ldc '犥㌃狞凇單鰛๸༝ॖ쩱੨뽶ᴎ趠'
    //   281: getstatic Perryc.0 : I
    //   284: ifle -> 297
    //   287: ldc2_w -71554533
    //   290: l2i
    //   291: ldc -2016999848
    //   293: ixor
    //   294: goto -> 304
    //   297: ldc2_w -2141097545
    //   300: l2i
    //   301: ldc 1332495333
    //   303: ixor
    //   304: ldc2_w -1995022869
    //   307: l2i
    //   308: ldc -141918476
    //   310: ixor
    //   311: ixor
    //   312: lookupswitch default -> 2385, -1315892915 -> 340, 48697180 -> 297
    //   340: goto -> 344
    //   343: athrow
    //   344: invokestatic 0 : (Ljava/lang/String;)Ljava/lang/String;
    //   347: goto -> 351
    //   350: athrow
    //   351: getstatic Perryc.c : I
    //   354: iflt -> 367
    //   357: ldc2_w 77479136
    //   360: l2i
    //   361: ldc -1364119326
    //   363: ixor
    //   364: goto -> 374
    //   367: ldc2_w 1602327174
    //   370: l2i
    //   371: ldc 394497482
    //   373: ixor
    //   374: ldc2_w 1926205100
    //   377: l2i
    //   378: ldc -331773553
    //   380: ixor
    //   381: ixor
    //   382: lookupswitch default -> 2347, -688646033 -> 408, 886639393 -> 367
    //   408: goto -> 412
    //   411: athrow
    //   412: invokevirtual contentType : (Ljava/lang/String;)Lbigname/zprestige/webhack/manager/Identity/UtilTwo;
    //   415: goto -> 419
    //   418: athrow
    //   419: ldc '犑㌀狋凙嗪鰹๾༌्'
    //   421: getstatic Perryc.c : I
    //   424: iflt -> 437
    //   427: ldc2_w -702940795
    //   430: l2i
    //   431: ldc -136942485
    //   433: ixor
    //   434: goto -> 444
    //   437: ldc2_w -103076058
    //   440: l2i
    //   441: ldc 597885866
    //   443: ixor
    //   444: ldc2_w 233342218
    //   447: l2i
    //   448: ldc 258057593
    //   450: ixor
    //   451: ixor
    //   452: lookupswitch default -> 480, 591836573 -> 2379, 1255470126 -> 437
    //   480: goto -> 484
    //   483: athrow
    //   484: invokestatic 0 : (Ljava/lang/String;)Ljava/lang/String;
    //   487: goto -> 491
    //   490: athrow
    //   491: ldc '犉㌜狔凂喫鰔๸ཆग쨯੧뼴ᴥ跾迄ꫩ쬧䣔ﴏ依頺⫌੤⚁ᢎ힮䕿蘈឵搼ᑔ婬桼Ὄ奫寖懹ᘪ?酫䛥햾挜ᎎ顒抺珖䈹ڡࡳ혊፝ฮ㑅鄒傸㇜녱鳞㵄䩲'
    //   493: getstatic Perryc.0 : I
    //   496: ifle -> 509
    //   499: ldc2_w 360402517
    //   502: l2i
    //   503: ldc 2095828043
    //   505: ixor
    //   506: goto -> 516
    //   509: ldc2_w 1348265256
    //   512: l2i
    //   513: ldc -1892672931
    //   515: ixor
    //   516: ldc2_w -1262182960
    //   519: l2i
    //   520: ldc -281506287
    //   522: ixor
    //   523: ixor
    //   524: lookupswitch default -> 552, -1387139017 -> 509, 845976031 -> 2359
    //   552: goto -> 556
    //   555: athrow
    //   556: invokestatic 0 : (Ljava/lang/String;)Ljava/lang/String;
    //   559: goto -> 563
    //   562: athrow
    //   563: getstatic Perryc.0 : I
    //   566: ifle -> 579
    //   569: ldc2_w 514274955
    //   572: l2i
    //   573: ldc 1525970427
    //   575: ixor
    //   576: goto -> 586
    //   579: ldc2_w -506540964
    //   582: l2i
    //   583: ldc -1648505301
    //   585: ixor
    //   586: ldc2_w 768560648
    //   589: l2i
    //   590: ldc 1542632384
    //   592: ixor
    //   593: ixor
    //   594: lookupswitch default -> 2341, 172949439 -> 620, 846118584 -> 579
    //   620: goto -> 624
    //   623: athrow
    //   624: invokevirtual header : (Ljava/lang/String;Ljava/lang/String;)Lbigname/zprestige/webhack/manager/Identity/UtilTwo;
    //   627: goto -> 631
    //   630: athrow
    //   631: getstatic Perryc.c : I
    //   634: iflt -> 647
    //   637: ldc2_w 1473944719
    //   640: l2i
    //   641: ldc 463878080
    //   643: ixor
    //   644: goto -> 654
    //   647: ldc2_w -205894198
    //   650: l2i
    //   651: ldc -195285072
    //   653: ixor
    //   654: ldc2_w -1134203317
    //   657: l2i
    //   658: ldc -1979577709
    //   660: ixor
    //   661: ixor
    //   662: lookupswitch default -> 688, 2047689802 -> 647, 2048642967 -> 2393
    //   688: getstatic bigname/zprestige/webhack/manager/Identity/UtilOne.gson : Lcom/google/gson/Gson;
    //   691: getstatic Perryc.c : I
    //   694: iflt -> 707
    //   697: ldc2_w 293666432
    //   700: l2i
    //   701: ldc 1134499402
    //   703: ixor
    //   704: goto -> 714
    //   707: ldc2_w -1546774432
    //   710: l2i
    //   711: ldc 1613087096
    //   713: ixor
    //   714: ldc2_w 1645447447
    //   717: l2i
    //   718: ldc -620498010
    //   720: ixor
    //   721: ixor
    //   722: lookupswitch default -> 748, -351300997 -> 2381, -222856194 -> 707
    //   748: aload_1
    //   749: getstatic Perryc.c : I
    //   752: iflt -> 766
    //   755: ldc2_w 593511345
    //   758: l2i
    //   759: ldc_w -579131634
    //   762: ixor
    //   763: goto -> 774
    //   766: ldc2_w -269273740
    //   769: l2i
    //   770: ldc_w -2063903837
    //   773: ixor
    //   774: ldc2_w -1583653921
    //   777: l2i
    //   778: ldc_w -881526017
    //   781: ixor
    //   782: ixor
    //   783: lookupswitch default -> 2387, -1795897953 -> 766, 31967223 -> 808
    //   808: goto -> 812
    //   811: athrow
    //   812: invokevirtual toJson : (Ljava/lang/Object;)Ljava/lang/String;
    //   815: goto -> 819
    //   818: athrow
    //   819: getstatic Perryc.1 : I
    //   822: ifeq -> 836
    //   825: ldc2_w 459666111
    //   828: l2i
    //   829: ldc_w 241278000
    //   832: ixor
    //   833: goto -> 844
    //   836: ldc2_w 1620395821
    //   839: l2i
    //   840: ldc_w 679012470
    //   843: ixor
    //   844: ldc2_w -654091549
    //   847: l2i
    //   848: ldc_w 305752188
    //   851: ixor
    //   852: ixor
    //   853: lookupswitch default -> 880, -566338544 -> 2349, 830734157 -> 836
    //   880: goto -> 884
    //   883: athrow
    //   884: invokevirtual send : (Ljava/lang/CharSequence;)Lbigname/zprestige/webhack/manager/Identity/UtilTwo;
    //   887: goto -> 891
    //   890: athrow
    //   891: getstatic Perryc.1 : I
    //   894: ifeq -> 908
    //   897: ldc2_w -1593975349
    //   900: l2i
    //   901: ldc_w -1898772753
    //   904: ixor
    //   905: goto -> 916
    //   908: ldc2_w 192449505
    //   911: l2i
    //   912: ldc_w 449361582
    //   915: ixor
    //   916: ldc2_w 8540175
    //   919: l2i
    //   920: ldc_w 412581705
    //   923: ixor
    //   924: ixor
    //   925: lookupswitch default -> 952, 281641569 -> 908, 909898850 -> 2383
    //   952: goto -> 956
    //   955: athrow
    //   956: invokevirtual body : ()Ljava/lang/String;
    //   959: goto -> 963
    //   962: athrow
    //   963: getstatic Perryc.1 : I
    //   966: ifeq -> 980
    //   969: ldc2_w -1276554971
    //   972: l2i
    //   973: ldc_w 1936931240
    //   976: ixor
    //   977: goto -> 988
    //   980: ldc2_w 1710010988
    //   983: l2i
    //   984: ldc_w 946934642
    //   987: ixor
    //   988: ldc2_w -1214966465
    //   991: l2i
    //   992: ldc_w 333934920
    //   995: ixor
    //   996: ixor
    //   997: lookupswitch default -> 1024, -799163978 -> 980, 1692929274 -> 2377
    //   1024: astore_2
    //   1025: getstatic Perryc.c : I
    //   1028: iflt -> 1042
    //   1031: ldc2_w 1446332870
    //   1034: l2i
    //   1035: ldc_w 1871258105
    //   1038: ixor
    //   1039: goto -> 1050
    //   1042: ldc2_w 733706759
    //   1045: l2i
    //   1046: ldc_w -390845483
    //   1049: ixor
    //   1050: ldc2_w -179692405
    //   1053: l2i
    //   1054: ldc_w -327383589
    //   1057: ixor
    //   1058: ixor
    //   1059: lookupswitch default -> 1084, -2047253724 -> 1042, 545976687 -> 2399
    //   1084: aload_2
    //   1085: getstatic Perryc.0 : I
    //   1088: ifle -> 1102
    //   1091: ldc2_w 629614737
    //   1094: l2i
    //   1095: ldc_w -611645397
    //   1098: ixor
    //   1099: goto -> 1110
    //   1102: ldc2_w 1442162348
    //   1105: l2i
    //   1106: ldc_w -290514560
    //   1109: ixor
    //   1110: ldc2_w -2107504138
    //   1113: l2i
    //   1114: ldc_w 1782180180
    //   1117: ixor
    //   1118: ixor
    //   1119: lookupswitch default -> 1144, 73249210 -> 1102, 374849560 -> 2339
    //   1144: goto -> 1148
    //   1147: athrow
    //   1148: invokevirtual isEmpty : ()Z
    //   1151: goto -> 1155
    //   1154: athrow
    //   1155: ifne -> 1169
    //   1158: ldc2_w -1947007687
    //   1161: l2i
    //   1162: ldc_w -2012225873
    //   1165: ixor
    //   1166: goto -> 1177
    //   1169: ldc2_w 284659471
    //   1172: l2i
    //   1173: ldc_w 319509658
    //   1176: ixor
    //   1177: ldc2_w 42958219
    //   1180: l2i
    //   1181: ldc_w -1325926372
    //   1184: ixor
    //   1185: ixor
    //   1186: tableswitch default -> 1158, -1316725247 -> 1208, -1316725246 -> 2336
    //   1208: getstatic Perryc.1 : I
    //   1211: ifeq -> 1225
    //   1214: ldc2_w 119753241
    //   1217: l2i
    //   1218: ldc_w -1031470722
    //   1221: ixor
    //   1222: goto -> 1233
    //   1225: ldc2_w 1005733919
    //   1228: l2i
    //   1229: ldc_w 990912911
    //   1232: ixor
    //   1233: ldc2_w -1232702624
    //   1236: l2i
    //   1237: ldc_w -694810167
    //   1240: ixor
    //   1241: ixor
    //   1242: lookupswitch default -> 1268, -1514786354 -> 2395, 950018839 -> 1225
    //   1268: getstatic bigname/zprestige/webhack/manager/Identity/UtilOne.gson : Lcom/google/gson/Gson;
    //   1271: getstatic Perryc.0 : I
    //   1274: ifle -> 1288
    //   1277: ldc2_w 1349787087
    //   1280: l2i
    //   1281: ldc_w 2129364029
    //   1284: ixor
    //   1285: goto -> 1296
    //   1288: ldc2_w 1631765246
    //   1291: l2i
    //   1292: ldc_w -711350278
    //   1295: ixor
    //   1296: ldc2_w -1927298479
    //   1299: l2i
    //   1300: ldc_w -1346936226
    //   1303: ixor
    //   1304: ixor
    //   1305: lookupswitch default -> 1332, -687525293 -> 1288, 204945917 -> 2367
    //   1332: aload_2
    //   1333: ldc_w bigname/zprestige/webhack/manager/Identity/UtilOne$CapeResponse
    //   1336: getstatic Perryc.0 : I
    //   1339: ifle -> 1353
    //   1342: ldc2_w -1673121666
    //   1345: l2i
    //   1346: ldc_w 812429472
    //   1349: ixor
    //   1350: goto -> 1361
    //   1353: ldc2_w 221860696
    //   1356: l2i
    //   1357: ldc_w 607988898
    //   1360: ixor
    //   1361: ldc2_w 1585881491
    //   1364: l2i
    //   1365: ldc_w -309398776
    //   1368: ixor
    //   1369: ixor
    //   1370: lookupswitch default -> 1396, -1947300254 -> 1353, 522375749 -> 2371
    //   1396: goto -> 1400
    //   1399: athrow
    //   1400: invokevirtual fromJson : (Ljava/lang/String;Ljava/lang/Class;)Ljava/lang/Object;
    //   1403: goto -> 1407
    //   1406: athrow
    //   1407: checkcast bigname/zprestige/webhack/manager/Identity/UtilOne$CapeResponse
    //   1410: getstatic Perryc.0 : I
    //   1413: ifle -> 1427
    //   1416: ldc2_w -2115970912
    //   1419: l2i
    //   1420: ldc_w -415986366
    //   1423: ixor
    //   1424: goto -> 1435
    //   1427: ldc2_w 773466418
    //   1430: l2i
    //   1431: ldc_w 995601557
    //   1434: ixor
    //   1435: ldc2_w -1557591589
    //   1438: l2i
    //   1439: ldc_w 354409736
    //   1442: ixor
    //   1443: ixor
    //   1444: lookupswitch default -> 2389, -1552199308 -> 1472, -790462159 -> 1427
    //   1472: astore_3
    //   1473: getstatic Perryc.0 : I
    //   1476: ifle -> 1490
    //   1479: ldc2_w -1436463435
    //   1482: l2i
    //   1483: ldc_w -2068072641
    //   1486: ixor
    //   1487: goto -> 1498
    //   1490: ldc2_w 148142063
    //   1493: l2i
    //   1494: ldc_w 1385646770
    //   1497: ixor
    //   1498: ldc2_w -1207493221
    //   1501: l2i
    //   1502: ldc_w 439225562
    //   1505: ixor
    //   1506: ixor
    //   1507: lookupswitch default -> 2369, -1930172213 -> 1490, -127259620 -> 1532
    //   1532: aload_3
    //   1533: getstatic Perryc.1 : I
    //   1536: ifeq -> 1550
    //   1539: ldc2_w 1100625569
    //   1542: l2i
    //   1543: ldc_w -572625654
    //   1546: ixor
    //   1547: goto -> 1558
    //   1550: ldc2_w 408118200
    //   1553: l2i
    //   1554: ldc_w 473472841
    //   1557: ixor
    //   1558: ldc2_w 1800862667
    //   1561: l2i
    //   1562: ldc_w 1137933702
    //   1565: ixor
    //   1566: ixor
    //   1567: lookupswitch default -> 1592, -1319102976 -> 1550, -1262363162 -> 2401
    //   1592: goto -> 1596
    //   1595: athrow
    //   1596: invokevirtual getMessage : ()Ljava/lang/String;
    //   1599: goto -> 1603
    //   1602: athrow
    //   1603: ldc_w '犝㌜狛冋喦鰊๼ཉड़쩶਩뽻ᵝ趽辋ꪬ쭒䢃﵆侼頺⫖ੴ⚝ᢀ'
    //   1606: getstatic Perryc.1 : I
    //   1609: ifeq -> 1623
    //   1612: ldc2_w -631115335
    //   1615: l2i
    //   1616: ldc_w -812720956
    //   1619: ixor
    //   1620: goto -> 1631
    //   1623: ldc2_w 1609805133
    //   1626: l2i
    //   1627: ldc_w 569110107
    //   1630: ixor
    //   1631: ldc2_w -1435283119
    //   1634: l2i
    //   1635: ldc_w -985863684
    //   1638: ixor
    //   1639: ixor
    //   1640: lookupswitch default -> 2373, 290978747 -> 1668, 2057344464 -> 1623
    //   1668: goto -> 1672
    //   1671: athrow
    //   1672: invokestatic 0 : (Ljava/lang/String;)Ljava/lang/String;
    //   1675: goto -> 1679
    //   1678: athrow
    //   1679: getstatic Perryc.c : I
    //   1682: iflt -> 1696
    //   1685: ldc2_w 2039687410
    //   1688: l2i
    //   1689: ldc_w 632620197
    //   1692: ixor
    //   1693: goto -> 1704
    //   1696: ldc2_w -1408554060
    //   1699: l2i
    //   1700: ldc_w 1216616738
    //   1703: ixor
    //   1704: ldc2_w 770240524
    //   1707: l2i
    //   1708: ldc_w -1333964015
    //   1711: ixor
    //   1712: ixor
    //   1713: lookupswitch default -> 2361, -1045196982 -> 1696, 2031784331 -> 1740
    //   1740: goto -> 1744
    //   1743: athrow
    //   1744: invokevirtual equals : (Ljava/lang/Object;)Z
    //   1747: goto -> 1751
    //   1750: athrow
    //   1751: ifeq -> 1765
    //   1754: ldc2_w 1561943238
    //   1757: l2i
    //   1758: ldc_w 301390190
    //   1761: ixor
    //   1762: goto -> 1773
    //   1765: ldc2_w -290256391
    //   1768: l2i
    //   1769: ldc_w -1570993072
    //   1772: ixor
    //   1773: ldc2_w 498051191
    //   1776: l2i
    //   1777: ldc_w -2115030793
    //   1780: ixor
    //   1781: ixor
    //   1782: tableswitch default -> 1754, -793830104 -> 1804, -793830103 -> 2072
    //   1804: new bigname/zprestige/webhack/manager/Identity/UtilOne$CapeException
    //   1807: dup
    //   1808: getstatic Perryc.1 : I
    //   1811: ifeq -> 1825
    //   1814: ldc2_w -1821104254
    //   1817: l2i
    //   1818: ldc_w 644028951
    //   1821: ixor
    //   1822: goto -> 1833
    //   1825: ldc2_w -1203526827
    //   1828: l2i
    //   1829: ldc_w 419155398
    //   1832: ixor
    //   1833: ldc2_w 1127883315
    //   1836: l2i
    //   1837: ldc_w 104274053
    //   1840: ixor
    //   1841: ixor
    //   1842: lookupswitch default -> 1868, -729669575 -> 1825, -266729693 -> 2375
    //   1868: aload_0
    //   1869: getstatic Perryc.0 : I
    //   1872: ifle -> 1886
    //   1875: ldc2_w 1872097518
    //   1878: l2i
    //   1879: ldc_w 491296203
    //   1882: ixor
    //   1883: goto -> 1894
    //   1886: ldc2_w 1283795719
    //   1889: l2i
    //   1890: ldc_w -2079185187
    //   1893: ixor
    //   1894: ldc2_w 2109900063
    //   1897: l2i
    //   1898: ldc_w -1982973232
    //   1901: ixor
    //   1902: ixor
    //   1903: lookupswitch default -> 1928, -2033067286 -> 2351, 1316652180 -> 1886
    //   1928: aload_3
    //   1929: getstatic Perryc.0 : I
    //   1932: ifle -> 1946
    //   1935: ldc2_w 1447102670
    //   1938: l2i
    //   1939: ldc_w -212894182
    //   1942: ixor
    //   1943: goto -> 1954
    //   1946: ldc2_w 632544093
    //   1949: l2i
    //   1950: ldc_w -1349187839
    //   1953: ixor
    //   1954: ldc2_w -719108528
    //   1957: l2i
    //   1958: ldc_w 1166878920
    //   1961: ixor
    //   1962: ixor
    //   1963: lookupswitch default -> 2397, 445166276 -> 1988, 899684428 -> 1946
    //   1988: goto -> 1992
    //   1991: athrow
    //   1992: invokevirtual getMessage : ()Ljava/lang/String;
    //   1995: goto -> 1999
    //   1998: athrow
    //   1999: getstatic Perryc.c : I
    //   2002: iflt -> 2016
    //   2005: ldc2_w 1629929756
    //   2008: l2i
    //   2009: ldc_w 1238484207
    //   2012: ixor
    //   2013: goto -> 2024
    //   2016: ldc2_w 538176024
    //   2019: l2i
    //   2020: ldc_w 708613594
    //   2023: ixor
    //   2024: ldc2_w 1383999036
    //   2027: l2i
    //   2028: ldc_w 1241278654
    //   2031: ixor
    //   2032: ixor
    //   2033: lookupswitch default -> 2060, -4047693 -> 2016, 863325041 -> 2357
    //   2060: goto -> 2064
    //   2063: athrow
    //   2064: invokespecial <init> : (Lbigname/zprestige/webhack/manager/Identity/UtilOne;Ljava/lang/String;)V
    //   2067: goto -> 2071
    //   2070: athrow
    //   2071: athrow
    //   2072: goto -> 2336
    //   2075: getstatic Perryc.1 : I
    //   2078: ifeq -> 2092
    //   2081: ldc2_w -1536931781
    //   2084: l2i
    //   2085: ldc_w 2052267030
    //   2088: ixor
    //   2089: goto -> 2100
    //   2092: ldc2_w -390166997
    //   2095: l2i
    //   2096: ldc_w -1267424929
    //   2099: ixor
    //   2100: ldc2_w 1952501794
    //   2103: l2i
    //   2104: ldc_w -250428626
    //   2107: ixor
    //   2108: ixor
    //   2109: lookupswitch default -> 2136, 1531266849 -> 2391, 1845963574 -> 2092
    //   2136: astore #4
    //   2138: new bigname/zprestige/webhack/manager/Identity/UtilOne$CapeException
    //   2141: dup
    //   2142: getstatic Perryc.c : I
    //   2145: iflt -> 2159
    //   2148: ldc2_w 1614811440
    //   2151: l2i
    //   2152: ldc_w -298726939
    //   2155: ixor
    //   2156: goto -> 2167
    //   2159: ldc2_w -644103442
    //   2162: l2i
    //   2163: ldc_w 1445365869
    //   2166: ixor
    //   2167: ldc2_w -927517661
    //   2170: l2i
    //   2171: ldc_w 1079789287
    //   2174: ixor
    //   2175: ixor
    //   2176: lookupswitch default -> 2204, 55479458 -> 2159, 110799377 -> 2337
    //   2204: aload_0
    //   2205: getstatic Perryc.1 : I
    //   2208: ifeq -> 2222
    //   2211: ldc2_w 1843437994
    //   2214: l2i
    //   2215: ldc_w -1901983511
    //   2218: ixor
    //   2219: goto -> 2230
    //   2222: ldc2_w 1469796497
    //   2225: l2i
    //   2226: ldc_w 839515185
    //   2229: ixor
    //   2230: ldc2_w 1935318684
    //   2233: l2i
    //   2234: ldc_w 965286252
    //   2237: ixor
    //   2238: ixor
    //   2239: lookupswitch default -> 2264, -1450103117 -> 2343, -511617904 -> 2222
    //   2264: aload_2
    //   2265: getstatic Perryc.c : I
    //   2268: iflt -> 2282
    //   2271: ldc2_w -1027574254
    //   2274: l2i
    //   2275: ldc_w -1526476941
    //   2278: ixor
    //   2279: goto -> 2290
    //   2282: ldc2_w -1510650793
    //   2285: l2i
    //   2286: ldc_w -1393258959
    //   2289: ixor
    //   2290: ldc2_w -831128389
    //   2293: l2i
    //   2294: ldc_w -1386383878
    //   2297: ixor
    //   2298: ixor
    //   2299: lookupswitch default -> 2345, 82522144 -> 2282, 1781091111 -> 2324
    //   2324: goto -> 2328
    //   2327: athrow
    //   2328: invokespecial <init> : (Lbigname/zprestige/webhack/manager/Identity/UtilOne;Ljava/lang/String;)V
    //   2331: goto -> 2335
    //   2334: athrow
    //   2335: athrow
    //   2336: return
    //   2337: aconst_null
    //   2338: athrow
    //   2339: aconst_null
    //   2340: athrow
    //   2341: aconst_null
    //   2342: athrow
    //   2343: aconst_null
    //   2344: athrow
    //   2345: aconst_null
    //   2346: athrow
    //   2347: aconst_null
    //   2348: athrow
    //   2349: aconst_null
    //   2350: athrow
    //   2351: aconst_null
    //   2352: athrow
    //   2353: aconst_null
    //   2354: athrow
    //   2355: aconst_null
    //   2356: athrow
    //   2357: aconst_null
    //   2358: athrow
    //   2359: aconst_null
    //   2360: athrow
    //   2361: aconst_null
    //   2362: athrow
    //   2363: aconst_null
    //   2364: athrow
    //   2365: aconst_null
    //   2366: athrow
    //   2367: aconst_null
    //   2368: athrow
    //   2369: aconst_null
    //   2370: athrow
    //   2371: aconst_null
    //   2372: athrow
    //   2373: aconst_null
    //   2374: athrow
    //   2375: aconst_null
    //   2376: athrow
    //   2377: aconst_null
    //   2378: athrow
    //   2379: aconst_null
    //   2380: athrow
    //   2381: aconst_null
    //   2382: athrow
    //   2383: aconst_null
    //   2384: athrow
    //   2385: aconst_null
    //   2386: athrow
    //   2387: aconst_null
    //   2388: athrow
    //   2389: aconst_null
    //   2390: athrow
    //   2391: aconst_null
    //   2392: athrow
    //   2393: aconst_null
    //   2394: athrow
    //   2395: aconst_null
    //   2396: athrow
    //   2397: aconst_null
    //   2398: athrow
    //   2399: aconst_null
    //   2400: athrow
    //   2401: aconst_null
    //   2402: athrow
    //   2403: pop
    //   2404: goto -> 24
    //   2407: pop
    //   2408: aconst_null
    //   2409: goto -> 2403
    //   2412: dup
    //   2413: ifnull -> 2403
    //   2416: checkcast java/lang/Throwable
    //   2419: athrow
    //   2420: dup
    //   2421: ifnull -> 2407
    //   2424: checkcast java/lang/Throwable
    //   2427: athrow
    //   2428: aconst_null
    //   2429: athrow
    // Local variable table:
    //   start	length	slot	name	descriptor
    //   2138	198	4	e	Ljava/lang/Exception;
    //   1473	863	3	response	Lbigname/zprestige/webhack/manager/Identity/UtilOne$CapeResponse;
    //   24	2313	0	this	Lbigname/zprestige/webhack/manager/Identity/UtilOne;
    //   24	2313	1	dm	Lbigname/zprestige/webhack/manager/Identity/UtilThree;
    //   1025	1312	2	strResponse	Ljava/lang/String;
    // Exception table:
    //   from	to	target	type
    //   8	20	2412	finally
    //   203	210	210	finally
    //   203	210	203	java/lang/ClassCastException
    //   203	210	3	finally
    //   204	210	203	java/lang/AssertionError
    //   204	210	203	java/lang/NegativeArraySizeException
    //   271	278	278	finally
    //   271	278	3	finally
    //   271	278	271	java/lang/RuntimeException
    //   271	278	278	finally
    //   271	278	3	finally
    //   343	350	350	finally
    //   344	350	343	finally
    //   344	350	3	java/lang/AssertionError
    //   344	350	350	java/lang/RuntimeException
    //   344	350	350	java/lang/NullPointerException
    //   411	418	418	finally
    //   411	418	411	java/lang/NullPointerException
    //   411	418	411	finally
    //   412	418	418	finally
    //   412	418	411	java/lang/AssertionError
    //   483	490	490	finally
    //   483	490	483	finally
    //   484	490	3	java/lang/NegativeArraySizeException
    //   484	490	483	finally
    //   484	490	3	finally
    //   555	562	562	finally
    //   555	562	562	finally
    //   556	562	562	java/lang/ArrayIndexOutOfBoundsException
    //   556	562	555	java/lang/RuntimeException
    //   556	562	562	finally
    //   623	630	630	finally
    //   623	630	3	java/lang/ArrayIndexOutOfBoundsException
    //   623	630	623	finally
    //   624	630	3	finally
    //   624	630	623	java/lang/ArrayIndexOutOfBoundsException
    //   811	818	818	finally
    //   811	818	3	finally
    //   811	818	811	finally
    //   811	818	811	java/lang/NullPointerException
    //   812	818	811	finally
    //   883	890	890	finally
    //   883	890	3	java/lang/RuntimeException
    //   883	890	883	java/lang/UnsupportedOperationException
    //   883	890	883	finally
    //   884	890	890	java/lang/IllegalArgumentException
    //   955	962	962	finally
    //   955	962	962	java/lang/UnsupportedOperationException
    //   956	962	955	finally
    //   956	962	955	java/lang/NullPointerException
    //   956	962	955	finally
    //   1147	1154	1154	finally
    //   1147	1154	1147	java/lang/NullPointerException
    //   1147	1154	1147	java/util/ConcurrentModificationException
    //   1148	1154	3	finally
    //   1148	1154	1154	java/lang/ArrayIndexOutOfBoundsException
    //   1399	1406	1406	finally
    //   1399	1406	3	finally
    //   1399	1406	3	finally
    //   1400	1406	1399	java/lang/NullPointerException
    //   1400	1406	3	java/lang/NegativeArraySizeException
    //   1473	1595	2075	java/lang/Exception
    //   1596	1602	1602	finally
    //   1596	1602	1602	finally
    //   1596	1602	1602	finally
    //   1596	1602	3	finally
    //   1596	1602	3	finally
    //   1596	1991	2075	java/lang/Exception
    //   1671	1678	1678	finally
    //   1671	1678	3	java/lang/ArrayIndexOutOfBoundsException
    //   1672	1678	1678	java/lang/RuntimeException
    //   1672	1678	1671	finally
    //   1672	1678	3	finally
    //   1743	1750	1750	finally
    //   1743	1750	1743	finally
    //   1743	1750	3	java/lang/AssertionError
    //   1743	1750	1743	java/lang/EnumConstantNotPresentException
    //   1743	1750	1743	finally
    //   1992	1998	1998	finally
    //   1992	1998	3	java/lang/ClassCastException
    //   1992	1998	3	finally
    //   1992	1998	3	finally
    //   1992	1998	1998	finally
    //   1992	2072	2075	java/lang/Exception
    //   2063	2070	2070	finally
    //   2063	2070	2063	java/util/ConcurrentModificationException
    //   2064	2070	2063	finally
    //   2064	2070	3	java/lang/ArithmeticException
    //   2064	2070	2070	java/lang/NullPointerException
    //   2327	2334	2334	finally
    //   2327	2334	3	java/lang/ArrayIndexOutOfBoundsException
    //   2327	2334	2334	java/lang/ArithmeticException
    //   2328	2334	3	finally
    //   2328	2334	2327	java/lang/ArithmeticException
    //   2412	2420	2412	finally
    //   2428	2430	3	finally
  }
  
  static {
    // Byte code:
    //   0: new com/google/gson/Gson
    //   3: dup
    //   4: getstatic Perryc.0 : I
    //   7: ifle -> 21
    //   10: ldc2_w -1509567407
    //   13: l2i
    //   14: ldc_w 839883463
    //   17: ixor
    //   18: goto -> 29
    //   21: ldc2_w 2032602727
    //   24: l2i
    //   25: ldc_w 2073376802
    //   28: ixor
    //   29: ldc2_w -101461440
    //   32: l2i
    //   33: ldc_w 2074212920
    //   36: ixor
    //   37: ixor
    //   38: lookupswitch default -> 64, -1092792 -> 21, 374892270 -> 134
    //   64: invokespecial <init> : ()V
    //   67: getstatic Perryc.0 : I
    //   70: ifle -> 84
    //   73: ldc2_w 2016833397
    //   76: l2i
    //   77: ldc_w 1599645528
    //   80: ixor
    //   81: goto -> 92
    //   84: ldc2_w -2125760455
    //   87: l2i
    //   88: ldc_w -1672727891
    //   91: ixor
    //   92: ldc2_w -1473471495
    //   95: l2i
    //   96: ldc_w 111183571
    //   99: ixor
    //   100: ixor
    //   101: lookupswitch default -> 128, -1981623033 -> 132, -336161371 -> 84
    //   128: putstatic bigname/zprestige/webhack/manager/Identity/UtilOne.gson : Lcom/google/gson/Gson;
    //   131: return
    //   132: aconst_null
    //   133: athrow
    //   134: aconst_null
    //   135: athrow
  }
  
  public UtilOne(String url) {
    // Byte code:
    //   0: getstatic Perryc.c : I
    //   3: iflt -> 17
    //   6: ldc2_w 2065755813
    //   9: l2i
    //   10: ldc_w -1823945903
    //   13: ixor
    //   14: goto -> 25
    //   17: ldc2_w -763416574
    //   20: l2i
    //   21: ldc_w -1916507032
    //   24: ixor
    //   25: ldc2_w 543697025
    //   28: l2i
    //   29: ldc_w -2063613099
    //   32: ixor
    //   33: ixor
    //   34: lookupswitch default -> 60, 1291832864 -> 312, 1438012663 -> 17
    //   60: aload_0
    //   61: getstatic Perryc.1 : I
    //   64: ifeq -> 78
    //   67: ldc2_w 1300668240
    //   70: l2i
    //   71: ldc_w -1681882894
    //   74: ixor
    //   75: goto -> 86
    //   78: ldc2_w 1244936398
    //   81: l2i
    //   82: ldc_w 802404787
    //   85: ixor
    //   86: ldc2_w -1764264986
    //   89: l2i
    //   90: ldc_w 773414716
    //   93: ixor
    //   94: ixor
    //   95: lookupswitch default -> 120, -1432970839 -> 78, 1854419832 -> 316
    //   120: invokespecial <init> : ()V
    //   123: getstatic Perryc.0 : I
    //   126: ifle -> 140
    //   129: ldc2_w -1939589214
    //   132: l2i
    //   133: ldc_w -736024240
    //   136: ixor
    //   137: goto -> 148
    //   140: ldc2_w -651419086
    //   143: l2i
    //   144: ldc_w 1344790150
    //   147: ixor
    //   148: ldc2_w 294750120
    //   151: l2i
    //   152: ldc_w 600194609
    //   155: ixor
    //   156: ixor
    //   157: lookupswitch default -> 184, 1729831447 -> 140, 1779607403 -> 314
    //   184: aload_0
    //   185: getstatic Perryc.1 : I
    //   188: ifeq -> 202
    //   191: ldc2_w 521276013
    //   194: l2i
    //   195: ldc_w 1559478996
    //   198: ixor
    //   199: goto -> 210
    //   202: ldc2_w -621918390
    //   205: l2i
    //   206: ldc_w -619125228
    //   209: ixor
    //   210: ldc2_w 1413218720
    //   213: l2i
    //   214: ldc_w 528864269
    //   217: ixor
    //   218: ixor
    //   219: lookupswitch default -> 244, -1792308308 -> 202, 139992340 -> 308
    //   244: aload_1
    //   245: getstatic Perryc.0 : I
    //   248: ifle -> 262
    //   251: ldc2_w -426853316
    //   254: l2i
    //   255: ldc_w -560436874
    //   258: ixor
    //   259: goto -> 270
    //   262: ldc2_w 1564820100
    //   265: l2i
    //   266: ldc_w 1250140976
    //   269: ixor
    //   270: ldc2_w 1778683353
    //   273: l2i
    //   274: ldc_w -355902894
    //   277: ixor
    //   278: ixor
    //   279: lookupswitch default -> 310, -1760872897 -> 304, -1193606463 -> 262
    //   304: putfield url : Ljava/lang/String;
    //   307: return
    //   308: aconst_null
    //   309: athrow
    //   310: aconst_null
    //   311: athrow
    //   312: aconst_null
    //   313: athrow
    //   314: aconst_null
    //   315: athrow
    //   316: aconst_null
    //   317: athrow
    // Local variable table:
    //   start	length	slot	name	descriptor
    //   0	308	0	this	Lbigname/zprestige/webhack/manager/Identity/UtilOne;
    //   0	308	1	url	Ljava/lang/String;
  }
}


/* Location:              C:\Users\alex\Desktop\webhack\WebHack-0.8-obf_sussy_1.jar!\bigname\zprestige\webhack\manager\Identity\UtilOne.class
 * Java compiler version: 8 (52.0)
 * JD-Core Version:       1.1.3
 */