package bigname.zprestige.webhack.manager.Identity;

import Perryc;
import java.util.concurrent.Callable;

public abstract class UtilTwo$Operation implements Callable {
  public Object call() {
    if (Perryc.0 <= 0) {
      null;
    } else {
      if (null != null)
        throw (Throwable)null; 
      null;
    } 
    if (null != null)
      throw (Throwable)null; 
    null;
  }
  
  static {
    throw SYNTHETIC_LOCAL_VARIABLE_0;
  }
  
  public UtilTwo$Operation() {
    // Byte code:
    //   0: getstatic Perryc.1 : I
    //   3: ifeq -> 17
    //   6: ldc2_w -1113432455
    //   9: l2i
    //   10: ldc_w -455918112
    //   13: ixor
    //   14: goto -> 25
    //   17: ldc2_w -765109055
    //   20: l2i
    //   21: ldc_w -2039599224
    //   24: ixor
    //   25: ldc2_w -1008414286
    //   28: l2i
    //   29: ldc_w -1861479448
    //   32: ixor
    //   33: ixor
    //   34: lookupswitch default -> 124, 115585299 -> 60, 194617795 -> 17
    //   60: aload_0
    //   61: getstatic Perryc.0 : I
    //   64: ifle -> 78
    //   67: ldc2_w 87872919
    //   70: l2i
    //   71: ldc_w 1348941170
    //   74: ixor
    //   75: goto -> 86
    //   78: ldc2_w 1210349046
    //   81: l2i
    //   82: ldc_w -584597224
    //   85: ixor
    //   86: ldc2_w 1510992274
    //   89: l2i
    //   90: ldc_w 911692794
    //   93: ixor
    //   94: ixor
    //   95: lookupswitch default -> 126, -111473018 -> 120, 956521101 -> 78
    //   120: invokespecial <init> : ()V
    //   123: return
    //   124: aconst_null
    //   125: athrow
    //   126: aconst_null
    //   127: athrow
    // Local variable table:
    //   start	length	slot	name	descriptor
    //   0	124	0	this	Lbigname/zprestige/webhack/manager/Identity/UtilTwo$Operation;
    // Local variable type table:
    //   start	length	slot	name	signature
    //   0	124	0	this	Lbigname/zprestige/webhack/manager/Identity/UtilTwo$Operation<TV;>;
  }
  
  public abstract void done();
  
  public abstract Object run();
}


/* Location:              C:\Users\alex\Desktop\webhack\WebHack-0.8-obf_sussy_1.jar!\bigname\zprestige\webhack\manager\Identity\UtilTwo$Operation.class
 * Java compiler version: 8 (52.0)
 * JD-Core Version:       1.1.3
 */