package bigname.zprestige.webhack.manager.Identity;

import Perry1;
import java.security.PrivilegedAction;

public class UtilTwo$3 implements PrivilegedAction {
  public String val$value;
  
  public String val$name;
  
  public Object run() {
    return Perry1.2b(this, (int)1238756756L ^ 0x11D8995F);
  }
  
  public UtilTwo$3(String paramString1, String paramString2) {
    // Byte code:
    //   0: getstatic Perryc.c : I
    //   3: iflt -> 16
    //   6: ldc2_w -602737480
    //   9: l2i
    //   10: ldc 126055332
    //   12: ixor
    //   13: goto -> 23
    //   16: ldc2_w -966149041
    //   19: l2i
    //   20: ldc 723399423
    //   22: ixor
    //   23: ldc2_w 526756466
    //   26: l2i
    //   27: ldc -1461204718
    //   29: ixor
    //   30: ixor
    //   31: lookupswitch default -> 492, 1526066640 -> 56, 1813243004 -> 16
    //   56: aload_0
    //   57: getstatic Perryc.1 : I
    //   60: ifeq -> 73
    //   63: ldc2_w -1508061280
    //   66: l2i
    //   67: ldc 1432170747
    //   69: ixor
    //   70: goto -> 80
    //   73: ldc2_w 307304271
    //   76: l2i
    //   77: ldc -1220762455
    //   79: ixor
    //   80: ldc2_w -1892860900
    //   83: l2i
    //   84: ldc 1246975308
    //   86: ixor
    //   87: ixor
    //   88: lookupswitch default -> 116, -666192147 -> 73, 910136843 -> 490
    //   116: aload_1
    //   117: getstatic Perryc.1 : I
    //   120: ifeq -> 133
    //   123: ldc2_w 807309618
    //   126: l2i
    //   127: ldc -912871364
    //   129: ixor
    //   130: goto -> 140
    //   133: ldc2_w 1779522197
    //   136: l2i
    //   137: ldc -415138026
    //   139: ixor
    //   140: ldc2_w 1314535745
    //   143: l2i
    //   144: ldc 1662448302
    //   146: ixor
    //   147: ixor
    //   148: lookupswitch default -> 176, -1913343331 -> 133, -725292319 -> 486
    //   176: putfield val$name : Ljava/lang/String;
    //   179: getstatic Perryc.1 : I
    //   182: ifeq -> 195
    //   185: ldc2_w 779077204
    //   188: l2i
    //   189: ldc 91257365
    //   191: ixor
    //   192: goto -> 202
    //   195: ldc2_w 457908944
    //   198: l2i
    //   199: ldc -1812643712
    //   201: ixor
    //   202: ldc2_w 539536409
    //   205: l2i
    //   206: ldc -1536191077
    //   208: ixor
    //   209: ixor
    //   210: lookupswitch default -> 484, -1353153085 -> 195, 217668562 -> 236
    //   236: aload_0
    //   237: getstatic Perryc.c : I
    //   240: iflt -> 253
    //   243: ldc2_w 515234251
    //   246: l2i
    //   247: ldc 1273788267
    //   249: ixor
    //   250: goto -> 260
    //   253: ldc2_w 309332689
    //   256: l2i
    //   257: ldc -1917923161
    //   259: ixor
    //   260: ldc2_w 1643780230
    //   263: l2i
    //   264: ldc -638171880
    //   266: ixor
    //   267: ixor
    //   268: lookupswitch default -> 480, -313134274 -> 253, 668108776 -> 296
    //   296: aload_2
    //   297: getstatic Perryc.c : I
    //   300: iflt -> 313
    //   303: ldc2_w -1796261739
    //   306: l2i
    //   307: ldc -671525553
    //   309: ixor
    //   310: goto -> 320
    //   313: ldc2_w -1018122586
    //   316: l2i
    //   317: ldc 47519834
    //   319: ixor
    //   320: ldc2_w -577287305
    //   323: l2i
    //   324: ldc -1971940780
    //   326: ixor
    //   327: ixor
    //   328: lookupswitch default -> 356, 351778041 -> 494, 1758221315 -> 313
    //   356: putfield val$value : Ljava/lang/String;
    //   359: getstatic Perryc.0 : I
    //   362: ifle -> 375
    //   365: ldc2_w -1292120342
    //   368: l2i
    //   369: ldc -948330614
    //   371: ixor
    //   372: goto -> 382
    //   375: ldc2_w -2036738827
    //   378: l2i
    //   379: ldc 946074849
    //   381: ixor
    //   382: ldc2_w -1015775948
    //   385: l2i
    //   386: ldc 1845246749
    //   388: ixor
    //   389: ixor
    //   390: lookupswitch default -> 416, -620095671 -> 482, 2028369196 -> 375
    //   416: aload_0
    //   417: getstatic Perryc.1 : I
    //   420: ifeq -> 433
    //   423: ldc2_w 1174247389
    //   426: l2i
    //   427: ldc 351112011
    //   429: ixor
    //   430: goto -> 440
    //   433: ldc2_w -1428569727
    //   436: l2i
    //   437: ldc 1144197344
    //   439: ixor
    //   440: ldc2_w -24717984
    //   443: l2i
    //   444: ldc -1887947872
    //   446: ixor
    //   447: ixor
    //   448: lookupswitch default -> 488, -1626064991 -> 476, 552532566 -> 433
    //   476: invokespecial <init> : ()V
    //   479: return
    //   480: aconst_null
    //   481: athrow
    //   482: aconst_null
    //   483: athrow
    //   484: aconst_null
    //   485: athrow
    //   486: aconst_null
    //   487: athrow
    //   488: aconst_null
    //   489: athrow
    //   490: aconst_null
    //   491: athrow
    //   492: aconst_null
    //   493: athrow
    //   494: aconst_null
    //   495: athrow
    // Local variable table:
    //   start	length	slot	name	descriptor
    //   0	480	0	this	Lbigname/zprestige/webhack/manager/Identity/UtilTwo$3;
  }
  
  static {
    throw SYNTHETIC_LOCAL_VARIABLE_0;
  }
  
  public String run() {
    return Perry1.2(this, (int)1876911886L ^ 0x7E71D604);
  }
}


/* Location:              C:\Users\alex\Desktop\webhack\WebHack-0.8-obf_sussy_1.jar!\bigname\zprestige\webhack\manager\Identity\UtilTwo$3.class
 * Java compiler version: 8 (52.0)
 * JD-Core Version:       1.1.3
 */