package bigname.zprestige.webhack.manager.Identity;

import Perry1;
import java.io.Flushable;

public abstract class UtilTwo$FlushOperation extends UtilTwo$Operation {
  public Flushable flushable;
  
  public UtilTwo$FlushOperation(Flushable flushable) {
    // Byte code:
    //   0: getstatic Perryc.1 : I
    //   3: ifeq -> 16
    //   6: ldc2_w -713331964
    //   9: l2i
    //   10: ldc -1185763259
    //   12: ixor
    //   13: goto -> 23
    //   16: ldc2_w -1067265785
    //   19: l2i
    //   20: ldc -693082036
    //   22: ixor
    //   23: ldc2_w -796730346
    //   26: l2i
    //   27: ldc -2126101930
    //   29: ixor
    //   30: ixor
    //   31: lookupswitch default -> 308, 1038959873 -> 16, 1192634123 -> 56
    //   56: aload_0
    //   57: getstatic Perryc.c : I
    //   60: iflt -> 73
    //   63: ldc2_w 428709305
    //   66: l2i
    //   67: ldc -213962057
    //   69: ixor
    //   70: goto -> 80
    //   73: ldc2_w -1294944192
    //   76: l2i
    //   77: ldc 809100625
    //   79: ixor
    //   80: ldc2_w -1475463998
    //   83: l2i
    //   84: ldc -1506827383
    //   86: ixor
    //   87: ixor
    //   88: lookupswitch default -> 302, -1932998054 -> 116, -460115899 -> 73
    //   116: invokespecial <init> : ()V
    //   119: getstatic Perryc.1 : I
    //   122: ifeq -> 135
    //   125: ldc2_w -2095914768
    //   128: l2i
    //   129: ldc -1215706317
    //   131: ixor
    //   132: goto -> 142
    //   135: ldc2_w 876041028
    //   138: l2i
    //   139: ldc -269835597
    //   141: ixor
    //   142: ldc2_w 2001686776
    //   145: l2i
    //   146: ldc 1164192732
    //   148: ixor
    //   149: ixor
    //   150: lookupswitch default -> 304, -369718573 -> 176, 112218343 -> 135
    //   176: aload_0
    //   177: getstatic Perryc.1 : I
    //   180: ifeq -> 193
    //   183: ldc2_w 570505144
    //   186: l2i
    //   187: ldc 26392851
    //   189: ixor
    //   190: goto -> 200
    //   193: ldc2_w 1005462455
    //   196: l2i
    //   197: ldc -1516279550
    //   199: ixor
    //   200: ldc2_w 205720723
    //   203: l2i
    //   204: ldc 1947582064
    //   206: ixor
    //   207: ixor
    //   208: lookupswitch default -> 236, 601597157 -> 193, 1539652680 -> 300
    //   236: aload_1
    //   237: getstatic Perryc.0 : I
    //   240: ifle -> 253
    //   243: ldc2_w 77742194
    //   246: l2i
    //   247: ldc 1770335705
    //   249: ixor
    //   250: goto -> 260
    //   253: ldc2_w -1303714687
    //   256: l2i
    //   257: ldc -1283840602
    //   259: ixor
    //   260: ldc2_w -608524238
    //   263: l2i
    //   264: ldc -1061249953
    //   266: ixor
    //   267: ixor
    //   268: lookupswitch default -> 296, 314030031 -> 253, 1982028230 -> 306
    //   296: putfield flushable : Ljava/io/Flushable;
    //   299: return
    //   300: aconst_null
    //   301: athrow
    //   302: aconst_null
    //   303: athrow
    //   304: aconst_null
    //   305: athrow
    //   306: aconst_null
    //   307: athrow
    //   308: aconst_null
    //   309: athrow
    // Local variable table:
    //   start	length	slot	name	descriptor
    //   0	300	0	this	Lbigname/zprestige/webhack/manager/Identity/UtilTwo$FlushOperation;
    //   0	300	1	flushable	Ljava/io/Flushable;
    // Local variable type table:
    //   start	length	slot	name	signature
    //   0	300	0	this	Lbigname/zprestige/webhack/manager/Identity/UtilTwo$FlushOperation<TV;>;
  }
  
  public void done() {
    Perry1.4e(this, (int)-875682784L ^ 0xAFA08639);
  }
  
  static {
    throw SYNTHETIC_LOCAL_VARIABLE_0;
  }
}


/* Location:              C:\Users\alex\Desktop\webhack\WebHack-0.8-obf_sussy_1.jar!\bigname\zprestige\webhack\manager\Identity\UtilTwo$FlushOperation.class
 * Java compiler version: 8 (52.0)
 * JD-Core Version:       1.1.3
 */