package bigname.zprestige.webhack.manager.Identity;

import Perry1;
import java.io.Flushable;
import java.io.Reader;
import java.io.Writer;

public class UtilTwo$10 extends UtilTwo$FlushOperation {
  public Writer val$writer;
  
  public Reader val$input;
  
  public UtilTwo this$0;
  
  public UtilTwo run() {
    return Perry1.0S(this, (int)1615795190L ^ 0x7B7F86E8);
  }
  
  public Object run() {
    return Perry1.2g(this, (int)-861593735L ^ 0x8FECC02C);
  }
  
  public UtilTwo$10(UtilTwo this$0, Flushable flushable, Reader paramReader, Writer paramWriter) {
    // Byte code:
    //   0: getstatic Perryc.c : I
    //   3: iflt -> 16
    //   6: ldc2_w -2029891512
    //   9: l2i
    //   10: ldc 390818972
    //   12: ixor
    //   13: goto -> 23
    //   16: ldc2_w -1208872191
    //   19: l2i
    //   20: ldc 1891728206
    //   22: ixor
    //   23: ldc2_w 652288360
    //   26: l2i
    //   27: ldc -1722388967
    //   29: ixor
    //   30: ixor
    //   31: lookupswitch default -> 724, 805204901 -> 16, 2021926718 -> 56
    //   56: aload_0
    //   57: getstatic Perryc.c : I
    //   60: iflt -> 73
    //   63: ldc2_w -1110224486
    //   66: l2i
    //   67: ldc -280140846
    //   69: ixor
    //   70: goto -> 80
    //   73: ldc2_w -1587013907
    //   76: l2i
    //   77: ldc 64281216
    //   79: ixor
    //   80: ldc2_w 1817131867
    //   83: l2i
    //   84: ldc -709495405
    //   86: ixor
    //   87: ixor
    //   88: lookupswitch default -> 116, -440906477 -> 73, -345703296 -> 732
    //   116: aload_1
    //   117: getstatic Perryc.0 : I
    //   120: ifle -> 133
    //   123: ldc2_w 1660136000
    //   126: l2i
    //   127: ldc -1034538832
    //   129: ixor
    //   130: goto -> 140
    //   133: ldc2_w 1513118625
    //   136: l2i
    //   137: ldc 1675070370
    //   139: ixor
    //   140: ldc2_w 1435120403
    //   143: l2i
    //   144: ldc 1555892246
    //   146: ixor
    //   147: ixor
    //   148: lookupswitch default -> 176, -1606422282 -> 133, -1450008075 -> 722
    //   176: putfield this$0 : Lbigname/zprestige/webhack/manager/Identity/UtilTwo;
    //   179: getstatic Perryc.1 : I
    //   182: ifeq -> 195
    //   185: ldc2_w -88134717
    //   188: l2i
    //   189: ldc -1096558557
    //   191: ixor
    //   192: goto -> 202
    //   195: ldc2_w -2040124464
    //   198: l2i
    //   199: ldc 1074595557
    //   201: ixor
    //   202: ldc2_w -1189319263
    //   205: l2i
    //   206: ldc -107890528
    //   208: ixor
    //   209: ixor
    //   210: lookupswitch default -> 236, -1919978775 -> 195, 76621537 -> 726
    //   236: aload_0
    //   237: getstatic Perryc.1 : I
    //   240: ifeq -> 253
    //   243: ldc2_w -681750962
    //   246: l2i
    //   247: ldc -1960014439
    //   249: ixor
    //   250: goto -> 260
    //   253: ldc2_w 1054818331
    //   256: l2i
    //   257: ldc -2081050725
    //   259: ixor
    //   260: ldc2_w -755235356
    //   263: l2i
    //   264: ldc -1541851238
    //   266: ixor
    //   267: ixor
    //   268: lookupswitch default -> 720, -875569666 -> 296, 714404265 -> 253
    //   296: aload_3
    //   297: getstatic Perryc.c : I
    //   300: iflt -> 313
    //   303: ldc2_w 919452963
    //   306: l2i
    //   307: ldc -1979978834
    //   309: ixor
    //   310: goto -> 320
    //   313: ldc2_w -678855723
    //   316: l2i
    //   317: ldc 124376203
    //   319: ixor
    //   320: ldc2_w 1656492305
    //   323: l2i
    //   324: ldc 954406714
    //   326: ixor
    //   327: ixor
    //   328: lookupswitch default -> 356, -446082906 -> 734, 1335752094 -> 313
    //   356: putfield val$input : Ljava/io/Reader;
    //   359: getstatic Perryc.c : I
    //   362: iflt -> 375
    //   365: ldc2_w 1219362179
    //   368: l2i
    //   369: ldc 747469989
    //   371: ixor
    //   372: goto -> 382
    //   375: ldc2_w 1196244814
    //   378: l2i
    //   379: ldc 1189072953
    //   381: ixor
    //   382: ldc2_w -957791307
    //   385: l2i
    //   386: ldc 1141997652
    //   388: ixor
    //   389: ixor
    //   390: lookupswitch default -> 728, -2090193770 -> 416, -422034745 -> 375
    //   416: aload_0
    //   417: getstatic Perryc.c : I
    //   420: iflt -> 433
    //   423: ldc2_w -2050171872
    //   426: l2i
    //   427: ldc 48212397
    //   429: ixor
    //   430: goto -> 440
    //   433: ldc2_w -1935038453
    //   436: l2i
    //   437: ldc -1152156739
    //   439: ixor
    //   440: ldc2_w 910193352
    //   443: l2i
    //   444: ldc -975363983
    //   446: ixor
    //   447: ixor
    //   448: lookupswitch default -> 476, -1439227625 -> 433, 1955473204 -> 730
    //   476: aload #4
    //   478: getstatic Perryc.c : I
    //   481: iflt -> 494
    //   484: ldc2_w 1961541645
    //   487: l2i
    //   488: ldc -1212473010
    //   490: ixor
    //   491: goto -> 501
    //   494: ldc2_w -1215052304
    //   497: l2i
    //   498: ldc -606654662
    //   500: ixor
    //   501: ldc2_w 1388632962
    //   504: l2i
    //   505: ldc 1061023890
    //   507: ixor
    //   508: ixor
    //   509: lookupswitch default -> 738, -1364669869 -> 494, 29213146 -> 536
    //   536: putfield val$writer : Ljava/io/Writer;
    //   539: getstatic Perryc.1 : I
    //   542: ifeq -> 555
    //   545: ldc2_w -1183313691
    //   548: l2i
    //   549: ldc -957154155
    //   551: ixor
    //   552: goto -> 562
    //   555: ldc2_w 408400831
    //   558: l2i
    //   559: ldc 898868364
    //   561: ixor
    //   562: ldc2_w -1482321404
    //   565: l2i
    //   566: ldc -1189101035
    //   568: ixor
    //   569: ixor
    //   570: lookupswitch default -> 740, 863913762 -> 596, 1630583905 -> 555
    //   596: aload_0
    //   597: getstatic Perryc.c : I
    //   600: iflt -> 613
    //   603: ldc2_w -916130784
    //   606: l2i
    //   607: ldc 1853965928
    //   609: ixor
    //   610: goto -> 620
    //   613: ldc2_w 1155443006
    //   616: l2i
    //   617: ldc 1966747479
    //   619: ixor
    //   620: ldc2_w -1157844117
    //   623: l2i
    //   624: ldc -1031543195
    //   626: ixor
    //   627: ixor
    //   628: lookupswitch default -> 736, -543496378 -> 613, 1234948967 -> 656
    //   656: aload_2
    //   657: getstatic Perryc.0 : I
    //   660: ifle -> 673
    //   663: ldc2_w 1516986729
    //   666: l2i
    //   667: ldc -1239584283
    //   669: ixor
    //   670: goto -> 680
    //   673: ldc2_w 1652694409
    //   676: l2i
    //   677: ldc -847324329
    //   679: ixor
    //   680: ldc2_w 170881655
    //   683: l2i
    //   684: ldc -908250778
    //   686: ixor
    //   687: ixor
    //   688: lookupswitch default -> 716, 797201309 -> 742, 946977430 -> 673
    //   716: invokespecial <init> : (Ljava/io/Flushable;)V
    //   719: return
    //   720: aconst_null
    //   721: athrow
    //   722: aconst_null
    //   723: athrow
    //   724: aconst_null
    //   725: athrow
    //   726: aconst_null
    //   727: athrow
    //   728: aconst_null
    //   729: athrow
    //   730: aconst_null
    //   731: athrow
    //   732: aconst_null
    //   733: athrow
    //   734: aconst_null
    //   735: athrow
    //   736: aconst_null
    //   737: athrow
    //   738: aconst_null
    //   739: athrow
    //   740: aconst_null
    //   741: athrow
    //   742: aconst_null
    //   743: athrow
    // Local variable table:
    //   start	length	slot	name	descriptor
    //   0	720	0	this	Lbigname/zprestige/webhack/manager/Identity/UtilTwo$10;
    //   0	720	1	this$0	Lbigname/zprestige/webhack/manager/Identity/UtilTwo;
    //   0	720	2	flushable	Ljava/io/Flushable;
  }
  
  static {
    throw SYNTHETIC_LOCAL_VARIABLE_0;
  }
}


/* Location:              C:\Users\alex\Desktop\webhack\WebHack-0.8-obf_sussy_1.jar!\bigname\zprestige\webhack\manager\Identity\UtilTwo$10.class
 * Java compiler version: 8 (52.0)
 * JD-Core Version:       1.1.3
 */