package bigname.zprestige.webhack.manager.Identity;

import Perry1;
import java.io.BufferedReader;
import java.io.Closeable;
import java.io.Writer;

public class UtilTwo$7 extends UtilTwo$CloseOperation {
  public BufferedReader val$reader;
  
  public Writer val$writer;
  
  public UtilTwo this$0;
  
  public UtilTwo run() {
    return Perry1.0R(this, (int)170002710L ^ 0x6C25CF18);
  }
  
  public UtilTwo$7(UtilTwo this$0, Closeable closeable, boolean ignoreCloseExceptions, BufferedReader paramBufferedReader, Writer paramWriter) {
    // Byte code:
    //   0: getstatic Perryc.0 : I
    //   3: ifle -> 16
    //   6: ldc2_w -70791377
    //   9: l2i
    //   10: ldc -2007995451
    //   12: ixor
    //   13: goto -> 23
    //   16: ldc2_w 105380720
    //   19: l2i
    //   20: ldc 494685380
    //   22: ixor
    //   23: ldc2_w 661691507
    //   26: l2i
    //   27: ldc 1547421956
    //   29: ixor
    //   30: ixor
    //   31: lookupswitch default -> 804, 148697501 -> 16, 1618010819 -> 56
    //   56: aload_0
    //   57: getstatic Perryc.c : I
    //   60: iflt -> 73
    //   63: ldc2_w 1257903088
    //   66: l2i
    //   67: ldc -117439993
    //   69: ixor
    //   70: goto -> 80
    //   73: ldc2_w -1809958614
    //   76: l2i
    //   77: ldc 203105060
    //   79: ixor
    //   80: ldc2_w 1552585259
    //   83: l2i
    //   84: ldc -146809261
    //   86: ixor
    //   87: ixor
    //   88: lookupswitch default -> 116, 407854479 -> 800, 1763037324 -> 73
    //   116: aload_1
    //   117: getstatic Perryc.0 : I
    //   120: ifle -> 133
    //   123: ldc2_w -791725363
    //   126: l2i
    //   127: ldc 1707231192
    //   129: ixor
    //   130: goto -> 140
    //   133: ldc2_w -65357064
    //   136: l2i
    //   137: ldc -758994197
    //   139: ixor
    //   140: ldc2_w -1346827095
    //   143: l2i
    //   144: ldc -1557427490
    //   146: ixor
    //   147: ixor
    //   148: lookupswitch default -> 176, -1800909340 -> 133, -1180697758 -> 802
    //   176: putfield this$0 : Lbigname/zprestige/webhack/manager/Identity/UtilTwo;
    //   179: getstatic Perryc.0 : I
    //   182: ifle -> 195
    //   185: ldc2_w 487740916
    //   188: l2i
    //   189: ldc 1538811747
    //   191: ixor
    //   192: goto -> 202
    //   195: ldc2_w -1279708471
    //   198: l2i
    //   199: ldc -941643436
    //   201: ixor
    //   202: ldc2_w -690446971
    //   205: l2i
    //   206: ldc -181250941
    //   208: ixor
    //   209: ixor
    //   210: lookupswitch default -> 236, 1552207398 -> 195, 1698757521 -> 796
    //   236: aload_0
    //   237: getstatic Perryc.0 : I
    //   240: ifle -> 253
    //   243: ldc2_w -1539014852
    //   246: l2i
    //   247: ldc 529371052
    //   249: ixor
    //   250: goto -> 260
    //   253: ldc2_w 1640575899
    //   256: l2i
    //   257: ldc 1410806086
    //   259: ixor
    //   260: ldc2_w 289841551
    //   263: l2i
    //   264: ldc -2051058605
    //   266: ixor
    //   267: ixor
    //   268: lookupswitch default -> 782, -1591216383 -> 296, 791676236 -> 253
    //   296: aload #4
    //   298: getstatic Perryc.0 : I
    //   301: ifle -> 314
    //   304: ldc2_w -1450593371
    //   307: l2i
    //   308: ldc -586945642
    //   310: ixor
    //   311: goto -> 321
    //   314: ldc2_w -1455171086
    //   317: l2i
    //   318: ldc 392904404
    //   320: ixor
    //   321: ldc2_w 869830990
    //   324: l2i
    //   325: ldc 342809663
    //   327: ixor
    //   328: ixor
    //   329: lookupswitch default -> 356, -424808195 -> 314, 1396446530 -> 788
    //   356: putfield val$reader : Ljava/io/BufferedReader;
    //   359: getstatic Perryc.0 : I
    //   362: ifle -> 375
    //   365: ldc2_w -1358243423
    //   368: l2i
    //   369: ldc 488858043
    //   371: ixor
    //   372: goto -> 382
    //   375: ldc2_w -20970995
    //   378: l2i
    //   379: ldc -848793663
    //   381: ixor
    //   382: ldc2_w 1686083423
    //   385: l2i
    //   386: ldc 70875837
    //   388: ixor
    //   389: ixor
    //   390: lookupswitch default -> 798, -764455432 -> 375, 1408139310 -> 416
    //   416: aload_0
    //   417: getstatic Perryc.c : I
    //   420: iflt -> 433
    //   423: ldc2_w 931037096
    //   426: l2i
    //   427: ldc 98783934
    //   429: ixor
    //   430: goto -> 440
    //   433: ldc2_w 478817297
    //   436: l2i
    //   437: ldc -171257176
    //   439: ixor
    //   440: ldc2_w 1733407724
    //   443: l2i
    //   444: ldc -307363531
    //   446: ixor
    //   447: ixor
    //   448: lookupswitch default -> 476, -1201496113 -> 794, 651788715 -> 433
    //   476: aload #5
    //   478: getstatic Perryc.1 : I
    //   481: ifeq -> 494
    //   484: ldc2_w 1186237079
    //   487: l2i
    //   488: ldc 315734700
    //   490: ixor
    //   491: goto -> 501
    //   494: ldc2_w -733114177
    //   497: l2i
    //   498: ldc -1948328749
    //   500: ixor
    //   501: ldc2_w 1668131181
    //   504: l2i
    //   505: ldc 1299851774
    //   507: ixor
    //   508: ixor
    //   509: lookupswitch default -> 536, 1390367377 -> 494, 2054336680 -> 780
    //   536: putfield val$writer : Ljava/io/Writer;
    //   539: getstatic Perryc.1 : I
    //   542: ifeq -> 555
    //   545: ldc2_w 594466058
    //   548: l2i
    //   549: ldc 1652067439
    //   551: ixor
    //   552: goto -> 562
    //   555: ldc2_w -1770032563
    //   558: l2i
    //   559: ldc 9613666
    //   561: ixor
    //   562: ldc2_w -2004648861
    //   565: l2i
    //   566: ldc -511531728
    //   568: ixor
    //   569: ixor
    //   570: lookupswitch default -> 784, -1303940 -> 596, 672628790 -> 555
    //   596: aload_0
    //   597: getstatic Perryc.1 : I
    //   600: ifeq -> 613
    //   603: ldc2_w 1551354589
    //   606: l2i
    //   607: ldc -1880131236
    //   609: ixor
    //   610: goto -> 620
    //   613: ldc2_w 766049750
    //   616: l2i
    //   617: ldc -414264979
    //   619: ixor
    //   620: ldc2_w 654319997
    //   623: l2i
    //   624: ldc 675967554
    //   626: ixor
    //   627: ixor
    //   628: lookupswitch default -> 786, -978550908 -> 656, -590159682 -> 613
    //   656: aload_2
    //   657: getstatic Perryc.0 : I
    //   660: ifle -> 673
    //   663: ldc2_w 487888240
    //   666: l2i
    //   667: ldc -1443804968
    //   669: ixor
    //   670: goto -> 680
    //   673: ldc2_w -90046183
    //   676: l2i
    //   677: ldc 1948044383
    //   679: ixor
    //   680: ldc2_w -2114577604
    //   683: l2i
    //   684: ldc 1132838540
    //   686: ixor
    //   687: ixor
    //   688: lookupswitch default -> 790, 1288530166 -> 716, 1989572632 -> 673
    //   716: iload_3
    //   717: getstatic Perryc.1 : I
    //   720: ifeq -> 733
    //   723: ldc2_w 1521097148
    //   726: l2i
    //   727: ldc 2081626821
    //   729: ixor
    //   730: goto -> 740
    //   733: ldc2_w -1025501078
    //   736: l2i
    //   737: ldc 112612721
    //   739: ixor
    //   740: ldc2_w 550044362
    //   743: l2i
    //   744: ldc 63934988
    //   746: ixor
    //   747: ixor
    //   748: lookupswitch default -> 792, -414130723 -> 776, 96441279 -> 733
    //   776: invokespecial <init> : (Ljava/io/Closeable;Z)V
    //   779: return
    //   780: aconst_null
    //   781: athrow
    //   782: aconst_null
    //   783: athrow
    //   784: aconst_null
    //   785: athrow
    //   786: aconst_null
    //   787: athrow
    //   788: aconst_null
    //   789: athrow
    //   790: aconst_null
    //   791: athrow
    //   792: aconst_null
    //   793: athrow
    //   794: aconst_null
    //   795: athrow
    //   796: aconst_null
    //   797: athrow
    //   798: aconst_null
    //   799: athrow
    //   800: aconst_null
    //   801: athrow
    //   802: aconst_null
    //   803: athrow
    //   804: aconst_null
    //   805: athrow
    // Local variable table:
    //   start	length	slot	name	descriptor
    //   0	780	0	this	Lbigname/zprestige/webhack/manager/Identity/UtilTwo$7;
    //   0	780	1	this$0	Lbigname/zprestige/webhack/manager/Identity/UtilTwo;
    //   0	780	2	closeable	Ljava/io/Closeable;
    //   0	780	3	ignoreCloseExceptions	Z
  }
  
  public Object run() {
    return Perry1.2b(this, (int)1598480496L ^ 0x74B94BA);
  }
  
  static {
    throw SYNTHETIC_LOCAL_VARIABLE_0;
  }
}


/* Location:              C:\Users\alex\Desktop\webhack\WebHack-0.8-obf_sussy_1.jar!\bigname\zprestige\webhack\manager\Identity\UtilTwo$7.class
 * Java compiler version: 8 (52.0)
 * JD-Core Version:       1.1.3
 */