package bigname.zprestige.webhack.manager.Identity;

import Perry1;
import java.io.Closeable;
import java.io.InputStream;
import java.io.OutputStream;

public class UtilTwo$8 extends UtilTwo$CloseOperation {
  public UtilTwo this$0;
  
  public OutputStream val$output;
  
  public InputStream val$input;
  
  public Object run() {
    return Perry1.2d(this, (int)453277833L ^ 0x658114B4);
  }
  
  static {
    throw SYNTHETIC_LOCAL_VARIABLE_0;
  }
  
  public UtilTwo$8(UtilTwo this$0, Closeable closeable, boolean ignoreCloseExceptions, InputStream paramInputStream, OutputStream paramOutputStream) {
    // Byte code:
    //   0: getstatic Perryc.0 : I
    //   3: ifle -> 16
    //   6: ldc2_w 1123005504
    //   9: l2i
    //   10: ldc -1931374086
    //   12: ixor
    //   13: goto -> 23
    //   16: ldc2_w 480467590
    //   19: l2i
    //   20: ldc -645244771
    //   22: ixor
    //   23: ldc2_w 192318076
    //   26: l2i
    //   27: ldc 1276770968
    //   29: ixor
    //   30: ixor
    //   31: lookupswitch default -> 790, -2109312257 -> 56, -1990109858 -> 16
    //   56: aload_0
    //   57: getstatic Perryc.0 : I
    //   60: ifle -> 73
    //   63: ldc2_w -1868348255
    //   66: l2i
    //   67: ldc 919297319
    //   69: ixor
    //   70: goto -> 80
    //   73: ldc2_w 1153769150
    //   76: l2i
    //   77: ldc -614456047
    //   79: ixor
    //   80: ldc2_w -1740411223
    //   83: l2i
    //   84: ldc -1975658826
    //   86: ixor
    //   87: ixor
    //   88: lookupswitch default -> 116, -1273585255 -> 794, 827059405 -> 73
    //   116: aload_1
    //   117: getstatic Perryc.0 : I
    //   120: ifle -> 133
    //   123: ldc2_w -1075068330
    //   126: l2i
    //   127: ldc 481054763
    //   129: ixor
    //   130: goto -> 140
    //   133: ldc2_w -735042072
    //   136: l2i
    //   137: ldc -1857575546
    //   139: ixor
    //   140: ldc2_w 417162106
    //   143: l2i
    //   144: ldc -1571767349
    //   146: ixor
    //   147: ixor
    //   148: lookupswitch default -> 176, -459417508 -> 133, 432687820 -> 780
    //   176: putfield this$0 : Lbigname/zprestige/webhack/manager/Identity/UtilTwo;
    //   179: getstatic Perryc.1 : I
    //   182: ifeq -> 195
    //   185: ldc2_w -120888836
    //   188: l2i
    //   189: ldc 1526184278
    //   191: ixor
    //   192: goto -> 202
    //   195: ldc2_w 1337115207
    //   198: l2i
    //   199: ldc 1192821765
    //   201: ixor
    //   202: ldc2_w -644446528
    //   205: l2i
    //   206: ldc -1332349107
    //   208: ixor
    //   209: ixor
    //   210: lookupswitch default -> 786, -885020377 -> 195, 1638447055 -> 236
    //   236: aload_0
    //   237: getstatic Perryc.c : I
    //   240: iflt -> 253
    //   243: ldc2_w 886709186
    //   246: l2i
    //   247: ldc 1910806046
    //   249: ixor
    //   250: goto -> 260
    //   253: ldc2_w 947268308
    //   256: l2i
    //   257: ldc -1097692336
    //   259: ixor
    //   260: ldc2_w -1606166440
    //   263: l2i
    //   264: ldc 728792971
    //   266: ixor
    //   267: ixor
    //   268: lookupswitch default -> 296, -837998065 -> 788, 1073541437 -> 253
    //   296: aload #4
    //   298: getstatic Perryc.1 : I
    //   301: ifeq -> 314
    //   304: ldc2_w -1285396053
    //   307: l2i
    //   308: ldc -1524015153
    //   310: ixor
    //   311: goto -> 321
    //   314: ldc2_w -1573254412
    //   317: l2i
    //   318: ldc -1754005120
    //   320: ixor
    //   321: ldc2_w 1286580751
    //   324: l2i
    //   325: ldc -1467508473
    //   327: ixor
    //   328: ixor
    //   329: lookupswitch default -> 798, -781830020 -> 356, -228391572 -> 314
    //   356: putfield val$input : Ljava/io/InputStream;
    //   359: getstatic Perryc.0 : I
    //   362: ifle -> 375
    //   365: ldc2_w -1400014182
    //   368: l2i
    //   369: ldc 138105274
    //   371: ixor
    //   372: goto -> 382
    //   375: ldc2_w -774974678
    //   378: l2i
    //   379: ldc -1938662132
    //   381: ixor
    //   382: ldc2_w -1865539429
    //   385: l2i
    //   386: ldc 2043058475
    //   388: ixor
    //   389: ixor
    //   390: lookupswitch default -> 416, -1819445767 -> 375, 1304334992 -> 804
    //   416: aload_0
    //   417: getstatic Perryc.1 : I
    //   420: ifeq -> 433
    //   423: ldc2_w -1193538158
    //   426: l2i
    //   427: ldc -574099698
    //   429: ixor
    //   430: goto -> 440
    //   433: ldc2_w -1987050262
    //   436: l2i
    //   437: ldc 1669310167
    //   439: ixor
    //   440: ldc2_w 1068122594
    //   443: l2i
    //   444: ldc 1520959914
    //   446: ixor
    //   447: ixor
    //   448: lookupswitch default -> 792, -1880235403 -> 476, 1680084 -> 433
    //   476: aload #5
    //   478: getstatic Perryc.0 : I
    //   481: ifle -> 494
    //   484: ldc2_w -1286673641
    //   487: l2i
    //   488: ldc 249200389
    //   490: ixor
    //   491: goto -> 501
    //   494: ldc2_w -935009329
    //   497: l2i
    //   498: ldc 625307899
    //   500: ixor
    //   501: ldc2_w -677087981
    //   504: l2i
    //   505: ldc -2105221228
    //   507: ixor
    //   508: ixor
    //   509: lookupswitch default -> 536, -2040914728 -> 494, -390840683 -> 796
    //   536: putfield val$output : Ljava/io/OutputStream;
    //   539: getstatic Perryc.1 : I
    //   542: ifeq -> 555
    //   545: ldc2_w 44395431
    //   548: l2i
    //   549: ldc 101785510
    //   551: ixor
    //   552: goto -> 562
    //   555: ldc2_w 290429617
    //   558: l2i
    //   559: ldc -1569904729
    //   561: ixor
    //   562: ldc2_w -512981032
    //   565: l2i
    //   566: ldc -743343465
    //   568: ixor
    //   569: ixor
    //   570: lookupswitch default -> 596, 912886094 -> 782, 1927416317 -> 555
    //   596: aload_0
    //   597: getstatic Perryc.1 : I
    //   600: ifeq -> 613
    //   603: ldc2_w 2107816161
    //   606: l2i
    //   607: ldc -557769308
    //   609: ixor
    //   610: goto -> 620
    //   613: ldc2_w -1047876524
    //   616: l2i
    //   617: ldc 1718585
    //   619: ixor
    //   620: ldc2_w 1092104398
    //   623: l2i
    //   624: ldc 1782850576
    //   626: ixor
    //   627: ixor
    //   628: lookupswitch default -> 656, -2009091685 -> 784, 1535593470 -> 613
    //   656: aload_2
    //   657: getstatic Perryc.0 : I
    //   660: ifle -> 673
    //   663: ldc2_w 526719014
    //   666: l2i
    //   667: ldc -330279544
    //   669: ixor
    //   670: goto -> 680
    //   673: ldc2_w -1938868702
    //   676: l2i
    //   677: ldc -1327597761
    //   679: ixor
    //   680: ldc2_w -1178761652
    //   683: l2i
    //   684: ldc -63913893
    //   686: ixor
    //   687: ixor
    //   688: lookupswitch default -> 802, -1229452359 -> 673, 2033977098 -> 716
    //   716: iload_3
    //   717: getstatic Perryc.0 : I
    //   720: ifle -> 733
    //   723: ldc2_w 726553630
    //   726: l2i
    //   727: ldc -1248839741
    //   729: ixor
    //   730: goto -> 740
    //   733: ldc2_w 2042659314
    //   736: l2i
    //   737: ldc -617564102
    //   739: ixor
    //   740: ldc2_w -976855240
    //   743: l2i
    //   744: ldc -1487634813
    //   746: ixor
    //   747: ixor
    //   748: lookupswitch default -> 776, -1937524647 -> 733, -62111130 -> 800
    //   776: invokespecial <init> : (Ljava/io/Closeable;Z)V
    //   779: return
    //   780: aconst_null
    //   781: athrow
    //   782: aconst_null
    //   783: athrow
    //   784: aconst_null
    //   785: athrow
    //   786: aconst_null
    //   787: athrow
    //   788: aconst_null
    //   789: athrow
    //   790: aconst_null
    //   791: athrow
    //   792: aconst_null
    //   793: athrow
    //   794: aconst_null
    //   795: athrow
    //   796: aconst_null
    //   797: athrow
    //   798: aconst_null
    //   799: athrow
    //   800: aconst_null
    //   801: athrow
    //   802: aconst_null
    //   803: athrow
    //   804: aconst_null
    //   805: athrow
    // Local variable table:
    //   start	length	slot	name	descriptor
    //   0	780	0	this	Lbigname/zprestige/webhack/manager/Identity/UtilTwo$8;
    //   0	780	1	this$0	Lbigname/zprestige/webhack/manager/Identity/UtilTwo;
    //   0	780	2	closeable	Ljava/io/Closeable;
    //   0	780	3	ignoreCloseExceptions	Z
  }
  
  public UtilTwo run() {
    return Perry1.0R(this, (int)934890282L ^ 0x51BE8D25);
  }
}


/* Location:              C:\Users\alex\Desktop\webhack\WebHack-0.8-obf_sussy_1.jar!\bigname\zprestige\webhack\manager\Identity\UtilTwo$8.class
 * Java compiler version: 8 (52.0)
 * JD-Core Version:       1.1.3
 */