package bigname.zprestige.webhack.manager.Identity;

import Perry1;
import Perryc;

public class UtilTwo$Base64 {
  public static String PREFERRED_ENCODING;
  
  public static byte EQUALS_SIGN;
  
  public static byte[] _STANDARD_ALPHABET;
  
  public static byte[] encode3to4(byte[] source, int srcOffset, int numSigBytes, byte[] destination, int destOffset) {
    if (Perryc.1 <= 0) {
      null;
    } else {
      if (null != null)
        throw (Throwable)null; 
      null;
    } 
    if (null != null)
      throw (Throwable)null; 
    null;
  }
  
  public static String encodeBytes(byte[] source) {
    if (Perryc.0 <= 0) {
      null;
    } else {
      if (null != null)
        throw (Throwable)null; 
      null;
    } 
    if (null != null)
      throw (Throwable)null; 
    null;
  }
  
  public static String encodeBytes(byte[] source, int off, int len) {
    if (Perryc.0 <= 0) {
      null;
    } else {
      if (null != null)
        throw (Throwable)null; 
      null;
    } 
    if (null != null)
      throw (Throwable)null; 
    null;
  }
  
  public UtilTwo$Base64() {
    // Byte code:
    //   0: getstatic Perryc.c : I
    //   3: iflt -> 17
    //   6: ldc2_w -33200278
    //   9: l2i
    //   10: ldc_w 970012736
    //   13: ixor
    //   14: goto -> 25
    //   17: ldc2_w -1528462917
    //   20: l2i
    //   21: ldc_w 122220835
    //   24: ixor
    //   25: ldc2_w 1782426726
    //   28: l2i
    //   29: ldc_w 987537158
    //   32: ixor
    //   33: ixor
    //   34: lookupswitch default -> 124, -1758106550 -> 17, -213105672 -> 60
    //   60: aload_0
    //   61: getstatic Perryc.1 : I
    //   64: ifeq -> 78
    //   67: ldc2_w -247641618
    //   70: l2i
    //   71: ldc_w -696192750
    //   74: ixor
    //   75: goto -> 86
    //   78: ldc2_w 632668658
    //   81: l2i
    //   82: ldc_w 401357428
    //   85: ixor
    //   86: ldc2_w -1069010605
    //   89: l2i
    //   90: ldc_w 1063759415
    //   93: ixor
    //   94: ixor
    //   95: lookupswitch default -> 126, -847878942 -> 120, -661510248 -> 78
    //   120: invokespecial <init> : ()V
    //   123: return
    //   124: aconst_null
    //   125: athrow
    //   126: aconst_null
    //   127: athrow
    // Local variable table:
    //   start	length	slot	name	descriptor
    //   0	124	0	this	Lbigname/zprestige/webhack/manager/Identity/UtilTwo$Base64;
  }
  
  public static byte[] encodeBytesToBytes(byte[] source, int off, int len) {
    // Byte code:
    //   0: goto -> 8
    //   3: dup
    //   4: ifnull -> 5288
    //   7: athrow
    //   8: aconst_null
    //   9: getstatic Perryc.1 : I
    //   12: ifgt -> 5280
    //   15: pop
    //   16: aconst_null
    //   17: goto -> 5272
    //   20: nop
    //   21: nop
    //   22: nop
    //   23: athrow
    //   24: getstatic Perryc.0 : I
    //   27: ifle -> 41
    //   30: ldc2_w 2027500591
    //   33: l2i
    //   34: ldc_w 685109269
    //   37: ixor
    //   38: goto -> 49
    //   41: ldc2_w 933795902
    //   44: l2i
    //   45: ldc_w 1889118690
    //   48: ixor
    //   49: ldc2_w -1532178893
    //   52: l2i
    //   53: ldc_w -2108954267
    //   56: ixor
    //   57: ixor
    //   58: lookupswitch default -> 84, -1737209071 -> 41, 1995170668 -> 5255
    //   84: aload_0
    //   85: ifnonnull -> 99
    //   88: ldc2_w -82708691
    //   91: l2i
    //   92: ldc_w -1894691253
    //   95: ixor
    //   96: goto -> 107
    //   99: ldc2_w 1391999890
    //   102: l2i
    //   103: ldc_w 653820663
    //   106: ixor
    //   107: ldc2_w -2021200832
    //   110: l2i
    //   111: ldc_w -2088611445
    //   114: ixor
    //   115: ixor
    //   116: tableswitch default -> 88, 1879311533 -> 140, 1879311534 -> 292
    //   140: new java/lang/NullPointerException
    //   143: dup
    //   144: ldc_w '欮㌒歩漰ञ薥ูᚳ?嗽폟ਦꛙ⏡턃迟댁ᐷ侽膖ᑷ囆㼢ᣜ츏篅?'
    //   147: getstatic Perryc.c : I
    //   150: iflt -> 164
    //   153: ldc2_w 1000150666
    //   156: l2i
    //   157: ldc_w -1003436246
    //   160: ixor
    //   161: goto -> 172
    //   164: ldc2_w 655289030
    //   167: l2i
    //   168: ldc_w -1238155278
    //   171: ixor
    //   172: ldc2_w -379862465
    //   175: l2i
    //   176: ldc_w -2090344774
    //   179: ixor
    //   180: ixor
    //   181: lookupswitch default -> 5141, -1785606875 -> 164, -83768911 -> 208
    //   208: goto -> 212
    //   211: athrow
    //   212: invokestatic 0 : (Ljava/lang/String;)Ljava/lang/String;
    //   215: goto -> 219
    //   218: athrow
    //   219: getstatic Perryc.c : I
    //   222: iflt -> 236
    //   225: ldc2_w 1843393144
    //   228: l2i
    //   229: ldc_w -1086371850
    //   232: ixor
    //   233: goto -> 244
    //   236: ldc2_w 331886872
    //   239: l2i
    //   240: ldc_w -1392548685
    //   243: ixor
    //   244: ldc2_w 1861430944
    //   247: l2i
    //   248: ldc_w -851622756
    //   251: ixor
    //   252: ixor
    //   253: lookupswitch default -> 280, -645185303 -> 236, 1898897330 -> 5193
    //   280: goto -> 284
    //   283: athrow
    //   284: invokespecial <init> : (Ljava/lang/String;)V
    //   287: goto -> 291
    //   290: athrow
    //   291: athrow
    //   292: getstatic Perryc.1 : I
    //   295: ifeq -> 309
    //   298: ldc2_w 1063631258
    //   301: l2i
    //   302: ldc_w 125328043
    //   305: ixor
    //   306: goto -> 317
    //   309: ldc2_w 2031583883
    //   312: l2i
    //   313: ldc_w 1431162707
    //   316: ixor
    //   317: ldc2_w 2126105100
    //   320: l2i
    //   321: ldc_w 1950509861
    //   324: ixor
    //   325: ixor
    //   326: lookupswitch default -> 352, -1302888070 -> 309, 853951000 -> 5133
    //   352: iload_1
    //   353: ifge -> 367
    //   356: ldc2_w -1924796550
    //   359: l2i
    //   360: ldc_w -1461622898
    //   363: ixor
    //   364: goto -> 375
    //   367: ldc2_w -266356428
    //   370: l2i
    //   371: ldc_w -709152319
    //   374: ixor
    //   375: ldc2_w -94559438
    //   378: l2i
    //   379: ldc_w 1968077404
    //   382: ixor
    //   383: ixor
    //   384: tableswitch default -> 356, -1430793830 -> 408, -1430793829 -> 912
    //   408: new java/lang/IllegalArgumentException
    //   411: dup
    //   412: new java/lang/StringBuilder
    //   415: dup
    //   416: getstatic Perryc.c : I
    //   419: iflt -> 433
    //   422: ldc2_w 809242542
    //   425: l2i
    //   426: ldc_w 946816497
    //   429: ixor
    //   430: goto -> 441
    //   433: ldc2_w -1999285995
    //   436: l2i
    //   437: ldc_w -780203632
    //   440: ixor
    //   441: ldc2_w 341460524
    //   444: l2i
    //   445: ldc_w 440408273
    //   448: ixor
    //   449: ixor
    //   450: lookupswitch default -> 476, 105452706 -> 5247, 2026254823 -> 433
    //   476: goto -> 480
    //   479: athrow
    //   480: invokespecial <init> : ()V
    //   483: goto -> 487
    //   486: athrow
    //   487: ldc_w '欮㌒歩漰ञ薥ูᚨ?嗹폓੧ꛛ⏭턞辋댉ᐼ侾膜ᐱ囔㼵ᣚ칔箜'
    //   490: getstatic Perryc.1 : I
    //   493: ifeq -> 507
    //   496: ldc2_w 1880410359
    //   499: l2i
    //   500: ldc_w -446260219
    //   503: ixor
    //   504: goto -> 515
    //   507: ldc2_w -2125716827
    //   510: l2i
    //   511: ldc_w -800926525
    //   514: ixor
    //   515: ldc2_w -1088063662
    //   518: l2i
    //   519: ldc_w -1651618590
    //   522: ixor
    //   523: ixor
    //   524: lookupswitch default -> 552, -1210486974 -> 5233, 1794898034 -> 507
    //   552: goto -> 556
    //   555: athrow
    //   556: invokestatic 0 : (Ljava/lang/String;)Ljava/lang/String;
    //   559: goto -> 563
    //   562: athrow
    //   563: getstatic Perryc.c : I
    //   566: iflt -> 580
    //   569: ldc2_w 1082459384
    //   572: l2i
    //   573: ldc_w 1985287417
    //   576: ixor
    //   577: goto -> 588
    //   580: ldc2_w 1500119243
    //   583: l2i
    //   584: ldc_w -965930053
    //   587: ixor
    //   588: ldc2_w 1902086403
    //   591: l2i
    //   592: ldc_w -135622514
    //   595: ixor
    //   596: ixor
    //   597: lookupswitch default -> 5237, -1335555700 -> 580, 431098621 -> 624
    //   624: goto -> 628
    //   627: athrow
    //   628: invokevirtual append : (Ljava/lang/String;)Ljava/lang/StringBuilder;
    //   631: goto -> 635
    //   634: athrow
    //   635: getstatic Perryc.1 : I
    //   638: ifeq -> 652
    //   641: ldc2_w 481367246
    //   644: l2i
    //   645: ldc_w 836353496
    //   648: ixor
    //   649: goto -> 660
    //   652: ldc2_w -976353825
    //   655: l2i
    //   656: ldc_w -2048633099
    //   659: ixor
    //   660: ldc2_w -130777758
    //   663: l2i
    //   664: ldc_w 1990241060
    //   667: ixor
    //   668: ixor
    //   669: lookupswitch default -> 5145, -1543733424 -> 652, -826374804 -> 696
    //   696: iload_1
    //   697: getstatic Perryc.0 : I
    //   700: ifle -> 714
    //   703: ldc2_w -1723784865
    //   706: l2i
    //   707: ldc_w 1727992954
    //   710: ixor
    //   711: goto -> 722
    //   714: ldc2_w 433929766
    //   717: l2i
    //   718: ldc_w -569868058
    //   721: ixor
    //   722: ldc2_w 1102311643
    //   725: l2i
    //   726: ldc_w 836922142
    //   729: ixor
    //   730: ixor
    //   731: lookupswitch default -> 756, -1880117536 -> 5207, 539655617 -> 714
    //   756: goto -> 760
    //   759: athrow
    //   760: invokevirtual append : (I)Ljava/lang/StringBuilder;
    //   763: goto -> 767
    //   766: athrow
    //   767: getstatic Perryc.c : I
    //   770: iflt -> 784
    //   773: ldc2_w 1207380811
    //   776: l2i
    //   777: ldc_w -660478176
    //   780: ixor
    //   781: goto -> 792
    //   784: ldc2_w -1432695060
    //   787: l2i
    //   788: ldc_w -1324742807
    //   791: ixor
    //   792: ldc2_w 774795476
    //   795: l2i
    //   796: ldc_w -1481556928
    //   799: ixor
    //   800: ixor
    //   801: lookupswitch default -> 5185, -1844476655 -> 828, 382304511 -> 784
    //   828: goto -> 832
    //   831: athrow
    //   832: invokevirtual toString : ()Ljava/lang/String;
    //   835: goto -> 839
    //   838: athrow
    //   839: getstatic Perryc.c : I
    //   842: iflt -> 856
    //   845: ldc2_w 509326540
    //   848: l2i
    //   849: ldc_w 196580793
    //   852: ixor
    //   853: goto -> 864
    //   856: ldc2_w 274414435
    //   859: l2i
    //   860: ldc_w 158030849
    //   863: ixor
    //   864: ldc2_w -273053492
    //   867: l2i
    //   868: ldc_w -979889376
    //   871: ixor
    //   872: ixor
    //   873: lookupswitch default -> 5165, 856816782 -> 900, 1070447257 -> 856
    //   900: goto -> 904
    //   903: athrow
    //   904: invokespecial <init> : (Ljava/lang/String;)V
    //   907: goto -> 911
    //   910: athrow
    //   911: athrow
    //   912: getstatic Perryc.1 : I
    //   915: ifeq -> 929
    //   918: ldc2_w 731466848
    //   921: l2i
    //   922: ldc_w 165088452
    //   925: ixor
    //   926: goto -> 937
    //   929: ldc2_w -565193248
    //   932: l2i
    //   933: ldc_w -203621898
    //   936: ixor
    //   937: ldc2_w 435967427
    //   940: l2i
    //   941: ldc_w 1190039662
    //   944: ixor
    //   945: ixor
    //   946: lookupswitch default -> 5127, 1921116603 -> 972, 2103215369 -> 929
    //   972: iload_2
    //   973: ifge -> 987
    //   976: ldc2_w -1834184360
    //   979: l2i
    //   980: ldc_w -1552731050
    //   983: ixor
    //   984: goto -> 995
    //   987: ldc2_w -1495149660
    //   990: l2i
    //   991: ldc_w -1757514069
    //   994: ixor
    //   995: ldc2_w 706067935
    //   998: l2i
    //   999: ldc_w -1088960717
    //   1002: ixor
    //   1003: ixor
    //   1004: tableswitch default -> 976, -1528963102 -> 1028, -1528963101 -> 1532
    //   1028: new java/lang/IllegalArgumentException
    //   1031: dup
    //   1032: new java/lang/StringBuilder
    //   1035: dup
    //   1036: getstatic Perryc.0 : I
    //   1039: ifle -> 1053
    //   1042: ldc2_w 952136100
    //   1045: l2i
    //   1046: ldc_w 1467142754
    //   1049: ixor
    //   1050: goto -> 1061
    //   1053: ldc2_w 1578408805
    //   1056: l2i
    //   1057: ldc_w 910274208
    //   1060: ixor
    //   1061: ldc2_w -1665920178
    //   1064: l2i
    //   1065: ldc_w 975143798
    //   1068: ixor
    //   1069: ixor
    //   1070: lookupswitch default -> 1096, -921095170 -> 5171, -294615471 -> 1053
    //   1096: goto -> 1100
    //   1099: athrow
    //   1100: invokespecial <init> : ()V
    //   1103: goto -> 1107
    //   1106: athrow
    //   1107: ldc_w '欮㌒歩漰ञ薥ูᚨ?嗹폓੧ꛙ⏭턗辋댈ᐶ侷膉ᐲ囓㽪ᢎ'
    //   1110: getstatic Perryc.1 : I
    //   1113: ifeq -> 1127
    //   1116: ldc2_w 124980478
    //   1119: l2i
    //   1120: ldc_w -1703555354
    //   1123: ixor
    //   1124: goto -> 1135
    //   1127: ldc2_w 943225293
    //   1130: l2i
    //   1131: ldc_w -484318738
    //   1134: ixor
    //   1135: ldc2_w -104628888
    //   1138: l2i
    //   1139: ldc_w 1804026693
    //   1142: ixor
    //   1143: ixor
    //   1144: lookupswitch default -> 1172, -1355743430 -> 1127, 256048181 -> 5215
    //   1172: goto -> 1176
    //   1175: athrow
    //   1176: invokestatic 0 : (Ljava/lang/String;)Ljava/lang/String;
    //   1179: goto -> 1183
    //   1182: athrow
    //   1183: getstatic Perryc.1 : I
    //   1186: ifeq -> 1200
    //   1189: ldc2_w -730257842
    //   1192: l2i
    //   1193: ldc_w 850819150
    //   1196: ixor
    //   1197: goto -> 1208
    //   1200: ldc2_w -266414802
    //   1203: l2i
    //   1204: ldc_w 1056501864
    //   1207: ixor
    //   1208: ldc2_w 1679510159
    //   1211: l2i
    //   1212: ldc_w 358592292
    //   1215: ixor
    //   1216: ixor
    //   1217: lookupswitch default -> 1244, -1752450133 -> 5231, 637124939 -> 1200
    //   1244: goto -> 1248
    //   1247: athrow
    //   1248: invokevirtual append : (Ljava/lang/String;)Ljava/lang/StringBuilder;
    //   1251: goto -> 1255
    //   1254: athrow
    //   1255: getstatic Perryc.c : I
    //   1258: iflt -> 1272
    //   1261: ldc2_w 2106511224
    //   1264: l2i
    //   1265: ldc_w 1318764423
    //   1268: ixor
    //   1269: goto -> 1280
    //   1272: ldc2_w -483693397
    //   1275: l2i
    //   1276: ldc_w 224474785
    //   1279: ixor
    //   1280: ldc2_w 1793771237
    //   1283: l2i
    //   1284: ldc_w -1563164176
    //   1287: ixor
    //   1288: ixor
    //   1289: lookupswitch default -> 5155, -81086486 -> 1272, 645176607 -> 1316
    //   1316: iload_2
    //   1317: getstatic Perryc.1 : I
    //   1320: ifeq -> 1334
    //   1323: ldc2_w -286490789
    //   1326: l2i
    //   1327: ldc_w 1362182103
    //   1330: ixor
    //   1331: goto -> 1342
    //   1334: ldc2_w -1602096014
    //   1337: l2i
    //   1338: ldc_w 781236429
    //   1341: ixor
    //   1342: ldc2_w -7428668
    //   1345: l2i
    //   1346: ldc_w 224640032
    //   1349: ixor
    //   1350: ixor
    //   1351: lookupswitch default -> 1376, 701787962 -> 1334, 1295014248 -> 5161
    //   1376: goto -> 1380
    //   1379: athrow
    //   1380: invokevirtual append : (I)Ljava/lang/StringBuilder;
    //   1383: goto -> 1387
    //   1386: athrow
    //   1387: getstatic Perryc.1 : I
    //   1390: ifeq -> 1404
    //   1393: ldc2_w -1840054833
    //   1396: l2i
    //   1397: ldc_w -1630942482
    //   1400: ixor
    //   1401: goto -> 1412
    //   1404: ldc2_w 939418290
    //   1407: l2i
    //   1408: ldc_w -1333734984
    //   1411: ixor
    //   1412: ldc2_w -2010734523
    //   1415: l2i
    //   1416: ldc_w 1476286892
    //   1419: ixor
    //   1420: ixor
    //   1421: lookupswitch default -> 1448, -1330796659 -> 1404, -750530872 -> 5135
    //   1448: goto -> 1452
    //   1451: athrow
    //   1452: invokevirtual toString : ()Ljava/lang/String;
    //   1455: goto -> 1459
    //   1458: athrow
    //   1459: getstatic Perryc.1 : I
    //   1462: ifeq -> 1476
    //   1465: ldc2_w 119130192
    //   1468: l2i
    //   1469: ldc_w -307034236
    //   1472: ixor
    //   1473: goto -> 1484
    //   1476: ldc2_w -457325198
    //   1479: l2i
    //   1480: ldc_w -790056658
    //   1483: ixor
    //   1484: ldc2_w 1529288033
    //   1487: l2i
    //   1488: ldc_w -365087560
    //   1491: ixor
    //   1492: ixor
    //   1493: lookupswitch default -> 1520, 626665872 -> 1476, 1538321933 -> 5173
    //   1520: goto -> 1524
    //   1523: athrow
    //   1524: invokespecial <init> : (Ljava/lang/String;)V
    //   1527: goto -> 1531
    //   1530: athrow
    //   1531: athrow
    //   1532: getstatic Perryc.1 : I
    //   1535: ifeq -> 1549
    //   1538: ldc2_w 498888739
    //   1541: l2i
    //   1542: ldc_w -1241720538
    //   1545: ixor
    //   1546: goto -> 1557
    //   1549: ldc2_w 880002407
    //   1552: l2i
    //   1553: ldc_w 1685241167
    //   1556: ixor
    //   1557: ldc2_w -2037353102
    //   1560: l2i
    //   1561: ldc_w 1148946321
    //   1564: ixor
    //   1565: ixor
    //   1566: lookupswitch default -> 5187, -1830122805 -> 1592, 1789615078 -> 1549
    //   1592: iload_1
    //   1593: getstatic Perryc.1 : I
    //   1596: ifeq -> 1610
    //   1599: ldc2_w -1836712858
    //   1602: l2i
    //   1603: ldc_w -2120954794
    //   1606: ixor
    //   1607: goto -> 1618
    //   1610: ldc2_w -2121283119
    //   1613: l2i
    //   1614: ldc_w -1369017764
    //   1617: ixor
    //   1618: ldc2_w 1561098165
    //   1621: l2i
    //   1622: ldc_w 828580407
    //   1625: ixor
    //   1626: ixor
    //   1627: lookupswitch default -> 1652, 838221850 -> 1610, 2138990002 -> 5149
    //   1652: iload_2
    //   1653: iadd
    //   1654: getstatic Perryc.1 : I
    //   1657: ifeq -> 1671
    //   1660: ldc2_w 850779432
    //   1663: l2i
    //   1664: ldc_w 1713447218
    //   1667: ixor
    //   1668: goto -> 1679
    //   1671: ldc2_w 241327578
    //   1674: l2i
    //   1675: ldc_w 1506776418
    //   1678: ixor
    //   1679: ldc2_w -2062463942
    //   1682: l2i
    //   1683: ldc_w 528061818
    //   1686: ixor
    //   1687: ixor
    //   1688: lookupswitch default -> 5181, -842722824 -> 1716, -822336166 -> 1671
    //   1716: aload_0
    //   1717: arraylength
    //   1718: if_icmple -> 1732
    //   1721: ldc2_w 1282254016
    //   1724: l2i
    //   1725: ldc_w 93642912
    //   1728: ixor
    //   1729: goto -> 1740
    //   1732: ldc2_w 246263750
    //   1735: l2i
    //   1736: ldc_w 1196747685
    //   1739: ixor
    //   1740: ldc2_w 630163855
    //   1743: l2i
    //   1744: ldc_w -1957271614
    //   1747: ixor
    //   1748: ixor
    //   1749: tableswitch default -> 1721, -417289683 -> 1772, -417289682 -> 2432
    //   1772: new java/lang/IllegalArgumentException
    //   1775: dup
    //   1776: ldc_w '欮㌒歩漰ञ薥ูᚨ?嗹폓੧ꛚ⏮턟辚댔ᐶ俱臟ᐳ嚇㼱ᣀ츊箜?๏摻ය撪㓇ڦ奯䉶弃䪋쎘酻弌㿯嬨᎙膺屻⽻它ڽᆜ俵ឈ㐛裰渓洣ꢜ鲘⓼璓ꦢ'
    //   1779: getstatic Perryc.c : I
    //   1782: iflt -> 1796
    //   1785: ldc2_w -196481492
    //   1788: l2i
    //   1789: ldc_w -1171320966
    //   1792: ixor
    //   1793: goto -> 1804
    //   1796: ldc2_w 1620897644
    //   1799: l2i
    //   1800: ldc_w 2047579924
    //   1803: ixor
    //   1804: ldc2_w -1449753766
    //   1807: l2i
    //   1808: ldc_w -642132051
    //   1811: ixor
    //   1812: ixor
    //   1813: lookupswitch default -> 1840, 1045018017 -> 5175, 1997365207 -> 1796
    //   1840: goto -> 1844
    //   1843: athrow
    //   1844: invokestatic 0 : (Ljava/lang/String;)Ljava/lang/String;
    //   1847: goto -> 1851
    //   1850: athrow
    //   1851: ldc2_w 674990816
    //   1854: l2i
    //   1855: ldc_w 674990819
    //   1858: ixor
    //   1859: anewarray java/lang/Object
    //   1862: dup
    //   1863: ldc2_w -90091706
    //   1866: l2i
    //   1867: ldc_w -90091706
    //   1870: ixor
    //   1871: getstatic Perryc.1 : I
    //   1874: ifeq -> 1888
    //   1877: ldc2_w 827871646
    //   1880: l2i
    //   1881: ldc_w -980470535
    //   1884: ixor
    //   1885: goto -> 1896
    //   1888: ldc2_w -777606109
    //   1891: l2i
    //   1892: ldc_w 1129343184
    //   1895: ixor
    //   1896: ldc2_w -307852384
    //   1899: l2i
    //   1900: ldc_w 610511479
    //   1903: ixor
    //   1904: ixor
    //   1905: lookupswitch default -> 5249, 1024607408 -> 1888, 1530127652 -> 1932
    //   1932: iload_1
    //   1933: getstatic Perryc.0 : I
    //   1936: ifle -> 1950
    //   1939: ldc2_w -1648410354
    //   1942: l2i
    //   1943: ldc_w -246839683
    //   1946: ixor
    //   1947: goto -> 1958
    //   1950: ldc2_w 1911408482
    //   1953: l2i
    //   1954: ldc_w -1170120708
    //   1957: ixor
    //   1958: ldc2_w 945937722
    //   1961: l2i
    //   1962: ldc_w -1391229040
    //   1965: ixor
    //   1966: ixor
    //   1967: lookupswitch default -> 5183, -108749351 -> 1950, 1591657012 -> 1992
    //   1992: goto -> 1996
    //   1995: athrow
    //   1996: invokestatic valueOf : (I)Ljava/lang/Integer;
    //   1999: goto -> 2003
    //   2002: athrow
    //   2003: aastore
    //   2004: dup
    //   2005: ldc2_w 301215257
    //   2008: l2i
    //   2009: ldc_w 301215256
    //   2012: ixor
    //   2013: getstatic Perryc.0 : I
    //   2016: ifle -> 2030
    //   2019: ldc2_w 425850517
    //   2022: l2i
    //   2023: ldc_w 924681089
    //   2026: ixor
    //   2027: goto -> 2038
    //   2030: ldc2_w 647755491
    //   2033: l2i
    //   2034: ldc_w 434262777
    //   2037: ixor
    //   2038: ldc2_w -1112032640
    //   2041: l2i
    //   2042: ldc_w 1495898544
    //   2045: ixor
    //   2046: ixor
    //   2047: lookupswitch default -> 2072, -891136476 -> 5225, -736149410 -> 2030
    //   2072: iload_2
    //   2073: getstatic Perryc.1 : I
    //   2076: ifeq -> 2090
    //   2079: ldc2_w 1097524525
    //   2082: l2i
    //   2083: ldc_w 583806812
    //   2086: ixor
    //   2087: goto -> 2098
    //   2090: ldc2_w -1557129073
    //   2093: l2i
    //   2094: ldc_w -305549497
    //   2097: ixor
    //   2098: ldc2_w -776569990
    //   2101: l2i
    //   2102: ldc_w -1873330398
    //   2105: ixor
    //   2106: ixor
    //   2107: lookupswitch default -> 2132, 301371948 -> 2090, 575114793 -> 5199
    //   2132: goto -> 2136
    //   2135: athrow
    //   2136: invokestatic valueOf : (I)Ljava/lang/Integer;
    //   2139: goto -> 2143
    //   2142: athrow
    //   2143: aastore
    //   2144: dup
    //   2145: ldc2_w 1846639316
    //   2148: l2i
    //   2149: ldc_w 1846639318
    //   2152: ixor
    //   2153: getstatic Perryc.1 : I
    //   2156: ifeq -> 2170
    //   2159: ldc2_w -815720387
    //   2162: l2i
    //   2163: ldc_w 1389793800
    //   2166: ixor
    //   2167: goto -> 2178
    //   2170: ldc2_w -438788201
    //   2173: l2i
    //   2174: ldc_w -2109361897
    //   2177: ixor
    //   2178: ldc2_w -1044378775
    //   2181: l2i
    //   2182: ldc_w -411295753
    //   2185: ixor
    //   2186: ixor
    //   2187: lookupswitch default -> 5163, -1156866389 -> 2170, 1092696606 -> 2212
    //   2212: aload_0
    //   2213: arraylength
    //   2214: getstatic Perryc.0 : I
    //   2217: ifle -> 2231
    //   2220: ldc2_w -1667581779
    //   2223: l2i
    //   2224: ldc_w -337886522
    //   2227: ixor
    //   2228: goto -> 2239
    //   2231: ldc2_w 1307383270
    //   2234: l2i
    //   2235: ldc_w -1323625781
    //   2238: ixor
    //   2239: ldc2_w 1754368208
    //   2242: l2i
    //   2243: ldc_w -1608442799
    //   2246: ixor
    //   2247: ixor
    //   2248: lookupswitch default -> 2276, -1074368790 -> 5251, 555551726 -> 2231
    //   2276: goto -> 2280
    //   2279: athrow
    //   2280: invokestatic valueOf : (I)Ljava/lang/Integer;
    //   2283: goto -> 2287
    //   2286: athrow
    //   2287: aastore
    //   2288: getstatic Perryc.c : I
    //   2291: iflt -> 2305
    //   2294: ldc2_w -433730005
    //   2297: l2i
    //   2298: ldc_w -827060950
    //   2301: ixor
    //   2302: goto -> 2313
    //   2305: ldc2_w -104486550
    //   2308: l2i
    //   2309: ldc_w -778590845
    //   2312: ixor
    //   2313: ldc2_w 1256566771
    //   2316: l2i
    //   2317: ldc_w -457133410
    //   2320: ixor
    //   2321: ixor
    //   2322: lookupswitch default -> 2348, -2034966932 -> 5195, 2103091713 -> 2305
    //   2348: goto -> 2352
    //   2351: athrow
    //   2352: invokestatic format : (Ljava/lang/String;[Ljava/lang/Object;)Ljava/lang/String;
    //   2355: goto -> 2359
    //   2358: athrow
    //   2359: getstatic Perryc.1 : I
    //   2362: ifeq -> 2376
    //   2365: ldc2_w -1742762810
    //   2368: l2i
    //   2369: ldc_w -1870619171
    //   2372: ixor
    //   2373: goto -> 2384
    //   2376: ldc2_w 1200876429
    //   2379: l2i
    //   2380: ldc_w -736595041
    //   2383: ixor
    //   2384: ldc2_w 2079115000
    //   2387: l2i
    //   2388: ldc_w 61565700
    //   2391: ixor
    //   2392: ixor
    //   2393: lookupswitch default -> 5201, -338938386 -> 2420, 1893252327 -> 2376
    //   2420: goto -> 2424
    //   2423: athrow
    //   2424: invokespecial <init> : (Ljava/lang/String;)V
    //   2427: goto -> 2431
    //   2430: athrow
    //   2431: athrow
    //   2432: getstatic Perryc.1 : I
    //   2435: ifeq -> 2449
    //   2438: ldc2_w 955153570
    //   2441: l2i
    //   2442: ldc_w 1265459813
    //   2445: ixor
    //   2446: goto -> 2457
    //   2449: ldc2_w 1147507753
    //   2452: l2i
    //   2453: ldc_w -1187766096
    //   2456: ixor
    //   2457: ldc2_w 62032853
    //   2460: l2i
    //   2461: ldc_w 537474093
    //   2464: ixor
    //   2465: ixor
    //   2466: lookupswitch default -> 5129, -555087007 -> 2492, 1345888575 -> 2449
    //   2492: iload_2
    //   2493: ldc2_w -1395015401
    //   2496: l2i
    //   2497: ldc_w -1395015404
    //   2500: ixor
    //   2501: idiv
    //   2502: ldc2_w -1133586204
    //   2505: l2i
    //   2506: ldc_w -1133586208
    //   2509: ixor
    //   2510: imul
    //   2511: getstatic Perryc.0 : I
    //   2514: ifle -> 2528
    //   2517: ldc2_w -1468680572
    //   2520: l2i
    //   2521: ldc_w 236629558
    //   2524: ixor
    //   2525: goto -> 2536
    //   2528: ldc2_w -270723321
    //   2531: l2i
    //   2532: ldc_w 582633011
    //   2535: ixor
    //   2536: ldc2_w -1367599167
    //   2539: l2i
    //   2540: ldc_w -845569088
    //   2543: ixor
    //   2544: ixor
    //   2545: lookupswitch default -> 2572, -980767565 -> 5169, 1843184168 -> 2528
    //   2572: iload_2
    //   2573: ldc2_w 1961086235
    //   2576: l2i
    //   2577: ldc_w 1961086232
    //   2580: ixor
    //   2581: irem
    //   2582: ifle -> 2596
    //   2585: ldc2_w 1547603855
    //   2588: l2i
    //   2589: ldc_w -508315437
    //   2592: ixor
    //   2593: goto -> 2604
    //   2596: ldc2_w 1206495897
    //   2599: l2i
    //   2600: ldc_w -94069310
    //   2603: ixor
    //   2604: ldc2_w -1224708051
    //   2607: l2i
    //   2608: ldc_w 1785930986
    //   2611: ixor
    //   2612: ixor
    //   2613: tableswitch default -> 2585, 1627284379 -> 2636, 1627284380 -> 2647
    //   2636: ldc2_w -1281073939
    //   2639: l2i
    //   2640: ldc_w -1281073943
    //   2643: ixor
    //   2644: goto -> 2655
    //   2647: ldc2_w -225360381
    //   2650: l2i
    //   2651: ldc_w -225360381
    //   2654: ixor
    //   2655: iadd
    //   2656: getstatic Perryc.c : I
    //   2659: iflt -> 2673
    //   2662: ldc2_w 1895566061
    //   2665: l2i
    //   2666: ldc_w 37148525
    //   2669: ixor
    //   2670: goto -> 2681
    //   2673: ldc2_w -1047111904
    //   2676: l2i
    //   2677: ldc_w -801636636
    //   2680: ixor
    //   2681: ldc2_w -1244708924
    //   2684: l2i
    //   2685: ldc_w -2114621456
    //   2688: ixor
    //   2689: ixor
    //   2690: lookupswitch default -> 5217, 630979056 -> 2716, 1190170036 -> 2673
    //   2716: istore_3
    //   2717: getstatic Perryc.1 : I
    //   2720: ifeq -> 2734
    //   2723: ldc2_w 591923340
    //   2726: l2i
    //   2727: ldc_w 407115069
    //   2730: ixor
    //   2731: goto -> 2742
    //   2734: ldc2_w -1532904607
    //   2737: l2i
    //   2738: ldc_w 764793750
    //   2741: ixor
    //   2742: ldc2_w -1251461041
    //   2745: l2i
    //   2746: ldc_w 473975879
    //   2749: ixor
    //   2750: ixor
    //   2751: lookupswitch default -> 2776, -1843107399 -> 5137, -626832821 -> 2734
    //   2776: iload_3
    //   2777: newarray byte
    //   2779: getstatic Perryc.1 : I
    //   2782: ifeq -> 2796
    //   2785: ldc2_w -579000222
    //   2788: l2i
    //   2789: ldc_w 1878888175
    //   2792: ixor
    //   2793: goto -> 2804
    //   2796: ldc2_w 1556324087
    //   2799: l2i
    //   2800: ldc_w -1428264665
    //   2803: ixor
    //   2804: ldc2_w 1638211713
    //   2807: l2i
    //   2808: ldc_w -1716030139
    //   2811: ixor
    //   2812: ixor
    //   2813: lookupswitch default -> 5157, 235905556 -> 2840, 1251144521 -> 2796
    //   2840: astore #4
    //   2842: ldc2_w 1814068330
    //   2845: l2i
    //   2846: ldc_w 1814068330
    //   2849: ixor
    //   2850: getstatic Perryc.c : I
    //   2853: iflt -> 2867
    //   2856: ldc2_w -1444945797
    //   2859: l2i
    //   2860: ldc_w 584683771
    //   2863: ixor
    //   2864: goto -> 2875
    //   2867: ldc2_w 1033068626
    //   2870: l2i
    //   2871: ldc_w -2059237095
    //   2874: ixor
    //   2875: ldc2_w -2079720760
    //   2878: l2i
    //   2879: ldc_w 1715787199
    //   2882: ixor
    //   2883: ixor
    //   2884: lookupswitch default -> 5253, 1520223804 -> 2912, 1766547447 -> 2867
    //   2912: istore #5
    //   2914: ldc2_w -315964963
    //   2917: l2i
    //   2918: ldc_w -315964963
    //   2921: ixor
    //   2922: getstatic Perryc.1 : I
    //   2925: ifeq -> 2939
    //   2928: ldc2_w 981271091
    //   2931: l2i
    //   2932: ldc_w -1324832229
    //   2935: ixor
    //   2936: goto -> 2947
    //   2939: ldc2_w -2074913989
    //   2942: l2i
    //   2943: ldc_w 58718681
    //   2946: ixor
    //   2947: ldc2_w -287286001
    //   2950: l2i
    //   2951: ldc_w -1309327419
    //   2954: ixor
    //   2955: ixor
    //   2956: lookupswitch default -> 5241, -731854110 -> 2939, -667301848 -> 2984
    //   2984: istore #6
    //   2986: getstatic Perryc.1 : I
    //   2989: ifeq -> 3003
    //   2992: ldc2_w -256200417
    //   2995: l2i
    //   2996: ldc_w 1198191940
    //   2999: ixor
    //   3000: goto -> 3011
    //   3003: ldc2_w 958485853
    //   3006: l2i
    //   3007: ldc_w 382781866
    //   3010: ixor
    //   3011: ldc2_w -221714659
    //   3014: l2i
    //   3015: ldc_w -840277260
    //   3018: ixor
    //   3019: ixor
    //   3020: lookupswitch default -> 3048, -1997356622 -> 5203, -1744024099 -> 3003
    //   3048: iload_2
    //   3049: ldc2_w 86929232
    //   3052: l2i
    //   3053: ldc_w 86929234
    //   3056: ixor
    //   3057: isub
    //   3058: getstatic Perryc.1 : I
    //   3061: ifeq -> 3075
    //   3064: ldc2_w -1140174395
    //   3067: l2i
    //   3068: ldc_w -1042230827
    //   3071: ixor
    //   3072: goto -> 3083
    //   3075: ldc2_w 1804843509
    //   3078: l2i
    //   3079: ldc_w -1913393658
    //   3082: ixor
    //   3083: ldc2_w -780281349
    //   3086: l2i
    //   3087: ldc_w -514853379
    //   3090: ixor
    //   3091: ixor
    //   3092: lookupswitch default -> 3120, 1306045462 -> 5139, 1485419197 -> 3075
    //   3120: istore #7
    //   3122: getstatic Perryc.c : I
    //   3125: iflt -> 3139
    //   3128: ldc2_w -1760792590
    //   3131: l2i
    //   3132: ldc_w -772944613
    //   3135: ixor
    //   3136: goto -> 3147
    //   3139: ldc2_w -1051817104
    //   3142: l2i
    //   3143: ldc_w -940579846
    //   3146: ixor
    //   3147: ldc2_w 928909708
    //   3150: l2i
    //   3151: ldc_w 1818992992
    //   3154: ixor
    //   3155: ixor
    //   3156: lookupswitch default -> 3184, 500435461 -> 5245, 738235931 -> 3139
    //   3184: iload #5
    //   3186: getstatic Perryc.c : I
    //   3189: iflt -> 3203
    //   3192: ldc2_w 502462149
    //   3195: l2i
    //   3196: ldc_w -824201675
    //   3199: ixor
    //   3200: goto -> 3211
    //   3203: ldc2_w -312599767
    //   3206: l2i
    //   3207: ldc_w 2005994784
    //   3210: ixor
    //   3211: ldc2_w -1957183620
    //   3214: l2i
    //   3215: ldc_w 2044395930
    //   3218: ixor
    //   3219: ixor
    //   3220: lookupswitch default -> 5205, 564258326 -> 3203, 1749264623 -> 3248
    //   3248: iload #7
    //   3250: if_icmpge -> 3264
    //   3253: ldc2_w 795843244
    //   3256: l2i
    //   3257: ldc_w -1196151844
    //   3260: ixor
    //   3261: goto -> 3272
    //   3264: ldc2_w -50454586
    //   3267: l2i
    //   3268: ldc_w 1797631671
    //   3271: ixor
    //   3272: ldc2_w 1407574786
    //   3275: l2i
    //   3276: ldc_w 1228350248
    //   3279: ixor
    //   3280: ixor
    //   3281: tableswitch default -> 3253, -1928760998 -> 3304, -1928760997 -> 3709
    //   3304: getstatic Perryc.c : I
    //   3307: iflt -> 3321
    //   3310: ldc2_w -146177478
    //   3313: l2i
    //   3314: ldc_w 1142478865
    //   3317: ixor
    //   3318: goto -> 3329
    //   3321: ldc2_w -643774479
    //   3324: l2i
    //   3325: ldc_w 1670469027
    //   3328: ixor
    //   3329: ldc2_w 848021506
    //   3332: l2i
    //   3333: ldc_w 1586010034
    //   3336: ixor
    //   3337: ixor
    //   3338: lookupswitch default -> 5259, -701313566 -> 3364, -548272741 -> 3321
    //   3364: aload_0
    //   3365: getstatic Perryc.c : I
    //   3368: iflt -> 3382
    //   3371: ldc2_w -298751335
    //   3374: l2i
    //   3375: ldc_w -1613327603
    //   3378: ixor
    //   3379: goto -> 3390
    //   3382: ldc2_w 1485032263
    //   3385: l2i
    //   3386: ldc_w 112188479
    //   3389: ixor
    //   3390: ldc2_w -1023829205
    //   3393: l2i
    //   3394: ldc_w -1044775765
    //   3397: ixor
    //   3398: ixor
    //   3399: lookupswitch default -> 5229, 1567387896 -> 3424, 1923587604 -> 3382
    //   3424: iload #5
    //   3426: getstatic Perryc.1 : I
    //   3429: ifeq -> 3443
    //   3432: ldc2_w 422834580
    //   3435: l2i
    //   3436: ldc_w -386049636
    //   3439: ixor
    //   3440: goto -> 3451
    //   3443: ldc2_w 808311736
    //   3446: l2i
    //   3447: ldc_w -1175675122
    //   3450: ixor
    //   3451: ldc2_w 2113483435
    //   3454: l2i
    //   3455: ldc_w -1615043770
    //   3458: ixor
    //   3459: ixor
    //   3460: lookupswitch default -> 5235, 327940581 -> 3443, 1803818331 -> 3488
    //   3488: iload_1
    //   3489: iadd
    //   3490: ldc2_w 1509486120
    //   3493: l2i
    //   3494: ldc_w 1509486123
    //   3497: ixor
    //   3498: getstatic Perryc.1 : I
    //   3501: ifeq -> 3515
    //   3504: ldc2_w -77758589
    //   3507: l2i
    //   3508: ldc_w 896539520
    //   3511: ixor
    //   3512: goto -> 3523
    //   3515: ldc2_w -742362222
    //   3518: l2i
    //   3519: ldc_w -209851500
    //   3522: ixor
    //   3523: ldc2_w -2053561615
    //   3526: l2i
    //   3527: ldc_w -990358628
    //   3530: ixor
    //   3531: ixor
    //   3532: lookupswitch default -> 5243, -1890839186 -> 3515, 1641867627 -> 3560
    //   3560: aload #4
    //   3562: getstatic Perryc.0 : I
    //   3565: ifle -> 3579
    //   3568: ldc2_w 330574028
    //   3571: l2i
    //   3572: ldc_w 2084278755
    //   3575: ixor
    //   3576: goto -> 3587
    //   3579: ldc2_w -966349679
    //   3582: l2i
    //   3583: ldc_w 791004109
    //   3586: ixor
    //   3587: ldc2_w -2055693090
    //   3590: l2i
    //   3591: ldc_w 22101248
    //   3594: ixor
    //   3595: ixor
    //   3596: lookupswitch default -> 3624, -1126622635 -> 3579, -341436175 -> 5261
    //   3624: iload #6
    //   3626: getstatic Perryc.c : I
    //   3629: iflt -> 3643
    //   3632: ldc2_w 749945607
    //   3635: l2i
    //   3636: ldc_w -1830997489
    //   3639: ixor
    //   3640: goto -> 3651
    //   3643: ldc2_w -982558457
    //   3646: l2i
    //   3647: ldc_w -1437675308
    //   3650: ixor
    //   3651: ldc2_w -856924123
    //   3654: l2i
    //   3655: ldc_w 1294550897
    //   3658: ixor
    //   3659: ixor
    //   3660: lookupswitch default -> 3688, -1729285802 -> 3643, 1068193372 -> 5219
    //   3688: goto -> 3692
    //   3691: athrow
    //   3692: invokestatic encode3to4 : ([BII[BI)[B
    //   3695: goto -> 3699
    //   3698: athrow
    //   3699: pop
    //   3700: iinc #5, 3
    //   3703: iinc #6, 4
    //   3706: goto -> 3122
    //   3709: getstatic Perryc.1 : I
    //   3712: ifeq -> 3726
    //   3715: ldc2_w 910529855
    //   3718: l2i
    //   3719: ldc_w -468454064
    //   3722: ixor
    //   3723: goto -> 3734
    //   3726: ldc2_w -2044740980
    //   3729: l2i
    //   3730: ldc_w -1926724250
    //   3733: ixor
    //   3734: ldc2_w 164080810
    //   3737: l2i
    //   3738: ldc_w 376652876
    //   3741: ixor
    //   3742: ixor
    //   3743: lookupswitch default -> 5197, -840791927 -> 3726, 344184588 -> 3768
    //   3768: iload #5
    //   3770: getstatic Perryc.0 : I
    //   3773: ifle -> 3787
    //   3776: ldc2_w 1435036428
    //   3779: l2i
    //   3780: ldc_w 1374868440
    //   3783: ixor
    //   3784: goto -> 3795
    //   3787: ldc2_w -845851731
    //   3790: l2i
    //   3791: ldc_w 1765158847
    //   3794: ixor
    //   3795: ldc2_w -1904387016
    //   3798: l2i
    //   3799: ldc_w -474780992
    //   3802: ixor
    //   3803: ixor
    //   3804: lookupswitch default -> 3832, -119800074 -> 3787, 1773407788 -> 5151
    //   3832: iload_2
    //   3833: if_icmpge -> 3847
    //   3836: ldc2_w 816901349
    //   3839: l2i
    //   3840: ldc_w -659767738
    //   3843: ixor
    //   3844: goto -> 3855
    //   3847: ldc2_w -135328224
    //   3850: l2i
    //   3851: ldc_w 536042626
    //   3854: ixor
    //   3855: ldc2_w -1497542095
    //   3858: l2i
    //   3859: ldc_w 1778185524
    //   3862: ixor
    //   3863: ixor
    //   3864: tableswitch default -> 3836, 660469158 -> 3888, 660469159 -> 4403
    //   3888: getstatic Perryc.0 : I
    //   3891: ifle -> 3905
    //   3894: ldc2_w -1770143360
    //   3897: l2i
    //   3898: ldc_w -2067664272
    //   3901: ixor
    //   3902: goto -> 3913
    //   3905: ldc2_w -510267522
    //   3908: l2i
    //   3909: ldc_w -1579452408
    //   3912: ixor
    //   3913: ldc2_w -1040230443
    //   3916: l2i
    //   3917: ldc_w 34940516
    //   3920: ixor
    //   3921: ixor
    //   3922: lookupswitch default -> 5191, -2086345017 -> 3948, -782876095 -> 3905
    //   3948: aload_0
    //   3949: getstatic Perryc.0 : I
    //   3952: ifle -> 3966
    //   3955: ldc2_w 1136153958
    //   3958: l2i
    //   3959: ldc_w 1461299975
    //   3962: ixor
    //   3963: goto -> 3974
    //   3966: ldc2_w -582369033
    //   3969: l2i
    //   3970: ldc_w 1035518005
    //   3973: ixor
    //   3974: ldc2_w -627684275
    //   3977: l2i
    //   3978: ldc_w -1658783454
    //   3981: ixor
    //   3982: ixor
    //   3983: lookupswitch default -> 5257, -1488472659 -> 4008, 1394035470 -> 3966
    //   4008: iload #5
    //   4010: getstatic Perryc.1 : I
    //   4013: ifeq -> 4027
    //   4016: ldc2_w -211211718
    //   4019: l2i
    //   4020: ldc_w 368926522
    //   4023: ixor
    //   4024: goto -> 4035
    //   4027: ldc2_w -418642920
    //   4030: l2i
    //   4031: ldc_w -348683674
    //   4034: ixor
    //   4035: ldc2_w -1717603862
    //   4038: l2i
    //   4039: ldc_w -527037713
    //   4042: ixor
    //   4043: ixor
    //   4044: lookupswitch default -> 4072, -1617097211 -> 5143, 2069651777 -> 4027
    //   4072: iload_1
    //   4073: iadd
    //   4074: getstatic Perryc.1 : I
    //   4077: ifeq -> 4091
    //   4080: ldc2_w 456927644
    //   4083: l2i
    //   4084: ldc_w 1396318358
    //   4087: ixor
    //   4088: goto -> 4099
    //   4091: ldc2_w 1105060690
    //   4094: l2i
    //   4095: ldc_w -681486
    //   4098: ixor
    //   4099: ldc2_w 355973460
    //   4102: l2i
    //   4103: ldc_w -1869266619
    //   4106: ixor
    //   4107: ixor
    //   4108: lookupswitch default -> 4136, -844828389 -> 5189, 1326646931 -> 4091
    //   4136: iload_2
    //   4137: getstatic Perryc.c : I
    //   4140: iflt -> 4154
    //   4143: ldc2_w -617464091
    //   4146: l2i
    //   4147: ldc_w 283866641
    //   4150: ixor
    //   4151: goto -> 4162
    //   4154: ldc2_w -1146286678
    //   4157: l2i
    //   4158: ldc_w 761057311
    //   4161: ixor
    //   4162: ldc2_w -411460239
    //   4165: l2i
    //   4166: ldc_w -1418558172
    //   4169: ixor
    //   4170: ixor
    //   4171: lookupswitch default -> 5179, -2016259935 -> 4154, -621099552 -> 4196
    //   4196: iload #5
    //   4198: isub
    //   4199: getstatic Perryc.c : I
    //   4202: iflt -> 4216
    //   4205: ldc2_w 999276056
    //   4208: l2i
    //   4209: ldc_w 489496320
    //   4212: ixor
    //   4213: goto -> 4224
    //   4216: ldc2_w 742323329
    //   4219: l2i
    //   4220: ldc_w 1594401800
    //   4223: ixor
    //   4224: ldc2_w 557872412
    //   4227: l2i
    //   4228: ldc_w 574901126
    //   4231: ixor
    //   4232: ixor
    //   4233: lookupswitch default -> 5147, 631676802 -> 4216, 1882353171 -> 4260
    //   4260: aload #4
    //   4262: getstatic Perryc.0 : I
    //   4265: ifle -> 4279
    //   4268: ldc2_w -689324412
    //   4271: l2i
    //   4272: ldc_w -1862347088
    //   4275: ixor
    //   4276: goto -> 4287
    //   4279: ldc2_w 1513545991
    //   4282: l2i
    //   4283: ldc_w 1328190937
    //   4286: ixor
    //   4287: ldc2_w 1207439254
    //   4290: l2i
    //   4291: ldc_w 1942070212
    //   4294: ixor
    //   4295: ixor
    //   4296: lookupswitch default -> 4324, 1446118605 -> 4279, 1915667558 -> 5177
    //   4324: iload #6
    //   4326: getstatic Perryc.c : I
    //   4329: iflt -> 4343
    //   4332: ldc2_w 549468579
    //   4335: l2i
    //   4336: ldc_w -2032689717
    //   4339: ixor
    //   4340: goto -> 4351
    //   4343: ldc2_w 1433439498
    //   4346: l2i
    //   4347: ldc_w -1327629895
    //   4350: ixor
    //   4351: ldc2_w -1209886632
    //   4354: l2i
    //   4355: ldc_w -500712210
    //   4358: ixor
    //   4359: ixor
    //   4360: lookupswitch default -> 5167, -1335341051 -> 4388, -204308258 -> 4343
    //   4388: goto -> 4392
    //   4391: athrow
    //   4392: invokestatic encode3to4 : ([BII[BI)[B
    //   4395: goto -> 4399
    //   4398: athrow
    //   4399: pop
    //   4400: iinc #6, 4
    //   4403: getstatic Perryc.c : I
    //   4406: iflt -> 4420
    //   4409: ldc2_w -345413799
    //   4412: l2i
    //   4413: ldc_w -258484896
    //   4416: ixor
    //   4417: goto -> 4428
    //   4420: ldc2_w 1883380658
    //   4423: l2i
    //   4424: ldc_w 150464258
    //   4427: ixor
    //   4428: ldc2_w -1002190129
    //   4431: l2i
    //   4432: ldc_w -1278545058
    //   4435: ixor
    //   4436: ixor
    //   4437: lookupswitch default -> 4464, -506411427 -> 4420, 1819773864 -> 5223
    //   4464: iload #6
    //   4466: getstatic Perryc.0 : I
    //   4469: ifle -> 4483
    //   4472: ldc2_w 1069077910
    //   4475: l2i
    //   4476: ldc_w -1393765631
    //   4479: ixor
    //   4480: goto -> 4491
    //   4483: ldc2_w 1307620270
    //   4486: l2i
    //   4487: ldc_w -1713179456
    //   4490: ixor
    //   4491: ldc2_w 470123334
    //   4494: l2i
    //   4495: ldc_w 623222171
    //   4498: ixor
    //   4499: ixor
    //   4500: lookupswitch default -> 5211, -1435232182 -> 4483, -315467341 -> 4528
    //   4528: aload #4
    //   4530: arraylength
    //   4531: ldc2_w -45922164
    //   4534: l2i
    //   4535: ldc_w -45922163
    //   4538: ixor
    //   4539: isub
    //   4540: if_icmpgt -> 4554
    //   4543: ldc2_w 793588320
    //   4546: l2i
    //   4547: ldc_w 1283947790
    //   4550: ixor
    //   4551: goto -> 4562
    //   4554: ldc2_w 365366241
    //   4557: l2i
    //   4558: ldc_w 1980581004
    //   4561: ixor
    //   4562: ldc2_w -306558483
    //   4565: l2i
    //   4566: ldc_w -1561532690
    //   4569: ixor
    //   4570: ixor
    //   4571: tableswitch default -> 4543, 748478573 -> 4592, 748478574 -> 5063
    //   4592: getstatic Perryc.1 : I
    //   4595: ifeq -> 4609
    //   4598: ldc2_w 1912254618
    //   4601: l2i
    //   4602: ldc_w 972265583
    //   4605: ixor
    //   4606: goto -> 4617
    //   4609: ldc2_w 1060712555
    //   4612: l2i
    //   4613: ldc_w -249954427
    //   4616: ixor
    //   4617: ldc2_w -369238329
    //   4620: l2i
    //   4621: ldc_w -2089772596
    //   4624: ixor
    //   4625: ixor
    //   4626: lookupswitch default -> 4652, 549982051 -> 4609, 579104766 -> 5239
    //   4652: iload #6
    //   4654: newarray byte
    //   4656: getstatic Perryc.1 : I
    //   4659: ifeq -> 4673
    //   4662: ldc2_w 539226322
    //   4665: l2i
    //   4666: ldc_w -1317465836
    //   4669: ixor
    //   4670: goto -> 4681
    //   4673: ldc2_w -421000425
    //   4676: l2i
    //   4677: ldc_w 284889495
    //   4680: ixor
    //   4681: ldc2_w -27901687
    //   4684: l2i
    //   4685: ldc_w 824477467
    //   4688: ixor
    //   4689: ixor
    //   4690: lookupswitch default -> 4716, -2088952275 -> 4673, 1579689940 -> 5131
    //   4716: astore #8
    //   4718: getstatic Perryc.0 : I
    //   4721: ifle -> 4735
    //   4724: ldc2_w -1103085066
    //   4727: l2i
    //   4728: ldc_w 2141195805
    //   4731: ixor
    //   4732: goto -> 4743
    //   4735: ldc2_w 1747391322
    //   4738: l2i
    //   4739: ldc_w -590604016
    //   4742: ixor
    //   4743: ldc2_w -1847458992
    //   4746: l2i
    //   4747: ldc_w -1895913685
    //   4750: ixor
    //   4751: ixor
    //   4752: lookupswitch default -> 4780, -2097277006 -> 4735, -553849968 -> 5213
    //   4780: aload #4
    //   4782: ldc2_w 1103097379
    //   4785: l2i
    //   4786: ldc_w 1103097379
    //   4789: ixor
    //   4790: getstatic Perryc.c : I
    //   4793: iflt -> 4807
    //   4796: ldc2_w 1695171772
    //   4799: l2i
    //   4800: ldc_w 1379662522
    //   4803: ixor
    //   4804: goto -> 4815
    //   4807: ldc2_w -872030355
    //   4810: l2i
    //   4811: ldc_w -1207956964
    //   4814: ixor
    //   4815: ldc2_w -1174239759
    //   4818: l2i
    //   4819: ldc_w 1041637695
    //   4822: ixor
    //   4823: ixor
    //   4824: lookupswitch default -> 5227, -1289413944 -> 4807, -267292225 -> 4852
    //   4852: aload #8
    //   4854: ldc2_w 331839782
    //   4857: l2i
    //   4858: ldc_w 331839782
    //   4861: ixor
    //   4862: getstatic Perryc.0 : I
    //   4865: ifle -> 4879
    //   4868: ldc2_w 1775842241
    //   4871: l2i
    //   4872: ldc_w 1057242693
    //   4875: ixor
    //   4876: goto -> 4887
    //   4879: ldc2_w -37789900
    //   4882: l2i
    //   4883: ldc_w -609691835
    //   4886: ixor
    //   4887: ldc2_w -1328253521
    //   4890: l2i
    //   4891: ldc_w -1530958697
    //   4894: ixor
    //   4895: ixor
    //   4896: lookupswitch default -> 5153, 847024457 -> 4924, 1119229116 -> 4879
    //   4924: iload #6
    //   4926: getstatic Perryc.c : I
    //   4929: iflt -> 4943
    //   4932: ldc2_w -1896456989
    //   4935: l2i
    //   4936: ldc_w 476348531
    //   4939: ixor
    //   4940: goto -> 4951
    //   4943: ldc2_w -1067164711
    //   4946: l2i
    //   4947: ldc_w -1817946485
    //   4950: ixor
    //   4951: ldc2_w 989726265
    //   4954: l2i
    //   4955: ldc_w 331712825
    //   4958: ixor
    //   4959: ixor
    //   4960: lookupswitch default -> 4988, -1146530928 -> 5209, -761233157 -> 4943
    //   4988: goto -> 4992
    //   4991: athrow
    //   4992: invokestatic arraycopy : (Ljava/lang/Object;ILjava/lang/Object;II)V
    //   4995: goto -> 4999
    //   4998: athrow
    //   4999: getstatic Perryc.1 : I
    //   5002: ifeq -> 5016
    //   5005: ldc2_w 1171437952
    //   5008: l2i
    //   5009: ldc_w -1599512740
    //   5012: ixor
    //   5013: goto -> 5024
    //   5016: ldc2_w -1686098099
    //   5019: l2i
    //   5020: ldc_w -925615278
    //   5023: ixor
    //   5024: ldc2_w 1070143501
    //   5027: l2i
    //   5028: ldc_w 114963443
    //   5031: ixor
    //   5032: ixor
    //   5033: lookupswitch default -> 5221, -597111518 -> 5016, 1783054305 -> 5060
    //   5060: aload #8
    //   5062: areturn
    //   5063: getstatic Perryc.c : I
    //   5066: iflt -> 5080
    //   5069: ldc2_w -1360006983
    //   5072: l2i
    //   5073: ldc_w -1396004173
    //   5076: ixor
    //   5077: goto -> 5088
    //   5080: ldc2_w -974446606
    //   5083: l2i
    //   5084: ldc_w 942331083
    //   5087: ixor
    //   5088: ldc2_w -1414812816
    //   5091: l2i
    //   5092: ldc_w -786776236
    //   5095: ixor
    //   5096: ixor
    //   5097: lookupswitch default -> 5159, -2022645987 -> 5124, 2022985262 -> 5080
    //   5124: aload #4
    //   5126: areturn
    //   5127: aconst_null
    //   5128: athrow
    //   5129: aconst_null
    //   5130: athrow
    //   5131: aconst_null
    //   5132: athrow
    //   5133: aconst_null
    //   5134: athrow
    //   5135: aconst_null
    //   5136: athrow
    //   5137: aconst_null
    //   5138: athrow
    //   5139: aconst_null
    //   5140: athrow
    //   5141: aconst_null
    //   5142: athrow
    //   5143: aconst_null
    //   5144: athrow
    //   5145: aconst_null
    //   5146: athrow
    //   5147: aconst_null
    //   5148: athrow
    //   5149: aconst_null
    //   5150: athrow
    //   5151: aconst_null
    //   5152: athrow
    //   5153: aconst_null
    //   5154: athrow
    //   5155: aconst_null
    //   5156: athrow
    //   5157: aconst_null
    //   5158: athrow
    //   5159: aconst_null
    //   5160: athrow
    //   5161: aconst_null
    //   5162: athrow
    //   5163: aconst_null
    //   5164: athrow
    //   5165: aconst_null
    //   5166: athrow
    //   5167: aconst_null
    //   5168: athrow
    //   5169: aconst_null
    //   5170: athrow
    //   5171: aconst_null
    //   5172: athrow
    //   5173: aconst_null
    //   5174: athrow
    //   5175: aconst_null
    //   5176: athrow
    //   5177: aconst_null
    //   5178: athrow
    //   5179: aconst_null
    //   5180: athrow
    //   5181: aconst_null
    //   5182: athrow
    //   5183: aconst_null
    //   5184: athrow
    //   5185: aconst_null
    //   5186: athrow
    //   5187: aconst_null
    //   5188: athrow
    //   5189: aconst_null
    //   5190: athrow
    //   5191: aconst_null
    //   5192: athrow
    //   5193: aconst_null
    //   5194: athrow
    //   5195: aconst_null
    //   5196: athrow
    //   5197: aconst_null
    //   5198: athrow
    //   5199: aconst_null
    //   5200: athrow
    //   5201: aconst_null
    //   5202: athrow
    //   5203: aconst_null
    //   5204: athrow
    //   5205: aconst_null
    //   5206: athrow
    //   5207: aconst_null
    //   5208: athrow
    //   5209: aconst_null
    //   5210: athrow
    //   5211: aconst_null
    //   5212: athrow
    //   5213: aconst_null
    //   5214: athrow
    //   5215: aconst_null
    //   5216: athrow
    //   5217: aconst_null
    //   5218: athrow
    //   5219: aconst_null
    //   5220: athrow
    //   5221: aconst_null
    //   5222: athrow
    //   5223: aconst_null
    //   5224: athrow
    //   5225: aconst_null
    //   5226: athrow
    //   5227: aconst_null
    //   5228: athrow
    //   5229: aconst_null
    //   5230: athrow
    //   5231: aconst_null
    //   5232: athrow
    //   5233: aconst_null
    //   5234: athrow
    //   5235: aconst_null
    //   5236: athrow
    //   5237: aconst_null
    //   5238: athrow
    //   5239: aconst_null
    //   5240: athrow
    //   5241: aconst_null
    //   5242: athrow
    //   5243: aconst_null
    //   5244: athrow
    //   5245: aconst_null
    //   5246: athrow
    //   5247: aconst_null
    //   5248: athrow
    //   5249: aconst_null
    //   5250: athrow
    //   5251: aconst_null
    //   5252: athrow
    //   5253: aconst_null
    //   5254: athrow
    //   5255: aconst_null
    //   5256: athrow
    //   5257: aconst_null
    //   5258: athrow
    //   5259: aconst_null
    //   5260: athrow
    //   5261: aconst_null
    //   5262: athrow
    //   5263: pop
    //   5264: goto -> 24
    //   5267: pop
    //   5268: aconst_null
    //   5269: goto -> 5263
    //   5272: dup
    //   5273: ifnull -> 5263
    //   5276: checkcast java/lang/Throwable
    //   5279: athrow
    //   5280: dup
    //   5281: ifnull -> 5267
    //   5284: checkcast java/lang/Throwable
    //   5287: athrow
    //   5288: aconst_null
    //   5289: athrow
    // Local variable table:
    //   start	length	slot	name	descriptor
    //   4718	345	8	finalOut	[B
    //   24	5103	0	source	[B
    //   24	5103	1	off	I
    //   24	5103	2	len	I
    //   2717	2410	3	encLen	I
    //   2842	2285	4	outBuff	[B
    //   2914	2213	5	d	I
    //   2986	2141	6	e	I
    //   3122	2005	7	len2	I
    // Exception table:
    //   from	to	target	type
    //   8	20	5272	java/lang/StringIndexOutOfBoundsException
    //   211	218	218	finally
    //   211	218	218	finally
    //   212	218	211	finally
    //   212	218	218	finally
    //   212	218	3	finally
    //   283	290	290	finally
    //   283	290	290	java/lang/IllegalArgumentException
    //   283	290	290	finally
    //   284	290	290	java/lang/StringIndexOutOfBoundsException
    //   284	290	283	java/lang/UnsupportedOperationException
    //   479	486	486	finally
    //   480	486	479	java/lang/RuntimeException
    //   480	486	3	finally
    //   480	486	3	finally
    //   480	486	3	java/lang/ArrayIndexOutOfBoundsException
    //   555	562	562	finally
    //   555	562	3	finally
    //   555	562	555	finally
    //   556	562	562	finally
    //   556	562	562	java/lang/StringIndexOutOfBoundsException
    //   627	634	634	finally
    //   627	634	3	java/lang/NumberFormatException
    //   627	634	3	finally
    //   628	634	627	java/lang/IndexOutOfBoundsException
    //   628	634	3	finally
    //   759	766	766	finally
    //   759	766	3	java/lang/UnsupportedOperationException
    //   759	766	3	finally
    //   759	766	759	java/lang/StringIndexOutOfBoundsException
    //   760	766	766	java/util/NoSuchElementException
    //   832	838	838	finally
    //   832	838	838	java/lang/ArrayIndexOutOfBoundsException
    //   832	838	3	finally
    //   832	838	3	java/lang/ArithmeticException
    //   832	838	3	finally
    //   903	910	910	finally
    //   903	910	910	finally
    //   903	910	910	finally
    //   903	910	910	java/lang/ArithmeticException
    //   904	910	903	java/lang/RuntimeException
    //   1100	1106	1106	finally
    //   1100	1106	1106	java/lang/ArithmeticException
    //   1100	1106	3	java/lang/IllegalStateException
    //   1100	1106	1106	java/lang/EnumConstantNotPresentException
    //   1100	1106	1106	java/lang/IllegalStateException
    //   1175	1182	1182	finally
    //   1175	1182	1175	java/lang/ClassCastException
    //   1175	1182	1175	java/lang/IllegalArgumentException
    //   1176	1182	1182	finally
    //   1176	1182	3	java/lang/ClassCastException
    //   1247	1254	1254	finally
    //   1247	1254	1247	finally
    //   1248	1254	1254	java/lang/EnumConstantNotPresentException
    //   1248	1254	1247	java/lang/ArrayIndexOutOfBoundsException
    //   1248	1254	1247	java/lang/ClassCastException
    //   1380	1386	1386	finally
    //   1380	1386	3	java/lang/StringIndexOutOfBoundsException
    //   1380	1386	3	java/lang/NumberFormatException
    //   1380	1386	1386	java/lang/RuntimeException
    //   1380	1386	1386	java/lang/IllegalStateException
    //   1452	1458	1458	finally
    //   1452	1458	3	java/util/NoSuchElementException
    //   1452	1458	1458	finally
    //   1452	1458	1458	java/lang/UnsupportedOperationException
    //   1452	1458	3	java/lang/NullPointerException
    //   1524	1530	1530	finally
    //   1524	1530	1530	finally
    //   1524	1530	1530	finally
    //   1524	1530	1530	finally
    //   1524	1530	3	java/lang/UnsupportedOperationException
    //   1843	1850	1850	finally
    //   1843	1850	1850	finally
    //   1843	1850	1850	java/lang/IllegalStateException
    //   1844	1850	1843	java/lang/ClassCastException
    //   1844	1850	1850	finally
    //   1995	2002	2002	finally
    //   1996	2002	3	finally
    //   1996	2002	3	java/lang/ClassCastException
    //   1996	2002	1995	java/lang/UnsupportedOperationException
    //   1996	2002	2002	finally
    //   2135	2142	2142	finally
    //   2135	2142	2135	java/lang/EnumConstantNotPresentException
    //   2135	2142	3	finally
    //   2135	2142	2142	finally
    //   2135	2142	3	finally
    //   2280	2286	2286	finally
    //   2280	2286	2286	finally
    //   2280	2286	2286	java/lang/ArrayIndexOutOfBoundsException
    //   2280	2286	3	finally
    //   2280	2286	3	finally
    //   2351	2358	2358	finally
    //   2351	2358	2351	java/lang/ArrayIndexOutOfBoundsException
    //   2351	2358	2358	finally
    //   2352	2358	2351	finally
    //   2352	2358	3	java/lang/IndexOutOfBoundsException
    //   2423	2430	2430	finally
    //   2423	2430	2430	java/lang/ArithmeticException
    //   2424	2430	3	java/lang/NullPointerException
    //   2424	2430	2430	java/lang/StringIndexOutOfBoundsException
    //   2424	2430	2423	finally
    //   3691	3698	3698	finally
    //   3691	3698	3698	java/lang/NumberFormatException
    //   3691	3698	3698	finally
    //   3691	3698	3691	java/lang/ArrayIndexOutOfBoundsException
    //   3692	3698	3698	java/util/NoSuchElementException
    //   4392	4398	4398	finally
    //   4392	4398	3	java/lang/ArrayIndexOutOfBoundsException
    //   4392	4398	3	finally
    //   4392	4398	3	java/lang/UnsupportedOperationException
    //   4392	4398	3	finally
    //   4992	4998	4998	finally
    //   4992	4998	3	finally
    //   4992	4998	4998	finally
    //   4992	4998	3	java/lang/NullPointerException
    //   4992	4998	4998	finally
    //   5272	5280	5272	finally
    //   5288	5290	3	java/lang/AssertionError
  }
  
  static {
    // Byte code:
    //   0: ldc2_w 1920259458
    //   3: l2i
    //   4: ldc_w 1920259519
    //   7: ixor
    //   8: getstatic Perryc.0 : I
    //   11: ifle -> 25
    //   14: ldc2_w 1768933209
    //   17: l2i
    //   18: ldc_w -423437996
    //   21: ixor
    //   22: goto -> 33
    //   25: ldc2_w 1940464168
    //   28: l2i
    //   29: ldc_w -1903158493
    //   32: ixor
    //   33: ldc2_w -1402669891
    //   36: l2i
    //   37: ldc_w 2016148393
    //   40: ixor
    //   41: ixor
    //   42: lookupswitch default -> 68, -1227499849 -> 25, 1541542169 -> 1434
    //   68: putstatic bigname/zprestige/webhack/manager/Identity/UtilTwo$Base64.EQUALS_SIGN : B
    //   71: ldc_w '欸㌠欪ㅍ첐薒๐ᚉ'
    //   74: getstatic Perryc.c : I
    //   77: iflt -> 91
    //   80: ldc2_w 1789304487
    //   83: l2i
    //   84: ldc_w -894827000
    //   87: ixor
    //   88: goto -> 99
    //   91: ldc2_w 256175234
    //   94: l2i
    //   95: ldc_w 911043087
    //   98: ixor
    //   99: ldc2_w -393537884
    //   102: l2i
    //   103: ldc_w -616971730
    //   106: ixor
    //   107: ixor
    //   108: lookupswitch default -> 1430, -1816245211 -> 91, 180048391 -> 136
    //   136: invokestatic 0 : (Ljava/lang/String;)Ljava/lang/String;
    //   139: getstatic Perryc.1 : I
    //   142: ifeq -> 156
    //   145: ldc2_w -874409383
    //   148: l2i
    //   149: ldc_w -541043308
    //   152: ixor
    //   153: goto -> 164
    //   156: ldc2_w 214596270
    //   159: l2i
    //   160: ldc_w 1315699337
    //   163: ixor
    //   164: ldc2_w 206189516
    //   167: l2i
    //   168: ldc_w -1961683271
    //   171: ixor
    //   172: ixor
    //   173: lookupswitch default -> 200, -1820794184 -> 1432, -1297809111 -> 156
    //   200: putstatic bigname/zprestige/webhack/manager/Identity/UtilTwo$Base64.PREFERRED_ENCODING : Ljava/lang/String;
    //   203: ldc2_w -1838164647
    //   206: l2i
    //   207: ldc_w -1838164711
    //   210: ixor
    //   211: newarray byte
    //   213: dup
    //   214: ldc2_w 2104775853
    //   217: l2i
    //   218: ldc_w 2104775853
    //   221: ixor
    //   222: ldc2_w 1259424937
    //   225: l2i
    //   226: ldc_w 1259425000
    //   229: ixor
    //   230: bastore
    //   231: dup
    //   232: ldc2_w -725241410
    //   235: l2i
    //   236: ldc_w -725241409
    //   239: ixor
    //   240: ldc2_w 1146951660
    //   243: l2i
    //   244: ldc_w 1146951598
    //   247: ixor
    //   248: bastore
    //   249: dup
    //   250: ldc2_w -418209460
    //   253: l2i
    //   254: ldc_w -418209458
    //   257: ixor
    //   258: ldc2_w -1586772183
    //   261: l2i
    //   262: ldc_w -1586772118
    //   265: ixor
    //   266: bastore
    //   267: dup
    //   268: ldc2_w -1059625433
    //   271: l2i
    //   272: ldc_w -1059625436
    //   275: ixor
    //   276: ldc2_w -1707955711
    //   279: l2i
    //   280: ldc_w -1707955643
    //   283: ixor
    //   284: bastore
    //   285: dup
    //   286: ldc2_w -1815675276
    //   289: l2i
    //   290: ldc_w -1815675280
    //   293: ixor
    //   294: ldc2_w -761969233
    //   297: l2i
    //   298: ldc_w -761969174
    //   301: ixor
    //   302: bastore
    //   303: dup
    //   304: ldc2_w 1955311299
    //   307: l2i
    //   308: ldc_w 1955311302
    //   311: ixor
    //   312: ldc2_w -451094244
    //   315: l2i
    //   316: ldc_w -451094182
    //   319: ixor
    //   320: bastore
    //   321: dup
    //   322: ldc2_w -735319628
    //   325: l2i
    //   326: ldc_w -735319630
    //   329: ixor
    //   330: ldc2_w -323350371
    //   333: l2i
    //   334: ldc_w -323350310
    //   337: ixor
    //   338: bastore
    //   339: dup
    //   340: ldc2_w 798766314
    //   343: l2i
    //   344: ldc_w 798766317
    //   347: ixor
    //   348: ldc2_w 1431969519
    //   351: l2i
    //   352: ldc_w 1431969447
    //   355: ixor
    //   356: bastore
    //   357: dup
    //   358: ldc2_w -2111309421
    //   361: l2i
    //   362: ldc_w -2111309413
    //   365: ixor
    //   366: ldc2_w 546484769
    //   369: l2i
    //   370: ldc_w 546484840
    //   373: ixor
    //   374: bastore
    //   375: dup
    //   376: ldc2_w -747102883
    //   379: l2i
    //   380: ldc_w -747102892
    //   383: ixor
    //   384: ldc2_w -753761905
    //   387: l2i
    //   388: ldc_w -753761851
    //   391: ixor
    //   392: bastore
    //   393: dup
    //   394: ldc2_w 269776892
    //   397: l2i
    //   398: ldc_w 269776886
    //   401: ixor
    //   402: ldc2_w 1420683969
    //   405: l2i
    //   406: ldc_w 1420683914
    //   409: ixor
    //   410: bastore
    //   411: dup
    //   412: ldc2_w 607022685
    //   415: l2i
    //   416: ldc_w 607022678
    //   419: ixor
    //   420: ldc2_w 1027693433
    //   423: l2i
    //   424: ldc_w 1027693365
    //   427: ixor
    //   428: bastore
    //   429: dup
    //   430: ldc2_w -940032175
    //   433: l2i
    //   434: ldc_w -940032163
    //   437: ixor
    //   438: ldc2_w -1578613523
    //   441: l2i
    //   442: ldc_w -1578613600
    //   445: ixor
    //   446: bastore
    //   447: dup
    //   448: ldc2_w 141206666
    //   451: l2i
    //   452: ldc_w 141206663
    //   455: ixor
    //   456: ldc2_w -511853740
    //   459: l2i
    //   460: ldc_w -511853798
    //   463: ixor
    //   464: bastore
    //   465: dup
    //   466: ldc2_w 103765770
    //   469: l2i
    //   470: ldc_w 103765764
    //   473: ixor
    //   474: ldc2_w 363210664
    //   477: l2i
    //   478: ldc_w 363210727
    //   481: ixor
    //   482: bastore
    //   483: dup
    //   484: ldc2_w 2065248004
    //   487: l2i
    //   488: ldc_w 2065248011
    //   491: ixor
    //   492: ldc2_w -1192049390
    //   495: l2i
    //   496: ldc_w -1192049342
    //   499: ixor
    //   500: bastore
    //   501: dup
    //   502: ldc2_w -1009490110
    //   505: l2i
    //   506: ldc_w -1009490094
    //   509: ixor
    //   510: ldc2_w 622598045
    //   513: l2i
    //   514: ldc_w 622598092
    //   517: ixor
    //   518: bastore
    //   519: dup
    //   520: ldc2_w 605141441
    //   523: l2i
    //   524: ldc_w 605141456
    //   527: ixor
    //   528: ldc2_w 1150808118
    //   531: l2i
    //   532: ldc_w 1150808164
    //   535: ixor
    //   536: bastore
    //   537: dup
    //   538: ldc2_w -1523377519
    //   541: l2i
    //   542: ldc_w -1523377533
    //   545: ixor
    //   546: ldc2_w 2031531502
    //   549: l2i
    //   550: ldc_w 2031531453
    //   553: ixor
    //   554: bastore
    //   555: dup
    //   556: ldc2_w 2053869842
    //   559: l2i
    //   560: ldc_w 2053869825
    //   563: ixor
    //   564: ldc2_w 2016755948
    //   567: l2i
    //   568: ldc_w 2016755896
    //   571: ixor
    //   572: bastore
    //   573: dup
    //   574: ldc2_w -322702720
    //   577: l2i
    //   578: ldc_w -322702700
    //   581: ixor
    //   582: ldc2_w -174296862
    //   585: l2i
    //   586: ldc_w -174296905
    //   589: ixor
    //   590: bastore
    //   591: dup
    //   592: ldc2_w -1970904301
    //   595: l2i
    //   596: ldc_w -1970904314
    //   599: ixor
    //   600: ldc2_w 56941883
    //   603: l2i
    //   604: ldc_w 56941933
    //   607: ixor
    //   608: bastore
    //   609: dup
    //   610: ldc2_w 1008887476
    //   613: l2i
    //   614: ldc_w 1008887458
    //   617: ixor
    //   618: ldc2_w 7853074
    //   621: l2i
    //   622: ldc_w 7853125
    //   625: ixor
    //   626: bastore
    //   627: dup
    //   628: ldc2_w 1685410954
    //   631: l2i
    //   632: ldc_w 1685410973
    //   635: ixor
    //   636: ldc2_w 1763429875
    //   639: l2i
    //   640: ldc_w 1763429803
    //   643: ixor
    //   644: bastore
    //   645: dup
    //   646: ldc2_w 1333431909
    //   649: l2i
    //   650: ldc_w 1333431933
    //   653: ixor
    //   654: ldc2_w -1220970697
    //   657: l2i
    //   658: ldc_w -1220970642
    //   661: ixor
    //   662: bastore
    //   663: dup
    //   664: ldc2_w 1228400563
    //   667: l2i
    //   668: ldc_w 1228400554
    //   671: ixor
    //   672: ldc2_w 1187091662
    //   675: l2i
    //   676: ldc_w 1187091604
    //   679: ixor
    //   680: bastore
    //   681: dup
    //   682: ldc2_w 82853786
    //   685: l2i
    //   686: ldc_w 82853760
    //   689: ixor
    //   690: ldc2_w 2002917888
    //   693: l2i
    //   694: ldc_w 2002917985
    //   697: ixor
    //   698: bastore
    //   699: dup
    //   700: ldc2_w 776499546
    //   703: l2i
    //   704: ldc_w 776499521
    //   707: ixor
    //   708: ldc2_w -649186525
    //   711: l2i
    //   712: ldc_w -649186495
    //   715: ixor
    //   716: bastore
    //   717: dup
    //   718: ldc2_w 1727369644
    //   721: l2i
    //   722: ldc_w 1727369648
    //   725: ixor
    //   726: ldc2_w 900193961
    //   729: l2i
    //   730: ldc_w 900193994
    //   733: ixor
    //   734: bastore
    //   735: dup
    //   736: ldc2_w -557021304
    //   739: l2i
    //   740: ldc_w -557021291
    //   743: ixor
    //   744: ldc2_w 532198915
    //   747: l2i
    //   748: ldc_w 532199015
    //   751: ixor
    //   752: bastore
    //   753: dup
    //   754: ldc2_w -412005230
    //   757: l2i
    //   758: ldc_w -412005236
    //   761: ixor
    //   762: ldc2_w -988628563
    //   765: l2i
    //   766: ldc_w -988628536
    //   769: ixor
    //   770: bastore
    //   771: dup
    //   772: ldc2_w -821438402
    //   775: l2i
    //   776: ldc_w -821438431
    //   779: ixor
    //   780: ldc2_w 602262589
    //   783: l2i
    //   784: ldc_w 602262619
    //   787: ixor
    //   788: bastore
    //   789: dup
    //   790: ldc2_w 464599668
    //   793: l2i
    //   794: ldc_w 464599636
    //   797: ixor
    //   798: ldc2_w 963716763
    //   801: l2i
    //   802: ldc_w 963716860
    //   805: ixor
    //   806: bastore
    //   807: dup
    //   808: ldc2_w -1756775418
    //   811: l2i
    //   812: ldc_w -1756775385
    //   815: ixor
    //   816: ldc2_w 841945274
    //   819: l2i
    //   820: ldc_w 841945298
    //   823: ixor
    //   824: bastore
    //   825: dup
    //   826: ldc2_w -1938286620
    //   829: l2i
    //   830: ldc_w -1938286650
    //   833: ixor
    //   834: ldc2_w 658890304
    //   837: l2i
    //   838: ldc_w 658890281
    //   841: ixor
    //   842: bastore
    //   843: dup
    //   844: ldc2_w -1054841470
    //   847: l2i
    //   848: ldc_w -1054841439
    //   851: ixor
    //   852: ldc2_w 777371157
    //   855: l2i
    //   856: ldc_w 777371263
    //   859: ixor
    //   860: bastore
    //   861: dup
    //   862: ldc2_w 297830529
    //   865: l2i
    //   866: ldc_w 297830565
    //   869: ixor
    //   870: ldc2_w 1229275963
    //   873: l2i
    //   874: ldc_w 1229275984
    //   877: ixor
    //   878: bastore
    //   879: dup
    //   880: ldc2_w 1496650493
    //   883: l2i
    //   884: ldc_w 1496650456
    //   887: ixor
    //   888: ldc2_w -1987871282
    //   891: l2i
    //   892: ldc_w -1987871326
    //   895: ixor
    //   896: bastore
    //   897: dup
    //   898: ldc2_w 869254478
    //   901: l2i
    //   902: ldc_w 869254504
    //   905: ixor
    //   906: ldc2_w -1618716223
    //   909: l2i
    //   910: ldc_w -1618716244
    //   913: ixor
    //   914: bastore
    //   915: dup
    //   916: ldc2_w 834302919
    //   919: l2i
    //   920: ldc_w 834302944
    //   923: ixor
    //   924: ldc2_w -1145368492
    //   927: l2i
    //   928: ldc_w -1145368518
    //   931: ixor
    //   932: bastore
    //   933: dup
    //   934: ldc2_w 430272269
    //   937: l2i
    //   938: ldc_w 430272293
    //   941: ixor
    //   942: ldc2_w -984834399
    //   945: l2i
    //   946: ldc_w -984834354
    //   949: ixor
    //   950: bastore
    //   951: dup
    //   952: ldc2_w -1961673587
    //   955: l2i
    //   956: ldc_w -1961673564
    //   959: ixor
    //   960: ldc2_w 350260755
    //   963: l2i
    //   964: ldc_w 350260835
    //   967: ixor
    //   968: bastore
    //   969: dup
    //   970: ldc2_w 1007299178
    //   973: l2i
    //   974: ldc_w 1007299136
    //   977: ixor
    //   978: ldc2_w 635321826
    //   981: l2i
    //   982: ldc_w 635321747
    //   985: ixor
    //   986: bastore
    //   987: dup
    //   988: ldc2_w -1189256888
    //   991: l2i
    //   992: ldc_w -1189256861
    //   995: ixor
    //   996: ldc2_w -1949527716
    //   999: l2i
    //   1000: ldc_w -1949527762
    //   1003: ixor
    //   1004: bastore
    //   1005: dup
    //   1006: ldc2_w -1512430519
    //   1009: l2i
    //   1010: ldc_w -1512430491
    //   1013: ixor
    //   1014: ldc2_w -1602847266
    //   1017: l2i
    //   1018: ldc_w -1602847315
    //   1021: ixor
    //   1022: bastore
    //   1023: dup
    //   1024: ldc2_w -1083282218
    //   1027: l2i
    //   1028: ldc_w -1083282181
    //   1031: ixor
    //   1032: ldc2_w 1944543598
    //   1035: l2i
    //   1036: ldc_w 1944543514
    //   1039: ixor
    //   1040: bastore
    //   1041: dup
    //   1042: ldc2_w 451687564
    //   1045: l2i
    //   1046: ldc_w 451687586
    //   1049: ixor
    //   1050: ldc2_w 295131928
    //   1053: l2i
    //   1054: ldc_w 295132013
    //   1057: ixor
    //   1058: bastore
    //   1059: dup
    //   1060: ldc2_w 1990216421
    //   1063: l2i
    //   1064: ldc_w 1990216394
    //   1067: ixor
    //   1068: ldc2_w -1444397299
    //   1071: l2i
    //   1072: ldc_w -1444397189
    //   1075: ixor
    //   1076: bastore
    //   1077: dup
    //   1078: ldc2_w -514597072
    //   1081: l2i
    //   1082: ldc_w -514597120
    //   1085: ixor
    //   1086: ldc2_w 1519075007
    //   1089: l2i
    //   1090: ldc_w 1519075016
    //   1093: ixor
    //   1094: bastore
    //   1095: dup
    //   1096: ldc2_w -94447943
    //   1099: l2i
    //   1100: ldc_w -94447992
    //   1103: ixor
    //   1104: ldc2_w -626938919
    //   1107: l2i
    //   1108: ldc_w -626938975
    //   1111: ixor
    //   1112: bastore
    //   1113: dup
    //   1114: ldc2_w -227356920
    //   1117: l2i
    //   1118: ldc_w -227356870
    //   1121: ixor
    //   1122: ldc2_w -724009041
    //   1125: l2i
    //   1126: ldc_w -724009002
    //   1129: ixor
    //   1130: bastore
    //   1131: dup
    //   1132: ldc2_w -441523678
    //   1135: l2i
    //   1136: ldc_w -441523695
    //   1139: ixor
    //   1140: ldc2_w -1482966028
    //   1143: l2i
    //   1144: ldc_w -1482966130
    //   1147: ixor
    //   1148: bastore
    //   1149: dup
    //   1150: ldc2_w 1976534846
    //   1153: l2i
    //   1154: ldc_w 1976534794
    //   1157: ixor
    //   1158: ldc2_w 1584835406
    //   1161: l2i
    //   1162: ldc_w 1584835454
    //   1165: ixor
    //   1166: bastore
    //   1167: dup
    //   1168: ldc2_w -186660123
    //   1171: l2i
    //   1172: ldc_w -186660144
    //   1175: ixor
    //   1176: ldc2_w -561136478
    //   1179: l2i
    //   1180: ldc_w -561136493
    //   1183: ixor
    //   1184: bastore
    //   1185: dup
    //   1186: ldc2_w 134898032
    //   1189: l2i
    //   1190: ldc_w 134897990
    //   1193: ixor
    //   1194: ldc2_w -2072263566
    //   1197: l2i
    //   1198: ldc_w -2072263616
    //   1201: ixor
    //   1202: bastore
    //   1203: dup
    //   1204: ldc2_w -1367169683
    //   1207: l2i
    //   1208: ldc_w -1367169702
    //   1211: ixor
    //   1212: ldc2_w -862144364
    //   1215: l2i
    //   1216: ldc_w -862144345
    //   1219: ixor
    //   1220: bastore
    //   1221: dup
    //   1222: ldc2_w -2094245968
    //   1225: l2i
    //   1226: ldc_w -2094246008
    //   1229: ixor
    //   1230: ldc2_w -619478351
    //   1233: l2i
    //   1234: ldc_w -619478395
    //   1237: ixor
    //   1238: bastore
    //   1239: dup
    //   1240: ldc2_w -1424449797
    //   1243: l2i
    //   1244: ldc_w -1424449854
    //   1247: ixor
    //   1248: ldc2_w 729849716
    //   1251: l2i
    //   1252: ldc_w 729849665
    //   1255: ixor
    //   1256: bastore
    //   1257: dup
    //   1258: ldc2_w 2078996084
    //   1261: l2i
    //   1262: ldc_w 2078996046
    //   1265: ixor
    //   1266: ldc2_w -687458049
    //   1269: l2i
    //   1270: ldc_w -687458103
    //   1273: ixor
    //   1274: bastore
    //   1275: dup
    //   1276: ldc2_w 654170948
    //   1279: l2i
    //   1280: ldc_w 654171007
    //   1283: ixor
    //   1284: ldc2_w 1829972789
    //   1287: l2i
    //   1288: ldc_w 1829972738
    //   1291: ixor
    //   1292: bastore
    //   1293: dup
    //   1294: ldc2_w -467781562
    //   1297: l2i
    //   1298: ldc_w -467781510
    //   1301: ixor
    //   1302: ldc2_w -881274733
    //   1305: l2i
    //   1306: ldc_w -881274709
    //   1309: ixor
    //   1310: bastore
    //   1311: dup
    //   1312: ldc2_w 1275877713
    //   1315: l2i
    //   1316: ldc_w 1275877740
    //   1319: ixor
    //   1320: ldc2_w 855351754
    //   1323: l2i
    //   1324: ldc_w 855351795
    //   1327: ixor
    //   1328: bastore
    //   1329: dup
    //   1330: ldc2_w 291145639
    //   1333: l2i
    //   1334: ldc_w 291145625
    //   1337: ixor
    //   1338: ldc2_w -958773481
    //   1341: l2i
    //   1342: ldc_w -958773444
    //   1345: ixor
    //   1346: bastore
    //   1347: dup
    //   1348: ldc2_w -776411649
    //   1351: l2i
    //   1352: ldc_w -776411712
    //   1355: ixor
    //   1356: ldc2_w -1071585008
    //   1359: l2i
    //   1360: ldc_w -1071584961
    //   1363: ixor
    //   1364: bastore
    //   1365: getstatic Perryc.0 : I
    //   1368: ifle -> 1382
    //   1371: ldc2_w 1632663391
    //   1374: l2i
    //   1375: ldc_w 1929403775
    //   1378: ixor
    //   1379: goto -> 1390
    //   1382: ldc2_w 1100522441
    //   1385: l2i
    //   1386: ldc_w 1104958857
    //   1389: ixor
    //   1390: ldc2_w -1556120229
    //   1393: l2i
    //   1394: ldc_w 1058056051
    //   1397: ixor
    //   1398: ixor
    //   1399: lookupswitch default -> 1428, -1904218104 -> 1382, -1670697880 -> 1424
    //   1424: putstatic bigname/zprestige/webhack/manager/Identity/UtilTwo$Base64._STANDARD_ALPHABET : [B
    //   1427: return
    //   1428: aconst_null
    //   1429: athrow
    //   1430: aconst_null
    //   1431: athrow
    //   1432: aconst_null
    //   1433: athrow
    //   1434: aconst_null
    //   1435: athrow
  }
  
  public static String encode(String paramString) {
    return Perry1.6a(null, (int)1660074926L ^ 0xC95F10F, paramString);
  }
}


/* Location:              C:\Users\alex\Desktop\webhack\WebHack-0.8-obf_sussy_1.jar!\bigname\zprestige\webhack\manager\Identity\UtilTwo$Base64.class
 * Java compiler version: 8 (52.0)
 * JD-Core Version:       1.1.3
 */