package bigname.zprestige.webhack.manager.Identity;

import Perry1;
import Perryc;
import java.io.IOException;

public class UtilTwo$HttpRequestException extends RuntimeException {
  public static long serialVersionUID = -538173343L ^ 0x103E5586BB50DDA8L;
  
  public Throwable getCause() {
    return Perry1.0g(this, (int)-1794834835L ^ 0xE938EE99);
  }
  
  public IOException getCause() {
    if (Perryc.c < 0) {
      null;
    } else {
      if (null != null)
        throw (Throwable)null; 
      null;
    } 
    if (null != null)
      throw (Throwable)null; 
    null;
  }
  
  public UtilTwo$HttpRequestException(IOException cause) {
    // Byte code:
    //   0: getstatic Perryc.1 : I
    //   3: ifeq -> 16
    //   6: ldc2_w 177937237
    //   9: l2i
    //   10: ldc -930924406
    //   12: ixor
    //   13: goto -> 23
    //   16: ldc2_w 2102934966
    //   19: l2i
    //   20: ldc -289290090
    //   22: ixor
    //   23: ldc2_w -1132245652
    //   26: l2i
    //   27: ldc 929853468
    //   29: ixor
    //   30: ixor
    //   31: lookupswitch default -> 56, 1139040959 -> 16, 1240932015 -> 182
    //   56: aload_0
    //   57: getstatic Perryc.c : I
    //   60: iflt -> 73
    //   63: ldc2_w 269177315
    //   66: l2i
    //   67: ldc -927605001
    //   69: ixor
    //   70: goto -> 80
    //   73: ldc2_w -515861391
    //   76: l2i
    //   77: ldc -942138631
    //   79: ixor
    //   80: ldc2_w -1848926213
    //   83: l2i
    //   84: ldc -515384846
    //   86: ixor
    //   87: ixor
    //   88: lookupswitch default -> 180, -1473066723 -> 73, 1444202625 -> 116
    //   116: aload_1
    //   117: getstatic Perryc.0 : I
    //   120: ifle -> 133
    //   123: ldc2_w -1481765950
    //   126: l2i
    //   127: ldc -2088489858
    //   129: ixor
    //   130: goto -> 140
    //   133: ldc2_w 976981443
    //   136: l2i
    //   137: ldc -964526653
    //   139: ixor
    //   140: ldc2_w -647441102
    //   143: l2i
    //   144: ldc 1622587579
    //   146: ixor
    //   147: ixor
    //   148: lookupswitch default -> 184, -1644934603 -> 133, 1164418441 -> 176
    //   176: invokespecial <init> : (Ljava/lang/Throwable;)V
    //   179: return
    //   180: aconst_null
    //   181: athrow
    //   182: aconst_null
    //   183: athrow
    //   184: aconst_null
    //   185: athrow
    // Local variable table:
    //   start	length	slot	name	descriptor
    //   0	180	0	this	Lbigname/zprestige/webhack/manager/Identity/UtilTwo$HttpRequestException;
    //   0	180	1	cause	Ljava/io/IOException;
  }
}


/* Location:              C:\Users\alex\Desktop\webhack\WebHack-0.8-obf_sussy_1.jar!\bigname\zprestige\webhack\manager\Identity\UtilTwo$HttpRequestException.class
 * Java compiler version: 8 (52.0)
 * JD-Core Version:       1.1.3
 */