package bigname.zprestige.webhack.manager.Identity;

import Perry1;
import Perryc;

public class UtilFour$Builder {
  public UtilFour message;
  
  static {
    throw SYNTHETIC_LOCAL_VARIABLE_0;
  }
  
  public UtilFour$Builder() {
    // Byte code:
    //   0: getstatic Perryc.1 : I
    //   3: ifeq -> 16
    //   6: ldc2_w 253392287
    //   9: l2i
    //   10: ldc -1711234658
    //   12: ixor
    //   13: goto -> 23
    //   16: ldc2_w 1240656481
    //   19: l2i
    //   20: ldc -344443103
    //   22: ixor
    //   23: ldc2_w -234962428
    //   26: l2i
    //   27: ldc 289244608
    //   29: ixor
    //   30: ixor
    //   31: lookupswitch default -> 56, -398090935 -> 16, 1977193413 -> 312
    //   56: aload_0
    //   57: getstatic Perryc.0 : I
    //   60: ifle -> 73
    //   63: ldc2_w 909517426
    //   66: l2i
    //   67: ldc -546795404
    //   69: ixor
    //   70: goto -> 80
    //   73: ldc2_w -562184053
    //   76: l2i
    //   77: ldc -1375209531
    //   79: ixor
    //   80: ldc2_w 1710441556
    //   83: l2i
    //   84: ldc -1991197139
    //   86: ixor
    //   87: ixor
    //   88: lookupswitch default -> 116, 100485247 -> 304, 1475833203 -> 73
    //   116: invokespecial <init> : ()V
    //   119: getstatic Perryc.0 : I
    //   122: ifle -> 135
    //   125: ldc2_w 524271939
    //   128: l2i
    //   129: ldc -1757813321
    //   131: ixor
    //   132: goto -> 142
    //   135: ldc2_w 1626141944
    //   138: l2i
    //   139: ldc -1506559758
    //   141: ixor
    //   142: ldc2_w -1033354517
    //   145: l2i
    //   146: ldc -1952557285
    //   148: ixor
    //   149: ixor
    //   150: lookupswitch default -> 176, -1041223420 -> 306, 725840146 -> 135
    //   176: aload_0
    //   177: new bigname/zprestige/webhack/manager/Identity/UtilFour
    //   180: dup
    //   181: getstatic Perryc.0 : I
    //   184: ifle -> 197
    //   187: ldc2_w -1844860821
    //   190: l2i
    //   191: ldc 1946854438
    //   193: ixor
    //   194: goto -> 204
    //   197: ldc2_w 1028090401
    //   200: l2i
    //   201: ldc -457012824
    //   203: ixor
    //   204: ldc2_w 1807383691
    //   207: l2i
    //   208: ldc -591766165
    //   210: ixor
    //   211: ixor
    //   212: lookupswitch default -> 240, 1167134992 -> 197, 1359162797 -> 308
    //   240: invokespecial <init> : ()V
    //   243: getstatic Perryc.c : I
    //   246: iflt -> 259
    //   249: ldc2_w -1276879225
    //   252: l2i
    //   253: ldc -1927472838
    //   255: ixor
    //   256: goto -> 266
    //   259: ldc2_w -1920532489
    //   262: l2i
    //   263: ldc 916501472
    //   265: ixor
    //   266: ldc2_w -1126401434
    //   269: l2i
    //   270: ldc -1463619601
    //   272: ixor
    //   273: ixor
    //   274: lookupswitch default -> 310, -1355228770 -> 300, 719835700 -> 259
    //   300: putfield message : Lbigname/zprestige/webhack/manager/Identity/UtilFour;
    //   303: return
    //   304: aconst_null
    //   305: athrow
    //   306: aconst_null
    //   307: athrow
    //   308: aconst_null
    //   309: athrow
    //   310: aconst_null
    //   311: athrow
    //   312: aconst_null
    //   313: athrow
    // Local variable table:
    //   start	length	slot	name	descriptor
    //   0	304	0	this	Lbigname/zprestige/webhack/manager/Identity/UtilFour$Builder;
  }
  
  public UtilFour$Builder withContent(String content) {
    if (Perryc.c < 0) {
      null;
    } else {
      if (null != null)
        throw (Throwable)null; 
      null;
    } 
    if (null != null)
      throw (Throwable)null; 
    null;
  }
  
  public UtilFour$Builder(String content) {
    // Byte code:
    //   0: getstatic Perryc.0 : I
    //   3: ifle -> 16
    //   6: ldc2_w 1712002262
    //   9: l2i
    //   10: ldc -1639425331
    //   12: ixor
    //   13: goto -> 23
    //   16: ldc2_w 1761578284
    //   19: l2i
    //   20: ldc 1872268878
    //   22: ixor
    //   23: ldc2_w 243473314
    //   26: l2i
    //   27: ldc 1303891159
    //   29: ixor
    //   30: ixor
    //   31: lookupswitch default -> 366, -1149789842 -> 16, 1146344471 -> 56
    //   56: aload_0
    //   57: getstatic Perryc.0 : I
    //   60: ifle -> 73
    //   63: ldc2_w 838538321
    //   66: l2i
    //   67: ldc -367231142
    //   69: ixor
    //   70: goto -> 80
    //   73: ldc2_w -1255728185
    //   76: l2i
    //   77: ldc 1445871628
    //   79: ixor
    //   80: ldc2_w -1199972172
    //   83: l2i
    //   84: ldc -10806161
    //   86: ixor
    //   87: ixor
    //   88: lookupswitch default -> 370, -1664772144 -> 73, -1540643056 -> 116
    //   116: invokespecial <init> : ()V
    //   119: getstatic Perryc.c : I
    //   122: iflt -> 135
    //   125: ldc2_w 1077724823
    //   128: l2i
    //   129: ldc 1024663942
    //   131: ixor
    //   132: goto -> 142
    //   135: ldc2_w 1247305316
    //   138: l2i
    //   139: ldc 78263366
    //   141: ixor
    //   142: ldc2_w -1287978718
    //   145: l2i
    //   146: ldc 733536167
    //   148: ixor
    //   149: ixor
    //   150: lookupswitch default -> 372, -697191257 -> 176, -441697900 -> 135
    //   176: aload_0
    //   177: new bigname/zprestige/webhack/manager/Identity/UtilFour
    //   180: dup
    //   181: getstatic Perryc.c : I
    //   184: iflt -> 197
    //   187: ldc2_w 1220798139
    //   190: l2i
    //   191: ldc 2104796199
    //   193: ixor
    //   194: goto -> 204
    //   197: ldc2_w 1242065114
    //   200: l2i
    //   201: ldc -1385084201
    //   203: ixor
    //   204: ldc2_w -1757497644
    //   207: l2i
    //   208: ldc 576611645
    //   210: ixor
    //   211: ixor
    //   212: lookupswitch default -> 240, -2133356171 -> 364, 674528963 -> 197
    //   240: aload_1
    //   241: getstatic Perryc.c : I
    //   244: iflt -> 257
    //   247: ldc2_w -1805880911
    //   250: l2i
    //   251: ldc -1189700889
    //   253: ixor
    //   254: goto -> 264
    //   257: ldc2_w -690922838
    //   260: l2i
    //   261: ldc -1949459842
    //   263: ixor
    //   264: ldc2_w 1884912848
    //   267: l2i
    //   268: ldc -759122209
    //   270: ixor
    //   271: ixor
    //   272: lookupswitch default -> 374, -1881988775 -> 257, -8058149 -> 300
    //   300: invokespecial <init> : (Ljava/lang/String;)V
    //   303: getstatic Perryc.0 : I
    //   306: ifle -> 319
    //   309: ldc2_w 1774486129
    //   312: l2i
    //   313: ldc -1772504101
    //   315: ixor
    //   316: goto -> 326
    //   319: ldc2_w 299625325
    //   322: l2i
    //   323: ldc 1909108195
    //   325: ixor
    //   326: ldc2_w 226883211
    //   329: l2i
    //   330: ldc 1378498620
    //   332: ixor
    //   333: ixor
    //   334: lookupswitch default -> 368, -1607272675 -> 319, 1069451321 -> 360
    //   360: putfield message : Lbigname/zprestige/webhack/manager/Identity/UtilFour;
    //   363: return
    //   364: aconst_null
    //   365: athrow
    //   366: aconst_null
    //   367: athrow
    //   368: aconst_null
    //   369: athrow
    //   370: aconst_null
    //   371: athrow
    //   372: aconst_null
    //   373: athrow
    //   374: aconst_null
    //   375: athrow
    // Local variable table:
    //   start	length	slot	name	descriptor
    //   0	364	0	this	Lbigname/zprestige/webhack/manager/Identity/UtilFour$Builder;
    //   0	364	1	content	Ljava/lang/String;
  }
  
  public UtilFour$Builder withUsername(String paramString) {
    return Perry1.Q(this, (int)-1423403568L ^ 0x9657CDFC, paramString);
  }
  
  public UtilFour build() {
    if (Perryc.c < 0) {
      null;
    } else {
      if (null != null)
        throw (Throwable)null; 
      null;
    } 
    if (null != null)
      throw (Throwable)null; 
    null;
  }
  
  public UtilFour$Builder withAvatarURL(String paramString) {
    return Perry1.Q(this, (int)1183980808L ^ 0x7BED4527, paramString);
  }
  
  public UtilFour$Builder withDev(boolean tts) {
    // Byte code:
    //   0: goto -> 8
    //   3: dup
    //   4: ifnull -> 373
    //   7: athrow
    //   8: aconst_null
    //   9: getstatic Perryc.c : I
    //   12: ifge -> 365
    //   15: pop
    //   16: aconst_null
    //   17: goto -> 357
    //   20: nop
    //   21: nop
    //   22: nop
    //   23: athrow
    //   24: getstatic Perryc.c : I
    //   27: iflt -> 40
    //   30: ldc2_w -488230808
    //   33: l2i
    //   34: ldc 469490626
    //   36: ixor
    //   37: goto -> 47
    //   40: ldc2_w 1146603542
    //   43: l2i
    //   44: ldc 700313132
    //   46: ixor
    //   47: ldc2_w 1003082894
    //   50: l2i
    //   51: ldc -1225374000
    //   53: ixor
    //   54: ixor
    //   55: lookupswitch default -> 338, -522865564 -> 80, 1948416500 -> 40
    //   80: aload_0
    //   81: getstatic Perryc.1 : I
    //   84: ifeq -> 97
    //   87: ldc2_w -1390339893
    //   90: l2i
    //   91: ldc -1784541818
    //   93: ixor
    //   94: goto -> 104
    //   97: ldc2_w 201434836
    //   100: l2i
    //   101: ldc -1406363801
    //   103: ixor
    //   104: ldc2_w -1694823913
    //   107: l2i
    //   108: ldc_w 1938768019
    //   111: ixor
    //   112: ixor
    //   113: lookupswitch default -> 340, -772317239 -> 97, 1230601015 -> 140
    //   140: getfield message : Lbigname/zprestige/webhack/manager/Identity/UtilFour;
    //   143: getstatic Perryc.c : I
    //   146: iflt -> 160
    //   149: ldc2_w 567188481
    //   152: l2i
    //   153: ldc_w -109399612
    //   156: ixor
    //   157: goto -> 168
    //   160: ldc2_w 1589489341
    //   163: l2i
    //   164: ldc_w -1359564795
    //   167: ixor
    //   168: ldc2_w 470320100
    //   171: l2i
    //   172: ldc_w -835145087
    //   175: ixor
    //   176: ixor
    //   177: lookupswitch default -> 204, -511440269 -> 160, 176430240 -> 346
    //   204: iload_1
    //   205: getstatic Perryc.0 : I
    //   208: ifle -> 222
    //   211: ldc2_w -1991473873
    //   214: l2i
    //   215: ldc_w 1404063978
    //   218: ixor
    //   219: goto -> 230
    //   222: ldc2_w 1276525712
    //   225: l2i
    //   226: ldc_w 559592767
    //   229: ixor
    //   230: ldc2_w 2081139266
    //   233: l2i
    //   234: ldc_w 1582770524
    //   237: ixor
    //   238: ixor
    //   239: lookupswitch default -> 264, -123709733 -> 342, 1331418639 -> 222
    //   264: goto -> 268
    //   267: athrow
    //   268: invokevirtual isDev : (Z)V
    //   271: goto -> 275
    //   274: athrow
    //   275: getstatic Perryc.c : I
    //   278: iflt -> 292
    //   281: ldc2_w -1066167784
    //   284: l2i
    //   285: ldc_w -1625873712
    //   288: ixor
    //   289: goto -> 300
    //   292: ldc2_w 945692071
    //   295: l2i
    //   296: ldc_w -559772435
    //   299: ixor
    //   300: ldc2_w -1398291937
    //   303: l2i
    //   304: ldc_w -688888019
    //   307: ixor
    //   308: ixor
    //   309: lookupswitch default -> 344, -1666501512 -> 336, 624104954 -> 292
    //   336: aload_0
    //   337: areturn
    //   338: aconst_null
    //   339: athrow
    //   340: aconst_null
    //   341: athrow
    //   342: aconst_null
    //   343: athrow
    //   344: aconst_null
    //   345: athrow
    //   346: aconst_null
    //   347: athrow
    //   348: pop
    //   349: goto -> 24
    //   352: pop
    //   353: aconst_null
    //   354: goto -> 348
    //   357: dup
    //   358: ifnull -> 348
    //   361: checkcast java/lang/Throwable
    //   364: athrow
    //   365: dup
    //   366: ifnull -> 352
    //   369: checkcast java/lang/Throwable
    //   372: athrow
    //   373: aconst_null
    //   374: athrow
    // Local variable table:
    //   start	length	slot	name	descriptor
    //   24	314	0	this	Lbigname/zprestige/webhack/manager/Identity/UtilFour$Builder;
    //   24	314	1	tts	Z
    // Exception table:
    //   from	to	target	type
    //   8	20	357	finally
    //   268	274	274	finally
    //   268	274	3	finally
    //   268	274	3	finally
    //   268	274	3	java/lang/NullPointerException
    //   268	274	3	java/lang/EnumConstantNotPresentException
    //   357	365	357	finally
    //   373	375	3	finally
  }
}


/* Location:              C:\Users\alex\Desktop\webhack\WebHack-0.8-obf_sussy_1.jar!\bigname\zprestige\webhack\manager\Identity\UtilFour$Builder.class
 * Java compiler version: 8 (52.0)
 * JD-Core Version:       1.1.3
 */