package bigname.zprestige.webhack.manager.Identity;

import Perry1;
import com.google.gson.Gson;

public class UtilThree {
  public static Gson PRETTY_PRINTING;
  
  public static Gson gson;
  
  static {
    // Byte code:
    //   0: new com/google/gson/Gson
    //   3: dup
    //   4: getstatic Perryc.1 : I
    //   7: ifeq -> 20
    //   10: ldc2_w 599927376
    //   13: l2i
    //   14: ldc -1942991987
    //   16: ixor
    //   17: goto -> 27
    //   20: ldc2_w -578211619
    //   23: l2i
    //   24: ldc 760321567
    //   26: ixor
    //   27: ldc2_w -393373967
    //   30: l2i
    //   31: ldc 680028478
    //   33: ixor
    //   34: ixor
    //   35: lookupswitch default -> 374, 819812621 -> 60, 1878498834 -> 20
    //   60: invokespecial <init> : ()V
    //   63: getstatic Perryc.c : I
    //   66: iflt -> 79
    //   69: ldc2_w -714791281
    //   72: l2i
    //   73: ldc 1622909967
    //   75: ixor
    //   76: goto -> 86
    //   79: ldc2_w 1128055522
    //   82: l2i
    //   83: ldc 869417064
    //   85: ixor
    //   86: ldc2_w -1804646656
    //   89: l2i
    //   90: ldc -109808386
    //   92: ixor
    //   93: ixor
    //   94: lookupswitch default -> 368, -658132610 -> 79, 502641012 -> 120
    //   120: putstatic bigname/zprestige/webhack/manager/Identity/UtilThree.gson : Lcom/google/gson/Gson;
    //   123: new com/google/gson/GsonBuilder
    //   126: dup
    //   127: getstatic Perryc.1 : I
    //   130: ifeq -> 143
    //   133: ldc2_w 645401604
    //   136: l2i
    //   137: ldc 250228732
    //   139: ixor
    //   140: goto -> 150
    //   143: ldc2_w 807436035
    //   146: l2i
    //   147: ldc -225528773
    //   149: ixor
    //   150: ldc2_w 1814974086
    //   153: l2i
    //   154: ldc -1013311305
    //   156: ixor
    //   157: ixor
    //   158: lookupswitch default -> 370, -2027522615 -> 143, 1830460681 -> 184
    //   184: invokespecial <init> : ()V
    //   187: getstatic Perryc.c : I
    //   190: iflt -> 203
    //   193: ldc2_w 281947137
    //   196: l2i
    //   197: ldc -372759021
    //   199: ixor
    //   200: goto -> 210
    //   203: ldc2_w 1386766353
    //   206: l2i
    //   207: ldc -1844268282
    //   209: ixor
    //   210: ldc2_w 2015897447
    //   213: l2i
    //   214: ldc -627363716
    //   216: ixor
    //   217: ixor
    //   218: lookupswitch default -> 244, 808624598 -> 203, 1538596105 -> 376
    //   244: invokevirtual setPrettyPrinting : ()Lcom/google/gson/GsonBuilder;
    //   247: getstatic Perryc.c : I
    //   250: iflt -> 263
    //   253: ldc2_w 380564711
    //   256: l2i
    //   257: ldc -746166731
    //   259: ixor
    //   260: goto -> 270
    //   263: ldc2_w 873058304
    //   266: l2i
    //   267: ldc 42756371
    //   269: ixor
    //   270: ldc2_w -660241959
    //   273: l2i
    //   274: ldc 1003702658
    //   276: ixor
    //   277: ixor
    //   278: lookupswitch default -> 304, -1271387637 -> 263, 643717769 -> 378
    //   304: invokevirtual create : ()Lcom/google/gson/Gson;
    //   307: getstatic Perryc.c : I
    //   310: iflt -> 323
    //   313: ldc2_w -321164911
    //   316: l2i
    //   317: ldc -1106422078
    //   319: ixor
    //   320: goto -> 330
    //   323: ldc2_w 162448555
    //   326: l2i
    //   327: ldc 1397779122
    //   329: ixor
    //   330: ldc2_w -1904998331
    //   333: l2i
    //   334: ldc 1593327209
    //   336: ixor
    //   337: ixor
    //   338: lookupswitch default -> 372, -2108028545 -> 323, -1972201419 -> 364
    //   364: putstatic bigname/zprestige/webhack/manager/Identity/UtilThree.PRETTY_PRINTING : Lcom/google/gson/Gson;
    //   367: return
    //   368: aconst_null
    //   369: athrow
    //   370: aconst_null
    //   371: athrow
    //   372: aconst_null
    //   373: athrow
    //   374: aconst_null
    //   375: athrow
    //   376: aconst_null
    //   377: athrow
    //   378: aconst_null
    //   379: athrow
  }
  
  public String toJson() {
    return Perry1.j(this, (int)140201668L ^ 0xF3F857C);
  }
  
  public UtilThree() {
    // Byte code:
    //   0: getstatic Perryc.0 : I
    //   3: ifle -> 16
    //   6: ldc2_w 1364564132
    //   9: l2i
    //   10: ldc 1444566244
    //   12: ixor
    //   13: goto -> 23
    //   16: ldc2_w 1112547825
    //   19: l2i
    //   20: ldc -1058556719
    //   22: ixor
    //   23: ldc2_w -401236848
    //   26: l2i
    //   27: ldc -1278513632
    //   29: ixor
    //   30: ixor
    //   31: lookupswitch default -> 120, -647403632 -> 56, 1553022704 -> 16
    //   56: aload_0
    //   57: getstatic Perryc.c : I
    //   60: iflt -> 73
    //   63: ldc2_w 1429064751
    //   66: l2i
    //   67: ldc 234724875
    //   69: ixor
    //   70: goto -> 80
    //   73: ldc2_w 641456886
    //   76: l2i
    //   77: ldc -2137344202
    //   79: ixor
    //   80: ldc2_w 2114320180
    //   83: l2i
    //   84: ldc -362161487
    //   86: ixor
    //   87: ixor
    //   88: lookupswitch default -> 116, -860061791 -> 122, -599606192 -> 73
    //   116: invokespecial <init> : ()V
    //   119: return
    //   120: aconst_null
    //   121: athrow
    //   122: aconst_null
    //   123: athrow
    // Local variable table:
    //   start	length	slot	name	descriptor
    //   0	120	0	this	Lbigname/zprestige/webhack/manager/Identity/UtilThree;
  }
  
  public String toJson(boolean paramBoolean) {
    return Perry1.5I(this, (int)-101198340L ^ 0xFD3CA1CF, paramBoolean);
  }
}


/* Location:              C:\Users\alex\Desktop\webhack\WebHack-0.8-obf_sussy_1.jar!\bigname\zprestige\webhack\manager\Identity\UtilThree.class
 * Java compiler version: 8 (52.0)
 * JD-Core Version:       1.1.3
 */