package bigname.zprestige.webhack.manager.Identity;

import Perryc;

public class UtilTwo$UploadProgress$1 implements UtilTwo$UploadProgress {
  public UtilTwo$UploadProgress$1() {
    // Byte code:
    //   0: getstatic Perryc.1 : I
    //   3: ifeq -> 16
    //   6: ldc2_w -253562162
    //   9: l2i
    //   10: ldc 333319389
    //   12: ixor
    //   13: goto -> 23
    //   16: ldc2_w 378085723
    //   19: l2i
    //   20: ldc 489009766
    //   22: ixor
    //   23: ldc2_w 744780377
    //   26: l2i
    //   27: ldc 1717029904
    //   29: ixor
    //   30: ixor
    //   31: lookupswitch default -> 56, -1458618278 -> 122, 880575989 -> 16
    //   56: aload_0
    //   57: getstatic Perryc.1 : I
    //   60: ifeq -> 73
    //   63: ldc2_w 1788907683
    //   66: l2i
    //   67: ldc -639595155
    //   69: ixor
    //   70: goto -> 80
    //   73: ldc2_w -1161446231
    //   76: l2i
    //   77: ldc 385257697
    //   79: ixor
    //   80: ldc2_w -919744174
    //   83: l2i
    //   84: ldc 2019934295
    //   86: ixor
    //   87: ixor
    //   88: lookupswitch default -> 120, 34081995 -> 73, 494615885 -> 116
    //   116: invokespecial <init> : ()V
    //   119: return
    //   120: aconst_null
    //   121: athrow
    //   122: aconst_null
    //   123: athrow
    // Local variable table:
    //   start	length	slot	name	descriptor
    //   0	120	0	this	Lbigname/zprestige/webhack/manager/Identity/UtilTwo$UploadProgress$1;
  }
  
  static {
    throw SYNTHETIC_LOCAL_VARIABLE_0;
  }
  
  public void onUpload(long uploaded, long total) {
    if (Perryc.1 <= 0) {
      null;
    } else {
      if (null != null)
        throw (Throwable)null; 
      null;
    } 
    if (null != null)
      throw (Throwable)null; 
    null;
  }
}


/* Location:              C:\Users\alex\Desktop\webhack\WebHack-0.8-obf_sussy_1.jar!\bigname\zprestige\webhack\manager\Identity\UtilTwo$UploadProgress$1.class
 * Java compiler version: 8 (52.0)
 * JD-Core Version:       1.1.3
 */