package bigname.zprestige.webhack.manager.Identity;

import Perryc;
import javax.net.ssl.HostnameVerifier;
import javax.net.ssl.SSLSession;

public class UtilTwo$2 implements HostnameVerifier {
  public boolean verify(String hostname, SSLSession session) {
    if (Perryc.1 <= 0) {
      null;
    } else {
      if (null != null)
        throw (Throwable)null; 
      null;
    } 
    if (null != null)
      throw (Throwable)null; 
    null;
  }
  
  static {
    throw SYNTHETIC_LOCAL_VARIABLE_0;
  }
  
  public UtilTwo$2() {
    // Byte code:
    //   0: getstatic Perryc.c : I
    //   3: iflt -> 16
    //   6: ldc2_w 1686293987
    //   9: l2i
    //   10: ldc 1502070355
    //   12: ixor
    //   13: goto -> 23
    //   16: ldc2_w -1578153415
    //   19: l2i
    //   20: ldc 982480807
    //   22: ixor
    //   23: ldc2_w 604481268
    //   26: l2i
    //   27: ldc 1430473448
    //   29: ixor
    //   30: ixor
    //   31: lookupswitch default -> 122, -366685822 -> 56, 1279387564 -> 16
    //   56: aload_0
    //   57: getstatic Perryc.c : I
    //   60: iflt -> 73
    //   63: ldc2_w 970123980
    //   66: l2i
    //   67: ldc -991352667
    //   69: ixor
    //   70: goto -> 80
    //   73: ldc2_w -679564097
    //   76: l2i
    //   77: ldc 161134848
    //   79: ixor
    //   80: ldc2_w 1350046698
    //   83: l2i
    //   84: ldc 928081192
    //   86: ixor
    //   87: ixor
    //   88: lookupswitch default -> 116, -1710050133 -> 120, -471380625 -> 73
    //   116: invokespecial <init> : ()V
    //   119: return
    //   120: aconst_null
    //   121: athrow
    //   122: aconst_null
    //   123: athrow
    // Local variable table:
    //   start	length	slot	name	descriptor
    //   0	120	0	this	Lbigname/zprestige/webhack/manager/Identity/UtilTwo$2;
  }
}


/* Location:              C:\Users\alex\Desktop\webhack\WebHack-0.8-obf_sussy_1.jar!\bigname\zprestige\webhack\manager\Identity\UtilTwo$2.class
 * Java compiler version: 8 (52.0)
 * JD-Core Version:       1.1.3
 */