package bigname.zprestige.webhack.manager.Identity;

public class UtilOne$CapeException extends RuntimeException {
  public UtilOne this$0;
  
  public UtilOne$CapeException(UtilOne this$0, String message) {
    // Byte code:
    //   0: getstatic Perryc.0 : I
    //   3: ifle -> 16
    //   6: ldc2_w -1209649663
    //   9: l2i
    //   10: ldc -47152244
    //   12: ixor
    //   13: goto -> 23
    //   16: ldc2_w -610849471
    //   19: l2i
    //   20: ldc 1068516963
    //   22: ixor
    //   23: ldc2_w 995091265
    //   26: l2i
    //   27: ldc 967893163
    //   29: ixor
    //   30: ixor
    //   31: lookupswitch default -> 366, -422025016 -> 56, 1210693223 -> 16
    //   56: aload_0
    //   57: getstatic Perryc.c : I
    //   60: iflt -> 73
    //   63: ldc2_w -1688495698
    //   66: l2i
    //   67: ldc 2056832510
    //   69: ixor
    //   70: goto -> 80
    //   73: ldc2_w 1415838358
    //   76: l2i
    //   77: ldc 2090577181
    //   79: ixor
    //   80: ldc2_w -384772344
    //   83: l2i
    //   84: ldc 429995359
    //   86: ixor
    //   87: ixor
    //   88: lookupswitch default -> 368, -666257956 -> 116, 292732423 -> 73
    //   116: aload_1
    //   117: getstatic Perryc.1 : I
    //   120: ifeq -> 133
    //   123: ldc2_w 778277765
    //   126: l2i
    //   127: ldc 88506375
    //   129: ixor
    //   130: goto -> 140
    //   133: ldc2_w -1846502143
    //   136: l2i
    //   137: ldc 2078601009
    //   139: ixor
    //   140: ldc2_w -376090814
    //   143: l2i
    //   144: ldc -1246873817
    //   146: ixor
    //   147: ixor
    //   148: lookupswitch default -> 364, -1238431147 -> 176, 1998482407 -> 133
    //   176: putfield this$0 : Lbigname/zprestige/webhack/manager/Identity/UtilOne;
    //   179: getstatic Perryc.1 : I
    //   182: ifeq -> 195
    //   185: ldc2_w -2123147713
    //   188: l2i
    //   189: ldc 747017880
    //   191: ixor
    //   192: goto -> 202
    //   195: ldc2_w -1228234407
    //   198: l2i
    //   199: ldc -350994745
    //   201: ixor
    //   202: ldc2_w -1475190684
    //   205: l2i
    //   206: ldc 196754392
    //   208: ixor
    //   209: ixor
    //   210: lookupswitch default -> 362, -25770974 -> 236, 241015579 -> 195
    //   236: aload_0
    //   237: getstatic Perryc.0 : I
    //   240: ifle -> 253
    //   243: ldc2_w -739592242
    //   246: l2i
    //   247: ldc 1887398539
    //   249: ixor
    //   250: goto -> 260
    //   253: ldc2_w 1615876243
    //   256: l2i
    //   257: ldc -330670407
    //   259: ixor
    //   260: ldc2_w -1343721501
    //   263: l2i
    //   264: ldc 16372492
    //   266: ixor
    //   267: ixor
    //   268: lookupswitch default -> 370, 210002346 -> 253, 587969221 -> 296
    //   296: aload_2
    //   297: getstatic Perryc.1 : I
    //   300: ifeq -> 313
    //   303: ldc2_w -1359414761
    //   306: l2i
    //   307: ldc 1556283685
    //   309: ixor
    //   310: goto -> 320
    //   313: ldc2_w -1755469365
    //   316: l2i
    //   317: ldc 359242108
    //   319: ixor
    //   320: ldc2_w -1611558238
    //   323: l2i
    //   324: ldc -804990221
    //   326: ixor
    //   327: ixor
    //   328: lookupswitch default -> 356, -1241750950 -> 313, -1110525085 -> 360
    //   356: invokespecial <init> : (Ljava/lang/String;)V
    //   359: return
    //   360: aconst_null
    //   361: athrow
    //   362: aconst_null
    //   363: athrow
    //   364: aconst_null
    //   365: athrow
    //   366: aconst_null
    //   367: athrow
    //   368: aconst_null
    //   369: athrow
    //   370: aconst_null
    //   371: athrow
    // Local variable table:
    //   start	length	slot	name	descriptor
    //   0	360	0	this	Lbigname/zprestige/webhack/manager/Identity/UtilOne$CapeException;
    //   0	360	1	this$0	Lbigname/zprestige/webhack/manager/Identity/UtilOne;
    //   0	360	2	message	Ljava/lang/String;
  }
  
  static {
    throw SYNTHETIC_LOCAL_VARIABLE_0;
  }
}


/* Location:              C:\Users\alex\Desktop\webhack\WebHack-0.8-obf_sussy_1.jar!\bigname\zprestige\webhack\manager\Identity\UtilOne$CapeException.class
 * Java compiler version: 8 (52.0)
 * JD-Core Version:       1.1.3
 */