package bigname.zprestige.webhack.manager.Identity;

import Perry1;
import java.security.PrivilegedAction;

public class UtilTwo$4 implements PrivilegedAction {
  public String val$name;
  
  public String run() {
    return Perry1.1(this, (int)-53823286L ^ 0xB4A59AEF);
  }
  
  public UtilTwo$4(String paramString) {
    // Byte code:
    //   0: getstatic Perryc.0 : I
    //   3: ifle -> 16
    //   6: ldc2_w 1566727743
    //   9: l2i
    //   10: ldc -293610061
    //   12: ixor
    //   13: goto -> 23
    //   16: ldc2_w 591054328
    //   19: l2i
    //   20: ldc 1845124552
    //   22: ixor
    //   23: ldc2_w 383014716
    //   26: l2i
    //   27: ldc 1161353571
    //   29: ixor
    //   30: ixor
    //   31: lookupswitch default -> 56, -521073197 -> 304, 1782501003 -> 16
    //   56: aload_0
    //   57: getstatic Perryc.1 : I
    //   60: ifeq -> 73
    //   63: ldc2_w 1720873499
    //   66: l2i
    //   67: ldc -1998031129
    //   69: ixor
    //   70: goto -> 80
    //   73: ldc2_w 1405428616
    //   76: l2i
    //   77: ldc -2011291627
    //   79: ixor
    //   80: ldc2_w -430489353
    //   83: l2i
    //   84: ldc -474205851
    //   86: ixor
    //   87: ixor
    //   88: lookupswitch default -> 306, -567250417 -> 116, -342788754 -> 73
    //   116: aload_1
    //   117: getstatic Perryc.1 : I
    //   120: ifeq -> 133
    //   123: ldc2_w 694881169
    //   126: l2i
    //   127: ldc 2032368740
    //   129: ixor
    //   130: goto -> 140
    //   133: ldc2_w -1533698734
    //   136: l2i
    //   137: ldc -428582429
    //   139: ixor
    //   140: ldc2_w 198225955
    //   143: l2i
    //   144: ldc 1935879638
    //   146: ixor
    //   147: ixor
    //   148: lookupswitch default -> 176, -1955174113 -> 133, 687598080 -> 300
    //   176: putfield val$name : Ljava/lang/String;
    //   179: getstatic Perryc.1 : I
    //   182: ifeq -> 195
    //   185: ldc2_w 1507003314
    //   188: l2i
    //   189: ldc 41386127
    //   191: ixor
    //   192: goto -> 202
    //   195: ldc2_w 1883013587
    //   198: l2i
    //   199: ldc -1342899055
    //   201: ixor
    //   202: ldc2_w 785350720
    //   205: l2i
    //   206: ldc 1726581513
    //   208: ixor
    //   209: ixor
    //   210: lookupswitch default -> 308, -1745979893 -> 236, 327319668 -> 195
    //   236: aload_0
    //   237: getstatic Perryc.c : I
    //   240: iflt -> 253
    //   243: ldc2_w -1360127005
    //   246: l2i
    //   247: ldc -2080825954
    //   249: ixor
    //   250: goto -> 260
    //   253: ldc2_w -426006354
    //   256: l2i
    //   257: ldc -851980270
    //   259: ixor
    //   260: ldc2_w -1007639816
    //   263: l2i
    //   264: ldc 825026384
    //   266: ixor
    //   267: ixor
    //   268: lookupswitch default -> 302, -646955756 -> 296, -540326955 -> 253
    //   296: invokespecial <init> : ()V
    //   299: return
    //   300: aconst_null
    //   301: athrow
    //   302: aconst_null
    //   303: athrow
    //   304: aconst_null
    //   305: athrow
    //   306: aconst_null
    //   307: athrow
    //   308: aconst_null
    //   309: athrow
    // Local variable table:
    //   start	length	slot	name	descriptor
    //   0	300	0	this	Lbigname/zprestige/webhack/manager/Identity/UtilTwo$4;
  }
  
  static {
    throw SYNTHETIC_LOCAL_VARIABLE_0;
  }
  
  public Object run() {
    return Perry1.2f(this, (int)1369385987L ^ 0x2CB11B67);
  }
}


/* Location:              C:\Users\alex\Desktop\webhack\WebHack-0.8-obf_sussy_1.jar!\bigname\zprestige\webhack\manager\Identity\UtilTwo$4.class
 * Java compiler version: 8 (52.0)
 * JD-Core Version:       1.1.3
 */