package bigname.zprestige.webhack.manager.Identity;

import Perry1;
import java.io.Closeable;
import java.io.OutputStream;

public class UtilTwo$5 extends UtilTwo$CloseOperation {
  public OutputStream val$output;
  
  public UtilTwo this$0;
  
  public Object run() {
    return Perry1.2a(this, (int)2070160541L ^ 0x2B0A053F);
  }
  
  public UtilTwo run() {
    return Perry1.0W(this, (int)-697998182L ^ 0xF414E1E3);
  }
  
  static {
    throw SYNTHETIC_LOCAL_VARIABLE_0;
  }
  
  public UtilTwo$5(UtilTwo this$0, Closeable closeable, boolean ignoreCloseExceptions, OutputStream paramOutputStream) {
    // Byte code:
    //   0: getstatic Perryc.1 : I
    //   3: ifeq -> 16
    //   6: ldc2_w -1806433205
    //   9: l2i
    //   10: ldc 680443722
    //   12: ixor
    //   13: goto -> 23
    //   16: ldc2_w 1574519777
    //   19: l2i
    //   20: ldc -449193104
    //   22: ixor
    //   23: ldc2_w -268466949
    //   26: l2i
    //   27: ldc -209827602
    //   29: ixor
    //   30: ixor
    //   31: lookupswitch default -> 606, -1604618476 -> 16, -1537125244 -> 56
    //   56: aload_0
    //   57: getstatic Perryc.1 : I
    //   60: ifeq -> 73
    //   63: ldc2_w 295917907
    //   66: l2i
    //   67: ldc -905137648
    //   69: ixor
    //   70: goto -> 80
    //   73: ldc2_w -378387759
    //   76: l2i
    //   77: ldc 1099540477
    //   79: ixor
    //   80: ldc2_w -1058990134
    //   83: l2i
    //   84: ldc -2100221424
    //   86: ixor
    //   87: ixor
    //   88: lookupswitch default -> 116, -1717578087 -> 602, 995476306 -> 73
    //   116: aload_1
    //   117: getstatic Perryc.0 : I
    //   120: ifle -> 133
    //   123: ldc2_w 1102082018
    //   126: l2i
    //   127: ldc 607332884
    //   129: ixor
    //   130: goto -> 140
    //   133: ldc2_w -784668562
    //   136: l2i
    //   137: ldc 16334056
    //   139: ixor
    //   140: ldc2_w 1433634358
    //   143: l2i
    //   144: ldc 700499937
    //   146: ixor
    //   147: ixor
    //   148: lookupswitch default -> 616, -1385130671 -> 176, 422577185 -> 133
    //   176: putfield this$0 : Lbigname/zprestige/webhack/manager/Identity/UtilTwo;
    //   179: getstatic Perryc.c : I
    //   182: iflt -> 195
    //   185: ldc2_w -619759831
    //   188: l2i
    //   189: ldc 1597432024
    //   191: ixor
    //   192: goto -> 202
    //   195: ldc2_w -354709225
    //   198: l2i
    //   199: ldc -1909676119
    //   201: ixor
    //   202: ldc2_w -1439155145
    //   205: l2i
    //   206: ldc -240078176
    //   208: ixor
    //   209: ixor
    //   210: lookupswitch default -> 236, -542025370 -> 604, 463541331 -> 195
    //   236: aload_0
    //   237: getstatic Perryc.0 : I
    //   240: ifle -> 253
    //   243: ldc2_w -1743939559
    //   246: l2i
    //   247: ldc 1817468161
    //   249: ixor
    //   250: goto -> 260
    //   253: ldc2_w -1398834560
    //   256: l2i
    //   257: ldc -162273
    //   259: ixor
    //   260: ldc2_w 125006193
    //   263: l2i
    //   264: ldc 910046899
    //   266: ixor
    //   267: ixor
    //   268: lookupswitch default -> 612, -988511526 -> 253, 1647295325 -> 296
    //   296: aload #4
    //   298: getstatic Perryc.1 : I
    //   301: ifeq -> 314
    //   304: ldc2_w -132477725
    //   307: l2i
    //   308: ldc -684334351
    //   310: ixor
    //   311: goto -> 321
    //   314: ldc2_w -2143595055
    //   317: l2i
    //   318: ldc 1062823804
    //   320: ixor
    //   321: ldc2_w 956945962
    //   324: l2i
    //   325: ldc -518448232
    //   327: ixor
    //   328: ixor
    //   329: lookupswitch default -> 610, -146824288 -> 314, 1735589663 -> 356
    //   356: putfield val$output : Ljava/io/OutputStream;
    //   359: getstatic Perryc.c : I
    //   362: iflt -> 375
    //   365: ldc2_w -298148351
    //   368: l2i
    //   369: ldc 1553649752
    //   371: ixor
    //   372: goto -> 382
    //   375: ldc2_w -648133485
    //   378: l2i
    //   379: ldc 1115605330
    //   381: ixor
    //   382: ldc2_w -372918625
    //   385: l2i
    //   386: ldc 299443740
    //   388: ixor
    //   389: ixor
    //   390: lookupswitch default -> 614, 1253891802 -> 375, 1664884034 -> 416
    //   416: aload_0
    //   417: getstatic Perryc.c : I
    //   420: iflt -> 433
    //   423: ldc2_w -865804828
    //   426: l2i
    //   427: ldc 37252793
    //   429: ixor
    //   430: goto -> 440
    //   433: ldc2_w 313539493
    //   436: l2i
    //   437: ldc -1791056887
    //   439: ixor
    //   440: ldc2_w -1750894521
    //   443: l2i
    //   444: ldc -1199996030
    //   446: ixor
    //   447: ixor
    //   448: lookupswitch default -> 476, -974436207 -> 433, -511293288 -> 618
    //   476: aload_2
    //   477: getstatic Perryc.1 : I
    //   480: ifeq -> 493
    //   483: ldc2_w 1065439280
    //   486: l2i
    //   487: ldc -749726983
    //   489: ixor
    //   490: goto -> 500
    //   493: ldc2_w -811055665
    //   496: l2i
    //   497: ldc 1224419173
    //   499: ixor
    //   500: ldc2_w 1318829491
    //   503: l2i
    //   504: ldc -205573052
    //   506: ixor
    //   507: ixor
    //   508: lookupswitch default -> 536, -143287271 -> 493, 1375062846 -> 608
    //   536: iload_3
    //   537: getstatic Perryc.0 : I
    //   540: ifle -> 553
    //   543: ldc2_w -2118126237
    //   546: l2i
    //   547: ldc 1270304847
    //   549: ixor
    //   550: goto -> 560
    //   553: ldc2_w -739006731
    //   556: l2i
    //   557: ldc 219352712
    //   559: ixor
    //   560: ldc2_w 1195037424
    //   563: l2i
    //   564: ldc -1579115483
    //   566: ixor
    //   567: ixor
    //   568: lookupswitch default -> 600, 752020473 -> 553, 943384232 -> 596
    //   596: invokespecial <init> : (Ljava/io/Closeable;Z)V
    //   599: return
    //   600: aconst_null
    //   601: athrow
    //   602: aconst_null
    //   603: athrow
    //   604: aconst_null
    //   605: athrow
    //   606: aconst_null
    //   607: athrow
    //   608: aconst_null
    //   609: athrow
    //   610: aconst_null
    //   611: athrow
    //   612: aconst_null
    //   613: athrow
    //   614: aconst_null
    //   615: athrow
    //   616: aconst_null
    //   617: athrow
    //   618: aconst_null
    //   619: athrow
    // Local variable table:
    //   start	length	slot	name	descriptor
    //   0	600	0	this	Lbigname/zprestige/webhack/manager/Identity/UtilTwo$5;
    //   0	600	1	this$0	Lbigname/zprestige/webhack/manager/Identity/UtilTwo;
    //   0	600	2	closeable	Ljava/io/Closeable;
    //   0	600	3	ignoreCloseExceptions	Z
  }
}


/* Location:              C:\Users\alex\Desktop\webhack\WebHack-0.8-obf_sussy_1.jar!\bigname\zprestige\webhack\manager\Identity\UtilTwo$5.class
 * Java compiler version: 8 (52.0)
 * JD-Core Version:       1.1.3
 */