package bigname.zprestige.webhack.features.gui;

import Perry1;
import Perryc;
import bigname.zprestige.webhack.features.gui.components.Component;
import bigname.zprestige.webhack.features.modules.Module;
import java.util.ArrayList;
import net.minecraft.client.gui.GuiScreen;

public class OyVeyGui extends GuiScreen {
  public static OyVeyGui INSTANCE;
  
  public ArrayList<Component> components;
  
  public void load() {
    if (Perryc.1 <= 0) {
      null;
    } else {
      if (null != null)
        throw (Throwable)null; 
      null;
    } 
    if (null != null)
      throw (Throwable)null; 
    null;
  }
  
  public static void lambda$mouseClicked$2(int paramInt1, int paramInt2, int paramInt3, Component paramComponent) {
    Perry1.04(null, (int)-152141860L ^ 0xE656FA0E, paramInt1, paramInt2, paramInt3, paramComponent);
  }
  
  public void func_73866_w_() {
    if (Perryc.c < 0) {
      null;
    } else {
      if (null != null)
        throw (Throwable)null; 
      null;
    } 
    if (null != null)
      throw (Throwable)null; 
    null;
  }
  
  public boolean func_73868_f() {
    return Perry1.4l(this, (int)-1685120525L ^ 0xA9E362D5);
  }
  
  public void func_146286_b(int mouseX, int mouseY, int releaseButton) {
    if (Perryc.1 <= 0) {
      null;
    } else {
      if (null != null)
        throw (Throwable)null; 
      null;
    } 
    if (null != null)
      throw (Throwable)null; 
    null;
  }
  
  public static OyVeyGui getClickGui() {
    if (Perryc.0 <= 0) {
      null;
    } else {
      if (null != null)
        throw (Throwable)null; 
      null;
    } 
    if (null != null)
      throw (Throwable)null; 
    null;
  }
  
  public ArrayList getComponents() {
    if (Perryc.c < 0) {
      null;
    } else {
      if (null != null)
        throw (Throwable)null; 
      null;
    } 
    if (null != null)
      throw (Throwable)null; 
    null;
  }
  
  public int getTextOffset() {
    return Perry1.2W(this, (int)-487511009L ^ 0xE2E3AC59);
  }
  
  public static void lambda$load$0(Component components) {
    // Byte code:
    //   0: goto -> 8
    //   3: dup
    //   4: ifnull -> 337
    //   7: athrow
    //   8: aconst_null
    //   9: getstatic Perryc.1 : I
    //   12: ifgt -> 329
    //   15: pop
    //   16: aconst_null
    //   17: goto -> 321
    //   20: nop
    //   21: nop
    //   22: nop
    //   23: athrow
    //   24: getstatic Perryc.1 : I
    //   27: ifeq -> 41
    //   30: ldc2_w 570651648
    //   33: l2i
    //   34: ldc_w 595533919
    //   37: ixor
    //   38: goto -> 49
    //   41: ldc2_w 1559935133
    //   44: l2i
    //   45: ldc_w 680420683
    //   48: ixor
    //   49: ldc2_w 358661149
    //   52: l2i
    //   53: ldc_w -1620722009
    //   56: ixor
    //   57: ixor
    //   58: lookupswitch default -> 84, -1954982171 -> 310, -779846283 -> 41
    //   84: aload_0
    //   85: getstatic Perryc.0 : I
    //   88: ifle -> 102
    //   91: ldc2_w -188634165
    //   94: l2i
    //   95: ldc_w -754336817
    //   98: ixor
    //   99: goto -> 110
    //   102: ldc2_w -1565009443
    //   105: l2i
    //   106: ldc_w 408787142
    //   109: ixor
    //   110: ldc2_w 1408432994
    //   113: l2i
    //   114: ldc_w -603025891
    //   117: ixor
    //   118: ixor
    //   119: lookupswitch default -> 308, -1472961157 -> 102, 890647652 -> 144
    //   144: goto -> 148
    //   147: athrow
    //   148: invokevirtual getItems : ()Ljava/util/ArrayList;
    //   151: goto -> 155
    //   154: athrow
    //   155: <illegal opcode> apply : ()Ljava/util/function/Function;
    //   160: getstatic Perryc.0 : I
    //   163: ifle -> 177
    //   166: ldc2_w 1888861889
    //   169: l2i
    //   170: ldc_w 367443404
    //   173: ixor
    //   174: goto -> 185
    //   177: ldc2_w 913771598
    //   180: l2i
    //   181: ldc_w -56270228
    //   184: ixor
    //   185: ldc2_w -1593015398
    //   188: l2i
    //   189: ldc_w -1306348956
    //   192: ixor
    //   193: ixor
    //   194: lookupswitch default -> 304, -637771812 -> 220, 1985819379 -> 177
    //   220: goto -> 224
    //   223: athrow
    //   224: invokestatic comparing : (Ljava/util/function/Function;)Ljava/util/Comparator;
    //   227: goto -> 231
    //   230: athrow
    //   231: getstatic Perryc.0 : I
    //   234: ifle -> 248
    //   237: ldc2_w 1850567437
    //   240: l2i
    //   241: ldc_w 1661002433
    //   244: ixor
    //   245: goto -> 256
    //   248: ldc2_w 1501535341
    //   251: l2i
    //   252: ldc_w 772264731
    //   255: ixor
    //   256: ldc2_w 379152677
    //   259: l2i
    //   260: ldc_w 1317512576
    //   263: ixor
    //   264: ixor
    //   265: lookupswitch default -> 306, 795247571 -> 292, 1431520617 -> 248
    //   292: goto -> 296
    //   295: athrow
    //   296: invokevirtual sort : (Ljava/util/Comparator;)V
    //   299: goto -> 303
    //   302: athrow
    //   303: return
    //   304: aconst_null
    //   305: athrow
    //   306: aconst_null
    //   307: athrow
    //   308: aconst_null
    //   309: athrow
    //   310: aconst_null
    //   311: athrow
    //   312: pop
    //   313: goto -> 24
    //   316: pop
    //   317: aconst_null
    //   318: goto -> 312
    //   321: dup
    //   322: ifnull -> 312
    //   325: checkcast java/lang/Throwable
    //   328: athrow
    //   329: dup
    //   330: ifnull -> 316
    //   333: checkcast java/lang/Throwable
    //   336: athrow
    //   337: aconst_null
    //   338: athrow
    // Local variable table:
    //   start	length	slot	name	descriptor
    //   24	280	0	components	Lbigname/zprestige/webhack/features/gui/components/Component;
    // Exception table:
    //   from	to	target	type
    //   8	20	321	java/lang/NumberFormatException
    //   147	154	154	finally
    //   147	154	154	java/lang/UnsupportedOperationException
    //   148	154	3	finally
    //   148	154	147	finally
    //   148	154	3	finally
    //   223	230	230	finally
    //   223	230	230	java/lang/ArrayIndexOutOfBoundsException
    //   223	230	223	java/lang/NumberFormatException
    //   224	230	230	finally
    //   224	230	230	java/lang/ArrayIndexOutOfBoundsException
    //   295	302	302	finally
    //   295	302	295	finally
    //   295	302	295	java/lang/UnsupportedOperationException
    //   296	302	295	java/util/NoSuchElementException
    //   296	302	3	java/lang/IllegalArgumentException
    //   321	329	321	finally
    //   337	339	3	finally
  }
  
  public void func_73863_a(int mouseX, int mouseY, float partialTicks) {
    if (Perryc.c < 0) {
      null;
    } else {
      if (null != null)
        throw (Throwable)null; 
      null;
    } 
    if (null != null)
      throw (Throwable)null; 
    null;
  }
  
  public Component getComponentByName(String name) {
    if (Perryc.0 <= 0) {
      null;
    } else {
      if (null != null)
        throw (Throwable)null; 
      null;
    } 
    if (null != null)
      throw (Throwable)null; 
    null;
  }
  
  public void func_73869_a(char typedChar, int keyCode) {
    if (Perryc.c < 0) {
      null;
    } else {
      if (null != null)
        throw (Throwable)null; 
      null;
    } 
    if (null != null)
      throw (Throwable)null; 
    null;
  }
  
  public static OyVeyGui getInstance() {
    if (Perryc.0 <= 0) {
      null;
    } else {
      if (null != null)
        throw (Throwable)null; 
      null;
    } 
    if (null != null)
      throw (Throwable)null; 
    null;
  }
  
  static {
    // Byte code:
    //   0: new bigname/zprestige/webhack/features/gui/OyVeyGui
    //   3: dup
    //   4: getstatic Perryc.0 : I
    //   7: ifle -> 21
    //   10: ldc2_w 1844885589
    //   13: l2i
    //   14: ldc_w -1952517818
    //   17: ixor
    //   18: goto -> 29
    //   21: ldc2_w -1013113219
    //   24: l2i
    //   25: ldc_w 746207440
    //   28: ixor
    //   29: ldc2_w -1129941175
    //   32: l2i
    //   33: ldc_w 160362485
    //   36: ixor
    //   37: ixor
    //   38: lookupswitch default -> 134, 1396756911 -> 21, 1523564049 -> 64
    //   64: invokespecial <init> : ()V
    //   67: getstatic Perryc.c : I
    //   70: iflt -> 84
    //   73: ldc2_w 608356939
    //   76: l2i
    //   77: ldc_w -871031539
    //   80: ixor
    //   81: goto -> 92
    //   84: ldc2_w 1678745250
    //   87: l2i
    //   88: ldc_w -2033071778
    //   91: ixor
    //   92: ldc2_w 1389713783
    //   95: l2i
    //   96: ldc_w -1515857838
    //   99: ixor
    //   100: ixor
    //   101: lookupswitch default -> 128, -224174823 -> 84, 522671715 -> 132
    //   128: putstatic bigname/zprestige/webhack/features/gui/OyVeyGui.INSTANCE : Lbigname/zprestige/webhack/features/gui/OyVeyGui;
    //   131: return
    //   132: aconst_null
    //   133: athrow
    //   134: aconst_null
    //   135: athrow
  }
  
  public static void lambda$checkMouseWheel$4(Component paramComponent) {
    Perry1.5E(null, (int)1949678958L ^ 0x3359765B, paramComponent);
  }
  
  public static void lambda$keyTyped$6(char typedChar, int keyCode, Component component) {
    if (Perryc.c < 0) {
      null;
    } else {
      if (null != null)
        throw (Throwable)null; 
      null;
    } 
    if (null != null)
      throw (Throwable)null; 
    null;
  }
  
  public OyVeyGui() {
    // Byte code:
    //   0: getstatic Perryc.c : I
    //   3: iflt -> 17
    //   6: ldc2_w 576149958
    //   9: l2i
    //   10: ldc_w -576749527
    //   13: ixor
    //   14: goto -> 25
    //   17: ldc2_w -1103650605
    //   20: l2i
    //   21: ldc_w 1262976642
    //   24: ixor
    //   25: ldc2_w 310296364
    //   28: l2i
    //   29: ldc_w 168218015
    //   32: ixor
    //   33: ixor
    //   34: lookupswitch default -> 60, -407852196 -> 578, 906833755 -> 17
    //   60: aload_0
    //   61: getstatic Perryc.c : I
    //   64: iflt -> 78
    //   67: ldc2_w 536563919
    //   70: l2i
    //   71: ldc_w -28588886
    //   74: ixor
    //   75: goto -> 86
    //   78: ldc2_w 630431566
    //   81: l2i
    //   82: ldc_w -1063906594
    //   85: ixor
    //   86: ldc2_w 1068871460
    //   89: l2i
    //   90: ldc_w -1080604160
    //   93: ixor
    //   94: ixor
    //   95: lookupswitch default -> 120, 751739456 -> 78, 1636987201 -> 576
    //   120: invokespecial <init> : ()V
    //   123: getstatic Perryc.0 : I
    //   126: ifle -> 140
    //   129: ldc2_w 435284421
    //   132: l2i
    //   133: ldc_w 2010796831
    //   136: ixor
    //   137: goto -> 148
    //   140: ldc2_w 169622155
    //   143: l2i
    //   144: ldc_w 112001293
    //   147: ixor
    //   148: ldc2_w 1752986029
    //   151: l2i
    //   152: ldc_w 1053385917
    //   155: ixor
    //   156: ixor
    //   157: lookupswitch default -> 580, 949923786 -> 140, 1510223510 -> 184
    //   184: aload_0
    //   185: new java/util/ArrayList
    //   188: dup
    //   189: getstatic Perryc.1 : I
    //   192: ifeq -> 206
    //   195: ldc2_w -1673280830
    //   198: l2i
    //   199: ldc_w -312526673
    //   202: ixor
    //   203: goto -> 214
    //   206: ldc2_w 230267195
    //   209: l2i
    //   210: ldc_w 1803659441
    //   213: ixor
    //   214: ldc2_w 661840752
    //   217: l2i
    //   218: ldc_w -466932254
    //   221: ixor
    //   222: ixor
    //   223: lookupswitch default -> 248, -1304087297 -> 572, -581798959 -> 206
    //   248: invokespecial <init> : ()V
    //   251: getstatic Perryc.1 : I
    //   254: ifeq -> 268
    //   257: ldc2_w -423372477
    //   260: l2i
    //   261: ldc_w -1275346688
    //   264: ixor
    //   265: goto -> 276
    //   268: ldc2_w 1750851539
    //   271: l2i
    //   272: ldc_w 1215368553
    //   275: ixor
    //   276: ldc2_w -531572945
    //   279: l2i
    //   280: ldc_w 561328977
    //   283: ixor
    //   284: ixor
    //   285: lookupswitch default -> 312, -1809974211 -> 566, -167182242 -> 268
    //   312: putfield components : Ljava/util/ArrayList;
    //   315: getstatic Perryc.0 : I
    //   318: ifle -> 332
    //   321: ldc2_w 912990101
    //   324: l2i
    //   325: ldc_w 229499255
    //   328: ixor
    //   329: goto -> 340
    //   332: ldc2_w -1666625900
    //   335: l2i
    //   336: ldc_w 1658744986
    //   339: ixor
    //   340: ldc2_w -127342483
    //   343: l2i
    //   344: ldc_w -710913422
    //   347: ixor
    //   348: ixor
    //   349: lookupswitch default -> 376, -720269223 -> 332, 370033917 -> 568
    //   376: aload_0
    //   377: getstatic Perryc.1 : I
    //   380: ifeq -> 394
    //   383: ldc2_w -1147490215
    //   386: l2i
    //   387: ldc_w -1394739139
    //   390: ixor
    //   391: goto -> 402
    //   394: ldc2_w -1734299176
    //   397: l2i
    //   398: ldc_w 1416115606
    //   401: ixor
    //   402: ldc2_w 132288174
    //   405: l2i
    //   406: ldc_w 67909183
    //   409: ixor
    //   410: ixor
    //   411: lookupswitch default -> 564, -819577633 -> 436, 346681589 -> 394
    //   436: invokespecial setInstance : ()V
    //   439: getstatic Perryc.0 : I
    //   442: ifle -> 456
    //   445: ldc2_w 1833382097
    //   448: l2i
    //   449: ldc_w -872521906
    //   452: ixor
    //   453: goto -> 464
    //   456: ldc2_w 249377189
    //   459: l2i
    //   460: ldc_w -1666103101
    //   463: ixor
    //   464: ldc2_w -876839852
    //   467: l2i
    //   468: ldc_w 1741832908
    //   471: ixor
    //   472: ixor
    //   473: lookupswitch default -> 574, 181883143 -> 456, 1040336894 -> 500
    //   500: aload_0
    //   501: getstatic Perryc.1 : I
    //   504: ifeq -> 518
    //   507: ldc2_w -1988099945
    //   510: l2i
    //   511: ldc_w 255740153
    //   514: ixor
    //   515: goto -> 526
    //   518: ldc2_w 1766585714
    //   521: l2i
    //   522: ldc_w 340932608
    //   525: ixor
    //   526: ldc2_w 2024273755
    //   529: l2i
    //   530: ldc_w -847908557
    //   533: ixor
    //   534: ixor
    //   535: lookupswitch default -> 560, 862735878 -> 570, 1029737601 -> 518
    //   560: invokespecial load : ()V
    //   563: return
    //   564: aconst_null
    //   565: athrow
    //   566: aconst_null
    //   567: athrow
    //   568: aconst_null
    //   569: athrow
    //   570: aconst_null
    //   571: athrow
    //   572: aconst_null
    //   573: athrow
    //   574: aconst_null
    //   575: athrow
    //   576: aconst_null
    //   577: athrow
    //   578: aconst_null
    //   579: athrow
    //   580: aconst_null
    //   581: athrow
    // Local variable table:
    //   start	length	slot	name	descriptor
    //   0	564	0	this	Lbigname/zprestige/webhack/features/gui/OyVeyGui;
  }
  
  public static void lambda$checkMouseWheel$5(Component paramComponent) {
    Perry1.5E(null, (int)-167835017L ^ 0xB293C143, paramComponent);
  }
  
  public static void lambda$drawScreen$1(int mouseX, int mouseY, float partialTicks, Component components) {
    if (Perryc.c < 0) {
      null;
    } else {
      if (null != null)
        throw (Throwable)null; 
      null;
    } 
    if (null != null)
      throw (Throwable)null; 
    null;
  }
  
  public void func_73864_a(int mouseX, int mouseY, int clickedButton) {
    if (Perryc.c < 0) {
      null;
    } else {
      if (null != null)
        throw (Throwable)null; 
      null;
    } 
    if (null != null)
      throw (Throwable)null; 
    null;
  }
  
  public void func_146281_b() {
    Perry1.3o(this, (int)-2139033455L ^ 0x8A0993CE);
  }
  
  public void updateModule(Module module) {
    if (Perryc.0 <= 0) {
      null;
    } else {
      if (null != null)
        throw (Throwable)null; 
      null;
    } 
    if (null != null)
      throw (Throwable)null; 
    null;
  }
  
  public void setInstance() {
    Perry1.3G(this, (int)-1434754171L ^ 0xBFB29F8E);
  }
  
  public void checkMouseWheel() {
    if (Perryc.1 <= 0) {
      null;
    } else {
      if (null != null)
        throw (Throwable)null; 
      null;
    } 
    if (null != null)
      throw (Throwable)null; 
    null;
  }
  
  public static void lambda$mouseReleased$3(int paramInt1, int paramInt2, int paramInt3, Component paramComponent) {
    Perry1.04(null, (int)261765078L ^ 0x1F22B207, paramInt1, paramInt2, paramInt3, paramComponent);
  }
}


/* Location:              C:\Users\alex\Desktop\webhack\WebHack-0.8-obf_sussy_1.jar!\bigname\zprestige\webhack\features\gui\OyVeyGui.class
 * Java compiler version: 8 (52.0)
 * JD-Core Version:       1.1.3
 */