package bigname.zprestige.webhack.features.modules.Client;

import Perryc;

public enum ClickGui$rainbowMode {
  Static;
  
  public static ClickGui$rainbowMode[] $VALUES;
  
  static {
    // Byte code:
    //   0: new bigname/zprestige/webhack/features/modules/Client/ClickGui$rainbowMode
    //   3: dup
    //   4: ldc '睵㌇眭ㅸ駹'
    //   6: getstatic Perryc.c : I
    //   9: iflt -> 22
    //   12: ldc2_w 2140914182
    //   15: l2i
    //   16: ldc -1542078671
    //   18: ixor
    //   19: goto -> 29
    //   22: ldc2_w 2025272346
    //   25: l2i
    //   26: ldc 1481893262
    //   28: ixor
    //   29: ldc2_w -2092364164
    //   32: l2i
    //   33: ldc 1084305011
    //   35: ixor
    //   36: ixor
    //   37: lookupswitch default -> 64, -528352012 -> 22, 409361720 -> 338
    //   64: invokestatic 0 : (Ljava/lang/String;)Ljava/lang/String;
    //   67: ldc2_w -1831240337
    //   70: l2i
    //   71: ldc -1831240337
    //   73: ixor
    //   74: getstatic Perryc.1 : I
    //   77: ifeq -> 90
    //   80: ldc2_w 2139470429
    //   83: l2i
    //   84: ldc 830906794
    //   86: ixor
    //   87: goto -> 97
    //   90: ldc2_w -1829477055
    //   93: l2i
    //   94: ldc -1765243915
    //   96: ixor
    //   97: ldc2_w -205211077
    //   100: l2i
    //   101: ldc -37094993
    //   103: ixor
    //   104: ixor
    //   105: lookupswitch default -> 344, 171025696 -> 132, 1074681955 -> 90
    //   132: invokespecial <init> : (Ljava/lang/String;I)V
    //   135: getstatic Perryc.1 : I
    //   138: ifeq -> 151
    //   141: ldc2_w 1106755601
    //   144: l2i
    //   145: ldc -787844232
    //   147: ixor
    //   148: goto -> 158
    //   151: ldc2_w -648316281
    //   154: l2i
    //   155: ldc -842871279
    //   157: ixor
    //   158: ldc2_w -821726201
    //   161: l2i
    //   162: ldc 1105976547
    //   164: ixor
    //   165: ixor
    //   166: lookupswitch default -> 342, -1703469966 -> 192, 504568717 -> 151
    //   192: putstatic bigname/zprestige/webhack/features/modules/Client/ClickGui$rainbowMode.Static : Lbigname/zprestige/webhack/features/modules/Client/ClickGui$rainbowMode;
    //   195: ldc2_w -2091678858
    //   198: l2i
    //   199: ldc -2091678857
    //   201: ixor
    //   202: anewarray bigname/zprestige/webhack/features/modules/Client/ClickGui$rainbowMode
    //   205: dup
    //   206: ldc2_w 641122318
    //   209: l2i
    //   210: ldc 641122318
    //   212: ixor
    //   213: getstatic Perryc.1 : I
    //   216: ifeq -> 229
    //   219: ldc2_w 1471384684
    //   222: l2i
    //   223: ldc 1059292192
    //   225: ixor
    //   226: goto -> 236
    //   229: ldc2_w -711584963
    //   232: l2i
    //   233: ldc 1373894968
    //   235: ixor
    //   236: ldc2_w 1009682125
    //   239: l2i
    //   240: ldc 357867265
    //   242: ixor
    //   243: ixor
    //   244: lookupswitch default -> 272, 68290579 -> 229, 1105858944 -> 340
    //   272: getstatic bigname/zprestige/webhack/features/modules/Client/ClickGui$rainbowMode.Static : Lbigname/zprestige/webhack/features/modules/Client/ClickGui$rainbowMode;
    //   275: aastore
    //   276: getstatic Perryc.0 : I
    //   279: ifle -> 292
    //   282: ldc2_w 1342218596
    //   285: l2i
    //   286: ldc 1113876704
    //   288: ixor
    //   289: goto -> 299
    //   292: ldc2_w -1239354411
    //   295: l2i
    //   296: ldc 767001710
    //   298: ixor
    //   299: ldc2_w 309084060
    //   302: l2i
    //   303: ldc 1920641926
    //   305: ixor
    //   306: ixor
    //   307: lookupswitch default -> 332, 87565934 -> 292, 1920097694 -> 336
    //   332: putstatic bigname/zprestige/webhack/features/modules/Client/ClickGui$rainbowMode.$VALUES : [Lbigname/zprestige/webhack/features/modules/Client/ClickGui$rainbowMode;
    //   335: return
    //   336: aconst_null
    //   337: athrow
    //   338: aconst_null
    //   339: athrow
    //   340: aconst_null
    //   341: athrow
    //   342: aconst_null
    //   343: athrow
    //   344: aconst_null
    //   345: athrow
  }
}


/* Location:              C:\Users\alex\Desktop\webhack\WebHack-0.8-obf_sussy_1.jar!\bigname\zprestige\webhack\features\modules\Client\ClickGui$rainbowMode.class
 * Java compiler version: 8 (52.0)
 * JD-Core Version:       1.1.3
 */