package bigname.zprestige.webhack.features.modules.Client;

import Perryc;

public enum ClickGui$Settings {
  GUIGRADIENT, GUIBACKGROUND, CLICKGUI;
  
  public static ClickGui$Settings[] $VALUES;
  
  static {
    // Byte code:
    //   0: new bigname/zprestige/webhack/features/modules/Client/ClickGui$Settings
    //   3: dup
    //   4: ldc 'ﻁ㌿ﺙㅏ䂹ၹ์荞'
    //   6: getstatic Perryc.0 : I
    //   9: ifle -> 22
    //   12: ldc2_w 979517991
    //   15: l2i
    //   16: ldc 1348244427
    //   18: ixor
    //   19: goto -> 29
    //   22: ldc2_w -44396437
    //   25: l2i
    //   26: ldc -242713099
    //   28: ixor
    //   29: ldc2_w 259901076
    //   32: l2i
    //   33: ldc -1233781869
    //   35: ixor
    //   36: ixor
    //   37: lookupswitch default -> 64, -1133268977 -> 22, -751375125 -> 876
    //   64: invokestatic 0 : (Ljava/lang/String;)Ljava/lang/String;
    //   67: ldc2_w 1178485765
    //   70: l2i
    //   71: ldc 1178485765
    //   73: ixor
    //   74: getstatic Perryc.1 : I
    //   77: ifeq -> 90
    //   80: ldc2_w 1037196373
    //   83: l2i
    //   84: ldc 458999896
    //   86: ixor
    //   87: goto -> 97
    //   90: ldc2_w -875109859
    //   93: l2i
    //   94: ldc -2072899013
    //   96: ixor
    //   97: ldc2_w -1573726608
    //   100: l2i
    //   101: ldc 21950932
    //   103: ixor
    //   104: ixor
    //   105: lookupswitch default -> 892, -2047495255 -> 90, -321333374 -> 132
    //   132: invokespecial <init> : (Ljava/lang/String;I)V
    //   135: getstatic Perryc.1 : I
    //   138: ifeq -> 151
    //   141: ldc2_w -268762067
    //   144: l2i
    //   145: ldc 809873596
    //   147: ixor
    //   148: goto -> 158
    //   151: ldc2_w 1889481707
    //   154: l2i
    //   155: ldc 1922665500
    //   157: ixor
    //   158: ldc2_w 1494237839
    //   161: l2i
    //   162: ldc 1497945828
    //   164: ixor
    //   165: ixor
    //   166: lookupswitch default -> 894, -538566406 -> 151, 39725980 -> 192
    //   192: putstatic bigname/zprestige/webhack/features/modules/Client/ClickGui$Settings.CLICKGUI : Lbigname/zprestige/webhack/features/modules/Client/ClickGui$Settings;
    //   195: new bigname/zprestige/webhack/features/modules/Client/ClickGui$Settings
    //   198: dup
    //   199: ldc 'ﻅ㌦ﺙㅋ䂠ၿ๝荞芝᱂䘍'
    //   201: getstatic Perryc.1 : I
    //   204: ifeq -> 217
    //   207: ldc2_w -1805223493
    //   210: l2i
    //   211: ldc -863485952
    //   213: ixor
    //   214: goto -> 224
    //   217: ldc2_w -2081930166
    //   220: l2i
    //   221: ldc -1580065856
    //   223: ixor
    //   224: ldc2_w -2047652412
    //   227: l2i
    //   228: ldc -1718370732
    //   230: ixor
    //   231: ixor
    //   232: lookupswitch default -> 896, 1046129690 -> 260, 1150208555 -> 217
    //   260: invokestatic 0 : (Ljava/lang/String;)Ljava/lang/String;
    //   263: ldc2_w 724348646
    //   266: l2i
    //   267: ldc 724348647
    //   269: ixor
    //   270: getstatic Perryc.c : I
    //   273: iflt -> 286
    //   276: ldc2_w 1002663710
    //   279: l2i
    //   280: ldc -1260434301
    //   282: ixor
    //   283: goto -> 293
    //   286: ldc2_w -1738397019
    //   289: l2i
    //   290: ldc -116139868
    //   292: ixor
    //   293: ldc2_w 1384317976
    //   296: l2i
    //   297: ldc -930854249
    //   299: ixor
    //   300: ixor
    //   301: lookupswitch default -> 880, -76104562 -> 328, 354118930 -> 286
    //   328: invokespecial <init> : (Ljava/lang/String;I)V
    //   331: getstatic Perryc.0 : I
    //   334: ifle -> 347
    //   337: ldc2_w -662546607
    //   340: l2i
    //   341: ldc 816190622
    //   343: ixor
    //   344: goto -> 354
    //   347: ldc2_w 1866244809
    //   350: l2i
    //   351: ldc 1904675039
    //   353: ixor
    //   354: ldc2_w 604820538
    //   357: l2i
    //   358: ldc -2033830206
    //   360: ixor
    //   361: ixor
    //   362: lookupswitch default -> 388, 701244980 -> 347, 1257152823 -> 884
    //   388: putstatic bigname/zprestige/webhack/features/modules/Client/ClickGui$Settings.GUIGRADIENT : Lbigname/zprestige/webhack/features/modules/Client/ClickGui$Settings;
    //   391: new bigname/zprestige/webhack/features/modules/Client/ClickGui$Settings
    //   394: dup
    //   395: ldc 'ﻅ㌦ﺙㅎ䂳ၽ๒荐芊᱃䘌ਉ㌦'
    //   397: getstatic Perryc.c : I
    //   400: iflt -> 413
    //   403: ldc2_w 2119118918
    //   406: l2i
    //   407: ldc 254082280
    //   409: ixor
    //   410: goto -> 420
    //   413: ldc2_w 754411145
    //   416: l2i
    //   417: ldc -1657344508
    //   419: ixor
    //   420: ldc2_w -156951992
    //   423: l2i
    //   424: ldc 338515635
    //   426: ixor
    //   427: ixor
    //   428: lookupswitch default -> 878, -1813807019 -> 413, 1397343350 -> 456
    //   456: invokestatic 0 : (Ljava/lang/String;)Ljava/lang/String;
    //   459: ldc2_w -1176293670
    //   462: l2i
    //   463: ldc -1176293672
    //   465: ixor
    //   466: getstatic Perryc.1 : I
    //   469: ifeq -> 482
    //   472: ldc2_w 1214913382
    //   475: l2i
    //   476: ldc 1164486028
    //   478: ixor
    //   479: goto -> 489
    //   482: ldc2_w -176417898
    //   485: l2i
    //   486: ldc -786663892
    //   488: ixor
    //   489: ldc2_w -1985639955
    //   492: l2i
    //   493: ldc -1728245468
    //   495: ixor
    //   496: ixor
    //   497: lookupswitch default -> 524, -147174739 -> 482, 475670051 -> 890
    //   524: invokespecial <init> : (Ljava/lang/String;I)V
    //   527: getstatic Perryc.1 : I
    //   530: ifeq -> 543
    //   533: ldc2_w -316914325
    //   536: l2i
    //   537: ldc -1797103237
    //   539: ixor
    //   540: goto -> 550
    //   543: ldc2_w 426536807
    //   546: l2i
    //   547: ldc 1703230957
    //   549: ixor
    //   550: ldc2_w -1748605238
    //   553: l2i
    //   554: ldc -2088132764
    //   556: ixor
    //   557: ixor
    //   558: lookupswitch default -> 886, 1755753252 -> 584, 1840373182 -> 543
    //   584: putstatic bigname/zprestige/webhack/features/modules/Client/ClickGui$Settings.GUIBACKGROUND : Lbigname/zprestige/webhack/features/modules/Client/ClickGui$Settings;
    //   587: ldc2_w -1046197055
    //   590: l2i
    //   591: ldc -1046197054
    //   593: ixor
    //   594: anewarray bigname/zprestige/webhack/features/modules/Client/ClickGui$Settings
    //   597: dup
    //   598: ldc2_w 826435937
    //   601: l2i
    //   602: ldc 826435937
    //   604: ixor
    //   605: getstatic Perryc.1 : I
    //   608: ifeq -> 621
    //   611: ldc2_w -407575390
    //   614: l2i
    //   615: ldc -344314389
    //   617: ixor
    //   618: goto -> 628
    //   621: ldc2_w 693598219
    //   624: l2i
    //   625: ldc 675151412
    //   627: ixor
    //   628: ldc2_w -959728111
    //   631: l2i
    //   632: ldc -1792153965
    //   634: ixor
    //   635: ixor
    //   636: lookupswitch default -> 664, -853566037 -> 621, 1596496331 -> 872
    //   664: getstatic bigname/zprestige/webhack/features/modules/Client/ClickGui$Settings.CLICKGUI : Lbigname/zprestige/webhack/features/modules/Client/ClickGui$Settings;
    //   667: aastore
    //   668: dup
    //   669: ldc2_w -1594730705
    //   672: l2i
    //   673: ldc -1594730706
    //   675: ixor
    //   676: getstatic Perryc.1 : I
    //   679: ifeq -> 692
    //   682: ldc2_w 385056585
    //   685: l2i
    //   686: ldc -1390878473
    //   688: ixor
    //   689: goto -> 699
    //   692: ldc2_w -53202442
    //   695: l2i
    //   696: ldc 801701251
    //   698: ixor
    //   699: ldc2_w 531230856
    //   702: l2i
    //   703: ldc 1426660339
    //   705: ixor
    //   706: ixor
    //   707: lookupswitch default -> 888, -1715722482 -> 732, -246713147 -> 692
    //   732: getstatic bigname/zprestige/webhack/features/modules/Client/ClickGui$Settings.GUIGRADIENT : Lbigname/zprestige/webhack/features/modules/Client/ClickGui$Settings;
    //   735: aastore
    //   736: dup
    //   737: ldc2_w 1326952471
    //   740: l2i
    //   741: ldc 1326952469
    //   743: ixor
    //   744: getstatic Perryc.1 : I
    //   747: ifeq -> 760
    //   750: ldc2_w -574861721
    //   753: l2i
    //   754: ldc -580934353
    //   756: ixor
    //   757: goto -> 767
    //   760: ldc2_w -1779933489
    //   763: l2i
    //   764: ldc 798787251
    //   766: ixor
    //   767: ldc2_w -1304519010
    //   770: l2i
    //   771: ldc_w -241423648
    //   774: ixor
    //   775: ixor
    //   776: lookupswitch default -> 804, 1128357686 -> 882, 1876832115 -> 760
    //   804: getstatic bigname/zprestige/webhack/features/modules/Client/ClickGui$Settings.GUIBACKGROUND : Lbigname/zprestige/webhack/features/modules/Client/ClickGui$Settings;
    //   807: aastore
    //   808: getstatic Perryc.0 : I
    //   811: ifle -> 825
    //   814: ldc2_w 373995515
    //   817: l2i
    //   818: ldc_w 426833979
    //   821: ixor
    //   822: goto -> 833
    //   825: ldc2_w -836397337
    //   828: l2i
    //   829: ldc_w -488404368
    //   832: ixor
    //   833: ldc2_w -1801239214
    //   836: l2i
    //   837: ldc_w 1951716666
    //   840: ixor
    //   841: ixor
    //   842: lookupswitch default -> 874, -869167873 -> 868, -271720536 -> 825
    //   868: putstatic bigname/zprestige/webhack/features/modules/Client/ClickGui$Settings.$VALUES : [Lbigname/zprestige/webhack/features/modules/Client/ClickGui$Settings;
    //   871: return
    //   872: aconst_null
    //   873: athrow
    //   874: aconst_null
    //   875: athrow
    //   876: aconst_null
    //   877: athrow
    //   878: aconst_null
    //   879: athrow
    //   880: aconst_null
    //   881: athrow
    //   882: aconst_null
    //   883: athrow
    //   884: aconst_null
    //   885: athrow
    //   886: aconst_null
    //   887: athrow
    //   888: aconst_null
    //   889: athrow
    //   890: aconst_null
    //   891: athrow
    //   892: aconst_null
    //   893: athrow
    //   894: aconst_null
    //   895: athrow
    //   896: aconst_null
    //   897: athrow
  }
}


/* Location:              C:\Users\alex\Desktop\webhack\WebHack-0.8-obf_sussy_1.jar!\bigname\zprestige\webhack\features\modules\Client\ClickGui$Settings.class
 * Java compiler version: 8 (52.0)
 * JD-Core Version:       1.1.3
 */