package bigname.zprestige.webhack.features.modules.Client;

import Perryc;

public enum ClickGui$rainbowModeArray {
  Up, Static;
  
  public static ClickGui$rainbowModeArray[] $VALUES;
  
  static {
    // Byte code:
    //   0: new bigname/zprestige/webhack/features/modules/Client/ClickGui$rainbowModeArray
    //   3: dup
    //   4: ldc '?㌇?ㅸ悼぀'
    //   6: getstatic Perryc.1 : I
    //   9: ifeq -> 22
    //   12: ldc2_w 1347781843
    //   15: l2i
    //   16: ldc -502634380
    //   18: ixor
    //   19: goto -> 29
    //   22: ldc2_w 1893502667
    //   25: l2i
    //   26: ldc 2145543064
    //   28: ixor
    //   29: ldc2_w -2086569114
    //   32: l2i
    //   33: ldc -314793649
    //   35: ixor
    //   36: ixor
    //   37: lookupswitch default -> 64, -1399424889 -> 22, -591251826 -> 606
    //   64: invokestatic 0 : (Ljava/lang/String;)Ljava/lang/String;
    //   67: ldc2_w 491946703
    //   70: l2i
    //   71: ldc 491946703
    //   73: ixor
    //   74: getstatic Perryc.0 : I
    //   77: ifle -> 90
    //   80: ldc2_w 2105406839
    //   83: l2i
    //   84: ldc 784559950
    //   86: ixor
    //   87: goto -> 97
    //   90: ldc2_w 1129776189
    //   93: l2i
    //   94: ldc 1997646614
    //   96: ixor
    //   97: ldc2_w 462859163
    //   100: l2i
    //   101: ldc -870209586
    //   103: ixor
    //   104: ixor
    //   105: lookupswitch default -> 132, -2079746452 -> 608, -1340714327 -> 90
    //   132: invokespecial <init> : (Ljava/lang/String;I)V
    //   135: getstatic Perryc.1 : I
    //   138: ifeq -> 151
    //   141: ldc2_w -2033081203
    //   144: l2i
    //   145: ldc -803619037
    //   147: ixor
    //   148: goto -> 158
    //   151: ldc2_w 1953512305
    //   154: l2i
    //   155: ldc -1322675154
    //   157: ixor
    //   158: ldc2_w 337018628
    //   161: l2i
    //   162: ldc 1506221562
    //   164: ixor
    //   165: ixor
    //   166: lookupswitch default -> 192, -1120395913 -> 151, 454654288 -> 600
    //   192: putstatic bigname/zprestige/webhack/features/modules/Client/ClickGui$rainbowModeArray.Static : Lbigname/zprestige/webhack/features/modules/Client/ClickGui$rainbowModeArray;
    //   195: new bigname/zprestige/webhack/features/modules/Client/ClickGui$rainbowModeArray
    //   198: dup
    //   199: ldc '?㌃'
    //   201: getstatic Perryc.c : I
    //   204: iflt -> 217
    //   207: ldc2_w -1101219153
    //   210: l2i
    //   211: ldc -302997213
    //   213: ixor
    //   214: goto -> 224
    //   217: ldc2_w -1058094484
    //   220: l2i
    //   221: ldc 2067782401
    //   223: ixor
    //   224: ldc2_w 26185315
    //   227: l2i
    //   228: ldc -938185867
    //   230: ixor
    //   231: ixor
    //   232: lookupswitch default -> 260, -1816217034 -> 217, -1707606374 -> 610
    //   260: invokestatic 0 : (Ljava/lang/String;)Ljava/lang/String;
    //   263: ldc2_w 1740912959
    //   266: l2i
    //   267: ldc 1740912958
    //   269: ixor
    //   270: getstatic Perryc.c : I
    //   273: iflt -> 286
    //   276: ldc2_w 242356251
    //   279: l2i
    //   280: ldc 1469279700
    //   282: ixor
    //   283: goto -> 293
    //   286: ldc2_w -1541249965
    //   289: l2i
    //   290: ldc -288337933
    //   292: ixor
    //   293: ldc2_w -512032303
    //   296: l2i
    //   297: ldc 1541681238
    //   299: ixor
    //   300: ixor
    //   301: lookupswitch default -> 616, -478262200 -> 286, -261285337 -> 328
    //   328: invokespecial <init> : (Ljava/lang/String;I)V
    //   331: getstatic Perryc.0 : I
    //   334: ifle -> 347
    //   337: ldc2_w -673190980
    //   340: l2i
    //   341: ldc 753688818
    //   343: ixor
    //   344: goto -> 354
    //   347: ldc2_w 233681353
    //   350: l2i
    //   351: ldc -306935298
    //   353: ixor
    //   354: ldc2_w 1229286024
    //   357: l2i
    //   358: ldc 1174233846
    //   360: ixor
    //   361: ixor
    //   362: lookupswitch default -> 612, -320786359 -> 388, -141851856 -> 347
    //   388: putstatic bigname/zprestige/webhack/features/modules/Client/ClickGui$rainbowModeArray.Up : Lbigname/zprestige/webhack/features/modules/Client/ClickGui$rainbowModeArray;
    //   391: ldc2_w 1734136165
    //   394: l2i
    //   395: ldc 1734136167
    //   397: ixor
    //   398: anewarray bigname/zprestige/webhack/features/modules/Client/ClickGui$rainbowModeArray
    //   401: dup
    //   402: ldc2_w 909972926
    //   405: l2i
    //   406: ldc 909972926
    //   408: ixor
    //   409: getstatic Perryc.0 : I
    //   412: ifle -> 425
    //   415: ldc2_w 521142715
    //   418: l2i
    //   419: ldc -555067389
    //   421: ixor
    //   422: goto -> 432
    //   425: ldc2_w 1684631984
    //   428: l2i
    //   429: ldc 1550179130
    //   431: ixor
    //   432: ldc2_w -393631475
    //   435: l2i
    //   436: ldc 200390533
    //   438: ixor
    //   439: ixor
    //   440: lookupswitch default -> 604, -613108734 -> 468, 578963248 -> 425
    //   468: getstatic bigname/zprestige/webhack/features/modules/Client/ClickGui$rainbowModeArray.Static : Lbigname/zprestige/webhack/features/modules/Client/ClickGui$rainbowModeArray;
    //   471: aastore
    //   472: dup
    //   473: ldc2_w 205598476
    //   476: l2i
    //   477: ldc 205598477
    //   479: ixor
    //   480: getstatic Perryc.1 : I
    //   483: ifeq -> 496
    //   486: ldc2_w -426646131
    //   489: l2i
    //   490: ldc 555123129
    //   492: ixor
    //   493: goto -> 503
    //   496: ldc2_w -342043798
    //   499: l2i
    //   500: ldc -329174106
    //   502: ixor
    //   503: ldc2_w -634163243
    //   506: l2i
    //   507: ldc 952176875
    //   509: ixor
    //   510: ixor
    //   511: lookupswitch default -> 536, 628431626 -> 614, 2031283948 -> 496
    //   536: getstatic bigname/zprestige/webhack/features/modules/Client/ClickGui$rainbowModeArray.Up : Lbigname/zprestige/webhack/features/modules/Client/ClickGui$rainbowModeArray;
    //   539: aastore
    //   540: getstatic Perryc.0 : I
    //   543: ifle -> 556
    //   546: ldc2_w 111232974
    //   549: l2i
    //   550: ldc -1143257587
    //   552: ixor
    //   553: goto -> 563
    //   556: ldc2_w 1355531546
    //   559: l2i
    //   560: ldc 238931604
    //   562: ixor
    //   563: ldc2_w -1842726540
    //   566: l2i
    //   567: ldc -2075742085
    //   569: ixor
    //   570: ixor
    //   571: lookupswitch default -> 602, -1424586548 -> 556, 1218085505 -> 596
    //   596: putstatic bigname/zprestige/webhack/features/modules/Client/ClickGui$rainbowModeArray.$VALUES : [Lbigname/zprestige/webhack/features/modules/Client/ClickGui$rainbowModeArray;
    //   599: return
    //   600: aconst_null
    //   601: athrow
    //   602: aconst_null
    //   603: athrow
    //   604: aconst_null
    //   605: athrow
    //   606: aconst_null
    //   607: athrow
    //   608: aconst_null
    //   609: athrow
    //   610: aconst_null
    //   611: athrow
    //   612: aconst_null
    //   613: athrow
    //   614: aconst_null
    //   615: athrow
    //   616: aconst_null
    //   617: athrow
  }
}


/* Location:              C:\Users\alex\Desktop\webhack\WebHack-0.8-obf_sussy_1.jar!\bigname\zprestige\webhack\features\modules\Client\ClickGui$rainbowModeArray.class
 * Java compiler version: 8 (52.0)
 * JD-Core Version:       1.1.3
 */