package bigname.zprestige.webhack.features.modules.Misc;

import Perryc;

public enum MCP$Mode {
  MIDDLECLICK;
  
  public static MCP$Mode[] $VALUES;
  
  static {
    // Byte code:
    //   0: new bigname/zprestige/webhack/features/modules/Misc/MCP$Mode
    //   3: dup
    //   4: ldc '⬇㌺⭬ㅈ賶얳๚嚣芑퀇鏚'
    //   6: getstatic Perryc.c : I
    //   9: iflt -> 22
    //   12: ldc2_w -574756189
    //   15: l2i
    //   16: ldc 61600960
    //   18: ixor
    //   19: goto -> 29
    //   22: ldc2_w 1408264261
    //   25: l2i
    //   26: ldc 1303759717
    //   28: ixor
    //   29: ldc2_w 1293147887
    //   32: l2i
    //   33: ldc 430398488
    //   35: ixor
    //   36: ixor
    //   37: lookupswitch default -> 64, -1969054572 -> 340, -1098844766 -> 22
    //   64: invokestatic 0 : (Ljava/lang/String;)Ljava/lang/String;
    //   67: ldc2_w 717073726
    //   70: l2i
    //   71: ldc 717073726
    //   73: ixor
    //   74: getstatic Perryc.c : I
    //   77: iflt -> 90
    //   80: ldc2_w 2131195515
    //   83: l2i
    //   84: ldc -1154113742
    //   86: ixor
    //   87: goto -> 97
    //   90: ldc2_w -1121714389
    //   93: l2i
    //   94: ldc -638679305
    //   96: ixor
    //   97: ldc2_w 1303083177
    //   100: l2i
    //   101: ldc 97283717
    //   103: ixor
    //   104: ixor
    //   105: lookupswitch default -> 132, -1940521115 -> 342, -966141041 -> 90
    //   132: invokespecial <init> : (Ljava/lang/String;I)V
    //   135: getstatic Perryc.c : I
    //   138: iflt -> 151
    //   141: ldc2_w -1533416866
    //   144: l2i
    //   145: ldc 871080527
    //   147: ixor
    //   148: goto -> 158
    //   151: ldc2_w -1293452378
    //   154: l2i
    //   155: ldc 1910329553
    //   157: ixor
    //   158: ldc2_w -297295184
    //   161: l2i
    //   162: ldc -214377191
    //   164: ixor
    //   165: ixor
    //   166: lookupswitch default -> 344, -1978845256 -> 151, -565881634 -> 192
    //   192: putstatic bigname/zprestige/webhack/features/modules/Misc/MCP$Mode.MIDDLECLICK : Lbigname/zprestige/webhack/features/modules/Misc/MCP$Mode;
    //   195: ldc2_w 263130791
    //   198: l2i
    //   199: ldc 263130790
    //   201: ixor
    //   202: anewarray bigname/zprestige/webhack/features/modules/Misc/MCP$Mode
    //   205: dup
    //   206: ldc2_w 477436608
    //   209: l2i
    //   210: ldc 477436608
    //   212: ixor
    //   213: getstatic Perryc.c : I
    //   216: iflt -> 229
    //   219: ldc2_w -2079964079
    //   222: l2i
    //   223: ldc 1647046266
    //   225: ixor
    //   226: goto -> 236
    //   229: ldc2_w 1005072773
    //   232: l2i
    //   233: ldc -823448529
    //   235: ixor
    //   236: ldc2_w -580074243
    //   239: l2i
    //   240: ldc -1696500689
    //   242: ixor
    //   243: ixor
    //   244: lookupswitch default -> 272, -1583342855 -> 336, 336879235 -> 229
    //   272: getstatic bigname/zprestige/webhack/features/modules/Misc/MCP$Mode.MIDDLECLICK : Lbigname/zprestige/webhack/features/modules/Misc/MCP$Mode;
    //   275: aastore
    //   276: getstatic Perryc.1 : I
    //   279: ifeq -> 292
    //   282: ldc2_w -637678723
    //   285: l2i
    //   286: ldc 449599142
    //   288: ixor
    //   289: goto -> 299
    //   292: ldc2_w -100898455
    //   295: l2i
    //   296: ldc 2126673701
    //   298: ixor
    //   299: ldc2_w -1562885478
    //   302: l2i
    //   303: ldc -295749989
    //   305: ixor
    //   306: ixor
    //   307: lookupswitch default -> 332, -1883837990 -> 338, -173013904 -> 292
    //   332: putstatic bigname/zprestige/webhack/features/modules/Misc/MCP$Mode.$VALUES : [Lbigname/zprestige/webhack/features/modules/Misc/MCP$Mode;
    //   335: return
    //   336: aconst_null
    //   337: athrow
    //   338: aconst_null
    //   339: athrow
    //   340: aconst_null
    //   341: athrow
    //   342: aconst_null
    //   343: athrow
    //   344: aconst_null
    //   345: athrow
  }
}


/* Location:              C:\Users\alex\Desktop\webhack\WebHack-0.8-obf_sussy_1.jar!\bigname\zprestige\webhack\features\modules\Misc\MCP$Mode.class
 * Java compiler version: 8 (52.0)
 * JD-Core Version:       1.1.3
 */