package bigname.zprestige.webhack.features.setting;

import Perry1;
import Perryc;

public class Bind {
  public int key;
  
  public String toString() {
    if (Perryc.1 <= 0) {
      null;
    } else {
      if (null != null)
        throw (Throwable)null; 
      null;
    } 
    if (null != null)
      throw (Throwable)null; 
    null;
  }
  
  public static Bind none() {
    if (Perryc.1 <= 0) {
      null;
    } else {
      if (null != null)
        throw (Throwable)null; 
      null;
    } 
    if (null != null)
      throw (Throwable)null; 
    null;
  }
  
  public void setKey(int paramInt) {
    Perry1.D(this, (int)1766882477L ^ 0x708F7FE4, paramInt);
  }
  
  public Bind(int key) {
    // Byte code:
    //   0: getstatic Perryc.0 : I
    //   3: ifle -> 16
    //   6: ldc2_w -363190987
    //   9: l2i
    //   10: ldc 1151529270
    //   12: ixor
    //   13: goto -> 23
    //   16: ldc2_w 1810006897
    //   19: l2i
    //   20: ldc -473748417
    //   22: ixor
    //   23: ldc2_w 1866360932
    //   26: l2i
    //   27: ldc -1952716728
    //   29: ixor
    //   30: ixor
    //   31: lookupswitch default -> 56, -1612091315 -> 16, 1247630383 -> 306
    //   56: aload_0
    //   57: getstatic Perryc.c : I
    //   60: iflt -> 73
    //   63: ldc2_w -892970272
    //   66: l2i
    //   67: ldc -142984549
    //   69: ixor
    //   70: goto -> 80
    //   73: ldc2_w 194321067
    //   76: l2i
    //   77: ldc 1008678005
    //   79: ixor
    //   80: ldc2_w -1278842100
    //   83: l2i
    //   84: ldc -971544443
    //   86: ixor
    //   87: ixor
    //   88: lookupswitch default -> 308, 1113271639 -> 116, 1215128562 -> 73
    //   116: invokespecial <init> : ()V
    //   119: getstatic Perryc.0 : I
    //   122: ifle -> 135
    //   125: ldc2_w 2052038929
    //   128: l2i
    //   129: ldc 1751399226
    //   131: ixor
    //   132: goto -> 142
    //   135: ldc2_w -1475913169
    //   138: l2i
    //   139: ldc 1725286452
    //   141: ixor
    //   142: ldc2_w 1086373871
    //   145: l2i
    //   146: ldc -1740657356
    //   148: ixor
    //   149: ixor
    //   150: lookupswitch default -> 304, -892040976 -> 135, 372080832 -> 176
    //   176: aload_0
    //   177: getstatic Perryc.c : I
    //   180: iflt -> 193
    //   183: ldc2_w -1575230450
    //   186: l2i
    //   187: ldc 103345027
    //   189: ixor
    //   190: goto -> 200
    //   193: ldc2_w -924714133
    //   196: l2i
    //   197: ldc -1791237815
    //   199: ixor
    //   200: ldc2_w -1794336362
    //   203: l2i
    //   204: ldc 15642441
    //   206: ixor
    //   207: ixor
    //   208: lookupswitch default -> 236, -1983415417 -> 193, 835795282 -> 300
    //   236: iload_1
    //   237: getstatic Perryc.1 : I
    //   240: ifeq -> 254
    //   243: ldc2_w -1683596234
    //   246: l2i
    //   247: ldc_w -1779951518
    //   250: ixor
    //   251: goto -> 262
    //   254: ldc2_w -983741146
    //   257: l2i
    //   258: ldc_w 666004943
    //   261: ixor
    //   262: ldc2_w -270799234
    //   265: l2i
    //   266: ldc_w 821737830
    //   269: ixor
    //   270: ixor
    //   271: lookupswitch default -> 296, -781249716 -> 302, 262012876 -> 254
    //   296: putfield key : I
    //   299: return
    //   300: aconst_null
    //   301: athrow
    //   302: aconst_null
    //   303: athrow
    //   304: aconst_null
    //   305: athrow
    //   306: aconst_null
    //   307: athrow
    //   308: aconst_null
    //   309: athrow
    // Local variable table:
    //   start	length	slot	name	descriptor
    //   0	300	0	this	Lbigname/zprestige/webhack/features/setting/Bind;
    //   0	300	1	key	I
  }
  
  public boolean isDown() {
    return Perry1.4y(this, (int)1307095307L ^ 0x64F4D7B4);
  }
  
  public int getKey() {
    return Perry1.34(this, (int)1984182947L ^ 0xA2986F5);
  }
  
  public String capitalise(String str) {
    // Byte code:
    //   0: goto -> 8
    //   3: dup
    //   4: ifnull -> 1177
    //   7: athrow
    //   8: aconst_null
    //   9: getstatic Perryc.c : I
    //   12: ifge -> 1169
    //   15: pop
    //   16: aconst_null
    //   17: goto -> 1161
    //   20: nop
    //   21: nop
    //   22: nop
    //   23: athrow
    //   24: getstatic Perryc.c : I
    //   27: iflt -> 41
    //   30: ldc2_w 131939357
    //   33: l2i
    //   34: ldc_w -1886354045
    //   37: ixor
    //   38: goto -> 49
    //   41: ldc2_w 523414101
    //   44: l2i
    //   45: ldc_w -1578496870
    //   48: ixor
    //   49: ldc2_w -887439873
    //   52: l2i
    //   53: ldc_w -1762629564
    //   56: ixor
    //   57: ixor
    //   58: lookupswitch default -> 84, -1617178640 -> 41, -710448091 -> 1140
    //   84: aload_1
    //   85: getstatic Perryc.c : I
    //   88: iflt -> 102
    //   91: ldc2_w -1104754196
    //   94: l2i
    //   95: ldc_w -1235955642
    //   98: ixor
    //   99: goto -> 110
    //   102: ldc2_w -1562302543
    //   105: l2i
    //   106: ldc_w 105904729
    //   109: ixor
    //   110: ldc2_w 1992559644
    //   113: l2i
    //   114: ldc_w -1890571902
    //   117: ixor
    //   118: ixor
    //   119: lookupswitch default -> 1126, -236569548 -> 102, 1564145782 -> 144
    //   144: goto -> 148
    //   147: athrow
    //   148: invokevirtual isEmpty : ()Z
    //   151: goto -> 155
    //   154: athrow
    //   155: ifeq -> 169
    //   158: ldc2_w -1418480964
    //   161: l2i
    //   162: ldc_w -444364389
    //   165: ixor
    //   166: goto -> 177
    //   169: ldc2_w -550659142
    //   172: l2i
    //   173: ldc_w -1847746404
    //   176: ixor
    //   177: ldc2_w 1952536682
    //   180: l2i
    //   181: ldc_w 1553199199
    //   184: ixor
    //   185: ixor
    //   186: tableswitch default -> 158, 1711444754 -> 208, 1711444755 -> 212
    //   208: ldc_w ''
    //   211: areturn
    //   212: new java/lang/StringBuilder
    //   215: dup
    //   216: getstatic Perryc.0 : I
    //   219: ifle -> 233
    //   222: ldc2_w -3297748
    //   225: l2i
    //   226: ldc_w 1004451675
    //   229: ixor
    //   230: goto -> 241
    //   233: ldc2_w -1539616965
    //   236: l2i
    //   237: ldc_w 373960098
    //   240: ixor
    //   241: ldc2_w 1925145276
    //   244: l2i
    //   245: ldc_w 1895319028
    //   248: ixor
    //   249: ixor
    //   250: lookupswitch default -> 276, -967557569 -> 1150, 1311990816 -> 233
    //   276: goto -> 280
    //   279: athrow
    //   280: invokespecial <init> : ()V
    //   283: goto -> 287
    //   286: athrow
    //   287: getstatic Perryc.0 : I
    //   290: ifle -> 304
    //   293: ldc2_w 1456508088
    //   296: l2i
    //   297: ldc_w -835332394
    //   300: ixor
    //   301: goto -> 312
    //   304: ldc2_w -1374062310
    //   307: l2i
    //   308: ldc_w 1267080110
    //   311: ixor
    //   312: ldc2_w -1487226296
    //   315: l2i
    //   316: ldc_w -2062652249
    //   319: ixor
    //   320: ixor
    //   321: lookupswitch default -> 1148, -1162769279 -> 304, -942951333 -> 348
    //   348: aload_1
    //   349: ldc2_w 1657570501
    //   352: l2i
    //   353: ldc_w 1657570501
    //   356: ixor
    //   357: getstatic Perryc.c : I
    //   360: iflt -> 374
    //   363: ldc2_w -1510832869
    //   366: l2i
    //   367: ldc_w 197272996
    //   370: ixor
    //   371: goto -> 382
    //   374: ldc2_w -52705815
    //   377: l2i
    //   378: ldc_w 1270859080
    //   381: ixor
    //   382: ldc2_w -616321747
    //   385: l2i
    //   386: ldc_w -2137451622
    //   389: ixor
    //   390: ixor
    //   391: lookupswitch default -> 416, -169206264 -> 1144, 454888283 -> 374
    //   416: goto -> 420
    //   419: athrow
    //   420: invokevirtual charAt : (I)C
    //   423: goto -> 427
    //   426: athrow
    //   427: getstatic Perryc.0 : I
    //   430: ifle -> 444
    //   433: ldc2_w 2012355379
    //   436: l2i
    //   437: ldc_w 1204819700
    //   440: ixor
    //   441: goto -> 452
    //   444: ldc2_w -586425893
    //   447: l2i
    //   448: ldc_w 1196974915
    //   451: ixor
    //   452: ldc2_w -465622447
    //   455: l2i
    //   456: ldc_w -1623852901
    //   459: ixor
    //   460: ixor
    //   461: lookupswitch default -> 1124, -514234286 -> 488, 1260969741 -> 444
    //   488: goto -> 492
    //   491: athrow
    //   492: invokestatic toUpperCase : (C)C
    //   495: goto -> 499
    //   498: athrow
    //   499: getstatic Perryc.0 : I
    //   502: ifle -> 516
    //   505: ldc2_w -1215247015
    //   508: l2i
    //   509: ldc_w -1554781729
    //   512: ixor
    //   513: goto -> 524
    //   516: ldc2_w 878970515
    //   519: l2i
    //   520: ldc_w 2069377088
    //   523: ixor
    //   524: ldc2_w -764205952
    //   527: l2i
    //   528: ldc_w 1550030375
    //   531: ixor
    //   532: ixor
    //   533: lookupswitch default -> 1134, -1697409503 -> 516, -1054047116 -> 560
    //   560: goto -> 564
    //   563: athrow
    //   564: invokevirtual append : (C)Ljava/lang/StringBuilder;
    //   567: goto -> 571
    //   570: athrow
    //   571: getstatic Perryc.1 : I
    //   574: ifeq -> 588
    //   577: ldc2_w 229011428
    //   580: l2i
    //   581: ldc_w 2070944804
    //   584: ixor
    //   585: goto -> 596
    //   588: ldc2_w 179662451
    //   591: l2i
    //   592: ldc_w -577983824
    //   595: ixor
    //   596: ldc2_w 253637520
    //   599: l2i
    //   600: ldc_w 2017464072
    //   603: ixor
    //   604: ixor
    //   605: lookupswitch default -> 1128, -1603798949 -> 632, 25710424 -> 588
    //   632: aload_1
    //   633: getstatic Perryc.c : I
    //   636: iflt -> 650
    //   639: ldc2_w -1429554985
    //   642: l2i
    //   643: ldc_w 1861818995
    //   646: ixor
    //   647: goto -> 658
    //   650: ldc2_w 1986587953
    //   653: l2i
    //   654: ldc_w -2106352420
    //   657: ixor
    //   658: ldc2_w 950721685
    //   661: l2i
    //   662: ldc_w 1139071065
    //   665: ixor
    //   666: ixor
    //   667: lookupswitch default -> 1130, -1890224863 -> 692, -1082284440 -> 650
    //   692: goto -> 696
    //   695: athrow
    //   696: invokevirtual length : ()I
    //   699: goto -> 703
    //   702: athrow
    //   703: ldc2_w -1405516628
    //   706: l2i
    //   707: ldc_w -1405516627
    //   710: ixor
    //   711: if_icmpeq -> 725
    //   714: ldc2_w 2091273394
    //   717: l2i
    //   718: ldc_w -1891942429
    //   721: ixor
    //   722: goto -> 733
    //   725: ldc2_w -1147594859
    //   728: l2i
    //   729: ldc_w 1208247499
    //   732: ixor
    //   733: ldc2_w 1865998202
    //   736: l2i
    //   737: ldc_w -1644917316
    //   740: ixor
    //   741: ixor
    //   742: tableswitch default -> 714, 22094231 -> 764, 22094232 -> 978
    //   764: getstatic Perryc.0 : I
    //   767: ifle -> 781
    //   770: ldc2_w -77404529
    //   773: l2i
    //   774: ldc_w -424834053
    //   777: ixor
    //   778: goto -> 789
    //   781: ldc2_w 1213011329
    //   784: l2i
    //   785: ldc_w 1987381306
    //   788: ixor
    //   789: ldc2_w 1148671555
    //   792: l2i
    //   793: ldc_w 675123019
    //   796: ixor
    //   797: ixor
    //   798: lookupswitch default -> 1136, 1383253171 -> 824, 1904587900 -> 781
    //   824: aload_1
    //   825: ldc2_w -9730780
    //   828: l2i
    //   829: ldc_w -9730779
    //   832: ixor
    //   833: getstatic Perryc.c : I
    //   836: iflt -> 850
    //   839: ldc2_w 97641316
    //   842: l2i
    //   843: ldc_w 435060941
    //   846: ixor
    //   847: goto -> 858
    //   850: ldc2_w -18515114
    //   853: l2i
    //   854: ldc_w 1238423343
    //   857: ixor
    //   858: ldc2_w 1311550352
    //   861: l2i
    //   862: ldc_w 1996524340
    //   865: ixor
    //   866: ixor
    //   867: lookupswitch default -> 892, -1319737477 -> 850, 622019341 -> 1142
    //   892: goto -> 896
    //   895: athrow
    //   896: invokevirtual substring : (I)Ljava/lang/String;
    //   899: goto -> 903
    //   902: athrow
    //   903: getstatic Perryc.1 : I
    //   906: ifeq -> 920
    //   909: ldc2_w -920930718
    //   912: l2i
    //   913: ldc_w 1343556373
    //   916: ixor
    //   917: goto -> 928
    //   920: ldc2_w -2097354975
    //   923: l2i
    //   924: ldc_w 1360330122
    //   927: ixor
    //   928: ldc2_w 212439174
    //   931: l2i
    //   932: ldc_w -655317478
    //   935: ixor
    //   936: ixor
    //   937: lookupswitch default -> 964, 1297583083 -> 1138, 1369436665 -> 920
    //   964: goto -> 968
    //   967: athrow
    //   968: invokevirtual toLowerCase : ()Ljava/lang/String;
    //   971: goto -> 975
    //   974: athrow
    //   975: goto -> 981
    //   978: ldc_w ''
    //   981: getstatic Perryc.1 : I
    //   984: ifeq -> 998
    //   987: ldc2_w 1534438
    //   990: l2i
    //   991: ldc_w 1317134786
    //   994: ixor
    //   995: goto -> 1006
    //   998: ldc2_w 1054492329
    //   1001: l2i
    //   1002: ldc_w 1309907772
    //   1005: ixor
    //   1006: ldc2_w -629112476
    //   1009: l2i
    //   1010: ldc_w 1297850510
    //   1013: ixor
    //   1014: ixor
    //   1015: lookupswitch default -> 1040, -807753312 -> 998, -649221682 -> 1146
    //   1040: goto -> 1044
    //   1043: athrow
    //   1044: invokevirtual append : (Ljava/lang/String;)Ljava/lang/StringBuilder;
    //   1047: goto -> 1051
    //   1050: athrow
    //   1051: getstatic Perryc.c : I
    //   1054: iflt -> 1068
    //   1057: ldc2_w -396303870
    //   1060: l2i
    //   1061: ldc_w -1636975007
    //   1064: ixor
    //   1065: goto -> 1076
    //   1068: ldc2_w 767431278
    //   1071: l2i
    //   1072: ldc_w -1806151311
    //   1075: ixor
    //   1076: ldc2_w -50809083
    //   1079: l2i
    //   1080: ldc_w -1839562809
    //   1083: ixor
    //   1084: ixor
    //   1085: lookupswitch default -> 1112, 414160033 -> 1132, 761059578 -> 1068
    //   1112: goto -> 1116
    //   1115: athrow
    //   1116: invokevirtual toString : ()Ljava/lang/String;
    //   1119: goto -> 1123
    //   1122: athrow
    //   1123: areturn
    //   1124: aconst_null
    //   1125: athrow
    //   1126: aconst_null
    //   1127: athrow
    //   1128: aconst_null
    //   1129: athrow
    //   1130: aconst_null
    //   1131: athrow
    //   1132: aconst_null
    //   1133: athrow
    //   1134: aconst_null
    //   1135: athrow
    //   1136: aconst_null
    //   1137: athrow
    //   1138: aconst_null
    //   1139: athrow
    //   1140: aconst_null
    //   1141: athrow
    //   1142: aconst_null
    //   1143: athrow
    //   1144: aconst_null
    //   1145: athrow
    //   1146: aconst_null
    //   1147: athrow
    //   1148: aconst_null
    //   1149: athrow
    //   1150: aconst_null
    //   1151: athrow
    //   1152: pop
    //   1153: goto -> 24
    //   1156: pop
    //   1157: aconst_null
    //   1158: goto -> 1152
    //   1161: dup
    //   1162: ifnull -> 1152
    //   1165: checkcast java/lang/Throwable
    //   1168: athrow
    //   1169: dup
    //   1170: ifnull -> 1156
    //   1173: checkcast java/lang/Throwable
    //   1176: athrow
    //   1177: aconst_null
    //   1178: athrow
    // Local variable table:
    //   start	length	slot	name	descriptor
    //   24	1100	0	this	Lbigname/zprestige/webhack/features/setting/Bind;
    //   24	1100	1	str	Ljava/lang/String;
    // Exception table:
    //   from	to	target	type
    //   8	20	1161	java/lang/ArrayIndexOutOfBoundsException
    //   147	154	154	finally
    //   147	154	147	java/lang/IndexOutOfBoundsException
    //   148	154	154	java/lang/RuntimeException
    //   148	154	154	java/lang/AssertionError
    //   148	154	154	java/lang/IndexOutOfBoundsException
    //   280	286	286	finally
    //   280	286	3	finally
    //   280	286	286	java/util/ConcurrentModificationException
    //   280	286	286	java/lang/StringIndexOutOfBoundsException
    //   280	286	286	finally
    //   419	426	426	finally
    //   419	426	426	java/lang/IndexOutOfBoundsException
    //   419	426	419	finally
    //   419	426	3	finally
    //   420	426	426	java/lang/AssertionError
    //   492	498	498	finally
    //   492	498	498	java/lang/NegativeArraySizeException
    //   492	498	498	finally
    //   492	498	498	finally
    //   492	498	3	java/lang/NumberFormatException
    //   563	570	570	finally
    //   563	570	563	finally
    //   564	570	3	java/lang/IllegalArgumentException
    //   564	570	563	finally
    //   564	570	3	finally
    //   695	702	702	finally
    //   695	702	695	finally
    //   696	702	3	finally
    //   696	702	3	java/lang/IndexOutOfBoundsException
    //   696	702	695	finally
    //   895	902	902	finally
    //   895	902	895	finally
    //   895	902	3	finally
    //   895	902	902	finally
    //   896	902	902	finally
    //   967	974	974	finally
    //   967	974	967	java/lang/NullPointerException
    //   967	974	967	java/lang/StringIndexOutOfBoundsException
    //   968	974	3	java/lang/AssertionError
    //   968	974	3	java/util/NoSuchElementException
    //   1043	1050	1050	finally
    //   1043	1050	1043	finally
    //   1043	1050	3	finally
    //   1044	1050	1043	java/lang/ClassCastException
    //   1044	1050	1050	java/lang/NullPointerException
    //   1115	1122	1122	finally
    //   1115	1122	1122	finally
    //   1115	1122	3	finally
    //   1116	1122	3	finally
    //   1116	1122	1115	finally
    //   1161	1169	1161	java/util/ConcurrentModificationException
    //   1177	1179	3	java/lang/IllegalStateException
  }
  
  static {
    throw SYNTHETIC_LOCAL_VARIABLE_0;
  }
  
  public boolean isEmpty() {
    return Perry1.4H(this, (int)-617637095L ^ 0xA8E90357);
  }
}


/* Location:              C:\Users\alex\Desktop\webhack\WebHack-0.8-obf_sussy_1.jar!\bigname\zprestige\webhack\features\setting\Bind.class
 * Java compiler version: 8 (52.0)
 * JD-Core Version:       1.1.3
 */