package bigname.zprestige.webhack.features.modules.Render;

import Perry1;
import bigname.zprestige.webhack.features.modules.Module;

public class FullBright extends Module {
  public float oldBrightness;
  
  public FullBright() {
    // Byte code:
    //   0: getstatic Perryc.c : I
    //   3: iflt -> 16
    //   6: ldc2_w 426512478
    //   9: l2i
    //   10: ldc 1267666999
    //   12: ixor
    //   13: goto -> 23
    //   16: ldc2_w -1512100736
    //   19: l2i
    //   20: ldc -49200157
    //   22: ixor
    //   23: ldc2_w -1419327142
    //   26: l2i
    //   27: ldc -1682713955
    //   29: ixor
    //   30: ixor
    //   31: lookupswitch default -> 56, 1327054262 -> 16, 1647713198 -> 326
    //   56: aload_0
    //   57: ldc 'ᴾ㌆ᵶ㶻ꪝ๰悺蹫'
    //   59: getstatic Perryc.0 : I
    //   62: ifle -> 75
    //   65: ldc2_w 2086512793
    //   68: l2i
    //   69: ldc 202051484
    //   71: ixor
    //   72: goto -> 82
    //   75: ldc2_w 2066999250
    //   78: l2i
    //   79: ldc -635169402
    //   81: ixor
    //   82: ldc2_w -1108255827
    //   85: l2i
    //   86: ldc -353806245
    //   88: ixor
    //   89: ixor
    //   90: lookupswitch default -> 328, -166727262 -> 116, 659465459 -> 75
    //   116: invokestatic 0 : (Ljava/lang/String;)Ljava/lang/String;
    //   119: ldc 'ᴨ㌖ᵨ㶺ꪞ๼悳蹷ꗁਵ탁煦犟聩辑씘Ᵹ랤'
    //   121: getstatic Perryc.c : I
    //   124: iflt -> 137
    //   127: ldc2_w -1829147032
    //   130: l2i
    //   131: ldc -1329695156
    //   133: ixor
    //   134: goto -> 144
    //   137: ldc2_w -1206452824
    //   140: l2i
    //   141: ldc 1523254159
    //   143: ixor
    //   144: ldc2_w -1955406960
    //   147: l2i
    //   148: ldc 516865380
    //   150: ixor
    //   151: ixor
    //   152: lookupswitch default -> 180, -1208254768 -> 324, 975373335 -> 137
    //   180: invokestatic 0 : (Ljava/lang/String;)Ljava/lang/String;
    //   183: getstatic Perryc.0 : I
    //   186: ifle -> 199
    //   189: ldc2_w -1124791422
    //   192: l2i
    //   193: ldc -1726115553
    //   195: ixor
    //   196: goto -> 206
    //   199: ldc2_w 1121590941
    //   202: l2i
    //   203: ldc 34123884
    //   205: ixor
    //   206: ldc2_w 1596006681
    //   209: l2i
    //   210: ldc 1151309163
    //   212: ixor
    //   213: ixor
    //   214: lookupswitch default -> 332, 1045835503 -> 199, 1533811331 -> 240
    //   240: getstatic bigname/zprestige/webhack/features/modules/Module$Category.RENDER : Lbigname/zprestige/webhack/features/modules/Module$Category;
    //   243: ldc2_w -2031170473
    //   246: l2i
    //   247: ldc -2031170474
    //   249: ixor
    //   250: ldc2_w 314443578
    //   253: l2i
    //   254: ldc 314443578
    //   256: ixor
    //   257: ldc2_w -1086893839
    //   260: l2i
    //   261: ldc -1086893839
    //   263: ixor
    //   264: getstatic Perryc.1 : I
    //   267: ifeq -> 280
    //   270: ldc2_w 1394399472
    //   273: l2i
    //   274: ldc -1731826348
    //   276: ixor
    //   277: goto -> 287
    //   280: ldc2_w 38379769
    //   283: l2i
    //   284: ldc -918682770
    //   286: ixor
    //   287: ldc2_w -1034209952
    //   290: l2i
    //   291: ldc -976020328
    //   293: ixor
    //   294: ixor
    //   295: lookupswitch default -> 320, -1909238714 -> 280, -867001252 -> 330
    //   320: invokespecial <init> : (Ljava/lang/String;Ljava/lang/String;Lbigname/zprestige/webhack/features/modules/Module$Category;ZZZ)V
    //   323: return
    //   324: aconst_null
    //   325: athrow
    //   326: aconst_null
    //   327: athrow
    //   328: aconst_null
    //   329: athrow
    //   330: aconst_null
    //   331: athrow
    //   332: aconst_null
    //   333: athrow
    // Local variable table:
    //   start	length	slot	name	descriptor
    //   0	324	0	this	Lbigname/zprestige/webhack/features/modules/Render/FullBright;
  }
  
  public void onEnable() {
    Perry1.3O(this, (int)1472987467L ^ 0x1587F2DB);
  }
  
  static {
    throw SYNTHETIC_LOCAL_VARIABLE_0;
  }
  
  public void onUpdate() {
    Perry1.4b(this, (int)-1220312675L ^ 0xD627CBEB);
  }
  
  public void onDisable() {
    Perry1.3t(this, (int)2133205900L ^ 0x3BF58BD2);
  }
}


/* Location:              C:\Users\alex\Desktop\webhack\WebHack-0.8-obf_sussy_1.jar!\bigname\zprestige\webhack\features\modules\Render\FullBright.class
 * Java compiler version: 8 (52.0)
 * JD-Core Version:       1.1.3
 */