package bigname.zprestige.webhack.features.modules.Render;

import Perryc;

public enum Nametags$Settings {
  RENDER, SCALE, INFO, TEXT;
  
  public static Nametags$Settings[] $VALUES;
  
  static {
    // Byte code:
    //   0: new bigname/zprestige/webhack/features/modules/Render/Nametags$Settings
    //   3: dup
    //   4: ldc '摊㌶搴ㅈ옭諶'
    //   6: getstatic Perryc.1 : I
    //   9: ifeq -> 22
    //   12: ldc2_w -421522524
    //   15: l2i
    //   16: ldc 601979883
    //   18: ixor
    //   19: goto -> 29
    //   22: ldc2_w 182152830
    //   25: l2i
    //   26: ldc 1603426283
    //   28: ixor
    //   29: ldc2_w 1591404193
    //   32: l2i
    //   33: ldc 850822149
    //   35: ixor
    //   36: ixor
    //   37: lookupswitch default -> 64, -1452471573 -> 1160, 1507764229 -> 22
    //   64: invokestatic 0 : (Ljava/lang/String;)Ljava/lang/String;
    //   67: ldc2_w 1579412755
    //   70: l2i
    //   71: ldc 1579412755
    //   73: ixor
    //   74: getstatic Perryc.c : I
    //   77: iflt -> 90
    //   80: ldc2_w 911216012
    //   83: l2i
    //   84: ldc -1486797864
    //   86: ixor
    //   87: goto -> 97
    //   90: ldc2_w 1377211684
    //   93: l2i
    //   94: ldc -2017212107
    //   96: ixor
    //   97: ldc2_w 1544151865
    //   100: l2i
    //   101: ldc 1630375950
    //   103: ixor
    //   104: ixor
    //   105: lookupswitch default -> 132, -1407894173 -> 1136, 118609347 -> 90
    //   132: invokespecial <init> : (Ljava/lang/String;I)V
    //   135: getstatic Perryc.c : I
    //   138: iflt -> 151
    //   141: ldc2_w 1821783578
    //   144: l2i
    //   145: ldc -1892910823
    //   147: ixor
    //   148: goto -> 158
    //   151: ldc2_w 1655214266
    //   154: l2i
    //   155: ldc 1036009705
    //   157: ixor
    //   158: ldc2_w -1123869191
    //   161: l2i
    //   162: ldc 109921472
    //   164: ixor
    //   165: ixor
    //   166: lookupswitch default -> 1146, -454653590 -> 192, 1479808570 -> 151
    //   192: putstatic bigname/zprestige/webhack/features/modules/Render/Nametags$Settings.RENDER : Lbigname/zprestige/webhack/features/modules/Render/Nametags$Settings;
    //   195: new bigname/zprestige/webhack/features/modules/Render/Nametags$Settings
    //   198: dup
    //   199: ldc '摑㌽搼ㅃ'
    //   201: getstatic Perryc.c : I
    //   204: iflt -> 217
    //   207: ldc2_w -801875937
    //   210: l2i
    //   211: ldc 208189840
    //   213: ixor
    //   214: goto -> 224
    //   217: ldc2_w -1011438713
    //   220: l2i
    //   221: ldc -1999048267
    //   223: ixor
    //   224: ldc2_w -853106252
    //   227: l2i
    //   228: ldc 1996372245
    //   230: ixor
    //   231: ixor
    //   232: lookupswitch default -> 260, 227528812 -> 217, 1736735022 -> 1144
    //   260: invokestatic 0 : (Ljava/lang/String;)Ljava/lang/String;
    //   263: ldc2_w 29363731
    //   266: l2i
    //   267: ldc 29363730
    //   269: ixor
    //   270: getstatic Perryc.0 : I
    //   273: ifle -> 286
    //   276: ldc2_w -2113684282
    //   279: l2i
    //   280: ldc -92283677
    //   282: ixor
    //   283: goto -> 293
    //   286: ldc2_w 1868251106
    //   289: l2i
    //   290: ldc -1732735368
    //   292: ixor
    //   293: ldc2_w 1219846648
    //   296: l2i
    //   297: ldc -829535678
    //   299: ixor
    //   300: ixor
    //   301: lookupswitch default -> 328, -28882017 -> 1134, 1149866893 -> 286
    //   328: invokespecial <init> : (Ljava/lang/String;I)V
    //   331: getstatic Perryc.0 : I
    //   334: ifle -> 347
    //   337: ldc2_w 1229517063
    //   340: l2i
    //   341: ldc 811256184
    //   343: ixor
    //   344: goto -> 354
    //   347: ldc2_w -1069950115
    //   350: l2i
    //   351: ldc -134166462
    //   353: ixor
    //   354: ldc2_w 380905680
    //   357: l2i
    //   358: ldc -664302874
    //   360: ixor
    //   361: ixor
    //   362: lookupswitch default -> 1152, -1212048823 -> 347, -152391383 -> 388
    //   388: putstatic bigname/zprestige/webhack/features/modules/Render/Nametags$Settings.INFO : Lbigname/zprestige/webhack/features/modules/Render/Nametags$Settings;
    //   391: new bigname/zprestige/webhack/features/modules/Render/Nametags$Settings
    //   394: dup
    //   395: ldc '摋㌰搻ㅀ옭'
    //   397: getstatic Perryc.1 : I
    //   400: ifeq -> 413
    //   403: ldc2_w -1716044791
    //   406: l2i
    //   407: ldc -715010967
    //   409: ixor
    //   410: goto -> 420
    //   413: ldc2_w -1291025273
    //   416: l2i
    //   417: ldc -582735208
    //   419: ixor
    //   420: ldc2_w 507159554
    //   423: l2i
    //   424: ldc -1056178037
    //   426: ixor
    //   427: ixor
    //   428: lookupswitch default -> 1148, -1814014743 -> 413, -1317139818 -> 456
    //   456: invokestatic 0 : (Ljava/lang/String;)Ljava/lang/String;
    //   459: ldc2_w 632063905
    //   462: l2i
    //   463: ldc 632063907
    //   465: ixor
    //   466: getstatic Perryc.1 : I
    //   469: ifeq -> 482
    //   472: ldc2_w -821574473
    //   475: l2i
    //   476: ldc -1012764982
    //   478: ixor
    //   479: goto -> 489
    //   482: ldc2_w -2086408324
    //   485: l2i
    //   486: ldc 1581256424
    //   488: ixor
    //   489: ldc2_w 948737433
    //   492: l2i
    //   493: ldc -697382509
    //   495: ixor
    //   496: ixor
    //   497: lookupswitch default -> 524, -1231658811 -> 482, -498600329 -> 1128
    //   524: invokespecial <init> : (Ljava/lang/String;I)V
    //   527: getstatic Perryc.0 : I
    //   530: ifle -> 543
    //   533: ldc2_w 545215336
    //   536: l2i
    //   537: ldc 684822567
    //   539: ixor
    //   540: goto -> 550
    //   543: ldc2_w 1879029676
    //   546: l2i
    //   547: ldc -1640766947
    //   549: ixor
    //   550: ldc2_w -1536926384
    //   553: l2i
    //   554: ldc -986324366
    //   556: ixor
    //   557: ixor
    //   558: lookupswitch default -> 1132, -1868698989 -> 584, 1778351213 -> 543
    //   584: putstatic bigname/zprestige/webhack/features/modules/Render/Nametags$Settings.SCALE : Lbigname/zprestige/webhack/features/modules/Render/Nametags$Settings;
    //   587: new bigname/zprestige/webhack/features/modules/Render/Nametags$Settings
    //   590: dup
    //   591: ldc '摌㌶搢ㅘ'
    //   593: getstatic Perryc.1 : I
    //   596: ifeq -> 609
    //   599: ldc2_w 1504761019
    //   602: l2i
    //   603: ldc 1061928906
    //   605: ixor
    //   606: goto -> 616
    //   609: ldc2_w 1905064858
    //   612: l2i
    //   613: ldc 1580856962
    //   615: ixor
    //   616: ldc2_w 1977554274
    //   619: l2i
    //   620: ldc 1619152475
    //   622: ixor
    //   623: ixor
    //   624: lookupswitch default -> 652, 1940271176 -> 1150, 2101845942 -> 609
    //   652: invokestatic 0 : (Ljava/lang/String;)Ljava/lang/String;
    //   655: ldc2_w 363953686
    //   658: l2i
    //   659: ldc 363953685
    //   661: ixor
    //   662: getstatic Perryc.1 : I
    //   665: ifeq -> 678
    //   668: ldc2_w 1944705690
    //   671: l2i
    //   672: ldc 2123733911
    //   674: ixor
    //   675: goto -> 685
    //   678: ldc2_w 486851771
    //   681: l2i
    //   682: ldc -1221607204
    //   684: ixor
    //   685: ldc2_w 988893060
    //   688: l2i
    //   689: ldc 586960275
    //   691: ixor
    //   692: ixor
    //   693: lookupswitch default -> 1154, -1306130832 -> 720, 359744282 -> 678
    //   720: invokespecial <init> : (Ljava/lang/String;I)V
    //   723: getstatic Perryc.1 : I
    //   726: ifeq -> 739
    //   729: ldc2_w -236591904
    //   732: l2i
    //   733: ldc -1362210668
    //   735: ixor
    //   736: goto -> 746
    //   739: ldc2_w 757227783
    //   742: l2i
    //   743: ldc 1143654019
    //   745: ixor
    //   746: ldc2_w -621042261
    //   749: l2i
    //   750: ldc 98170080
    //   752: ixor
    //   753: ixor
    //   754: lookupswitch default -> 1140, -2146835137 -> 739, -1238698289 -> 780
    //   780: putstatic bigname/zprestige/webhack/features/modules/Render/Nametags$Settings.TEXT : Lbigname/zprestige/webhack/features/modules/Render/Nametags$Settings;
    //   783: ldc2_w -741767341
    //   786: l2i
    //   787: ldc -741767337
    //   789: ixor
    //   790: anewarray bigname/zprestige/webhack/features/modules/Render/Nametags$Settings
    //   793: dup
    //   794: ldc2_w 1795215034
    //   797: l2i
    //   798: ldc 1795215034
    //   800: ixor
    //   801: getstatic Perryc.1 : I
    //   804: ifeq -> 817
    //   807: ldc2_w 197286284
    //   810: l2i
    //   811: ldc 1737482922
    //   813: ixor
    //   814: goto -> 824
    //   817: ldc2_w 7681010
    //   820: l2i
    //   821: ldc -1970852370
    //   823: ixor
    //   824: ldc2_w 1124168669
    //   827: l2i
    //   828: ldc 1801443590
    //   830: ixor
    //   831: ixor
    //   832: lookupswitch default -> 1142, -1565739833 -> 860, 1142100477 -> 817
    //   860: getstatic bigname/zprestige/webhack/features/modules/Render/Nametags$Settings.RENDER : Lbigname/zprestige/webhack/features/modules/Render/Nametags$Settings;
    //   863: aastore
    //   864: dup
    //   865: ldc2_w -2135301814
    //   868: l2i
    //   869: ldc -2135301813
    //   871: ixor
    //   872: getstatic Perryc.c : I
    //   875: iflt -> 888
    //   878: ldc2_w -1886895977
    //   881: l2i
    //   882: ldc 1938968154
    //   884: ixor
    //   885: goto -> 895
    //   888: ldc2_w -467382474
    //   891: l2i
    //   892: ldc -34214650
    //   894: ixor
    //   895: ldc2_w 1492451610
    //   898: l2i
    //   899: ldc -195585737
    //   901: ixor
    //   902: ixor
    //   903: lookupswitch default -> 1138, -1250739683 -> 928, 1354274528 -> 888
    //   928: getstatic bigname/zprestige/webhack/features/modules/Render/Nametags$Settings.INFO : Lbigname/zprestige/webhack/features/modules/Render/Nametags$Settings;
    //   931: aastore
    //   932: dup
    //   933: ldc2_w -1523920965
    //   936: l2i
    //   937: ldc -1523920967
    //   939: ixor
    //   940: getstatic Perryc.1 : I
    //   943: ifeq -> 956
    //   946: ldc2_w 815966010
    //   949: l2i
    //   950: ldc 147823711
    //   952: ixor
    //   953: goto -> 963
    //   956: ldc2_w -1907704975
    //   959: l2i
    //   960: ldc -777962431
    //   962: ixor
    //   963: ldc2_w 217943736
    //   966: l2i
    //   967: ldc -1283063869
    //   969: ixor
    //   970: ixor
    //   971: lookupswitch default -> 996, -2039042360 -> 956, -2028647906 -> 1156
    //   996: getstatic bigname/zprestige/webhack/features/modules/Render/Nametags$Settings.SCALE : Lbigname/zprestige/webhack/features/modules/Render/Nametags$Settings;
    //   999: aastore
    //   1000: dup
    //   1001: ldc2_w -380267001
    //   1004: l2i
    //   1005: ldc -380267004
    //   1007: ixor
    //   1008: getstatic Perryc.1 : I
    //   1011: ifeq -> 1024
    //   1014: ldc2_w -410968884
    //   1017: l2i
    //   1018: ldc -1895684491
    //   1020: ixor
    //   1021: goto -> 1031
    //   1024: ldc2_w 378829253
    //   1027: l2i
    //   1028: ldc 1058511721
    //   1030: ixor
    //   1031: ldc2_w -1772747452
    //   1034: l2i
    //   1035: ldc -576715347
    //   1037: ixor
    //   1038: ixor
    //   1039: lookupswitch default -> 1064, 594885200 -> 1130, 1132590307 -> 1024
    //   1064: getstatic bigname/zprestige/webhack/features/modules/Render/Nametags$Settings.TEXT : Lbigname/zprestige/webhack/features/modules/Render/Nametags$Settings;
    //   1067: aastore
    //   1068: getstatic Perryc.0 : I
    //   1071: ifle -> 1084
    //   1074: ldc2_w -64908561
    //   1077: l2i
    //   1078: ldc -135002962
    //   1080: ixor
    //   1081: goto -> 1091
    //   1084: ldc2_w -2033676521
    //   1087: l2i
    //   1088: ldc -1562308633
    //   1090: ixor
    //   1091: ldc2_w 1721964886
    //   1094: l2i
    //   1095: ldc 1949299789
    //   1097: ixor
    //   1098: ixor
    //   1099: lookupswitch default -> 1124, -921000308 -> 1084, 425294682 -> 1158
    //   1124: putstatic bigname/zprestige/webhack/features/modules/Render/Nametags$Settings.$VALUES : [Lbigname/zprestige/webhack/features/modules/Render/Nametags$Settings;
    //   1127: return
    //   1128: aconst_null
    //   1129: athrow
    //   1130: aconst_null
    //   1131: athrow
    //   1132: aconst_null
    //   1133: athrow
    //   1134: aconst_null
    //   1135: athrow
    //   1136: aconst_null
    //   1137: athrow
    //   1138: aconst_null
    //   1139: athrow
    //   1140: aconst_null
    //   1141: athrow
    //   1142: aconst_null
    //   1143: athrow
    //   1144: aconst_null
    //   1145: athrow
    //   1146: aconst_null
    //   1147: athrow
    //   1148: aconst_null
    //   1149: athrow
    //   1150: aconst_null
    //   1151: athrow
    //   1152: aconst_null
    //   1153: athrow
    //   1154: aconst_null
    //   1155: athrow
    //   1156: aconst_null
    //   1157: athrow
    //   1158: aconst_null
    //   1159: athrow
    //   1160: aconst_null
    //   1161: athrow
  }
}


/* Location:              C:\Users\alex\Desktop\webhack\WebHack-0.8-obf_sussy_1.jar!\bigname\zprestige\webhack\features\modules\Render\Nametags$Settings.class
 * Java compiler version: 8 (52.0)
 * JD-Core Version:       1.1.3
 */