package bigname.zprestige.webhack.features.modules.Render;

import Perry1;
import bigname.zprestige.webhack.features.modules.Module;

public class OffhandSwing extends Module {
  public void onUpdate() {
    Perry1.47(this, (int)-784758825L ^ 0xCD6849AE);
  }
  
  static {
    throw SYNTHETIC_LOCAL_VARIABLE_0;
  }
  
  public OffhandSwing() {
    // Byte code:
    //   0: getstatic Perryc.c : I
    //   3: iflt -> 16
    //   6: ldc2_w 1054123687
    //   9: l2i
    //   10: ldc -1303487523
    //   12: ixor
    //   13: goto -> 23
    //   16: ldc2_w 1493416405
    //   19: l2i
    //   20: ldc -1828975715
    //   22: ixor
    //   23: ldc2_w 499313000
    //   26: l2i
    //   27: ldc -356060273
    //   29: ixor
    //   30: ixor
    //   31: lookupswitch default -> 332, 1023125679 -> 56, 2074011549 -> 16
    //   56: aload_0
    //   57: ldc '캜㌕컇㶿簉 ๽댵蹴⃿癦ਠ'
    //   59: getstatic Perryc.0 : I
    //   62: ifle -> 75
    //   65: ldc2_w -396791636
    //   68: l2i
    //   69: ldc -1899693466
    //   71: ixor
    //   72: goto -> 82
    //   75: ldc2_w -868690965
    //   78: l2i
    //   79: ldc 1856187993
    //   81: ixor
    //   82: ldc2_w 1939273488
    //   85: l2i
    //   86: ldc -1109983857
    //   88: ixor
    //   89: ixor
    //   90: lookupswitch default -> 116, -1461878699 -> 324, -228911464 -> 75
    //   116: invokestatic 0 : (Ljava/lang/String;)Ljava/lang/String;
    //   119: ldc '캐㌛컀㶹簏 ๪덆蹮⃷癡਩ͻ煠ꐎ叒迟ᚵꝹ愩䅖侶⑼䚪⏑髎ᣁ殮⥓꿷꯵摻ꠟ'
    //   121: getstatic Perryc.c : I
    //   124: iflt -> 137
    //   127: ldc2_w 1043669121
    //   130: l2i
    //   131: ldc 477180533
    //   133: ixor
    //   134: goto -> 144
    //   137: ldc2_w 2097602372
    //   140: l2i
    //   141: ldc -1622360642
    //   143: ixor
    //   144: ldc2_w -2098004861
    //   147: l2i
    //   148: ldc 1390576109
    //   150: ixor
    //   151: ixor
    //   152: lookupswitch default -> 180, -229347430 -> 328, 1674685818 -> 137
    //   180: invokestatic 0 : (Ljava/lang/String;)Ljava/lang/String;
    //   183: getstatic Perryc.1 : I
    //   186: ifeq -> 199
    //   189: ldc2_w 1719163666
    //   192: l2i
    //   193: ldc 1242762944
    //   195: ixor
    //   196: goto -> 206
    //   199: ldc2_w 46759298
    //   202: l2i
    //   203: ldc -1274392648
    //   205: ixor
    //   206: ldc2_w 482412618
    //   209: l2i
    //   210: ldc 1955338367
    //   212: ixor
    //   213: ixor
    //   214: lookupswitch default -> 330, -561110513 -> 240, 1143358951 -> 199
    //   240: getstatic bigname/zprestige/webhack/features/modules/Module$Category.RENDER : Lbigname/zprestige/webhack/features/modules/Module$Category;
    //   243: ldc2_w -283298226
    //   246: l2i
    //   247: ldc -283298226
    //   249: ixor
    //   250: ldc2_w -395049338
    //   253: l2i
    //   254: ldc -395049338
    //   256: ixor
    //   257: ldc2_w 1900087378
    //   260: l2i
    //   261: ldc 1900087378
    //   263: ixor
    //   264: getstatic Perryc.c : I
    //   267: iflt -> 280
    //   270: ldc2_w -331773666
    //   273: l2i
    //   274: ldc -1455174764
    //   276: ixor
    //   277: goto -> 287
    //   280: ldc2_w 233288512
    //   283: l2i
    //   284: ldc 1802398628
    //   286: ixor
    //   287: ldc2_w 804515182
    //   290: l2i
    //   291: ldc 2115083820
    //   293: ixor
    //   294: ixor
    //   295: lookupswitch default -> 320, -1242583623 -> 280, 345518536 -> 326
    //   320: invokespecial <init> : (Ljava/lang/String;Ljava/lang/String;Lbigname/zprestige/webhack/features/modules/Module$Category;ZZZ)V
    //   323: return
    //   324: aconst_null
    //   325: athrow
    //   326: aconst_null
    //   327: athrow
    //   328: aconst_null
    //   329: athrow
    //   330: aconst_null
    //   331: athrow
    //   332: aconst_null
    //   333: athrow
    // Local variable table:
    //   start	length	slot	name	descriptor
    //   0	324	0	this	Lbigname/zprestige/webhack/features/modules/Render/OffhandSwing;
  }
}


/* Location:              C:\Users\alex\Desktop\webhack\WebHack-0.8-obf_sussy_1.jar!\bigname\zprestige\webhack\features\modules\Render\OffhandSwing.class
 * Java compiler version: 8 (52.0)
 * JD-Core Version:       1.1.3
 */