package bigname.zprestige.webhack.manager;

public class EventManager$1 {
  public static int[] $SwitchMap$net$minecraft$network$play$server$SPacketPlayerListItem$Action;
  
  static {
    // Byte code:
    //   0: getstatic Perryc.0 : I
    //   3: ifle -> 16
    //   6: ldc2_w 1659582199
    //   9: l2i
    //   10: ldc -1130232287
    //   12: ixor
    //   13: goto -> 23
    //   16: ldc2_w -2126029597
    //   19: l2i
    //   20: ldc -590312508
    //   22: ixor
    //   23: ldc2_w -570584723
    //   26: l2i
    //   27: ldc -1996721397
    //   29: ixor
    //   30: ixor
    //   31: lookupswitch default -> 626, -1958161744 -> 16, 144061761 -> 56
    //   56: invokestatic values : ()[Lnet/minecraft/network/play/server/SPacketPlayerListItem$Action;
    //   59: arraylength
    //   60: newarray int
    //   62: getstatic Perryc.c : I
    //   65: iflt -> 78
    //   68: ldc2_w -596319671
    //   71: l2i
    //   72: ldc -1268712988
    //   74: ixor
    //   75: goto -> 85
    //   78: ldc2_w -785925222
    //   81: l2i
    //   82: ldc 50061429
    //   84: ixor
    //   85: ldc2_w -1439113767
    //   88: l2i
    //   89: ldc -381616993
    //   91: ixor
    //   92: ixor
    //   93: lookupswitch default -> 120, 728513259 -> 640, 1034231845 -> 78
    //   120: putstatic bigname/zprestige/webhack/manager/EventManager$1.$SwitchMap$net$minecraft$network$play$server$SPacketPlayerListItem$Action : [I
    //   123: getstatic Perryc.c : I
    //   126: iflt -> 139
    //   129: ldc2_w -251950413
    //   132: l2i
    //   133: ldc -860032234
    //   135: ixor
    //   136: goto -> 146
    //   139: ldc2_w 1761483174
    //   142: l2i
    //   143: ldc -1015819541
    //   145: ixor
    //   146: ldc2_w -163255029
    //   149: l2i
    //   150: ldc -2042302486
    //   152: ixor
    //   153: ixor
    //   154: lookupswitch default -> 638, -611464788 -> 180, 1279753028 -> 139
    //   180: getstatic bigname/zprestige/webhack/manager/EventManager$1.$SwitchMap$net$minecraft$network$play$server$SPacketPlayerListItem$Action : [I
    //   183: getstatic Perryc.1 : I
    //   186: ifeq -> 199
    //   189: ldc2_w 510358601
    //   192: l2i
    //   193: ldc -985531709
    //   195: ixor
    //   196: goto -> 206
    //   199: ldc2_w 560328915
    //   202: l2i
    //   203: ldc -214450324
    //   205: ixor
    //   206: ldc2_w 22491950
    //   209: l2i
    //   210: ldc -1559524689
    //   212: ixor
    //   213: ixor
    //   214: lookupswitch default -> 632, 1880028734 -> 240, 2037790475 -> 199
    //   240: getstatic net/minecraft/network/play/server/SPacketPlayerListItem$Action.ADD_PLAYER : Lnet/minecraft/network/play/server/SPacketPlayerListItem$Action;
    //   243: getstatic Perryc.1 : I
    //   246: ifeq -> 259
    //   249: ldc2_w -1526069535
    //   252: l2i
    //   253: ldc -1056301696
    //   255: ixor
    //   256: goto -> 266
    //   259: ldc2_w -2133572710
    //   262: l2i
    //   263: ldc -2045467264
    //   265: ixor
    //   266: ldc2_w -796973902
    //   269: l2i
    //   270: ldc 126642081
    //   272: ixor
    //   273: ixor
    //   274: lookupswitch default -> 300, -1275897742 -> 636, -62499961 -> 259
    //   300: invokevirtual ordinal : ()I
    //   303: ldc2_w 1565762254
    //   306: l2i
    //   307: ldc 1565762255
    //   309: ixor
    //   310: iastore
    //   311: goto -> 373
    //   314: getstatic Perryc.1 : I
    //   317: ifeq -> 330
    //   320: ldc2_w -128588796
    //   323: l2i
    //   324: ldc 1125264875
    //   326: ixor
    //   327: goto -> 337
    //   330: ldc2_w -1323535131
    //   333: l2i
    //   334: ldc 1889546654
    //   336: ixor
    //   337: ldc2_w 9621505
    //   340: l2i
    //   341: ldc 64556642
    //   343: ixor
    //   344: ixor
    //   345: lookupswitch default -> 372, -1207167092 -> 628, 379245656 -> 330
    //   372: astore_0
    //   373: getstatic Perryc.0 : I
    //   376: ifle -> 389
    //   379: ldc2_w -504241747
    //   382: l2i
    //   383: ldc 85292453
    //   385: ixor
    //   386: goto -> 396
    //   389: ldc2_w -870931608
    //   392: l2i
    //   393: ldc 407830229
    //   395: ixor
    //   396: ldc2_w -1130475930
    //   399: l2i
    //   400: ldc -1529201487
    //   402: ixor
    //   403: ixor
    //   404: lookupswitch default -> 644, -870568086 -> 432, -56564001 -> 389
    //   432: getstatic bigname/zprestige/webhack/manager/EventManager$1.$SwitchMap$net$minecraft$network$play$server$SPacketPlayerListItem$Action : [I
    //   435: getstatic Perryc.c : I
    //   438: iflt -> 451
    //   441: ldc2_w 1577376577
    //   444: l2i
    //   445: ldc 113325851
    //   447: ixor
    //   448: goto -> 458
    //   451: ldc2_w 1961900994
    //   454: l2i
    //   455: ldc -491197305
    //   457: ixor
    //   458: ldc2_w -1734539685
    //   461: l2i
    //   462: ldc 1745023131
    //   464: ixor
    //   465: ixor
    //   466: lookupswitch default -> 492, -1470489958 -> 642, 1427622616 -> 451
    //   492: getstatic net/minecraft/network/play/server/SPacketPlayerListItem$Action.REMOVE_PLAYER : Lnet/minecraft/network/play/server/SPacketPlayerListItem$Action;
    //   495: getstatic Perryc.c : I
    //   498: iflt -> 511
    //   501: ldc2_w -349274108
    //   504: l2i
    //   505: ldc -575862971
    //   507: ixor
    //   508: goto -> 518
    //   511: ldc2_w 926677814
    //   514: l2i
    //   515: ldc 1106113060
    //   517: ixor
    //   518: ldc2_w 942750381
    //   521: l2i
    //   522: ldc 124515044
    //   524: ixor
    //   525: ixor
    //   526: lookupswitch default -> 634, 165236488 -> 511, 1233961307 -> 552
    //   552: invokevirtual ordinal : ()I
    //   555: ldc2_w 1827695811
    //   558: l2i
    //   559: ldc 1827695809
    //   561: ixor
    //   562: iastore
    //   563: goto -> 625
    //   566: getstatic Perryc.1 : I
    //   569: ifeq -> 582
    //   572: ldc2_w -978320541
    //   575: l2i
    //   576: ldc 1108636723
    //   578: ixor
    //   579: goto -> 589
    //   582: ldc2_w -1892725770
    //   585: l2i
    //   586: ldc -215413099
    //   588: ixor
    //   589: ldc2_w 980623082
    //   592: l2i
    //   593: ldc 1335750739
    //   595: ixor
    //   596: ixor
    //   597: lookupswitch default -> 624, -229991959 -> 630, 816050047 -> 582
    //   624: astore_0
    //   625: return
    //   626: aconst_null
    //   627: athrow
    //   628: aconst_null
    //   629: athrow
    //   630: aconst_null
    //   631: athrow
    //   632: aconst_null
    //   633: athrow
    //   634: aconst_null
    //   635: athrow
    //   636: aconst_null
    //   637: athrow
    //   638: aconst_null
    //   639: athrow
    //   640: aconst_null
    //   641: athrow
    //   642: aconst_null
    //   643: athrow
    //   644: aconst_null
    //   645: athrow
    // Exception table:
    //   from	to	target	type
    //   123	311	314	java/lang/NoSuchFieldError
    //   373	563	566	java/lang/NoSuchFieldError
  }
}


/* Location:              C:\Users\alex\Desktop\webhack\WebHack-0.8-obf_sussy_1.jar!\bigname\zprestige\webhack\manager\EventManager$1.class
 * Java compiler version: 8 (52.0)
 * JD-Core Version:       1.1.3
 */