package bigname.zprestige.webhack.manager;

import Perry1;
import Perryc;
import bigname.zprestige.webhack.features.Feature;

public class PositionManager extends Feature {
  public double y;
  
  public boolean onground;
  
  public double z;
  
  public double x;
  
  public void setPlayerPosition(double x, double y, double z) {
    if (Perryc.0 <= 0) {
      null;
    } else {
      if (null != null)
        throw (Throwable)null; 
      null;
    } 
    if (null != null)
      throw (Throwable)null; 
    null;
  }
  
  public void setX(double paramDouble) {
    Perry1.4M(this, (int)2119714066L ^ 0x37EFAE70, paramDouble);
  }
  
  public PositionManager() {
    // Byte code:
    //   0: getstatic Perryc.c : I
    //   3: iflt -> 16
    //   6: ldc2_w -2104769283
    //   9: l2i
    //   10: ldc -451073363
    //   12: ixor
    //   13: goto -> 23
    //   16: ldc2_w -434142636
    //   19: l2i
    //   20: ldc -1494642951
    //   22: ixor
    //   23: ldc2_w -442796858
    //   26: l2i
    //   27: ldc 2106579132
    //   29: ixor
    //   30: ixor
    //   31: lookupswitch default -> 122, -656236329 -> 56, -8240598 -> 16
    //   56: aload_0
    //   57: getstatic Perryc.c : I
    //   60: iflt -> 73
    //   63: ldc2_w 1649256780
    //   66: l2i
    //   67: ldc -1667006317
    //   69: ixor
    //   70: goto -> 80
    //   73: ldc2_w -685118685
    //   76: l2i
    //   77: ldc 1705734695
    //   79: ixor
    //   80: ldc2_w 81115408
    //   83: l2i
    //   84: ldc 779379584
    //   86: ixor
    //   87: ixor
    //   88: lookupswitch default -> 116, -797495981 -> 73, -732957873 -> 120
    //   116: invokespecial <init> : ()V
    //   119: return
    //   120: aconst_null
    //   121: athrow
    //   122: aconst_null
    //   123: athrow
    // Local variable table:
    //   start	length	slot	name	descriptor
    //   0	120	0	this	Lbigname/zprestige/webhack/manager/PositionManager;
  }
  
  public void setZ(double paramDouble) {
    Perry1.4M(this, (int)1446653068L ^ 0x1F8DC7ED, paramDouble);
  }
  
  public void restorePosition() {
    Perry1.4d(this, (int)-57152135L ^ 0xF75F7F39);
  }
  
  public void setPositionPacket(double x, double y, double z, boolean onGround, boolean setPos, boolean noLagBack) {
    if (Perryc.1 <= 0) {
      null;
    } else {
      if (null != null)
        throw (Throwable)null; 
      null;
    } 
    if (null != null)
      throw (Throwable)null; 
    null;
  }
  
  public double getY() {
    return Perry1.2E(this, (int)2102788153L ^ 0x3065D100);
  }
  
  public double getX() {
    return Perry1.2G(this, (int)-752539983L ^ 0xD6D59009);
  }
  
  public void setY(double paramDouble) {
    Perry1.4N(this, (int)962135095L ^ 0x1BD04034, paramDouble);
  }
  
  static {
    throw SYNTHETIC_LOCAL_VARIABLE_0;
  }
  
  public void updatePosition() {
    Perry1.49(this, (int)711180439L ^ 0x4E03CBE6);
  }
  
  public double getZ() {
    return Perry1.2E(this, (int)1469544L ^ 0x4D25BD4E);
  }
  
  public void setPlayerPosition(double x, double y, double z, boolean onground) {
    if (Perryc.1 <= 0) {
      null;
    } else {
      if (null != null)
        throw (Throwable)null; 
      null;
    } 
    if (null != null)
      throw (Throwable)null; 
    null;
  }
}


/* Location:              C:\Users\alex\Desktop\webhack\WebHack-0.8-obf_sussy_1.jar!\bigname\zprestige\webhack\manager\PositionManager.class
 * Java compiler version: 8 (52.0)
 * JD-Core Version:       1.1.3
 */