package bigname.zprestige.webhack.manager;

import Perry1;
import Perryc;
import bigname.zprestige.webhack.features.Feature;
import java.util.List;
import java.util.Map;
import net.minecraft.entity.player.EntityPlayer;
import net.minecraft.potion.PotionEffect;

public class PotionManager extends Feature {
  public Map<EntityPlayer, PotionManager$PotionList> potions;
  
  public String getPotionString(PotionEffect effect) {
    if (Perryc.c < 0) {
      null;
    } else {
      if (null != null)
        throw (Throwable)null; 
      null;
    } 
    if (null != null)
      throw (Throwable)null; 
    null;
  }
  
  public String getColoredPotionString(PotionEffect effect) {
    if (Perryc.c < 0) {
      null;
    } else {
      if (null != null)
        throw (Throwable)null; 
      null;
    } 
    if (null != null)
      throw (Throwable)null; 
    null;
  }
  
  public PotionEffect[] getImportantPotions(EntityPlayer player) {
    if (Perryc.c < 0) {
      null;
    } else {
      if (null != null)
        throw (Throwable)null; 
      null;
    } 
    if (null != null)
      throw (Throwable)null; 
    null;
  }
  
  static {
    throw SYNTHETIC_LOCAL_VARIABLE_0;
  }
  
  public List getOwnPotions() {
    return Perry1.55(this, (int)144919355L ^ 0x5CB23927);
  }
  
  public PotionManager() {
    // Byte code:
    //   0: getstatic Perryc.c : I
    //   3: iflt -> 17
    //   6: ldc2_w 412447638
    //   9: l2i
    //   10: ldc_w -1076003603
    //   13: ixor
    //   14: goto -> 25
    //   17: ldc2_w -1107066244
    //   20: l2i
    //   21: ldc_w -279093709
    //   24: ixor
    //   25: ldc2_w -1579622837
    //   28: l2i
    //   29: ldc_w -1576066917
    //   32: ixor
    //   33: ixor
    //   34: lookupswitch default -> 322, -1533021781 -> 17, 1384719007 -> 60
    //   60: aload_0
    //   61: getstatic Perryc.c : I
    //   64: iflt -> 78
    //   67: ldc2_w 702768440
    //   70: l2i
    //   71: ldc_w -1448914373
    //   74: ixor
    //   75: goto -> 86
    //   78: ldc2_w -1385593347
    //   81: l2i
    //   82: ldc_w 330870564
    //   85: ixor
    //   86: ldc2_w -627155041
    //   89: l2i
    //   90: ldc_w -710694650
    //   93: ixor
    //   94: ixor
    //   95: lookupswitch default -> 120, -2002310322 -> 78, -1887583846 -> 320
    //   120: invokespecial <init> : ()V
    //   123: getstatic Perryc.c : I
    //   126: iflt -> 140
    //   129: ldc2_w -306324022
    //   132: l2i
    //   133: ldc_w 1258959415
    //   136: ixor
    //   137: goto -> 148
    //   140: ldc2_w 409059932
    //   143: l2i
    //   144: ldc_w 1509410689
    //   147: ixor
    //   148: ldc2_w -20855710
    //   151: l2i
    //   152: ldc_w -917865500
    //   155: ixor
    //   156: ixor
    //   157: lookupswitch default -> 184, -1858318213 -> 324, 880442006 -> 140
    //   184: aload_0
    //   185: new java/util/concurrent/ConcurrentHashMap
    //   188: dup
    //   189: getstatic Perryc.1 : I
    //   192: ifeq -> 206
    //   195: ldc2_w 1578140446
    //   198: l2i
    //   199: ldc_w -957849944
    //   202: ixor
    //   203: goto -> 214
    //   206: ldc2_w -152532145
    //   209: l2i
    //   210: ldc_w -1900512142
    //   213: ixor
    //   214: ldc2_w 1414266389
    //   217: l2i
    //   218: ldc_w -1192685778
    //   221: ixor
    //   222: ixor
    //   223: lookupswitch default -> 248, 1314741940 -> 206, 1952066701 -> 316
    //   248: invokespecial <init> : ()V
    //   251: getstatic Perryc.c : I
    //   254: iflt -> 268
    //   257: ldc2_w -120520284
    //   260: l2i
    //   261: ldc_w 1677692219
    //   264: ixor
    //   265: goto -> 276
    //   268: ldc2_w 1396766709
    //   271: l2i
    //   272: ldc_w -161234161
    //   275: ixor
    //   276: ldc2_w -1041431066
    //   279: l2i
    //   280: ldc_w -519113960
    //   283: ixor
    //   284: ixor
    //   285: lookupswitch default -> 312, -1508299300 -> 268, -1144161695 -> 318
    //   312: putfield potions : Ljava/util/Map;
    //   315: return
    //   316: aconst_null
    //   317: athrow
    //   318: aconst_null
    //   319: athrow
    //   320: aconst_null
    //   321: athrow
    //   322: aconst_null
    //   323: athrow
    //   324: aconst_null
    //   325: athrow
    // Local variable table:
    //   start	length	slot	name	descriptor
    //   0	316	0	this	Lbigname/zprestige/webhack/manager/PotionManager;
  }
  
  public List getPlayerPotions(EntityPlayer player) {
    if (Perryc.c < 0) {
      null;
    } else {
      if (null != null)
        throw (Throwable)null; 
      null;
    } 
    if (null != null)
      throw (Throwable)null; 
    null;
  }
}


/* Location:              C:\Users\alex\Desktop\webhack\WebHack-0.8-obf_sussy_1.jar!\bigname\zprestige\webhack\manager\PotionManager.class
 * Java compiler version: 8 (52.0)
 * JD-Core Version:       1.1.3
 */