package bigname.zprestige.webhack.manager;

import Perry1;
import Perryc;
import java.util.List;
import net.minecraft.potion.PotionEffect;

public class PotionManager$PotionList {
  public List<PotionEffect> effects;
  
  static {
    throw SYNTHETIC_LOCAL_VARIABLE_0;
  }
  
  public void addEffect(PotionEffect effect) {
    if (Perryc.c < 0) {
      null;
    } else {
      if (null != null)
        throw (Throwable)null; 
      null;
    } 
    if (null != null)
      throw (Throwable)null; 
    null;
  }
  
  public List getEffects() {
    return Perry1.59(this, (int)1391981418L ^ 0x1B1353F0);
  }
  
  public PotionManager$PotionList() {
    // Byte code:
    //   0: getstatic Perryc.c : I
    //   3: iflt -> 16
    //   6: ldc2_w -667202398
    //   9: l2i
    //   10: ldc 2034563479
    //   12: ixor
    //   13: goto -> 23
    //   16: ldc2_w 193599780
    //   19: l2i
    //   20: ldc 1104939710
    //   22: ixor
    //   23: ldc2_w -1183730057
    //   26: l2i
    //   27: ldc -930212896
    //   29: ixor
    //   30: ixor
    //   31: lookupswitch default -> 312, -796913502 -> 16, 1000977933 -> 56
    //   56: aload_0
    //   57: getstatic Perryc.0 : I
    //   60: ifle -> 73
    //   63: ldc2_w -630049060
    //   66: l2i
    //   67: ldc -864927445
    //   69: ixor
    //   70: goto -> 80
    //   73: ldc2_w 1502048731
    //   76: l2i
    //   77: ldc 337717012
    //   79: ixor
    //   80: ldc2_w 567572834
    //   83: l2i
    //   84: ldc 1208267543
    //   86: ixor
    //   87: ixor
    //   88: lookupswitch default -> 310, 611753146 -> 116, 2144386434 -> 73
    //   116: invokespecial <init> : ()V
    //   119: getstatic Perryc.c : I
    //   122: iflt -> 135
    //   125: ldc2_w 2076009968
    //   128: l2i
    //   129: ldc 1043753330
    //   131: ixor
    //   132: goto -> 142
    //   135: ldc2_w -1882398196
    //   138: l2i
    //   139: ldc -1716066754
    //   141: ixor
    //   142: ldc2_w -253191121
    //   145: l2i
    //   146: ldc 1959807767
    //   148: ixor
    //   149: ixor
    //   150: lookupswitch default -> 176, -1045177414 -> 306, -349916305 -> 135
    //   176: aload_0
    //   177: new java/util/ArrayList
    //   180: dup
    //   181: getstatic Perryc.0 : I
    //   184: ifle -> 197
    //   187: ldc2_w -1877475928
    //   190: l2i
    //   191: ldc -1017207795
    //   193: ixor
    //   194: goto -> 204
    //   197: ldc2_w 243358115
    //   200: l2i
    //   201: ldc 926996920
    //   203: ixor
    //   204: ldc2_w -561594124
    //   207: l2i
    //   208: ldc 1244731726
    //   210: ixor
    //   211: ixor
    //   212: lookupswitch default -> 308, -1384752735 -> 240, -939622369 -> 197
    //   240: invokespecial <init> : ()V
    //   243: getstatic Perryc.0 : I
    //   246: ifle -> 259
    //   249: ldc2_w -1711435081
    //   252: l2i
    //   253: ldc 1679626594
    //   255: ixor
    //   256: goto -> 266
    //   259: ldc2_w 221747973
    //   262: l2i
    //   263: ldc -518669951
    //   265: ixor
    //   266: ldc2_w 964892683
    //   269: l2i
    //   270: ldc -1508492600
    //   272: ixor
    //   273: ixor
    //   274: lookupswitch default -> 304, 1651876118 -> 259, 1941372999 -> 300
    //   300: putfield effects : Ljava/util/List;
    //   303: return
    //   304: aconst_null
    //   305: athrow
    //   306: aconst_null
    //   307: athrow
    //   308: aconst_null
    //   309: athrow
    //   310: aconst_null
    //   311: athrow
    //   312: aconst_null
    //   313: athrow
    // Local variable table:
    //   start	length	slot	name	descriptor
    //   0	304	0	this	Lbigname/zprestige/webhack/manager/PotionManager$PotionList;
  }
}


/* Location:              C:\Users\alex\Desktop\webhack\WebHack-0.8-obf_sussy_1.jar!\bigname\zprestige\webhack\manager\PotionManager$PotionList.class
 * Java compiler version: 8 (52.0)
 * JD-Core Version:       1.1.3
 */