package bigname.zprestige.webhack.features.modules.Combat;

import Perryc;

public enum CrystalAura$AutoSwitch {
  None;
  
  public static CrystalAura$AutoSwitch[] $VALUES;
  
  static {
    // Byte code:
    //   0: new bigname/zprestige/webhack/features/modules/Combat/CrystalAura$AutoSwitch
    //   3: dup
    //   4: ldc 'ᷭ㌜ᷟㅩ'
    //   6: getstatic Perryc.c : I
    //   9: iflt -> 22
    //   12: ldc2_w 1318208703
    //   15: l2i
    //   16: ldc 110966877
    //   18: ixor
    //   19: goto -> 29
    //   22: ldc2_w 1464854632
    //   25: l2i
    //   26: ldc -866132773
    //   28: ixor
    //   29: ldc2_w -441848138
    //   32: l2i
    //   33: ldc 302579277
    //   35: ixor
    //   36: ixor
    //   37: lookupswitch default -> 64, -1079088103 -> 338, 220238543 -> 22
    //   64: invokestatic 0 : (Ljava/lang/String;)Ljava/lang/String;
    //   67: ldc2_w -261995725
    //   70: l2i
    //   71: ldc -261995725
    //   73: ixor
    //   74: getstatic Perryc.0 : I
    //   77: ifle -> 90
    //   80: ldc2_w 54815012
    //   83: l2i
    //   84: ldc 1049393900
    //   86: ixor
    //   87: goto -> 97
    //   90: ldc2_w 1997760994
    //   93: l2i
    //   94: ldc 492876709
    //   96: ixor
    //   97: ldc2_w -205922938
    //   100: l2i
    //   101: ldc 1573045932
    //   103: ixor
    //   104: ixor
    //   105: lookupswitch default -> 132, -1816983326 -> 336, -65994973 -> 90
    //   132: invokespecial <init> : (Ljava/lang/String;I)V
    //   135: getstatic Perryc.0 : I
    //   138: ifle -> 151
    //   141: ldc2_w 521294020
    //   144: l2i
    //   145: ldc -1666218348
    //   147: ixor
    //   148: goto -> 158
    //   151: ldc2_w 573163060
    //   154: l2i
    //   155: ldc -367142391
    //   157: ixor
    //   158: ldc2_w -1935905446
    //   161: l2i
    //   162: ldc 1289631998
    //   164: ixor
    //   165: ixor
    //   166: lookupswitch default -> 192, 1140818932 -> 344, 1248246009 -> 151
    //   192: putstatic bigname/zprestige/webhack/features/modules/Combat/CrystalAura$AutoSwitch.None : Lbigname/zprestige/webhack/features/modules/Combat/CrystalAura$AutoSwitch;
    //   195: ldc2_w -1854315796
    //   198: l2i
    //   199: ldc -1854315795
    //   201: ixor
    //   202: anewarray bigname/zprestige/webhack/features/modules/Combat/CrystalAura$AutoSwitch
    //   205: dup
    //   206: ldc2_w -964473874
    //   209: l2i
    //   210: ldc -964473874
    //   212: ixor
    //   213: getstatic Perryc.c : I
    //   216: iflt -> 229
    //   219: ldc2_w 1742801156
    //   222: l2i
    //   223: ldc -114742174
    //   225: ixor
    //   226: goto -> 236
    //   229: ldc2_w -1106516081
    //   232: l2i
    //   233: ldc 152410512
    //   235: ixor
    //   236: ldc2_w -54768852
    //   239: l2i
    //   240: ldc 1338939
    //   242: ixor
    //   243: ixor
    //   244: lookupswitch default -> 340, 1270242056 -> 272, 1650458737 -> 229
    //   272: getstatic bigname/zprestige/webhack/features/modules/Combat/CrystalAura$AutoSwitch.None : Lbigname/zprestige/webhack/features/modules/Combat/CrystalAura$AutoSwitch;
    //   275: aastore
    //   276: getstatic Perryc.c : I
    //   279: iflt -> 292
    //   282: ldc2_w 673665501
    //   285: l2i
    //   286: ldc -898298512
    //   288: ixor
    //   289: goto -> 299
    //   292: ldc2_w -609954576
    //   295: l2i
    //   296: ldc 1129742780
    //   298: ixor
    //   299: ldc2_w 166178475
    //   302: l2i
    //   303: ldc -1231537290
    //   305: ixor
    //   306: ixor
    //   307: lookupswitch default -> 342, 663601297 -> 332, 1563281776 -> 292
    //   332: putstatic bigname/zprestige/webhack/features/modules/Combat/CrystalAura$AutoSwitch.$VALUES : [Lbigname/zprestige/webhack/features/modules/Combat/CrystalAura$AutoSwitch;
    //   335: return
    //   336: aconst_null
    //   337: athrow
    //   338: aconst_null
    //   339: athrow
    //   340: aconst_null
    //   341: athrow
    //   342: aconst_null
    //   343: athrow
    //   344: aconst_null
    //   345: athrow
  }
}


/* Location:              C:\Users\alex\Desktop\webhack\WebHack-0.8-obf_sussy_1.jar!\bigname\zprestige\webhack\features\modules\Combat\CrystalAura$AutoSwitch.class
 * Java compiler version: 8 (52.0)
 * JD-Core Version:       1.1.3
 */