package bigname.zprestige.webhack.features.modules.Combat;

import Perryc;

public enum CrystalAura$Swing {
  None;
  
  public static CrystalAura$Swing[] $VALUES;
  
  static {
    // Byte code:
    //   0: new bigname/zprestige/webhack/features/modules/Combat/CrystalAura$Swing
    //   3: dup
    //   4: ldc '囤㌜嚦ㅩ'
    //   6: getstatic Perryc.0 : I
    //   9: ifle -> 22
    //   12: ldc2_w 657913461
    //   15: l2i
    //   16: ldc -302497071
    //   18: ixor
    //   19: goto -> 29
    //   22: ldc2_w -752075211
    //   25: l2i
    //   26: ldc 949982195
    //   28: ixor
    //   29: ldc2_w -414807227
    //   32: l2i
    //   33: ldc 1061785897
    //   35: ixor
    //   36: ixor
    //   37: lookupswitch default -> 340, 314683080 -> 22, 868005802 -> 64
    //   64: invokestatic 0 : (Ljava/lang/String;)Ljava/lang/String;
    //   67: ldc2_w -1264852864
    //   70: l2i
    //   71: ldc -1264852864
    //   73: ixor
    //   74: getstatic Perryc.1 : I
    //   77: ifeq -> 90
    //   80: ldc2_w -685516162
    //   83: l2i
    //   84: ldc -178183876
    //   86: ixor
    //   87: goto -> 97
    //   90: ldc2_w -1639679640
    //   93: l2i
    //   94: ldc 1610045318
    //   96: ixor
    //   97: ldc2_w 58861129
    //   100: l2i
    //   101: ldc 1024401550
    //   103: ixor
    //   104: ixor
    //   105: lookupswitch default -> 342, -12703703 -> 132, 483392901 -> 90
    //   132: invokespecial <init> : (Ljava/lang/String;I)V
    //   135: getstatic Perryc.c : I
    //   138: iflt -> 151
    //   141: ldc2_w -783593080
    //   144: l2i
    //   145: ldc -2068528990
    //   147: ixor
    //   148: goto -> 158
    //   151: ldc2_w -698257137
    //   154: l2i
    //   155: ldc -16637263
    //   157: ixor
    //   158: ldc2_w -1308789068
    //   161: l2i
    //   162: ldc 1917014069
    //   164: ixor
    //   165: ixor
    //   166: lookupswitch default -> 192, -1774078037 -> 338, 1353533348 -> 151
    //   192: putstatic bigname/zprestige/webhack/features/modules/Combat/CrystalAura$Swing.None : Lbigname/zprestige/webhack/features/modules/Combat/CrystalAura$Swing;
    //   195: ldc2_w 1338494992
    //   198: l2i
    //   199: ldc 1338494993
    //   201: ixor
    //   202: anewarray bigname/zprestige/webhack/features/modules/Combat/CrystalAura$Swing
    //   205: dup
    //   206: ldc2_w 328982677
    //   209: l2i
    //   210: ldc 328982677
    //   212: ixor
    //   213: getstatic Perryc.1 : I
    //   216: ifeq -> 229
    //   219: ldc2_w -223789892
    //   222: l2i
    //   223: ldc -1529274148
    //   225: ixor
    //   226: goto -> 236
    //   229: ldc2_w -80093055
    //   232: l2i
    //   233: ldc 1856346568
    //   235: ixor
    //   236: ldc2_w -1274718032
    //   239: l2i
    //   240: ldc 683461019
    //   242: ixor
    //   243: ixor
    //   244: lookupswitch default -> 272, -1263888973 -> 229, -892760757 -> 336
    //   272: getstatic bigname/zprestige/webhack/features/modules/Combat/CrystalAura$Swing.None : Lbigname/zprestige/webhack/features/modules/Combat/CrystalAura$Swing;
    //   275: aastore
    //   276: getstatic Perryc.1 : I
    //   279: ifeq -> 292
    //   282: ldc2_w 1326520282
    //   285: l2i
    //   286: ldc -113509889
    //   288: ixor
    //   289: goto -> 299
    //   292: ldc2_w -281917077
    //   295: l2i
    //   296: ldc -1203343223
    //   298: ixor
    //   299: ldc2_w -1591054527
    //   302: l2i
    //   303: ldc -2077886468
    //   305: ixor
    //   306: ixor
    //   307: lookupswitch default -> 344, -1826261352 -> 292, 1920704863 -> 332
    //   332: putstatic bigname/zprestige/webhack/features/modules/Combat/CrystalAura$Swing.$VALUES : [Lbigname/zprestige/webhack/features/modules/Combat/CrystalAura$Swing;
    //   335: return
    //   336: aconst_null
    //   337: athrow
    //   338: aconst_null
    //   339: athrow
    //   340: aconst_null
    //   341: athrow
    //   342: aconst_null
    //   343: athrow
    //   344: aconst_null
    //   345: athrow
  }
}


/* Location:              C:\Users\alex\Desktop\webhack\WebHack-0.8-obf_sussy_1.jar!\bigname\zprestige\webhack\features\modules\Combat\CrystalAura$Swing.class
 * Java compiler version: 8 (52.0)
 * JD-Core Version:       1.1.3
 */