package bigname.zprestige.webhack.features.modules.Combat;

import Perryc;

public enum CrystalAura$RotateMode {
  Off;
  
  public static CrystalAura$RotateMode[] $VALUES;
  
  static {
    // Byte code:
    //   0: new bigname/zprestige/webhack/features/modules/Combat/CrystalAura$RotateMode
    //   3: dup
    //   4: ldc '禱㌕秲'
    //   6: getstatic Perryc.0 : I
    //   9: ifle -> 22
    //   12: ldc2_w 2065480812
    //   15: l2i
    //   16: ldc -1789669060
    //   18: ixor
    //   19: goto -> 29
    //   22: ldc2_w -510841245
    //   25: l2i
    //   26: ldc 1402148917
    //   28: ixor
    //   29: ldc2_w -1128446352
    //   32: l2i
    //   33: ldc -2123554233
    //   35: ixor
    //   36: ixor
    //   37: lookupswitch default -> 344, -1882303903 -> 64, -744552089 -> 22
    //   64: invokestatic 0 : (Ljava/lang/String;)Ljava/lang/String;
    //   67: ldc2_w -1755318837
    //   70: l2i
    //   71: ldc -1755318837
    //   73: ixor
    //   74: getstatic Perryc.0 : I
    //   77: ifle -> 90
    //   80: ldc2_w -492665561
    //   83: l2i
    //   84: ldc 566518342
    //   86: ixor
    //   87: goto -> 97
    //   90: ldc2_w 750094496
    //   93: l2i
    //   94: ldc -963022492
    //   96: ixor
    //   97: ldc2_w 952752075
    //   100: l2i
    //   101: ldc -381808043
    //   103: ixor
    //   104: ixor
    //   105: lookupswitch default -> 132, -1088174431 -> 90, 311501567 -> 342
    //   132: invokespecial <init> : (Ljava/lang/String;I)V
    //   135: getstatic Perryc.1 : I
    //   138: ifeq -> 151
    //   141: ldc2_w 956627707
    //   144: l2i
    //   145: ldc -1023893748
    //   147: ixor
    //   148: goto -> 158
    //   151: ldc2_w -875247191
    //   154: l2i
    //   155: ldc -654384992
    //   157: ixor
    //   158: ldc2_w -1612410054
    //   161: l2i
    //   162: ldc 1958616242
    //   164: ixor
    //   165: ixor
    //   166: lookupswitch default -> 192, 279374463 -> 336, 320703056 -> 151
    //   192: putstatic bigname/zprestige/webhack/features/modules/Combat/CrystalAura$RotateMode.Off : Lbigname/zprestige/webhack/features/modules/Combat/CrystalAura$RotateMode;
    //   195: ldc2_w 116663738
    //   198: l2i
    //   199: ldc 116663739
    //   201: ixor
    //   202: anewarray bigname/zprestige/webhack/features/modules/Combat/CrystalAura$RotateMode
    //   205: dup
    //   206: ldc2_w 1061362319
    //   209: l2i
    //   210: ldc 1061362319
    //   212: ixor
    //   213: getstatic Perryc.1 : I
    //   216: ifeq -> 229
    //   219: ldc2_w -1853167193
    //   222: l2i
    //   223: ldc -848744579
    //   225: ixor
    //   226: goto -> 236
    //   229: ldc2_w -1949693258
    //   232: l2i
    //   233: ldc -293001367
    //   235: ixor
    //   236: ldc2_w 740867018
    //   239: l2i
    //   240: ldc -1386891198
    //   242: ixor
    //   243: ixor
    //   244: lookupswitch default -> 340, -576797358 -> 229, -465686953 -> 272
    //   272: getstatic bigname/zprestige/webhack/features/modules/Combat/CrystalAura$RotateMode.Off : Lbigname/zprestige/webhack/features/modules/Combat/CrystalAura$RotateMode;
    //   275: aastore
    //   276: getstatic Perryc.1 : I
    //   279: ifeq -> 292
    //   282: ldc2_w -1944406949
    //   285: l2i
    //   286: ldc 29636081
    //   288: ixor
    //   289: goto -> 299
    //   292: ldc2_w 2053705125
    //   295: l2i
    //   296: ldc 1108921023
    //   298: ixor
    //   299: ldc2_w -468920242
    //   302: l2i
    //   303: ldc -940701786
    //   305: ixor
    //   306: ixor
    //   307: lookupswitch default -> 332, -1371775422 -> 338, -777233777 -> 292
    //   332: putstatic bigname/zprestige/webhack/features/modules/Combat/CrystalAura$RotateMode.$VALUES : [Lbigname/zprestige/webhack/features/modules/Combat/CrystalAura$RotateMode;
    //   335: return
    //   336: aconst_null
    //   337: athrow
    //   338: aconst_null
    //   339: athrow
    //   340: aconst_null
    //   341: athrow
    //   342: aconst_null
    //   343: athrow
    //   344: aconst_null
    //   345: athrow
  }
}


/* Location:              C:\Users\alex\Desktop\webhack\WebHack-0.8-obf_sussy_1.jar!\bigname\zprestige\webhack\features\modules\Combat\CrystalAura$RotateMode.class
 * Java compiler version: 8 (52.0)
 * JD-Core Version:       1.1.3
 */