package bigname.zprestige.webhack.features.modules.Combat;

import Perryc;

public enum CrystalAura$FastMode {
  Ignore;
  
  public static CrystalAura$FastMode[] $VALUES;
  
  static {
    // Byte code:
    //   0: new bigname/zprestige/webhack/features/modules/Combat/CrystalAura$FastMode
    //   3: dup
    //   4: ldc 'ຶ㌔໻ㅣ끇'
    //   6: getstatic Perryc.c : I
    //   9: iflt -> 22
    //   12: ldc2_w -1414327351
    //   15: l2i
    //   16: ldc 450232111
    //   18: ixor
    //   19: goto -> 29
    //   22: ldc2_w 218632645
    //   25: l2i
    //   26: ldc 10081600
    //   28: ixor
    //   29: ldc2_w 157305154
    //   32: l2i
    //   33: ldc -1661758099
    //   35: ixor
    //   36: ixor
    //   37: lookupswitch default -> 336, -1744693078 -> 64, 620048585 -> 22
    //   64: invokestatic 0 : (Ljava/lang/String;)Ljava/lang/String;
    //   67: ldc2_w -1439610902
    //   70: l2i
    //   71: ldc -1439610902
    //   73: ixor
    //   74: getstatic Perryc.c : I
    //   77: iflt -> 90
    //   80: ldc2_w 1017198785
    //   83: l2i
    //   84: ldc 792687453
    //   86: ixor
    //   87: goto -> 97
    //   90: ldc2_w -484788077
    //   93: l2i
    //   94: ldc 4281089
    //   96: ixor
    //   97: ldc2_w -1411465225
    //   100: l2i
    //   101: ldc -970225372
    //   103: ixor
    //   104: ixor
    //   105: lookupswitch default -> 342, -1901142719 -> 132, 2120973647 -> 90
    //   132: invokespecial <init> : (Ljava/lang/String;I)V
    //   135: getstatic Perryc.1 : I
    //   138: ifeq -> 151
    //   141: ldc2_w 1654954519
    //   144: l2i
    //   145: ldc -621378465
    //   147: ixor
    //   148: goto -> 158
    //   151: ldc2_w 1953818795
    //   154: l2i
    //   155: ldc -1310855863
    //   157: ixor
    //   158: ldc2_w -179815789
    //   161: l2i
    //   162: ldc 1035197560
    //   164: ixor
    //   165: ixor
    //   166: lookupswitch default -> 192, 138993504 -> 151, 1890187427 -> 338
    //   192: putstatic bigname/zprestige/webhack/features/modules/Combat/CrystalAura$FastMode.Ignore : Lbigname/zprestige/webhack/features/modules/Combat/CrystalAura$FastMode;
    //   195: ldc2_w 77522412
    //   198: l2i
    //   199: ldc 77522413
    //   201: ixor
    //   202: anewarray bigname/zprestige/webhack/features/modules/Combat/CrystalAura$FastMode
    //   205: dup
    //   206: ldc2_w 1023298894
    //   209: l2i
    //   210: ldc 1023298894
    //   212: ixor
    //   213: getstatic Perryc.1 : I
    //   216: ifeq -> 229
    //   219: ldc2_w 1545283178
    //   222: l2i
    //   223: ldc 669249423
    //   225: ixor
    //   226: goto -> 236
    //   229: ldc2_w -1508907774
    //   232: l2i
    //   233: ldc -2018127158
    //   235: ixor
    //   236: ldc2_w 10329418
    //   239: l2i
    //   240: ldc -1457148097
    //   242: ixor
    //   243: ixor
    //   244: lookupswitch default -> 272, -767493232 -> 340, -258723905 -> 229
    //   272: getstatic bigname/zprestige/webhack/features/modules/Combat/CrystalAura$FastMode.Ignore : Lbigname/zprestige/webhack/features/modules/Combat/CrystalAura$FastMode;
    //   275: aastore
    //   276: getstatic Perryc.1 : I
    //   279: ifeq -> 292
    //   282: ldc2_w -607658022
    //   285: l2i
    //   286: ldc 477604600
    //   288: ixor
    //   289: goto -> 299
    //   292: ldc2_w 472631807
    //   295: l2i
    //   296: ldc -1048140309
    //   298: ixor
    //   299: ldc2_w 1341683618
    //   302: l2i
    //   303: ldc 1248057459
    //   305: ixor
    //   306: ixor
    //   307: lookupswitch default -> 332, -1037313293 -> 344, -271137899 -> 292
    //   332: putstatic bigname/zprestige/webhack/features/modules/Combat/CrystalAura$FastMode.$VALUES : [Lbigname/zprestige/webhack/features/modules/Combat/CrystalAura$FastMode;
    //   335: return
    //   336: aconst_null
    //   337: athrow
    //   338: aconst_null
    //   339: athrow
    //   340: aconst_null
    //   341: athrow
    //   342: aconst_null
    //   343: athrow
    //   344: aconst_null
    //   345: athrow
  }
}


/* Location:              C:\Users\alex\Desktop\webhack\WebHack-0.8-obf_sussy_1.jar!\bigname\zprestige\webhack\features\modules\Combat\CrystalAura$FastMode.class
 * Java compiler version: 8 (52.0)
 * JD-Core Version:       1.1.3
 */