package bigname.zprestige.webhack.features.modules.Combat;

import Perryc;

public enum HoleFiller$Settings {
  SETTINGS;
  
  public static HoleFiller$Settings[] $VALUES;
  
  static {
    // Byte code:
    //   0: new bigname/zprestige/webhack/features/modules/Combat/HoleFiller$Settings
    //   3: dup
    //   4: ldc '繝㌶縰ㅘ쀯郼๞ϰ'
    //   6: getstatic Perryc.0 : I
    //   9: ifle -> 22
    //   12: ldc2_w 1236527763
    //   15: l2i
    //   16: ldc 1747477941
    //   18: ixor
    //   19: goto -> 29
    //   22: ldc2_w -2067000596
    //   25: l2i
    //   26: ldc 269344812
    //   28: ixor
    //   29: ldc2_w 1788906679
    //   32: l2i
    //   33: ldc 455082337
    //   35: ixor
    //   36: ixor
    //   37: lookupswitch default -> 64, -132688150 -> 22, 1343947504 -> 340
    //   64: invokestatic 0 : (Ljava/lang/String;)Ljava/lang/String;
    //   67: ldc2_w -1154972025
    //   70: l2i
    //   71: ldc -1154972025
    //   73: ixor
    //   74: getstatic Perryc.0 : I
    //   77: ifle -> 90
    //   80: ldc2_w 381880314
    //   83: l2i
    //   84: ldc 765047158
    //   86: ixor
    //   87: goto -> 97
    //   90: ldc2_w -492484470
    //   93: l2i
    //   94: ldc -764767865
    //   96: ixor
    //   97: ldc2_w -1470774132
    //   100: l2i
    //   101: ldc 1209652688
    //   103: ixor
    //   104: ixor
    //   105: lookupswitch default -> 132, -619272240 -> 338, 1891692106 -> 90
    //   132: invokespecial <init> : (Ljava/lang/String;I)V
    //   135: getstatic Perryc.0 : I
    //   138: ifle -> 151
    //   141: ldc2_w 2145610719
    //   144: l2i
    //   145: ldc 1257352078
    //   147: ixor
    //   148: goto -> 158
    //   151: ldc2_w -1228276881
    //   154: l2i
    //   155: ldc -49541796
    //   157: ixor
    //   158: ldc2_w -8378743
    //   161: l2i
    //   162: ldc 480014965
    //   164: ixor
    //   165: ixor
    //   166: lookupswitch default -> 192, -1032317112 -> 151, -703687507 -> 342
    //   192: putstatic bigname/zprestige/webhack/features/modules/Combat/HoleFiller$Settings.SETTINGS : Lbigname/zprestige/webhack/features/modules/Combat/HoleFiller$Settings;
    //   195: ldc2_w -755208692
    //   198: l2i
    //   199: ldc -755208691
    //   201: ixor
    //   202: anewarray bigname/zprestige/webhack/features/modules/Combat/HoleFiller$Settings
    //   205: dup
    //   206: ldc2_w 1254340433
    //   209: l2i
    //   210: ldc 1254340433
    //   212: ixor
    //   213: getstatic Perryc.0 : I
    //   216: ifle -> 229
    //   219: ldc2_w -826666654
    //   222: l2i
    //   223: ldc -245226101
    //   225: ixor
    //   226: goto -> 236
    //   229: ldc2_w -1560554753
    //   232: l2i
    //   233: ldc -608067037
    //   235: ixor
    //   236: ldc2_w -589999711
    //   239: l2i
    //   240: ldc -919747792
    //   242: ixor
    //   243: ixor
    //   244: lookupswitch default -> 272, -277056932 -> 229, 706782840 -> 344
    //   272: getstatic bigname/zprestige/webhack/features/modules/Combat/HoleFiller$Settings.SETTINGS : Lbigname/zprestige/webhack/features/modules/Combat/HoleFiller$Settings;
    //   275: aastore
    //   276: getstatic Perryc.0 : I
    //   279: ifle -> 292
    //   282: ldc2_w 2057177569
    //   285: l2i
    //   286: ldc 1533328365
    //   288: ixor
    //   289: goto -> 299
    //   292: ldc2_w 2031342787
    //   295: l2i
    //   296: ldc -2034151848
    //   298: ixor
    //   299: ldc2_w -1708007680
    //   302: l2i
    //   303: ldc 307883268
    //   305: ixor
    //   306: ixor
    //   307: lookupswitch default -> 336, -1450016760 -> 292, 2008721567 -> 332
    //   332: putstatic bigname/zprestige/webhack/features/modules/Combat/HoleFiller$Settings.$VALUES : [Lbigname/zprestige/webhack/features/modules/Combat/HoleFiller$Settings;
    //   335: return
    //   336: aconst_null
    //   337: athrow
    //   338: aconst_null
    //   339: athrow
    //   340: aconst_null
    //   341: athrow
    //   342: aconst_null
    //   343: athrow
    //   344: aconst_null
    //   345: athrow
  }
}


/* Location:              C:\Users\alex\Desktop\webhack\WebHack-0.8-obf_sussy_1.jar!\bigname\zprestige\webhack\features\modules\Combat\HoleFiller$Settings.class
 * Java compiler version: 8 (52.0)
 * JD-Core Version:       1.1.3
 */