package bigname.zprestige.webhack.features.modules.Combat;

public class Offhand$1 {
  public static int[] $SwitchMap$bigname$zprestige$webhack$features$modules$Combat$Offhand$Mode2;
  
  static {
    // Byte code:
    //   0: getstatic Perryc.c : I
    //   3: iflt -> 16
    //   6: ldc2_w 1123951546
    //   9: l2i
    //   10: ldc -1430675655
    //   12: ixor
    //   13: goto -> 23
    //   16: ldc2_w -1389864985
    //   19: l2i
    //   20: ldc 595145382
    //   22: ixor
    //   23: ldc2_w 621028012
    //   26: l2i
    //   27: ldc 113952507
    //   29: ixor
    //   30: ixor
    //   31: lookupswitch default -> 56, -880191276 -> 640, 925714465 -> 16
    //   56: invokestatic values : ()[Lbigname/zprestige/webhack/features/modules/Combat/Offhand$Mode2;
    //   59: arraylength
    //   60: newarray int
    //   62: getstatic Perryc.0 : I
    //   65: ifle -> 78
    //   68: ldc2_w -1933273443
    //   71: l2i
    //   72: ldc 1984248866
    //   74: ixor
    //   75: goto -> 85
    //   78: ldc2_w -346486337
    //   81: l2i
    //   82: ldc -429267337
    //   84: ixor
    //   85: ldc2_w 1544667886
    //   88: l2i
    //   89: ldc -253781565
    //   91: ixor
    //   92: ixor
    //   93: lookupswitch default -> 626, -1577143067 -> 120, 1448079762 -> 78
    //   120: putstatic bigname/zprestige/webhack/features/modules/Combat/Offhand$1.$SwitchMap$bigname$zprestige$webhack$features$modules$Combat$Offhand$Mode2 : [I
    //   123: getstatic Perryc.1 : I
    //   126: ifeq -> 139
    //   129: ldc2_w -584602600
    //   132: l2i
    //   133: ldc 1566465409
    //   135: ixor
    //   136: goto -> 146
    //   139: ldc2_w -1706159273
    //   142: l2i
    //   143: ldc 960542205
    //   145: ixor
    //   146: ldc2_w -311058182
    //   149: l2i
    //   150: ldc -214681078
    //   152: ixor
    //   153: ixor
    //   154: lookupswitch default -> 634, -1640469655 -> 139, -1118880678 -> 180
    //   180: getstatic bigname/zprestige/webhack/features/modules/Combat/Offhand$1.$SwitchMap$bigname$zprestige$webhack$features$modules$Combat$Offhand$Mode2 : [I
    //   183: getstatic Perryc.1 : I
    //   186: ifeq -> 199
    //   189: ldc2_w 108800850
    //   192: l2i
    //   193: ldc -5785146
    //   195: ixor
    //   196: goto -> 206
    //   199: ldc2_w -908592720
    //   202: l2i
    //   203: ldc -324406374
    //   205: ixor
    //   206: ldc2_w 1678636774
    //   209: l2i
    //   210: ldc -1130085047
    //   212: ixor
    //   213: ixor
    //   214: lookupswitch default -> 630, -36193915 -> 240, 561127739 -> 199
    //   240: getstatic bigname/zprestige/webhack/features/modules/Combat/Offhand$Mode2.TOTEMS : Lbigname/zprestige/webhack/features/modules/Combat/Offhand$Mode2;
    //   243: getstatic Perryc.1 : I
    //   246: ifeq -> 259
    //   249: ldc2_w -2122628425
    //   252: l2i
    //   253: ldc -356862166
    //   255: ixor
    //   256: goto -> 266
    //   259: ldc2_w 432512517
    //   262: l2i
    //   263: ldc -267635197
    //   265: ixor
    //   266: ldc2_w -448307014
    //   269: l2i
    //   270: ldc 425743973
    //   272: ixor
    //   273: ixor
    //   274: lookupswitch default -> 632, -1746484414 -> 259, 367828697 -> 300
    //   300: invokevirtual ordinal : ()I
    //   303: ldc2_w -1201735534
    //   306: l2i
    //   307: ldc -1201735533
    //   309: ixor
    //   310: iastore
    //   311: goto -> 373
    //   314: getstatic Perryc.1 : I
    //   317: ifeq -> 330
    //   320: ldc2_w 585220838
    //   323: l2i
    //   324: ldc 918929294
    //   326: ixor
    //   327: goto -> 337
    //   330: ldc2_w -1148110288
    //   333: l2i
    //   334: ldc 1343824399
    //   336: ixor
    //   337: ldc2_w -1781396845
    //   340: l2i
    //   341: ldc 1471616738
    //   343: ixor
    //   344: ixor
    //   345: lookupswitch default -> 636, -700358375 -> 330, 703398990 -> 372
    //   372: astore_0
    //   373: getstatic Perryc.0 : I
    //   376: ifle -> 389
    //   379: ldc2_w -1296783154
    //   382: l2i
    //   383: ldc 895200437
    //   385: ixor
    //   386: goto -> 396
    //   389: ldc2_w -339474928
    //   392: l2i
    //   393: ldc -1436127970
    //   395: ixor
    //   396: ldc2_w -58526289
    //   399: l2i
    //   400: ldc 1565286298
    //   402: ixor
    //   403: ixor
    //   404: lookupswitch default -> 432, -1616886188 -> 389, 639741518 -> 644
    //   432: getstatic bigname/zprestige/webhack/features/modules/Combat/Offhand$1.$SwitchMap$bigname$zprestige$webhack$features$modules$Combat$Offhand$Mode2 : [I
    //   435: getstatic Perryc.1 : I
    //   438: ifeq -> 451
    //   441: ldc2_w -1253353526
    //   444: l2i
    //   445: ldc 1324012824
    //   447: ixor
    //   448: goto -> 458
    //   451: ldc2_w -955202403
    //   454: l2i
    //   455: ldc -1214019733
    //   457: ixor
    //   458: ldc2_w -60541936
    //   461: l2i
    //   462: ldc -654958819
    //   464: ixor
    //   465: ixor
    //   466: lookupswitch default -> 492, -550262305 -> 642, -460677933 -> 451
    //   492: getstatic bigname/zprestige/webhack/features/modules/Combat/Offhand$Mode2.GAPPLES : Lbigname/zprestige/webhack/features/modules/Combat/Offhand$Mode2;
    //   495: getstatic Perryc.c : I
    //   498: iflt -> 511
    //   501: ldc2_w -917799987
    //   504: l2i
    //   505: ldc 732296309
    //   507: ixor
    //   508: goto -> 518
    //   511: ldc2_w -1473047410
    //   514: l2i
    //   515: ldc 1710199800
    //   517: ixor
    //   518: ldc2_w 1114387057
    //   521: l2i
    //   522: ldc -573583647
    //   524: ixor
    //   525: ixor
    //   526: lookupswitch default -> 552, -1474612629 -> 511, 2102227752 -> 638
    //   552: invokevirtual ordinal : ()I
    //   555: ldc2_w -1964619566
    //   558: l2i
    //   559: ldc -1964619568
    //   561: ixor
    //   562: iastore
    //   563: goto -> 625
    //   566: getstatic Perryc.c : I
    //   569: iflt -> 582
    //   572: ldc2_w -1219692782
    //   575: l2i
    //   576: ldc 1651307501
    //   578: ixor
    //   579: goto -> 589
    //   582: ldc2_w 1622747237
    //   585: l2i
    //   586: ldc -214349074
    //   588: ixor
    //   589: ldc2_w -1326849983
    //   592: l2i
    //   593: ldc -1534305867
    //   595: ixor
    //   596: ixor
    //   597: lookupswitch default -> 628, -2014979201 -> 624, -1052394229 -> 582
    //   624: astore_0
    //   625: return
    //   626: aconst_null
    //   627: athrow
    //   628: aconst_null
    //   629: athrow
    //   630: aconst_null
    //   631: athrow
    //   632: aconst_null
    //   633: athrow
    //   634: aconst_null
    //   635: athrow
    //   636: aconst_null
    //   637: athrow
    //   638: aconst_null
    //   639: athrow
    //   640: aconst_null
    //   641: athrow
    //   642: aconst_null
    //   643: athrow
    //   644: aconst_null
    //   645: athrow
    // Exception table:
    //   from	to	target	type
    //   123	311	314	java/lang/NoSuchFieldError
    //   373	563	566	java/lang/NoSuchFieldError
  }
}


/* Location:              C:\Users\alex\Desktop\webhack\WebHack-0.8-obf_sussy_1.jar!\bigname\zprestige\webhack\features\modules\Combat\Offhand$1.class
 * Java compiler version: 8 (52.0)
 * JD-Core Version:       1.1.3
 */