package bigname.zprestige.webhack.features.modules.Combat;

import Perryc;

public enum Offhand2$Mode2 {
  GAPPLES, TOTEMS, CRYSTALS;
  
  public static Offhand2$Mode2[] $VALUES;
  
  static {
    // Byte code:
    //   0: new bigname/zprestige/webhack/features/modules/Combat/Offhand2$Mode2
    //   3: dup
    //   4: ldc 'ꛤ㌼Ꚗㅉࡍ䡟'
    //   6: getstatic Perryc.0 : I
    //   9: ifle -> 22
    //   12: ldc2_w 625266496
    //   15: l2i
    //   16: ldc 1344963281
    //   18: ixor
    //   19: goto -> 29
    //   22: ldc2_w 2074223714
    //   25: l2i
    //   26: ldc 107508585
    //   28: ixor
    //   29: ldc2_w -2005069653
    //   32: l2i
    //   33: ldc 1046598219
    //   35: ixor
    //   36: ixor
    //   37: lookupswitch default -> 64, -1015902351 -> 864, 1030399058 -> 22
    //   64: invokestatic 0 : (Ljava/lang/String;)Ljava/lang/String;
    //   67: ldc2_w -864716433
    //   70: l2i
    //   71: ldc -864716433
    //   73: ixor
    //   74: getstatic Perryc.c : I
    //   77: iflt -> 90
    //   80: ldc2_w -160943143
    //   83: l2i
    //   84: ldc -720227152
    //   86: ixor
    //   87: goto -> 97
    //   90: ldc2_w 218584798
    //   93: l2i
    //   94: ldc 2139533346
    //   96: ixor
    //   97: ldc2_w -178561156
    //   100: l2i
    //   101: ldc -312940054
    //   103: ixor
    //   104: ixor
    //   105: lookupswitch default -> 132, -1463820694 -> 90, 997831167 -> 878
    //   132: invokespecial <init> : (Ljava/lang/String;I)V
    //   135: getstatic Perryc.0 : I
    //   138: ifle -> 151
    //   141: ldc2_w 528353621
    //   144: l2i
    //   145: ldc -829898526
    //   147: ixor
    //   148: goto -> 158
    //   151: ldc2_w 1585012370
    //   154: l2i
    //   155: ldc 452095246
    //   157: ixor
    //   158: ldc2_w -1597311938
    //   161: l2i
    //   162: ldc -2011644027
    //   164: ixor
    //   165: ixor
    //   166: lookupswitch default -> 880, -115047924 -> 151, 1817802791 -> 192
    //   192: putstatic bigname/zprestige/webhack/features/modules/Combat/Offhand2$Mode2.TOTEMS : Lbigname/zprestige/webhack/features/modules/Combat/Offhand2$Mode2;
    //   195: new bigname/zprestige/webhack/features/modules/Combat/Offhand2$Mode2
    //   198: dup
    //   199: ldc '꛷㌲Ꚓㅜࡌ䡉๊'
    //   201: getstatic Perryc.c : I
    //   204: iflt -> 217
    //   207: ldc2_w 2121093532
    //   210: l2i
    //   211: ldc -1404406541
    //   213: ixor
    //   214: goto -> 224
    //   217: ldc2_w 802525058
    //   220: l2i
    //   221: ldc 2145605473
    //   223: ixor
    //   224: ldc2_w -1251707730
    //   227: l2i
    //   228: ldc 2128093480
    //   230: ixor
    //   231: ixor
    //   232: lookupswitch default -> 260, -1117902053 -> 217, 429617385 -> 886
    //   260: invokestatic 0 : (Ljava/lang/String;)Ljava/lang/String;
    //   263: ldc2_w 1895372462
    //   266: l2i
    //   267: ldc 1895372463
    //   269: ixor
    //   270: getstatic Perryc.c : I
    //   273: iflt -> 286
    //   276: ldc2_w 168049183
    //   279: l2i
    //   280: ldc -1170248242
    //   282: ixor
    //   283: goto -> 293
    //   286: ldc2_w -900729213
    //   289: l2i
    //   290: ldc -584690422
    //   292: ixor
    //   293: ldc2_w 1999576204
    //   296: l2i
    //   297: ldc -314026276
    //   299: ixor
    //   300: ixor
    //   301: lookupswitch default -> 328, 710679937 -> 882, 1607175504 -> 286
    //   328: invokespecial <init> : (Ljava/lang/String;I)V
    //   331: getstatic Perryc.0 : I
    //   334: ifle -> 347
    //   337: ldc2_w 253370575
    //   340: l2i
    //   341: ldc -122116231
    //   343: ixor
    //   344: goto -> 354
    //   347: ldc2_w 1681425454
    //   350: l2i
    //   351: ldc -1317218076
    //   353: ixor
    //   354: ldc2_w 1649510310
    //   357: l2i
    //   358: ldc 944556649
    //   360: ixor
    //   361: ixor
    //   362: lookupswitch default -> 876, -1889988347 -> 388, -1379939719 -> 347
    //   388: putstatic bigname/zprestige/webhack/features/modules/Combat/Offhand2$Mode2.GAPPLES : Lbigname/zprestige/webhack/features/modules/Combat/Offhand2$Mode2;
    //   391: new bigname/zprestige/webhack/features/modules/Combat/Offhand2$Mode2
    //   394: dup
    //   395: ldc '꛳㌡ꚛㅟࡔ䡍๕?'
    //   397: getstatic Perryc.0 : I
    //   400: ifle -> 413
    //   403: ldc2_w -331133094
    //   406: l2i
    //   407: ldc -1429111138
    //   409: ixor
    //   410: goto -> 420
    //   413: ldc2_w 1520740517
    //   416: l2i
    //   417: ldc -1410009839
    //   419: ixor
    //   420: ldc2_w 38246928
    //   423: l2i
    //   424: ldc 710013121
    //   426: ixor
    //   427: ixor
    //   428: lookupswitch default -> 456, -1992526440 -> 413, 1854167829 -> 884
    //   456: invokestatic 0 : (Ljava/lang/String;)Ljava/lang/String;
    //   459: ldc2_w 1876712674
    //   462: l2i
    //   463: ldc 1876712672
    //   465: ixor
    //   466: getstatic Perryc.1 : I
    //   469: ifeq -> 482
    //   472: ldc2_w 130168920
    //   475: l2i
    //   476: ldc -1010907654
    //   478: ixor
    //   479: goto -> 489
    //   482: ldc2_w 1417141363
    //   485: l2i
    //   486: ldc 661937024
    //   488: ixor
    //   489: ldc2_w 1765390984
    //   492: l2i
    //   493: ldc -1421680813
    //   495: ixor
    //   496: ixor
    //   497: lookupswitch default -> 874, -1317477848 -> 524, 101161081 -> 482
    //   524: invokespecial <init> : (Ljava/lang/String;I)V
    //   527: getstatic Perryc.0 : I
    //   530: ifle -> 543
    //   533: ldc2_w -984570365
    //   536: l2i
    //   537: ldc -809580910
    //   539: ixor
    //   540: goto -> 550
    //   543: ldc2_w 1629980614
    //   546: l2i
    //   547: ldc -778603553
    //   549: ixor
    //   550: ldc2_w 1006684858
    //   553: l2i
    //   554: ldc 308378388
    //   556: ixor
    //   557: ixor
    //   558: lookupswitch default -> 870, -1630452297 -> 584, 613404991 -> 543
    //   584: putstatic bigname/zprestige/webhack/features/modules/Combat/Offhand2$Mode2.CRYSTALS : Lbigname/zprestige/webhack/features/modules/Combat/Offhand2$Mode2;
    //   587: ldc2_w 592175331
    //   590: l2i
    //   591: ldc 592175328
    //   593: ixor
    //   594: anewarray bigname/zprestige/webhack/features/modules/Combat/Offhand2$Mode2
    //   597: dup
    //   598: ldc2_w -1705394732
    //   601: l2i
    //   602: ldc -1705394732
    //   604: ixor
    //   605: getstatic Perryc.1 : I
    //   608: ifeq -> 621
    //   611: ldc2_w 1538721030
    //   614: l2i
    //   615: ldc -1485857364
    //   617: ixor
    //   618: goto -> 628
    //   621: ldc2_w -1743529806
    //   624: l2i
    //   625: ldc 1851387688
    //   627: ixor
    //   628: ldc2_w -240493403
    //   631: l2i
    //   632: ldc 842762420
    //   634: ixor
    //   635: ixor
    //   636: lookupswitch default -> 866, 903603083 -> 664, 1061768379 -> 621
    //   664: getstatic bigname/zprestige/webhack/features/modules/Combat/Offhand2$Mode2.TOTEMS : Lbigname/zprestige/webhack/features/modules/Combat/Offhand2$Mode2;
    //   667: aastore
    //   668: dup
    //   669: ldc2_w -288095650
    //   672: l2i
    //   673: ldc -288095649
    //   675: ixor
    //   676: getstatic Perryc.c : I
    //   679: iflt -> 692
    //   682: ldc2_w 1139178656
    //   685: l2i
    //   686: ldc -1057225417
    //   688: ixor
    //   689: goto -> 699
    //   692: ldc2_w -1238927870
    //   695: l2i
    //   696: ldc -1914763554
    //   698: ixor
    //   699: ldc2_w -366303807
    //   702: l2i
    //   703: ldc -1713844028
    //   705: ixor
    //   706: ixor
    //   707: lookupswitch default -> 868, -253227886 -> 692, 1208616409 -> 732
    //   732: getstatic bigname/zprestige/webhack/features/modules/Combat/Offhand2$Mode2.GAPPLES : Lbigname/zprestige/webhack/features/modules/Combat/Offhand2$Mode2;
    //   735: aastore
    //   736: dup
    //   737: ldc2_w -1550052660
    //   740: l2i
    //   741: ldc -1550052658
    //   743: ixor
    //   744: getstatic Perryc.1 : I
    //   747: ifeq -> 760
    //   750: ldc2_w 727166820
    //   753: l2i
    //   754: ldc -1643679114
    //   756: ixor
    //   757: goto -> 767
    //   760: ldc2_w -1179776553
    //   763: l2i
    //   764: ldc 1619368479
    //   766: ixor
    //   767: ldc2_w -469483742
    //   770: l2i
    //   771: ldc 1615175272
    //   773: ixor
    //   774: ixor
    //   775: lookupswitch default -> 800, 236731996 -> 760, 823229528 -> 872
    //   800: getstatic bigname/zprestige/webhack/features/modules/Combat/Offhand2$Mode2.CRYSTALS : Lbigname/zprestige/webhack/features/modules/Combat/Offhand2$Mode2;
    //   803: aastore
    //   804: getstatic Perryc.1 : I
    //   807: ifeq -> 820
    //   810: ldc2_w -1295867950
    //   813: l2i
    //   814: ldc -1227182712
    //   816: ixor
    //   817: goto -> 827
    //   820: ldc2_w 1821267113
    //   823: l2i
    //   824: ldc -1032194109
    //   826: ixor
    //   827: ldc2_w -1096666044
    //   830: l2i
    //   831: ldc -1253548978
    //   833: ixor
    //   834: ixor
    //   835: lookupswitch default -> 888, -1524774048 -> 860, 267541072 -> 820
    //   860: putstatic bigname/zprestige/webhack/features/modules/Combat/Offhand2$Mode2.$VALUES : [Lbigname/zprestige/webhack/features/modules/Combat/Offhand2$Mode2;
    //   863: return
    //   864: aconst_null
    //   865: athrow
    //   866: aconst_null
    //   867: athrow
    //   868: aconst_null
    //   869: athrow
    //   870: aconst_null
    //   871: athrow
    //   872: aconst_null
    //   873: athrow
    //   874: aconst_null
    //   875: athrow
    //   876: aconst_null
    //   877: athrow
    //   878: aconst_null
    //   879: athrow
    //   880: aconst_null
    //   881: athrow
    //   882: aconst_null
    //   883: athrow
    //   884: aconst_null
    //   885: athrow
    //   886: aconst_null
    //   887: athrow
    //   888: aconst_null
    //   889: athrow
  }
}


/* Location:              C:\Users\alex\Desktop\webhack\WebHack-0.8-obf_sussy_1.jar!\bigname\zprestige\webhack\features\modules\Combat\Offhand2$Mode2.class
 * Java compiler version: 8 (52.0)
 * JD-Core Version:       1.1.3
 */