package bigname.zprestige.webhack.features.modules.Combat;

public class Offhand2$1 {
  public static int[] $SwitchMap$bigname$zprestige$webhack$features$modules$Combat$Offhand2$Mode2;
  
  static {
    // Byte code:
    //   0: getstatic Perryc.c : I
    //   3: iflt -> 16
    //   6: ldc2_w 1002861709
    //   9: l2i
    //   10: ldc 167213651
    //   12: ixor
    //   13: goto -> 23
    //   16: ldc2_w -1545866646
    //   19: l2i
    //   20: ldc 339916506
    //   22: ixor
    //   23: ldc2_w -500866849
    //   26: l2i
    //   27: ldc -1015675552
    //   29: ixor
    //   30: ixor
    //   31: lookupswitch default -> 56, 325217121 -> 642, 1132670667 -> 16
    //   56: invokestatic values : ()[Lbigname/zprestige/webhack/features/modules/Combat/Offhand2$Mode2;
    //   59: arraylength
    //   60: newarray int
    //   62: getstatic Perryc.1 : I
    //   65: ifeq -> 78
    //   68: ldc2_w 1649407629
    //   71: l2i
    //   72: ldc -1001954612
    //   74: ixor
    //   75: goto -> 85
    //   78: ldc2_w -361915161
    //   81: l2i
    //   82: ldc 355419724
    //   84: ixor
    //   85: ldc2_w 1155550138
    //   88: l2i
    //   89: ldc 481655963
    //   91: ixor
    //   92: ixor
    //   93: lookupswitch default -> 638, -1491604086 -> 120, -27417760 -> 78
    //   120: putstatic bigname/zprestige/webhack/features/modules/Combat/Offhand2$1.$SwitchMap$bigname$zprestige$webhack$features$modules$Combat$Offhand2$Mode2 : [I
    //   123: getstatic Perryc.c : I
    //   126: iflt -> 139
    //   129: ldc2_w -1737978824
    //   132: l2i
    //   133: ldc 1447741920
    //   135: ixor
    //   136: goto -> 146
    //   139: ldc2_w 111835694
    //   142: l2i
    //   143: ldc -629273817
    //   145: ixor
    //   146: ldc2_w 1023941
    //   149: l2i
    //   150: ldc 2004227953
    //   152: ixor
    //   153: ixor
    //   154: lookupswitch default -> 644, -1414661699 -> 180, -1185165972 -> 139
    //   180: getstatic bigname/zprestige/webhack/features/modules/Combat/Offhand2$1.$SwitchMap$bigname$zprestige$webhack$features$modules$Combat$Offhand2$Mode2 : [I
    //   183: getstatic Perryc.0 : I
    //   186: ifle -> 199
    //   189: ldc2_w 1013836393
    //   192: l2i
    //   193: ldc 1001299489
    //   195: ixor
    //   196: goto -> 206
    //   199: ldc2_w 467758347
    //   202: l2i
    //   203: ldc 922783902
    //   205: ixor
    //   206: ldc2_w 1244384429
    //   209: l2i
    //   210: ldc -979754005
    //   212: ixor
    //   213: ixor
    //   214: lookupswitch default -> 626, -2005755122 -> 199, -1555033389 -> 240
    //   240: getstatic bigname/zprestige/webhack/features/modules/Combat/Offhand2$Mode2.TOTEMS : Lbigname/zprestige/webhack/features/modules/Combat/Offhand2$Mode2;
    //   243: getstatic Perryc.c : I
    //   246: iflt -> 259
    //   249: ldc2_w 507965180
    //   252: l2i
    //   253: ldc 1879482539
    //   255: ixor
    //   256: goto -> 266
    //   259: ldc2_w -1581933135
    //   262: l2i
    //   263: ldc -980476245
    //   265: ixor
    //   266: ldc2_w 192734951
    //   269: l2i
    //   270: ldc 2021251456
    //   272: ixor
    //   273: ixor
    //   274: lookupswitch default -> 636, 390052989 -> 300, 491090224 -> 259
    //   300: invokevirtual ordinal : ()I
    //   303: ldc2_w 791699625
    //   306: l2i
    //   307: ldc 791699624
    //   309: ixor
    //   310: iastore
    //   311: goto -> 373
    //   314: getstatic Perryc.c : I
    //   317: iflt -> 330
    //   320: ldc2_w -911532430
    //   323: l2i
    //   324: ldc -1086898056
    //   326: ixor
    //   327: goto -> 337
    //   330: ldc2_w 654692771
    //   333: l2i
    //   334: ldc -1375478076
    //   336: ixor
    //   337: ldc2_w 1554831595
    //   340: l2i
    //   341: ldc -96466383
    //   343: ixor
    //   344: ixor
    //   345: lookupswitch default -> 372, -1420793757 -> 330, -797930288 -> 628
    //   372: astore_0
    //   373: getstatic Perryc.c : I
    //   376: iflt -> 389
    //   379: ldc2_w -336049521
    //   382: l2i
    //   383: ldc 603203978
    //   385: ixor
    //   386: goto -> 396
    //   389: ldc2_w 393444172
    //   392: l2i
    //   393: ldc -2005774345
    //   395: ixor
    //   396: ldc2_w 1028177021
    //   399: l2i
    //   400: ldc -856944059
    //   402: ixor
    //   403: ixor
    //   404: lookupswitch default -> 432, -747466740 -> 389, 967363901 -> 634
    //   432: getstatic bigname/zprestige/webhack/features/modules/Combat/Offhand2$1.$SwitchMap$bigname$zprestige$webhack$features$modules$Combat$Offhand2$Mode2 : [I
    //   435: getstatic Perryc.c : I
    //   438: iflt -> 451
    //   441: ldc2_w -481758959
    //   444: l2i
    //   445: ldc -1534074682
    //   447: ixor
    //   448: goto -> 458
    //   451: ldc2_w 2115794373
    //   454: l2i
    //   455: ldc -723767758
    //   457: ixor
    //   458: ldc2_w 625065811
    //   461: l2i
    //   462: ldc -2009377955
    //   464: ixor
    //   465: ixor
    //   466: lookupswitch default -> 640, -356647463 -> 451, 129677305 -> 492
    //   492: getstatic bigname/zprestige/webhack/features/modules/Combat/Offhand2$Mode2.GAPPLES : Lbigname/zprestige/webhack/features/modules/Combat/Offhand2$Mode2;
    //   495: getstatic Perryc.0 : I
    //   498: ifle -> 511
    //   501: ldc2_w -2133631149
    //   504: l2i
    //   505: ldc 629768493
    //   507: ixor
    //   508: goto -> 518
    //   511: ldc2_w -1548003418
    //   514: l2i
    //   515: ldc 220765754
    //   517: ixor
    //   518: ldc2_w 975629234
    //   521: l2i
    //   522: ldc -204338779
    //   524: ixor
    //   525: ixor
    //   526: lookupswitch default -> 630, 1734814603 -> 552, 1823358057 -> 511
    //   552: invokevirtual ordinal : ()I
    //   555: ldc2_w 81582932
    //   558: l2i
    //   559: ldc 81582934
    //   561: ixor
    //   562: iastore
    //   563: goto -> 625
    //   566: getstatic Perryc.1 : I
    //   569: ifeq -> 582
    //   572: ldc2_w -1246916487
    //   575: l2i
    //   576: ldc 1190472403
    //   578: ixor
    //   579: goto -> 589
    //   582: ldc2_w 697501521
    //   585: l2i
    //   586: ldc 150142133
    //   588: ixor
    //   589: ldc2_w 1302817523
    //   592: l2i
    //   593: ldc 1034000809
    //   595: ixor
    //   596: ixor
    //   597: lookupswitch default -> 632, -2090972688 -> 582, 1365706942 -> 624
    //   624: astore_0
    //   625: return
    //   626: aconst_null
    //   627: athrow
    //   628: aconst_null
    //   629: athrow
    //   630: aconst_null
    //   631: athrow
    //   632: aconst_null
    //   633: athrow
    //   634: aconst_null
    //   635: athrow
    //   636: aconst_null
    //   637: athrow
    //   638: aconst_null
    //   639: athrow
    //   640: aconst_null
    //   641: athrow
    //   642: aconst_null
    //   643: athrow
    //   644: aconst_null
    //   645: athrow
    // Exception table:
    //   from	to	target	type
    //   123	311	314	java/lang/NoSuchFieldError
    //   373	563	566	java/lang/NoSuchFieldError
  }
}


/* Location:              C:\Users\alex\Desktop\webhack\WebHack-0.8-obf_sussy_1.jar!\bigname\zprestige\webhack\features\modules\Combat\Offhand2$1.class
 * Java compiler version: 8 (52.0)
 * JD-Core Version:       1.1.3
 */