package bigname.zprestige.webhack.util;

import Perryc;
import net.minecraft.util.math.AxisAlignedBB;

public class HoleUtil$HoleInfo {
  public AxisAlignedBB centre;
  
  public HoleUtil$BlockSafety safety;
  
  public HoleUtil$HoleType type;
  
  public void setSafety(HoleUtil$BlockSafety safety) {
    if (Perryc.0 <= 0) {
      null;
    } else {
      if (null != null)
        throw (Throwable)null; 
      null;
    } 
    if (null != null)
      throw (Throwable)null; 
    null;
  }
  
  public HoleUtil$HoleType getType() {
    if (Perryc.1 <= 0) {
      null;
    } else {
      if (null != null)
        throw (Throwable)null; 
      null;
    } 
    if (null != null)
      throw (Throwable)null; 
    null;
  }
  
  public void setType(HoleUtil$HoleType type) {
    if (Perryc.0 <= 0) {
      null;
    } else {
      if (null != null)
        throw (Throwable)null; 
      null;
    } 
    if (null != null)
      throw (Throwable)null; 
    null;
  }
  
  public HoleUtil$HoleInfo(HoleUtil$BlockSafety safety, HoleUtil$HoleType type) {
    // Byte code:
    //   0: getstatic Perryc.1 : I
    //   3: ifeq -> 16
    //   6: ldc2_w -1026146172
    //   9: l2i
    //   10: ldc -109137509
    //   12: ixor
    //   13: goto -> 23
    //   16: ldc2_w -713751769
    //   19: l2i
    //   20: ldc 1797574150
    //   22: ixor
    //   23: ldc2_w -537177370
    //   26: l2i
    //   27: ldc 1115493050
    //   29: ixor
    //   30: ixor
    //   31: lookupswitch default -> 486, -1506889405 -> 16, 601329021 -> 56
    //   56: aload_0
    //   57: getstatic Perryc.0 : I
    //   60: ifle -> 73
    //   63: ldc2_w 2005450125
    //   66: l2i
    //   67: ldc 1079922649
    //   69: ixor
    //   70: goto -> 80
    //   73: ldc2_w 461414015
    //   76: l2i
    //   77: ldc 335942223
    //   79: ixor
    //   80: ldc2_w -1397449863
    //   83: l2i
    //   84: ldc -2032757588
    //   86: ixor
    //   87: ixor
    //   88: lookupswitch default -> 116, 498400641 -> 488, 819014270 -> 73
    //   116: invokespecial <init> : ()V
    //   119: getstatic Perryc.0 : I
    //   122: ifle -> 135
    //   125: ldc2_w -982749023
    //   128: l2i
    //   129: ldc 569191969
    //   131: ixor
    //   132: goto -> 142
    //   135: ldc2_w 1107827259
    //   138: l2i
    //   139: ldc -1652203716
    //   141: ixor
    //   142: ldc2_w -1371152542
    //   145: l2i
    //   146: ldc -1282965367
    //   148: ixor
    //   149: ixor
    //   150: lookupswitch default -> 480, -1035003156 -> 176, -113049237 -> 135
    //   176: aload_0
    //   177: getstatic Perryc.0 : I
    //   180: ifle -> 193
    //   183: ldc2_w 1742433206
    //   186: l2i
    //   187: ldc 1606111996
    //   189: ixor
    //   190: goto -> 200
    //   193: ldc2_w 399351284
    //   196: l2i
    //   197: ldc 724525015
    //   199: ixor
    //   200: ldc2_w 529168670
    //   203: l2i
    //   204: ldc 409239298
    //   206: ixor
    //   207: ixor
    //   208: lookupswitch default -> 490, 990692415 -> 236, 1066286934 -> 193
    //   236: aload_2
    //   237: getstatic Perryc.0 : I
    //   240: ifle -> 253
    //   243: ldc2_w 2016189162
    //   246: l2i
    //   247: ldc -661009401
    //   249: ixor
    //   250: goto -> 260
    //   253: ldc2_w 1380160716
    //   256: l2i
    //   257: ldc 1770972216
    //   259: ixor
    //   260: ldc2_w -194768744
    //   263: l2i
    //   264: ldc 2086177299
    //   266: ixor
    //   267: ixor
    //   268: lookupswitch default -> 492, -1275991425 -> 296, 680119398 -> 253
    //   296: putfield type : Lbigname/zprestige/webhack/util/HoleUtil$HoleType;
    //   299: getstatic Perryc.1 : I
    //   302: ifeq -> 315
    //   305: ldc2_w -401125245
    //   308: l2i
    //   309: ldc 2104114943
    //   311: ixor
    //   312: goto -> 322
    //   315: ldc2_w 1359813900
    //   318: l2i
    //   319: ldc 153124569
    //   321: ixor
    //   322: ldc2_w 150208383
    //   325: l2i
    //   326: ldc 1516651188
    //   328: ixor
    //   329: ixor
    //   330: lookupswitch default -> 494, -941042761 -> 315, 179887646 -> 356
    //   356: aload_0
    //   357: getstatic Perryc.0 : I
    //   360: ifle -> 373
    //   363: ldc2_w -675194815
    //   366: l2i
    //   367: ldc 9831384
    //   369: ixor
    //   370: goto -> 380
    //   373: ldc2_w 376051823
    //   376: l2i
    //   377: ldc 1005576880
    //   379: ixor
    //   380: ldc2_w 84411739
    //   383: l2i
    //   384: ldc 1580635782
    //   386: ixor
    //   387: ixor
    //   388: lookupswitch default -> 482, -1939224508 -> 373, 1991993602 -> 416
    //   416: aload_1
    //   417: getstatic Perryc.0 : I
    //   420: ifle -> 433
    //   423: ldc2_w 1909910929
    //   426: l2i
    //   427: ldc 632154459
    //   429: ixor
    //   430: goto -> 440
    //   433: ldc2_w 1668429099
    //   436: l2i
    //   437: ldc 348321950
    //   439: ixor
    //   440: ldc2_w -243895675
    //   443: l2i
    //   444: ldc 781135875
    //   446: ixor
    //   447: ixor
    //   448: lookupswitch default -> 476, -1954396596 -> 484, -1025939205 -> 433
    //   476: putfield safety : Lbigname/zprestige/webhack/util/HoleUtil$BlockSafety;
    //   479: return
    //   480: aconst_null
    //   481: athrow
    //   482: aconst_null
    //   483: athrow
    //   484: aconst_null
    //   485: athrow
    //   486: aconst_null
    //   487: athrow
    //   488: aconst_null
    //   489: athrow
    //   490: aconst_null
    //   491: athrow
    //   492: aconst_null
    //   493: athrow
    //   494: aconst_null
    //   495: athrow
    // Local variable table:
    //   start	length	slot	name	descriptor
    //   0	480	0	this	Lbigname/zprestige/webhack/util/HoleUtil$HoleInfo;
    //   0	480	1	safety	Lbigname/zprestige/webhack/util/HoleUtil$BlockSafety;
    //   0	480	2	type	Lbigname/zprestige/webhack/util/HoleUtil$HoleType;
  }
  
  public AxisAlignedBB getCentre() {
    if (Perryc.0 <= 0) {
      null;
    } else {
      if (null != null)
        throw (Throwable)null; 
      null;
    } 
    if (null != null)
      throw (Throwable)null; 
    null;
  }
  
  public HoleUtil$BlockSafety getSafety() {
    if (Perryc.1 <= 0) {
      null;
    } else {
      if (null != null)
        throw (Throwable)null; 
      null;
    } 
    if (null != null)
      throw (Throwable)null; 
    null;
  }
  
  public HoleUtil$HoleInfo() {
    // Byte code:
    //   0: getstatic Perryc.c : I
    //   3: iflt -> 16
    //   6: ldc2_w -1371677309
    //   9: l2i
    //   10: ldc 1272457108
    //   12: ixor
    //   13: goto -> 23
    //   16: ldc2_w 203084995
    //   19: l2i
    //   20: ldc -656690907
    //   22: ixor
    //   23: ldc2_w -1551344188
    //   26: l2i
    //   27: ldc -1903665948
    //   29: ixor
    //   30: ixor
    //   31: lookupswitch default -> 56, -1062718957 -> 16, -924452041 -> 248
    //   56: aload_0
    //   57: getstatic Perryc.0 : I
    //   60: ifle -> 73
    //   63: ldc2_w -1275602273
    //   66: l2i
    //   67: ldc 1220081376
    //   69: ixor
    //   70: goto -> 80
    //   73: ldc2_w -1905094534
    //   76: l2i
    //   77: ldc -511422288
    //   79: ixor
    //   80: ldc2_w 347795099
    //   83: l2i
    //   84: ldc_w 397673430
    //   87: ixor
    //   88: ixor
    //   89: lookupswitch default -> 116, -129908430 -> 254, 107477562 -> 73
    //   116: getstatic bigname/zprestige/webhack/util/HoleUtil$BlockSafety.UNBREAKABLE : Lbigname/zprestige/webhack/util/HoleUtil$BlockSafety;
    //   119: getstatic Perryc.0 : I
    //   122: ifle -> 136
    //   125: ldc2_w -248651564
    //   128: l2i
    //   129: ldc_w -486956493
    //   132: ixor
    //   133: goto -> 144
    //   136: ldc2_w -163498318
    //   139: l2i
    //   140: ldc_w 1115170683
    //   143: ixor
    //   144: ldc2_w 510762377
    //   147: l2i
    //   148: ldc_w 1655066007
    //   151: ixor
    //   152: ixor
    //   153: lookupswitch default -> 252, -923876905 -> 180, 1862505209 -> 136
    //   180: getstatic bigname/zprestige/webhack/util/HoleUtil$HoleType.NONE : Lbigname/zprestige/webhack/util/HoleUtil$HoleType;
    //   183: getstatic Perryc.1 : I
    //   186: ifeq -> 200
    //   189: ldc2_w 426190204
    //   192: l2i
    //   193: ldc_w 1017725266
    //   196: ixor
    //   197: goto -> 208
    //   200: ldc2_w -1571477631
    //   203: l2i
    //   204: ldc_w 818280755
    //   207: ixor
    //   208: ldc2_w -1974785290
    //   211: l2i
    //   212: ldc_w 1633041424
    //   215: ixor
    //   216: ixor
    //   217: lookupswitch default -> 244, -1995656608 -> 200, -825003320 -> 250
    //   244: invokespecial <init> : (Lbigname/zprestige/webhack/util/HoleUtil$BlockSafety;Lbigname/zprestige/webhack/util/HoleUtil$HoleType;)V
    //   247: return
    //   248: aconst_null
    //   249: athrow
    //   250: aconst_null
    //   251: athrow
    //   252: aconst_null
    //   253: athrow
    //   254: aconst_null
    //   255: athrow
    // Local variable table:
    //   start	length	slot	name	descriptor
    //   0	248	0	this	Lbigname/zprestige/webhack/util/HoleUtil$HoleInfo;
  }
  
  static {
    throw SYNTHETIC_LOCAL_VARIABLE_0;
  }
  
  public void setCentre(AxisAlignedBB centre) {
    if (Perryc.c < 0) {
      null;
    } else {
      if (null != null)
        throw (Throwable)null; 
      null;
    } 
    if (null != null)
      throw (Throwable)null; 
    null;
  }
}


/* Location:              C:\Users\alex\Desktop\webhack\WebHack-0.8-obf_sussy_1.jar!\bigname\zprestige\webhac\\util\HoleUtil$HoleInfo.class
 * Java compiler version: 8 (52.0)
 * JD-Core Version:       1.1.3
 */