package bigname.zprestige.webhack.util;

import Perryc;

public class HudUtil implements Util {
  public static String getTpsStatus() {
    if (Perryc.1 <= 0) {
      null;
    } else {
      if (null != null)
        throw (Throwable)null; 
      null;
    } 
    if (null != null)
      throw (Throwable)null; 
    null;
  }
  
  static {
    throw SYNTHETIC_LOCAL_VARIABLE_0;
  }
  
  public static String getFpsStatus() {
    if (Perryc.1 <= 0) {
      null;
    } else {
      if (null != null)
        throw (Throwable)null; 
      null;
    } 
    if (null != null)
      throw (Throwable)null; 
    null;
  }
  
  public HudUtil() {
    // Byte code:
    //   0: getstatic Perryc.c : I
    //   3: iflt -> 17
    //   6: ldc2_w -1006878526
    //   9: l2i
    //   10: ldc_w 424788383
    //   13: ixor
    //   14: goto -> 25
    //   17: ldc2_w 1303017840
    //   20: l2i
    //   21: ldc_w 407611091
    //   24: ixor
    //   25: ldc2_w 884213028
    //   28: l2i
    //   29: ldc_w 1345385909
    //   32: ixor
    //   33: ixor
    //   34: lookupswitch default -> 60, -1104580148 -> 126, 378057513 -> 17
    //   60: aload_0
    //   61: getstatic Perryc.c : I
    //   64: iflt -> 78
    //   67: ldc2_w 501032298
    //   70: l2i
    //   71: ldc_w 1795559062
    //   74: ixor
    //   75: goto -> 86
    //   78: ldc2_w 531446870
    //   81: l2i
    //   82: ldc_w 741772225
    //   85: ixor
    //   86: ldc2_w 1029251928
    //   89: l2i
    //   90: ldc_w 2068786358
    //   93: ixor
    //   94: ixor
    //   95: lookupswitch default -> 124, 818750482 -> 78, 1972222073 -> 120
    //   120: invokespecial <init> : ()V
    //   123: return
    //   124: aconst_null
    //   125: athrow
    //   126: aconst_null
    //   127: athrow
    // Local variable table:
    //   start	length	slot	name	descriptor
    //   0	124	0	this	Lbigname/zprestige/webhack/util/HudUtil;
  }
  
  public static String getPingSatus() {
    if (Perryc.c < 0) {
      null;
    } else {
      if (null != null)
        throw (Throwable)null; 
      null;
    } 
    if (null != null)
      throw (Throwable)null; 
    null;
  }
}


/* Location:              C:\Users\alex\Desktop\webhack\WebHack-0.8-obf_sussy_1.jar!\bigname\zprestige\webhac\\util\HudUtil.class
 * Java compiler version: 8 (52.0)
 * JD-Core Version:       1.1.3
 */