package bigname.zprestige.webhack.util;

public class InventoryUtil$1 {
  public static int[] $SwitchMap$bigname$zprestige$webhack$util$InventoryUtil$Switch;
  
  static {
    // Byte code:
    //   0: getstatic Perryc.0 : I
    //   3: ifle -> 16
    //   6: ldc2_w -1768538438
    //   9: l2i
    //   10: ldc 890243938
    //   12: ixor
    //   13: goto -> 23
    //   16: ldc2_w 905484200
    //   19: l2i
    //   20: ldc 1347344049
    //   22: ixor
    //   23: ldc2_w -800378460
    //   26: l2i
    //   27: ldc -685099230
    //   29: ixor
    //   30: ixor
    //   31: lookupswitch default -> 56, -1528351906 -> 882, 950826348 -> 16
    //   56: invokestatic values : ()[Lbigname/zprestige/webhack/util/InventoryUtil$Switch;
    //   59: arraylength
    //   60: newarray int
    //   62: getstatic Perryc.c : I
    //   65: iflt -> 78
    //   68: ldc2_w -179252168
    //   71: l2i
    //   72: ldc -1444704565
    //   74: ixor
    //   75: goto -> 85
    //   78: ldc2_w -633807141
    //   81: l2i
    //   82: ldc -997742840
    //   84: ixor
    //   85: ldc2_w -1103677881
    //   88: l2i
    //   89: ldc 438732250
    //   91: ixor
    //   92: ixor
    //   93: lookupswitch default -> 900, -1162950066 -> 120, -123541138 -> 78
    //   120: putstatic bigname/zprestige/webhack/util/InventoryUtil$1.$SwitchMap$bigname$zprestige$webhack$util$InventoryUtil$Switch : [I
    //   123: getstatic Perryc.1 : I
    //   126: ifeq -> 139
    //   129: ldc2_w 1670505126
    //   132: l2i
    //   133: ldc 335887474
    //   135: ixor
    //   136: goto -> 146
    //   139: ldc2_w 609939020
    //   142: l2i
    //   143: ldc -1598074104
    //   145: ixor
    //   146: ldc2_w 1537714279
    //   149: l2i
    //   150: ldc 1015870636
    //   152: ixor
    //   153: ixor
    //   154: lookupswitch default -> 180, -904167741 -> 139, 280986143 -> 902
    //   180: getstatic bigname/zprestige/webhack/util/InventoryUtil$1.$SwitchMap$bigname$zprestige$webhack$util$InventoryUtil$Switch : [I
    //   183: getstatic Perryc.0 : I
    //   186: ifle -> 199
    //   189: ldc2_w 1059875296
    //   192: l2i
    //   193: ldc -1186087771
    //   195: ixor
    //   196: goto -> 206
    //   199: ldc2_w -1520974516
    //   202: l2i
    //   203: ldc 1591487577
    //   205: ixor
    //   206: ldc2_w -1399691658
    //   209: l2i
    //   210: ldc 2024222802
    //   212: ixor
    //   213: ixor
    //   214: lookupswitch default -> 240, 673688066 -> 199, 1381270369 -> 884
    //   240: getstatic bigname/zprestige/webhack/util/InventoryUtil$Switch.NORMAL : Lbigname/zprestige/webhack/util/InventoryUtil$Switch;
    //   243: getstatic Perryc.1 : I
    //   246: ifeq -> 259
    //   249: ldc2_w 1982412261
    //   252: l2i
    //   253: ldc -972163430
    //   255: ixor
    //   256: goto -> 266
    //   259: ldc2_w 2086861543
    //   262: l2i
    //   263: ldc -969325083
    //   265: ixor
    //   266: ldc2_w -734776494
    //   269: l2i
    //   270: ldc 485227346
    //   272: ixor
    //   273: ixor
    //   274: lookupswitch default -> 300, 464596550 -> 259, 2029718399 -> 894
    //   300: invokevirtual ordinal : ()I
    //   303: ldc2_w 1795155976
    //   306: l2i
    //   307: ldc 1795155977
    //   309: ixor
    //   310: iastore
    //   311: goto -> 373
    //   314: getstatic Perryc.c : I
    //   317: iflt -> 330
    //   320: ldc2_w -67281203
    //   323: l2i
    //   324: ldc -573971075
    //   326: ixor
    //   327: goto -> 337
    //   330: ldc2_w -2004245447
    //   333: l2i
    //   334: ldc 1123803164
    //   336: ixor
    //   337: ldc2_w -735367876
    //   340: l2i
    //   341: ldc -1946398740
    //   343: ixor
    //   344: ixor
    //   345: lookupswitch default -> 880, -1784338699 -> 372, 2044975456 -> 330
    //   372: astore_0
    //   373: getstatic Perryc.0 : I
    //   376: ifle -> 389
    //   379: ldc2_w -347138138
    //   382: l2i
    //   383: ldc 169573429
    //   385: ixor
    //   386: goto -> 396
    //   389: ldc2_w -1740051070
    //   392: l2i
    //   393: ldc 889975567
    //   395: ixor
    //   396: ldc2_w -1056205153
    //   399: l2i
    //   400: ldc -1467573190
    //   402: ixor
    //   403: ixor
    //   404: lookupswitch default -> 432, -1999019722 -> 890, 1181554008 -> 389
    //   432: getstatic bigname/zprestige/webhack/util/InventoryUtil$1.$SwitchMap$bigname$zprestige$webhack$util$InventoryUtil$Switch : [I
    //   435: getstatic Perryc.1 : I
    //   438: ifeq -> 451
    //   441: ldc2_w -297800717
    //   444: l2i
    //   445: ldc -1030457415
    //   447: ixor
    //   448: goto -> 458
    //   451: ldc2_w 1126637907
    //   454: l2i
    //   455: ldc -1049376365
    //   457: ixor
    //   458: ldc2_w 1937060654
    //   461: l2i
    //   462: ldc 1729241708
    //   464: ixor
    //   465: ixor
    //   466: lookupswitch default -> 886, -1774978686 -> 492, 952929544 -> 451
    //   492: getstatic bigname/zprestige/webhack/util/InventoryUtil$Switch.SILENT : Lbigname/zprestige/webhack/util/InventoryUtil$Switch;
    //   495: getstatic Perryc.c : I
    //   498: iflt -> 511
    //   501: ldc2_w -1676381507
    //   504: l2i
    //   505: ldc -48263450
    //   507: ixor
    //   508: goto -> 518
    //   511: ldc2_w -2044128404
    //   514: l2i
    //   515: ldc 1242877773
    //   517: ixor
    //   518: ldc2_w -844990075
    //   521: l2i
    //   522: ldc 1397645352
    //   524: ixor
    //   525: ixor
    //   526: lookupswitch default -> 552, -1897876615 -> 511, -1579530 -> 878
    //   552: invokevirtual ordinal : ()I
    //   555: ldc2_w 271487001
    //   558: l2i
    //   559: ldc 271487003
    //   561: ixor
    //   562: iastore
    //   563: goto -> 625
    //   566: getstatic Perryc.1 : I
    //   569: ifeq -> 582
    //   572: ldc2_w 141377108
    //   575: l2i
    //   576: ldc -2125249975
    //   578: ixor
    //   579: goto -> 589
    //   582: ldc2_w 1284838823
    //   585: l2i
    //   586: ldc 912412222
    //   588: ixor
    //   589: ldc2_w -2139141083
    //   592: l2i
    //   593: ldc -1813291909
    //   595: ixor
    //   596: ixor
    //   597: lookupswitch default -> 624, -1700107197 -> 898, -841221577 -> 582
    //   624: astore_0
    //   625: getstatic Perryc.0 : I
    //   628: ifle -> 641
    //   631: ldc2_w 1721700053
    //   634: l2i
    //   635: ldc 1238998936
    //   637: ixor
    //   638: goto -> 648
    //   641: ldc2_w -513837632
    //   644: l2i
    //   645: ldc 1731287192
    //   647: ixor
    //   648: ldc2_w 2102595903
    //   651: l2i
    //   652: ldc -1407328693
    //   654: ixor
    //   655: ixor
    //   656: lookupswitch default -> 684, -33006023 -> 892, -23778334 -> 641
    //   684: getstatic bigname/zprestige/webhack/util/InventoryUtil$1.$SwitchMap$bigname$zprestige$webhack$util$InventoryUtil$Switch : [I
    //   687: getstatic Perryc.0 : I
    //   690: ifle -> 703
    //   693: ldc2_w 165933734
    //   696: l2i
    //   697: ldc 679093530
    //   699: ixor
    //   700: goto -> 710
    //   703: ldc2_w -1906571923
    //   706: l2i
    //   707: ldc 1672717106
    //   709: ixor
    //   710: ldc2_w -590165518
    //   713: l2i
    //   714: ldc -1238508989
    //   716: ixor
    //   717: ixor
    //   718: lookupswitch default -> 888, -2028947986 -> 744, 1265026061 -> 703
    //   744: getstatic bigname/zprestige/webhack/util/InventoryUtil$Switch.NONE : Lbigname/zprestige/webhack/util/InventoryUtil$Switch;
    //   747: getstatic Perryc.1 : I
    //   750: ifeq -> 763
    //   753: ldc2_w 1732986050
    //   756: l2i
    //   757: ldc 1550234961
    //   759: ixor
    //   760: goto -> 770
    //   763: ldc2_w 1075665613
    //   766: l2i
    //   767: ldc 1470289974
    //   769: ixor
    //   770: ldc2_w -687160090
    //   773: l2i
    //   774: ldc -1948819871
    //   776: ixor
    //   777: ixor
    //   778: lookupswitch default -> 804, -320452451 -> 763, 1743809300 -> 896
    //   804: invokevirtual ordinal : ()I
    //   807: ldc2_w 1446001566
    //   810: l2i
    //   811: ldc 1446001565
    //   813: ixor
    //   814: iastore
    //   815: goto -> 877
    //   818: getstatic Perryc.1 : I
    //   821: ifeq -> 834
    //   824: ldc2_w -451656547
    //   827: l2i
    //   828: ldc 276597033
    //   830: ixor
    //   831: goto -> 841
    //   834: ldc2_w -179820391
    //   837: l2i
    //   838: ldc 1065922028
    //   840: ixor
    //   841: ldc2_w -1358392111
    //   844: l2i
    //   845: ldc 1044893606
    //   847: ixor
    //   848: ixor
    //   849: lookupswitch default -> 904, 1536155138 -> 876, 1680316099 -> 834
    //   876: astore_0
    //   877: return
    //   878: aconst_null
    //   879: athrow
    //   880: aconst_null
    //   881: athrow
    //   882: aconst_null
    //   883: athrow
    //   884: aconst_null
    //   885: athrow
    //   886: aconst_null
    //   887: athrow
    //   888: aconst_null
    //   889: athrow
    //   890: aconst_null
    //   891: athrow
    //   892: aconst_null
    //   893: athrow
    //   894: aconst_null
    //   895: athrow
    //   896: aconst_null
    //   897: athrow
    //   898: aconst_null
    //   899: athrow
    //   900: aconst_null
    //   901: athrow
    //   902: aconst_null
    //   903: athrow
    //   904: aconst_null
    //   905: athrow
    // Exception table:
    //   from	to	target	type
    //   123	311	314	java/lang/NoSuchFieldError
    //   373	563	566	java/lang/NoSuchFieldError
    //   625	815	818	java/lang/NoSuchFieldError
  }
}


/* Location:              C:\Users\alex\Desktop\webhack\WebHack-0.8-obf_sussy_1.jar!\bigname\zprestige\webhac\\util\InventoryUtil$1.class
 * Java compiler version: 8 (52.0)
 * JD-Core Version:       1.1.3
 */