package bigname.zprestige.webhack.util;

import Perry1;
import Perryc;
import java.util.List;
import java.util.Map;
import java.util.Random;
import net.minecraft.entity.Entity;
import net.minecraft.entity.player.EntityPlayer;
import net.minecraft.util.math.Vec3d;

public class MathUtil implements Util {
  public static Random random;
  
  public static List getBlockBlocks(Entity entity) {
    // Byte code:
    //   0: goto -> 8
    //   3: dup
    //   4: ifnull -> 5109
    //   7: athrow
    //   8: aconst_null
    //   9: getstatic Perryc.0 : I
    //   12: ifgt -> 5101
    //   15: pop
    //   16: aconst_null
    //   17: goto -> 5093
    //   20: nop
    //   21: nop
    //   22: nop
    //   23: athrow
    //   24: new java/util/ArrayList
    //   27: dup
    //   28: getstatic Perryc.1 : I
    //   31: ifeq -> 44
    //   34: ldc2_w 730728853
    //   37: l2i
    //   38: ldc -1753888054
    //   40: ixor
    //   41: goto -> 51
    //   44: ldc2_w 434183922
    //   47: l2i
    //   48: ldc 1365722443
    //   50: ixor
    //   51: ldc2_w 1089018683
    //   54: l2i
    //   55: ldc 641901175
    //   57: ixor
    //   58: ixor
    //   59: lookupswitch default -> 84, -632260077 -> 5042, 765633332 -> 44
    //   84: goto -> 88
    //   87: athrow
    //   88: invokespecial <init> : ()V
    //   91: goto -> 95
    //   94: athrow
    //   95: getstatic Perryc.1 : I
    //   98: ifeq -> 111
    //   101: ldc2_w -885787517
    //   104: l2i
    //   105: ldc -1831692778
    //   107: ixor
    //   108: goto -> 118
    //   111: ldc2_w 1610918470
    //   114: l2i
    //   115: ldc 1854640098
    //   117: ixor
    //   118: ldc2_w -1032603137
    //   121: l2i
    //   122: ldc 149919456
    //   124: ixor
    //   125: ixor
    //   126: lookupswitch default -> 152, -1820504694 -> 4940, 1349030143 -> 111
    //   152: astore_1
    //   153: getstatic Perryc.1 : I
    //   156: ifeq -> 169
    //   159: ldc2_w 1269466175
    //   162: l2i
    //   163: ldc 1302546011
    //   165: ixor
    //   166: goto -> 176
    //   169: ldc2_w -750642848
    //   172: l2i
    //   173: ldc -1801656890
    //   175: ixor
    //   176: ldc2_w -88708498
    //   179: l2i
    //   180: ldc -1589862746
    //   182: ixor
    //   183: ixor
    //   184: lookupswitch default -> 4974, 475269230 -> 212, 1568880300 -> 169
    //   212: aload_0
    //   213: getstatic Perryc.0 : I
    //   216: ifle -> 229
    //   219: ldc2_w 2126848696
    //   222: l2i
    //   223: ldc -312394965
    //   225: ixor
    //   226: goto -> 236
    //   229: ldc2_w -1036795530
    //   232: l2i
    //   233: ldc 1335074158
    //   235: ixor
    //   236: ldc2_w 416018679
    //   239: l2i
    //   240: ldc 493675036
    //   242: ixor
    //   243: ixor
    //   244: lookupswitch default -> 5080, -2012786957 -> 272, -1778185352 -> 229
    //   272: goto -> 276
    //   275: athrow
    //   276: invokevirtual func_174813_aQ : ()Lnet/minecraft/util/math/AxisAlignedBB;
    //   279: goto -> 283
    //   282: athrow
    //   283: getstatic Perryc.0 : I
    //   286: ifle -> 299
    //   289: ldc2_w -544091670
    //   292: l2i
    //   293: ldc -473993689
    //   295: ixor
    //   296: goto -> 306
    //   299: ldc2_w -726849380
    //   302: l2i
    //   303: ldc -723155982
    //   305: ixor
    //   306: ldc2_w 552719670
    //   309: l2i
    //   310: ldc -812487853
    //   312: ixor
    //   313: ixor
    //   314: lookupswitch default -> 340, -1819246880 -> 299, -749928024 -> 5028
    //   340: astore_2
    //   341: getstatic Perryc.0 : I
    //   344: ifle -> 357
    //   347: ldc2_w 819590636
    //   350: l2i
    //   351: ldc -1714725178
    //   353: ixor
    //   354: goto -> 364
    //   357: ldc2_w -1179055355
    //   360: l2i
    //   361: ldc -1031772469
    //   363: ixor
    //   364: ldc2_w 450654680
    //   367: l2i
    //   368: ldc -240821791
    //   370: ixor
    //   371: ixor
    //   372: lookupswitch default -> 5078, -1874835977 -> 400, 1114342163 -> 357
    //   400: aload_0
    //   401: getstatic Perryc.1 : I
    //   404: ifeq -> 417
    //   407: ldc2_w 128572858
    //   410: l2i
    //   411: ldc -1319968105
    //   413: ixor
    //   414: goto -> 424
    //   417: ldc2_w 1475113342
    //   420: l2i
    //   421: ldc 2143203837
    //   423: ixor
    //   424: ldc2_w 367803345
    //   427: l2i
    //   428: ldc -1057346951
    //   430: ixor
    //   431: ixor
    //   432: lookupswitch default -> 460, -2056004130 -> 417, 1676488325 -> 4946
    //   460: getfield field_70163_u : D
    //   463: getstatic Perryc.c : I
    //   466: iflt -> 479
    //   469: ldc2_w 150888575
    //   472: l2i
    //   473: ldc -1834733532
    //   475: ixor
    //   476: goto -> 486
    //   479: ldc2_w -1636171465
    //   482: l2i
    //   483: ldc -2077415514
    //   485: ixor
    //   486: ldc2_w -262411245
    //   489: l2i
    //   490: ldc 1235788610
    //   492: ixor
    //   493: ixor
    //   494: lookupswitch default -> 5040, -1549506112 -> 520, 598286090 -> 479
    //   520: dstore_3
    //   521: getstatic Perryc.0 : I
    //   524: ifle -> 537
    //   527: ldc2_w 1315445364
    //   530: l2i
    //   531: ldc -843414346
    //   533: ixor
    //   534: goto -> 544
    //   537: ldc2_w 2100114534
    //   540: l2i
    //   541: ldc -348228212
    //   543: ixor
    //   544: ldc2_w -160085238
    //   547: l2i
    //   548: ldc 1785537007
    //   550: ixor
    //   551: ixor
    //   552: lookupswitch default -> 580, -2042490870 -> 537, 533394471 -> 4996
    //   580: aload_2
    //   581: getstatic Perryc.1 : I
    //   584: ifeq -> 597
    //   587: ldc2_w -389629242
    //   590: l2i
    //   591: ldc 564107248
    //   593: ixor
    //   594: goto -> 604
    //   597: ldc2_w 1093279924
    //   600: l2i
    //   601: ldc -115409364
    //   603: ixor
    //   604: ldc2_w 1989628797
    //   607: l2i
    //   608: ldc 1290935779
    //   610: ixor
    //   611: ixor
    //   612: lookupswitch default -> 640, -1014091649 -> 597, -214146136 -> 4976
    //   640: getfield field_72340_a : D
    //   643: ldc2_w -2123325153
    //   646: l2i
    //   647: ldc -2123325153
    //   649: ixor
    //   650: getstatic Perryc.0 : I
    //   653: ifle -> 666
    //   656: ldc2_w 1972751008
    //   659: l2i
    //   660: ldc 1387641887
    //   662: ixor
    //   663: goto -> 673
    //   666: ldc2_w -121081288
    //   669: l2i
    //   670: ldc -1504978693
    //   672: ixor
    //   673: ldc2_w 892733683
    //   676: l2i
    //   677: ldc -2060124049
    //   679: ixor
    //   680: ixor
    //   681: lookupswitch default -> 5046, -1759281629 -> 666, -293559713 -> 708
    //   708: goto -> 712
    //   711: athrow
    //   712: invokestatic round : (DI)D
    //   715: goto -> 719
    //   718: athrow
    //   719: getstatic Perryc.0 : I
    //   722: ifle -> 735
    //   725: ldc2_w -951998561
    //   728: l2i
    //   729: ldc -1391423035
    //   731: ixor
    //   732: goto -> 742
    //   735: ldc2_w 661627608
    //   738: l2i
    //   739: ldc 536378018
    //   741: ixor
    //   742: ldc2_w 1345779928
    //   745: l2i
    //   746: ldc -2035160967
    //   748: ixor
    //   749: ixor
    //   750: lookupswitch default -> 5000, -1126816005 -> 735, -300889893 -> 776
    //   776: dstore #5
    //   778: getstatic Perryc.1 : I
    //   781: ifeq -> 794
    //   784: ldc2_w 1067781012
    //   787: l2i
    //   788: ldc -805366474
    //   790: ixor
    //   791: goto -> 801
    //   794: ldc2_w -1312080383
    //   797: l2i
    //   798: ldc -1390413992
    //   800: ixor
    //   801: ldc2_w 1520791009
    //   804: l2i
    //   805: ldc 1550997146
    //   807: ixor
    //   808: ixor
    //   809: lookupswitch default -> 5076, -158521895 -> 794, 436466210 -> 836
    //   836: aload_2
    //   837: getstatic Perryc.1 : I
    //   840: ifeq -> 853
    //   843: ldc2_w -1820311142
    //   846: l2i
    //   847: ldc -74045995
    //   849: ixor
    //   850: goto -> 860
    //   853: ldc2_w -1277620585
    //   856: l2i
    //   857: ldc -1327258496
    //   859: ixor
    //   860: ldc2_w 909204441
    //   863: l2i
    //   864: ldc -511641076
    //   866: ixor
    //   867: ixor
    //   868: lookupswitch default -> 5068, -1079523942 -> 853, -729084990 -> 896
    //   896: getfield field_72339_c : D
    //   899: ldc2_w -531762117
    //   902: l2i
    //   903: ldc -531762117
    //   905: ixor
    //   906: getstatic Perryc.c : I
    //   909: iflt -> 922
    //   912: ldc2_w -904545963
    //   915: l2i
    //   916: ldc 1971933559
    //   918: ixor
    //   919: goto -> 929
    //   922: ldc2_w 1601281035
    //   925: l2i
    //   926: ldc 1010989492
    //   928: ixor
    //   929: ldc2_w -1677987727
    //   932: l2i
    //   933: ldc 1448469360
    //   935: ixor
    //   936: ixor
    //   937: lookupswitch default -> 964, 335752537 -> 922, 1915943715 -> 5058
    //   964: goto -> 968
    //   967: athrow
    //   968: invokestatic round : (DI)D
    //   971: goto -> 975
    //   974: athrow
    //   975: getstatic Perryc.0 : I
    //   978: ifle -> 991
    //   981: ldc2_w -1588735561
    //   984: l2i
    //   985: ldc -1591601190
    //   987: ixor
    //   988: goto -> 998
    //   991: ldc2_w -1780264664
    //   994: l2i
    //   995: ldc 531148321
    //   997: ixor
    //   998: ldc2_w 1683835253
    //   1001: l2i
    //   1002: ldc -1551522468
    //   1004: ixor
    //   1005: ixor
    //   1006: lookupswitch default -> 1032, -944297404 -> 4966, -630673135 -> 991
    //   1032: dstore #7
    //   1034: getstatic Perryc.0 : I
    //   1037: ifle -> 1050
    //   1040: ldc2_w 1727116770
    //   1043: l2i
    //   1044: ldc 420164310
    //   1046: ixor
    //   1047: goto -> 1057
    //   1050: ldc2_w -1327009944
    //   1053: l2i
    //   1054: ldc 1625131948
    //   1056: ixor
    //   1057: ldc2_w -607389578
    //   1060: l2i
    //   1061: ldc -1855064718
    //   1063: ixor
    //   1064: ixor
    //   1065: lookupswitch default -> 1092, 895257136 -> 4952, 1549892754 -> 1050
    //   1092: aload_2
    //   1093: getstatic Perryc.c : I
    //   1096: iflt -> 1109
    //   1099: ldc2_w -106628936
    //   1102: l2i
    //   1103: ldc -808198524
    //   1105: ixor
    //   1106: goto -> 1116
    //   1109: ldc2_w -1018650831
    //   1112: l2i
    //   1113: ldc 2080548014
    //   1115: ixor
    //   1116: ldc2_w -1785775817
    //   1119: l2i
    //   1120: ldc 511612959
    //   1122: ixor
    //   1123: ixor
    //   1124: lookupswitch default -> 1152, -1788934933 -> 1109, -1115257068 -> 4968
    //   1152: getfield field_72336_d : D
    //   1155: ldc2_w 875865651
    //   1158: l2i
    //   1159: ldc_w 875865651
    //   1162: ixor
    //   1163: getstatic Perryc.0 : I
    //   1166: ifle -> 1180
    //   1169: ldc2_w -377186162
    //   1172: l2i
    //   1173: ldc_w -939722012
    //   1176: ixor
    //   1177: goto -> 1188
    //   1180: ldc2_w 1902782252
    //   1183: l2i
    //   1184: ldc_w -1306479393
    //   1187: ixor
    //   1188: ldc2_w -1410760017
    //   1191: l2i
    //   1192: ldc_w 200819091
    //   1195: ixor
    //   1196: ixor
    //   1197: lookupswitch default -> 1224, -1905680042 -> 4970, 680199044 -> 1180
    //   1224: goto -> 1228
    //   1227: athrow
    //   1228: invokestatic round : (DI)D
    //   1231: goto -> 1235
    //   1234: athrow
    //   1235: getstatic Perryc.0 : I
    //   1238: ifle -> 1252
    //   1241: ldc2_w 813991758
    //   1244: l2i
    //   1245: ldc_w -1285500242
    //   1248: ixor
    //   1249: goto -> 1260
    //   1252: ldc2_w -1975879541
    //   1255: l2i
    //   1256: ldc_w 885052922
    //   1259: ixor
    //   1260: ldc2_w 449922691
    //   1263: l2i
    //   1264: ldc_w -1848351330
    //   1267: ixor
    //   1268: ixor
    //   1269: lookupswitch default -> 5072, 148993789 -> 1252, 905940588 -> 1296
    //   1296: dstore #9
    //   1298: getstatic Perryc.c : I
    //   1301: iflt -> 1315
    //   1304: ldc2_w 2147186665
    //   1307: l2i
    //   1308: ldc_w -818883629
    //   1311: ixor
    //   1312: goto -> 1323
    //   1315: ldc2_w -104794044
    //   1318: l2i
    //   1319: ldc_w -1976612845
    //   1322: ixor
    //   1323: ldc2_w 1225077614
    //   1326: l2i
    //   1327: ldc_w -1709984038
    //   1330: ixor
    //   1331: ixor
    //   1332: lookupswitch default -> 1360, 820999993 -> 1315, 1675436430 -> 5014
    //   1360: aload_2
    //   1361: getstatic Perryc.1 : I
    //   1364: ifeq -> 1378
    //   1367: ldc2_w -470288071
    //   1370: l2i
    //   1371: ldc_w -1459783691
    //   1374: ixor
    //   1375: goto -> 1386
    //   1378: ldc2_w -208655789
    //   1381: l2i
    //   1382: ldc_w -2054994593
    //   1385: ixor
    //   1386: ldc2_w 986143682
    //   1389: l2i
    //   1390: ldc_w 1068633124
    //   1393: ixor
    //   1394: ixor
    //   1395: lookupswitch default -> 1420, -2005037382 -> 1378, 1317001514 -> 5008
    //   1420: getfield field_72334_f : D
    //   1423: ldc2_w 39517920
    //   1426: l2i
    //   1427: ldc_w 39517920
    //   1430: ixor
    //   1431: getstatic Perryc.1 : I
    //   1434: ifeq -> 1448
    //   1437: ldc2_w 567299101
    //   1440: l2i
    //   1441: ldc_w 1699377205
    //   1444: ixor
    //   1445: goto -> 1456
    //   1448: ldc2_w -913810193
    //   1451: l2i
    //   1452: ldc_w 938418172
    //   1455: ixor
    //   1456: ldc2_w 1667880343
    //   1459: l2i
    //   1460: ldc_w 1490152908
    //   1463: ixor
    //   1464: ixor
    //   1465: lookupswitch default -> 1492, -174572434 -> 1448, 2132935795 -> 4986
    //   1492: goto -> 1496
    //   1495: athrow
    //   1496: invokestatic round : (DI)D
    //   1499: goto -> 1503
    //   1502: athrow
    //   1503: getstatic Perryc.0 : I
    //   1506: ifle -> 1520
    //   1509: ldc2_w -476627631
    //   1512: l2i
    //   1513: ldc_w 1792354529
    //   1516: ixor
    //   1517: goto -> 1528
    //   1520: ldc2_w -735146145
    //   1523: l2i
    //   1524: ldc_w 1783407301
    //   1527: ixor
    //   1528: ldc2_w -448998373
    //   1531: l2i
    //   1532: ldc_w -374595759
    //   1535: ixor
    //   1536: ixor
    //   1537: lookupswitch default -> 1564, -2049777926 -> 5004, -1516689395 -> 1520
    //   1564: dstore #11
    //   1566: getstatic Perryc.0 : I
    //   1569: ifle -> 1583
    //   1572: ldc2_w -1486240279
    //   1575: l2i
    //   1576: ldc_w 380284527
    //   1579: ixor
    //   1580: goto -> 1591
    //   1583: ldc2_w 321540216
    //   1586: l2i
    //   1587: ldc_w -1152092636
    //   1590: ixor
    //   1591: ldc2_w 1037721158
    //   1594: l2i
    //   1595: ldc_w 1963983944
    //   1598: ixor
    //   1599: ixor
    //   1600: lookupswitch default -> 1628, -116838008 -> 4988, 2114887702 -> 1583
    //   1628: dload #5
    //   1630: getstatic Perryc.0 : I
    //   1633: ifle -> 1647
    //   1636: ldc2_w 752846130
    //   1639: l2i
    //   1640: ldc_w -1522633106
    //   1643: ixor
    //   1644: goto -> 1655
    //   1647: ldc2_w 1337617171
    //   1650: l2i
    //   1651: ldc_w 1195194919
    //   1654: ixor
    //   1655: ldc2_w -394239314
    //   1658: l2i
    //   1659: ldc_w 1134249694
    //   1662: ixor
    //   1663: ixor
    //   1664: lookupswitch default -> 4950, -1550027452 -> 1692, 586864428 -> 1647
    //   1692: dload #9
    //   1694: dcmpl
    //   1695: ifeq -> 1709
    //   1698: ldc2_w 1093612958
    //   1701: l2i
    //   1702: ldc_w -1438890412
    //   1705: ixor
    //   1706: goto -> 1717
    //   1709: ldc2_w -1736244727
    //   1712: l2i
    //   1713: ldc_w 1938846144
    //   1716: ixor
    //   1717: ldc2_w 883891408
    //   1720: l2i
    //   1721: ldc_w -1844825701
    //   1724: ixor
    //   1725: ixor
    //   1726: tableswitch default -> 1698, 1303797377 -> 1748, 1303797378 -> 3574
    //   1748: getstatic Perryc.0 : I
    //   1751: ifle -> 1765
    //   1754: ldc2_w -24454976
    //   1757: l2i
    //   1758: ldc_w -1990768421
    //   1761: ixor
    //   1762: goto -> 1773
    //   1765: ldc2_w -740816567
    //   1768: l2i
    //   1769: ldc_w -1890004058
    //   1772: ixor
    //   1773: ldc2_w 1380597222
    //   1776: l2i
    //   1777: ldc_w 798243661
    //   1780: ixor
    //   1781: ixor
    //   1782: lookupswitch default -> 1808, 168007344 -> 5030, 1696460395 -> 1765
    //   1808: aload_1
    //   1809: new net/minecraft/util/math/Vec3d
    //   1812: dup
    //   1813: getstatic Perryc.c : I
    //   1816: iflt -> 1830
    //   1819: ldc2_w -1985832525
    //   1822: l2i
    //   1823: ldc_w 312470367
    //   1826: ixor
    //   1827: goto -> 1838
    //   1830: ldc2_w 1823181776
    //   1833: l2i
    //   1834: ldc_w 1339798612
    //   1837: ixor
    //   1838: ldc2_w -1415854187
    //   1841: l2i
    //   1842: ldc_w -1138307269
    //   1845: ixor
    //   1846: ixor
    //   1847: lookupswitch default -> 5020, -1937737150 -> 1830, 885864234 -> 1872
    //   1872: dload #5
    //   1874: getstatic Perryc.0 : I
    //   1877: ifle -> 1891
    //   1880: ldc2_w -1485119526
    //   1883: l2i
    //   1884: ldc_w -964976084
    //   1887: ixor
    //   1888: goto -> 1899
    //   1891: ldc2_w -769940486
    //   1894: l2i
    //   1895: ldc_w -1318296137
    //   1898: ixor
    //   1899: ldc2_w -854137583
    //   1902: l2i
    //   1903: ldc_w -1757717455
    //   1906: ixor
    //   1907: ixor
    //   1908: lookupswitch default -> 1936, -650455076 -> 1891, 992789718 -> 5026
    //   1936: dload_3
    //   1937: getstatic Perryc.1 : I
    //   1940: ifeq -> 1954
    //   1943: ldc2_w -46333401
    //   1946: l2i
    //   1947: ldc_w 1630363702
    //   1950: ixor
    //   1951: goto -> 1962
    //   1954: ldc2_w -2135252306
    //   1957: l2i
    //   1958: ldc_w 1470756787
    //   1961: ixor
    //   1962: ldc2_w 788321797
    //   1965: l2i
    //   1966: ldc_w -1593338833
    //   1969: ixor
    //   1970: ixor
    //   1971: lookupswitch default -> 1996, -1521999123 -> 1954, 334176315 -> 5032
    //   1996: dload #7
    //   1998: getstatic Perryc.1 : I
    //   2001: ifeq -> 2015
    //   2004: ldc2_w 1934493082
    //   2007: l2i
    //   2008: ldc_w 931642679
    //   2011: ixor
    //   2012: goto -> 2023
    //   2015: ldc2_w 2115359274
    //   2018: l2i
    //   2019: ldc_w -1035423145
    //   2022: ixor
    //   2023: ldc2_w -1054724773
    //   2026: l2i
    //   2027: ldc_w -1731980544
    //   2030: ixor
    //   2031: ixor
    //   2032: lookupswitch default -> 2060, 489654006 -> 5006, 664267101 -> 2015
    //   2060: goto -> 2064
    //   2063: athrow
    //   2064: invokespecial <init> : (DDD)V
    //   2067: goto -> 2071
    //   2070: athrow
    //   2071: getstatic Perryc.c : I
    //   2074: iflt -> 2088
    //   2077: ldc2_w 1184511373
    //   2080: l2i
    //   2081: ldc_w -799079873
    //   2084: ixor
    //   2085: goto -> 2096
    //   2088: ldc2_w -607025893
    //   2091: l2i
    //   2092: ldc_w 2055685243
    //   2095: ixor
    //   2096: ldc2_w 817276872
    //   2099: l2i
    //   2100: ldc_w -77573657
    //   2103: ixor
    //   2104: ixor
    //   2105: lookupswitch default -> 2132, -2054933258 -> 2088, 1561575837 -> 5034
    //   2132: goto -> 2136
    //   2135: athrow
    //   2136: invokevirtual add : (Ljava/lang/Object;)Z
    //   2139: goto -> 2143
    //   2142: athrow
    //   2143: pop
    //   2144: getstatic Perryc.1 : I
    //   2147: ifeq -> 2161
    //   2150: ldc2_w -335363879
    //   2153: l2i
    //   2154: ldc_w -684145548
    //   2157: ixor
    //   2158: goto -> 2169
    //   2161: ldc2_w -558248257
    //   2164: l2i
    //   2165: ldc_w -1676357159
    //   2168: ixor
    //   2169: ldc2_w 2081243686
    //   2172: l2i
    //   2173: ldc_w 2067812742
    //   2176: ixor
    //   2177: ixor
    //   2178: lookupswitch default -> 2204, -2045951893 -> 2161, 1014437645 -> 5064
    //   2204: aload_1
    //   2205: new net/minecraft/util/math/Vec3d
    //   2208: dup
    //   2209: getstatic Perryc.c : I
    //   2212: iflt -> 2226
    //   2215: ldc2_w 795018082
    //   2218: l2i
    //   2219: ldc_w -230426968
    //   2222: ixor
    //   2223: goto -> 2234
    //   2226: ldc2_w -854315596
    //   2229: l2i
    //   2230: ldc_w 1264134722
    //   2233: ixor
    //   2234: ldc2_w 1804333114
    //   2237: l2i
    //   2238: ldc_w -269202439
    //   2241: ixor
    //   2242: ixor
    //   2243: lookupswitch default -> 5010, 36879413 -> 2268, 1499418121 -> 2226
    //   2268: dload #9
    //   2270: getstatic Perryc.c : I
    //   2273: iflt -> 2287
    //   2276: ldc2_w -378383309
    //   2279: l2i
    //   2280: ldc_w 1219857979
    //   2283: ixor
    //   2284: goto -> 2295
    //   2287: ldc2_w -1164847469
    //   2290: l2i
    //   2291: ldc_w 1250010945
    //   2294: ixor
    //   2295: ldc2_w 2134845887
    //   2298: l2i
    //   2299: ldc_w 1832347224
    //   2302: ixor
    //   2303: ixor
    //   2304: lookupswitch default -> 4942, -1278241297 -> 2287, -501727691 -> 2332
    //   2332: dload_3
    //   2333: getstatic Perryc.0 : I
    //   2336: ifle -> 2350
    //   2339: ldc2_w 316864497
    //   2342: l2i
    //   2343: ldc_w 1379980075
    //   2346: ixor
    //   2347: goto -> 2358
    //   2350: ldc2_w -1432081791
    //   2353: l2i
    //   2354: ldc_w -401815741
    //   2357: ixor
    //   2358: ldc2_w -571728806
    //   2361: l2i
    //   2362: ldc_w -640833789
    //   2365: ixor
    //   2366: ixor
    //   2367: lookupswitch default -> 2392, -2115356634 -> 2350, 1149476739 -> 4990
    //   2392: dload #7
    //   2394: getstatic Perryc.c : I
    //   2397: iflt -> 2411
    //   2400: ldc2_w 1911913605
    //   2403: l2i
    //   2404: ldc_w -1431535078
    //   2407: ixor
    //   2408: goto -> 2419
    //   2411: ldc2_w -743544630
    //   2414: l2i
    //   2415: ldc_w 830196065
    //   2418: ixor
    //   2419: ldc2_w 1484745609
    //   2422: l2i
    //   2423: ldc_w 1894168350
    //   2426: ixor
    //   2427: ixor
    //   2428: lookupswitch default -> 2456, -205512184 -> 4956, 1142421520 -> 2411
    //   2456: goto -> 2460
    //   2459: athrow
    //   2460: invokespecial <init> : (DDD)V
    //   2463: goto -> 2467
    //   2466: athrow
    //   2467: getstatic Perryc.0 : I
    //   2470: ifle -> 2484
    //   2473: ldc2_w -714293052
    //   2476: l2i
    //   2477: ldc_w 1932343193
    //   2480: ixor
    //   2481: goto -> 2492
    //   2484: ldc2_w 219510911
    //   2487: l2i
    //   2488: ldc_w -1696327359
    //   2491: ixor
    //   2492: ldc2_w 224844051
    //   2495: l2i
    //   2496: ldc_w -2090953400
    //   2499: ixor
    //   2500: ixor
    //   2501: lookupswitch default -> 2528, 94032612 -> 2484, 679066374 -> 5066
    //   2528: goto -> 2532
    //   2531: athrow
    //   2532: invokevirtual add : (Ljava/lang/Object;)Z
    //   2535: goto -> 2539
    //   2538: athrow
    //   2539: pop
    //   2540: getstatic Perryc.0 : I
    //   2543: ifle -> 2557
    //   2546: ldc2_w -895354654
    //   2549: l2i
    //   2550: ldc_w 1310309877
    //   2553: ixor
    //   2554: goto -> 2565
    //   2557: ldc2_w -2030300286
    //   2560: l2i
    //   2561: ldc_w -1117294152
    //   2564: ixor
    //   2565: ldc2_w 1491302534
    //   2568: l2i
    //   2569: ldc_w -1667291760
    //   2572: ixor
    //   2573: ixor
    //   2574: lookupswitch default -> 2600, 1086593025 -> 4960, 1534353113 -> 2557
    //   2600: dload #7
    //   2602: getstatic Perryc.c : I
    //   2605: iflt -> 2619
    //   2608: ldc2_w 1237449670
    //   2611: l2i
    //   2612: ldc_w 899192883
    //   2615: ixor
    //   2616: goto -> 2627
    //   2619: ldc2_w 824242935
    //   2622: l2i
    //   2623: ldc_w 2079481808
    //   2626: ixor
    //   2627: ldc2_w -1377199403
    //   2630: l2i
    //   2631: ldc_w 1132537947
    //   2634: ixor
    //   2635: ixor
    //   2636: lookupswitch default -> 2664, -1842228869 -> 4948, 931176550 -> 2619
    //   2664: dload #11
    //   2666: dcmpl
    //   2667: ifeq -> 2681
    //   2670: ldc2_w -1548530834
    //   2673: l2i
    //   2674: ldc_w -803844927
    //   2677: ixor
    //   2678: goto -> 2689
    //   2681: ldc2_w 1041621087
    //   2684: l2i
    //   2685: ldc_w 1303439347
    //   2688: ixor
    //   2689: ldc2_w -175634046
    //   2692: l2i
    //   2693: ldc_w 632598712
    //   2696: ixor
    //   2697: ixor
    //   2698: tableswitch default -> 2670, -1550205291 -> 2720, -1550205290 -> 4610
    //   2720: getstatic Perryc.1 : I
    //   2723: ifeq -> 2737
    //   2726: ldc2_w -1890024943
    //   2729: l2i
    //   2730: ldc_w 485647658
    //   2733: ixor
    //   2734: goto -> 2745
    //   2737: ldc2_w -607945981
    //   2740: l2i
    //   2741: ldc_w 1929308435
    //   2744: ixor
    //   2745: ldc2_w 1726054226
    //   2748: l2i
    //   2749: ldc_w -1903866998
    //   2752: ixor
    //   2753: ixor
    //   2754: lookupswitch default -> 4994, 1096394440 -> 2780, 2077152227 -> 2737
    //   2780: aload_1
    //   2781: new net/minecraft/util/math/Vec3d
    //   2784: dup
    //   2785: getstatic Perryc.0 : I
    //   2788: ifle -> 2802
    //   2791: ldc2_w 1627606846
    //   2794: l2i
    //   2795: ldc_w 1421822401
    //   2798: ixor
    //   2799: goto -> 2810
    //   2802: ldc2_w -1228822679
    //   2805: l2i
    //   2806: ldc_w 1702553277
    //   2809: ixor
    //   2810: ldc2_w -572836469
    //   2813: l2i
    //   2814: ldc_w -824728334
    //   2817: ixor
    //   2818: ixor
    //   2819: lookupswitch default -> 2844, 263252713 -> 2802, 649107334 -> 4958
    //   2844: dload #5
    //   2846: getstatic Perryc.1 : I
    //   2849: ifeq -> 2863
    //   2852: ldc2_w 1588966136
    //   2855: l2i
    //   2856: ldc_w -2032011004
    //   2859: ixor
    //   2860: goto -> 2871
    //   2863: ldc2_w -886295992
    //   2866: l2i
    //   2867: ldc_w 48866423
    //   2870: ixor
    //   2871: ldc2_w 1779446328
    //   2874: l2i
    //   2875: ldc_w 411135816
    //   2878: ixor
    //   2879: ixor
    //   2880: lookupswitch default -> 2908, -1429924212 -> 5016, -1244031615 -> 2863
    //   2908: dload_3
    //   2909: getstatic Perryc.1 : I
    //   2912: ifeq -> 2926
    //   2915: ldc2_w 1662375648
    //   2918: l2i
    //   2919: ldc_w 325682007
    //   2922: ixor
    //   2923: goto -> 2934
    //   2926: ldc2_w -1491185142
    //   2929: l2i
    //   2930: ldc_w 2087230667
    //   2933: ixor
    //   2934: ldc2_w 758275185
    //   2937: l2i
    //   2938: ldc_w -1479867068
    //   2941: ixor
    //   2942: ixor
    //   2943: lookupswitch default -> 2968, -91943806 -> 4982, 727901792 -> 2926
    //   2968: dload #11
    //   2970: getstatic Perryc.c : I
    //   2973: iflt -> 2987
    //   2976: ldc2_w 1101308936
    //   2979: l2i
    //   2980: ldc_w -943509705
    //   2983: ixor
    //   2984: goto -> 2995
    //   2987: ldc2_w 1840674192
    //   2990: l2i
    //   2991: ldc_w 139199874
    //   2994: ixor
    //   2995: ldc2_w -67740198
    //   2998: l2i
    //   2999: ldc_w 1552641537
    //   3002: ixor
    //   3003: ixor
    //   3004: lookupswitch default -> 3032, -1015156297 -> 2987, 555399396 -> 5074
    //   3032: goto -> 3036
    //   3035: athrow
    //   3036: invokespecial <init> : (DDD)V
    //   3039: goto -> 3043
    //   3042: athrow
    //   3043: getstatic Perryc.1 : I
    //   3046: ifeq -> 3060
    //   3049: ldc2_w -271405846
    //   3052: l2i
    //   3053: ldc_w 1349008150
    //   3056: ixor
    //   3057: goto -> 3068
    //   3060: ldc2_w 1197260300
    //   3063: l2i
    //   3064: ldc_w 510901258
    //   3067: ixor
    //   3068: ldc2_w 438034565
    //   3071: l2i
    //   3072: ldc_w 186635107
    //   3075: ixor
    //   3076: ixor
    //   3077: lookupswitch default -> 5050, -1363237862 -> 3060, 1210790368 -> 3104
    //   3104: goto -> 3108
    //   3107: athrow
    //   3108: invokevirtual add : (Ljava/lang/Object;)Z
    //   3111: goto -> 3115
    //   3114: athrow
    //   3115: pop
    //   3116: getstatic Perryc.c : I
    //   3119: iflt -> 3133
    //   3122: ldc2_w 1211194634
    //   3125: l2i
    //   3126: ldc_w 1435057204
    //   3129: ixor
    //   3130: goto -> 3141
    //   3133: ldc2_w -652105451
    //   3136: l2i
    //   3137: ldc_w -217536961
    //   3140: ixor
    //   3141: ldc2_w 1692663868
    //   3144: l2i
    //   3145: ldc_w 1938117832
    //   3148: ixor
    //   3149: ixor
    //   3150: lookupswitch default -> 5002, 182007242 -> 3133, 1028152286 -> 3176
    //   3176: aload_1
    //   3177: new net/minecraft/util/math/Vec3d
    //   3180: dup
    //   3181: getstatic Perryc.1 : I
    //   3184: ifeq -> 3198
    //   3187: ldc2_w -470042666
    //   3190: l2i
    //   3191: ldc_w -1194370022
    //   3194: ixor
    //   3195: goto -> 3206
    //   3198: ldc2_w -5627796
    //   3201: l2i
    //   3202: ldc_w 934317335
    //   3205: ixor
    //   3206: ldc2_w 2067631395
    //   3209: l2i
    //   3210: ldc_w -598295629
    //   3213: ixor
    //   3214: ixor
    //   3215: lookupswitch default -> 4938, -60826276 -> 3198, 1869716459 -> 3240
    //   3240: dload #9
    //   3242: getstatic Perryc.1 : I
    //   3245: ifeq -> 3259
    //   3248: ldc2_w -1150291188
    //   3251: l2i
    //   3252: ldc_w 890277157
    //   3255: ixor
    //   3256: goto -> 3267
    //   3259: ldc2_w 2106668393
    //   3262: l2i
    //   3263: ldc_w 675789731
    //   3266: ixor
    //   3267: ldc2_w 1868284818
    //   3270: l2i
    //   3271: ldc_w -1775965801
    //   3274: ixor
    //   3275: ixor
    //   3276: lookupswitch default -> 3304, 1537746384 -> 3259, 1996510252 -> 4962
    //   3304: dload_3
    //   3305: getstatic Perryc.c : I
    //   3308: iflt -> 3322
    //   3311: ldc2_w -1496504864
    //   3314: l2i
    //   3315: ldc_w 1645150634
    //   3318: ixor
    //   3319: goto -> 3330
    //   3322: ldc2_w 594659515
    //   3325: l2i
    //   3326: ldc_w -1411538400
    //   3329: ixor
    //   3330: ldc2_w -622584292
    //   3333: l2i
    //   3334: ldc_w 1541661090
    //   3337: ixor
    //   3338: ixor
    //   3339: lookupswitch default -> 3364, -1160939121 -> 3322, 1170594804 -> 5038
    //   3364: dload #11
    //   3366: getstatic Perryc.1 : I
    //   3369: ifeq -> 3383
    //   3372: ldc2_w -69686565
    //   3375: l2i
    //   3376: ldc_w -188359626
    //   3379: ixor
    //   3380: goto -> 3391
    //   3383: ldc2_w 1929502072
    //   3386: l2i
    //   3387: ldc_w 1877269632
    //   3390: ixor
    //   3391: ldc2_w 1878565516
    //   3394: l2i
    //   3395: ldc_w 293803251
    //   3398: ixor
    //   3399: ixor
    //   3400: lookupswitch default -> 3428, -2072834232 -> 3383, 1902559378 -> 5036
    //   3428: goto -> 3432
    //   3431: athrow
    //   3432: invokespecial <init> : (DDD)V
    //   3435: goto -> 3439
    //   3438: athrow
    //   3439: getstatic Perryc.0 : I
    //   3442: ifle -> 3456
    //   3445: ldc2_w -1137811881
    //   3448: l2i
    //   3449: ldc_w -953454517
    //   3452: ixor
    //   3453: goto -> 3464
    //   3456: ldc2_w 53569928
    //   3459: l2i
    //   3460: ldc_w -1475704638
    //   3463: ixor
    //   3464: ldc2_w 313356131
    //   3467: l2i
    //   3468: ldc_w -1378653706
    //   3471: ixor
    //   3472: ixor
    //   3473: lookupswitch default -> 4984, -998561655 -> 3456, 340125663 -> 3500
    //   3500: goto -> 3504
    //   3503: athrow
    //   3504: invokevirtual add : (Ljava/lang/Object;)Z
    //   3507: goto -> 3511
    //   3510: athrow
    //   3511: pop
    //   3512: getstatic Perryc.c : I
    //   3515: iflt -> 3529
    //   3518: ldc2_w -1671470402
    //   3521: l2i
    //   3522: ldc_w -1540206720
    //   3525: ixor
    //   3526: goto -> 3537
    //   3529: ldc2_w 734970540
    //   3532: l2i
    //   3533: ldc_w 1788672426
    //   3536: ixor
    //   3537: ldc2_w -182088760
    //   3540: l2i
    //   3541: ldc_w 130092092
    //   3544: ixor
    //   3545: ixor
    //   3546: lookupswitch default -> 3572, -896947510 -> 5082, 1091691569 -> 3529
    //   3572: aload_1
    //   3573: areturn
    //   3574: getstatic Perryc.1 : I
    //   3577: ifeq -> 3591
    //   3580: ldc2_w 1086843445
    //   3583: l2i
    //   3584: ldc_w 1267026084
    //   3587: ixor
    //   3588: goto -> 3599
    //   3591: ldc2_w 243227735
    //   3594: l2i
    //   3595: ldc_w 1087010104
    //   3598: ixor
    //   3599: ldc2_w 136158363
    //   3602: l2i
    //   3603: ldc_w 991057424
    //   3606: ixor
    //   3607: ixor
    //   3608: lookupswitch default -> 3636, 944597018 -> 4944, 960947245 -> 3591
    //   3636: dload #7
    //   3638: getstatic Perryc.1 : I
    //   3641: ifeq -> 3655
    //   3644: ldc2_w 1545856927
    //   3647: l2i
    //   3648: ldc_w -1770580615
    //   3651: ixor
    //   3652: goto -> 3663
    //   3655: ldc2_w -273891929
    //   3658: l2i
    //   3659: ldc_w -1855964154
    //   3662: ixor
    //   3663: ldc2_w -1419467070
    //   3666: l2i
    //   3667: ldc_w 1022110890
    //   3670: ixor
    //   3671: ixor
    //   3672: lookupswitch default -> 3700, 1166206662 -> 3655, 1574729870 -> 5048
    //   3700: dload #11
    //   3702: dcmpl
    //   3703: ifeq -> 3717
    //   3706: ldc2_w 444287727
    //   3709: l2i
    //   3710: ldc_w 533002983
    //   3713: ixor
    //   3714: goto -> 3725
    //   3717: ldc2_w 381677786
    //   3720: l2i
    //   3721: ldc_w 318783697
    //   3724: ixor
    //   3725: ldc2_w 642237090
    //   3728: l2i
    //   3729: ldc_w -1604311985
    //   3732: ixor
    //   3733: ixor
    //   3734: tableswitch default -> 3706, -2087168283 -> 3756, -2087168282 -> 4610
    //   3756: getstatic Perryc.0 : I
    //   3759: ifle -> 3773
    //   3762: ldc2_w 44616524
    //   3765: l2i
    //   3766: ldc_w -12115428
    //   3769: ixor
    //   3770: goto -> 3781
    //   3773: ldc2_w -1632176282
    //   3776: l2i
    //   3777: ldc_w -1371259944
    //   3780: ixor
    //   3781: ldc2_w 717786217
    //   3784: l2i
    //   3785: ldc_w 1702126455
    //   3788: ixor
    //   3789: ixor
    //   3790: lookupswitch default -> 3816, -1303181746 -> 4980, 492002943 -> 3773
    //   3816: aload_1
    //   3817: new net/minecraft/util/math/Vec3d
    //   3820: dup
    //   3821: getstatic Perryc.0 : I
    //   3824: ifle -> 3838
    //   3827: ldc2_w -52657696
    //   3830: l2i
    //   3831: ldc_w -422195947
    //   3834: ixor
    //   3835: goto -> 3846
    //   3838: ldc2_w -2000515355
    //   3841: l2i
    //   3842: ldc_w 909937326
    //   3845: ixor
    //   3846: ldc2_w -1506098850
    //   3849: l2i
    //   3850: ldc_w 504988200
    //   3853: ixor
    //   3854: ixor
    //   3855: lookupswitch default -> 5056, -1574301821 -> 3838, 115164989 -> 3880
    //   3880: dload #5
    //   3882: getstatic Perryc.0 : I
    //   3885: ifle -> 3899
    //   3888: ldc2_w -1920900114
    //   3891: l2i
    //   3892: ldc_w 1841716005
    //   3895: ixor
    //   3896: goto -> 3907
    //   3899: ldc2_w -325002401
    //   3902: l2i
    //   3903: ldc_w -80969550
    //   3906: ixor
    //   3907: ldc2_w 442661102
    //   3910: l2i
    //   3911: ldc_w 807761268
    //   3914: ixor
    //   3915: ixor
    //   3916: lookupswitch default -> 3944, -905956015 -> 5070, 185914332 -> 3899
    //   3944: dload_3
    //   3945: getstatic Perryc.1 : I
    //   3948: ifeq -> 3962
    //   3951: ldc2_w -152695625
    //   3954: l2i
    //   3955: ldc_w 190323372
    //   3958: ixor
    //   3959: goto -> 3970
    //   3962: ldc2_w -1011826655
    //   3965: l2i
    //   3966: ldc_w -2143501130
    //   3969: ixor
    //   3970: ldc2_w 1762313459
    //   3973: l2i
    //   3974: ldc_w -2085502321
    //   3977: ixor
    //   3978: ixor
    //   3979: lookupswitch default -> 5060, -1456012565 -> 4004, 386207847 -> 3962
    //   4004: dload #7
    //   4006: getstatic Perryc.0 : I
    //   4009: ifle -> 4023
    //   4012: ldc2_w 1157727440
    //   4015: l2i
    //   4016: ldc_w -573240597
    //   4019: ixor
    //   4020: goto -> 4031
    //   4023: ldc2_w 1796611925
    //   4026: l2i
    //   4027: ldc_w -1724627607
    //   4030: ixor
    //   4031: ldc2_w -1091751809
    //   4034: l2i
    //   4035: ldc_w 1180317921
    //   4038: ixor
    //   4039: ixor
    //   4040: lookupswitch default -> 5052, 177558178 -> 4068, 1617135269 -> 4023
    //   4068: goto -> 4072
    //   4071: athrow
    //   4072: invokespecial <init> : (DDD)V
    //   4075: goto -> 4079
    //   4078: athrow
    //   4079: getstatic Perryc.1 : I
    //   4082: ifeq -> 4096
    //   4085: ldc2_w 2088834100
    //   4088: l2i
    //   4089: ldc_w 1235724683
    //   4092: ixor
    //   4093: goto -> 4104
    //   4096: ldc2_w -1836072222
    //   4099: l2i
    //   4100: ldc_w 107344586
    //   4103: ixor
    //   4104: ldc2_w 1747450991
    //   4107: l2i
    //   4108: ldc_w 1345933791
    //   4111: ixor
    //   4112: ixor
    //   4113: lookupswitch default -> 4140, -547137352 -> 4096, 221777935 -> 4954
    //   4140: goto -> 4144
    //   4143: athrow
    //   4144: invokevirtual add : (Ljava/lang/Object;)Z
    //   4147: goto -> 4151
    //   4150: athrow
    //   4151: pop
    //   4152: getstatic Perryc.0 : I
    //   4155: ifle -> 4169
    //   4158: ldc2_w -528099925
    //   4161: l2i
    //   4162: ldc_w -814850709
    //   4165: ixor
    //   4166: goto -> 4177
    //   4169: ldc2_w -652147381
    //   4172: l2i
    //   4173: ldc_w -353997802
    //   4176: ixor
    //   4177: ldc2_w 2105045516
    //   4180: l2i
    //   4181: ldc_w -1278979162
    //   4184: ixor
    //   4185: ixor
    //   4186: lookupswitch default -> 5022, -514348694 -> 4169, -42252041 -> 4212
    //   4212: aload_1
    //   4213: new net/minecraft/util/math/Vec3d
    //   4216: dup
    //   4217: getstatic Perryc.c : I
    //   4220: iflt -> 4234
    //   4223: ldc2_w 718321428
    //   4226: l2i
    //   4227: ldc_w 1226314983
    //   4230: ixor
    //   4231: goto -> 4242
    //   4234: ldc2_w 1398628884
    //   4237: l2i
    //   4238: ldc_w -1018762041
    //   4241: ixor
    //   4242: ldc2_w 2096204075
    //   4245: l2i
    //   4246: ldc_w 1091426745
    //   4249: ixor
    //   4250: ixor
    //   4251: lookupswitch default -> 5062, -1377313215 -> 4276, 1580528481 -> 4234
    //   4276: dload #5
    //   4278: getstatic Perryc.c : I
    //   4281: iflt -> 4295
    //   4284: ldc2_w -1256115277
    //   4287: l2i
    //   4288: ldc_w -20902867
    //   4291: ixor
    //   4292: goto -> 4303
    //   4295: ldc2_w 1727138048
    //   4298: l2i
    //   4299: ldc_w -1255974509
    //   4302: ixor
    //   4303: ldc2_w -975687868
    //   4306: l2i
    //   4307: ldc_w -340381421
    //   4310: ixor
    //   4311: ixor
    //   4312: lookupswitch default -> 4340, -1834879236 -> 4295, 1703813577 -> 5054
    //   4340: dload_3
    //   4341: getstatic Perryc.c : I
    //   4344: iflt -> 4358
    //   4347: ldc2_w 1718896436
    //   4350: l2i
    //   4351: ldc_w -75116418
    //   4354: ixor
    //   4355: goto -> 4366
    //   4358: ldc2_w -229058264
    //   4361: l2i
    //   4362: ldc_w 463488237
    //   4365: ixor
    //   4366: ldc2_w 981805618
    //   4369: l2i
    //   4370: ldc_w -207371766
    //   4373: ixor
    //   4374: ixor
    //   4375: lookupswitch default -> 4972, 551450109 -> 4400, 1423409010 -> 4358
    //   4400: dload #11
    //   4402: getstatic Perryc.1 : I
    //   4405: ifeq -> 4419
    //   4408: ldc2_w 81102387
    //   4411: l2i
    //   4412: ldc_w -1060507137
    //   4415: ixor
    //   4416: goto -> 4427
    //   4419: ldc2_w -186501379
    //   4422: l2i
    //   4423: ldc_w 1162509669
    //   4426: ixor
    //   4427: ldc2_w -117324869
    //   4430: l2i
    //   4431: ldc_w 2131739320
    //   4434: ixor
    //   4435: ixor
    //   4436: lookupswitch default -> 4978, 933644955 -> 4464, 1108506319 -> 4419
    //   4464: goto -> 4468
    //   4467: athrow
    //   4468: invokespecial <init> : (DDD)V
    //   4471: goto -> 4475
    //   4474: athrow
    //   4475: getstatic Perryc.c : I
    //   4478: iflt -> 4492
    //   4481: ldc2_w -1247005700
    //   4484: l2i
    //   4485: ldc_w 1934400429
    //   4488: ixor
    //   4489: goto -> 4500
    //   4492: ldc2_w -1444352529
    //   4495: l2i
    //   4496: ldc_w 1541404508
    //   4499: ixor
    //   4500: ldc2_w 389830697
    //   4503: l2i
    //   4504: ldc_w 425131435
    //   4507: ixor
    //   4508: ixor
    //   4509: lookupswitch default -> 4536, -930476589 -> 5024, 1093877552 -> 4492
    //   4536: goto -> 4540
    //   4539: athrow
    //   4540: invokevirtual add : (Ljava/lang/Object;)Z
    //   4543: goto -> 4547
    //   4546: athrow
    //   4547: pop
    //   4548: getstatic Perryc.c : I
    //   4551: iflt -> 4565
    //   4554: ldc2_w 119183832
    //   4557: l2i
    //   4558: ldc_w -2130715946
    //   4561: ixor
    //   4562: goto -> 4573
    //   4565: ldc2_w 800428092
    //   4568: l2i
    //   4569: ldc_w -178999431
    //   4572: ixor
    //   4573: ldc2_w -1275969061
    //   4576: l2i
    //   4577: ldc_w 592221589
    //   4580: ixor
    //   4581: ixor
    //   4582: lookupswitch default -> 4992, 391878464 -> 4565, 1247800075 -> 4608
    //   4608: aload_1
    //   4609: areturn
    //   4610: getstatic Perryc.1 : I
    //   4613: ifeq -> 4627
    //   4616: ldc2_w -1784876649
    //   4619: l2i
    //   4620: ldc_w -814166326
    //   4623: ixor
    //   4624: goto -> 4635
    //   4627: ldc2_w -1681291536
    //   4630: l2i
    //   4631: ldc_w 2141282709
    //   4634: ixor
    //   4635: ldc2_w -470764457
    //   4638: l2i
    //   4639: ldc_w 334655596
    //   4642: ixor
    //   4643: ixor
    //   4644: lookupswitch default -> 5018, -1427702938 -> 4627, 342500190 -> 4672
    //   4672: aload_1
    //   4673: getstatic Perryc.c : I
    //   4676: iflt -> 4690
    //   4679: ldc2_w 1600911742
    //   4682: l2i
    //   4683: ldc_w 481415726
    //   4686: ixor
    //   4687: goto -> 4698
    //   4690: ldc2_w -1244818390
    //   4693: l2i
    //   4694: ldc_w 562669684
    //   4697: ixor
    //   4698: ldc2_w -1519324908
    //   4701: l2i
    //   4702: ldc_w 1157721036
    //   4705: ixor
    //   4706: ixor
    //   4707: lookupswitch default -> 4732, -1549028984 -> 5044, 1453295876 -> 4690
    //   4732: aload_0
    //   4733: getstatic Perryc.0 : I
    //   4736: ifle -> 4750
    //   4739: ldc2_w 997879064
    //   4742: l2i
    //   4743: ldc_w -584707977
    //   4746: ixor
    //   4747: goto -> 4758
    //   4750: ldc2_w -1812493173
    //   4753: l2i
    //   4754: ldc_w 1114891412
    //   4757: ixor
    //   4758: ldc2_w 1363187095
    //   4761: l2i
    //   4762: ldc_w -1954535985
    //   4765: ixor
    //   4766: ixor
    //   4767: lookupswitch default -> 4792, 839187630 -> 4750, 1016909111 -> 4998
    //   4792: goto -> 4796
    //   4795: athrow
    //   4796: invokevirtual func_174791_d : ()Lnet/minecraft/util/math/Vec3d;
    //   4799: goto -> 4803
    //   4802: athrow
    //   4803: getstatic Perryc.1 : I
    //   4806: ifeq -> 4820
    //   4809: ldc2_w -1570220891
    //   4812: l2i
    //   4813: ldc_w -772576539
    //   4816: ixor
    //   4817: goto -> 4828
    //   4820: ldc2_w -498334716
    //   4823: l2i
    //   4824: ldc_w 1729344042
    //   4827: ixor
    //   4828: ldc2_w -1818305545
    //   4831: l2i
    //   4832: ldc_w -2057029546
    //   4835: ixor
    //   4836: ixor
    //   4837: lookupswitch default -> 5012, -1817881201 -> 4864, 1700912609 -> 4820
    //   4864: goto -> 4868
    //   4867: athrow
    //   4868: invokevirtual add : (Ljava/lang/Object;)Z
    //   4871: goto -> 4875
    //   4874: athrow
    //   4875: pop
    //   4876: getstatic Perryc.0 : I
    //   4879: ifle -> 4893
    //   4882: ldc2_w -1459240473
    //   4885: l2i
    //   4886: ldc_w -1415424470
    //   4889: ixor
    //   4890: goto -> 4901
    //   4893: ldc2_w 654813376
    //   4896: l2i
    //   4897: ldc_w -1462021734
    //   4900: ixor
    //   4901: ldc2_w -725944263
    //   4904: l2i
    //   4905: ldc_w -1486714538
    //   4908: ixor
    //   4909: ixor
    //   4910: lookupswitch default -> 4964, -66811851 -> 4936, 1904207522 -> 4893
    //   4936: aload_1
    //   4937: areturn
    //   4938: aconst_null
    //   4939: athrow
    //   4940: aconst_null
    //   4941: athrow
    //   4942: aconst_null
    //   4943: athrow
    //   4944: aconst_null
    //   4945: athrow
    //   4946: aconst_null
    //   4947: athrow
    //   4948: aconst_null
    //   4949: athrow
    //   4950: aconst_null
    //   4951: athrow
    //   4952: aconst_null
    //   4953: athrow
    //   4954: aconst_null
    //   4955: athrow
    //   4956: aconst_null
    //   4957: athrow
    //   4958: aconst_null
    //   4959: athrow
    //   4960: aconst_null
    //   4961: athrow
    //   4962: aconst_null
    //   4963: athrow
    //   4964: aconst_null
    //   4965: athrow
    //   4966: aconst_null
    //   4967: athrow
    //   4968: aconst_null
    //   4969: athrow
    //   4970: aconst_null
    //   4971: athrow
    //   4972: aconst_null
    //   4973: athrow
    //   4974: aconst_null
    //   4975: athrow
    //   4976: aconst_null
    //   4977: athrow
    //   4978: aconst_null
    //   4979: athrow
    //   4980: aconst_null
    //   4981: athrow
    //   4982: aconst_null
    //   4983: athrow
    //   4984: aconst_null
    //   4985: athrow
    //   4986: aconst_null
    //   4987: athrow
    //   4988: aconst_null
    //   4989: athrow
    //   4990: aconst_null
    //   4991: athrow
    //   4992: aconst_null
    //   4993: athrow
    //   4994: aconst_null
    //   4995: athrow
    //   4996: aconst_null
    //   4997: athrow
    //   4998: aconst_null
    //   4999: athrow
    //   5000: aconst_null
    //   5001: athrow
    //   5002: aconst_null
    //   5003: athrow
    //   5004: aconst_null
    //   5005: athrow
    //   5006: aconst_null
    //   5007: athrow
    //   5008: aconst_null
    //   5009: athrow
    //   5010: aconst_null
    //   5011: athrow
    //   5012: aconst_null
    //   5013: athrow
    //   5014: aconst_null
    //   5015: athrow
    //   5016: aconst_null
    //   5017: athrow
    //   5018: aconst_null
    //   5019: athrow
    //   5020: aconst_null
    //   5021: athrow
    //   5022: aconst_null
    //   5023: athrow
    //   5024: aconst_null
    //   5025: athrow
    //   5026: aconst_null
    //   5027: athrow
    //   5028: aconst_null
    //   5029: athrow
    //   5030: aconst_null
    //   5031: athrow
    //   5032: aconst_null
    //   5033: athrow
    //   5034: aconst_null
    //   5035: athrow
    //   5036: aconst_null
    //   5037: athrow
    //   5038: aconst_null
    //   5039: athrow
    //   5040: aconst_null
    //   5041: athrow
    //   5042: aconst_null
    //   5043: athrow
    //   5044: aconst_null
    //   5045: athrow
    //   5046: aconst_null
    //   5047: athrow
    //   5048: aconst_null
    //   5049: athrow
    //   5050: aconst_null
    //   5051: athrow
    //   5052: aconst_null
    //   5053: athrow
    //   5054: aconst_null
    //   5055: athrow
    //   5056: aconst_null
    //   5057: athrow
    //   5058: aconst_null
    //   5059: athrow
    //   5060: aconst_null
    //   5061: athrow
    //   5062: aconst_null
    //   5063: athrow
    //   5064: aconst_null
    //   5065: athrow
    //   5066: aconst_null
    //   5067: athrow
    //   5068: aconst_null
    //   5069: athrow
    //   5070: aconst_null
    //   5071: athrow
    //   5072: aconst_null
    //   5073: athrow
    //   5074: aconst_null
    //   5075: athrow
    //   5076: aconst_null
    //   5077: athrow
    //   5078: aconst_null
    //   5079: athrow
    //   5080: aconst_null
    //   5081: athrow
    //   5082: aconst_null
    //   5083: athrow
    //   5084: pop
    //   5085: goto -> 24
    //   5088: pop
    //   5089: aconst_null
    //   5090: goto -> 5084
    //   5093: dup
    //   5094: ifnull -> 5084
    //   5097: checkcast java/lang/Throwable
    //   5100: athrow
    //   5101: dup
    //   5102: ifnull -> 5088
    //   5105: checkcast java/lang/Throwable
    //   5108: athrow
    //   5109: aconst_null
    //   5110: athrow
    // Local variable table:
    //   start	length	slot	name	descriptor
    //   24	4914	0	entity	Lnet/minecraft/entity/Entity;
    //   153	4785	1	vec3ds	Ljava/util/ArrayList;
    //   341	4597	2	bb	Lnet/minecraft/util/math/AxisAlignedBB;
    //   521	4417	3	y	D
    //   778	4160	5	minX	D
    //   1034	3904	7	minZ	D
    //   1298	3640	9	maxX	D
    //   1566	3372	11	maxZ	D
    // Local variable type table:
    //   start	length	slot	name	signature
    //   153	4785	1	vec3ds	Ljava/util/ArrayList<Lnet/minecraft/util/math/Vec3d;>;
    // Exception table:
    //   from	to	target	type
    //   8	20	5093	java/lang/NegativeArraySizeException
    //   88	94	94	finally
    //   88	94	94	java/lang/IndexOutOfBoundsException
    //   88	94	3	finally
    //   88	94	3	finally
    //   88	94	94	java/lang/StringIndexOutOfBoundsException
    //   275	282	282	finally
    //   275	282	275	java/lang/AssertionError
    //   275	282	3	java/lang/ArrayIndexOutOfBoundsException
    //   275	282	3	java/lang/RuntimeException
    //   276	282	275	java/lang/StringIndexOutOfBoundsException
    //   711	718	718	finally
    //   711	718	718	java/lang/EnumConstantNotPresentException
    //   712	718	3	finally
    //   712	718	718	java/lang/NegativeArraySizeException
    //   712	718	711	finally
    //   967	974	974	finally
    //   967	974	967	finally
    //   967	974	967	finally
    //   968	974	3	java/util/ConcurrentModificationException
    //   968	974	967	java/lang/IndexOutOfBoundsException
    //   1228	1234	1234	finally
    //   1228	1234	3	java/lang/ArithmeticException
    //   1228	1234	3	java/lang/NumberFormatException
    //   1228	1234	3	finally
    //   1228	1234	3	java/lang/EnumConstantNotPresentException
    //   1495	1502	1502	finally
    //   1495	1502	1502	java/lang/NullPointerException
    //   1495	1502	1495	java/util/NoSuchElementException
    //   1495	1502	3	java/lang/NumberFormatException
    //   1496	1502	1502	finally
    //   2063	2070	2070	finally
    //   2063	2070	2070	finally
    //   2063	2070	3	finally
    //   2064	2070	2063	java/lang/IllegalArgumentException
    //   2064	2070	2070	finally
    //   2135	2142	2142	finally
    //   2135	2142	2142	finally
    //   2136	2142	2135	finally
    //   2136	2142	2135	finally
    //   2136	2142	3	java/lang/ArrayIndexOutOfBoundsException
    //   2459	2466	2466	finally
    //   2459	2466	3	java/lang/ArithmeticException
    //   2460	2466	2459	java/lang/EnumConstantNotPresentException
    //   2460	2466	2466	finally
    //   2460	2466	3	finally
    //   2531	2538	2538	finally
    //   2531	2538	3	finally
    //   2531	2538	2531	finally
    //   2531	2538	2531	java/lang/StringIndexOutOfBoundsException
    //   2532	2538	2538	java/util/NoSuchElementException
    //   3036	3042	3042	finally
    //   3036	3042	3042	java/util/NoSuchElementException
    //   3036	3042	3042	finally
    //   3036	3042	3042	java/lang/IllegalStateException
    //   3036	3042	3	finally
    //   3107	3114	3114	finally
    //   3107	3114	3114	java/lang/EnumConstantNotPresentException
    //   3107	3114	3107	java/lang/IllegalStateException
    //   3108	3114	3114	java/lang/UnsupportedOperationException
    //   3108	3114	3114	java/lang/NumberFormatException
    //   3432	3438	3438	finally
    //   3432	3438	3438	finally
    //   3432	3438	3	finally
    //   3432	3438	3438	finally
    //   3432	3438	3	java/lang/IllegalArgumentException
    //   3503	3510	3510	finally
    //   3503	3510	3503	finally
    //   3504	3510	3503	java/lang/ArithmeticException
    //   3504	3510	3510	finally
    //   3504	3510	3	java/lang/ClassCastException
    //   4072	4078	4078	finally
    //   4072	4078	4078	java/lang/AssertionError
    //   4072	4078	4078	finally
    //   4072	4078	3	finally
    //   4072	4078	4078	java/util/ConcurrentModificationException
    //   4143	4150	4150	finally
    //   4143	4150	4150	finally
    //   4143	4150	4143	java/lang/UnsupportedOperationException
    //   4144	4150	4150	java/lang/ClassCastException
    //   4144	4150	3	java/lang/ArithmeticException
    //   4467	4474	4474	finally
    //   4467	4474	4467	finally
    //   4468	4474	4474	java/lang/EnumConstantNotPresentException
    //   4468	4474	3	finally
    //   4468	4474	4467	java/lang/IndexOutOfBoundsException
    //   4539	4546	4546	finally
    //   4539	4546	4539	finally
    //   4540	4546	4546	finally
    //   4540	4546	3	finally
    //   4540	4546	4539	finally
    //   4795	4802	4802	finally
    //   4795	4802	4802	java/lang/IndexOutOfBoundsException
    //   4795	4802	4795	finally
    //   4796	4802	3	finally
    //   4796	4802	4802	java/lang/EnumConstantNotPresentException
    //   4867	4874	4874	finally
    //   4867	4874	3	java/lang/IllegalArgumentException
    //   4867	4874	4867	finally
    //   4867	4874	3	java/lang/NumberFormatException
    //   4868	4874	4874	java/lang/NullPointerException
    //   5093	5101	5093	java/util/ConcurrentModificationException
    //   5109	5111	3	java/lang/StringIndexOutOfBoundsException
  }
  
  public static Map sortByValue(Map<K, V> map, boolean descending) {
    // Byte code:
    //   0: goto -> 8
    //   3: dup
    //   4: ifnull -> 2173
    //   7: athrow
    //   8: aconst_null
    //   9: getstatic Perryc.c : I
    //   12: ifge -> 2165
    //   15: pop
    //   16: aconst_null
    //   17: goto -> 2157
    //   20: nop
    //   21: nop
    //   22: nop
    //   23: athrow
    //   24: new java/util/LinkedList
    //   27: dup
    //   28: getstatic Perryc.1 : I
    //   31: ifeq -> 45
    //   34: ldc2_w 275749799
    //   37: l2i
    //   38: ldc_w 28750619
    //   41: ixor
    //   42: goto -> 53
    //   45: ldc2_w 1568067231
    //   48: l2i
    //   49: ldc_w -1136060412
    //   52: ixor
    //   53: ldc2_w 358361963
    //   56: l2i
    //   57: ldc_w -1468912194
    //   60: ixor
    //   61: ixor
    //   62: lookupswitch default -> 88, -1393086871 -> 2090, 1949848471 -> 45
    //   88: aload_0
    //   89: getstatic Perryc.c : I
    //   92: iflt -> 106
    //   95: ldc2_w -250854420
    //   98: l2i
    //   99: ldc_w 1753037681
    //   102: ixor
    //   103: goto -> 114
    //   106: ldc2_w 1901943902
    //   109: l2i
    //   110: ldc_w 40544323
    //   113: ixor
    //   114: ldc2_w -1276037537
    //   117: l2i
    //   118: ldc_w 121645866
    //   121: ixor
    //   122: ixor
    //   123: lookupswitch default -> 2112, -947459736 -> 148, 767583720 -> 106
    //   148: goto -> 152
    //   151: athrow
    //   152: invokeinterface entrySet : ()Ljava/util/Set;
    //   157: goto -> 161
    //   160: athrow
    //   161: getstatic Perryc.c : I
    //   164: iflt -> 178
    //   167: ldc2_w 627004886
    //   170: l2i
    //   171: ldc_w -2116227953
    //   174: ixor
    //   175: goto -> 186
    //   178: ldc2_w 1847158430
    //   181: l2i
    //   182: ldc_w 1474886244
    //   185: ixor
    //   186: ldc2_w -959939687
    //   189: l2i
    //   190: ldc_w 809799292
    //   193: ixor
    //   194: ixor
    //   195: lookupswitch default -> 2106, -813864673 -> 220, 1376734396 -> 178
    //   220: goto -> 224
    //   223: athrow
    //   224: invokespecial <init> : (Ljava/util/Collection;)V
    //   227: goto -> 231
    //   230: athrow
    //   231: getstatic Perryc.0 : I
    //   234: ifle -> 248
    //   237: ldc2_w 220798097
    //   240: l2i
    //   241: ldc_w 1749983188
    //   244: ixor
    //   245: goto -> 256
    //   248: ldc2_w 2078728075
    //   251: l2i
    //   252: ldc_w -1871161419
    //   255: ixor
    //   256: ldc2_w 794667537
    //   259: l2i
    //   260: ldc_w -632882650
    //   263: ixor
    //   264: ixor
    //   265: lookupswitch default -> 292, -1870867598 -> 2118, -1183744513 -> 248
    //   292: astore_2
    //   293: getstatic Perryc.0 : I
    //   296: ifle -> 310
    //   299: ldc2_w 701856507
    //   302: l2i
    //   303: ldc_w 381198639
    //   306: ixor
    //   307: goto -> 318
    //   310: ldc2_w -512331439
    //   313: l2i
    //   314: ldc_w 337514246
    //   317: ixor
    //   318: ldc2_w -2058455055
    //   321: l2i
    //   322: ldc_w -512134490
    //   325: ixor
    //   326: ixor
    //   327: lookupswitch default -> 352, -443011414 -> 310, 1532681859 -> 2116
    //   352: iload_1
    //   353: ifeq -> 367
    //   356: ldc2_w -1282547406
    //   359: l2i
    //   360: ldc_w 978344621
    //   363: ixor
    //   364: goto -> 375
    //   367: ldc2_w -1076340577
    //   370: l2i
    //   371: ldc_w 906355459
    //   374: ixor
    //   375: ldc2_w -1802154154
    //   378: l2i
    //   379: ldc_w 1666454476
    //   382: ixor
    //   383: ixor
    //   384: tableswitch default -> 356, 2115823365 -> 408, 2115823366 -> 686
    //   408: getstatic Perryc.0 : I
    //   411: ifle -> 425
    //   414: ldc2_w 799829922
    //   417: l2i
    //   418: ldc_w 2135113980
    //   421: ixor
    //   422: goto -> 433
    //   425: ldc2_w 66980058
    //   428: l2i
    //   429: ldc_w 1732045422
    //   432: ixor
    //   433: ldc2_w -369660142
    //   436: l2i
    //   437: ldc_w 1693850708
    //   440: ixor
    //   441: ixor
    //   442: lookupswitch default -> 468, -571581416 -> 2130, 770176523 -> 425
    //   468: aload_2
    //   469: getstatic Perryc.c : I
    //   472: iflt -> 486
    //   475: ldc2_w 512474333
    //   478: l2i
    //   479: ldc_w -1906408049
    //   482: ixor
    //   483: goto -> 494
    //   486: ldc2_w 1782758072
    //   489: l2i
    //   490: ldc_w -889113147
    //   493: ixor
    //   494: ldc2_w 556312576
    //   497: l2i
    //   498: ldc_w 1023932563
    //   501: ixor
    //   502: ixor
    //   503: lookupswitch default -> 2126, -1929745983 -> 486, -1116938258 -> 528
    //   528: goto -> 532
    //   531: athrow
    //   532: invokestatic reverseOrder : ()Ljava/util/Comparator;
    //   535: goto -> 539
    //   538: athrow
    //   539: getstatic Perryc.1 : I
    //   542: ifeq -> 556
    //   545: ldc2_w -1859523278
    //   548: l2i
    //   549: ldc_w 610116990
    //   552: ixor
    //   553: goto -> 564
    //   556: ldc2_w 215148211
    //   559: l2i
    //   560: ldc_w -819707403
    //   563: ixor
    //   564: ldc2_w 852281917
    //   567: l2i
    //   568: ldc_w -1136922821
    //   571: ixor
    //   572: ixor
    //   573: lookupswitch default -> 600, -316481407 -> 556, 998468938 -> 2100
    //   600: goto -> 604
    //   603: athrow
    //   604: invokestatic comparingByValue : (Ljava/util/Comparator;)Ljava/util/Comparator;
    //   607: goto -> 611
    //   610: athrow
    //   611: getstatic Perryc.c : I
    //   614: iflt -> 628
    //   617: ldc2_w 40176312
    //   620: l2i
    //   621: ldc_w 362273738
    //   624: ixor
    //   625: goto -> 636
    //   628: ldc2_w 1032168842
    //   631: l2i
    //   632: ldc_w -1009158606
    //   635: ixor
    //   636: ldc2_w 2017784372
    //   639: l2i
    //   640: ldc_w -109279785
    //   643: ixor
    //   644: ixor
    //   645: lookupswitch default -> 672, -1947709687 -> 628, -1765103983 -> 2094
    //   672: goto -> 676
    //   675: athrow
    //   676: invokevirtual sort : (Ljava/util/Comparator;)V
    //   679: goto -> 683
    //   682: athrow
    //   683: goto -> 891
    //   686: getstatic Perryc.1 : I
    //   689: ifeq -> 703
    //   692: ldc2_w 1614880496
    //   695: l2i
    //   696: ldc_w 235394408
    //   699: ixor
    //   700: goto -> 711
    //   703: ldc2_w 1216199383
    //   706: l2i
    //   707: ldc_w 1436536989
    //   710: ixor
    //   711: ldc2_w 1043484699
    //   714: l2i
    //   715: ldc_w -1776273230
    //   718: ixor
    //   719: ixor
    //   720: lookupswitch default -> 2092, -1242561821 -> 748, -967531727 -> 703
    //   748: aload_2
    //   749: getstatic Perryc.0 : I
    //   752: ifle -> 766
    //   755: ldc2_w 1271547870
    //   758: l2i
    //   759: ldc_w -915862073
    //   762: ixor
    //   763: goto -> 774
    //   766: ldc2_w 1978210195
    //   769: l2i
    //   770: ldc_w -214180291
    //   773: ixor
    //   774: ldc2_w -2076999118
    //   777: l2i
    //   778: ldc_w -679704905
    //   781: ixor
    //   782: ixor
    //   783: lookupswitch default -> 808, -773042532 -> 2120, 698411176 -> 766
    //   808: goto -> 812
    //   811: athrow
    //   812: invokestatic comparingByValue : ()Ljava/util/Comparator;
    //   815: goto -> 819
    //   818: athrow
    //   819: getstatic Perryc.1 : I
    //   822: ifeq -> 836
    //   825: ldc2_w -1949116204
    //   828: l2i
    //   829: ldc_w 1566636893
    //   832: ixor
    //   833: goto -> 844
    //   836: ldc2_w 1752709588
    //   839: l2i
    //   840: ldc_w 1872164589
    //   843: ixor
    //   844: ldc2_w -508080913
    //   847: l2i
    //   848: ldc_w -142759564
    //   851: ixor
    //   852: ixor
    //   853: lookupswitch default -> 2110, -1065826798 -> 836, 287582882 -> 880
    //   880: goto -> 884
    //   883: athrow
    //   884: invokevirtual sort : (Ljava/util/Comparator;)V
    //   887: goto -> 891
    //   890: athrow
    //   891: new java/util/LinkedHashMap
    //   894: dup
    //   895: getstatic Perryc.c : I
    //   898: iflt -> 912
    //   901: ldc2_w 437018919
    //   904: l2i
    //   905: ldc_w -1520486323
    //   908: ixor
    //   909: goto -> 920
    //   912: ldc2_w 286086898
    //   915: l2i
    //   916: ldc_w 332225421
    //   919: ixor
    //   920: ldc2_w 381442070
    //   923: l2i
    //   924: ldc_w -943402499
    //   927: ixor
    //   928: ixor
    //   929: lookupswitch default -> 956, -1519320471 -> 912, 1848365185 -> 2144
    //   956: goto -> 960
    //   959: athrow
    //   960: invokespecial <init> : ()V
    //   963: goto -> 967
    //   966: athrow
    //   967: getstatic Perryc.c : I
    //   970: iflt -> 984
    //   973: ldc2_w -906026690
    //   976: l2i
    //   977: ldc_w 2021549666
    //   980: ixor
    //   981: goto -> 992
    //   984: ldc2_w 2129313733
    //   987: l2i
    //   988: ldc_w -1950185775
    //   991: ixor
    //   992: ldc2_w 700229947
    //   995: l2i
    //   996: ldc_w -367063857
    //   999: ixor
    //   1000: ixor
    //   1001: lookupswitch default -> 2142, 915119328 -> 1028, 1914888872 -> 984
    //   1028: astore_3
    //   1029: getstatic Perryc.c : I
    //   1032: iflt -> 1046
    //   1035: ldc2_w 1886400797
    //   1038: l2i
    //   1039: ldc_w -443910165
    //   1042: ixor
    //   1043: goto -> 1054
    //   1046: ldc2_w -757173958
    //   1049: l2i
    //   1050: ldc_w -1868951091
    //   1053: ixor
    //   1054: ldc2_w 89493892
    //   1057: l2i
    //   1058: ldc_w -1848036294
    //   1061: ixor
    //   1062: ixor
    //   1063: lookupswitch default -> 1088, -1091151308 -> 1046, 24568648 -> 2134
    //   1088: aload_2
    //   1089: getstatic Perryc.1 : I
    //   1092: ifeq -> 1106
    //   1095: ldc2_w 1166165238
    //   1098: l2i
    //   1099: ldc_w 369599390
    //   1102: ixor
    //   1103: goto -> 1114
    //   1106: ldc2_w -399466327
    //   1109: l2i
    //   1110: ldc_w 1846816117
    //   1113: ixor
    //   1114: ldc2_w -388591274
    //   1117: l2i
    //   1118: ldc_w 2027332194
    //   1121: ixor
    //   1122: ixor
    //   1123: lookupswitch default -> 1148, -1014639524 -> 2108, -342945875 -> 1106
    //   1148: goto -> 1152
    //   1151: athrow
    //   1152: invokevirtual iterator : ()Ljava/util/Iterator;
    //   1155: goto -> 1159
    //   1158: athrow
    //   1159: getstatic Perryc.c : I
    //   1162: iflt -> 1176
    //   1165: ldc2_w -89500329
    //   1168: l2i
    //   1169: ldc_w 415890736
    //   1172: ixor
    //   1173: goto -> 1184
    //   1176: ldc2_w 200064129
    //   1179: l2i
    //   1180: ldc_w -801693169
    //   1183: ixor
    //   1184: ldc2_w -456318309
    //   1187: l2i
    //   1188: ldc_w -1168647237
    //   1191: ixor
    //   1192: ixor
    //   1193: lookupswitch default -> 1220, -1124511417 -> 2104, 82945753 -> 1176
    //   1220: astore #4
    //   1222: getstatic Perryc.0 : I
    //   1225: ifle -> 1239
    //   1228: ldc2_w -1575631193
    //   1231: l2i
    //   1232: ldc_w -1640219474
    //   1235: ixor
    //   1236: goto -> 1247
    //   1239: ldc2_w 1998609550
    //   1242: l2i
    //   1243: ldc_w -1033318026
    //   1246: ixor
    //   1247: ldc2_w -1157982735
    //   1250: l2i
    //   1251: ldc_w 29052586
    //   1254: ixor
    //   1255: ixor
    //   1256: lookupswitch default -> 2128, -2023218862 -> 1239, 235493027 -> 1284
    //   1284: aload #4
    //   1286: getstatic Perryc.0 : I
    //   1289: ifle -> 1303
    //   1292: ldc2_w -466154948
    //   1295: l2i
    //   1296: ldc_w 1021887535
    //   1299: ixor
    //   1300: goto -> 1311
    //   1303: ldc2_w -1271671977
    //   1306: l2i
    //   1307: ldc_w 1972503342
    //   1310: ixor
    //   1311: ldc2_w -1325171760
    //   1314: l2i
    //   1315: ldc_w 537836125
    //   1318: ixor
    //   1319: ixor
    //   1320: lookupswitch default -> 2098, 1238503326 -> 1303, 1353454068 -> 1348
    //   1348: goto -> 1352
    //   1351: athrow
    //   1352: invokeinterface hasNext : ()Z
    //   1357: goto -> 1361
    //   1360: athrow
    //   1361: ifeq -> 1375
    //   1364: ldc2_w 1941884198
    //   1367: l2i
    //   1368: ldc_w -1553380182
    //   1371: ixor
    //   1372: goto -> 1383
    //   1375: ldc2_w -1722369688
    //   1378: l2i
    //   1379: ldc_w 1233205483
    //   1382: ixor
    //   1383: ldc2_w -1295087092
    //   1386: l2i
    //   1387: ldc_w -668632265
    //   1390: ixor
    //   1391: ixor
    //   1392: tableswitch default -> 1364, -1170444105 -> 1416, -1170444104 -> 2027
    //   1416: getstatic Perryc.0 : I
    //   1419: ifle -> 1433
    //   1422: ldc2_w 945977770
    //   1425: l2i
    //   1426: ldc_w -546161150
    //   1429: ixor
    //   1430: goto -> 1441
    //   1433: ldc2_w 1765418799
    //   1436: l2i
    //   1437: ldc_w 1365467984
    //   1440: ixor
    //   1441: ldc2_w 2033700953
    //   1444: l2i
    //   1445: ldc_w 981886735
    //   1448: ixor
    //   1449: ixor
    //   1450: lookupswitch default -> 1476, -1623226781 -> 1433, -1532890882 -> 2102
    //   1476: aload #4
    //   1478: getstatic Perryc.1 : I
    //   1481: ifeq -> 1495
    //   1484: ldc2_w -1754827567
    //   1487: l2i
    //   1488: ldc_w 118189124
    //   1491: ixor
    //   1492: goto -> 1503
    //   1495: ldc2_w 642578841
    //   1498: l2i
    //   1499: ldc_w 1797648342
    //   1502: ixor
    //   1503: ldc2_w 576506896
    //   1506: l2i
    //   1507: ldc_w -1214972261
    //   1510: ixor
    //   1511: ixor
    //   1512: lookupswitch default -> 1540, 94644766 -> 2122, 169619915 -> 1495
    //   1540: goto -> 1544
    //   1543: athrow
    //   1544: invokeinterface next : ()Ljava/lang/Object;
    //   1549: goto -> 1553
    //   1552: athrow
    //   1553: checkcast java/util/Map$Entry
    //   1556: getstatic Perryc.1 : I
    //   1559: ifeq -> 1573
    //   1562: ldc2_w 2096464990
    //   1565: l2i
    //   1566: ldc_w 2112440446
    //   1569: ixor
    //   1570: goto -> 1581
    //   1573: ldc2_w -1092755407
    //   1576: l2i
    //   1577: ldc_w 1039194306
    //   1580: ixor
    //   1581: ldc2_w -1395660775
    //   1584: l2i
    //   1585: ldc_w 182254088
    //   1588: ixor
    //   1589: ixor
    //   1590: lookupswitch default -> 1616, -1492132303 -> 2136, 1367341624 -> 1573
    //   1616: astore #5
    //   1618: getstatic Perryc.1 : I
    //   1621: ifeq -> 1635
    //   1624: ldc2_w 196008960
    //   1627: l2i
    //   1628: ldc_w -2141483525
    //   1631: ixor
    //   1632: goto -> 1643
    //   1635: ldc2_w 58485063
    //   1638: l2i
    //   1639: ldc_w -690142815
    //   1642: ixor
    //   1643: ldc2_w 2099171591
    //   1646: l2i
    //   1647: ldc_w 1139786997
    //   1650: ixor
    //   1651: ixor
    //   1652: lookupswitch default -> 1680, -1340041676 -> 1635, -1258011639 -> 2124
    //   1680: aload_3
    //   1681: getstatic Perryc.0 : I
    //   1684: ifle -> 1698
    //   1687: ldc2_w 585987542
    //   1690: l2i
    //   1691: ldc_w 935499526
    //   1694: ixor
    //   1695: goto -> 1706
    //   1698: ldc2_w -1734418708
    //   1701: l2i
    //   1702: ldc_w -1403202195
    //   1705: ixor
    //   1706: ldc2_w 1716541163
    //   1709: l2i
    //   1710: ldc_w -544905795
    //   1713: ixor
    //   1714: ixor
    //   1715: lookupswitch default -> 2132, -1927857961 -> 1740, -1392848506 -> 1698
    //   1740: aload #5
    //   1742: getstatic Perryc.1 : I
    //   1745: ifeq -> 1759
    //   1748: ldc2_w -854165744
    //   1751: l2i
    //   1752: ldc_w -1227691952
    //   1755: ixor
    //   1756: goto -> 1767
    //   1759: ldc2_w 1313727843
    //   1762: l2i
    //   1763: ldc_w -611220656
    //   1766: ixor
    //   1767: ldc2_w 1486278937
    //   1770: l2i
    //   1771: ldc_w -736328898
    //   1774: ixor
    //   1775: ixor
    //   1776: lookupswitch default -> 1804, -2072415012 -> 1759, -145830553 -> 2140
    //   1804: goto -> 1808
    //   1807: athrow
    //   1808: invokeinterface getKey : ()Ljava/lang/Object;
    //   1813: goto -> 1817
    //   1816: athrow
    //   1817: getstatic Perryc.c : I
    //   1820: iflt -> 1834
    //   1823: ldc2_w -1343509686
    //   1826: l2i
    //   1827: ldc_w -1358288557
    //   1830: ixor
    //   1831: goto -> 1842
    //   1834: ldc2_w 1288804684
    //   1837: l2i
    //   1838: ldc_w 1709094411
    //   1841: ixor
    //   1842: ldc2_w 1325088182
    //   1845: l2i
    //   1846: ldc_w 572082222
    //   1849: ixor
    //   1850: ixor
    //   1851: lookupswitch default -> 1876, -1241714830 -> 1834, 1812199297 -> 2138
    //   1876: aload #5
    //   1878: getstatic Perryc.0 : I
    //   1881: ifle -> 1895
    //   1884: ldc2_w 339990261
    //   1887: l2i
    //   1888: ldc_w -1454509066
    //   1891: ixor
    //   1892: goto -> 1903
    //   1895: ldc2_w -555322662
    //   1898: l2i
    //   1899: ldc_w -348487730
    //   1902: ixor
    //   1903: ldc2_w 2044595684
    //   1906: l2i
    //   1907: ldc_w 912506980
    //   1910: ixor
    //   1911: ixor
    //   1912: lookupswitch default -> 1940, -1455966341 -> 1895, -223090557 -> 2114
    //   1940: goto -> 1944
    //   1943: athrow
    //   1944: invokeinterface getValue : ()Ljava/lang/Object;
    //   1949: goto -> 1953
    //   1952: athrow
    //   1953: getstatic Perryc.c : I
    //   1956: iflt -> 1970
    //   1959: ldc2_w -1583086342
    //   1962: l2i
    //   1963: ldc_w -659696033
    //   1966: ixor
    //   1967: goto -> 1978
    //   1970: ldc2_w 349849641
    //   1973: l2i
    //   1974: ldc_w 706464139
    //   1977: ixor
    //   1978: ldc2_w -358068146
    //   1981: l2i
    //   1982: ldc_w 886261202
    //   1985: ixor
    //   1986: ixor
    //   1987: lookupswitch default -> 2012, -1485650119 -> 2096, -1215676535 -> 1970
    //   2012: goto -> 2016
    //   2015: athrow
    //   2016: invokevirtual put : (Ljava/lang/Object;Ljava/lang/Object;)Ljava/lang/Object;
    //   2019: goto -> 2023
    //   2022: athrow
    //   2023: pop
    //   2024: goto -> 1222
    //   2027: getstatic Perryc.0 : I
    //   2030: ifle -> 2044
    //   2033: ldc2_w -911871781
    //   2036: l2i
    //   2037: ldc_w 313678183
    //   2040: ixor
    //   2041: goto -> 2052
    //   2044: ldc2_w 2047779489
    //   2047: l2i
    //   2048: ldc_w -1369879417
    //   2051: ixor
    //   2052: ldc2_w 1724959112
    //   2055: l2i
    //   2056: ldc_w 1281032009
    //   2059: ixor
    //   2060: ixor
    //   2061: lookupswitch default -> 2088, -700506186 -> 2044, -241328259 -> 2146
    //   2088: aload_3
    //   2089: areturn
    //   2090: aconst_null
    //   2091: athrow
    //   2092: aconst_null
    //   2093: athrow
    //   2094: aconst_null
    //   2095: athrow
    //   2096: aconst_null
    //   2097: athrow
    //   2098: aconst_null
    //   2099: athrow
    //   2100: aconst_null
    //   2101: athrow
    //   2102: aconst_null
    //   2103: athrow
    //   2104: aconst_null
    //   2105: athrow
    //   2106: aconst_null
    //   2107: athrow
    //   2108: aconst_null
    //   2109: athrow
    //   2110: aconst_null
    //   2111: athrow
    //   2112: aconst_null
    //   2113: athrow
    //   2114: aconst_null
    //   2115: athrow
    //   2116: aconst_null
    //   2117: athrow
    //   2118: aconst_null
    //   2119: athrow
    //   2120: aconst_null
    //   2121: athrow
    //   2122: aconst_null
    //   2123: athrow
    //   2124: aconst_null
    //   2125: athrow
    //   2126: aconst_null
    //   2127: athrow
    //   2128: aconst_null
    //   2129: athrow
    //   2130: aconst_null
    //   2131: athrow
    //   2132: aconst_null
    //   2133: athrow
    //   2134: aconst_null
    //   2135: athrow
    //   2136: aconst_null
    //   2137: athrow
    //   2138: aconst_null
    //   2139: athrow
    //   2140: aconst_null
    //   2141: athrow
    //   2142: aconst_null
    //   2143: athrow
    //   2144: aconst_null
    //   2145: athrow
    //   2146: aconst_null
    //   2147: athrow
    //   2148: pop
    //   2149: goto -> 24
    //   2152: pop
    //   2153: aconst_null
    //   2154: goto -> 2148
    //   2157: dup
    //   2158: ifnull -> 2148
    //   2161: checkcast java/lang/Throwable
    //   2164: athrow
    //   2165: dup
    //   2166: ifnull -> 2152
    //   2169: checkcast java/lang/Throwable
    //   2172: athrow
    //   2173: aconst_null
    //   2174: athrow
    // Local variable table:
    //   start	length	slot	name	descriptor
    //   1618	406	5	entry	Ljava/util/Map$Entry;
    //   24	2066	0	map	Ljava/util/Map;
    //   24	2066	1	descending	Z
    //   293	1797	2	list	Ljava/util/LinkedList;
    //   1029	1061	3	result	Ljava/util/LinkedHashMap;
    // Local variable type table:
    //   start	length	slot	name	signature
    //   24	2066	0	map	Ljava/util/Map<TK;TV;>;
    //   293	1797	2	list	Ljava/util/LinkedList<Ljava/util/Map$Entry<TK;TV;>;>;
    // Exception table:
    //   from	to	target	type
    //   8	20	2157	finally
    //   151	160	160	finally
    //   151	160	3	finally
    //   151	160	3	java/util/NoSuchElementException
    //   151	160	160	java/lang/IndexOutOfBoundsException
    //   152	160	151	java/util/NoSuchElementException
    //   223	230	230	finally
    //   223	230	3	finally
    //   223	230	3	finally
    //   224	230	223	finally
    //   224	230	3	finally
    //   531	538	538	finally
    //   531	538	3	finally
    //   531	538	3	java/util/ConcurrentModificationException
    //   532	538	531	finally
    //   532	538	531	java/lang/AssertionError
    //   604	610	610	finally
    //   604	610	610	java/lang/ArrayIndexOutOfBoundsException
    //   604	610	3	finally
    //   604	610	610	finally
    //   604	610	3	java/lang/IndexOutOfBoundsException
    //   676	682	682	finally
    //   676	682	3	java/lang/IllegalStateException
    //   676	682	3	java/util/NoSuchElementException
    //   676	682	682	java/lang/IllegalArgumentException
    //   676	682	682	java/lang/RuntimeException
    //   812	818	818	finally
    //   812	818	818	finally
    //   812	818	3	java/lang/AssertionError
    //   812	818	3	finally
    //   812	818	818	finally
    //   883	890	890	finally
    //   883	890	890	java/lang/EnumConstantNotPresentException
    //   883	890	890	java/lang/UnsupportedOperationException
    //   884	890	883	java/util/NoSuchElementException
    //   884	890	3	java/lang/IllegalStateException
    //   959	966	966	finally
    //   959	966	959	java/lang/NumberFormatException
    //   959	966	966	finally
    //   959	966	959	java/lang/IndexOutOfBoundsException
    //   960	966	959	java/lang/ArrayIndexOutOfBoundsException
    //   1152	1158	1158	finally
    //   1152	1158	3	java/lang/RuntimeException
    //   1152	1158	3	java/lang/RuntimeException
    //   1152	1158	3	finally
    //   1152	1158	1158	finally
    //   1351	1360	1360	finally
    //   1351	1360	1351	finally
    //   1351	1360	1351	finally
    //   1351	1360	3	finally
    //   1352	1360	1360	finally
    //   1544	1552	1552	finally
    //   1544	1552	3	java/lang/NullPointerException
    //   1544	1552	3	java/lang/IllegalArgumentException
    //   1544	1552	3	java/lang/ArrayIndexOutOfBoundsException
    //   1544	1552	3	finally
    //   1807	1816	1816	finally
    //   1807	1816	1816	java/lang/NegativeArraySizeException
    //   1808	1816	1807	java/lang/NumberFormatException
    //   1808	1816	1807	java/lang/EnumConstantNotPresentException
    //   1808	1816	3	finally
    //   1943	1952	1952	finally
    //   1944	1952	1943	finally
    //   1944	1952	1943	java/lang/ArrayIndexOutOfBoundsException
    //   1944	1952	3	finally
    //   1944	1952	1943	java/lang/ArithmeticException
    //   2015	2022	2022	finally
    //   2015	2022	2022	java/lang/UnsupportedOperationException
    //   2015	2022	3	finally
    //   2015	2022	2022	finally
    //   2016	2022	2015	java/lang/IndexOutOfBoundsException
    //   2157	2165	2157	finally
    //   2173	2175	3	finally
  }
  
  public static Vec3d calculateLine(Vec3d x1, Vec3d x2, double distance) {
    if (Perryc.c < 0) {
      null;
    } else {
      if (null != null)
        throw (Throwable)null; 
      null;
    } 
    if (null != null)
      throw (Throwable)null; 
    null;
  }
  
  public static String getTimeOfDay() {
    return Perry1.e(null, (int)803384740L ^ 0x2C55801B);
  }
  
  public static Vec3d direction(float yaw) {
    if (Perryc.1 <= 0) {
      null;
    } else {
      if (null != null)
        throw (Throwable)null; 
      null;
    } 
    if (null != null)
      throw (Throwable)null; 
    null;
  }
  
  public static int getRandom(int min, int max) {
    if (Perryc.c < 0) {
      null;
    } else {
      if (null != null)
        throw (Throwable)null; 
      null;
    } 
    if (null != null)
      throw (Throwable)null; 
    null;
  }
  
  public static boolean areVec3dsAligned(Vec3d paramVec3d1, Vec3d paramVec3d2) {
    return Perry1.0H(null, (int)2134800039L ^ 0x1D151B9, paramVec3d1, paramVec3d2);
  }
  
  public static double round(double value, int places) {
    // Byte code:
    //   0: goto -> 8
    //   3: dup
    //   4: ifnull -> 905
    //   7: athrow
    //   8: aconst_null
    //   9: getstatic Perryc.1 : I
    //   12: ifgt -> 897
    //   15: pop
    //   16: aconst_null
    //   17: goto -> 889
    //   20: nop
    //   21: nop
    //   22: nop
    //   23: athrow
    //   24: getstatic Perryc.c : I
    //   27: iflt -> 41
    //   30: ldc2_w -483918320
    //   33: l2i
    //   34: ldc_w 1685535203
    //   37: ixor
    //   38: goto -> 49
    //   41: ldc2_w 598437939
    //   44: l2i
    //   45: ldc_w -1650165457
    //   48: ixor
    //   49: ldc2_w -2047435525
    //   52: l2i
    //   53: ldc_w -1562428167
    //   56: ixor
    //   57: ixor
    //   58: lookupswitch default -> 862, -1725519586 -> 84, -1602656271 -> 41
    //   84: iload_2
    //   85: ifge -> 99
    //   88: ldc2_w 1132267462
    //   91: l2i
    //   92: ldc_w -1160950755
    //   95: ixor
    //   96: goto -> 107
    //   99: ldc2_w -2045484325
    //   102: l2i
    //   103: ldc_w 2141464835
    //   106: ixor
    //   107: ldc2_w 944745369
    //   110: l2i
    //   111: ldc_w -164864525
    //   114: ixor
    //   115: ixor
    //   116: tableswitch default -> 88, 936623537 -> 140, 936623538 -> 216
    //   140: new java/lang/IllegalArgumentException
    //   143: dup
    //   144: getstatic Perryc.1 : I
    //   147: ifeq -> 161
    //   150: ldc2_w -753447714
    //   153: l2i
    //   154: ldc_w 2061029728
    //   157: ixor
    //   158: goto -> 169
    //   161: ldc2_w -1786806164
    //   164: l2i
    //   165: ldc_w 876852363
    //   168: ixor
    //   169: ldc2_w -1010528872
    //   172: l2i
    //   173: ldc_w 1557410802
    //   176: ixor
    //   177: ixor
    //   178: lookupswitch default -> 866, 920593364 -> 161, 1043106445 -> 204
    //   204: goto -> 208
    //   207: athrow
    //   208: invokespecial <init> : ()V
    //   211: goto -> 215
    //   214: athrow
    //   215: athrow
    //   216: getstatic Perryc.0 : I
    //   219: ifle -> 233
    //   222: ldc2_w -1071840129
    //   225: l2i
    //   226: ldc_w -577422584
    //   229: ixor
    //   230: goto -> 241
    //   233: ldc2_w 154598478
    //   236: l2i
    //   237: ldc_w 29408016
    //   240: ixor
    //   241: ldc2_w 281605959
    //   244: l2i
    //   245: ldc_w 435118086
    //   248: ixor
    //   249: ixor
    //   250: lookupswitch default -> 276, 347056182 -> 874, 1610088687 -> 233
    //   276: dload_0
    //   277: getstatic Perryc.1 : I
    //   280: ifeq -> 294
    //   283: ldc2_w -484180138
    //   286: l2i
    //   287: ldc_w -518411514
    //   290: ixor
    //   291: goto -> 302
    //   294: ldc2_w 1872556311
    //   297: l2i
    //   298: ldc_w 586314822
    //   301: ixor
    //   302: ldc2_w 1897365487
    //   305: l2i
    //   306: ldc_w -1901988201
    //   309: ixor
    //   310: ixor
    //   311: lookupswitch default -> 336, -41099992 -> 870, 1634592376 -> 294
    //   336: goto -> 340
    //   339: athrow
    //   340: invokestatic valueOf : (D)Ljava/math/BigDecimal;
    //   343: goto -> 347
    //   346: athrow
    //   347: getstatic Perryc.c : I
    //   350: iflt -> 364
    //   353: ldc2_w 390014242
    //   356: l2i
    //   357: ldc_w -1301775701
    //   360: ixor
    //   361: goto -> 372
    //   364: ldc2_w 1814840713
    //   367: l2i
    //   368: ldc_w 261213815
    //   371: ixor
    //   372: ldc2_w -1371294230
    //   375: l2i
    //   376: ldc_w -766248243
    //   379: ixor
    //   380: ixor
    //   381: lookupswitch default -> 864, -649654098 -> 364, 531481817 -> 408
    //   408: astore_3
    //   409: getstatic Perryc.1 : I
    //   412: ifeq -> 426
    //   415: ldc2_w 1681508627
    //   418: l2i
    //   419: ldc_w 1738526755
    //   422: ixor
    //   423: goto -> 434
    //   426: ldc2_w 1483745193
    //   429: l2i
    //   430: ldc_w -1729557893
    //   433: ixor
    //   434: ldc2_w -1420357337
    //   437: l2i
    //   438: ldc_w -733890084
    //   441: ixor
    //   442: ixor
    //   443: lookupswitch default -> 876, -1081113303 -> 468, 2091954635 -> 426
    //   468: aload_3
    //   469: getstatic Perryc.0 : I
    //   472: ifle -> 486
    //   475: ldc2_w -146823610
    //   478: l2i
    //   479: ldc_w 631306424
    //   482: ixor
    //   483: goto -> 494
    //   486: ldc2_w 1265389411
    //   489: l2i
    //   490: ldc_w -711062432
    //   493: ixor
    //   494: ldc2_w 506314024
    //   497: l2i
    //   498: ldc_w 989089598
    //   501: ixor
    //   502: ixor
    //   503: lookupswitch default -> 528, -2024374949 -> 486, -163140376 -> 856
    //   528: iload_2
    //   529: getstatic Perryc.0 : I
    //   532: ifle -> 546
    //   535: ldc2_w -811174581
    //   538: l2i
    //   539: ldc_w -1343664541
    //   542: ixor
    //   543: goto -> 554
    //   546: ldc2_w -1224751924
    //   549: l2i
    //   550: ldc_w -456214233
    //   553: ixor
    //   554: ldc2_w -373000052
    //   557: l2i
    //   558: ldc_w -640890428
    //   561: ixor
    //   562: ixor
    //   563: lookupswitch default -> 588, 1346865760 -> 858, 2143140618 -> 546
    //   588: getstatic java/math/RoundingMode.FLOOR : Ljava/math/RoundingMode;
    //   591: getstatic Perryc.c : I
    //   594: iflt -> 608
    //   597: ldc2_w 2090268771
    //   600: l2i
    //   601: ldc_w -436922857
    //   604: ixor
    //   605: goto -> 616
    //   608: ldc2_w -2094404996
    //   611: l2i
    //   612: ldc_w 1529862040
    //   615: ixor
    //   616: ldc2_w 1706641375
    //   619: l2i
    //   620: ldc_w 486665195
    //   623: ixor
    //   624: ixor
    //   625: lookupswitch default -> 652, -505724352 -> 868, 2087062831 -> 608
    //   652: goto -> 656
    //   655: athrow
    //   656: invokevirtual setScale : (ILjava/math/RoundingMode;)Ljava/math/BigDecimal;
    //   659: goto -> 663
    //   662: athrow
    //   663: getstatic Perryc.0 : I
    //   666: ifle -> 680
    //   669: ldc2_w 1998878402
    //   672: l2i
    //   673: ldc_w -2131738186
    //   676: ixor
    //   677: goto -> 688
    //   680: ldc2_w -1647768815
    //   683: l2i
    //   684: ldc_w -1001321765
    //   687: ixor
    //   688: ldc2_w -1324467680
    //   691: l2i
    //   692: ldc_w 2041055731
    //   695: ixor
    //   696: ixor
    //   697: lookupswitch default -> 878, -1858194919 -> 724, 1064436903 -> 680
    //   724: astore_3
    //   725: getstatic Perryc.c : I
    //   728: iflt -> 742
    //   731: ldc2_w 1180184300
    //   734: l2i
    //   735: ldc_w 685602640
    //   738: ixor
    //   739: goto -> 750
    //   742: ldc2_w 1390820634
    //   745: l2i
    //   746: ldc_w -1001182699
    //   749: ixor
    //   750: ldc2_w 2144824116
    //   753: l2i
    //   754: ldc_w 772147706
    //   757: ixor
    //   758: ixor
    //   759: lookupswitch default -> 872, -949717567 -> 784, 1062484850 -> 742
    //   784: aload_3
    //   785: getstatic Perryc.c : I
    //   788: iflt -> 802
    //   791: ldc2_w 1228665891
    //   794: l2i
    //   795: ldc_w -1123943944
    //   798: ixor
    //   799: goto -> 810
    //   802: ldc2_w -439478649
    //   805: l2i
    //   806: ldc_w 286452247
    //   809: ixor
    //   810: ldc2_w 2126861394
    //   813: l2i
    //   814: ldc_w -1353351730
    //   817: ixor
    //   818: ixor
    //   819: lookupswitch default -> 860, 625792268 -> 844, 631907399 -> 802
    //   844: goto -> 848
    //   847: athrow
    //   848: invokevirtual doubleValue : ()D
    //   851: goto -> 855
    //   854: athrow
    //   855: dreturn
    //   856: aconst_null
    //   857: athrow
    //   858: aconst_null
    //   859: athrow
    //   860: aconst_null
    //   861: athrow
    //   862: aconst_null
    //   863: athrow
    //   864: aconst_null
    //   865: athrow
    //   866: aconst_null
    //   867: athrow
    //   868: aconst_null
    //   869: athrow
    //   870: aconst_null
    //   871: athrow
    //   872: aconst_null
    //   873: athrow
    //   874: aconst_null
    //   875: athrow
    //   876: aconst_null
    //   877: athrow
    //   878: aconst_null
    //   879: athrow
    //   880: pop
    //   881: goto -> 24
    //   884: pop
    //   885: aconst_null
    //   886: goto -> 880
    //   889: dup
    //   890: ifnull -> 880
    //   893: checkcast java/lang/Throwable
    //   896: athrow
    //   897: dup
    //   898: ifnull -> 884
    //   901: checkcast java/lang/Throwable
    //   904: athrow
    //   905: aconst_null
    //   906: athrow
    // Local variable table:
    //   start	length	slot	name	descriptor
    //   24	832	0	value	D
    //   24	832	2	places	I
    //   409	447	3	bd	Ljava/math/BigDecimal;
    // Exception table:
    //   from	to	target	type
    //   8	20	889	finally
    //   207	214	214	finally
    //   207	214	214	java/lang/EnumConstantNotPresentException
    //   207	214	207	finally
    //   207	214	207	java/util/NoSuchElementException
    //   208	214	214	finally
    //   340	346	346	finally
    //   340	346	346	java/lang/ClassCastException
    //   340	346	346	finally
    //   340	346	3	finally
    //   340	346	3	java/lang/IllegalArgumentException
    //   655	662	662	finally
    //   655	662	655	java/lang/StringIndexOutOfBoundsException
    //   656	662	662	java/lang/IllegalStateException
    //   656	662	662	finally
    //   656	662	3	java/util/NoSuchElementException
    //   847	854	854	finally
    //   847	854	854	finally
    //   847	854	847	finally
    //   847	854	3	java/lang/IllegalArgumentException
    //   848	854	847	finally
    //   889	897	889	finally
    //   905	907	3	finally
  }
  
  public MathUtil() {
    // Byte code:
    //   0: getstatic Perryc.0 : I
    //   3: ifle -> 17
    //   6: ldc2_w -634194517
    //   9: l2i
    //   10: ldc_w 1515350090
    //   13: ixor
    //   14: goto -> 25
    //   17: ldc2_w -1798293787
    //   20: l2i
    //   21: ldc_w 815818488
    //   24: ixor
    //   25: ldc2_w 883436043
    //   28: l2i
    //   29: ldc_w -1743932666
    //   32: ixor
    //   33: ixor
    //   34: lookupswitch default -> 124, 148228368 -> 60, 751109356 -> 17
    //   60: aload_0
    //   61: getstatic Perryc.0 : I
    //   64: ifle -> 78
    //   67: ldc2_w 2123930675
    //   70: l2i
    //   71: ldc_w -1238699256
    //   74: ixor
    //   75: goto -> 86
    //   78: ldc2_w -682757643
    //   81: l2i
    //   82: ldc_w -1354025661
    //   85: ixor
    //   86: ldc2_w -1506362658
    //   89: l2i
    //   90: ldc_w 674339144
    //   93: ixor
    //   94: ixor
    //   95: lookupswitch default -> 126, -167647456 -> 120, 1186286765 -> 78
    //   120: invokespecial <init> : ()V
    //   123: return
    //   124: aconst_null
    //   125: athrow
    //   126: aconst_null
    //   127: athrow
    // Local variable table:
    //   start	length	slot	name	descriptor
    //   0	124	0	this	Lbigname/zprestige/webhack/util/MathUtil;
  }
  
  public static float cos(float paramFloat) {
    return Perry1.0K(null, (int)2115844518L ^ 0x64BF4F71, paramFloat);
  }
  
  public static double multiply(double paramDouble) {
    return Perry1.1s(null, (int)1513012196L ^ 0x41D89DDC, paramDouble);
  }
  
  public static double clamp(double num, double min, double max) {
    if (Perryc.0 <= 0) {
      null;
    } else {
      if (null != null)
        throw (Throwable)null; 
      null;
    } 
    if (null != null)
      throw (Throwable)null; 
    null;
  }
  
  public static int clamp(int paramInt1, int paramInt2, int paramInt3) {
    return Perry1.3a(null, (int)-2020625478L ^ 0xA64AB608, paramInt1, paramInt2, paramInt3);
  }
  
  public static float wrapDegrees(float paramFloat) {
    return Perry1.0J(null, (int)-2092919361L ^ 0xA69385A8, paramFloat);
  }
  
  public static float sin(float paramFloat) {
    return Perry1.0L(null, (int)832149730L ^ 0x3C2B69D6, paramFloat);
  }
  
  public static float getRandom(float min, float max) {
    // Byte code:
    //   0: goto -> 8
    //   3: dup
    //   4: ifnull -> 515
    //   7: athrow
    //   8: aconst_null
    //   9: getstatic Perryc.c : I
    //   12: ifge -> 507
    //   15: pop
    //   16: aconst_null
    //   17: goto -> 499
    //   20: nop
    //   21: nop
    //   22: nop
    //   23: athrow
    //   24: getstatic Perryc.0 : I
    //   27: ifle -> 41
    //   30: ldc2_w -2088076302
    //   33: l2i
    //   34: ldc_w 699896466
    //   37: ixor
    //   38: goto -> 49
    //   41: ldc2_w -111213301
    //   44: l2i
    //   45: ldc_w 1490724513
    //   48: ixor
    //   49: ldc2_w -1841205669
    //   52: l2i
    //   53: ldc_w -1677630490
    //   56: ixor
    //   57: ixor
    //   58: lookupswitch default -> 84, -1535253283 -> 476, -1503797236 -> 41
    //   84: fload_0
    //   85: getstatic Perryc.0 : I
    //   88: ifle -> 102
    //   91: ldc2_w -1181910527
    //   94: l2i
    //   95: ldc_w -908599124
    //   98: ixor
    //   99: goto -> 110
    //   102: ldc2_w 1586348554
    //   105: l2i
    //   106: ldc_w -742522828
    //   109: ixor
    //   110: ldc2_w -906193789
    //   113: l2i
    //   114: ldc_w -1821219532
    //   117: ixor
    //   118: ixor
    //   119: lookupswitch default -> 144, 710303040 -> 102, 718564122 -> 482
    //   144: getstatic bigname/zprestige/webhack/util/MathUtil.random : Ljava/util/Random;
    //   147: getstatic Perryc.1 : I
    //   150: ifeq -> 164
    //   153: ldc2_w -814538489
    //   156: l2i
    //   157: ldc_w -136487705
    //   160: ixor
    //   161: goto -> 172
    //   164: ldc2_w 1912583055
    //   167: l2i
    //   168: ldc_w -1143015621
    //   171: ixor
    //   172: ldc2_w -181898243
    //   175: l2i
    //   176: ldc_w 353461387
    //   179: ixor
    //   180: ixor
    //   181: lookupswitch default -> 480, -661165418 -> 164, 706237378 -> 208
    //   208: goto -> 212
    //   211: athrow
    //   212: invokevirtual nextFloat : ()F
    //   215: goto -> 219
    //   218: athrow
    //   219: getstatic Perryc.c : I
    //   222: iflt -> 236
    //   225: ldc2_w -102264952
    //   228: l2i
    //   229: ldc_w -790873669
    //   232: ixor
    //   233: goto -> 244
    //   236: ldc2_w -122333119
    //   239: l2i
    //   240: ldc_w 513615725
    //   243: ixor
    //   244: ldc2_w -537165658
    //   247: l2i
    //   248: ldc_w -113104451
    //   251: ixor
    //   252: ixor
    //   253: lookupswitch default -> 488, -1064184265 -> 280, 260185896 -> 236
    //   280: fload_1
    //   281: fmul
    //   282: fadd
    //   283: getstatic Perryc.1 : I
    //   286: ifeq -> 300
    //   289: ldc2_w 187725792
    //   292: l2i
    //   293: ldc_w 170804093
    //   296: ixor
    //   297: goto -> 308
    //   300: ldc2_w 1488215492
    //   303: l2i
    //   304: ldc_w 1740233392
    //   307: ixor
    //   308: ldc2_w 99783315
    //   311: l2i
    //   312: ldc_w 448334916
    //   315: ixor
    //   316: ixor
    //   317: lookupswitch default -> 484, 508930634 -> 300, 541464995 -> 344
    //   344: fload_0
    //   345: getstatic Perryc.1 : I
    //   348: ifeq -> 362
    //   351: ldc2_w -1265095352
    //   354: l2i
    //   355: ldc_w 754926301
    //   358: ixor
    //   359: goto -> 370
    //   362: ldc2_w -361007138
    //   365: l2i
    //   366: ldc_w -1804469222
    //   369: ixor
    //   370: ldc2_w -1384603501
    //   373: l2i
    //   374: ldc_w 335745417
    //   377: ixor
    //   378: ixor
    //   379: lookupswitch default -> 478, -948880674 -> 404, 555540111 -> 362
    //   404: fload_1
    //   405: getstatic Perryc.1 : I
    //   408: ifeq -> 422
    //   411: ldc2_w -673926078
    //   414: l2i
    //   415: ldc_w -1867750596
    //   418: ixor
    //   419: goto -> 430
    //   422: ldc2_w 1802075560
    //   425: l2i
    //   426: ldc_w 384318150
    //   429: ixor
    //   430: ldc2_w 750795162
    //   433: l2i
    //   434: ldc_w 1183622507
    //   437: ixor
    //   438: ixor
    //   439: lookupswitch default -> 486, 399367071 -> 464, 758401935 -> 422
    //   464: goto -> 468
    //   467: athrow
    //   468: invokestatic func_76131_a : (FFF)F
    //   471: goto -> 475
    //   474: athrow
    //   475: freturn
    //   476: aconst_null
    //   477: athrow
    //   478: aconst_null
    //   479: athrow
    //   480: aconst_null
    //   481: athrow
    //   482: aconst_null
    //   483: athrow
    //   484: aconst_null
    //   485: athrow
    //   486: aconst_null
    //   487: athrow
    //   488: aconst_null
    //   489: athrow
    //   490: pop
    //   491: goto -> 24
    //   494: pop
    //   495: aconst_null
    //   496: goto -> 490
    //   499: dup
    //   500: ifnull -> 490
    //   503: checkcast java/lang/Throwable
    //   506: athrow
    //   507: dup
    //   508: ifnull -> 494
    //   511: checkcast java/lang/Throwable
    //   514: athrow
    //   515: aconst_null
    //   516: athrow
    // Local variable table:
    //   start	length	slot	name	descriptor
    //   24	452	0	min	F
    //   24	452	1	max	F
    // Exception table:
    //   from	to	target	type
    //   8	20	499	finally
    //   211	218	218	finally
    //   211	218	3	finally
    //   212	218	3	java/lang/StringIndexOutOfBoundsException
    //   212	218	218	java/lang/IllegalStateException
    //   212	218	211	finally
    //   467	474	474	finally
    //   467	474	3	java/lang/AssertionError
    //   467	474	3	finally
    //   467	474	3	java/lang/AssertionError
    //   468	474	467	finally
    //   499	507	499	finally
    //   515	517	3	finally
  }
  
  public static double getIncremental(double paramDouble1, double paramDouble2) {
    return Perry1.52(null, (int)-663430655L ^ 0xE4838E7A, paramDouble1, paramDouble2);
  }
  
  public static boolean areVec3dsAlignedRetarded(Vec3d vec3d1, Vec3d vec3d2) {
    if (Perryc.0 <= 0) {
      null;
    } else {
      if (null != null)
        throw (Throwable)null; 
      null;
    } 
    if (null != null)
      throw (Throwable)null; 
    null;
  }
  
  public static double degToRad(double paramDouble) {
    return Perry1.1q(null, (int)-1562140373L ^ 0xD07F4C2E, paramDouble);
  }
  
  static {
    // Byte code:
    //   0: new java/util/Random
    //   3: dup
    //   4: getstatic Perryc.1 : I
    //   7: ifeq -> 21
    //   10: ldc2_w -913132173
    //   13: l2i
    //   14: ldc_w -50526678
    //   17: ixor
    //   18: goto -> 29
    //   21: ldc2_w -716405477
    //   24: l2i
    //   25: ldc_w -841246101
    //   28: ixor
    //   29: ldc2_w -687681400
    //   32: l2i
    //   33: ldc_w -578272215
    //   36: ixor
    //   37: ixor
    //   38: lookupswitch default -> 134, 303926225 -> 64, 1071982584 -> 21
    //   64: invokespecial <init> : ()V
    //   67: getstatic Perryc.1 : I
    //   70: ifeq -> 84
    //   73: ldc2_w 1469102099
    //   76: l2i
    //   77: ldc_w -1394678194
    //   80: ixor
    //   81: goto -> 92
    //   84: ldc2_w -2077301635
    //   87: l2i
    //   88: ldc_w -1680577025
    //   91: ixor
    //   92: ldc2_w -1339881445
    //   95: l2i
    //   96: ldc_w 1540690761
    //   99: ixor
    //   100: ixor
    //   101: lookupswitch default -> 128, 280511759 -> 132, 527263860 -> 84
    //   128: putstatic bigname/zprestige/webhack/util/MathUtil.random : Ljava/util/Random;
    //   131: return
    //   132: aconst_null
    //   133: athrow
    //   134: aconst_null
    //   135: athrow
  }
  
  public static Vec3d roundVec(Vec3d vec3d, int places) {
    // Byte code:
    //   0: goto -> 8
    //   3: dup
    //   4: ifnull -> 919
    //   7: athrow
    //   8: aconst_null
    //   9: getstatic Perryc.0 : I
    //   12: ifgt -> 911
    //   15: pop
    //   16: aconst_null
    //   17: goto -> 903
    //   20: nop
    //   21: nop
    //   22: nop
    //   23: athrow
    //   24: new net/minecraft/util/math/Vec3d
    //   27: dup
    //   28: getstatic Perryc.c : I
    //   31: iflt -> 45
    //   34: ldc2_w 1765195653
    //   37: l2i
    //   38: ldc_w 1132343957
    //   41: ixor
    //   42: goto -> 53
    //   45: ldc2_w -1354670288
    //   48: l2i
    //   49: ldc_w 940673932
    //   52: ixor
    //   53: ldc2_w -2112836466
    //   56: l2i
    //   57: ldc_w -1476102471
    //   60: ixor
    //   61: ixor
    //   62: lookupswitch default -> 886, -1119613301 -> 88, 6051623 -> 45
    //   88: aload_0
    //   89: getstatic Perryc.0 : I
    //   92: ifle -> 106
    //   95: ldc2_w -530688185
    //   98: l2i
    //   99: ldc_w -5732298
    //   102: ixor
    //   103: goto -> 114
    //   106: ldc2_w 2073086367
    //   109: l2i
    //   110: ldc_w 22712287
    //   113: ixor
    //   114: ldc2_w -951853056
    //   117: l2i
    //   118: ldc_w -814569717
    //   121: ixor
    //   122: ixor
    //   123: lookupswitch default -> 148, -104604061 -> 106, 398956666 -> 878
    //   148: getfield field_72450_a : D
    //   151: getstatic Perryc.0 : I
    //   154: ifle -> 168
    //   157: ldc2_w 122920909
    //   160: l2i
    //   161: ldc_w 1422703796
    //   164: ixor
    //   165: goto -> 176
    //   168: ldc2_w 1785316057
    //   171: l2i
    //   172: ldc_w -990123158
    //   175: ixor
    //   176: ldc2_w -1847178289
    //   179: l2i
    //   180: ldc_w -1126223495
    //   183: ixor
    //   184: ixor
    //   185: lookupswitch default -> 212, 1709635488 -> 168, 2124831183 -> 880
    //   212: iload_1
    //   213: getstatic Perryc.1 : I
    //   216: ifeq -> 230
    //   219: ldc2_w 1884936992
    //   222: l2i
    //   223: ldc_w 2132234470
    //   226: ixor
    //   227: goto -> 238
    //   230: ldc2_w 1969594302
    //   233: l2i
    //   234: ldc_w -230281692
    //   237: ixor
    //   238: ldc2_w -1836985214
    //   241: l2i
    //   242: ldc_w 1470339067
    //   245: ixor
    //   246: ixor
    //   247: lookupswitch default -> 876, -898840385 -> 230, 1107423971 -> 272
    //   272: goto -> 276
    //   275: athrow
    //   276: invokestatic round : (DI)D
    //   279: goto -> 283
    //   282: athrow
    //   283: getstatic Perryc.1 : I
    //   286: ifeq -> 300
    //   289: ldc2_w -484161812
    //   292: l2i
    //   293: ldc_w 1973671516
    //   296: ixor
    //   297: goto -> 308
    //   300: ldc2_w 519994144
    //   303: l2i
    //   304: ldc_w -1022620171
    //   307: ixor
    //   308: ldc2_w 779963397
    //   311: l2i
    //   312: ldc_w -514668816
    //   315: ixor
    //   316: ixor
    //   317: lookupswitch default -> 868, 316537888 -> 344, 1504188997 -> 300
    //   344: aload_0
    //   345: getstatic Perryc.c : I
    //   348: iflt -> 362
    //   351: ldc2_w -877590912
    //   354: l2i
    //   355: ldc_w -1948754130
    //   358: ixor
    //   359: goto -> 370
    //   362: ldc2_w 563177624
    //   365: l2i
    //   366: ldc_w 103493207
    //   369: ixor
    //   370: ldc2_w 1107917171
    //   373: l2i
    //   374: ldc_w 302357189
    //   377: ixor
    //   378: ixor
    //   379: lookupswitch default -> 874, 275102232 -> 362, 2008458617 -> 404
    //   404: getfield field_72448_b : D
    //   407: getstatic Perryc.0 : I
    //   410: ifle -> 424
    //   413: ldc2_w 2126731228
    //   416: l2i
    //   417: ldc_w 1265475681
    //   420: ixor
    //   421: goto -> 432
    //   424: ldc2_w -937461256
    //   427: l2i
    //   428: ldc_w 483016446
    //   431: ixor
    //   432: ldc2_w 23907457
    //   435: l2i
    //   436: ldc_w -1110579819
    //   439: ixor
    //   440: ixor
    //   441: lookupswitch default -> 468, -1995448663 -> 890, 1524962540 -> 424
    //   468: iload_1
    //   469: getstatic Perryc.1 : I
    //   472: ifeq -> 486
    //   475: ldc2_w 2088317031
    //   478: l2i
    //   479: ldc_w 638483683
    //   482: ixor
    //   483: goto -> 494
    //   486: ldc2_w 455341463
    //   489: l2i
    //   490: ldc_w -79115933
    //   493: ixor
    //   494: ldc2_w -1745790541
    //   497: l2i
    //   498: ldc_w -82550250
    //   501: ixor
    //   502: ixor
    //   503: lookupswitch default -> 872, -1936849071 -> 528, 915568417 -> 486
    //   528: goto -> 532
    //   531: athrow
    //   532: invokestatic round : (DI)D
    //   535: goto -> 539
    //   538: athrow
    //   539: getstatic Perryc.1 : I
    //   542: ifeq -> 556
    //   545: ldc2_w 258011136
    //   548: l2i
    //   549: ldc_w 602770151
    //   552: ixor
    //   553: goto -> 564
    //   556: ldc2_w -904302058
    //   559: l2i
    //   560: ldc_w -2123509281
    //   563: ixor
    //   564: ldc2_w 885914584
    //   567: l2i
    //   568: ldc_w 128543203
    //   571: ixor
    //   572: ixor
    //   573: lookupswitch default -> 888, 535423196 -> 556, 2014327282 -> 600
    //   600: aload_0
    //   601: getstatic Perryc.1 : I
    //   604: ifeq -> 618
    //   607: ldc2_w -592488865
    //   610: l2i
    //   611: ldc_w -1776898255
    //   614: ixor
    //   615: goto -> 626
    //   618: ldc2_w -1688445105
    //   621: l2i
    //   622: ldc_w 1406917239
    //   625: ixor
    //   626: ldc2_w -959312753
    //   629: l2i
    //   630: ldc_w -553588557
    //   633: ixor
    //   634: ixor
    //   635: lookupswitch default -> 660, 145994475 -> 618, 1399528786 -> 892
    //   660: getfield field_72449_c : D
    //   663: getstatic Perryc.0 : I
    //   666: ifle -> 680
    //   669: ldc2_w -491810368
    //   672: l2i
    //   673: ldc_w 1881050689
    //   676: ixor
    //   677: goto -> 688
    //   680: ldc2_w 229063211
    //   683: l2i
    //   684: ldc_w -1476031019
    //   687: ixor
    //   688: ldc2_w -413666129
    //   691: l2i
    //   692: ldc_w 1977135103
    //   695: ixor
    //   696: ixor
    //   697: lookupswitch default -> 724, -1836932280 -> 680, 4080849 -> 870
    //   724: iload_1
    //   725: getstatic Perryc.0 : I
    //   728: ifle -> 742
    //   731: ldc2_w 2085008326
    //   734: l2i
    //   735: ldc_w -1625550975
    //   738: ixor
    //   739: goto -> 750
    //   742: ldc2_w -772297616
    //   745: l2i
    //   746: ldc_w -2061321162
    //   749: ixor
    //   750: ldc2_w 1316446526
    //   753: l2i
    //   754: ldc_w 1160475956
    //   757: ixor
    //   758: ixor
    //   759: lookupswitch default -> 784, -402216883 -> 884, 568869417 -> 742
    //   784: goto -> 788
    //   787: athrow
    //   788: invokestatic round : (DI)D
    //   791: goto -> 795
    //   794: athrow
    //   795: getstatic Perryc.0 : I
    //   798: ifle -> 812
    //   801: ldc2_w 2060817630
    //   804: l2i
    //   805: ldc_w -1478160182
    //   808: ixor
    //   809: goto -> 820
    //   812: ldc2_w 1208970000
    //   815: l2i
    //   816: ldc_w 1315162759
    //   819: ixor
    //   820: ldc2_w 264919184
    //   823: l2i
    //   824: ldc_w -1696485773
    //   827: ixor
    //   828: ixor
    //   829: lookupswitch default -> 882, -1824041100 -> 856, 1209758455 -> 812
    //   856: goto -> 860
    //   859: athrow
    //   860: invokespecial <init> : (DDD)V
    //   863: goto -> 867
    //   866: athrow
    //   867: areturn
    //   868: aconst_null
    //   869: athrow
    //   870: aconst_null
    //   871: athrow
    //   872: aconst_null
    //   873: athrow
    //   874: aconst_null
    //   875: athrow
    //   876: aconst_null
    //   877: athrow
    //   878: aconst_null
    //   879: athrow
    //   880: aconst_null
    //   881: athrow
    //   882: aconst_null
    //   883: athrow
    //   884: aconst_null
    //   885: athrow
    //   886: aconst_null
    //   887: athrow
    //   888: aconst_null
    //   889: athrow
    //   890: aconst_null
    //   891: athrow
    //   892: aconst_null
    //   893: athrow
    //   894: pop
    //   895: goto -> 24
    //   898: pop
    //   899: aconst_null
    //   900: goto -> 894
    //   903: dup
    //   904: ifnull -> 894
    //   907: checkcast java/lang/Throwable
    //   910: athrow
    //   911: dup
    //   912: ifnull -> 898
    //   915: checkcast java/lang/Throwable
    //   918: athrow
    //   919: aconst_null
    //   920: athrow
    // Local variable table:
    //   start	length	slot	name	descriptor
    //   24	844	0	vec3d	Lnet/minecraft/util/math/Vec3d;
    //   24	844	1	places	I
    // Exception table:
    //   from	to	target	type
    //   8	20	903	finally
    //   275	282	282	finally
    //   275	282	3	finally
    //   275	282	282	finally
    //   276	282	275	finally
    //   276	282	282	java/lang/IndexOutOfBoundsException
    //   531	538	538	finally
    //   531	538	531	java/lang/ClassCastException
    //   532	538	538	java/lang/ClassCastException
    //   532	538	531	java/lang/AssertionError
    //   532	538	531	finally
    //   788	794	794	finally
    //   788	794	794	finally
    //   788	794	794	java/lang/RuntimeException
    //   788	794	794	finally
    //   788	794	3	finally
    //   859	866	866	finally
    //   859	866	866	finally
    //   859	866	3	finally
    //   860	866	859	finally
    //   860	866	3	java/lang/NullPointerException
    //   903	911	903	finally
    //   919	921	3	java/lang/EnumConstantNotPresentException
  }
  
  public static float clamp(float num, float min, float max) {
    // Byte code:
    //   0: goto -> 8
    //   3: dup
    //   4: ifnull -> 493
    //   7: athrow
    //   8: aconst_null
    //   9: getstatic Perryc.1 : I
    //   12: ifgt -> 485
    //   15: pop
    //   16: aconst_null
    //   17: goto -> 477
    //   20: nop
    //   21: nop
    //   22: nop
    //   23: athrow
    //   24: getstatic Perryc.1 : I
    //   27: ifeq -> 41
    //   30: ldc2_w -906754471
    //   33: l2i
    //   34: ldc_w -1334901173
    //   37: ixor
    //   38: goto -> 49
    //   41: ldc2_w 619673791
    //   44: l2i
    //   45: ldc_w 2056868609
    //   48: ixor
    //   49: ldc2_w 1978435738
    //   52: l2i
    //   53: ldc_w -1270888970
    //   56: ixor
    //   57: ixor
    //   58: lookupswitch default -> 458, -1616550190 -> 84, -1203221122 -> 41
    //   84: fload_0
    //   85: getstatic Perryc.0 : I
    //   88: ifle -> 102
    //   91: ldc2_w 433642227
    //   94: l2i
    //   95: ldc_w 252255527
    //   98: ixor
    //   99: goto -> 110
    //   102: ldc2_w -1133130636
    //   105: l2i
    //   106: ldc_w -1720574564
    //   109: ixor
    //   110: ldc2_w 206999937
    //   113: l2i
    //   114: ldc_w -622003852
    //   117: ixor
    //   118: ixor
    //   119: lookupswitch default -> 144, -1066684639 -> 460, 476134097 -> 102
    //   144: fload_1
    //   145: fcmpg
    //   146: ifge -> 160
    //   149: ldc2_w -1467133225
    //   152: l2i
    //   153: ldc_w 1510024597
    //   156: ixor
    //   157: goto -> 168
    //   160: ldc2_w -97234042
    //   163: l2i
    //   164: ldc_w 146285767
    //   167: ixor
    //   168: ldc2_w -1164835014
    //   171: l2i
    //   172: ldc_w 1973876597
    //   175: ixor
    //   176: ixor
    //   177: tableswitch default -> 149, 1035503373 -> 200, 1035503374 -> 264
    //   200: getstatic Perryc.0 : I
    //   203: ifle -> 217
    //   206: ldc2_w 382685235
    //   209: l2i
    //   210: ldc_w -304000073
    //   213: ixor
    //   214: goto -> 225
    //   217: ldc2_w -1307432424
    //   220: l2i
    //   221: ldc_w -1588979925
    //   224: ixor
    //   225: ldc2_w 1058206343
    //   228: l2i
    //   229: ldc_w -1115442390
    //   232: ixor
    //   233: ixor
    //   234: lookupswitch default -> 260, -1002785733 -> 217, 2042577449 -> 462
    //   260: fload_1
    //   261: goto -> 455
    //   264: getstatic Perryc.1 : I
    //   267: ifeq -> 281
    //   270: ldc2_w -1452685322
    //   273: l2i
    //   274: ldc_w 1749704296
    //   277: ixor
    //   278: goto -> 289
    //   281: ldc2_w 1566272753
    //   284: l2i
    //   285: ldc_w -1460450045
    //   288: ixor
    //   289: ldc2_w 1612241249
    //   292: l2i
    //   293: ldc_w -1044489370
    //   296: ixor
    //   297: ixor
    //   298: lookupswitch default -> 324, -1314337976 -> 281, 1619336089 -> 464
    //   324: fload_0
    //   325: getstatic Perryc.1 : I
    //   328: ifeq -> 342
    //   331: ldc2_w 573686478
    //   334: l2i
    //   335: ldc_w 1846349229
    //   338: ixor
    //   339: goto -> 350
    //   342: ldc2_w -1602697128
    //   345: l2i
    //   346: ldc_w -1486753244
    //   349: ixor
    //   350: ldc2_w -560209532
    //   353: l2i
    //   354: ldc_w -1821013765
    //   357: ixor
    //   358: ixor
    //   359: lookupswitch default -> 466, 30582300 -> 342, 1257722627 -> 384
    //   384: fload_2
    //   385: getstatic Perryc.0 : I
    //   388: ifle -> 402
    //   391: ldc2_w -907497028
    //   394: l2i
    //   395: ldc_w -1224652570
    //   398: ixor
    //   399: goto -> 410
    //   402: ldc2_w 35563156
    //   405: l2i
    //   406: ldc_w -1019790240
    //   409: ixor
    //   410: ldc2_w 1525633645
    //   413: l2i
    //   414: ldc_w 886830499
    //   417: ixor
    //   418: ixor
    //   419: lookupswitch default -> 456, -1357038278 -> 444, 282943124 -> 402
    //   444: goto -> 448
    //   447: athrow
    //   448: invokestatic min : (FF)F
    //   451: goto -> 455
    //   454: athrow
    //   455: freturn
    //   456: aconst_null
    //   457: athrow
    //   458: aconst_null
    //   459: athrow
    //   460: aconst_null
    //   461: athrow
    //   462: aconst_null
    //   463: athrow
    //   464: aconst_null
    //   465: athrow
    //   466: aconst_null
    //   467: athrow
    //   468: pop
    //   469: goto -> 24
    //   472: pop
    //   473: aconst_null
    //   474: goto -> 468
    //   477: dup
    //   478: ifnull -> 468
    //   481: checkcast java/lang/Throwable
    //   484: athrow
    //   485: dup
    //   486: ifnull -> 472
    //   489: checkcast java/lang/Throwable
    //   492: athrow
    //   493: aconst_null
    //   494: athrow
    // Local variable table:
    //   start	length	slot	name	descriptor
    //   24	432	0	num	F
    //   24	432	1	min	F
    //   24	432	2	max	F
    // Exception table:
    //   from	to	target	type
    //   8	20	477	java/lang/ArithmeticException
    //   448	454	454	finally
    //   448	454	454	java/lang/UnsupportedOperationException
    //   448	454	454	java/lang/RuntimeException
    //   448	454	454	finally
    //   448	454	3	finally
    //   477	485	477	finally
    //   493	495	3	java/lang/IllegalStateException
  }
  
  public static double wrapDegrees(double paramDouble) {
    return Perry1.1r(null, (int)791448382L ^ 0x73719D81, paramDouble);
  }
  
  public static float round(float value, int places) {
    if (Perryc.c < 0) {
      null;
    } else {
      if (null != null)
        throw (Throwable)null; 
      null;
    } 
    if (null != null)
      throw (Throwable)null; 
    null;
  }
  
  public static double getRandom(double paramDouble1, double paramDouble2) {
    return Perry1.52(null, (int)-2096881426L ^ 0xBFF37494, paramDouble1, paramDouble2);
  }
  
  public static double radToDeg(double paramDouble) {
    return Perry1.1s(null, (int)17934935L ^ 0x1AE78C6C, paramDouble);
  }
  
  public static double square(double input) {
    if (Perryc.1 <= 0) {
      null;
    } else {
      if (null != null)
        throw (Throwable)null; 
      null;
    } 
    if (null != null)
      throw (Throwable)null; 
    null;
  }
  
  public static double[] directionSpeed(double paramDouble) {
    return Perry1.0F(null, (int)404969421L ^ 0x5B92DD80, paramDouble);
  }
  
  public static float[] calcAngle(Vec3d from, Vec3d to) {
    if (Perryc.0 <= 0) {
      null;
    } else {
      if (null != null)
        throw (Throwable)null; 
      null;
    } 
    if (null != null)
      throw (Throwable)null; 
    null;
  }
  
  public static Vec3d extrapolatePlayerPosition(EntityPlayer player, int ticks) {
    // Byte code:
    //   0: goto -> 8
    //   3: dup
    //   4: ifnull -> 2635
    //   7: athrow
    //   8: aconst_null
    //   9: getstatic Perryc.1 : I
    //   12: ifgt -> 2627
    //   15: pop
    //   16: aconst_null
    //   17: goto -> 2619
    //   20: nop
    //   21: nop
    //   22: nop
    //   23: athrow
    //   24: new net/minecraft/util/math/Vec3d
    //   27: dup
    //   28: getstatic Perryc.0 : I
    //   31: ifle -> 45
    //   34: ldc2_w -843147108
    //   37: l2i
    //   38: ldc_w -1309243686
    //   41: ixor
    //   42: goto -> 53
    //   45: ldc2_w -1361889638
    //   48: l2i
    //   49: ldc_w 1269232810
    //   52: ixor
    //   53: ldc2_w -36359609
    //   56: l2i
    //   57: ldc_w 2021862033
    //   60: ixor
    //   61: ixor
    //   62: lookupswitch default -> 88, -932424850 -> 45, -115472752 -> 2552
    //   88: aload_0
    //   89: getstatic Perryc.c : I
    //   92: iflt -> 106
    //   95: ldc2_w 1683539599
    //   98: l2i
    //   99: ldc_w -1968646925
    //   102: ixor
    //   103: goto -> 114
    //   106: ldc2_w -1559246509
    //   109: l2i
    //   110: ldc_w 642027547
    //   113: ixor
    //   114: ldc2_w -73708724
    //   117: l2i
    //   118: ldc_w -332891821
    //   121: ixor
    //   122: ixor
    //   123: lookupswitch default -> 2592, -1829213353 -> 148, -113041309 -> 106
    //   148: getfield field_70142_S : D
    //   151: getstatic Perryc.0 : I
    //   154: ifle -> 168
    //   157: ldc2_w 1328024560
    //   160: l2i
    //   161: ldc_w 2085286136
    //   164: ixor
    //   165: goto -> 176
    //   168: ldc2_w 38453578
    //   171: l2i
    //   172: ldc_w -2043074369
    //   175: ixor
    //   176: ldc2_w -1844863240
    //   179: l2i
    //   180: ldc_w 237872333
    //   183: ixor
    //   184: ixor
    //   185: lookupswitch default -> 2554, -1354317507 -> 168, 408409024 -> 212
    //   212: aload_0
    //   213: getstatic Perryc.0 : I
    //   216: ifle -> 230
    //   219: ldc2_w 1868752626
    //   222: l2i
    //   223: ldc_w 508705332
    //   226: ixor
    //   227: goto -> 238
    //   230: ldc2_w 1711325293
    //   233: l2i
    //   234: ldc_w -981973835
    //   237: ixor
    //   238: ldc2_w 301815692
    //   241: l2i
    //   242: ldc_w 2093929482
    //   245: ixor
    //   246: ixor
    //   247: lookupswitch default -> 2588, -833943714 -> 272, 469983040 -> 230
    //   272: getfield field_70137_T : D
    //   275: getstatic Perryc.c : I
    //   278: iflt -> 292
    //   281: ldc2_w 1608698580
    //   284: l2i
    //   285: ldc_w -1384881386
    //   288: ixor
    //   289: goto -> 300
    //   292: ldc2_w -1887346910
    //   295: l2i
    //   296: ldc_w 35206713
    //   299: ixor
    //   300: ldc2_w 1157229792
    //   303: l2i
    //   304: ldc_w -1423190862
    //   307: ixor
    //   308: ixor
    //   309: lookupswitch default -> 336, 491032976 -> 2600, 1836004380 -> 292
    //   336: aload_0
    //   337: getstatic Perryc.c : I
    //   340: iflt -> 354
    //   343: ldc2_w 1965989650
    //   346: l2i
    //   347: ldc_w 1880196439
    //   350: ixor
    //   351: goto -> 362
    //   354: ldc2_w -739330782
    //   357: l2i
    //   358: ldc_w -365946446
    //   361: ixor
    //   362: ldc2_w 2072485099
    //   365: l2i
    //   366: ldc_w 781932080
    //   369: ixor
    //   370: ixor
    //   371: lookupswitch default -> 2604, 1344524446 -> 354, 1824679499 -> 396
    //   396: getfield field_70136_U : D
    //   399: getstatic Perryc.0 : I
    //   402: ifle -> 416
    //   405: ldc2_w 980445958
    //   408: l2i
    //   409: ldc_w -1052217704
    //   412: ixor
    //   413: goto -> 424
    //   416: ldc2_w 454792744
    //   419: l2i
    //   420: ldc_w 804928078
    //   423: ixor
    //   424: ldc2_w 416840517
    //   427: l2i
    //   428: ldc_w 1494973430
    //   431: ixor
    //   432: ixor
    //   433: lookupswitch default -> 2560, -1157954259 -> 416, 1965206741 -> 460
    //   460: goto -> 464
    //   463: athrow
    //   464: invokespecial <init> : (DDD)V
    //   467: goto -> 471
    //   470: athrow
    //   471: getstatic Perryc.0 : I
    //   474: ifle -> 488
    //   477: ldc2_w 102725772
    //   480: l2i
    //   481: ldc_w 527284845
    //   484: ixor
    //   485: goto -> 496
    //   488: ldc2_w 257865803
    //   491: l2i
    //   492: ldc_w 296786187
    //   495: ixor
    //   496: ldc2_w -436817851
    //   499: l2i
    //   500: ldc_w -524719037
    //   503: ixor
    //   504: ixor
    //   505: lookupswitch default -> 2580, 463600966 -> 532, 473767655 -> 488
    //   532: astore_2
    //   533: new net/minecraft/util/math/Vec3d
    //   536: dup
    //   537: getstatic Perryc.1 : I
    //   540: ifeq -> 554
    //   543: ldc2_w -1212742694
    //   546: l2i
    //   547: ldc_w -594293091
    //   550: ixor
    //   551: goto -> 562
    //   554: ldc2_w -1608824391
    //   557: l2i
    //   558: ldc_w -1709471946
    //   561: ixor
    //   562: ldc2_w -384011791
    //   565: l2i
    //   566: ldc_w -764936741
    //   569: ixor
    //   570: ixor
    //   571: lookupswitch default -> 596, -1271362058 -> 554, 1348419949 -> 2568
    //   596: aload_0
    //   597: getstatic Perryc.c : I
    //   600: iflt -> 614
    //   603: ldc2_w 31331852
    //   606: l2i
    //   607: ldc_w -881350224
    //   610: ixor
    //   611: goto -> 622
    //   614: ldc2_w 635239536
    //   617: l2i
    //   618: ldc_w 447682845
    //   621: ixor
    //   622: ldc2_w -348199157
    //   625: l2i
    //   626: ldc_w 1350379909
    //   629: ixor
    //   630: ixor
    //   631: lookupswitch default -> 2578, -2077217821 -> 656, 1911189810 -> 614
    //   656: getfield field_70165_t : D
    //   659: getstatic Perryc.c : I
    //   662: iflt -> 676
    //   665: ldc2_w -2040064028
    //   668: l2i
    //   669: ldc_w 1707055361
    //   672: ixor
    //   673: goto -> 684
    //   676: ldc2_w -1153713777
    //   679: l2i
    //   680: ldc_w 707534036
    //   683: ixor
    //   684: ldc2_w 2100737735
    //   687: l2i
    //   688: ldc_w 1476200679
    //   691: ixor
    //   692: ixor
    //   693: lookupswitch default -> 720, -921489211 -> 2574, 1365181841 -> 676
    //   720: aload_0
    //   721: getstatic Perryc.c : I
    //   724: iflt -> 738
    //   727: ldc2_w -1009191443
    //   730: l2i
    //   731: ldc_w 297299915
    //   734: ixor
    //   735: goto -> 746
    //   738: ldc2_w 1934962507
    //   741: l2i
    //   742: ldc_w -1762378349
    //   745: ixor
    //   746: ldc2_w 628674746
    //   749: l2i
    //   750: ldc_w -475815529
    //   753: ixor
    //   754: ixor
    //   755: lookupswitch default -> 2582, 347859723 -> 738, 595223541 -> 780
    //   780: getfield field_70163_u : D
    //   783: getstatic Perryc.0 : I
    //   786: ifle -> 800
    //   789: ldc2_w -545192593
    //   792: l2i
    //   793: ldc_w 1335062503
    //   796: ixor
    //   797: goto -> 808
    //   800: ldc2_w 1776563201
    //   803: l2i
    //   804: ldc_w -2110299393
    //   807: ixor
    //   808: ldc2_w 1415389120
    //   811: l2i
    //   812: ldc_w 903952973
    //   815: ixor
    //   816: ixor
    //   817: lookupswitch default -> 844, -240234747 -> 2546, 1738083091 -> 800
    //   844: aload_0
    //   845: getstatic Perryc.0 : I
    //   848: ifle -> 862
    //   851: ldc2_w -2064233292
    //   854: l2i
    //   855: ldc_w -19838695
    //   858: ixor
    //   859: goto -> 870
    //   862: ldc2_w -1532805972
    //   865: l2i
    //   866: ldc_w 1815179183
    //   869: ixor
    //   870: ldc2_w -1739942544
    //   873: l2i
    //   874: ldc_w 1430720427
    //   877: ixor
    //   878: ixor
    //   879: lookupswitch default -> 2594, -1221943434 -> 862, 94357976 -> 904
    //   904: getfield field_70161_v : D
    //   907: getstatic Perryc.c : I
    //   910: iflt -> 924
    //   913: ldc2_w 1815404013
    //   916: l2i
    //   917: ldc_w 1143929901
    //   920: ixor
    //   921: goto -> 932
    //   924: ldc2_w 95548343
    //   927: l2i
    //   928: ldc_w 512929972
    //   931: ixor
    //   932: ldc2_w 1210130281
    //   935: l2i
    //   936: ldc_w -951046042
    //   939: ixor
    //   940: ixor
    //   941: lookupswitch default -> 2596, -1806537716 -> 968, -1486156081 -> 924
    //   968: goto -> 972
    //   971: athrow
    //   972: invokespecial <init> : (DDD)V
    //   975: goto -> 979
    //   978: athrow
    //   979: getstatic Perryc.c : I
    //   982: iflt -> 996
    //   985: ldc2_w -493896520
    //   988: l2i
    //   989: ldc_w 1132406414
    //   992: ixor
    //   993: goto -> 1004
    //   996: ldc2_w -1510274978
    //   999: l2i
    //   1000: ldc_w 391289896
    //   1003: ixor
    //   1004: ldc2_w 1744149955
    //   1007: l2i
    //   1008: ldc_w -1236254342
    //   1011: ixor
    //   1012: ixor
    //   1013: lookupswitch default -> 2566, 1661749455 -> 1040, 1884636815 -> 996
    //   1040: astore_3
    //   1041: getstatic Perryc.0 : I
    //   1044: ifle -> 1058
    //   1047: ldc2_w 994381852
    //   1050: l2i
    //   1051: ldc_w 2001111934
    //   1054: ixor
    //   1055: goto -> 1066
    //   1058: ldc2_w 378837232
    //   1061: l2i
    //   1062: ldc_w -774406913
    //   1065: ixor
    //   1066: ldc2_w -1110270808
    //   1069: l2i
    //   1070: ldc_w -1240083314
    //   1073: ixor
    //   1074: ixor
    //   1075: lookupswitch default -> 1100, 1204081476 -> 2542, 1844936176 -> 1058
    //   1100: aload_0
    //   1101: getstatic Perryc.c : I
    //   1104: iflt -> 1118
    //   1107: ldc2_w -751196417
    //   1110: l2i
    //   1111: ldc_w -173219373
    //   1114: ixor
    //   1115: goto -> 1126
    //   1118: ldc2_w 1564664178
    //   1121: l2i
    //   1122: ldc_w -109505088
    //   1125: ixor
    //   1126: ldc2_w 1800974095
    //   1129: l2i
    //   1130: ldc_w 187876412
    //   1133: ixor
    //   1134: ixor
    //   1135: lookupswitch default -> 2576, -1001283711 -> 1160, 1191128095 -> 1118
    //   1160: getfield field_70159_w : D
    //   1163: getstatic Perryc.c : I
    //   1166: iflt -> 1180
    //   1169: ldc2_w 595685378
    //   1172: l2i
    //   1173: ldc_w -1913648000
    //   1176: ixor
    //   1177: goto -> 1188
    //   1180: ldc2_w -1158108504
    //   1183: l2i
    //   1184: ldc_w 954495788
    //   1187: ixor
    //   1188: ldc2_w -2021671624
    //   1191: l2i
    //   1192: ldc_w 1364574150
    //   1195: ixor
    //   1196: ixor
    //   1197: lookupswitch default -> 1224, 766815642 -> 1180, 2019262076 -> 2606
    //   1224: goto -> 1228
    //   1227: athrow
    //   1228: invokestatic multiply : (D)D
    //   1231: goto -> 1235
    //   1234: athrow
    //   1235: getstatic Perryc.c : I
    //   1238: iflt -> 1252
    //   1241: ldc2_w 190343
    //   1244: l2i
    //   1245: ldc_w 704170782
    //   1248: ixor
    //   1249: goto -> 1260
    //   1252: ldc2_w 1717867022
    //   1255: l2i
    //   1256: ldc_w 1344312910
    //   1259: ixor
    //   1260: ldc2_w -432513075
    //   1263: l2i
    //   1264: ldc_w 2056027389
    //   1267: ixor
    //   1268: ixor
    //   1269: lookupswitch default -> 1296, -1253175383 -> 2558, -546937275 -> 1252
    //   1296: aload_0
    //   1297: getstatic Perryc.1 : I
    //   1300: ifeq -> 1314
    //   1303: ldc2_w 1921375234
    //   1306: l2i
    //   1307: ldc_w 2061768875
    //   1310: ixor
    //   1311: goto -> 1322
    //   1314: ldc2_w 1070212676
    //   1317: l2i
    //   1318: ldc_w 1566724241
    //   1321: ixor
    //   1322: ldc2_w 891895252
    //   1325: l2i
    //   1326: ldc_w 1501300529
    //   1329: ixor
    //   1330: ixor
    //   1331: lookupswitch default -> 1356, 571794577 -> 1314, 1681194572 -> 2572
    //   1356: getfield field_70181_x : D
    //   1359: getstatic Perryc.1 : I
    //   1362: ifeq -> 1376
    //   1365: ldc2_w -1602272909
    //   1368: l2i
    //   1369: ldc_w 672355642
    //   1372: ixor
    //   1373: goto -> 1384
    //   1376: ldc2_w 510957188
    //   1379: l2i
    //   1380: ldc_w 307447877
    //   1383: ixor
    //   1384: ldc2_w 1721587144
    //   1387: l2i
    //   1388: ldc_w 1136805785
    //   1391: ixor
    //   1392: ixor
    //   1393: lookupswitch default -> 2536, -1389165032 -> 1376, 695782544 -> 1420
    //   1420: goto -> 1424
    //   1423: athrow
    //   1424: invokestatic multiply : (D)D
    //   1427: goto -> 1431
    //   1430: athrow
    //   1431: dadd
    //   1432: getstatic Perryc.0 : I
    //   1435: ifle -> 1449
    //   1438: ldc2_w 2081936488
    //   1441: l2i
    //   1442: ldc_w -829115515
    //   1445: ixor
    //   1446: goto -> 1457
    //   1449: ldc2_w 726796935
    //   1452: l2i
    //   1453: ldc_w -1987649462
    //   1456: ixor
    //   1457: ldc2_w -1397535464
    //   1460: l2i
    //   1461: ldc_w -612524986
    //   1464: ixor
    //   1465: ixor
    //   1466: lookupswitch default -> 1492, -1679732762 -> 1449, -984762701 -> 2550
    //   1492: aload_0
    //   1493: getstatic Perryc.c : I
    //   1496: iflt -> 1510
    //   1499: ldc2_w 1569613740
    //   1502: l2i
    //   1503: ldc_w 800771455
    //   1506: ixor
    //   1507: goto -> 1518
    //   1510: ldc2_w 1704669621
    //   1513: l2i
    //   1514: ldc_w -1179878812
    //   1517: ixor
    //   1518: ldc2_w -1396519056
    //   1521: l2i
    //   1522: ldc_w 1617808702
    //   1525: ixor
    //   1526: ixor
    //   1527: lookupswitch default -> 1552, -1667730080 -> 1510, -1097095011 -> 2564
    //   1552: getfield field_70179_y : D
    //   1555: getstatic Perryc.0 : I
    //   1558: ifle -> 1572
    //   1561: ldc2_w -1807297663
    //   1564: l2i
    //   1565: ldc_w 465440007
    //   1568: ixor
    //   1569: goto -> 1580
    //   1572: ldc2_w -2084232664
    //   1575: l2i
    //   1576: ldc_w -1823036126
    //   1579: ixor
    //   1580: ldc2_w 363319408
    //   1583: l2i
    //   1584: ldc_w -2088423149
    //   1587: ixor
    //   1588: ixor
    //   1589: lookupswitch default -> 1616, 175097313 -> 1572, 433733605 -> 2556
    //   1616: goto -> 1620
    //   1619: athrow
    //   1620: invokestatic multiply : (D)D
    //   1623: goto -> 1627
    //   1626: athrow
    //   1627: dadd
    //   1628: getstatic Perryc.0 : I
    //   1631: ifle -> 1645
    //   1634: ldc2_w 1644154494
    //   1637: l2i
    //   1638: ldc_w 2054435929
    //   1641: ixor
    //   1642: goto -> 1653
    //   1645: ldc2_w 1320506108
    //   1648: l2i
    //   1649: ldc_w -348769242
    //   1652: ixor
    //   1653: ldc2_w -1872845409
    //   1656: l2i
    //   1657: ldc_w -1879258671
    //   1660: ixor
    //   1661: ixor
    //   1662: lookupswitch default -> 2562, -1172239724 -> 1688, 69834345 -> 1645
    //   1688: dstore #4
    //   1690: getstatic Perryc.1 : I
    //   1693: ifeq -> 1707
    //   1696: ldc2_w 1666252895
    //   1699: l2i
    //   1700: ldc_w 821629232
    //   1703: ixor
    //   1704: goto -> 1715
    //   1707: ldc2_w -1218362566
    //   1710: l2i
    //   1711: ldc_w -378173446
    //   1714: ixor
    //   1715: ldc2_w 1925623910
    //   1718: l2i
    //   1719: ldc_w 403383541
    //   1722: ixor
    //   1723: ixor
    //   1724: lookupswitch default -> 2608, 886657107 -> 1752, 962954748 -> 1707
    //   1752: aload_2
    //   1753: getstatic Perryc.1 : I
    //   1756: ifeq -> 1770
    //   1759: ldc2_w -417693899
    //   1762: l2i
    //   1763: ldc_w -854405858
    //   1766: ixor
    //   1767: goto -> 1778
    //   1770: ldc2_w -1754465258
    //   1773: l2i
    //   1774: ldc_w 1153212842
    //   1777: ixor
    //   1778: ldc2_w -623335846
    //   1781: l2i
    //   1782: ldc_w -1047400171
    //   1785: ixor
    //   1786: ixor
    //   1787: lookupswitch default -> 2540, -929494285 -> 1812, 826402148 -> 1770
    //   1812: aload_3
    //   1813: getstatic Perryc.0 : I
    //   1816: ifle -> 1830
    //   1819: ldc2_w -973428736
    //   1822: l2i
    //   1823: ldc_w 1372880304
    //   1826: ixor
    //   1827: goto -> 1838
    //   1830: ldc2_w -23709706
    //   1833: l2i
    //   1834: ldc_w -1019339847
    //   1837: ixor
    //   1838: ldc2_w -1108967066
    //   1841: l2i
    //   1842: ldc_w -2121834517
    //   1845: ixor
    //   1846: ixor
    //   1847: lookupswitch default -> 2602, -1471214787 -> 1830, 30012098 -> 1872
    //   1872: dload #4
    //   1874: getstatic Perryc.c : I
    //   1877: iflt -> 1891
    //   1880: ldc2_w 1918718028
    //   1883: l2i
    //   1884: ldc_w -258884302
    //   1887: ixor
    //   1888: goto -> 1899
    //   1891: ldc2_w 1008110718
    //   1894: l2i
    //   1895: ldc_w -506290744
    //   1898: ixor
    //   1899: ldc2_w 1029529137
    //   1902: l2i
    //   1903: ldc_w 1512027465
    //   1906: ixor
    //   1907: ixor
    //   1908: lookupswitch default -> 1936, -443677178 -> 2586, 1685296651 -> 1891
    //   1936: iload_1
    //   1937: i2d
    //   1938: dmul
    //   1939: getstatic Perryc.1 : I
    //   1942: ifeq -> 1956
    //   1945: ldc2_w 1379329098
    //   1948: l2i
    //   1949: ldc_w -1104332837
    //   1952: ixor
    //   1953: goto -> 1964
    //   1956: ldc2_w -1589030323
    //   1959: l2i
    //   1960: ldc_w -1733719770
    //   1963: ixor
    //   1964: ldc2_w -311846207
    //   1967: l2i
    //   1968: ldc_w 1355777428
    //   1971: ixor
    //   1972: ixor
    //   1973: lookupswitch default -> 2544, -2075737026 -> 2000, 1371393220 -> 1956
    //   2000: goto -> 2004
    //   2003: athrow
    //   2004: invokestatic calculateLine : (Lnet/minecraft/util/math/Vec3d;Lnet/minecraft/util/math/Vec3d;D)Lnet/minecraft/util/math/Vec3d;
    //   2007: goto -> 2011
    //   2010: athrow
    //   2011: getstatic Perryc.1 : I
    //   2014: ifeq -> 2028
    //   2017: ldc2_w -876333712
    //   2020: l2i
    //   2021: ldc_w -1738778747
    //   2024: ixor
    //   2025: goto -> 2036
    //   2028: ldc2_w 1168337518
    //   2031: l2i
    //   2032: ldc_w -1061400409
    //   2035: ixor
    //   2036: ldc2_w 1626756095
    //   2039: l2i
    //   2040: ldc_w 28943258
    //   2043: ixor
    //   2044: ixor
    //   2045: lookupswitch default -> 2072, -1385500914 -> 2028, 852988560 -> 2532
    //   2072: astore #6
    //   2074: new net/minecraft/util/math/Vec3d
    //   2077: dup
    //   2078: getstatic Perryc.0 : I
    //   2081: ifle -> 2095
    //   2084: ldc2_w -964212682
    //   2087: l2i
    //   2088: ldc_w 2129073247
    //   2091: ixor
    //   2092: goto -> 2103
    //   2095: ldc2_w 490018207
    //   2098: l2i
    //   2099: ldc_w -1410229275
    //   2102: ixor
    //   2103: ldc2_w -1630802259
    //   2106: l2i
    //   2107: ldc_w 1901816747
    //   2110: ixor
    //   2111: ixor
    //   2112: lookupswitch default -> 2548, 1475402095 -> 2095, 1498680188 -> 2140
    //   2140: aload #6
    //   2142: getstatic Perryc.c : I
    //   2145: iflt -> 2159
    //   2148: ldc2_w -645811526
    //   2151: l2i
    //   2152: ldc_w 1362705256
    //   2155: ixor
    //   2156: goto -> 2167
    //   2159: ldc2_w 89481423
    //   2162: l2i
    //   2163: ldc_w -1030932225
    //   2166: ixor
    //   2167: ldc2_w -440174043
    //   2170: l2i
    //   2171: ldc_w 962436764
    //   2174: ixor
    //   2175: ixor
    //   2176: lookupswitch default -> 2590, 457620617 -> 2204, 1411804523 -> 2159
    //   2204: getfield field_72450_a : D
    //   2207: getstatic Perryc.1 : I
    //   2210: ifeq -> 2224
    //   2213: ldc2_w -388342109
    //   2216: l2i
    //   2217: ldc_w -651239487
    //   2220: ixor
    //   2221: goto -> 2232
    //   2224: ldc2_w 1333491601
    //   2227: l2i
    //   2228: ldc_w -1658515692
    //   2231: ixor
    //   2232: ldc2_w 361496508
    //   2235: l2i
    //   2236: ldc_w -577162725
    //   2239: ixor
    //   2240: ixor
    //   2241: lookupswitch default -> 2534, -102347579 -> 2224, 441234722 -> 2268
    //   2268: aload_0
    //   2269: getstatic Perryc.c : I
    //   2272: iflt -> 2286
    //   2275: ldc2_w -1864793557
    //   2278: l2i
    //   2279: ldc_w 1524299273
    //   2282: ixor
    //   2283: goto -> 2294
    //   2286: ldc2_w -1296802985
    //   2289: l2i
    //   2290: ldc_w -250783740
    //   2293: ixor
    //   2294: ldc2_w -1904339208
    //   2297: l2i
    //   2298: ldc_w -1051248675
    //   2301: ixor
    //   2302: ixor
    //   2303: lookupswitch default -> 2584, -2060823289 -> 2286, 210772598 -> 2328
    //   2328: getfield field_70163_u : D
    //   2331: getstatic Perryc.0 : I
    //   2334: ifle -> 2348
    //   2337: ldc2_w -748387642
    //   2340: l2i
    //   2341: ldc_w 2020450745
    //   2344: ixor
    //   2345: goto -> 2356
    //   2348: ldc2_w 1965433262
    //   2351: l2i
    //   2352: ldc_w 826546931
    //   2355: ixor
    //   2356: ldc2_w 1833795391
    //   2359: l2i
    //   2360: ldc_w -41192796
    //   2363: ixor
    //   2364: ixor
    //   2365: lookupswitch default -> 2538, -727435578 -> 2392, 1003433700 -> 2348
    //   2392: aload #6
    //   2394: getstatic Perryc.c : I
    //   2397: iflt -> 2411
    //   2400: ldc2_w -52062826
    //   2403: l2i
    //   2404: ldc_w 1621790417
    //   2407: ixor
    //   2408: goto -> 2419
    //   2411: ldc2_w -521150646
    //   2414: l2i
    //   2415: ldc_w -833878111
    //   2418: ixor
    //   2419: ldc2_w -1298289165
    //   2422: l2i
    //   2423: ldc_w -877331425
    //   2426: ixor
    //   2427: ixor
    //   2428: lookupswitch default -> 2456, -652113250 -> 2411, -446281045 -> 2598
    //   2456: getfield field_72449_c : D
    //   2459: getstatic Perryc.c : I
    //   2462: iflt -> 2476
    //   2465: ldc2_w 1021050911
    //   2468: l2i
    //   2469: ldc_w -1552399225
    //   2472: ixor
    //   2473: goto -> 2484
    //   2476: ldc2_w -888816794
    //   2479: l2i
    //   2480: ldc_w -1251685811
    //   2483: ixor
    //   2484: ldc2_w 846763978
    //   2487: l2i
    //   2488: ldc_w 1495946874
    //   2491: ixor
    //   2492: ixor
    //   2493: lookupswitch default -> 2570, -185170648 -> 2476, 355709083 -> 2520
    //   2520: goto -> 2524
    //   2523: athrow
    //   2524: invokespecial <init> : (DDD)V
    //   2527: goto -> 2531
    //   2530: athrow
    //   2531: areturn
    //   2532: aconst_null
    //   2533: athrow
    //   2534: aconst_null
    //   2535: athrow
    //   2536: aconst_null
    //   2537: athrow
    //   2538: aconst_null
    //   2539: athrow
    //   2540: aconst_null
    //   2541: athrow
    //   2542: aconst_null
    //   2543: athrow
    //   2544: aconst_null
    //   2545: athrow
    //   2546: aconst_null
    //   2547: athrow
    //   2548: aconst_null
    //   2549: athrow
    //   2550: aconst_null
    //   2551: athrow
    //   2552: aconst_null
    //   2553: athrow
    //   2554: aconst_null
    //   2555: athrow
    //   2556: aconst_null
    //   2557: athrow
    //   2558: aconst_null
    //   2559: athrow
    //   2560: aconst_null
    //   2561: athrow
    //   2562: aconst_null
    //   2563: athrow
    //   2564: aconst_null
    //   2565: athrow
    //   2566: aconst_null
    //   2567: athrow
    //   2568: aconst_null
    //   2569: athrow
    //   2570: aconst_null
    //   2571: athrow
    //   2572: aconst_null
    //   2573: athrow
    //   2574: aconst_null
    //   2575: athrow
    //   2576: aconst_null
    //   2577: athrow
    //   2578: aconst_null
    //   2579: athrow
    //   2580: aconst_null
    //   2581: athrow
    //   2582: aconst_null
    //   2583: athrow
    //   2584: aconst_null
    //   2585: athrow
    //   2586: aconst_null
    //   2587: athrow
    //   2588: aconst_null
    //   2589: athrow
    //   2590: aconst_null
    //   2591: athrow
    //   2592: aconst_null
    //   2593: athrow
    //   2594: aconst_null
    //   2595: athrow
    //   2596: aconst_null
    //   2597: athrow
    //   2598: aconst_null
    //   2599: athrow
    //   2600: aconst_null
    //   2601: athrow
    //   2602: aconst_null
    //   2603: athrow
    //   2604: aconst_null
    //   2605: athrow
    //   2606: aconst_null
    //   2607: athrow
    //   2608: aconst_null
    //   2609: athrow
    //   2610: pop
    //   2611: goto -> 24
    //   2614: pop
    //   2615: aconst_null
    //   2616: goto -> 2610
    //   2619: dup
    //   2620: ifnull -> 2610
    //   2623: checkcast java/lang/Throwable
    //   2626: athrow
    //   2627: dup
    //   2628: ifnull -> 2614
    //   2631: checkcast java/lang/Throwable
    //   2634: athrow
    //   2635: aconst_null
    //   2636: athrow
    // Local variable table:
    //   start	length	slot	name	descriptor
    //   24	2508	0	player	Lnet/minecraft/entity/player/EntityPlayer;
    //   24	2508	1	ticks	I
    //   533	1999	2	lastPos	Lnet/minecraft/util/math/Vec3d;
    //   1041	1491	3	currentPos	Lnet/minecraft/util/math/Vec3d;
    //   1690	842	4	distance	D
    //   2074	458	6	tempVec	Lnet/minecraft/util/math/Vec3d;
    // Exception table:
    //   from	to	target	type
    //   8	20	2619	finally
    //   464	470	470	finally
    //   464	470	3	finally
    //   464	470	470	java/lang/UnsupportedOperationException
    //   464	470	470	java/lang/NullPointerException
    //   464	470	470	finally
    //   971	978	978	finally
    //   971	978	978	finally
    //   972	978	971	java/lang/RuntimeException
    //   972	978	978	finally
    //   972	978	3	java/lang/ArithmeticException
    //   1228	1234	1234	finally
    //   1228	1234	1234	java/lang/IllegalStateException
    //   1228	1234	1234	finally
    //   1228	1234	3	finally
    //   1228	1234	1234	finally
    //   1424	1430	1430	finally
    //   1424	1430	3	finally
    //   1424	1430	3	java/lang/IndexOutOfBoundsException
    //   1424	1430	3	java/lang/NumberFormatException
    //   1424	1430	1430	finally
    //   1619	1626	1626	finally
    //   1619	1626	1626	finally
    //   1620	1626	1619	java/lang/IndexOutOfBoundsException
    //   1620	1626	1626	java/lang/IllegalArgumentException
    //   1620	1626	3	java/lang/NegativeArraySizeException
    //   2004	2010	2010	finally
    //   2004	2010	2010	finally
    //   2004	2010	2010	java/lang/UnsupportedOperationException
    //   2004	2010	2010	java/lang/UnsupportedOperationException
    //   2004	2010	3	java/lang/EnumConstantNotPresentException
    //   2523	2530	2530	finally
    //   2524	2530	3	java/lang/AssertionError
    //   2524	2530	2523	finally
    //   2524	2530	3	finally
    //   2524	2530	3	java/lang/UnsupportedOperationException
    //   2619	2627	2619	java/lang/IllegalStateException
    //   2635	2637	3	java/lang/IllegalArgumentException
  }
  
  public static float wrap(float paramFloat) {
    return Perry1.0K(null, (int)92923104L ^ 0x1F2B9236, paramFloat);
  }
}


/* Location:              C:\Users\alex\Desktop\webhack\WebHack-0.8-obf_sussy_1.jar!\bigname\zprestige\webhac\\util\MathUtil.class
 * Java compiler version: 8 (52.0)
 * JD-Core Version:       1.1.3
 */