package bigname.zprestige.webhack.util;

import Perry1;

public class MovementUtil extends RuntimeException {
  public synchronized Throwable fillInStackTrace() {
    return Perry1.0g(this, (int)2079984570L ^ 0x7C61B4F);
  }
  
  static {
    throw SYNTHETIC_LOCAL_VARIABLE_0;
  }
  
  public MovementUtil(String msg) {
    // Byte code:
    //   0: getstatic Perryc.c : I
    //   3: iflt -> 16
    //   6: ldc2_w 1577933171
    //   9: l2i
    //   10: ldc -497643683
    //   12: ixor
    //   13: goto -> 23
    //   16: ldc2_w -1827593607
    //   19: l2i
    //   20: ldc -1705028569
    //   22: ixor
    //   23: ldc2_w 757648712
    //   26: l2i
    //   27: ldc -1441204317
    //   29: ixor
    //   30: ixor
    //   31: lookupswitch default -> 312, -1904325451 -> 56, 996928709 -> 16
    //   56: aload_0
    //   57: getstatic Perryc.c : I
    //   60: iflt -> 73
    //   63: ldc2_w 784544622
    //   66: l2i
    //   67: ldc -1581492793
    //   69: ixor
    //   70: goto -> 80
    //   73: ldc2_w -1203482275
    //   76: l2i
    //   77: ldc 1872638832
    //   79: ixor
    //   80: ldc2_w -445805304
    //   83: l2i
    //   84: ldc 1979546314
    //   86: ixor
    //   87: ixor
    //   88: lookupswitch default -> 116, 535794027 -> 316, 1071169605 -> 73
    //   116: aload_1
    //   117: getstatic Perryc.0 : I
    //   120: ifle -> 133
    //   123: ldc2_w 513650590
    //   126: l2i
    //   127: ldc 1902872256
    //   129: ixor
    //   130: goto -> 140
    //   133: ldc2_w -466571092
    //   136: l2i
    //   137: ldc -879178008
    //   139: ixor
    //   140: ldc2_w 1243207583
    //   143: l2i
    //   144: ldc -193231727
    //   146: ixor
    //   147: ixor
    //   148: lookupswitch default -> 314, -1849021110 -> 176, -778798512 -> 133
    //   176: invokespecial <init> : (Ljava/lang/String;)V
    //   179: getstatic Perryc.c : I
    //   182: iflt -> 195
    //   185: ldc2_w -1116001340
    //   188: l2i
    //   189: ldc -1300397132
    //   191: ixor
    //   192: goto -> 202
    //   195: ldc2_w -30471253
    //   198: l2i
    //   199: ldc 921088280
    //   201: ixor
    //   202: ldc2_w -1350897499
    //   205: l2i
    //   206: ldc -18814859
    //   208: ixor
    //   209: ixor
    //   210: lookupswitch default -> 308, -1722572189 -> 236, 1587327136 -> 195
    //   236: aload_0
    //   237: ldc2_w -826473979
    //   240: l2i
    //   241: ldc -826473979
    //   243: ixor
    //   244: anewarray java/lang/StackTraceElement
    //   247: getstatic Perryc.0 : I
    //   250: ifle -> 263
    //   253: ldc2_w -177616719
    //   256: l2i
    //   257: ldc -1912887666
    //   259: ixor
    //   260: goto -> 270
    //   263: ldc2_w 286701160
    //   266: l2i
    //   267: ldc -1999771986
    //   269: ixor
    //   270: ldc2_w -1523901867
    //   273: l2i
    //   274: ldc 872054828
    //   276: ixor
    //   277: ixor
    //   278: lookupswitch default -> 310, -297536442 -> 263, 252365503 -> 304
    //   304: invokevirtual setStackTrace : ([Ljava/lang/StackTraceElement;)V
    //   307: return
    //   308: aconst_null
    //   309: athrow
    //   310: aconst_null
    //   311: athrow
    //   312: aconst_null
    //   313: athrow
    //   314: aconst_null
    //   315: athrow
    //   316: aconst_null
    //   317: athrow
    // Local variable table:
    //   start	length	slot	name	descriptor
    //   0	308	0	this	Lbigname/zprestige/webhack/util/MovementUtil;
    //   0	308	1	msg	Ljava/lang/String;
  }
}


/* Location:              C:\Users\alex\Desktop\webhack\WebHack-0.8-obf_sussy_1.jar!\bigname\zprestige\webhac\\util\MovementUtil.class
 * Java compiler version: 8 (52.0)
 * JD-Core Version:       1.1.3
 */