package bigname.zprestige.webhack.util;

import Perryc;
import net.minecraft.entity.Entity;
import net.minecraft.entity.player.EntityPlayer;
import net.minecraft.util.math.BlockPos;
import net.minecraft.util.math.RayTraceResult;

public class RaytraceUtil implements Util {
  public static RayTraceResult raytrace(EntityPlayer player, Entity entity) {
    if (Perryc.c < 0) {
      null;
    } else {
      if (null != null)
        throw (Throwable)null; 
      null;
    } 
    if (null != null)
      throw (Throwable)null; 
    null;
  }
  
  static {
    throw SYNTHETIC_LOCAL_VARIABLE_0;
  }
  
  public static RayTraceResult raytrace(EntityPlayer player, BlockPos block) {
    // Byte code:
    //   0: goto -> 8
    //   3: dup
    //   4: ifnull -> 973
    //   7: athrow
    //   8: aconst_null
    //   9: getstatic Perryc.0 : I
    //   12: ifgt -> 965
    //   15: pop
    //   16: aconst_null
    //   17: goto -> 957
    //   20: nop
    //   21: nop
    //   22: nop
    //   23: athrow
    //   24: new net/minecraft/util/math/Vec3d
    //   27: dup
    //   28: getstatic Perryc.0 : I
    //   31: ifle -> 44
    //   34: ldc2_w -1794141093
    //   37: l2i
    //   38: ldc -901997765
    //   40: ixor
    //   41: goto -> 51
    //   44: ldc2_w 1871541753
    //   47: l2i
    //   48: ldc 619942875
    //   50: ixor
    //   51: ldc2_w 264821331
    //   54: l2i
    //   55: ldc 175915374
    //   57: ixor
    //   58: ixor
    //   59: lookupswitch default -> 940, 1321893151 -> 84, 1518834781 -> 44
    //   84: aload_1
    //   85: getstatic Perryc.1 : I
    //   88: ifeq -> 101
    //   91: ldc2_w -938268435
    //   94: l2i
    //   95: ldc 1659112255
    //   97: ixor
    //   98: goto -> 108
    //   101: ldc2_w 1940778602
    //   104: l2i
    //   105: ldc 641681856
    //   107: ixor
    //   108: ldc2_w 1601307586
    //   111: l2i
    //   112: ldc 262062165
    //   114: ixor
    //   115: ixor
    //   116: lookupswitch default -> 144, -98836411 -> 944, 157014284 -> 101
    //   144: goto -> 148
    //   147: athrow
    //   148: invokevirtual func_177958_n : ()I
    //   151: goto -> 155
    //   154: athrow
    //   155: i2d
    //   156: getstatic Perryc.1 : I
    //   159: ifeq -> 172
    //   162: ldc2_w -659667365
    //   165: l2i
    //   166: ldc -1072956749
    //   168: ixor
    //   169: goto -> 179
    //   172: ldc2_w -1243573359
    //   175: l2i
    //   176: ldc -1358012262
    //   178: ixor
    //   179: ldc2_w 1962231374
    //   182: l2i
    //   183: ldc -141678449
    //   185: ixor
    //   186: ixor
    //   187: lookupswitch default -> 932, -1718247990 -> 212, -1679896023 -> 172
    //   212: aload_1
    //   213: getstatic Perryc.1 : I
    //   216: ifeq -> 229
    //   219: ldc2_w -1140608827
    //   222: l2i
    //   223: ldc 166319799
    //   225: ixor
    //   226: goto -> 236
    //   229: ldc2_w -317092536
    //   232: l2i
    //   233: ldc -1634860711
    //   235: ixor
    //   236: ldc2_w 518742332
    //   239: l2i
    //   240: ldc 1177956810
    //   242: ixor
    //   243: ixor
    //   244: lookupswitch default -> 924, -315148668 -> 229, 726326503 -> 272
    //   272: goto -> 276
    //   275: athrow
    //   276: invokevirtual func_177956_o : ()I
    //   279: goto -> 283
    //   282: athrow
    //   283: i2d
    //   284: getstatic Perryc.0 : I
    //   287: ifle -> 300
    //   290: ldc2_w -1706422348
    //   293: l2i
    //   294: ldc 471465419
    //   296: ixor
    //   297: goto -> 307
    //   300: ldc2_w -1847069093
    //   303: l2i
    //   304: ldc 1885117206
    //   306: ixor
    //   307: ldc2_w 878945181
    //   310: l2i
    //   311: ldc 1660418134
    //   313: ixor
    //   314: ixor
    //   315: lookupswitch default -> 936, -1221642618 -> 340, -792221260 -> 300
    //   340: aload_1
    //   341: getstatic Perryc.0 : I
    //   344: ifle -> 357
    //   347: ldc2_w -1455726555
    //   350: l2i
    //   351: ldc -1373398687
    //   353: ixor
    //   354: goto -> 364
    //   357: ldc2_w -1961581810
    //   360: l2i
    //   361: ldc 830731286
    //   363: ixor
    //   364: ldc2_w -488407436
    //   367: l2i
    //   368: ldc 789130539
    //   370: ixor
    //   371: ixor
    //   372: lookupswitch default -> 400, -890066405 -> 920, -642637785 -> 357
    //   400: goto -> 404
    //   403: athrow
    //   404: invokevirtual func_177952_p : ()I
    //   407: goto -> 411
    //   410: athrow
    //   411: i2d
    //   412: getstatic Perryc.0 : I
    //   415: ifle -> 428
    //   418: ldc2_w 380073240
    //   421: l2i
    //   422: ldc 1705062564
    //   424: ixor
    //   425: goto -> 435
    //   428: ldc2_w 1809050231
    //   431: l2i
    //   432: ldc 1710904909
    //   434: ixor
    //   435: ldc2_w -1266521839
    //   438: l2i
    //   439: ldc 516939876
    //   441: ixor
    //   442: ixor
    //   443: lookupswitch default -> 930, -1536936625 -> 468, -649343799 -> 428
    //   468: goto -> 472
    //   471: athrow
    //   472: invokespecial <init> : (DDD)V
    //   475: goto -> 479
    //   478: athrow
    //   479: getstatic Perryc.0 : I
    //   482: ifle -> 495
    //   485: ldc2_w 1501570487
    //   488: l2i
    //   489: ldc 204484835
    //   491: ixor
    //   492: goto -> 502
    //   495: ldc2_w 1145416312
    //   498: l2i
    //   499: ldc -1374098817
    //   501: ixor
    //   502: ldc2_w 1320977776
    //   505: l2i
    //   506: ldc 1954837712
    //   508: ixor
    //   509: ixor
    //   510: lookupswitch default -> 536, -1902524133 -> 495, 1871242484 -> 942
    //   536: astore_2
    //   537: getstatic Perryc.1 : I
    //   540: ifeq -> 553
    //   543: ldc2_w 1310525291
    //   546: l2i
    //   547: ldc -813982938
    //   549: ixor
    //   550: goto -> 560
    //   553: ldc2_w -174028345
    //   556: l2i
    //   557: ldc -1706330204
    //   559: ixor
    //   560: ldc2_w 1803447791
    //   563: l2i
    //   564: ldc 1419395028
    //   566: ixor
    //   567: ixor
    //   568: lookupswitch default -> 596, -1098723722 -> 934, -880394599 -> 553
    //   596: getstatic bigname/zprestige/webhack/util/RaytraceUtil.mc : Lnet/minecraft/client/Minecraft;
    //   599: getstatic Perryc.1 : I
    //   602: ifeq -> 615
    //   605: ldc2_w -1866330962
    //   608: l2i
    //   609: ldc -853271112
    //   611: ixor
    //   612: goto -> 622
    //   615: ldc2_w 1392952959
    //   618: l2i
    //   619: ldc 345583152
    //   621: ixor
    //   622: ldc2_w 1686886913
    //   625: l2i
    //   626: ldc 1804674624
    //   628: ixor
    //   629: ixor
    //   630: lookupswitch default -> 656, 1392307543 -> 946, 1508257625 -> 615
    //   656: getfield field_71441_e : Lnet/minecraft/client/multiplayer/WorldClient;
    //   659: getstatic Perryc.1 : I
    //   662: ifeq -> 675
    //   665: ldc2_w -243084717
    //   668: l2i
    //   669: ldc -751287772
    //   671: ixor
    //   672: goto -> 682
    //   675: ldc2_w -1235836669
    //   678: l2i
    //   679: ldc -1240837974
    //   681: ixor
    //   682: ldc2_w 1869183478
    //   685: l2i
    //   686: ldc 46574562
    //   688: ixor
    //   689: ixor
    //   690: lookupswitch default -> 922, 1326793315 -> 675, 1844650941 -> 716
    //   716: aload_0
    //   717: getstatic Perryc.1 : I
    //   720: ifeq -> 734
    //   723: ldc2_w 1178098370
    //   726: l2i
    //   727: ldc_w -1440205031
    //   730: ixor
    //   731: goto -> 742
    //   734: ldc2_w 126353086
    //   737: l2i
    //   738: ldc_w 1063028571
    //   741: ixor
    //   742: ldc2_w -1758361591
    //   745: l2i
    //   746: ldc_w 1146781203
    //   749: ixor
    //   750: ixor
    //   751: lookupswitch default -> 776, 797917097 -> 734, 1065065409 -> 938
    //   776: goto -> 780
    //   779: athrow
    //   780: invokevirtual func_174791_d : ()Lnet/minecraft/util/math/Vec3d;
    //   783: goto -> 787
    //   786: athrow
    //   787: getstatic Perryc.1 : I
    //   790: ifeq -> 804
    //   793: ldc2_w 442438242
    //   796: l2i
    //   797: ldc_w 488962218
    //   800: ixor
    //   801: goto -> 812
    //   804: ldc2_w -378447020
    //   807: l2i
    //   808: ldc_w 1343023989
    //   811: ixor
    //   812: ldc2_w 102462838
    //   815: l2i
    //   816: ldc_w 468104894
    //   819: ixor
    //   820: ixor
    //   821: lookupswitch default -> 928, -1535085591 -> 848, 444999936 -> 804
    //   848: aload_2
    //   849: getstatic Perryc.c : I
    //   852: iflt -> 866
    //   855: ldc2_w 622213691
    //   858: l2i
    //   859: ldc_w -969931066
    //   862: ixor
    //   863: goto -> 874
    //   866: ldc2_w 994137712
    //   869: l2i
    //   870: ldc_w -2037477256
    //   873: ixor
    //   874: ldc2_w -821479708
    //   877: l2i
    //   878: ldc_w 861434430
    //   881: ixor
    //   882: ixor
    //   883: lookupswitch default -> 908, 527923239 -> 926, 1847707419 -> 866
    //   908: goto -> 912
    //   911: athrow
    //   912: invokevirtual func_72933_a : (Lnet/minecraft/util/math/Vec3d;Lnet/minecraft/util/math/Vec3d;)Lnet/minecraft/util/math/RayTraceResult;
    //   915: goto -> 919
    //   918: athrow
    //   919: areturn
    //   920: aconst_null
    //   921: athrow
    //   922: aconst_null
    //   923: athrow
    //   924: aconst_null
    //   925: athrow
    //   926: aconst_null
    //   927: athrow
    //   928: aconst_null
    //   929: athrow
    //   930: aconst_null
    //   931: athrow
    //   932: aconst_null
    //   933: athrow
    //   934: aconst_null
    //   935: athrow
    //   936: aconst_null
    //   937: athrow
    //   938: aconst_null
    //   939: athrow
    //   940: aconst_null
    //   941: athrow
    //   942: aconst_null
    //   943: athrow
    //   944: aconst_null
    //   945: athrow
    //   946: aconst_null
    //   947: athrow
    //   948: pop
    //   949: goto -> 24
    //   952: pop
    //   953: aconst_null
    //   954: goto -> 948
    //   957: dup
    //   958: ifnull -> 948
    //   961: checkcast java/lang/Throwable
    //   964: athrow
    //   965: dup
    //   966: ifnull -> 952
    //   969: checkcast java/lang/Throwable
    //   972: athrow
    //   973: aconst_null
    //   974: athrow
    // Local variable table:
    //   start	length	slot	name	descriptor
    //   24	896	0	player	Lnet/minecraft/entity/player/EntityPlayer;
    //   24	896	1	block	Lnet/minecraft/util/math/BlockPos;
    //   537	383	2	blockPosition	Lnet/minecraft/util/math/Vec3d;
    // Exception table:
    //   from	to	target	type
    //   8	20	957	java/lang/RuntimeException
    //   147	154	154	finally
    //   147	154	3	finally
    //   147	154	154	finally
    //   148	154	147	java/util/NoSuchElementException
    //   148	154	3	java/lang/ClassCastException
    //   275	282	282	finally
    //   275	282	282	finally
    //   275	282	275	java/lang/IllegalStateException
    //   276	282	282	java/lang/NumberFormatException
    //   276	282	275	finally
    //   404	410	410	finally
    //   404	410	3	finally
    //   404	410	3	finally
    //   404	410	410	finally
    //   404	410	3	java/lang/ArithmeticException
    //   471	478	478	finally
    //   471	478	478	finally
    //   471	478	478	java/lang/RuntimeException
    //   472	478	471	finally
    //   472	478	3	java/util/NoSuchElementException
    //   779	786	786	finally
    //   779	786	786	finally
    //   779	786	779	java/lang/RuntimeException
    //   780	786	786	java/lang/RuntimeException
    //   780	786	786	finally
    //   911	918	918	finally
    //   911	918	911	java/lang/NullPointerException
    //   911	918	918	java/lang/NumberFormatException
    //   912	918	3	finally
    //   912	918	918	java/util/NoSuchElementException
    //   957	965	957	finally
    //   973	975	3	java/util/NoSuchElementException
  }
  
  public RaytraceUtil() {
    // Byte code:
    //   0: getstatic Perryc.c : I
    //   3: iflt -> 17
    //   6: ldc2_w -132583056
    //   9: l2i
    //   10: ldc_w 184702574
    //   13: ixor
    //   14: goto -> 25
    //   17: ldc2_w -918069751
    //   20: l2i
    //   21: ldc_w -204625928
    //   24: ixor
    //   25: ldc2_w -450830154
    //   28: l2i
    //   29: ldc_w 690348167
    //   32: ixor
    //   33: ixor
    //   34: lookupswitch default -> 60, 1059039023 -> 124, 1815244961 -> 17
    //   60: aload_0
    //   61: getstatic Perryc.c : I
    //   64: iflt -> 78
    //   67: ldc2_w 1105844931
    //   70: l2i
    //   71: ldc_w -299452939
    //   74: ixor
    //   75: goto -> 86
    //   78: ldc2_w 728800500
    //   81: l2i
    //   82: ldc_w -944469784
    //   85: ixor
    //   86: ldc2_w -1015465094
    //   89: l2i
    //   90: ldc_w -611811549
    //   93: ixor
    //   94: ixor
    //   95: lookupswitch default -> 120, -1220662417 -> 126, 561221702 -> 78
    //   120: invokespecial <init> : ()V
    //   123: return
    //   124: aconst_null
    //   125: athrow
    //   126: aconst_null
    //   127: athrow
    // Local variable table:
    //   start	length	slot	name	descriptor
    //   0	124	0	this	Lbigname/zprestige/webhack/util/RaytraceUtil;
  }
}


/* Location:              C:\Users\alex\Desktop\webhack\WebHack-0.8-obf_sussy_1.jar!\bigname\zprestige\webhac\\util\RaytraceUtil.class
 * Java compiler version: 8 (52.0)
 * JD-Core Version:       1.1.3
 */