package bigname.zprestige.webhack.util;

public class TextUtil$1 {
  public static int[] $SwitchMap$bigname$zprestige$webhack$util$TextUtil$Color;
  
  static {
    // Byte code:
    //   0: getstatic Perryc.0 : I
    //   3: ifle -> 16
    //   6: ldc2_w -2141298950
    //   9: l2i
    //   10: ldc -1652426802
    //   12: ixor
    //   13: goto -> 23
    //   16: ldc2_w -693739611
    //   19: l2i
    //   20: ldc 1365769754
    //   22: ixor
    //   23: ldc2_w 555788227
    //   26: l2i
    //   27: ldc -42426591
    //   29: ixor
    //   30: ixor
    //   31: lookupswitch default -> 56, -1048079914 -> 4382, 1623867210 -> 16
    //   56: invokestatic values : ()[Lbigname/zprestige/webhack/util/TextUtil$Color;
    //   59: arraylength
    //   60: newarray int
    //   62: getstatic Perryc.1 : I
    //   65: ifeq -> 78
    //   68: ldc2_w -223517518
    //   71: l2i
    //   72: ldc -179428706
    //   74: ixor
    //   75: goto -> 85
    //   78: ldc2_w -338448759
    //   81: l2i
    //   82: ldc -1870828186
    //   84: ixor
    //   85: ldc2_w -1713389966
    //   88: l2i
    //   89: ldc -1077371119
    //   91: ixor
    //   92: ixor
    //   93: lookupswitch default -> 120, -336283951 -> 78, 569665359 -> 4356
    //   120: putstatic bigname/zprestige/webhack/util/TextUtil$1.$SwitchMap$bigname$zprestige$webhack$util$TextUtil$Color : [I
    //   123: getstatic Perryc.1 : I
    //   126: ifeq -> 139
    //   129: ldc2_w -730559546
    //   132: l2i
    //   133: ldc -861226969
    //   135: ixor
    //   136: goto -> 146
    //   139: ldc2_w -743796675
    //   142: l2i
    //   143: ldc 786321017
    //   145: ixor
    //   146: ldc2_w -1516271050
    //   149: l2i
    //   150: ldc 1777068272
    //   152: ixor
    //   153: ixor
    //   154: lookupswitch default -> 180, -1595061351 -> 139, -727035609 -> 4306
    //   180: getstatic bigname/zprestige/webhack/util/TextUtil$1.$SwitchMap$bigname$zprestige$webhack$util$TextUtil$Color : [I
    //   183: getstatic Perryc.c : I
    //   186: iflt -> 199
    //   189: ldc2_w 910562206
    //   192: l2i
    //   193: ldc 684052063
    //   195: ixor
    //   196: goto -> 206
    //   199: ldc2_w 1881249459
    //   202: l2i
    //   203: ldc -2132569797
    //   205: ixor
    //   206: ldc2_w 347293315
    //   209: l2i
    //   210: ldc 978733056
    //   212: ixor
    //   213: ixor
    //   214: lookupswitch default -> 240, 501146523 -> 199, 812045122 -> 4324
    //   240: getstatic bigname/zprestige/webhack/util/TextUtil$Color.AQUA : Lbigname/zprestige/webhack/util/TextUtil$Color;
    //   243: getstatic Perryc.1 : I
    //   246: ifeq -> 259
    //   249: ldc2_w -284634122
    //   252: l2i
    //   253: ldc 347787426
    //   255: ixor
    //   256: goto -> 266
    //   259: ldc2_w -12100969
    //   262: l2i
    //   263: ldc 1725246794
    //   265: ixor
    //   266: ldc2_w 1523860119
    //   269: l2i
    //   270: ldc 1317334802
    //   272: ixor
    //   273: ixor
    //   274: lookupswitch default -> 300, -270356783 -> 4308, 648831333 -> 259
    //   300: invokevirtual ordinal : ()I
    //   303: ldc2_w 1256251697
    //   306: l2i
    //   307: ldc 1256251696
    //   309: ixor
    //   310: iastore
    //   311: goto -> 373
    //   314: getstatic Perryc.c : I
    //   317: iflt -> 330
    //   320: ldc2_w -2138922079
    //   323: l2i
    //   324: ldc 510339700
    //   326: ixor
    //   327: goto -> 337
    //   330: ldc2_w 1713632728
    //   333: l2i
    //   334: ldc -831037574
    //   336: ixor
    //   337: ldc2_w 1532289995
    //   340: l2i
    //   341: ldc 1007919402
    //   343: ixor
    //   344: ixor
    //   345: lookupswitch default -> 4292, -820778941 -> 372, -105985228 -> 330
    //   372: astore_0
    //   373: getstatic Perryc.0 : I
    //   376: ifle -> 389
    //   379: ldc2_w -1741410508
    //   382: l2i
    //   383: ldc 1985115390
    //   385: ixor
    //   386: goto -> 396
    //   389: ldc2_w 1541576837
    //   392: l2i
    //   393: ldc -1484821333
    //   395: ixor
    //   396: ldc2_w 272480353
    //   399: l2i
    //   400: ldc 779591030
    //   402: ixor
    //   403: ixor
    //   404: lookupswitch default -> 4372, -1026043591 -> 432, -802390307 -> 389
    //   432: getstatic bigname/zprestige/webhack/util/TextUtil$1.$SwitchMap$bigname$zprestige$webhack$util$TextUtil$Color : [I
    //   435: getstatic Perryc.1 : I
    //   438: ifeq -> 451
    //   441: ldc2_w 1504773021
    //   444: l2i
    //   445: ldc 155994040
    //   447: ixor
    //   448: goto -> 458
    //   451: ldc2_w 39303910
    //   454: l2i
    //   455: ldc -1329741886
    //   457: ixor
    //   458: ldc2_w 463288946
    //   461: l2i
    //   462: ldc -718413161
    //   464: ixor
    //   465: ixor
    //   466: lookupswitch default -> 492, -1639080768 -> 4346, 379626533 -> 451
    //   492: getstatic bigname/zprestige/webhack/util/TextUtil$Color.WHITE : Lbigname/zprestige/webhack/util/TextUtil$Color;
    //   495: getstatic Perryc.1 : I
    //   498: ifeq -> 511
    //   501: ldc2_w -384869393
    //   504: l2i
    //   505: ldc -663492205
    //   507: ixor
    //   508: goto -> 518
    //   511: ldc2_w 1963044873
    //   514: l2i
    //   515: ldc 756388377
    //   517: ixor
    //   518: ldc2_w 941181929
    //   521: l2i
    //   522: ldc -940462210
    //   524: ixor
    //   525: ixor
    //   526: lookupswitch default -> 552, -829139221 -> 4332, 1834460342 -> 511
    //   552: invokevirtual ordinal : ()I
    //   555: ldc2_w 367476485
    //   558: l2i
    //   559: ldc 367476487
    //   561: ixor
    //   562: iastore
    //   563: goto -> 625
    //   566: getstatic Perryc.c : I
    //   569: iflt -> 582
    //   572: ldc2_w -1602978693
    //   575: l2i
    //   576: ldc 1217550323
    //   578: ixor
    //   579: goto -> 589
    //   582: ldc2_w 430750067
    //   585: l2i
    //   586: ldc 1496428440
    //   588: ixor
    //   589: ldc2_w 827273984
    //   592: l2i
    //   593: ldc 1421777172
    //   595: ixor
    //   596: ixor
    //   597: lookupswitch default -> 4342, -1927839332 -> 582, 627883263 -> 624
    //   624: astore_0
    //   625: getstatic Perryc.1 : I
    //   628: ifeq -> 641
    //   631: ldc2_w 22876540
    //   634: l2i
    //   635: ldc -1957677191
    //   637: ixor
    //   638: goto -> 648
    //   641: ldc2_w -47620697
    //   644: l2i
    //   645: ldc 226015988
    //   647: ixor
    //   648: ldc2_w -439056191
    //   651: l2i
    //   652: ldc 1667258102
    //   654: ixor
    //   655: ixor
    //   656: lookupswitch default -> 684, 213514290 -> 4400, 953421198 -> 641
    //   684: getstatic bigname/zprestige/webhack/util/TextUtil$1.$SwitchMap$bigname$zprestige$webhack$util$TextUtil$Color : [I
    //   687: getstatic Perryc.1 : I
    //   690: ifeq -> 703
    //   693: ldc2_w -111520273
    //   696: l2i
    //   697: ldc 18707580
    //   699: ixor
    //   700: goto -> 710
    //   703: ldc2_w 1908442570
    //   706: l2i
    //   707: ldc 326457135
    //   709: ixor
    //   710: ldc2_w 1626080719
    //   713: l2i
    //   714: ldc 353822128
    //   716: ixor
    //   717: ixor
    //   718: lookupswitch default -> 4398, -1916943892 -> 703, 391066266 -> 744
    //   744: getstatic bigname/zprestige/webhack/util/TextUtil$Color.BLACK : Lbigname/zprestige/webhack/util/TextUtil$Color;
    //   747: getstatic Perryc.0 : I
    //   750: ifle -> 763
    //   753: ldc2_w -447192437
    //   756: l2i
    //   757: ldc 1867325744
    //   759: ixor
    //   760: goto -> 770
    //   763: ldc2_w -916973153
    //   766: l2i
    //   767: ldc 1907291188
    //   769: ixor
    //   770: ldc2_w -1647929268
    //   773: l2i
    //   774: ldc -1055998311
    //   776: ixor
    //   777: ixor
    //   778: lookupswitch default -> 4290, -690133650 -> 763, -465646722 -> 804
    //   804: invokevirtual ordinal : ()I
    //   807: ldc2_w 1029293693
    //   810: l2i
    //   811: ldc 1029293694
    //   813: ixor
    //   814: iastore
    //   815: goto -> 877
    //   818: getstatic Perryc.1 : I
    //   821: ifeq -> 834
    //   824: ldc2_w 1688179949
    //   827: l2i
    //   828: ldc 1901681716
    //   830: ixor
    //   831: goto -> 841
    //   834: ldc2_w 1145592453
    //   837: l2i
    //   838: ldc 1698072042
    //   840: ixor
    //   841: ldc2_w 1479466574
    //   844: l2i
    //   845: ldc -1388641895
    //   847: ixor
    //   848: ixor
    //   849: lookupswitch default -> 876, -523036914 -> 4304, 1302230719 -> 834
    //   876: astore_0
    //   877: getstatic Perryc.c : I
    //   880: iflt -> 893
    //   883: ldc2_w 355931597
    //   886: l2i
    //   887: ldc -479030014
    //   889: ixor
    //   890: goto -> 900
    //   893: ldc2_w -1817045012
    //   896: l2i
    //   897: ldc 386613952
    //   899: ixor
    //   900: ldc2_w -582696262
    //   903: l2i
    //   904: ldc 109196230
    //   906: ixor
    //   907: ixor
    //   908: lookupswitch default -> 4408, 763589043 -> 893, 1602200656 -> 936
    //   936: getstatic bigname/zprestige/webhack/util/TextUtil$1.$SwitchMap$bigname$zprestige$webhack$util$TextUtil$Color : [I
    //   939: getstatic Perryc.0 : I
    //   942: ifle -> 955
    //   945: ldc2_w 1475092063
    //   948: l2i
    //   949: ldc 1407197629
    //   951: ixor
    //   952: goto -> 962
    //   955: ldc2_w -1212979720
    //   958: l2i
    //   959: ldc -366630540
    //   961: ixor
    //   962: ldc2_w 547449169
    //   965: l2i
    //   966: ldc -1346134943
    //   968: ixor
    //   969: ixor
    //   970: lookupswitch default -> 996, -1955673390 -> 4330, 369560667 -> 955
    //   996: getstatic bigname/zprestige/webhack/util/TextUtil$Color.DARK_BLUE : Lbigname/zprestige/webhack/util/TextUtil$Color;
    //   999: getstatic Perryc.0 : I
    //   1002: ifle -> 1015
    //   1005: ldc2_w 1287425064
    //   1008: l2i
    //   1009: ldc 684851791
    //   1011: ixor
    //   1012: goto -> 1022
    //   1015: ldc2_w 1646522855
    //   1018: l2i
    //   1019: ldc 553995790
    //   1021: ixor
    //   1022: ldc2_w 611312523
    //   1025: l2i
    //   1026: ldc -1272045190
    //   1028: ixor
    //   1029: ixor
    //   1030: lookupswitch default -> 4374, -748192488 -> 1056, -198226794 -> 1015
    //   1056: invokevirtual ordinal : ()I
    //   1059: ldc2_w -794024247
    //   1062: l2i
    //   1063: ldc -794024243
    //   1065: ixor
    //   1066: iastore
    //   1067: goto -> 1129
    //   1070: getstatic Perryc.1 : I
    //   1073: ifeq -> 1086
    //   1076: ldc2_w -864725713
    //   1079: l2i
    //   1080: ldc 199596299
    //   1082: ixor
    //   1083: goto -> 1093
    //   1086: ldc2_w -560185960
    //   1089: l2i
    //   1090: ldc -351277307
    //   1092: ixor
    //   1093: ldc2_w 1021499841
    //   1096: l2i
    //   1097: ldc 964704061
    //   1099: ixor
    //   1100: ixor
    //   1101: lookupswitch default -> 1128, -1024318760 -> 4388, -28487479 -> 1086
    //   1128: astore_0
    //   1129: getstatic Perryc.c : I
    //   1132: iflt -> 1145
    //   1135: ldc2_w -1078837951
    //   1138: l2i
    //   1139: ldc 336482844
    //   1141: ixor
    //   1142: goto -> 1152
    //   1145: ldc2_w 1007311370
    //   1148: l2i
    //   1149: ldc -237857007
    //   1151: ixor
    //   1152: ldc2_w -1843957577
    //   1155: l2i
    //   1156: ldc 1450961352
    //   1158: ixor
    //   1159: ixor
    //   1160: lookupswitch default -> 4394, 162813028 -> 1188, 1875965474 -> 1145
    //   1188: getstatic bigname/zprestige/webhack/util/TextUtil$1.$SwitchMap$bigname$zprestige$webhack$util$TextUtil$Color : [I
    //   1191: getstatic Perryc.0 : I
    //   1194: ifle -> 1207
    //   1197: ldc2_w 1704126868
    //   1200: l2i
    //   1201: ldc -233944207
    //   1203: ixor
    //   1204: goto -> 1214
    //   1207: ldc2_w 2117693395
    //   1210: l2i
    //   1211: ldc 754594755
    //   1213: ixor
    //   1214: ldc2_w 483309783
    //   1217: l2i
    //   1218: ldc -776836415
    //   1220: ixor
    //   1221: ixor
    //   1222: lookupswitch default -> 4360, -1614836218 -> 1248, 1524658419 -> 1207
    //   1248: getstatic bigname/zprestige/webhack/util/TextUtil$Color.DARK_GREEN : Lbigname/zprestige/webhack/util/TextUtil$Color;
    //   1251: getstatic Perryc.c : I
    //   1254: iflt -> 1267
    //   1257: ldc2_w 1927095548
    //   1260: l2i
    //   1261: ldc 849299745
    //   1263: ixor
    //   1264: goto -> 1274
    //   1267: ldc2_w -2060190527
    //   1270: l2i
    //   1271: ldc -2043589215
    //   1273: ixor
    //   1274: ldc2_w 1441091580
    //   1277: l2i
    //   1278: ldc 280169899
    //   1280: ixor
    //   1281: ixor
    //   1282: lookupswitch default -> 4338, 85208970 -> 1267, 1179972407 -> 1308
    //   1308: invokevirtual ordinal : ()I
    //   1311: ldc2_w 1129958184
    //   1314: l2i
    //   1315: ldc_w 1129958189
    //   1318: ixor
    //   1319: iastore
    //   1320: goto -> 1385
    //   1323: getstatic Perryc.1 : I
    //   1326: ifeq -> 1340
    //   1329: ldc2_w -1747042683
    //   1332: l2i
    //   1333: ldc_w -768571936
    //   1336: ixor
    //   1337: goto -> 1348
    //   1340: ldc2_w 1152193963
    //   1343: l2i
    //   1344: ldc_w -1998326241
    //   1347: ixor
    //   1348: ldc2_w 185926300
    //   1351: l2i
    //   1352: ldc_w 763421138
    //   1355: ixor
    //   1356: ixor
    //   1357: lookupswitch default -> 4344, -354746118 -> 1384, 1669027883 -> 1340
    //   1384: astore_0
    //   1385: getstatic Perryc.0 : I
    //   1388: ifle -> 1402
    //   1391: ldc2_w 212706020
    //   1394: l2i
    //   1395: ldc_w 1835750753
    //   1398: ixor
    //   1399: goto -> 1410
    //   1402: ldc2_w 886094493
    //   1405: l2i
    //   1406: ldc_w 88599426
    //   1409: ixor
    //   1410: ldc2_w -175753546
    //   1413: l2i
    //   1414: ldc_w 224460611
    //   1417: ixor
    //   1418: ixor
    //   1419: lookupswitch default -> 4396, -1725940112 -> 1402, -915302166 -> 1444
    //   1444: getstatic bigname/zprestige/webhack/util/TextUtil$1.$SwitchMap$bigname$zprestige$webhack$util$TextUtil$Color : [I
    //   1447: getstatic Perryc.0 : I
    //   1450: ifle -> 1464
    //   1453: ldc2_w 1097228021
    //   1456: l2i
    //   1457: ldc_w -855832662
    //   1460: ixor
    //   1461: goto -> 1472
    //   1464: ldc2_w -870385226
    //   1467: l2i
    //   1468: ldc_w -361445942
    //   1471: ixor
    //   1472: ldc2_w 1721478067
    //   1475: l2i
    //   1476: ldc_w 792551245
    //   1479: ixor
    //   1480: ixor
    //   1481: lookupswitch default -> 4350, -1002590815 -> 1464, 1875691650 -> 1508
    //   1508: getstatic bigname/zprestige/webhack/util/TextUtil$Color.DARK_AQUA : Lbigname/zprestige/webhack/util/TextUtil$Color;
    //   1511: getstatic Perryc.1 : I
    //   1514: ifeq -> 1528
    //   1517: ldc2_w 491243978
    //   1520: l2i
    //   1521: ldc_w 1102000903
    //   1524: ixor
    //   1525: goto -> 1536
    //   1528: ldc2_w 1348283594
    //   1531: l2i
    //   1532: ldc_w 765509957
    //   1535: ixor
    //   1536: ldc2_w -1223939139
    //   1539: l2i
    //   1540: ldc_w 232392534
    //   1543: ixor
    //   1544: ixor
    //   1545: lookupswitch default -> 4384, -953433756 -> 1572, -432089562 -> 1528
    //   1572: invokevirtual ordinal : ()I
    //   1575: ldc2_w -975717466
    //   1578: l2i
    //   1579: ldc_w -975717472
    //   1582: ixor
    //   1583: iastore
    //   1584: goto -> 1649
    //   1587: getstatic Perryc.1 : I
    //   1590: ifeq -> 1604
    //   1593: ldc2_w 713580673
    //   1596: l2i
    //   1597: ldc_w -557928431
    //   1600: ixor
    //   1601: goto -> 1612
    //   1604: ldc2_w -1528019402
    //   1607: l2i
    //   1608: ldc_w -1790559872
    //   1611: ixor
    //   1612: ldc2_w -194316699
    //   1615: l2i
    //   1616: ldc_w -1426355326
    //   1619: ixor
    //   1620: ixor
    //   1621: lookupswitch default -> 1648, -1817634229 -> 1604, -1431851657 -> 4376
    //   1648: astore_0
    //   1649: getstatic Perryc.0 : I
    //   1652: ifle -> 1666
    //   1655: ldc2_w 1376399807
    //   1658: l2i
    //   1659: ldc_w 1107064684
    //   1662: ixor
    //   1663: goto -> 1674
    //   1666: ldc2_w 1184686652
    //   1669: l2i
    //   1670: ldc_w -1392737655
    //   1673: ixor
    //   1674: ldc2_w 1522870422
    //   1677: l2i
    //   1678: ldc_w -1648884779
    //   1681: ixor
    //   1682: ixor
    //   1683: lookupswitch default -> 1708, -729059952 -> 4416, -647744086 -> 1666
    //   1708: getstatic bigname/zprestige/webhack/util/TextUtil$1.$SwitchMap$bigname$zprestige$webhack$util$TextUtil$Color : [I
    //   1711: getstatic Perryc.c : I
    //   1714: iflt -> 1728
    //   1717: ldc2_w 1085920643
    //   1720: l2i
    //   1721: ldc_w 1081413737
    //   1724: ixor
    //   1725: goto -> 1736
    //   1728: ldc2_w 908131044
    //   1731: l2i
    //   1732: ldc_w 255696951
    //   1735: ixor
    //   1736: ldc2_w 1314202771
    //   1739: l2i
    //   1740: ldc_w 1024857265
    //   1743: ixor
    //   1744: ixor
    //   1745: lookupswitch default -> 1772, 213001255 -> 1728, 1938814408 -> 4418
    //   1772: getstatic bigname/zprestige/webhack/util/TextUtil$Color.DARK_RED : Lbigname/zprestige/webhack/util/TextUtil$Color;
    //   1775: getstatic Perryc.c : I
    //   1778: iflt -> 1792
    //   1781: ldc2_w -1760777109
    //   1784: l2i
    //   1785: ldc_w -1229911273
    //   1788: ixor
    //   1789: goto -> 1800
    //   1792: ldc2_w 1499671030
    //   1795: l2i
    //   1796: ldc_w 1840855111
    //   1799: ixor
    //   1800: ldc2_w 1609402482
    //   1803: l2i
    //   1804: ldc_w -80481161
    //   1807: ixor
    //   1808: ixor
    //   1809: lookupswitch default -> 1836, -2057053319 -> 4420, 2134375197 -> 1792
    //   1836: invokevirtual ordinal : ()I
    //   1839: ldc2_w 818157697
    //   1842: l2i
    //   1843: ldc_w 818157702
    //   1846: ixor
    //   1847: iastore
    //   1848: goto -> 1913
    //   1851: getstatic Perryc.0 : I
    //   1854: ifle -> 1868
    //   1857: ldc2_w -1318753438
    //   1860: l2i
    //   1861: ldc_w -488820425
    //   1864: ixor
    //   1865: goto -> 1876
    //   1868: ldc2_w 1491259917
    //   1871: l2i
    //   1872: ldc_w 5101817
    //   1875: ixor
    //   1876: ldc2_w -384108302
    //   1879: l2i
    //   1880: ldc_w -633648337
    //   1883: ixor
    //   1884: ixor
    //   1885: lookupswitch default -> 1912, -1227499501 -> 1868, 1620699528 -> 4298
    //   1912: astore_0
    //   1913: getstatic Perryc.c : I
    //   1916: iflt -> 1930
    //   1919: ldc2_w -574055299
    //   1922: l2i
    //   1923: ldc_w 1717481198
    //   1926: ixor
    //   1927: goto -> 1938
    //   1930: ldc2_w -1115044851
    //   1933: l2i
    //   1934: ldc_w 1015910439
    //   1937: ixor
    //   1938: ldc2_w -497417866
    //   1941: l2i
    //   1942: ldc_w -732244800
    //   1945: ixor
    //   1946: ixor
    //   1947: lookupswitch default -> 1972, -1919490267 -> 4358, 835427366 -> 1930
    //   1972: getstatic bigname/zprestige/webhack/util/TextUtil$1.$SwitchMap$bigname$zprestige$webhack$util$TextUtil$Color : [I
    //   1975: getstatic Perryc.1 : I
    //   1978: ifeq -> 1992
    //   1981: ldc2_w -809945244
    //   1984: l2i
    //   1985: ldc_w 272914757
    //   1988: ixor
    //   1989: goto -> 2000
    //   1992: ldc2_w 1286651010
    //   1995: l2i
    //   1996: ldc_w -2006941033
    //   1999: ixor
    //   2000: ldc2_w -1076717370
    //   2003: l2i
    //   2004: ldc_w 2094111758
    //   2007: ixor
    //   2008: ixor
    //   2009: lookupswitch default -> 2036, -1528890166 -> 1992, 486435561 -> 4340
    //   2036: getstatic bigname/zprestige/webhack/util/TextUtil$Color.DARK_PURPLE : Lbigname/zprestige/webhack/util/TextUtil$Color;
    //   2039: getstatic Perryc.c : I
    //   2042: iflt -> 2056
    //   2045: ldc2_w -75266906
    //   2048: l2i
    //   2049: ldc_w -1514197476
    //   2052: ixor
    //   2053: goto -> 2064
    //   2056: ldc2_w -1656159818
    //   2059: l2i
    //   2060: ldc_w 1456373491
    //   2063: ixor
    //   2064: ldc2_w 715226563
    //   2067: l2i
    //   2068: ldc_w 849225348
    //   2071: ixor
    //   2072: ixor
    //   2073: lookupswitch default -> 4412, -742906878 -> 2100, 1174663677 -> 2056
    //   2100: invokevirtual ordinal : ()I
    //   2103: ldc2_w -654697606
    //   2106: l2i
    //   2107: ldc_w -654697614
    //   2110: ixor
    //   2111: iastore
    //   2112: goto -> 2177
    //   2115: getstatic Perryc.1 : I
    //   2118: ifeq -> 2132
    //   2121: ldc2_w -1978963500
    //   2124: l2i
    //   2125: ldc_w 1247402616
    //   2128: ixor
    //   2129: goto -> 2140
    //   2132: ldc2_w 926291582
    //   2135: l2i
    //   2136: ldc_w -1808309596
    //   2139: ixor
    //   2140: ldc2_w 737149829
    //   2143: l2i
    //   2144: ldc_w -1705197112
    //   2147: ixor
    //   2148: ixor
    //   2149: lookupswitch default -> 2176, -387682734 -> 2132, 1912500705 -> 4410
    //   2176: astore_0
    //   2177: getstatic Perryc.0 : I
    //   2180: ifle -> 2194
    //   2183: ldc2_w -47622878
    //   2186: l2i
    //   2187: ldc_w -1548768177
    //   2190: ixor
    //   2191: goto -> 2202
    //   2194: ldc2_w 25480878
    //   2197: l2i
    //   2198: ldc_w 480200948
    //   2201: ixor
    //   2202: ldc2_w -402667556
    //   2205: l2i
    //   2206: ldc_w 1457120965
    //   2209: ixor
    //   2210: ixor
    //   2211: lookupswitch default -> 2236, -274671500 -> 4348, 1650271075 -> 2194
    //   2236: getstatic bigname/zprestige/webhack/util/TextUtil$1.$SwitchMap$bigname$zprestige$webhack$util$TextUtil$Color : [I
    //   2239: getstatic Perryc.c : I
    //   2242: iflt -> 2256
    //   2245: ldc2_w -1945634709
    //   2248: l2i
    //   2249: ldc_w -377816092
    //   2252: ixor
    //   2253: goto -> 2264
    //   2256: ldc2_w -972869603
    //   2259: l2i
    //   2260: ldc_w 373018648
    //   2263: ixor
    //   2264: ldc2_w -948371641
    //   2267: l2i
    //   2268: ldc_w 1580706076
    //   2271: ixor
    //   2272: ixor
    //   2273: lookupswitch default -> 2300, -63810092 -> 4392, 2129853760 -> 2256
    //   2300: getstatic bigname/zprestige/webhack/util/TextUtil$Color.GOLD : Lbigname/zprestige/webhack/util/TextUtil$Color;
    //   2303: getstatic Perryc.0 : I
    //   2306: ifle -> 2320
    //   2309: ldc2_w 1076733944
    //   2312: l2i
    //   2313: ldc_w 818485233
    //   2316: ixor
    //   2317: goto -> 2328
    //   2320: ldc2_w -1661521270
    //   2323: l2i
    //   2324: ldc_w -919719593
    //   2327: ixor
    //   2328: ldc2_w -1678048604
    //   2331: l2i
    //   2332: ldc_w -1786248798
    //   2335: ixor
    //   2336: ixor
    //   2337: lookupswitch default -> 2364, 143343435 -> 2320, 2123870991 -> 4310
    //   2364: invokevirtual ordinal : ()I
    //   2367: ldc2_w 1889114188
    //   2370: l2i
    //   2371: ldc_w 1889114181
    //   2374: ixor
    //   2375: iastore
    //   2376: goto -> 2441
    //   2379: getstatic Perryc.0 : I
    //   2382: ifle -> 2396
    //   2385: ldc2_w -1656506191
    //   2388: l2i
    //   2389: ldc_w 386338698
    //   2392: ixor
    //   2393: goto -> 2404
    //   2396: ldc2_w 1726166494
    //   2399: l2i
    //   2400: ldc_w -1230658192
    //   2403: ixor
    //   2404: ldc2_w 1371898877
    //   2407: l2i
    //   2408: ldc_w -749788469
    //   2411: ixor
    //   2412: ixor
    //   2413: lookupswitch default -> 4318, 147723789 -> 2396, 1389113752 -> 2440
    //   2440: astore_0
    //   2441: getstatic Perryc.c : I
    //   2444: iflt -> 2458
    //   2447: ldc2_w 1239423939
    //   2450: l2i
    //   2451: ldc_w -633409602
    //   2454: ixor
    //   2455: goto -> 2466
    //   2458: ldc2_w 1153272965
    //   2461: l2i
    //   2462: ldc_w -391480546
    //   2465: ixor
    //   2466: ldc2_w -1396883104
    //   2469: l2i
    //   2470: ldc_w 386851352
    //   2473: ixor
    //   2474: ixor
    //   2475: lookupswitch default -> 4294, 396645603 -> 2500, 678254341 -> 2458
    //   2500: getstatic bigname/zprestige/webhack/util/TextUtil$1.$SwitchMap$bigname$zprestige$webhack$util$TextUtil$Color : [I
    //   2503: getstatic Perryc.0 : I
    //   2506: ifle -> 2520
    //   2509: ldc2_w -1460781923
    //   2512: l2i
    //   2513: ldc_w -980644484
    //   2516: ixor
    //   2517: goto -> 2528
    //   2520: ldc2_w 673142905
    //   2523: l2i
    //   2524: ldc_w 457488811
    //   2527: ixor
    //   2528: ldc2_w -1151611818
    //   2531: l2i
    //   2532: ldc_w 824354517
    //   2535: ixor
    //   2536: ixor
    //   2537: lookupswitch default -> 2564, -417604766 -> 4352, -12603174 -> 2520
    //   2564: getstatic bigname/zprestige/webhack/util/TextUtil$Color.DARK_GRAY : Lbigname/zprestige/webhack/util/TextUtil$Color;
    //   2567: getstatic Perryc.1 : I
    //   2570: ifeq -> 2584
    //   2573: ldc2_w 982562262
    //   2576: l2i
    //   2577: ldc_w -2042249588
    //   2580: ixor
    //   2581: goto -> 2592
    //   2584: ldc2_w -1269229267
    //   2587: l2i
    //   2588: ldc_w 1765220734
    //   2591: ixor
    //   2592: ldc2_w -2018687643
    //   2595: l2i
    //   2596: ldc_w -1178418294
    //   2599: ixor
    //   2600: ixor
    //   2601: lookupswitch default -> 2628, -2101703243 -> 4390, -253593093 -> 2584
    //   2628: invokevirtual ordinal : ()I
    //   2631: ldc2_w -1108878240
    //   2634: l2i
    //   2635: ldc_w -1108878230
    //   2638: ixor
    //   2639: iastore
    //   2640: goto -> 2705
    //   2643: getstatic Perryc.c : I
    //   2646: iflt -> 2660
    //   2649: ldc2_w 119717723
    //   2652: l2i
    //   2653: ldc_w -1360402519
    //   2656: ixor
    //   2657: goto -> 2668
    //   2660: ldc2_w 1137077879
    //   2663: l2i
    //   2664: ldc_w 302775680
    //   2667: ixor
    //   2668: ldc2_w 1009367723
    //   2671: l2i
    //   2672: ldc_w -530532104
    //   2675: ixor
    //   2676: ixor
    //   2677: lookupswitch default -> 4366, -1920691804 -> 2704, 1971477153 -> 2660
    //   2704: astore_0
    //   2705: getstatic Perryc.1 : I
    //   2708: ifeq -> 2722
    //   2711: ldc2_w 1806553852
    //   2714: l2i
    //   2715: ldc_w 1458944380
    //   2718: ixor
    //   2719: goto -> 2730
    //   2722: ldc2_w 1557495438
    //   2725: l2i
    //   2726: ldc_w -90661099
    //   2729: ixor
    //   2730: ldc2_w 439459955
    //   2733: l2i
    //   2734: ldc_w -1445850532
    //   2737: ixor
    //   2738: ixor
    //   2739: lookupswitch default -> 2764, -2131023520 -> 2722, -1900291665 -> 4302
    //   2764: getstatic bigname/zprestige/webhack/util/TextUtil$1.$SwitchMap$bigname$zprestige$webhack$util$TextUtil$Color : [I
    //   2767: getstatic Perryc.1 : I
    //   2770: ifeq -> 2784
    //   2773: ldc2_w 976645771
    //   2776: l2i
    //   2777: ldc_w -2067760467
    //   2780: ixor
    //   2781: goto -> 2792
    //   2784: ldc2_w -2120699469
    //   2787: l2i
    //   2788: ldc_w -1857374768
    //   2791: ixor
    //   2792: ldc2_w -182884892
    //   2795: l2i
    //   2796: ldc_w -93957463
    //   2799: ixor
    //   2800: ixor
    //   2801: lookupswitch default -> 4378, -1316412565 -> 2784, 531444526 -> 2828
    //   2828: getstatic bigname/zprestige/webhack/util/TextUtil$Color.GRAY : Lbigname/zprestige/webhack/util/TextUtil$Color;
    //   2831: getstatic Perryc.0 : I
    //   2834: ifle -> 2848
    //   2837: ldc2_w 1516065617
    //   2840: l2i
    //   2841: ldc_w -533106226
    //   2844: ixor
    //   2845: goto -> 2856
    //   2848: ldc2_w -609377736
    //   2851: l2i
    //   2852: ldc_w 150002474
    //   2855: ixor
    //   2856: ldc2_w -71433876
    //   2859: l2i
    //   2860: ldc_w 633458901
    //   2863: ixor
    //   2864: ixor
    //   2865: lookupswitch default -> 2892, -2121607625 -> 2848, 1679553318 -> 4312
    //   2892: invokevirtual ordinal : ()I
    //   2895: ldc2_w 628666416
    //   2898: l2i
    //   2899: ldc_w 628666427
    //   2902: ixor
    //   2903: iastore
    //   2904: goto -> 2969
    //   2907: getstatic Perryc.0 : I
    //   2910: ifle -> 2924
    //   2913: ldc2_w 1383465513
    //   2916: l2i
    //   2917: ldc_w -70470805
    //   2920: ixor
    //   2921: goto -> 2932
    //   2924: ldc2_w 1524116326
    //   2927: l2i
    //   2928: ldc_w -394112188
    //   2931: ixor
    //   2932: ldc2_w 344765071
    //   2935: l2i
    //   2936: ldc_w 2138103830
    //   2939: ixor
    //   2940: ixor
    //   2941: lookupswitch default -> 4364, -1035541541 -> 2924, -643421509 -> 2968
    //   2968: astore_0
    //   2969: getstatic Perryc.1 : I
    //   2972: ifeq -> 2986
    //   2975: ldc2_w 1589916251
    //   2978: l2i
    //   2979: ldc_w -75883947
    //   2982: ixor
    //   2983: goto -> 2994
    //   2986: ldc2_w -1374662115
    //   2989: l2i
    //   2990: ldc_w 1043773573
    //   2993: ixor
    //   2994: ldc2_w 466243624
    //   2997: l2i
    //   2998: ldc_w 1334237755
    //   3001: ixor
    //   3002: ixor
    //   3003: lookupswitch default -> 3028, -458496610 -> 2986, -235757027 -> 4326
    //   3028: getstatic bigname/zprestige/webhack/util/TextUtil$1.$SwitchMap$bigname$zprestige$webhack$util$TextUtil$Color : [I
    //   3031: getstatic Perryc.c : I
    //   3034: iflt -> 3048
    //   3037: ldc2_w 194339218
    //   3040: l2i
    //   3041: ldc_w 751756472
    //   3044: ixor
    //   3045: goto -> 3056
    //   3048: ldc2_w 2069187787
    //   3051: l2i
    //   3052: ldc_w 591885562
    //   3055: ixor
    //   3056: ldc2_w 140300670
    //   3059: l2i
    //   3060: ldc_w -776748157
    //   3063: ixor
    //   3064: ixor
    //   3065: lookupswitch default -> 4354, -2114114868 -> 3092, -21719081 -> 3048
    //   3092: getstatic bigname/zprestige/webhack/util/TextUtil$Color.BLUE : Lbigname/zprestige/webhack/util/TextUtil$Color;
    //   3095: getstatic Perryc.c : I
    //   3098: iflt -> 3112
    //   3101: ldc2_w -190014727
    //   3104: l2i
    //   3105: ldc_w -1154613625
    //   3108: ixor
    //   3109: goto -> 3120
    //   3112: ldc2_w -2140015127
    //   3115: l2i
    //   3116: ldc_w 1200665129
    //   3119: ixor
    //   3120: ldc2_w -799396025
    //   3123: l2i
    //   3124: ldc_w 808926495
    //   3127: ixor
    //   3128: ixor
    //   3129: lookupswitch default -> 3156, -1343457754 -> 4320, 1943024709 -> 3112
    //   3156: invokevirtual ordinal : ()I
    //   3159: ldc2_w -140310764
    //   3162: l2i
    //   3163: ldc_w -140310760
    //   3166: ixor
    //   3167: iastore
    //   3168: goto -> 3233
    //   3171: getstatic Perryc.c : I
    //   3174: iflt -> 3188
    //   3177: ldc2_w -774136764
    //   3180: l2i
    //   3181: ldc_w -939173166
    //   3184: ixor
    //   3185: goto -> 3196
    //   3188: ldc2_w 562774897
    //   3191: l2i
    //   3192: ldc_w 550701249
    //   3195: ixor
    //   3196: ldc2_w 193027088
    //   3199: l2i
    //   3200: ldc_w 1561579965
    //   3203: ixor
    //   3204: ixor
    //   3205: lookupswitch default -> 4328, 1330400059 -> 3188, 1472906781 -> 3232
    //   3232: astore_0
    //   3233: getstatic Perryc.0 : I
    //   3236: ifle -> 3250
    //   3239: ldc2_w 1864906277
    //   3242: l2i
    //   3243: ldc_w -263209138
    //   3246: ixor
    //   3247: goto -> 3258
    //   3250: ldc2_w 1961009832
    //   3253: l2i
    //   3254: ldc_w 1527312160
    //   3257: ixor
    //   3258: ldc2_w 781429394
    //   3261: l2i
    //   3262: ldc_w 710586816
    //   3265: ixor
    //   3266: ixor
    //   3267: lookupswitch default -> 4414, -1683058119 -> 3250, 723736282 -> 3292
    //   3292: getstatic bigname/zprestige/webhack/util/TextUtil$1.$SwitchMap$bigname$zprestige$webhack$util$TextUtil$Color : [I
    //   3295: getstatic Perryc.c : I
    //   3298: iflt -> 3312
    //   3301: ldc2_w 1483939993
    //   3304: l2i
    //   3305: ldc_w 1689807267
    //   3308: ixor
    //   3309: goto -> 3320
    //   3312: ldc2_w -90981397
    //   3315: l2i
    //   3316: ldc_w 1510972977
    //   3319: ixor
    //   3320: ldc2_w 1894712428
    //   3323: l2i
    //   3324: ldc_w 1282915757
    //   3327: ixor
    //   3328: ixor
    //   3329: lookupswitch default -> 4296, -1677419493 -> 3356, 5501179 -> 3312
    //   3356: getstatic bigname/zprestige/webhack/util/TextUtil$Color.RED : Lbigname/zprestige/webhack/util/TextUtil$Color;
    //   3359: getstatic Perryc.c : I
    //   3362: iflt -> 3376
    //   3365: ldc2_w 911585788
    //   3368: l2i
    //   3369: ldc_w 1900794318
    //   3372: ixor
    //   3373: goto -> 3384
    //   3376: ldc2_w 392113155
    //   3379: l2i
    //   3380: ldc_w 1527697788
    //   3383: ixor
    //   3384: ldc2_w -591017103
    //   3387: l2i
    //   3388: ldc_w -2037077505
    //   3391: ixor
    //   3392: ixor
    //   3393: lookupswitch default -> 3420, 491717308 -> 4322, 648486083 -> 3376
    //   3420: invokevirtual ordinal : ()I
    //   3423: ldc2_w -7774574
    //   3426: l2i
    //   3427: ldc_w -7774561
    //   3430: ixor
    //   3431: iastore
    //   3432: goto -> 3497
    //   3435: getstatic Perryc.0 : I
    //   3438: ifle -> 3452
    //   3441: ldc2_w 1808074025
    //   3444: l2i
    //   3445: ldc_w -143897479
    //   3448: ixor
    //   3449: goto -> 3460
    //   3452: ldc2_w -266557130
    //   3455: l2i
    //   3456: ldc_w 628958050
    //   3459: ixor
    //   3460: ldc2_w -824895152
    //   3463: l2i
    //   3464: ldc_w 2064690043
    //   3467: ixor
    //   3468: ixor
    //   3469: lookupswitch default -> 3496, 695008123 -> 4404, 1348772584 -> 3452
    //   3496: astore_0
    //   3497: getstatic Perryc.1 : I
    //   3500: ifeq -> 3514
    //   3503: ldc2_w -1633042110
    //   3506: l2i
    //   3507: ldc_w -1888689258
    //   3510: ixor
    //   3511: goto -> 3522
    //   3514: ldc2_w 65936668
    //   3517: l2i
    //   3518: ldc_w -220725125
    //   3521: ixor
    //   3522: ldc2_w 1450764229
    //   3525: l2i
    //   3526: ldc_w 1855811325
    //   3529: ixor
    //   3530: ixor
    //   3531: lookupswitch default -> 4334, -908880801 -> 3556, 690007020 -> 3514
    //   3556: getstatic bigname/zprestige/webhack/util/TextUtil$1.$SwitchMap$bigname$zprestige$webhack$util$TextUtil$Color : [I
    //   3559: getstatic Perryc.0 : I
    //   3562: ifle -> 3576
    //   3565: ldc2_w -1087712234
    //   3568: l2i
    //   3569: ldc_w -1938389130
    //   3572: ixor
    //   3573: goto -> 3584
    //   3576: ldc2_w -2104928036
    //   3579: l2i
    //   3580: ldc_w -333590813
    //   3583: ixor
    //   3584: ldc2_w -712239660
    //   3587: l2i
    //   3588: ldc_w -1999327100
    //   3591: ixor
    //   3592: ixor
    //   3593: lookupswitch default -> 3620, 410919994 -> 3576, 1845818928 -> 4370
    //   3620: getstatic bigname/zprestige/webhack/util/TextUtil$Color.GREEN : Lbigname/zprestige/webhack/util/TextUtil$Color;
    //   3623: getstatic Perryc.c : I
    //   3626: iflt -> 3640
    //   3629: ldc2_w -1838406514
    //   3632: l2i
    //   3633: ldc_w -572327854
    //   3636: ixor
    //   3637: goto -> 3648
    //   3640: ldc2_w 2043960431
    //   3643: l2i
    //   3644: ldc_w -1226636104
    //   3647: ixor
    //   3648: ldc2_w 191770121
    //   3651: l2i
    //   3652: ldc_w -829882638
    //   3655: ixor
    //   3656: ixor
    //   3657: lookupswitch default -> 3684, -1972892633 -> 4336, -746901178 -> 3640
    //   3684: invokevirtual ordinal : ()I
    //   3687: ldc2_w -1096789816
    //   3690: l2i
    //   3691: ldc_w -1096789818
    //   3694: ixor
    //   3695: iastore
    //   3696: goto -> 3761
    //   3699: getstatic Perryc.c : I
    //   3702: iflt -> 3716
    //   3705: ldc2_w 549316082
    //   3708: l2i
    //   3709: ldc_w 1230961975
    //   3712: ixor
    //   3713: goto -> 3724
    //   3716: ldc2_w 600050158
    //   3719: l2i
    //   3720: ldc_w 1820691484
    //   3723: ixor
    //   3724: ldc2_w -854657881
    //   3727: l2i
    //   3728: ldc_w -2055080432
    //   3731: ixor
    //   3732: ixor
    //   3733: lookupswitch default -> 4380, 130975557 -> 3760, 560732786 -> 3716
    //   3760: astore_0
    //   3761: getstatic Perryc.c : I
    //   3764: iflt -> 3778
    //   3767: ldc2_w 378056812
    //   3770: l2i
    //   3771: ldc_w 2081824155
    //   3774: ixor
    //   3775: goto -> 3786
    //   3778: ldc2_w 682864018
    //   3781: l2i
    //   3782: ldc_w 1086898107
    //   3785: ixor
    //   3786: ldc2_w 315509586
    //   3789: l2i
    //   3790: ldc_w -1275441193
    //   3793: ixor
    //   3794: ixor
    //   3795: lookupswitch default -> 3820, -1966827944 -> 3778, -878007950 -> 4300
    //   3820: getstatic bigname/zprestige/webhack/util/TextUtil$1.$SwitchMap$bigname$zprestige$webhack$util$TextUtil$Color : [I
    //   3823: getstatic Perryc.0 : I
    //   3826: ifle -> 3840
    //   3829: ldc2_w 1189408782
    //   3832: l2i
    //   3833: ldc_w -1203725192
    //   3836: ixor
    //   3837: goto -> 3848
    //   3840: ldc2_w 1512570023
    //   3843: l2i
    //   3844: ldc_w 57918123
    //   3847: ixor
    //   3848: ldc2_w 1705443909
    //   3851: l2i
    //   3852: ldc_w -1567761183
    //   3855: ixor
    //   3856: ixor
    //   3857: lookupswitch default -> 4314, -1635852120 -> 3884, 965653202 -> 3840
    //   3884: getstatic bigname/zprestige/webhack/util/TextUtil$Color.LIGHT_PURPLE : Lbigname/zprestige/webhack/util/TextUtil$Color;
    //   3887: getstatic Perryc.1 : I
    //   3890: ifeq -> 3904
    //   3893: ldc2_w -594422102
    //   3896: l2i
    //   3897: ldc_w 1806690558
    //   3900: ixor
    //   3901: goto -> 3912
    //   3904: ldc2_w 1606080971
    //   3907: l2i
    //   3908: ldc_w -1349192475
    //   3911: ixor
    //   3912: ldc2_w -1241232670
    //   3915: l2i
    //   3916: ldc_w -287382538
    //   3919: ixor
    //   3920: ixor
    //   3921: lookupswitch default -> 4368, -1460370374 -> 3948, -270231744 -> 3904
    //   3948: invokevirtual ordinal : ()I
    //   3951: ldc2_w 898196486
    //   3954: l2i
    //   3955: ldc_w 898196489
    //   3958: ixor
    //   3959: iastore
    //   3960: goto -> 4025
    //   3963: getstatic Perryc.0 : I
    //   3966: ifle -> 3980
    //   3969: ldc2_w 1179173902
    //   3972: l2i
    //   3973: ldc_w -583759714
    //   3976: ixor
    //   3977: goto -> 3988
    //   3980: ldc2_w 271284347
    //   3983: l2i
    //   3984: ldc_w -406775225
    //   3987: ixor
    //   3988: ldc2_w -713327622
    //   3991: l2i
    //   3992: ldc_w -2027246965
    //   3995: ixor
    //   3996: ixor
    //   3997: lookupswitch default -> 4386, -1514425523 -> 4024, -919757343 -> 3980
    //   4024: astore_0
    //   4025: getstatic Perryc.c : I
    //   4028: iflt -> 4042
    //   4031: ldc2_w -58487910
    //   4034: l2i
    //   4035: ldc_w 1668355250
    //   4038: ixor
    //   4039: goto -> 4050
    //   4042: ldc2_w -1200560794
    //   4045: l2i
    //   4046: ldc_w -1873802723
    //   4049: ixor
    //   4050: ldc2_w -1384407687
    //   4053: l2i
    //   4054: ldc_w 488244336
    //   4057: ixor
    //   4058: ixor
    //   4059: lookupswitch default -> 4406, -1740540302 -> 4084, 798164513 -> 4042
    //   4084: getstatic bigname/zprestige/webhack/util/TextUtil$1.$SwitchMap$bigname$zprestige$webhack$util$TextUtil$Color : [I
    //   4087: getstatic Perryc.c : I
    //   4090: iflt -> 4104
    //   4093: ldc2_w 566474763
    //   4096: l2i
    //   4097: ldc_w 1415123880
    //   4100: ixor
    //   4101: goto -> 4112
    //   4104: ldc2_w -144179397
    //   4107: l2i
    //   4108: ldc_w -1017310436
    //   4111: ixor
    //   4112: ldc2_w -98087104
    //   4115: l2i
    //   4116: ldc_w 1126724341
    //   4119: ixor
    //   4120: ixor
    //   4121: lookupswitch default -> 4148, -862611946 -> 4362, 1897705721 -> 4104
    //   4148: getstatic bigname/zprestige/webhack/util/TextUtil$Color.YELLOW : Lbigname/zprestige/webhack/util/TextUtil$Color;
    //   4151: getstatic Perryc.0 : I
    //   4154: ifle -> 4168
    //   4157: ldc2_w -1731462573
    //   4160: l2i
    //   4161: ldc_w -927385485
    //   4164: ixor
    //   4165: goto -> 4176
    //   4168: ldc2_w -769543096
    //   4171: l2i
    //   4172: ldc_w -1392680563
    //   4175: ixor
    //   4176: ldc2_w 437840982
    //   4179: l2i
    //   4180: ldc_w -243653292
    //   4183: ixor
    //   4184: ixor
    //   4185: lookupswitch default -> 4212, -1182435926 -> 4168, -1156576478 -> 4316
    //   4212: invokevirtual ordinal : ()I
    //   4215: ldc2_w -194548292
    //   4218: l2i
    //   4219: ldc_w -194548308
    //   4222: ixor
    //   4223: iastore
    //   4224: goto -> 4289
    //   4227: getstatic Perryc.1 : I
    //   4230: ifeq -> 4244
    //   4233: ldc2_w -188991101
    //   4236: l2i
    //   4237: ldc_w -2064067316
    //   4240: ixor
    //   4241: goto -> 4252
    //   4244: ldc2_w 537856068
    //   4247: l2i
    //   4248: ldc_w -971272418
    //   4251: ixor
    //   4252: ldc2_w 633826781
    //   4255: l2i
    //   4256: ldc_w 737306814
    //   4259: ixor
    //   4260: ixor
    //   4261: lookupswitch default -> 4402, -400457159 -> 4288, 2121394668 -> 4244
    //   4288: astore_0
    //   4289: return
    //   4290: aconst_null
    //   4291: athrow
    //   4292: aconst_null
    //   4293: athrow
    //   4294: aconst_null
    //   4295: athrow
    //   4296: aconst_null
    //   4297: athrow
    //   4298: aconst_null
    //   4299: athrow
    //   4300: aconst_null
    //   4301: athrow
    //   4302: aconst_null
    //   4303: athrow
    //   4304: aconst_null
    //   4305: athrow
    //   4306: aconst_null
    //   4307: athrow
    //   4308: aconst_null
    //   4309: athrow
    //   4310: aconst_null
    //   4311: athrow
    //   4312: aconst_null
    //   4313: athrow
    //   4314: aconst_null
    //   4315: athrow
    //   4316: aconst_null
    //   4317: athrow
    //   4318: aconst_null
    //   4319: athrow
    //   4320: aconst_null
    //   4321: athrow
    //   4322: aconst_null
    //   4323: athrow
    //   4324: aconst_null
    //   4325: athrow
    //   4326: aconst_null
    //   4327: athrow
    //   4328: aconst_null
    //   4329: athrow
    //   4330: aconst_null
    //   4331: athrow
    //   4332: aconst_null
    //   4333: athrow
    //   4334: aconst_null
    //   4335: athrow
    //   4336: aconst_null
    //   4337: athrow
    //   4338: aconst_null
    //   4339: athrow
    //   4340: aconst_null
    //   4341: athrow
    //   4342: aconst_null
    //   4343: athrow
    //   4344: aconst_null
    //   4345: athrow
    //   4346: aconst_null
    //   4347: athrow
    //   4348: aconst_null
    //   4349: athrow
    //   4350: aconst_null
    //   4351: athrow
    //   4352: aconst_null
    //   4353: athrow
    //   4354: aconst_null
    //   4355: athrow
    //   4356: aconst_null
    //   4357: athrow
    //   4358: aconst_null
    //   4359: athrow
    //   4360: aconst_null
    //   4361: athrow
    //   4362: aconst_null
    //   4363: athrow
    //   4364: aconst_null
    //   4365: athrow
    //   4366: aconst_null
    //   4367: athrow
    //   4368: aconst_null
    //   4369: athrow
    //   4370: aconst_null
    //   4371: athrow
    //   4372: aconst_null
    //   4373: athrow
    //   4374: aconst_null
    //   4375: athrow
    //   4376: aconst_null
    //   4377: athrow
    //   4378: aconst_null
    //   4379: athrow
    //   4380: aconst_null
    //   4381: athrow
    //   4382: aconst_null
    //   4383: athrow
    //   4384: aconst_null
    //   4385: athrow
    //   4386: aconst_null
    //   4387: athrow
    //   4388: aconst_null
    //   4389: athrow
    //   4390: aconst_null
    //   4391: athrow
    //   4392: aconst_null
    //   4393: athrow
    //   4394: aconst_null
    //   4395: athrow
    //   4396: aconst_null
    //   4397: athrow
    //   4398: aconst_null
    //   4399: athrow
    //   4400: aconst_null
    //   4401: athrow
    //   4402: aconst_null
    //   4403: athrow
    //   4404: aconst_null
    //   4405: athrow
    //   4406: aconst_null
    //   4407: athrow
    //   4408: aconst_null
    //   4409: athrow
    //   4410: aconst_null
    //   4411: athrow
    //   4412: aconst_null
    //   4413: athrow
    //   4414: aconst_null
    //   4415: athrow
    //   4416: aconst_null
    //   4417: athrow
    //   4418: aconst_null
    //   4419: athrow
    //   4420: aconst_null
    //   4421: athrow
    // Exception table:
    //   from	to	target	type
    //   123	311	314	java/lang/NoSuchFieldError
    //   373	563	566	java/lang/NoSuchFieldError
    //   625	815	818	java/lang/NoSuchFieldError
    //   877	1067	1070	java/lang/NoSuchFieldError
    //   1129	1320	1323	java/lang/NoSuchFieldError
    //   1385	1584	1587	java/lang/NoSuchFieldError
    //   1649	1848	1851	java/lang/NoSuchFieldError
    //   1913	2112	2115	java/lang/NoSuchFieldError
    //   2177	2376	2379	java/lang/NoSuchFieldError
    //   2441	2640	2643	java/lang/NoSuchFieldError
    //   2705	2904	2907	java/lang/NoSuchFieldError
    //   2969	3168	3171	java/lang/NoSuchFieldError
    //   3233	3432	3435	java/lang/NoSuchFieldError
    //   3497	3696	3699	java/lang/NoSuchFieldError
    //   3761	3960	3963	java/lang/NoSuchFieldError
    //   4025	4224	4227	java/lang/NoSuchFieldError
  }
}


/* Location:              C:\Users\alex\Desktop\webhack\WebHack-0.8-obf_sussy_1.jar!\bigname\zprestige\webhac\\util\TextUtil$1.class
 * Java compiler version: 8 (52.0)
 * JD-Core Version:       1.1.3
 */