package bigname.zprestige.webhack.util;

import Perryc;

public enum TextUtil$Color {
  DARK_BLUE, RED, DARK_PURPLE, DARK_GREEN, YELLOW, GOLD, GRAY, BLACK, NONE, GREEN, DARK_RED, LIGHT_PURPLE, WHITE, AQUA, DARK_AQUA, BLUE, DARK_GRAY;
  
  public static TextUtil$Color[] $VALUES;
  
  static {
    // Byte code:
    //   0: new bigname/zprestige/webhack/util/TextUtil$Color
    //   3: dup
    //   4: ldc '寝㌼宯ㅉ'
    //   6: getstatic Perryc.0 : I
    //   9: ifle -> 22
    //   12: ldc2_w -200986837
    //   15: l2i
    //   16: ldc -179083571
    //   18: ixor
    //   19: goto -> 29
    //   22: ldc2_w -915981787
    //   25: l2i
    //   26: ldc 1961651402
    //   28: ixor
    //   29: ldc2_w -1082806321
    //   32: l2i
    //   33: ldc 154606188
    //   35: ixor
    //   36: ixor
    //   37: lookupswitch default -> 4910, -1223361467 -> 22, 197780300 -> 64
    //   64: invokestatic 0 : (Ljava/lang/String;)Ljava/lang/String;
    //   67: ldc2_w 1708790319
    //   70: l2i
    //   71: ldc 1708790319
    //   73: ixor
    //   74: getstatic Perryc.c : I
    //   77: iflt -> 90
    //   80: ldc2_w 1156507232
    //   83: l2i
    //   84: ldc 324910179
    //   86: ixor
    //   87: goto -> 97
    //   90: ldc2_w 1131408205
    //   93: l2i
    //   94: ldc -2081298422
    //   96: ixor
    //   97: ldc2_w -204558911
    //   100: l2i
    //   101: ldc -1565153873
    //   103: ixor
    //   104: ixor
    //   105: lookupswitch default -> 4816, -1847260375 -> 132, 113791597 -> 90
    //   132: invokespecial <init> : (Ljava/lang/String;I)V
    //   135: getstatic Perryc.1 : I
    //   138: ifeq -> 151
    //   141: ldc2_w 1559950813
    //   144: l2i
    //   145: ldc -1611416976
    //   147: ixor
    //   148: goto -> 158
    //   151: ldc2_w -1607573742
    //   154: l2i
    //   155: ldc 172054326
    //   157: ixor
    //   158: ldc2_w 18634751
    //   161: l2i
    //   162: ldc 598813928
    //   164: ixor
    //   165: ixor
    //   166: lookupswitch default -> 192, -509332294 -> 4802, 1468712896 -> 151
    //   192: putstatic bigname/zprestige/webhack/util/TextUtil$Color.NONE : Lbigname/zprestige/webhack/util/TextUtil$Color;
    //   195: new bigname/zprestige/webhack/util/TextUtil$Color
    //   198: dup
    //   199: ldc '寄㌻宨ㅘᮤ'
    //   201: getstatic Perryc.1 : I
    //   204: ifeq -> 217
    //   207: ldc2_w -97863438
    //   210: l2i
    //   211: ldc 1554144602
    //   213: ixor
    //   214: goto -> 224
    //   217: ldc2_w 1522124171
    //   220: l2i
    //   221: ldc -619413381
    //   223: ixor
    //   224: ldc2_w -1870444947
    //   227: l2i
    //   228: ldc 374953575
    //   230: ixor
    //   231: ixor
    //   232: lookupswitch default -> 260, -792320503 -> 217, 542307746 -> 4828
    //   260: invokestatic 0 : (Ljava/lang/String;)Ljava/lang/String;
    //   263: ldc2_w 854884768
    //   266: l2i
    //   267: ldc 854884769
    //   269: ixor
    //   270: getstatic Perryc.1 : I
    //   273: ifeq -> 286
    //   276: ldc2_w 833408472
    //   279: l2i
    //   280: ldc -2103151442
    //   282: ixor
    //   283: goto -> 293
    //   286: ldc2_w 843230228
    //   289: l2i
    //   290: ldc 2022690985
    //   292: ixor
    //   293: ldc2_w -1753058128
    //   296: l2i
    //   297: ldc 26825665
    //   299: ixor
    //   300: ixor
    //   301: lookupswitch default -> 328, -18753051 -> 286, 622042631 -> 4846
    //   328: invokespecial <init> : (Ljava/lang/String;I)V
    //   331: getstatic Perryc.1 : I
    //   334: ifeq -> 347
    //   337: ldc2_w -488900464
    //   340: l2i
    //   341: ldc -690786215
    //   343: ixor
    //   344: goto -> 354
    //   347: ldc2_w -822297441
    //   350: l2i
    //   351: ldc -155601955
    //   353: ixor
    //   354: ldc2_w -2053921241
    //   357: l2i
    //   358: ldc -697643307
    //   360: ixor
    //   361: ixor
    //   362: lookupswitch default -> 388, -1444215121 -> 347, 1743904827 -> 4864
    //   388: putstatic bigname/zprestige/webhack/util/TextUtil$Color.WHITE : Lbigname/zprestige/webhack/util/TextUtil$Color;
    //   391: new bigname/zprestige/webhack/util/TextUtil$Color
    //   394: dup
    //   395: ldc '寑㌿宠ㅏ᮪'
    //   397: getstatic Perryc.0 : I
    //   400: ifle -> 413
    //   403: ldc2_w -21023692
    //   406: l2i
    //   407: ldc -1979712382
    //   409: ixor
    //   410: goto -> 420
    //   413: ldc2_w 836868845
    //   416: l2i
    //   417: ldc -1297642542
    //   419: ixor
    //   420: ldc2_w 2129791229
    //   423: l2i
    //   424: ldc 773612792
    //   426: ixor
    //   427: ixor
    //   428: lookupswitch default -> 456, 665756851 -> 4884, 762862290 -> 413
    //   456: invokestatic 0 : (Ljava/lang/String;)Ljava/lang/String;
    //   459: ldc2_w 1838424978
    //   462: l2i
    //   463: ldc 1838424976
    //   465: ixor
    //   466: getstatic Perryc.c : I
    //   469: iflt -> 482
    //   472: ldc2_w -701981242
    //   475: l2i
    //   476: ldc -1547628338
    //   478: ixor
    //   479: goto -> 489
    //   482: ldc2_w 2034858526
    //   485: l2i
    //   486: ldc -293350110
    //   488: ixor
    //   489: ldc2_w -1285586449
    //   492: l2i
    //   493: ldc 1596990133
    //   495: ixor
    //   496: ixor
    //   497: lookupswitch default -> 524, -1719259566 -> 4912, -903424262 -> 482
    //   524: invokespecial <init> : (Ljava/lang/String;I)V
    //   527: getstatic Perryc.1 : I
    //   530: ifeq -> 543
    //   533: ldc2_w -215829416
    //   536: l2i
    //   537: ldc -2083026102
    //   539: ixor
    //   540: goto -> 550
    //   543: ldc2_w -866245984
    //   546: l2i
    //   547: ldc -62724796
    //   549: ixor
    //   550: ldc2_w 1603755872
    //   553: l2i
    //   554: ldc -959367129
    //   556: ixor
    //   557: ixor
    //   558: lookupswitch default -> 4862, -1453678429 -> 584, -374122411 -> 543
    //   584: putstatic bigname/zprestige/webhack/util/TextUtil$Color.BLACK : Lbigname/zprestige/webhack/util/TextUtil$Color;
    //   587: new bigname/zprestige/webhack/util/TextUtil$Color
    //   590: dup
    //   591: ldc '寗㌲害ㅇᮾ땭๕♳芝'
    //   593: getstatic Perryc.1 : I
    //   596: ifeq -> 609
    //   599: ldc2_w 1193525178
    //   602: l2i
    //   603: ldc -1047361141
    //   605: ixor
    //   606: goto -> 616
    //   609: ldc2_w -777530996
    //   612: l2i
    //   613: ldc -265586502
    //   615: ixor
    //   616: ldc2_w -1112601396
    //   619: l2i
    //   620: ldc 1883048177
    //   622: ixor
    //   623: ixor
    //   624: lookupswitch default -> 4900, -333533941 -> 652, 1260597772 -> 609
    //   652: invokestatic 0 : (Ljava/lang/String;)Ljava/lang/String;
    //   655: ldc2_w -803551754
    //   658: l2i
    //   659: ldc -803551755
    //   661: ixor
    //   662: getstatic Perryc.c : I
    //   665: iflt -> 678
    //   668: ldc2_w 430815908
    //   671: l2i
    //   672: ldc 921853088
    //   674: ixor
    //   675: goto -> 685
    //   678: ldc2_w 676098786
    //   681: l2i
    //   682: ldc 2125207724
    //   684: ixor
    //   685: ldc2_w 1178597168
    //   688: l2i
    //   689: ldc -676164470
    //   691: ixor
    //   692: ixor
    //   693: lookupswitch default -> 720, -1093493314 -> 4918, -132761256 -> 678
    //   720: invokespecial <init> : (Ljava/lang/String;I)V
    //   723: getstatic Perryc.1 : I
    //   726: ifeq -> 739
    //   729: ldc2_w 1443269173
    //   732: l2i
    //   733: ldc 313431714
    //   735: ixor
    //   736: goto -> 746
    //   739: ldc2_w -309325167
    //   742: l2i
    //   743: ldc -249696771
    //   745: ixor
    //   746: ldc2_w 216486903
    //   749: l2i
    //   750: ldc -1949376368
    //   752: ixor
    //   753: ixor
    //   754: lookupswitch default -> 4838, -1683731445 -> 780, -1014910992 -> 739
    //   780: putstatic bigname/zprestige/webhack/util/TextUtil$Color.DARK_BLUE : Lbigname/zprestige/webhack/util/TextUtil$Color;
    //   783: new bigname/zprestige/webhack/util/TextUtil$Color
    //   786: dup
    //   787: ldc_w '寗㌲害ㅇᮾ땨๋♣芝䝑'
    //   790: getstatic Perryc.c : I
    //   793: iflt -> 807
    //   796: ldc2_w -754514565
    //   799: l2i
    //   800: ldc_w -2071179007
    //   803: ixor
    //   804: goto -> 815
    //   807: ldc2_w -1926557709
    //   810: l2i
    //   811: ldc_w -645140289
    //   814: ixor
    //   815: ldc2_w -1077845875
    //   818: l2i
    //   819: ldc_w -1326156112
    //   822: ixor
    //   823: ixor
    //   824: lookupswitch default -> 4830, 1488863815 -> 807, 1536551281 -> 852
    //   852: invokestatic 0 : (Ljava/lang/String;)Ljava/lang/String;
    //   855: ldc2_w 1652639788
    //   858: l2i
    //   859: ldc_w 1652639784
    //   862: ixor
    //   863: getstatic Perryc.0 : I
    //   866: ifle -> 880
    //   869: ldc2_w -1681702811
    //   872: l2i
    //   873: ldc_w -1998595490
    //   876: ixor
    //   877: goto -> 888
    //   880: ldc2_w 163007881
    //   883: l2i
    //   884: ldc_w -2027903060
    //   887: ixor
    //   888: ldc2_w -435068087
    //   891: l2i
    //   892: ldc_w 1303846252
    //   895: ixor
    //   896: ixor
    //   897: lookupswitch default -> 4800, -1195711458 -> 880, 624006144 -> 924
    //   924: invokespecial <init> : (Ljava/lang/String;I)V
    //   927: getstatic Perryc.c : I
    //   930: iflt -> 944
    //   933: ldc2_w -778250626
    //   936: l2i
    //   937: ldc_w 1377673854
    //   940: ixor
    //   941: goto -> 952
    //   944: ldc2_w -2117761105
    //   947: l2i
    //   948: ldc_w 575712219
    //   951: ixor
    //   952: ldc2_w -549174033
    //   955: l2i
    //   956: ldc_w 506446766
    //   959: ixor
    //   960: ixor
    //   961: lookupswitch default -> 988, 1122693953 -> 4788, 1973460156 -> 944
    //   988: putstatic bigname/zprestige/webhack/util/TextUtil$Color.DARK_GREEN : Lbigname/zprestige/webhack/util/TextUtil$Color;
    //   991: new bigname/zprestige/webhack/util/TextUtil$Color
    //   994: dup
    //   995: ldc_w '寗㌲害ㅇᮾ땮่♳芙'
    //   998: getstatic Perryc.0 : I
    //   1001: ifle -> 1015
    //   1004: ldc2_w -454691579
    //   1007: l2i
    //   1008: ldc_w 543227680
    //   1011: ixor
    //   1012: goto -> 1023
    //   1015: ldc2_w 1170789986
    //   1018: l2i
    //   1019: ldc_w -959621910
    //   1022: ixor
    //   1023: ldc2_w 753390250
    //   1026: l2i
    //   1027: ldc_w -2034962365
    //   1030: ixor
    //   1031: ixor
    //   1032: lookupswitch default -> 4818, 693543009 -> 1060, 1859528908 -> 1015
    //   1060: invokestatic 0 : (Ljava/lang/String;)Ljava/lang/String;
    //   1063: ldc2_w -1397315749
    //   1066: l2i
    //   1067: ldc_w -1397315746
    //   1070: ixor
    //   1071: getstatic Perryc.1 : I
    //   1074: ifeq -> 1088
    //   1077: ldc2_w 697218486
    //   1080: l2i
    //   1081: ldc_w -1560680490
    //   1084: ixor
    //   1085: goto -> 1096
    //   1088: ldc2_w -745004048
    //   1091: l2i
    //   1092: ldc_w 1782201005
    //   1095: ixor
    //   1096: ldc2_w -105064233
    //   1099: l2i
    //   1100: ldc_w 2121487175
    //   1103: ixor
    //   1104: ixor
    //   1105: lookupswitch default -> 1132, -370425290 -> 1088, 213441008 -> 4868
    //   1132: invokespecial <init> : (Ljava/lang/String;I)V
    //   1135: getstatic Perryc.1 : I
    //   1138: ifeq -> 1152
    //   1141: ldc2_w -730404115
    //   1144: l2i
    //   1145: ldc_w 1067732005
    //   1148: ixor
    //   1149: goto -> 1160
    //   1152: ldc2_w -1468161509
    //   1155: l2i
    //   1156: ldc_w -44841536
    //   1159: ixor
    //   1160: ldc2_w 1358874457
    //   1163: l2i
    //   1164: ldc_w -1043900570
    //   1167: ixor
    //   1168: ixor
    //   1169: lookupswitch default -> 4832, -1005062172 -> 1196, 2062235383 -> 1152
    //   1196: putstatic bigname/zprestige/webhack/util/TextUtil$Color.DARK_AQUA : Lbigname/zprestige/webhack/util/TextUtil$Color;
    //   1199: new bigname/zprestige/webhack/util/TextUtil$Color
    //   1202: dup
    //   1203: ldc_w '寗㌲害ㅇᮾ땽๜♢'
    //   1206: getstatic Perryc.c : I
    //   1209: iflt -> 1223
    //   1212: ldc2_w 672928997
    //   1215: l2i
    //   1216: ldc_w 723840708
    //   1219: ixor
    //   1220: goto -> 1231
    //   1223: ldc2_w -984676869
    //   1226: l2i
    //   1227: ldc_w -1493234851
    //   1230: ixor
    //   1231: ldc2_w -2065236180
    //   1234: l2i
    //   1235: ldc_w 1645337721
    //   1238: ixor
    //   1239: ixor
    //   1240: lookupswitch default -> 4858, -2058932749 -> 1268, -439363212 -> 1223
    //   1268: invokestatic 0 : (Ljava/lang/String;)Ljava/lang/String;
    //   1271: ldc2_w -673804097
    //   1274: l2i
    //   1275: ldc_w -673804103
    //   1278: ixor
    //   1279: getstatic Perryc.0 : I
    //   1282: ifle -> 1296
    //   1285: ldc2_w 1600878522
    //   1288: l2i
    //   1289: ldc_w -1771699182
    //   1292: ixor
    //   1293: goto -> 1304
    //   1296: ldc2_w -1952495272
    //   1299: l2i
    //   1300: ldc_w 1247325668
    //   1303: ixor
    //   1304: ldc2_w -1240539612
    //   1307: l2i
    //   1308: ldc_w -117289657
    //   1311: ixor
    //   1312: ixor
    //   1313: lookupswitch default -> 4824, -2046697269 -> 1296, -1899268129 -> 1340
    //   1340: invokespecial <init> : (Ljava/lang/String;I)V
    //   1343: getstatic Perryc.0 : I
    //   1346: ifle -> 1360
    //   1349: ldc2_w 1684489939
    //   1352: l2i
    //   1353: ldc_w 370870720
    //   1356: ixor
    //   1357: goto -> 1368
    //   1360: ldc2_w 225264198
    //   1363: l2i
    //   1364: ldc_w 2010948759
    //   1367: ixor
    //   1368: ldc2_w -1084391824
    //   1371: l2i
    //   1372: ldc_w -193290792
    //   1375: ixor
    //   1376: ixor
    //   1377: lookupswitch default -> 1404, -337563499 -> 1360, 962309307 -> 4860
    //   1404: putstatic bigname/zprestige/webhack/util/TextUtil$Color.DARK_RED : Lbigname/zprestige/webhack/util/TextUtil$Color;
    //   1407: new bigname/zprestige/webhack/util/TextUtil$Color
    //   1410: dup
    //   1411: ldc_w '寗㌲害ㅇᮾ땿์♴芈䝓'
    //   1414: getstatic Perryc.c : I
    //   1417: iflt -> 1431
    //   1420: ldc2_w -852110499
    //   1423: l2i
    //   1424: ldc_w 25647580
    //   1427: ixor
    //   1428: goto -> 1439
    //   1431: ldc2_w 487012927
    //   1434: l2i
    //   1435: ldc_w 2111464321
    //   1438: ixor
    //   1439: ldc2_w 802350034
    //   1442: l2i
    //   1443: ldc_w 1451158355
    //   1446: ixor
    //   1447: ixor
    //   1448: lookupswitch default -> 1476, -1328805579 -> 1431, -1256291840 -> 4886
    //   1476: invokestatic 0 : (Ljava/lang/String;)Ljava/lang/String;
    //   1479: ldc2_w 321206560
    //   1482: l2i
    //   1483: ldc_w 321206567
    //   1486: ixor
    //   1487: getstatic Perryc.0 : I
    //   1490: ifle -> 1504
    //   1493: ldc2_w -1534918088
    //   1496: l2i
    //   1497: ldc_w -1887529051
    //   1500: ixor
    //   1501: goto -> 1512
    //   1504: ldc2_w 1610266042
    //   1507: l2i
    //   1508: ldc_w 1188703470
    //   1511: ixor
    //   1512: ldc2_w 1661910329
    //   1515: l2i
    //   1516: ldc_w 1238678917
    //   1519: ixor
    //   1520: ixor
    //   1521: lookupswitch default -> 1548, -1807921469 -> 1504, 19371297 -> 4852
    //   1548: invokespecial <init> : (Ljava/lang/String;I)V
    //   1551: getstatic Perryc.0 : I
    //   1554: ifle -> 1568
    //   1557: ldc2_w 1092483718
    //   1560: l2i
    //   1561: ldc_w -1872531782
    //   1564: ixor
    //   1565: goto -> 1576
    //   1568: ldc2_w 1302779642
    //   1571: l2i
    //   1572: ldc_w 1096928224
    //   1575: ixor
    //   1576: ldc2_w -561430257
    //   1579: l2i
    //   1580: ldc_w -912147857
    //   1583: ixor
    //   1584: ixor
    //   1585: lookupswitch default -> 4872, -967413924 -> 1568, 468706938 -> 1612
    //   1612: putstatic bigname/zprestige/webhack/util/TextUtil$Color.DARK_PURPLE : Lbigname/zprestige/webhack/util/TextUtil$Color;
    //   1615: new bigname/zprestige/webhack/util/TextUtil$Color
    //   1618: dup
    //   1619: ldc_w '寔㌼宭ㅈ'
    //   1622: getstatic Perryc.0 : I
    //   1625: ifle -> 1639
    //   1628: ldc2_w 1314660323
    //   1631: l2i
    //   1632: ldc_w -648158215
    //   1635: ixor
    //   1636: goto -> 1647
    //   1639: ldc2_w -169211940
    //   1642: l2i
    //   1643: ldc_w -274620700
    //   1646: ixor
    //   1647: ldc2_w 725553137
    //   1650: l2i
    //   1651: ldc_w -1252362824
    //   1654: ixor
    //   1655: ixor
    //   1656: lookupswitch default -> 4878, -2077301903 -> 1684, 157582931 -> 1639
    //   1684: invokestatic 0 : (Ljava/lang/String;)Ljava/lang/String;
    //   1687: ldc2_w 1035247918
    //   1690: l2i
    //   1691: ldc_w 1035247910
    //   1694: ixor
    //   1695: getstatic Perryc.0 : I
    //   1698: ifle -> 1712
    //   1701: ldc2_w -779031910
    //   1704: l2i
    //   1705: ldc_w -984565188
    //   1708: ixor
    //   1709: goto -> 1720
    //   1712: ldc2_w 1484224351
    //   1715: l2i
    //   1716: ldc_w -1344331524
    //   1719: ixor
    //   1720: ldc2_w -980820739
    //   1723: l2i
    //   1724: ldc_w -1214874901
    //   1727: ixor
    //   1728: ixor
    //   1729: lookupswitch default -> 4840, -2051542603 -> 1756, 1725953712 -> 1712
    //   1756: invokespecial <init> : (Ljava/lang/String;I)V
    //   1759: getstatic Perryc.c : I
    //   1762: iflt -> 1776
    //   1765: ldc2_w -579680387
    //   1768: l2i
    //   1769: ldc_w 1313103120
    //   1772: ixor
    //   1773: goto -> 1784
    //   1776: ldc2_w -79244027
    //   1779: l2i
    //   1780: ldc_w -821695533
    //   1783: ixor
    //   1784: ldc2_w 981995725
    //   1787: l2i
    //   1788: ldc_w -1782000664
    //   1791: ixor
    //   1792: ixor
    //   1793: lookupswitch default -> 1820, -796239370 -> 1776, 1014389064 -> 4854
    //   1820: putstatic bigname/zprestige/webhack/util/TextUtil$Color.GOLD : Lbigname/zprestige/webhack/util/TextUtil$Color;
    //   1823: new bigname/zprestige/webhack/util/TextUtil$Color
    //   1826: dup
    //   1827: ldc_w '寔㌡宠ㅕ'
    //   1830: getstatic Perryc.c : I
    //   1833: iflt -> 1847
    //   1836: ldc2_w 577678699
    //   1839: l2i
    //   1840: ldc_w -434270111
    //   1843: ixor
    //   1844: goto -> 1855
    //   1847: ldc2_w -36840183
    //   1850: l2i
    //   1851: ldc_w 972412258
    //   1854: ixor
    //   1855: ldc2_w -1561332631
    //   1858: l2i
    //   1859: ldc_w -983926145
    //   1862: ixor
    //   1863: ixor
    //   1864: lookupswitch default -> 4870, -1551006083 -> 1892, -1547259108 -> 1847
    //   1892: invokestatic 0 : (Ljava/lang/String;)Ljava/lang/String;
    //   1895: ldc2_w -994299896
    //   1898: l2i
    //   1899: ldc_w -994299903
    //   1902: ixor
    //   1903: getstatic Perryc.1 : I
    //   1906: ifeq -> 1920
    //   1909: ldc2_w -83984967
    //   1912: l2i
    //   1913: ldc_w -791680360
    //   1916: ixor
    //   1917: goto -> 1928
    //   1920: ldc2_w -563519950
    //   1923: l2i
    //   1924: ldc_w -1993721046
    //   1927: ixor
    //   1928: ldc2_w -1050299951
    //   1931: l2i
    //   1932: ldc_w -816938383
    //   1935: ixor
    //   1936: ixor
    //   1937: lookupswitch default -> 1964, -2002801375 -> 1920, 605725825 -> 4880
    //   1964: invokespecial <init> : (Ljava/lang/String;I)V
    //   1967: getstatic Perryc.c : I
    //   1970: iflt -> 1984
    //   1973: ldc2_w 172785985
    //   1976: l2i
    //   1977: ldc_w -1009546676
    //   1980: ixor
    //   1981: goto -> 1992
    //   1984: ldc2_w 11025146
    //   1987: l2i
    //   1988: ldc_w -627647748
    //   1991: ixor
    //   1992: ldc2_w 383369
    //   1995: l2i
    //   1996: ldc_w -219387713
    //   1999: ixor
    //   2000: ixor
    //   2001: lookupswitch default -> 2028, -1059645713 -> 1984, 997636667 -> 4806
    //   2028: putstatic bigname/zprestige/webhack/util/TextUtil$Color.GRAY : Lbigname/zprestige/webhack/util/TextUtil$Color;
    //   2031: new bigname/zprestige/webhack/util/TextUtil$Color
    //   2034: dup
    //   2035: ldc_w '寗㌲害ㅇᮾ땨๋♧芁'
    //   2038: getstatic Perryc.0 : I
    //   2041: ifle -> 2055
    //   2044: ldc2_w -2128566864
    //   2047: l2i
    //   2048: ldc_w 2117402369
    //   2051: ixor
    //   2052: goto -> 2063
    //   2055: ldc2_w 616783775
    //   2058: l2i
    //   2059: ldc_w 622720032
    //   2062: ixor
    //   2063: ldc2_w -1469928354
    //   2066: l2i
    //   2067: ldc_w 461440249
    //   2070: ixor
    //   2071: ixor
    //   2072: lookupswitch default -> 4902, -1304624360 -> 2100, 1291317782 -> 2055
    //   2100: invokestatic 0 : (Ljava/lang/String;)Ljava/lang/String;
    //   2103: ldc2_w -2051382011
    //   2106: l2i
    //   2107: ldc_w -2051382001
    //   2110: ixor
    //   2111: getstatic Perryc.1 : I
    //   2114: ifeq -> 2128
    //   2117: ldc2_w -798232802
    //   2120: l2i
    //   2121: ldc_w -1276581714
    //   2124: ixor
    //   2125: goto -> 2136
    //   2128: ldc2_w 1864584926
    //   2131: l2i
    //   2132: ldc_w -2012260330
    //   2135: ixor
    //   2136: ldc2_w -495352768
    //   2139: l2i
    //   2140: ldc_w -2022406477
    //   2143: ixor
    //   2144: ixor
    //   2145: lookupswitch default -> 4792, -2111761349 -> 2172, 109970755 -> 2128
    //   2172: invokespecial <init> : (Ljava/lang/String;I)V
    //   2175: getstatic Perryc.1 : I
    //   2178: ifeq -> 2192
    //   2181: ldc2_w 878436022
    //   2184: l2i
    //   2185: ldc_w -337615371
    //   2188: ixor
    //   2189: goto -> 2200
    //   2192: ldc2_w -1839242481
    //   2195: l2i
    //   2196: ldc_w 1089687654
    //   2199: ixor
    //   2200: ldc2_w -1265025348
    //   2203: l2i
    //   2204: ldc_w 1636260434
    //   2207: ixor
    //   2208: ixor
    //   2209: lookupswitch default -> 4848, 129128327 -> 2236, 178642861 -> 2192
    //   2236: putstatic bigname/zprestige/webhack/util/TextUtil$Color.DARK_GRAY : Lbigname/zprestige/webhack/util/TextUtil$Color;
    //   2239: new bigname/zprestige/webhack/util/TextUtil$Color
    //   2242: dup
    //   2243: ldc_w '寑㌿宴ㅉ'
    //   2246: getstatic Perryc.0 : I
    //   2249: ifle -> 2263
    //   2252: ldc2_w -280538885
    //   2255: l2i
    //   2256: ldc_w 1456299621
    //   2259: ixor
    //   2260: goto -> 2271
    //   2263: ldc2_w 1017752517
    //   2266: l2i
    //   2267: ldc_w -1514844818
    //   2270: ixor
    //   2271: ldc2_w -1477000041
    //   2274: l2i
    //   2275: ldc_w 1457916920
    //   2278: ixor
    //   2279: ixor
    //   2280: lookupswitch default -> 4796, 1218101745 -> 2263, 1745627588 -> 2308
    //   2308: invokestatic 0 : (Ljava/lang/String;)Ljava/lang/String;
    //   2311: ldc2_w 380081373
    //   2314: l2i
    //   2315: ldc_w 380081366
    //   2318: ixor
    //   2319: getstatic Perryc.c : I
    //   2322: iflt -> 2336
    //   2325: ldc2_w -863647226
    //   2328: l2i
    //   2329: ldc_w -1039455240
    //   2332: ixor
    //   2333: goto -> 2344
    //   2336: ldc2_w 711249555
    //   2339: l2i
    //   2340: ldc_w 540026606
    //   2343: ixor
    //   2344: ldc2_w -1283998705
    //   2347: l2i
    //   2348: ldc_w 307994693
    //   2351: ixor
    //   2352: ixor
    //   2353: lookupswitch default -> 2380, -1348272716 -> 4822, -204990198 -> 2336
    //   2380: invokespecial <init> : (Ljava/lang/String;I)V
    //   2383: getstatic Perryc.1 : I
    //   2386: ifeq -> 2400
    //   2389: ldc2_w 1380654801
    //   2392: l2i
    //   2393: ldc_w 1516309104
    //   2396: ixor
    //   2397: goto -> 2408
    //   2400: ldc2_w -9275848
    //   2403: l2i
    //   2404: ldc_w 1595284712
    //   2407: ixor
    //   2408: ldc2_w 722973594
    //   2411: l2i
    //   2412: ldc_w 1179661711
    //   2415: ixor
    //   2416: ixor
    //   2417: lookupswitch default -> 2444, 338434339 -> 2400, 1701679796 -> 4894
    //   2444: putstatic bigname/zprestige/webhack/util/TextUtil$Color.BLUE : Lbigname/zprestige/webhack/util/TextUtil$Color;
    //   2447: new bigname/zprestige/webhack/util/TextUtil$Color
    //   2450: dup
    //   2451: ldc_w '寔㌡室ㅉᮯ'
    //   2454: getstatic Perryc.0 : I
    //   2457: ifle -> 2471
    //   2460: ldc2_w -654890629
    //   2463: l2i
    //   2464: ldc_w 1166998441
    //   2467: ixor
    //   2468: goto -> 2479
    //   2471: ldc2_w -291931121
    //   2474: l2i
    //   2475: ldc_w -1494304557
    //   2478: ixor
    //   2479: ldc2_w -374309513
    //   2482: l2i
    //   2483: ldc_w 795951320
    //   2486: ixor
    //   2487: ixor
    //   2488: lookupswitch default -> 2516, 74889472 -> 2471, 1538846589 -> 4920
    //   2516: invokestatic 0 : (Ljava/lang/String;)Ljava/lang/String;
    //   2519: ldc2_w 1117297663
    //   2522: l2i
    //   2523: ldc_w 1117297651
    //   2526: ixor
    //   2527: getstatic Perryc.1 : I
    //   2530: ifeq -> 2544
    //   2533: ldc2_w -1846357056
    //   2536: l2i
    //   2537: ldc_w -516064328
    //   2540: ixor
    //   2541: goto -> 2552
    //   2544: ldc2_w -1997832332
    //   2547: l2i
    //   2548: ldc_w -1467972980
    //   2551: ixor
    //   2552: ldc2_w -1155770574
    //   2555: l2i
    //   2556: ldc_w -886504056
    //   2559: ixor
    //   2560: ixor
    //   2561: lookupswitch default -> 2588, 16448194 -> 4810, 1520562495 -> 2544
    //   2588: invokespecial <init> : (Ljava/lang/String;I)V
    //   2591: getstatic Perryc.0 : I
    //   2594: ifle -> 2608
    //   2597: ldc2_w 171589260
    //   2600: l2i
    //   2601: ldc_w 838382570
    //   2604: ixor
    //   2605: goto -> 2616
    //   2608: ldc2_w -475089936
    //   2611: l2i
    //   2612: ldc_w -1402569795
    //   2615: ixor
    //   2616: ldc2_w -689741808
    //   2619: l2i
    //   2620: ldc_w 1254496183
    //   2623: ixor
    //   2624: ixor
    //   2625: lookupswitch default -> 2652, -1477969215 -> 4896, 1755463194 -> 2608
    //   2652: putstatic bigname/zprestige/webhack/util/TextUtil$Color.GREEN : Lbigname/zprestige/webhack/util/TextUtil$Color;
    //   2655: new bigname/zprestige/webhack/util/TextUtil$Color
    //   2658: dup
    //   2659: ldc_w '寒㌢宴ㅍ'
    //   2662: getstatic Perryc.0 : I
    //   2665: ifle -> 2679
    //   2668: ldc2_w -368304078
    //   2671: l2i
    //   2672: ldc_w -1213866908
    //   2675: ixor
    //   2676: goto -> 2687
    //   2679: ldc2_w -2005755353
    //   2682: l2i
    //   2683: ldc_w 1375762251
    //   2686: ixor
    //   2687: ldc2_w -507978650
    //   2690: l2i
    //   2691: ldc_w 2141695965
    //   2694: ixor
    //   2695: ixor
    //   2696: lookupswitch default -> 4808, -1011445779 -> 2679, 1148034775 -> 2724
    //   2724: invokestatic 0 : (Ljava/lang/String;)Ljava/lang/String;
    //   2727: ldc2_w -647978764
    //   2730: l2i
    //   2731: ldc_w -647978759
    //   2734: ixor
    //   2735: getstatic Perryc.0 : I
    //   2738: ifle -> 2752
    //   2741: ldc2_w -1530207770
    //   2744: l2i
    //   2745: ldc_w 813865190
    //   2748: ixor
    //   2749: goto -> 2760
    //   2752: ldc2_w -1313177431
    //   2755: l2i
    //   2756: ldc_w -344356898
    //   2759: ixor
    //   2760: ldc2_w 1571309959
    //   2763: l2i
    //   2764: ldc_w -402560922
    //   2767: ixor
    //   2768: ixor
    //   2769: lookupswitch default -> 2796, -1730581216 -> 2752, 568416481 -> 4892
    //   2796: invokespecial <init> : (Ljava/lang/String;I)V
    //   2799: getstatic Perryc.0 : I
    //   2802: ifle -> 2816
    //   2805: ldc2_w 549755240
    //   2808: l2i
    //   2809: ldc_w -1415715432
    //   2812: ixor
    //   2813: goto -> 2824
    //   2816: ldc2_w -1170550298
    //   2819: l2i
    //   2820: ldc_w -1138416690
    //   2823: ixor
    //   2824: ldc2_w -1662683772
    //   2827: l2i
    //   2828: ldc_w -2058241563
    //   2831: ixor
    //   2832: ixor
    //   2833: lookupswitch default -> 2860, -1829916527 -> 4804, -620890087 -> 2816
    //   2860: putstatic bigname/zprestige/webhack/util/TextUtil$Color.AQUA : Lbigname/zprestige/webhack/util/TextUtil$Color;
    //   2863: new bigname/zprestige/webhack/util/TextUtil$Color
    //   2866: dup
    //   2867: ldc_w '寁㌶宥'
    //   2870: getstatic Perryc.0 : I
    //   2873: ifle -> 2887
    //   2876: ldc2_w -1867442875
    //   2879: l2i
    //   2880: ldc_w -2070393820
    //   2883: ixor
    //   2884: goto -> 2895
    //   2887: ldc2_w 608608015
    //   2890: l2i
    //   2891: ldc_w 1330737665
    //   2894: ixor
    //   2895: ldc2_w 923990324
    //   2898: l2i
    //   2899: ldc_w 1611367395
    //   2902: ixor
    //   2903: ixor
    //   2904: lookupswitch default -> 4856, 1007589337 -> 2932, 1127228342 -> 2887
    //   2932: invokestatic 0 : (Ljava/lang/String;)Ljava/lang/String;
    //   2935: ldc2_w -1039729433
    //   2938: l2i
    //   2939: ldc_w -1039729431
    //   2942: ixor
    //   2943: getstatic Perryc.1 : I
    //   2946: ifeq -> 2960
    //   2949: ldc2_w 1579534627
    //   2952: l2i
    //   2953: ldc_w 1796230817
    //   2956: ixor
    //   2957: goto -> 2968
    //   2960: ldc2_w 1688003308
    //   2963: l2i
    //   2964: ldc_w -654291533
    //   2967: ixor
    //   2968: ldc2_w -760073833
    //   2971: l2i
    //   2972: ldc_w -1546634336
    //   2975: ixor
    //   2976: ixor
    //   2977: lookupswitch default -> 4850, -855726744 -> 3004, 1146588597 -> 2960
    //   3004: invokespecial <init> : (Ljava/lang/String;I)V
    //   3007: getstatic Perryc.1 : I
    //   3010: ifeq -> 3024
    //   3013: ldc2_w 1146888150
    //   3016: l2i
    //   3017: ldc_w 2025013052
    //   3020: ixor
    //   3021: goto -> 3032
    //   3024: ldc2_w -1195110966
    //   3027: l2i
    //   3028: ldc_w 1167771692
    //   3031: ixor
    //   3032: ldc2_w 1436076608
    //   3035: l2i
    //   3036: ldc_w -209751969
    //   3039: ixor
    //   3040: ixor
    //   3041: lookupswitch default -> 3068, -1710712075 -> 4906, -744673783 -> 3024
    //   3068: putstatic bigname/zprestige/webhack/util/TextUtil$Color.RED : Lbigname/zprestige/webhack/util/TextUtil$Color;
    //   3071: new bigname/zprestige/webhack/util/TextUtil$Color
    //   3074: dup
    //   3075: ldc_w '察㌺宦ㅄ᮵땰้♳芊䝏ਂ'
    //   3078: getstatic Perryc.1 : I
    //   3081: ifeq -> 3095
    //   3084: ldc2_w -723242471
    //   3087: l2i
    //   3088: ldc_w -1849165600
    //   3091: ixor
    //   3092: goto -> 3103
    //   3095: ldc2_w -1863508376
    //   3098: l2i
    //   3099: ldc_w 767925435
    //   3102: ixor
    //   3103: ldc2_w 1568680441
    //   3106: l2i
    //   3107: ldc_w 1959231616
    //   3110: ixor
    //   3111: ixor
    //   3112: lookupswitch default -> 4794, -1804653654 -> 3140, 1818518400 -> 3095
    //   3140: invokestatic 0 : (Ljava/lang/String;)Ljava/lang/String;
    //   3143: ldc2_w -816640619
    //   3146: l2i
    //   3147: ldc_w -816640614
    //   3150: ixor
    //   3151: getstatic Perryc.c : I
    //   3154: iflt -> 3168
    //   3157: ldc2_w 1302260526
    //   3160: l2i
    //   3161: ldc_w 326447738
    //   3164: ixor
    //   3165: goto -> 3176
    //   3168: ldc2_w 1971419227
    //   3171: l2i
    //   3172: ldc_w 597647101
    //   3175: ixor
    //   3176: ldc2_w 1786020484
    //   3179: l2i
    //   3180: ldc_w -1497400986
    //   3183: ixor
    //   3184: ixor
    //   3185: lookupswitch default -> 3212, -2090329083 -> 3168, -1843387722 -> 4914
    //   3212: invokespecial <init> : (Ljava/lang/String;I)V
    //   3215: getstatic Perryc.c : I
    //   3218: iflt -> 3232
    //   3221: ldc2_w -1456732374
    //   3224: l2i
    //   3225: ldc_w 718192791
    //   3228: ixor
    //   3229: goto -> 3240
    //   3232: ldc2_w 981970433
    //   3235: l2i
    //   3236: ldc_w -1794589221
    //   3239: ixor
    //   3240: ldc2_w -670236611
    //   3243: l2i
    //   3244: ldc_w 1435485801
    //   3247: ixor
    //   3248: ixor
    //   3249: lookupswitch default -> 4888, 241172969 -> 3232, 571331982 -> 3276
    //   3276: putstatic bigname/zprestige/webhack/util/TextUtil$Color.LIGHT_PURPLE : Lbigname/zprestige/webhack/util/TextUtil$Color;
    //   3279: new bigname/zprestige/webhack/util/TextUtil$Color
    //   3282: dup
    //   3283: ldc_w '寊㌶宭ㅀᮮ땸'
    //   3286: getstatic Perryc.0 : I
    //   3289: ifle -> 3303
    //   3292: ldc2_w 1677189395
    //   3295: l2i
    //   3296: ldc_w -787607300
    //   3299: ixor
    //   3300: goto -> 3311
    //   3303: ldc2_w -769032838
    //   3306: l2i
    //   3307: ldc_w -1645448343
    //   3310: ixor
    //   3311: ldc2_w 937865016
    //   3314: l2i
    //   3315: ldc_w -1803234518
    //   3318: ixor
    //   3319: ixor
    //   3320: lookupswitch default -> 4890, -324570623 -> 3348, 295407101 -> 3303
    //   3348: invokestatic 0 : (Ljava/lang/String;)Ljava/lang/String;
    //   3351: ldc2_w 587117364
    //   3354: l2i
    //   3355: ldc_w 587117348
    //   3358: ixor
    //   3359: getstatic Perryc.c : I
    //   3362: iflt -> 3376
    //   3365: ldc2_w 1700665849
    //   3368: l2i
    //   3369: ldc_w -241719355
    //   3372: ixor
    //   3373: goto -> 3384
    //   3376: ldc2_w -398072535
    //   3379: l2i
    //   3380: ldc_w -270871826
    //   3383: ixor
    //   3384: ldc2_w -182601981
    //   3387: l2i
    //   3388: ldc_w 129080110
    //   3391: ixor
    //   3392: ixor
    //   3393: lookupswitch default -> 4916, -181199894 -> 3420, 1717932561 -> 3376
    //   3420: invokespecial <init> : (Ljava/lang/String;I)V
    //   3423: getstatic Perryc.0 : I
    //   3426: ifle -> 3440
    //   3429: ldc2_w 1799670340
    //   3432: l2i
    //   3433: ldc_w 1865565443
    //   3436: ixor
    //   3437: goto -> 3448
    //   3440: ldc2_w 1054497582
    //   3443: l2i
    //   3444: ldc_w -2038451910
    //   3447: ixor
    //   3448: ldc2_w 1695430444
    //   3451: l2i
    //   3452: ldc_w -90009245
    //   3455: ixor
    //   3456: ixor
    //   3457: lookupswitch default -> 4866, -1680201464 -> 3440, 654920795 -> 3484
    //   3484: putstatic bigname/zprestige/webhack/util/TextUtil$Color.YELLOW : Lbigname/zprestige/webhack/util/TextUtil$Color;
    //   3487: ldc2_w 1282419868
    //   3490: l2i
    //   3491: ldc_w 1282419853
    //   3494: ixor
    //   3495: anewarray bigname/zprestige/webhack/util/TextUtil$Color
    //   3498: dup
    //   3499: ldc2_w -1406093553
    //   3502: l2i
    //   3503: ldc_w -1406093553
    //   3506: ixor
    //   3507: getstatic Perryc.0 : I
    //   3510: ifle -> 3524
    //   3513: ldc2_w 1057716913
    //   3516: l2i
    //   3517: ldc_w 8694088
    //   3520: ixor
    //   3521: goto -> 3532
    //   3524: ldc2_w -397803578
    //   3527: l2i
    //   3528: ldc_w 1183255078
    //   3531: ixor
    //   3532: ldc2_w 785443232
    //   3535: l2i
    //   3536: ldc_w -2016612343
    //   3539: ixor
    //   3540: ixor
    //   3541: lookupswitch default -> 3568, -1768699312 -> 4790, -1682434532 -> 3524
    //   3568: getstatic bigname/zprestige/webhack/util/TextUtil$Color.NONE : Lbigname/zprestige/webhack/util/TextUtil$Color;
    //   3571: aastore
    //   3572: dup
    //   3573: ldc2_w 104103387
    //   3576: l2i
    //   3577: ldc_w 104103386
    //   3580: ixor
    //   3581: getstatic Perryc.0 : I
    //   3584: ifle -> 3598
    //   3587: ldc2_w 1601347256
    //   3590: l2i
    //   3591: ldc_w -838004617
    //   3594: ixor
    //   3595: goto -> 3606
    //   3598: ldc2_w 1193142691
    //   3601: l2i
    //   3602: ldc_w 331159227
    //   3605: ixor
    //   3606: ldc2_w 127173474
    //   3609: l2i
    //   3610: ldc_w 637934846
    //   3613: ixor
    //   3614: ixor
    //   3615: lookupswitch default -> 3640, -1400909110 -> 3598, -1326640813 -> 4898
    //   3640: getstatic bigname/zprestige/webhack/util/TextUtil$Color.WHITE : Lbigname/zprestige/webhack/util/TextUtil$Color;
    //   3643: aastore
    //   3644: dup
    //   3645: ldc2_w 461445681
    //   3648: l2i
    //   3649: ldc_w 461445683
    //   3652: ixor
    //   3653: getstatic Perryc.0 : I
    //   3656: ifle -> 3670
    //   3659: ldc2_w -970268493
    //   3662: l2i
    //   3663: ldc_w 2030903292
    //   3666: ixor
    //   3667: goto -> 3678
    //   3670: ldc2_w -1399993250
    //   3673: l2i
    //   3674: ldc_w -1325186869
    //   3677: ixor
    //   3678: ldc2_w -2144982337
    //   3681: l2i
    //   3682: ldc_w -1996654947
    //   3685: ixor
    //   3686: ixor
    //   3687: lookupswitch default -> 3712, -1622540032 -> 3670, -1208179859 -> 4904
    //   3712: getstatic bigname/zprestige/webhack/util/TextUtil$Color.BLACK : Lbigname/zprestige/webhack/util/TextUtil$Color;
    //   3715: aastore
    //   3716: dup
    //   3717: ldc2_w 1782504541
    //   3720: l2i
    //   3721: ldc_w 1782504542
    //   3724: ixor
    //   3725: getstatic Perryc.0 : I
    //   3728: ifle -> 3742
    //   3731: ldc2_w 1808812818
    //   3734: l2i
    //   3735: ldc_w 1876478346
    //   3738: ixor
    //   3739: goto -> 3750
    //   3742: ldc2_w -352231945
    //   3745: l2i
    //   3746: ldc_w -1862561567
    //   3749: ixor
    //   3750: ldc2_w 1282677634
    //   3753: l2i
    //   3754: ldc_w -53441249
    //   3757: ixor
    //   3758: ixor
    //   3759: lookupswitch default -> 4798, -1263791099 -> 3742, -883008629 -> 3784
    //   3784: getstatic bigname/zprestige/webhack/util/TextUtil$Color.DARK_BLUE : Lbigname/zprestige/webhack/util/TextUtil$Color;
    //   3787: aastore
    //   3788: dup
    //   3789: ldc2_w -1280973110
    //   3792: l2i
    //   3793: ldc_w -1280973106
    //   3796: ixor
    //   3797: getstatic Perryc.c : I
    //   3800: iflt -> 3814
    //   3803: ldc2_w 67166742
    //   3806: l2i
    //   3807: ldc_w -1229015473
    //   3810: ixor
    //   3811: goto -> 3822
    //   3814: ldc2_w 1173708404
    //   3817: l2i
    //   3818: ldc_w -1715728146
    //   3821: ixor
    //   3822: ldc2_w 1872314422
    //   3825: l2i
    //   3826: ldc_w 864496950
    //   3829: ixor
    //   3830: ixor
    //   3831: lookupswitch default -> 3856, -1908565912 -> 3814, -291489447 -> 4924
    //   3856: getstatic bigname/zprestige/webhack/util/TextUtil$Color.DARK_GREEN : Lbigname/zprestige/webhack/util/TextUtil$Color;
    //   3859: aastore
    //   3860: dup
    //   3861: ldc2_w -1621303975
    //   3864: l2i
    //   3865: ldc_w -1621303972
    //   3868: ixor
    //   3869: getstatic Perryc.1 : I
    //   3872: ifeq -> 3886
    //   3875: ldc2_w -495016641
    //   3878: l2i
    //   3879: ldc_w -386758100
    //   3882: ixor
    //   3883: goto -> 3894
    //   3886: ldc2_w -920133796
    //   3889: l2i
    //   3890: ldc_w 1631009103
    //   3893: ixor
    //   3894: ldc2_w -1306800134
    //   3897: l2i
    //   3898: ldc_w -1148659416
    //   3901: ixor
    //   3902: ixor
    //   3903: lookupswitch default -> 3928, -757501345 -> 3886, 52378049 -> 4814
    //   3928: getstatic bigname/zprestige/webhack/util/TextUtil$Color.DARK_AQUA : Lbigname/zprestige/webhack/util/TextUtil$Color;
    //   3931: aastore
    //   3932: dup
    //   3933: ldc2_w 1865055254
    //   3936: l2i
    //   3937: ldc_w 1865055248
    //   3940: ixor
    //   3941: getstatic Perryc.0 : I
    //   3944: ifle -> 3958
    //   3947: ldc2_w -1178667680
    //   3950: l2i
    //   3951: ldc_w 217960310
    //   3954: ixor
    //   3955: goto -> 3966
    //   3958: ldc2_w -76367725
    //   3961: l2i
    //   3962: ldc_w -1751610537
    //   3965: ixor
    //   3966: ldc2_w 662845520
    //   3969: l2i
    //   3970: ldc_w 1219665381
    //   3973: ixor
    //   3974: ixor
    //   3975: lookupswitch default -> 4882, -629956701 -> 3958, 64657009 -> 4000
    //   4000: getstatic bigname/zprestige/webhack/util/TextUtil$Color.DARK_RED : Lbigname/zprestige/webhack/util/TextUtil$Color;
    //   4003: aastore
    //   4004: dup
    //   4005: ldc2_w 1493610381
    //   4008: l2i
    //   4009: ldc_w 1493610378
    //   4012: ixor
    //   4013: getstatic Perryc.c : I
    //   4016: iflt -> 4030
    //   4019: ldc2_w 2070617529
    //   4022: l2i
    //   4023: ldc_w 1042005875
    //   4026: ixor
    //   4027: goto -> 4038
    //   4030: ldc2_w 478274414
    //   4033: l2i
    //   4034: ldc_w 1578136062
    //   4037: ixor
    //   4038: ldc2_w 126611782
    //   4041: l2i
    //   4042: ldc_w -868803439
    //   4045: ixor
    //   4046: ixor
    //   4047: lookupswitch default -> 4812, -1993507001 -> 4072, -1899213027 -> 4030
    //   4072: getstatic bigname/zprestige/webhack/util/TextUtil$Color.DARK_PURPLE : Lbigname/zprestige/webhack/util/TextUtil$Color;
    //   4075: aastore
    //   4076: dup
    //   4077: ldc2_w -414963061
    //   4080: l2i
    //   4081: ldc_w -414963069
    //   4084: ixor
    //   4085: getstatic Perryc.1 : I
    //   4088: ifeq -> 4102
    //   4091: ldc2_w -1747312864
    //   4094: l2i
    //   4095: ldc_w 1895556270
    //   4098: ixor
    //   4099: goto -> 4110
    //   4102: ldc2_w 348864082
    //   4105: l2i
    //   4106: ldc_w 6074711
    //   4109: ixor
    //   4110: ldc2_w 1984843940
    //   4113: l2i
    //   4114: ldc_w -1104441699
    //   4117: ixor
    //   4118: ixor
    //   4119: lookupswitch default -> 4144, 792995255 -> 4842, 1268907766 -> 4102
    //   4144: getstatic bigname/zprestige/webhack/util/TextUtil$Color.GOLD : Lbigname/zprestige/webhack/util/TextUtil$Color;
    //   4147: aastore
    //   4148: dup
    //   4149: ldc2_w -687103446
    //   4152: l2i
    //   4153: ldc_w -687103453
    //   4156: ixor
    //   4157: getstatic Perryc.1 : I
    //   4160: ifeq -> 4174
    //   4163: ldc2_w 470454450
    //   4166: l2i
    //   4167: ldc_w -738946855
    //   4170: ixor
    //   4171: goto -> 4182
    //   4174: ldc2_w 1702604024
    //   4177: l2i
    //   4178: ldc_w 283325573
    //   4181: ixor
    //   4182: ldc2_w -1867714761
    //   4185: l2i
    //   4186: ldc_w -248478727
    //   4189: ixor
    //   4190: ixor
    //   4191: lookupswitch default -> 4820, -1369281371 -> 4174, 335869107 -> 4216
    //   4216: getstatic bigname/zprestige/webhack/util/TextUtil$Color.GRAY : Lbigname/zprestige/webhack/util/TextUtil$Color;
    //   4219: aastore
    //   4220: dup
    //   4221: ldc2_w -153762081
    //   4224: l2i
    //   4225: ldc_w -153762091
    //   4228: ixor
    //   4229: getstatic Perryc.c : I
    //   4232: iflt -> 4246
    //   4235: ldc2_w 279005661
    //   4238: l2i
    //   4239: ldc_w -352713434
    //   4242: ixor
    //   4243: goto -> 4254
    //   4246: ldc2_w -269632734
    //   4249: l2i
    //   4250: ldc_w -1846072689
    //   4253: ixor
    //   4254: ldc2_w -1270189326
    //   4257: l2i
    //   4258: ldc_w 967463055
    //   4261: ixor
    //   4262: ixor
    //   4263: lookupswitch default -> 4908, -201673776 -> 4288, 2008772230 -> 4246
    //   4288: getstatic bigname/zprestige/webhack/util/TextUtil$Color.DARK_GRAY : Lbigname/zprestige/webhack/util/TextUtil$Color;
    //   4291: aastore
    //   4292: dup
    //   4293: ldc2_w -1417053519
    //   4296: l2i
    //   4297: ldc_w -1417053510
    //   4300: ixor
    //   4301: getstatic Perryc.c : I
    //   4304: iflt -> 4318
    //   4307: ldc2_w 1274695364
    //   4310: l2i
    //   4311: ldc_w 1770859611
    //   4314: ixor
    //   4315: goto -> 4326
    //   4318: ldc2_w -1849518585
    //   4321: l2i
    //   4322: ldc_w 656611342
    //   4325: ixor
    //   4326: ldc2_w -12018915
    //   4329: l2i
    //   4330: ldc_w -1064663493
    //   4333: ixor
    //   4334: ixor
    //   4335: lookupswitch default -> 4360, -332021549 -> 4318, 498433977 -> 4874
    //   4360: getstatic bigname/zprestige/webhack/util/TextUtil$Color.BLUE : Lbigname/zprestige/webhack/util/TextUtil$Color;
    //   4363: aastore
    //   4364: dup
    //   4365: ldc2_w 742766144
    //   4368: l2i
    //   4369: ldc_w 742766156
    //   4372: ixor
    //   4373: getstatic Perryc.1 : I
    //   4376: ifeq -> 4390
    //   4379: ldc2_w 1938056023
    //   4382: l2i
    //   4383: ldc_w 238216349
    //   4386: ixor
    //   4387: goto -> 4398
    //   4390: ldc2_w 241742297
    //   4393: l2i
    //   4394: ldc_w -475512961
    //   4397: ixor
    //   4398: ldc2_w -1320661951
    //   4401: l2i
    //   4402: ldc_w -1369614039
    //   4405: ixor
    //   4406: ixor
    //   4407: lookupswitch default -> 4834, -220881970 -> 4432, 1654887074 -> 4390
    //   4432: getstatic bigname/zprestige/webhack/util/TextUtil$Color.GREEN : Lbigname/zprestige/webhack/util/TextUtil$Color;
    //   4435: aastore
    //   4436: dup
    //   4437: ldc2_w 1337938909
    //   4440: l2i
    //   4441: ldc_w 1337938896
    //   4444: ixor
    //   4445: getstatic Perryc.0 : I
    //   4448: ifle -> 4462
    //   4451: ldc2_w -374507427
    //   4454: l2i
    //   4455: ldc_w -615192342
    //   4458: ixor
    //   4459: goto -> 4470
    //   4462: ldc2_w -230511812
    //   4465: l2i
    //   4466: ldc_w -940209246
    //   4469: ixor
    //   4470: ldc2_w -762484549
    //   4473: l2i
    //   4474: ldc_w -1139758917
    //   4477: ixor
    //   4478: ixor
    //   4479: lookupswitch default -> 4504, -1687819876 -> 4462, 1550078135 -> 4922
    //   4504: getstatic bigname/zprestige/webhack/util/TextUtil$Color.AQUA : Lbigname/zprestige/webhack/util/TextUtil$Color;
    //   4507: aastore
    //   4508: dup
    //   4509: ldc2_w 893602321
    //   4512: l2i
    //   4513: ldc_w 893602335
    //   4516: ixor
    //   4517: getstatic Perryc.c : I
    //   4520: iflt -> 4534
    //   4523: ldc2_w -852758803
    //   4526: l2i
    //   4527: ldc_w -130978571
    //   4530: ixor
    //   4531: goto -> 4542
    //   4534: ldc2_w 51220489
    //   4537: l2i
    //   4538: ldc_w 1321896548
    //   4541: ixor
    //   4542: ldc2_w 1419893997
    //   4545: l2i
    //   4546: ldc_w -623839203
    //   4549: ixor
    //   4550: ixor
    //   4551: lookupswitch default -> 4576, -2066376182 -> 4534, -1150572824 -> 4844
    //   4576: getstatic bigname/zprestige/webhack/util/TextUtil$Color.RED : Lbigname/zprestige/webhack/util/TextUtil$Color;
    //   4579: aastore
    //   4580: dup
    //   4581: ldc2_w -399211611
    //   4584: l2i
    //   4585: ldc_w -399211606
    //   4588: ixor
    //   4589: getstatic Perryc.0 : I
    //   4592: ifle -> 4606
    //   4595: ldc2_w 973746992
    //   4598: l2i
    //   4599: ldc_w 95192253
    //   4602: ixor
    //   4603: goto -> 4614
    //   4606: ldc2_w 1219129885
    //   4609: l2i
    //   4610: ldc_w 1218818285
    //   4613: ixor
    //   4614: ldc2_w -436806234
    //   4617: l2i
    //   4618: ldc_w 289039135
    //   4621: ixor
    //   4622: ixor
    //   4623: lookupswitch default -> 4648, -882243276 -> 4836, -330808613 -> 4606
    //   4648: getstatic bigname/zprestige/webhack/util/TextUtil$Color.LIGHT_PURPLE : Lbigname/zprestige/webhack/util/TextUtil$Color;
    //   4651: aastore
    //   4652: dup
    //   4653: ldc2_w -1213243737
    //   4656: l2i
    //   4657: ldc_w -1213243721
    //   4660: ixor
    //   4661: getstatic Perryc.0 : I
    //   4664: ifle -> 4678
    //   4667: ldc2_w -1711833541
    //   4670: l2i
    //   4671: ldc_w -1929769609
    //   4674: ixor
    //   4675: goto -> 4686
    //   4678: ldc2_w -1674988570
    //   4681: l2i
    //   4682: ldc_w -1920804011
    //   4685: ixor
    //   4686: ldc2_w 1201525469
    //   4689: l2i
    //   4690: ldc_w 2023623025
    //   4693: ixor
    //   4694: ixor
    //   4695: lookupswitch default -> 4876, 705603808 -> 4678, 782807839 -> 4720
    //   4720: getstatic bigname/zprestige/webhack/util/TextUtil$Color.YELLOW : Lbigname/zprestige/webhack/util/TextUtil$Color;
    //   4723: aastore
    //   4724: getstatic Perryc.c : I
    //   4727: iflt -> 4741
    //   4730: ldc2_w 1938515263
    //   4733: l2i
    //   4734: ldc_w -1730576297
    //   4737: ixor
    //   4738: goto -> 4749
    //   4741: ldc2_w 1884331077
    //   4744: l2i
    //   4745: ldc_w 1494454311
    //   4748: ixor
    //   4749: ldc2_w 1746703696
    //   4752: l2i
    //   4753: ldc_w -1293406703
    //   4756: ixor
    //   4757: ixor
    //   4758: lookupswitch default -> 4826, -206063837 -> 4784, 832986665 -> 4741
    //   4784: putstatic bigname/zprestige/webhack/util/TextUtil$Color.$VALUES : [Lbigname/zprestige/webhack/util/TextUtil$Color;
    //   4787: return
    //   4788: aconst_null
    //   4789: athrow
    //   4790: aconst_null
    //   4791: athrow
    //   4792: aconst_null
    //   4793: athrow
    //   4794: aconst_null
    //   4795: athrow
    //   4796: aconst_null
    //   4797: athrow
    //   4798: aconst_null
    //   4799: athrow
    //   4800: aconst_null
    //   4801: athrow
    //   4802: aconst_null
    //   4803: athrow
    //   4804: aconst_null
    //   4805: athrow
    //   4806: aconst_null
    //   4807: athrow
    //   4808: aconst_null
    //   4809: athrow
    //   4810: aconst_null
    //   4811: athrow
    //   4812: aconst_null
    //   4813: athrow
    //   4814: aconst_null
    //   4815: athrow
    //   4816: aconst_null
    //   4817: athrow
    //   4818: aconst_null
    //   4819: athrow
    //   4820: aconst_null
    //   4821: athrow
    //   4822: aconst_null
    //   4823: athrow
    //   4824: aconst_null
    //   4825: athrow
    //   4826: aconst_null
    //   4827: athrow
    //   4828: aconst_null
    //   4829: athrow
    //   4830: aconst_null
    //   4831: athrow
    //   4832: aconst_null
    //   4833: athrow
    //   4834: aconst_null
    //   4835: athrow
    //   4836: aconst_null
    //   4837: athrow
    //   4838: aconst_null
    //   4839: athrow
    //   4840: aconst_null
    //   4841: athrow
    //   4842: aconst_null
    //   4843: athrow
    //   4844: aconst_null
    //   4845: athrow
    //   4846: aconst_null
    //   4847: athrow
    //   4848: aconst_null
    //   4849: athrow
    //   4850: aconst_null
    //   4851: athrow
    //   4852: aconst_null
    //   4853: athrow
    //   4854: aconst_null
    //   4855: athrow
    //   4856: aconst_null
    //   4857: athrow
    //   4858: aconst_null
    //   4859: athrow
    //   4860: aconst_null
    //   4861: athrow
    //   4862: aconst_null
    //   4863: athrow
    //   4864: aconst_null
    //   4865: athrow
    //   4866: aconst_null
    //   4867: athrow
    //   4868: aconst_null
    //   4869: athrow
    //   4870: aconst_null
    //   4871: athrow
    //   4872: aconst_null
    //   4873: athrow
    //   4874: aconst_null
    //   4875: athrow
    //   4876: aconst_null
    //   4877: athrow
    //   4878: aconst_null
    //   4879: athrow
    //   4880: aconst_null
    //   4881: athrow
    //   4882: aconst_null
    //   4883: athrow
    //   4884: aconst_null
    //   4885: athrow
    //   4886: aconst_null
    //   4887: athrow
    //   4888: aconst_null
    //   4889: athrow
    //   4890: aconst_null
    //   4891: athrow
    //   4892: aconst_null
    //   4893: athrow
    //   4894: aconst_null
    //   4895: athrow
    //   4896: aconst_null
    //   4897: athrow
    //   4898: aconst_null
    //   4899: athrow
    //   4900: aconst_null
    //   4901: athrow
    //   4902: aconst_null
    //   4903: athrow
    //   4904: aconst_null
    //   4905: athrow
    //   4906: aconst_null
    //   4907: athrow
    //   4908: aconst_null
    //   4909: athrow
    //   4910: aconst_null
    //   4911: athrow
    //   4912: aconst_null
    //   4913: athrow
    //   4914: aconst_null
    //   4915: athrow
    //   4916: aconst_null
    //   4917: athrow
    //   4918: aconst_null
    //   4919: athrow
    //   4920: aconst_null
    //   4921: athrow
    //   4922: aconst_null
    //   4923: athrow
    //   4924: aconst_null
    //   4925: athrow
  }
}


/* Location:              C:\Users\alex\Desktop\webhack\WebHack-0.8-obf_sussy_1.jar!\bigname\zprestige\webhac\\util\TextUtil$Color.class
 * Java compiler version: 8 (52.0)
 * JD-Core Version:       1.1.3
 */