package bigname.zprestige.webhack.features.command;

import Perry1;
import Perryc;
import net.minecraft.util.text.ITextComponent;
import net.minecraft.util.text.TextComponentBase;

public class Command$ChatMessage extends TextComponentBase {
  public String text;
  
  public ITextComponent func_150259_f() {
    if (Perryc.0 <= 0) {
      null;
    } else {
      if (null != null)
        throw (Throwable)null; 
      null;
    } 
    if (null != null)
      throw (Throwable)null; 
    null;
  }
  
  public String func_150261_e() {
    return Perry1.m(this, (int)1385407300L ^ 0x1844B688);
  }
  
  public Command$ChatMessage(String text) {
    // Byte code:
    //   0: getstatic Perryc.c : I
    //   3: iflt -> 16
    //   6: ldc2_w -1819230735
    //   9: l2i
    //   10: ldc 61294950
    //   12: ixor
    //   13: goto -> 23
    //   16: ldc2_w -315161526
    //   19: l2i
    //   20: ldc 504985903
    //   22: ixor
    //   23: ldc2_w -1397327308
    //   26: l2i
    //   27: ldc -76772134
    //   29: ixor
    //   30: ixor
    //   31: lookupswitch default -> 1822, -1527477365 -> 56, -940768647 -> 16
    //   56: aload_0
    //   57: getstatic Perryc.0 : I
    //   60: ifle -> 73
    //   63: ldc2_w 942904072
    //   66: l2i
    //   67: ldc 579609616
    //   69: ixor
    //   70: goto -> 80
    //   73: ldc2_w 1180574107
    //   76: l2i
    //   77: ldc 871854550
    //   79: ixor
    //   80: ldc2_w -508078356
    //   83: l2i
    //   84: ldc 856312650
    //   86: ixor
    //   87: ixor
    //   88: lookupswitch default -> 116, -939349314 -> 1780, -571946114 -> 73
    //   116: invokespecial <init> : ()V
    //   119: ldc 'ﴗ㌨ﵳ㷦䪄Ꮎอ肱踵ᙿ䗒੾ゐ煣鋝怰辚╂ꝼ埲犵侢៓䚵ᔽ'
    //   121: getstatic Perryc.0 : I
    //   124: ifle -> 137
    //   127: ldc2_w -1000721244
    //   130: l2i
    //   131: ldc -225764135
    //   133: ixor
    //   134: goto -> 144
    //   137: ldc2_w 229788402
    //   140: l2i
    //   141: ldc -500768392
    //   143: ixor
    //   144: ldc2_w 1290812003
    //   147: l2i
    //   148: ldc -1649608423
    //   150: ixor
    //   151: ixor
    //   152: lookupswitch default -> 180, -410129657 -> 1794, 2038280664 -> 137
    //   180: invokestatic 0 : (Ljava/lang/String;)Ljava/lang/String;
    //   183: getstatic Perryc.0 : I
    //   186: ifle -> 199
    //   189: ldc2_w -515479018
    //   192: l2i
    //   193: ldc -1096892273
    //   195: ixor
    //   196: goto -> 206
    //   199: ldc2_w 1600961348
    //   202: l2i
    //   203: ldc 296358302
    //   205: ixor
    //   206: ldc2_w 142653410
    //   209: l2i
    //   210: ldc -697160973
    //   212: ixor
    //   213: ixor
    //   214: lookupswitch default -> 1778, -2127939704 -> 199, -1875626037 -> 240
    //   240: invokestatic compile : (Ljava/lang/String;)Ljava/util/regex/Pattern;
    //   243: getstatic Perryc.1 : I
    //   246: ifeq -> 259
    //   249: ldc2_w -255552045
    //   252: l2i
    //   253: ldc 959756001
    //   255: ixor
    //   256: goto -> 266
    //   259: ldc2_w -453584510
    //   262: l2i
    //   263: ldc -767859409
    //   265: ixor
    //   266: ldc2_w -1655977715
    //   269: l2i
    //   270: ldc 1014474048
    //   272: ixor
    //   273: ixor
    //   274: lookupswitch default -> 300, -1976699334 -> 259, 1758220159 -> 1826
    //   300: astore_2
    //   301: getstatic Perryc.0 : I
    //   304: ifle -> 317
    //   307: ldc2_w -504261941
    //   310: l2i
    //   311: ldc 1863065750
    //   313: ixor
    //   314: goto -> 324
    //   317: ldc2_w 1565462424
    //   320: l2i
    //   321: ldc 159300184
    //   323: ixor
    //   324: ldc2_w -667444528
    //   327: l2i
    //   328: ldc 343826521
    //   330: ixor
    //   331: ixor
    //   332: lookupswitch default -> 360, 547726407 -> 317, 1119111380 -> 1818
    //   360: aload_2
    //   361: getstatic Perryc.c : I
    //   364: iflt -> 377
    //   367: ldc2_w -35245313
    //   370: l2i
    //   371: ldc -1953530630
    //   373: ixor
    //   374: goto -> 384
    //   377: ldc2_w -1585525449
    //   380: l2i
    //   381: ldc 254000987
    //   383: ixor
    //   384: ldc2_w 1038717000
    //   387: l2i
    //   388: ldc -980415379
    //   390: ixor
    //   391: ixor
    //   392: lookupswitch default -> 1790, -1911500256 -> 377, 1445260873 -> 420
    //   420: aload_1
    //   421: getstatic Perryc.1 : I
    //   424: ifeq -> 437
    //   427: ldc2_w 640213782
    //   430: l2i
    //   431: ldc -1189271464
    //   433: ixor
    //   434: goto -> 444
    //   437: ldc2_w 1714973177
    //   440: l2i
    //   441: ldc -163204097
    //   443: ixor
    //   444: ldc2_w -2011149604
    //   447: l2i
    //   448: ldc 106773996
    //   450: ixor
    //   451: ixor
    //   452: lookupswitch default -> 480, 183412914 -> 437, 289979518 -> 1808
    //   480: invokevirtual matcher : (Ljava/lang/CharSequence;)Ljava/util/regex/Matcher;
    //   483: getstatic Perryc.1 : I
    //   486: ifeq -> 499
    //   489: ldc2_w 1249201195
    //   492: l2i
    //   493: ldc -1166605067
    //   495: ixor
    //   496: goto -> 506
    //   499: ldc2_w -1388575371
    //   502: l2i
    //   503: ldc -83484347
    //   505: ixor
    //   506: ldc2_w -37843029
    //   509: l2i
    //   510: ldc -287395609
    //   512: ixor
    //   513: ixor
    //   514: lookupswitch default -> 1802, -480086126 -> 499, 1163533180 -> 540
    //   540: astore_3
    //   541: new java/lang/StringBuffer
    //   544: dup
    //   545: getstatic Perryc.0 : I
    //   548: ifle -> 561
    //   551: ldc2_w 1384516411
    //   554: l2i
    //   555: ldc 544188994
    //   557: ixor
    //   558: goto -> 568
    //   561: ldc2_w -1430519442
    //   564: l2i
    //   565: ldc 1429994600
    //   567: ixor
    //   568: ldc2_w -369090990
    //   571: l2i
    //   572: ldc -1268547188
    //   574: ixor
    //   575: ixor
    //   576: lookupswitch default -> 604, -1413338786 -> 561, 747257511 -> 1804
    //   604: invokespecial <init> : ()V
    //   607: getstatic Perryc.1 : I
    //   610: ifeq -> 623
    //   613: ldc2_w -967391835
    //   616: l2i
    //   617: ldc -320151174
    //   619: ixor
    //   620: goto -> 630
    //   623: ldc2_w 487195230
    //   626: l2i
    //   627: ldc 1559640539
    //   629: ixor
    //   630: ldc2_w -321983204
    //   633: l2i
    //   634: ldc -1104213452
    //   636: ixor
    //   637: ixor
    //   638: lookupswitch default -> 664, -1039972235 -> 623, 2019410935 -> 1784
    //   664: astore #4
    //   666: getstatic Perryc.c : I
    //   669: iflt -> 682
    //   672: ldc2_w 1823374398
    //   675: l2i
    //   676: ldc 1735466586
    //   678: ixor
    //   679: goto -> 689
    //   682: ldc2_w -2111912097
    //   685: l2i
    //   686: ldc 434815490
    //   688: ixor
    //   689: ldc2_w -1461257992
    //   692: l2i
    //   693: ldc -1216602333
    //   695: ixor
    //   696: ixor
    //   697: lookupswitch default -> 1824, -2073107834 -> 724, 340100543 -> 682
    //   724: aload_3
    //   725: getstatic Perryc.c : I
    //   728: iflt -> 741
    //   731: ldc2_w 1780387149
    //   734: l2i
    //   735: ldc -1801821733
    //   737: ixor
    //   738: goto -> 748
    //   741: ldc2_w 1837764549
    //   744: l2i
    //   745: ldc 915098941
    //   747: ixor
    //   748: ldc2_w -1229044210
    //   751: l2i
    //   752: ldc -354872399
    //   754: ixor
    //   755: ixor
    //   756: lookupswitch default -> 1792, -1562134231 -> 741, 124131143 -> 784
    //   784: invokevirtual find : ()Z
    //   787: ifeq -> 800
    //   790: ldc2_w 922070122
    //   793: l2i
    //   794: ldc -1213569561
    //   796: ixor
    //   797: goto -> 807
    //   800: ldc2_w -604553096
    //   803: l2i
    //   804: ldc 1520994804
    //   806: ixor
    //   807: ldc2_w 1627733765
    //   810: l2i
    //   811: ldc 1686873426
    //   813: ixor
    //   814: ixor
    //   815: tableswitch default -> 790, -2066656294 -> 836, -2066656293 -> 1335
    //   836: getstatic Perryc.1 : I
    //   839: ifeq -> 852
    //   842: ldc2_w 1094935007
    //   845: l2i
    //   846: ldc -1452231575
    //   848: ixor
    //   849: goto -> 859
    //   852: ldc2_w -1367827885
    //   855: l2i
    //   856: ldc 1121468350
    //   858: ixor
    //   859: ldc2_w 378291745
    //   862: l2i
    //   863: ldc -1517429616
    //   865: ixor
    //   866: ixor
    //   867: lookupswitch default -> 1812, 1530023687 -> 852, 1604403036 -> 892
    //   892: aload_3
    //   893: getstatic Perryc.0 : I
    //   896: ifle -> 909
    //   899: ldc2_w 1870474100
    //   902: l2i
    //   903: ldc -1734353915
    //   905: ixor
    //   906: goto -> 916
    //   909: ldc2_w 493863618
    //   912: l2i
    //   913: ldc 565334312
    //   915: ixor
    //   916: ldc2_w 1581850075
    //   919: l2i
    //   920: ldc 776974641
    //   922: ixor
    //   923: ixor
    //   924: lookupswitch default -> 952, -2015077477 -> 1806, -1448512069 -> 909
    //   952: invokevirtual group : ()Ljava/lang/String;
    //   955: ldc2_w -347791437
    //   958: l2i
    //   959: ldc -347791438
    //   961: ixor
    //   962: getstatic Perryc.1 : I
    //   965: ifeq -> 978
    //   968: ldc2_w 2137856786
    //   971: l2i
    //   972: ldc -82115017
    //   974: ixor
    //   975: goto -> 985
    //   978: ldc2_w 2135233459
    //   981: l2i
    //   982: ldc -1507568980
    //   984: ixor
    //   985: ldc2_w 25768732
    //   988: l2i
    //   989: ldc -421809918
    //   991: ixor
    //   992: ixor
    //   993: lookupswitch default -> 1814, 1043579649 -> 1020, 1663344443 -> 978
    //   1020: invokevirtual substring : (I)Ljava/lang/String;
    //   1023: getstatic Perryc.0 : I
    //   1026: ifle -> 1039
    //   1029: ldc2_w -876124594
    //   1032: l2i
    //   1033: ldc 896247101
    //   1035: ixor
    //   1036: goto -> 1046
    //   1039: ldc2_w -1631147367
    //   1042: l2i
    //   1043: ldc 1101751881
    //   1045: ixor
    //   1046: ldc2_w -119865598
    //   1049: l2i
    //   1050: ldc -399118398
    //   1052: ixor
    //   1053: ixor
    //   1054: lookupswitch default -> 1080, -297544781 -> 1828, 515510391 -> 1039
    //   1080: astore #5
    //   1082: getstatic Perryc.1 : I
    //   1085: ifeq -> 1098
    //   1088: ldc2_w 1708069453
    //   1091: l2i
    //   1092: ldc -1186941265
    //   1094: ixor
    //   1095: goto -> 1105
    //   1098: ldc2_w 1346511225
    //   1101: l2i
    //   1102: ldc 319432917
    //   1104: ixor
    //   1105: ldc2_w 1952315870
    //   1108: l2i
    //   1109: ldc -190853279
    //   1111: ixor
    //   1112: ixor
    //   1113: lookupswitch default -> 1140, 313196978 -> 1098, 1548587613 -> 1800
    //   1140: aload_3
    //   1141: getstatic Perryc.0 : I
    //   1144: ifle -> 1157
    //   1147: ldc2_w -1407078091
    //   1150: l2i
    //   1151: ldc -201372070
    //   1153: ixor
    //   1154: goto -> 1165
    //   1157: ldc2_w 1271691433
    //   1160: l2i
    //   1161: ldc_w 670160603
    //   1164: ixor
    //   1165: ldc2_w -755171822
    //   1168: l2i
    //   1169: ldc_w 1185777527
    //   1172: ixor
    //   1173: ixor
    //   1174: lookupswitch default -> 1200, -879786486 -> 1776, 1981741313 -> 1157
    //   1200: aload #4
    //   1202: getstatic Perryc.0 : I
    //   1205: ifle -> 1219
    //   1208: ldc2_w 609418598
    //   1211: l2i
    //   1212: ldc_w -1472710459
    //   1215: ixor
    //   1216: goto -> 1227
    //   1219: ldc2_w 161161970
    //   1222: l2i
    //   1223: ldc_w 167794998
    //   1226: ixor
    //   1227: ldc2_w -1228684457
    //   1230: l2i
    //   1231: ldc_w -1433318879
    //   1234: ixor
    //   1235: ixor
    //   1236: lookupswitch default -> 1264, -1928004409 -> 1219, -1875358507 -> 1782
    //   1264: aload #5
    //   1266: getstatic Perryc.1 : I
    //   1269: ifeq -> 1283
    //   1272: ldc2_w -239454146
    //   1275: l2i
    //   1276: ldc_w -386961078
    //   1279: ixor
    //   1280: goto -> 1291
    //   1283: ldc2_w -378397310
    //   1286: l2i
    //   1287: ldc_w -1213767243
    //   1290: ixor
    //   1291: ldc2_w 1194768257
    //   1294: l2i
    //   1295: ldc_w -770356619
    //   1298: ixor
    //   1299: ixor
    //   1300: lookupswitch default -> 1328, -1938377600 -> 1830, 581870858 -> 1283
    //   1328: invokevirtual appendReplacement : (Ljava/lang/StringBuffer;Ljava/lang/String;)Ljava/util/regex/Matcher;
    //   1331: pop
    //   1332: goto -> 666
    //   1335: getstatic Perryc.0 : I
    //   1338: ifle -> 1352
    //   1341: ldc2_w 467368638
    //   1344: l2i
    //   1345: ldc_w -66800718
    //   1348: ixor
    //   1349: goto -> 1360
    //   1352: ldc2_w -760534660
    //   1355: l2i
    //   1356: ldc_w 563482425
    //   1359: ixor
    //   1360: ldc2_w -418685081
    //   1363: l2i
    //   1364: ldc_w 1132188779
    //   1367: ixor
    //   1368: ixor
    //   1369: lookupswitch default -> 1810, 1135559168 -> 1352, 1464708425 -> 1396
    //   1396: aload_3
    //   1397: getstatic Perryc.c : I
    //   1400: iflt -> 1414
    //   1403: ldc2_w -1333547956
    //   1406: l2i
    //   1407: ldc_w 1828640491
    //   1410: ixor
    //   1411: goto -> 1422
    //   1414: ldc2_w 3051055
    //   1417: l2i
    //   1418: ldc_w 1952815892
    //   1421: ixor
    //   1422: ldc2_w 1371643902
    //   1425: l2i
    //   1426: ldc_w -1766313946
    //   1429: ixor
    //   1430: ixor
    //   1431: lookupswitch default -> 1456, -991574288 -> 1414, 453301631 -> 1816
    //   1456: aload #4
    //   1458: getstatic Perryc.1 : I
    //   1461: ifeq -> 1475
    //   1464: ldc2_w 1246971169
    //   1467: l2i
    //   1468: ldc_w -250121418
    //   1471: ixor
    //   1472: goto -> 1483
    //   1475: ldc2_w -904494367
    //   1478: l2i
    //   1479: ldc_w 540386151
    //   1482: ixor
    //   1483: ldc2_w -1883907773
    //   1486: l2i
    //   1487: ldc_w -1052116483
    //   1490: ixor
    //   1491: ixor
    //   1492: lookupswitch default -> 1798, -1528889032 -> 1520, -172484951 -> 1475
    //   1520: invokevirtual appendTail : (Ljava/lang/StringBuffer;)Ljava/lang/StringBuffer;
    //   1523: pop
    //   1524: getstatic Perryc.c : I
    //   1527: iflt -> 1541
    //   1530: ldc2_w -1770665137
    //   1533: l2i
    //   1534: ldc_w 1018324156
    //   1537: ixor
    //   1538: goto -> 1549
    //   1541: ldc2_w 58584479
    //   1544: l2i
    //   1545: ldc_w -1828703652
    //   1548: ixor
    //   1549: ldc2_w 337568508
    //   1552: l2i
    //   1553: ldc_w 974882865
    //   1556: ixor
    //   1557: ixor
    //   1558: lookupswitch default -> 1584, -2067610306 -> 1796, 1882764221 -> 1541
    //   1584: aload_0
    //   1585: getstatic Perryc.c : I
    //   1588: iflt -> 1602
    //   1591: ldc2_w 1876009439
    //   1594: l2i
    //   1595: ldc_w 1366696399
    //   1598: ixor
    //   1599: goto -> 1610
    //   1602: ldc2_w 1374749043
    //   1605: l2i
    //   1606: ldc_w -853787753
    //   1609: ixor
    //   1610: ldc2_w -874836405
    //   1613: l2i
    //   1614: ldc_w -1867197777
    //   1617: ixor
    //   1618: ixor
    //   1619: lookupswitch default -> 1644, 293631066 -> 1602, 1707629812 -> 1786
    //   1644: aload #4
    //   1646: getstatic Perryc.0 : I
    //   1649: ifle -> 1663
    //   1652: ldc2_w -1118214608
    //   1655: l2i
    //   1656: ldc_w 982670000
    //   1659: ixor
    //   1660: goto -> 1671
    //   1663: ldc2_w 1227337864
    //   1666: l2i
    //   1667: ldc_w -348237688
    //   1670: ixor
    //   1671: ldc2_w -1274913039
    //   1674: l2i
    //   1675: ldc_w -477287533
    //   1678: ixor
    //   1679: ixor
    //   1680: lookupswitch default -> 1708, -2034796924 -> 1663, -800831006 -> 1788
    //   1708: invokevirtual toString : ()Ljava/lang/String;
    //   1711: getstatic Perryc.0 : I
    //   1714: ifle -> 1728
    //   1717: ldc2_w 1766859432
    //   1720: l2i
    //   1721: ldc_w 55962596
    //   1724: ixor
    //   1725: goto -> 1736
    //   1728: ldc2_w -229326917
    //   1731: l2i
    //   1732: ldc_w 411127600
    //   1735: ixor
    //   1736: ldc2_w 1464742174
    //   1739: l2i
    //   1740: ldc_w 2144272763
    //   1743: ixor
    //   1744: ixor
    //   1745: lookupswitch default -> 1772, 1116010793 -> 1820, 1354757365 -> 1728
    //   1772: putfield text : Ljava/lang/String;
    //   1775: return
    //   1776: aconst_null
    //   1777: athrow
    //   1778: aconst_null
    //   1779: athrow
    //   1780: aconst_null
    //   1781: athrow
    //   1782: aconst_null
    //   1783: athrow
    //   1784: aconst_null
    //   1785: athrow
    //   1786: aconst_null
    //   1787: athrow
    //   1788: aconst_null
    //   1789: athrow
    //   1790: aconst_null
    //   1791: athrow
    //   1792: aconst_null
    //   1793: athrow
    //   1794: aconst_null
    //   1795: athrow
    //   1796: aconst_null
    //   1797: athrow
    //   1798: aconst_null
    //   1799: athrow
    //   1800: aconst_null
    //   1801: athrow
    //   1802: aconst_null
    //   1803: athrow
    //   1804: aconst_null
    //   1805: athrow
    //   1806: aconst_null
    //   1807: athrow
    //   1808: aconst_null
    //   1809: athrow
    //   1810: aconst_null
    //   1811: athrow
    //   1812: aconst_null
    //   1813: athrow
    //   1814: aconst_null
    //   1815: athrow
    //   1816: aconst_null
    //   1817: athrow
    //   1818: aconst_null
    //   1819: athrow
    //   1820: aconst_null
    //   1821: athrow
    //   1822: aconst_null
    //   1823: athrow
    //   1824: aconst_null
    //   1825: athrow
    //   1826: aconst_null
    //   1827: athrow
    //   1828: aconst_null
    //   1829: athrow
    //   1830: aconst_null
    //   1831: athrow
    // Local variable table:
    //   start	length	slot	name	descriptor
    //   1082	250	5	replacement	Ljava/lang/String;
    //   0	1776	0	this	Lbigname/zprestige/webhack/features/command/Command$ChatMessage;
    //   0	1776	1	text	Ljava/lang/String;
    //   301	1475	2	pattern	Ljava/util/regex/Pattern;
    //   541	1235	3	matcher	Ljava/util/regex/Matcher;
    //   666	1110	4	stringBuffer	Ljava/lang/StringBuffer;
  }
  
  public ITextComponent shallowCopy() {
    // Byte code:
    //   0: goto -> 8
    //   3: dup
    //   4: ifnull -> 255
    //   7: athrow
    //   8: aconst_null
    //   9: getstatic Perryc.c : I
    //   12: ifge -> 247
    //   15: pop
    //   16: aconst_null
    //   17: goto -> 239
    //   20: nop
    //   21: nop
    //   22: nop
    //   23: athrow
    //   24: new bigname/zprestige/webhack/features/command/Command$ChatMessage
    //   27: dup
    //   28: getstatic Perryc.0 : I
    //   31: ifle -> 45
    //   34: ldc2_w 1829019110
    //   37: l2i
    //   38: ldc_w -752200153
    //   41: ixor
    //   42: goto -> 53
    //   45: ldc2_w 305765536
    //   48: l2i
    //   49: ldc_w -1527246601
    //   52: ixor
    //   53: ldc2_w 1685932311
    //   56: l2i
    //   57: ldc_w 1870569928
    //   60: ixor
    //   61: ixor
    //   62: lookupswitch default -> 224, -1255333090 -> 45, -1111333752 -> 88
    //   88: aload_0
    //   89: getstatic Perryc.1 : I
    //   92: ifeq -> 106
    //   95: ldc2_w -487984210
    //   98: l2i
    //   99: ldc_w 273149408
    //   102: ixor
    //   103: goto -> 114
    //   106: ldc2_w 1631170222
    //   109: l2i
    //   110: ldc_w -787661665
    //   113: ixor
    //   114: ldc2_w 183475048
    //   117: l2i
    //   118: ldc_w 68988536
    //   121: ixor
    //   122: ixor
    //   123: lookupswitch default -> 226, -1094211807 -> 148, -61002914 -> 106
    //   148: getfield text : Ljava/lang/String;
    //   151: getstatic Perryc.0 : I
    //   154: ifle -> 168
    //   157: ldc2_w 416284653
    //   160: l2i
    //   161: ldc_w 1562586649
    //   164: ixor
    //   165: goto -> 176
    //   168: ldc2_w -2002630757
    //   171: l2i
    //   172: ldc_w 942163379
    //   175: ixor
    //   176: ldc2_w -1691999769
    //   179: l2i
    //   180: ldc_w 2100165747
    //   183: ixor
    //   184: ixor
    //   185: lookupswitch default -> 212, -1545139104 -> 228, -1450591416 -> 168
    //   212: goto -> 216
    //   215: athrow
    //   216: invokespecial <init> : (Ljava/lang/String;)V
    //   219: goto -> 223
    //   222: athrow
    //   223: areturn
    //   224: aconst_null
    //   225: athrow
    //   226: aconst_null
    //   227: athrow
    //   228: aconst_null
    //   229: athrow
    //   230: pop
    //   231: goto -> 24
    //   234: pop
    //   235: aconst_null
    //   236: goto -> 230
    //   239: dup
    //   240: ifnull -> 230
    //   243: checkcast java/lang/Throwable
    //   246: athrow
    //   247: dup
    //   248: ifnull -> 234
    //   251: checkcast java/lang/Throwable
    //   254: athrow
    //   255: aconst_null
    //   256: athrow
    // Local variable table:
    //   start	length	slot	name	descriptor
    //   24	200	0	this	Lbigname/zprestige/webhack/features/command/Command$ChatMessage;
    // Exception table:
    //   from	to	target	type
    //   8	20	239	finally
    //   216	222	222	finally
    //   216	222	3	finally
    //   216	222	3	finally
    //   216	222	3	java/lang/AssertionError
    //   216	222	3	finally
    //   239	247	239	java/lang/NegativeArraySizeException
    //   255	257	3	java/lang/ClassCastException
  }
  
  static {
    throw SYNTHETIC_LOCAL_VARIABLE_0;
  }
}


/* Location:              C:\Users\alex\Desktop\webhack\WebHack-0.8-obf_sussy_1.jar!\bigname\zprestige\webhack\features\command\Command$ChatMessage.class
 * Java compiler version: 8 (52.0)
 * JD-Core Version:       1.1.3
 */