package bigname.zprestige.webhack.util.WurstPlusThree;

public class WurstplusThreeCrystalUtil$1 {
  public static int[] $SwitchMap$net$minecraft$world$EnumDifficulty;
  
  static {
    // Byte code:
    //   0: getstatic Perryc.0 : I
    //   3: ifle -> 16
    //   6: ldc2_w -1453357865
    //   9: l2i
    //   10: ldc 2010868096
    //   12: ixor
    //   13: goto -> 23
    //   16: ldc2_w -1723846404
    //   19: l2i
    //   20: ldc -1476822294
    //   22: ixor
    //   23: ldc2_w 1375619668
    //   26: l2i
    //   27: ldc -1612870392
    //   29: ixor
    //   30: ixor
    //   31: lookupswitch default -> 1134, -258306742 -> 56, 279390731 -> 16
    //   56: invokestatic values : ()[Lnet/minecraft/world/EnumDifficulty;
    //   59: arraylength
    //   60: newarray int
    //   62: getstatic Perryc.c : I
    //   65: iflt -> 78
    //   68: ldc2_w 950540265
    //   71: l2i
    //   72: ldc 910648684
    //   74: ixor
    //   75: goto -> 85
    //   78: ldc2_w -1285765503
    //   81: l2i
    //   82: ldc -781727844
    //   84: ixor
    //   85: ldc2_w 868467804
    //   88: l2i
    //   89: ldc -349196835
    //   91: ixor
    //   92: ixor
    //   93: lookupswitch default -> 1156, -1160288100 -> 120, -704439548 -> 78
    //   120: putstatic bigname/zprestige/webhack/util/WurstPlusThree/WurstplusThreeCrystalUtil$1.$SwitchMap$net$minecraft$world$EnumDifficulty : [I
    //   123: getstatic Perryc.0 : I
    //   126: ifle -> 139
    //   129: ldc2_w -1736319935
    //   132: l2i
    //   133: ldc -333541385
    //   135: ixor
    //   136: goto -> 146
    //   139: ldc2_w -2106350661
    //   142: l2i
    //   143: ldc -317600487
    //   145: ixor
    //   146: ldc2_w -425493004
    //   149: l2i
    //   150: ldc -45445408
    //   152: ixor
    //   153: ixor
    //   154: lookupswitch default -> 1142, 1870045346 -> 139, 1955306934 -> 180
    //   180: getstatic bigname/zprestige/webhack/util/WurstPlusThree/WurstplusThreeCrystalUtil$1.$SwitchMap$net$minecraft$world$EnumDifficulty : [I
    //   183: getstatic Perryc.0 : I
    //   186: ifle -> 199
    //   189: ldc2_w -979978153
    //   192: l2i
    //   193: ldc 1933040406
    //   195: ixor
    //   196: goto -> 206
    //   199: ldc2_w -700478485
    //   202: l2i
    //   203: ldc -1769835893
    //   205: ixor
    //   206: ldc2_w -567723004
    //   209: l2i
    //   210: ldc 67715582
    //   212: ixor
    //   213: ixor
    //   214: lookupswitch default -> 240, -2018620721 -> 199, 1820401339 -> 1164
    //   240: getstatic net/minecraft/world/EnumDifficulty.PEACEFUL : Lnet/minecraft/world/EnumDifficulty;
    //   243: getstatic Perryc.c : I
    //   246: iflt -> 259
    //   249: ldc2_w 959809070
    //   252: l2i
    //   253: ldc 674164566
    //   255: ixor
    //   256: goto -> 266
    //   259: ldc2_w 17021385
    //   262: l2i
    //   263: ldc 1251735998
    //   265: ixor
    //   266: ldc2_w -849004204
    //   269: l2i
    //   270: ldc 1555808327
    //   272: ixor
    //   273: ixor
    //   274: lookupswitch default -> 1136, -2134536085 -> 259, -632899228 -> 300
    //   300: invokevirtual ordinal : ()I
    //   303: ldc2_w 704649812
    //   306: l2i
    //   307: ldc 704649813
    //   309: ixor
    //   310: iastore
    //   311: goto -> 373
    //   314: getstatic Perryc.c : I
    //   317: iflt -> 330
    //   320: ldc2_w -521594926
    //   323: l2i
    //   324: ldc 127697809
    //   326: ixor
    //   327: goto -> 337
    //   330: ldc2_w 45348336
    //   333: l2i
    //   334: ldc -1228349131
    //   336: ixor
    //   337: ldc2_w 1058836867
    //   340: l2i
    //   341: ldc -1539150935
    //   343: ixor
    //   344: ixor
    //   345: lookupswitch default -> 1146, 791015151 -> 372, 2083221097 -> 330
    //   372: astore_0
    //   373: getstatic Perryc.1 : I
    //   376: ifeq -> 389
    //   379: ldc2_w 807979256
    //   382: l2i
    //   383: ldc 655158872
    //   385: ixor
    //   386: goto -> 396
    //   389: ldc2_w -1796746400
    //   392: l2i
    //   393: ldc -707720595
    //   395: ixor
    //   396: ldc2_w -1048149350
    //   399: l2i
    //   400: ldc 881550222
    //   402: ixor
    //   403: ixor
    //   404: lookupswitch default -> 1130, -1271187431 -> 432, -500578380 -> 389
    //   432: getstatic bigname/zprestige/webhack/util/WurstPlusThree/WurstplusThreeCrystalUtil$1.$SwitchMap$net$minecraft$world$EnumDifficulty : [I
    //   435: getstatic Perryc.1 : I
    //   438: ifeq -> 451
    //   441: ldc2_w 1829047025
    //   444: l2i
    //   445: ldc -351339450
    //   447: ixor
    //   448: goto -> 458
    //   451: ldc2_w -727032183
    //   454: l2i
    //   455: ldc 1513218023
    //   457: ixor
    //   458: ldc2_w -1293069389
    //   461: l2i
    //   462: ldc 665898373
    //   464: ixor
    //   465: ixor
    //   466: lookupswitch default -> 1148, 324429953 -> 451, 465968984 -> 492
    //   492: getstatic net/minecraft/world/EnumDifficulty.EASY : Lnet/minecraft/world/EnumDifficulty;
    //   495: getstatic Perryc.c : I
    //   498: iflt -> 511
    //   501: ldc2_w 706519898
    //   504: l2i
    //   505: ldc 1285837923
    //   507: ixor
    //   508: goto -> 518
    //   511: ldc2_w -187561617
    //   514: l2i
    //   515: ldc 680753207
    //   517: ixor
    //   518: ldc2_w -2097597536
    //   521: l2i
    //   522: ldc -1481397426
    //   524: ixor
    //   525: ixor
    //   526: lookupswitch default -> 552, 1012750171 -> 511, 1139961815 -> 1132
    //   552: invokevirtual ordinal : ()I
    //   555: ldc2_w 1935048394
    //   558: l2i
    //   559: ldc 1935048392
    //   561: ixor
    //   562: iastore
    //   563: goto -> 625
    //   566: getstatic Perryc.c : I
    //   569: iflt -> 582
    //   572: ldc2_w -331872743
    //   575: l2i
    //   576: ldc -417850137
    //   578: ixor
    //   579: goto -> 589
    //   582: ldc2_w 666042889
    //   585: l2i
    //   586: ldc -1149975407
    //   588: ixor
    //   589: ldc2_w 801371973
    //   592: l2i
    //   593: ldc 670981436
    //   595: ixor
    //   596: ixor
    //   597: lookupswitch default -> 1150, -1795527455 -> 624, 52277383 -> 582
    //   624: astore_0
    //   625: getstatic Perryc.1 : I
    //   628: ifeq -> 641
    //   631: ldc2_w 1946442790
    //   634: l2i
    //   635: ldc 1720725399
    //   637: ixor
    //   638: goto -> 648
    //   641: ldc2_w -611179043
    //   644: l2i
    //   645: ldc 1605819417
    //   647: ixor
    //   648: ldc2_w -1606627917
    //   651: l2i
    //   652: ldc -581754691
    //   654: ixor
    //   655: ixor
    //   656: lookupswitch default -> 1144, -112519990 -> 684, 1878761151 -> 641
    //   684: getstatic bigname/zprestige/webhack/util/WurstPlusThree/WurstplusThreeCrystalUtil$1.$SwitchMap$net$minecraft$world$EnumDifficulty : [I
    //   687: getstatic Perryc.0 : I
    //   690: ifle -> 703
    //   693: ldc2_w -726289983
    //   696: l2i
    //   697: ldc 921894597
    //   699: ixor
    //   700: goto -> 710
    //   703: ldc2_w -391762229
    //   706: l2i
    //   707: ldc -1509172730
    //   709: ixor
    //   710: ldc2_w -299834743
    //   713: l2i
    //   714: ldc 1132340466
    //   716: ixor
    //   717: ixor
    //   718: lookupswitch default -> 744, -744585481 -> 703, 1327073663 -> 1158
    //   744: getstatic net/minecraft/world/EnumDifficulty.NORMAL : Lnet/minecraft/world/EnumDifficulty;
    //   747: getstatic Perryc.0 : I
    //   750: ifle -> 763
    //   753: ldc2_w -1638696755
    //   756: l2i
    //   757: ldc -1638640540
    //   759: ixor
    //   760: goto -> 770
    //   763: ldc2_w 284057990
    //   766: l2i
    //   767: ldc 2145915782
    //   769: ixor
    //   770: ldc2_w 3538317
    //   773: l2i
    //   774: ldc -1322575068
    //   776: ixor
    //   777: ixor
    //   778: lookupswitch default -> 804, -1446070056 -> 763, -1323709952 -> 1152
    //   804: invokevirtual ordinal : ()I
    //   807: ldc2_w 1709269042
    //   810: l2i
    //   811: ldc 1709269041
    //   813: ixor
    //   814: iastore
    //   815: goto -> 877
    //   818: getstatic Perryc.0 : I
    //   821: ifle -> 834
    //   824: ldc2_w -194749043
    //   827: l2i
    //   828: ldc -176062102
    //   830: ixor
    //   831: goto -> 841
    //   834: ldc2_w -1110340402
    //   837: l2i
    //   838: ldc 1671144210
    //   840: ixor
    //   841: ldc2_w 453047333
    //   844: l2i
    //   845: ldc -1603143783
    //   847: ixor
    //   848: ixor
    //   849: lookupswitch default -> 876, -2104090426 -> 834, -1164648613 -> 1162
    //   876: astore_0
    //   877: getstatic Perryc.c : I
    //   880: iflt -> 893
    //   883: ldc2_w 152607443
    //   886: l2i
    //   887: ldc 1712039243
    //   889: ixor
    //   890: goto -> 900
    //   893: ldc2_w -2027467808
    //   896: l2i
    //   897: ldc 1736131377
    //   899: ixor
    //   900: ldc2_w -370982141
    //   903: l2i
    //   904: ldc -160294279
    //   906: ixor
    //   907: ixor
    //   908: lookupswitch default -> 1154, -3321429 -> 936, 1887594210 -> 893
    //   936: getstatic bigname/zprestige/webhack/util/WurstPlusThree/WurstplusThreeCrystalUtil$1.$SwitchMap$net$minecraft$world$EnumDifficulty : [I
    //   939: getstatic Perryc.0 : I
    //   942: ifle -> 955
    //   945: ldc2_w -463959366
    //   948: l2i
    //   949: ldc -1478194791
    //   951: ixor
    //   952: goto -> 962
    //   955: ldc2_w 1571237086
    //   958: l2i
    //   959: ldc 1793539152
    //   961: ixor
    //   962: ldc2_w -224142602
    //   965: l2i
    //   966: ldc 447802084
    //   968: ixor
    //   969: ixor
    //   970: lookupswitch default -> 996, -1414581455 -> 1138, -668616710 -> 955
    //   996: getstatic net/minecraft/world/EnumDifficulty.HARD : Lnet/minecraft/world/EnumDifficulty;
    //   999: getstatic Perryc.0 : I
    //   1002: ifle -> 1015
    //   1005: ldc2_w 1537821940
    //   1008: l2i
    //   1009: ldc 1959520156
    //   1011: ixor
    //   1012: goto -> 1022
    //   1015: ldc2_w 393955283
    //   1018: l2i
    //   1019: ldc -1291720396
    //   1021: ixor
    //   1022: ldc2_w -1312953006
    //   1025: l2i
    //   1026: ldc 902619276
    //   1028: ixor
    //   1029: ixor
    //   1030: lookupswitch default -> 1160, -1424775498 -> 1015, 537633593 -> 1056
    //   1056: invokevirtual ordinal : ()I
    //   1059: ldc2_w -495514803
    //   1062: l2i
    //   1063: ldc -495514807
    //   1065: ixor
    //   1066: iastore
    //   1067: goto -> 1129
    //   1070: getstatic Perryc.1 : I
    //   1073: ifeq -> 1086
    //   1076: ldc2_w -1424081257
    //   1079: l2i
    //   1080: ldc -647732906
    //   1082: ixor
    //   1083: goto -> 1093
    //   1086: ldc2_w 1500876927
    //   1089: l2i
    //   1090: ldc -991742784
    //   1092: ixor
    //   1093: ldc2_w -2009929796
    //   1096: l2i
    //   1097: ldc 397631404
    //   1099: ixor
    //   1100: ixor
    //   1101: lookupswitch default -> 1128, -302258223 -> 1140, 976920661 -> 1086
    //   1128: astore_0
    //   1129: return
    //   1130: aconst_null
    //   1131: athrow
    //   1132: aconst_null
    //   1133: athrow
    //   1134: aconst_null
    //   1135: athrow
    //   1136: aconst_null
    //   1137: athrow
    //   1138: aconst_null
    //   1139: athrow
    //   1140: aconst_null
    //   1141: athrow
    //   1142: aconst_null
    //   1143: athrow
    //   1144: aconst_null
    //   1145: athrow
    //   1146: aconst_null
    //   1147: athrow
    //   1148: aconst_null
    //   1149: athrow
    //   1150: aconst_null
    //   1151: athrow
    //   1152: aconst_null
    //   1153: athrow
    //   1154: aconst_null
    //   1155: athrow
    //   1156: aconst_null
    //   1157: athrow
    //   1158: aconst_null
    //   1159: athrow
    //   1160: aconst_null
    //   1161: athrow
    //   1162: aconst_null
    //   1163: athrow
    //   1164: aconst_null
    //   1165: athrow
    // Exception table:
    //   from	to	target	type
    //   123	311	314	java/lang/NoSuchFieldError
    //   373	563	566	java/lang/NoSuchFieldError
    //   625	815	818	java/lang/NoSuchFieldError
    //   877	1067	1070	java/lang/NoSuchFieldError
  }
}


/* Location:              C:\Users\alex\Desktop\webhack\WebHack-0.8-obf_sussy_1.jar!\bigname\zprestige\webhac\\util\WurstPlusThree\WurstplusThreeCrystalUtil$1.class
 * Java compiler version: 8 (52.0)
 * JD-Core Version:       1.1.3
 */