package bigname.zprestige.webhack.util.WurstPlusThree;

import Perry1;
import Perryc;
import bigname.zprestige.webhack.util.Globals;
import java.awt.Color;
import java.util.List;
import net.minecraft.block.Block;
import net.minecraft.entity.Entity;
import net.minecraft.entity.player.EntityPlayer;
import net.minecraft.item.ItemStack;
import net.minecraft.util.math.BlockPos;
import net.minecraft.util.math.Vec3d;

public class WurstplusThreeEntityUtil implements Globals {
  public static Color getColor(Entity entity, int red, int green, int blue, int alpha, boolean colorFriends) {
    if (Perryc.0 <= 0) {
      null;
    } else {
      if (null != null)
        throw (Throwable)null; 
      null;
    } 
    if (null != null)
      throw (Throwable)null; 
    null;
  }
  
  public static Vec3d[] getUnsafeBlockArrayFromVec3d(Vec3d paramVec3d, int paramInt, boolean paramBoolean) {
    return Perry1.0E(null, (int)892465390L ^ 0x332D994A, paramVec3d, paramInt, paramBoolean);
  }
  
  public static List getSphere(BlockPos loc, float r, int h, boolean hollow, boolean sphere, int plusY) {
    if (Perryc.1 <= 0) {
      null;
    } else {
      if (null != null)
        throw (Throwable)null; 
      null;
    } 
    if (null != null)
      throw (Throwable)null; 
    null;
  }
  
  public static Vec3d getInterpolatedAmount(Entity paramEntity, float paramFloat) {
    return Perry1.K(null, (int)-2047009122L ^ 0xB1BCFE5D, paramEntity, paramFloat);
  }
  
  public static boolean isBedrockHole(BlockPos paramBlockPos) {
    return Perry1.6r(null, (int)-1211192060L ^ 0x9298B491, paramBlockPos);
  }
  
  public static boolean isBlockValid(BlockPos paramBlockPos) {
    return Perry1.6p(null, (int)666231453L ^ 0x7DF60A7E, paramBlockPos);
  }
  
  public static void setTimer(float paramFloat) {
    Perry1.0X(null, (int)-1286024641L ^ 0xE2D7B53D, paramFloat);
  }
  
  public static BlockPos getFlooredPos(Entity e) {
    if (Perryc.c < 0) {
      null;
    } else {
      if (null != null)
        throw (Throwable)null; 
      null;
    } 
    if (null != null)
      throw (Throwable)null; 
    null;
  }
  
  public static Vec3d getInterpolatedRenderPos(Entity paramEntity, float paramFloat) {
    return Perry1.L(null, (int)-1458650797L ^ 0xCD0A0013, paramEntity, paramFloat);
  }
  
  public static double sigmoid(double paramDouble) {
    return Perry1.1q(null, (int)-2120086820L ^ 0xF33EE7D8, paramDouble);
  }
  
  public static boolean isInLiquid() {
    if (Perryc.1 <= 0) {
      null;
    } else {
      if (null != null)
        throw (Throwable)null; 
      null;
    } 
    if (null != null)
      throw (Throwable)null; 
    null;
  }
  
  public static Vec3d[] getOffsets(int y, boolean floor) {
    if (Perryc.c < 0) {
      null;
    } else {
      if (null != null)
        throw (Throwable)null; 
      null;
    } 
    if (null != null)
      throw (Throwable)null; 
    null;
  }
  
  public WurstplusThreeEntityUtil() {
    // Byte code:
    //   0: getstatic Perryc.0 : I
    //   3: ifle -> 17
    //   6: ldc2_w -481794406
    //   9: l2i
    //   10: ldc_w -839547289
    //   13: ixor
    //   14: goto -> 25
    //   17: ldc2_w 685150318
    //   20: l2i
    //   21: ldc_w -1140569444
    //   24: ixor
    //   25: ldc2_w 1327690059
    //   28: l2i
    //   29: ldc_w 512797496
    //   32: ixor
    //   33: ixor
    //   34: lookupswitch default -> 126, -983531391 -> 60, 2131737230 -> 17
    //   60: aload_0
    //   61: getstatic Perryc.c : I
    //   64: iflt -> 78
    //   67: ldc2_w -1623217168
    //   70: l2i
    //   71: ldc_w 142558445
    //   74: ixor
    //   75: goto -> 86
    //   78: ldc2_w -420021545
    //   81: l2i
    //   82: ldc_w 1139920682
    //   85: ixor
    //   86: ldc2_w -208891695
    //   89: l2i
    //   90: ldc_w -497325245
    //   93: ixor
    //   94: ixor
    //   95: lookupswitch default -> 120, -2036919153 -> 124, -1788695870 -> 78
    //   120: invokespecial <init> : ()V
    //   123: return
    //   124: aconst_null
    //   125: athrow
    //   126: aconst_null
    //   127: athrow
    // Local variable table:
    //   start	length	slot	name	descriptor
    //   0	124	0	this	Lbigname/zprestige/webhack/util/WurstPlusThree/WurstplusThreeEntityUtil;
  }
  
  public static List getUnsafeBlocks(Entity paramEntity, int paramInt, boolean paramBoolean) {
    return Perry1.4Y(null, (int)1187970013L ^ 0x4853DCC3, paramEntity, paramInt, paramBoolean);
  }
  
  public static List getUnsafeBlocksFromVec3d(Vec3d pos, int height, boolean floor) {
    // Byte code:
    //   0: goto -> 8
    //   3: dup
    //   4: ifnull -> 3139
    //   7: athrow
    //   8: aconst_null
    //   9: getstatic Perryc.0 : I
    //   12: ifgt -> 3131
    //   15: pop
    //   16: aconst_null
    //   17: goto -> 3123
    //   20: nop
    //   21: nop
    //   22: nop
    //   23: athrow
    //   24: new java/util/ArrayList
    //   27: dup
    //   28: getstatic Perryc.0 : I
    //   31: ifle -> 45
    //   34: ldc2_w 422763216
    //   37: l2i
    //   38: ldc_w 1184124111
    //   41: ixor
    //   42: goto -> 53
    //   45: ldc2_w -1428365684
    //   48: l2i
    //   49: ldc_w 27733450
    //   52: ixor
    //   53: ldc2_w -1373947893
    //   56: l2i
    //   57: ldc_w 1311569212
    //   60: ixor
    //   61: ixor
    //   62: lookupswitch default -> 3046, -1080992984 -> 45, 1263287921 -> 88
    //   88: goto -> 92
    //   91: athrow
    //   92: invokespecial <init> : ()V
    //   95: goto -> 99
    //   98: athrow
    //   99: getstatic Perryc.0 : I
    //   102: ifle -> 116
    //   105: ldc2_w 1776313926
    //   108: l2i
    //   109: ldc_w -997895560
    //   112: ixor
    //   113: goto -> 124
    //   116: ldc2_w -288054477
    //   119: l2i
    //   120: ldc_w 1022523828
    //   123: ixor
    //   124: ldc2_w 1462262787
    //   127: l2i
    //   128: ldc_w -735428778
    //   131: ixor
    //   132: ixor
    //   133: lookupswitch default -> 3090, 778524523 -> 116, 1361361362 -> 160
    //   160: astore_3
    //   161: getstatic Perryc.c : I
    //   164: iflt -> 178
    //   167: ldc2_w 546024713
    //   170: l2i
    //   171: ldc_w -866980655
    //   174: ixor
    //   175: goto -> 186
    //   178: ldc2_w 1377009643
    //   181: l2i
    //   182: ldc_w 531484957
    //   185: ixor
    //   186: ldc2_w -1868446997
    //   189: l2i
    //   190: ldc_w 150888317
    //   193: ixor
    //   194: ixor
    //   195: lookupswitch default -> 220, -1223528580 -> 178, 1954995278 -> 3060
    //   220: iload_1
    //   221: getstatic Perryc.0 : I
    //   224: ifle -> 238
    //   227: ldc2_w -35856704
    //   230: l2i
    //   231: ldc_w -1187670109
    //   234: ixor
    //   235: goto -> 246
    //   238: ldc2_w 1466224401
    //   241: l2i
    //   242: ldc_w -1197632647
    //   245: ixor
    //   246: ldc2_w 33958379
    //   249: l2i
    //   250: ldc_w -745365532
    //   253: ixor
    //   254: ixor
    //   255: lookupswitch default -> 280, -1786904724 -> 3042, 30231728 -> 238
    //   280: iload_2
    //   281: getstatic Perryc.1 : I
    //   284: ifeq -> 298
    //   287: ldc2_w 2053554642
    //   290: l2i
    //   291: ldc_w 1982852333
    //   294: ixor
    //   295: goto -> 306
    //   298: ldc2_w 582263619
    //   301: l2i
    //   302: ldc_w -1874639752
    //   305: ixor
    //   306: ldc2_w -2087080563
    //   309: l2i
    //   310: ldc_w -371733100
    //   313: ixor
    //   314: ixor
    //   315: lookupswitch default -> 340, -1970875468 -> 298, 1711754534 -> 3034
    //   340: goto -> 344
    //   343: athrow
    //   344: invokestatic getOffsets : (IZ)[Lnet/minecraft/util/math/Vec3d;
    //   347: goto -> 351
    //   350: athrow
    //   351: getstatic Perryc.c : I
    //   354: iflt -> 368
    //   357: ldc2_w 2052482432
    //   360: l2i
    //   361: ldc_w -153066543
    //   364: ixor
    //   365: goto -> 376
    //   368: ldc2_w -643392260
    //   371: l2i
    //   372: ldc_w 1625288288
    //   375: ixor
    //   376: ldc2_w -1292485553
    //   379: l2i
    //   380: ldc_w -1118429599
    //   383: ixor
    //   384: ixor
    //   385: lookupswitch default -> 3082, -2095700865 -> 368, -1227272014 -> 412
    //   412: astore #4
    //   414: getstatic Perryc.c : I
    //   417: iflt -> 431
    //   420: ldc2_w -592939072
    //   423: l2i
    //   424: ldc_w 957787379
    //   427: ixor
    //   428: goto -> 439
    //   431: ldc2_w 398493216
    //   434: l2i
    //   435: ldc_w -1121078707
    //   438: ixor
    //   439: ldc2_w -1754362456
    //   442: l2i
    //   443: ldc_w 1383316777
    //   446: ixor
    //   447: ixor
    //   448: lookupswitch default -> 3062, 547613618 -> 431, 1878000876 -> 476
    //   476: aload #4
    //   478: arraylength
    //   479: getstatic Perryc.1 : I
    //   482: ifeq -> 496
    //   485: ldc2_w -1797551652
    //   488: l2i
    //   489: ldc_w -865875000
    //   492: ixor
    //   493: goto -> 504
    //   496: ldc2_w -941575055
    //   499: l2i
    //   500: ldc_w -1712858391
    //   503: ixor
    //   504: ldc2_w 807697436
    //   507: l2i
    //   508: ldc_w 1731912058
    //   511: ixor
    //   512: ixor
    //   513: lookupswitch default -> 540, -1591502180 -> 496, 262594418 -> 3100
    //   540: istore #5
    //   542: ldc2_w 1141365979
    //   545: l2i
    //   546: ldc_w 1141365979
    //   549: ixor
    //   550: getstatic Perryc.0 : I
    //   553: ifle -> 567
    //   556: ldc2_w 1509381968
    //   559: l2i
    //   560: ldc_w -526044022
    //   563: ixor
    //   564: goto -> 575
    //   567: ldc2_w -1047920546
    //   570: l2i
    //   571: ldc_w -323217547
    //   574: ixor
    //   575: ldc2_w 1304955090
    //   578: l2i
    //   579: ldc_w -1176518759
    //   582: ixor
    //   583: ixor
    //   584: lookupswitch default -> 3102, -652107680 -> 612, 1296422033 -> 567
    //   612: istore #6
    //   614: getstatic Perryc.1 : I
    //   617: ifeq -> 631
    //   620: ldc2_w 1084742032
    //   623: l2i
    //   624: ldc_w 958556790
    //   627: ixor
    //   628: goto -> 639
    //   631: ldc2_w -528292847
    //   634: l2i
    //   635: ldc_w -1040903769
    //   638: ixor
    //   639: ldc2_w 300207783
    //   642: l2i
    //   643: ldc_w -1623853493
    //   646: ixor
    //   647: ixor
    //   648: lookupswitch default -> 3050, -1348022950 -> 676, -145454326 -> 631
    //   676: iload #6
    //   678: getstatic Perryc.0 : I
    //   681: ifle -> 695
    //   684: ldc2_w -945231800
    //   687: l2i
    //   688: ldc_w -1375329630
    //   691: ixor
    //   692: goto -> 703
    //   695: ldc2_w 630827444
    //   698: l2i
    //   699: ldc_w -1667992351
    //   702: ixor
    //   703: ldc2_w -237237759
    //   706: l2i
    //   707: ldc_w -1762177134
    //   710: ixor
    //   711: ixor
    //   712: lookupswitch default -> 3038, -567895866 -> 740, 243634041 -> 695
    //   740: iload #5
    //   742: if_icmpge -> 756
    //   745: ldc2_w 739946676
    //   748: l2i
    //   749: ldc_w 115231670
    //   752: ixor
    //   753: goto -> 764
    //   756: ldc2_w -1343698766
    //   759: l2i
    //   760: ldc_w -2060700721
    //   763: ixor
    //   764: ldc2_w -117523431
    //   767: l2i
    //   768: ldc_w 737500580
    //   771: ixor
    //   772: ixor
    //   773: tableswitch default -> 745, -103867713 -> 796, -103867712 -> 2970
    //   796: getstatic Perryc.1 : I
    //   799: ifeq -> 813
    //   802: ldc2_w 327160274
    //   805: l2i
    //   806: ldc_w -1112463583
    //   809: ixor
    //   810: goto -> 821
    //   813: ldc2_w 782641877
    //   816: l2i
    //   817: ldc_w -413484745
    //   820: ixor
    //   821: ldc2_w -1467490285
    //   824: l2i
    //   825: ldc_w 870132537
    //   828: ixor
    //   829: ixor
    //   830: lookupswitch default -> 856, 475618701 -> 813, 896269785 -> 3054
    //   856: aload #4
    //   858: getstatic Perryc.0 : I
    //   861: ifle -> 875
    //   864: ldc2_w 1987299558
    //   867: l2i
    //   868: ldc_w 66159029
    //   871: ixor
    //   872: goto -> 883
    //   875: ldc2_w -495419374
    //   878: l2i
    //   879: ldc_w -499609628
    //   882: ixor
    //   883: ldc2_w 269746729
    //   886: l2i
    //   887: ldc_w -2032725231
    //   890: ixor
    //   891: ixor
    //   892: lookupswitch default -> 920, -970726464 -> 875, -482256789 -> 3106
    //   920: iload #6
    //   922: aaload
    //   923: getstatic Perryc.1 : I
    //   926: ifeq -> 940
    //   929: ldc2_w -326875374
    //   932: l2i
    //   933: ldc_w -1532094167
    //   936: ixor
    //   937: goto -> 948
    //   940: ldc2_w 1111680822
    //   943: l2i
    //   944: ldc_w -885728867
    //   947: ixor
    //   948: ldc2_w 741589364
    //   951: l2i
    //   952: ldc_w -1383158670
    //   955: ixor
    //   956: ixor
    //   957: lookupswitch default -> 3108, -912837827 -> 940, 147542957 -> 984
    //   984: astore #7
    //   986: new net/minecraft/util/math/BlockPos
    //   989: dup
    //   990: getstatic Perryc.c : I
    //   993: iflt -> 1007
    //   996: ldc2_w -659004548
    //   999: l2i
    //   1000: ldc_w 1374413979
    //   1003: ixor
    //   1004: goto -> 1015
    //   1007: ldc2_w 643377223
    //   1010: l2i
    //   1011: ldc_w 1840474572
    //   1014: ixor
    //   1015: ldc2_w -990843022
    //   1018: l2i
    //   1019: ldc_w -814157586
    //   1022: ixor
    //   1023: ixor
    //   1024: lookupswitch default -> 1052, -2099537797 -> 3110, -52397069 -> 1007
    //   1052: aload_0
    //   1053: getstatic Perryc.c : I
    //   1056: iflt -> 1070
    //   1059: ldc2_w 415843615
    //   1062: l2i
    //   1063: ldc_w -1150696225
    //   1066: ixor
    //   1067: goto -> 1078
    //   1070: ldc2_w 849701568
    //   1073: l2i
    //   1074: ldc_w -1570758745
    //   1077: ixor
    //   1078: ldc2_w -946117509
    //   1081: l2i
    //   1082: ldc_w -1773370196
    //   1085: ixor
    //   1086: ixor
    //   1087: lookupswitch default -> 1112, -1668561954 -> 1070, -227057385 -> 3048
    //   1112: goto -> 1116
    //   1115: athrow
    //   1116: invokespecial <init> : (Lnet/minecraft/util/math/Vec3d;)V
    //   1119: goto -> 1123
    //   1122: athrow
    //   1123: getstatic Perryc.0 : I
    //   1126: ifle -> 1140
    //   1129: ldc2_w 2112689028
    //   1132: l2i
    //   1133: ldc_w -517787535
    //   1136: ixor
    //   1137: goto -> 1148
    //   1140: ldc2_w -1965471310
    //   1143: l2i
    //   1144: ldc_w -371580254
    //   1147: ixor
    //   1148: ldc2_w 1502611026
    //   1151: l2i
    //   1152: ldc_w -1893711973
    //   1155: ixor
    //   1156: ixor
    //   1157: lookupswitch default -> 1184, -1692125518 -> 1140, 1249778236 -> 3066
    //   1184: aload #7
    //   1186: getstatic Perryc.1 : I
    //   1189: ifeq -> 1203
    //   1192: ldc2_w 2088363401
    //   1195: l2i
    //   1196: ldc_w -1913858866
    //   1199: ixor
    //   1200: goto -> 1211
    //   1203: ldc2_w -1147330868
    //   1206: l2i
    //   1207: ldc_w -1158477400
    //   1210: ixor
    //   1211: ldc2_w 1424556304
    //   1214: l2i
    //   1215: ldc_w -1326376676
    //   1218: ixor
    //   1219: ixor
    //   1220: lookupswitch default -> 1248, -859494312 -> 1203, 361572683 -> 3094
    //   1248: getfield field_72450_a : D
    //   1251: getstatic Perryc.0 : I
    //   1254: ifle -> 1268
    //   1257: ldc2_w 384203066
    //   1260: l2i
    //   1261: ldc_w -965273469
    //   1264: ixor
    //   1265: goto -> 1276
    //   1268: ldc2_w 106693986
    //   1271: l2i
    //   1272: ldc_w -2091878570
    //   1275: ixor
    //   1276: ldc2_w 1922294956
    //   1279: l2i
    //   1280: ldc_w -1202154423
    //   1283: ixor
    //   1284: ixor
    //   1285: lookupswitch default -> 1312, -914222993 -> 1268, 442110300 -> 3084
    //   1312: aload #7
    //   1314: getstatic Perryc.c : I
    //   1317: iflt -> 1331
    //   1320: ldc2_w -1981808804
    //   1323: l2i
    //   1324: ldc_w 635750644
    //   1327: ixor
    //   1328: goto -> 1339
    //   1331: ldc2_w -9897882
    //   1334: l2i
    //   1335: ldc_w 2035769235
    //   1338: ixor
    //   1339: ldc2_w 613120585
    //   1342: l2i
    //   1343: ldc_w -181989171
    //   1346: ixor
    //   1347: ixor
    //   1348: lookupswitch default -> 3064, 1469304177 -> 1376, 2107071788 -> 1331
    //   1376: getfield field_72448_b : D
    //   1379: getstatic Perryc.0 : I
    //   1382: ifle -> 1396
    //   1385: ldc2_w 1158304636
    //   1388: l2i
    //   1389: ldc_w 680137346
    //   1392: ixor
    //   1393: goto -> 1404
    //   1396: ldc2_w 1460962444
    //   1399: l2i
    //   1400: ldc_w -109814946
    //   1403: ixor
    //   1404: ldc2_w -1645681421
    //   1407: l2i
    //   1408: ldc_w 771934380
    //   1411: ixor
    //   1412: ixor
    //   1413: lookupswitch default -> 1440, -796100070 -> 1396, -563450463 -> 3104
    //   1440: aload #7
    //   1442: getstatic Perryc.0 : I
    //   1445: ifle -> 1459
    //   1448: ldc2_w -1936601906
    //   1451: l2i
    //   1452: ldc_w -76772835
    //   1455: ixor
    //   1456: goto -> 1467
    //   1459: ldc2_w 549090991
    //   1462: l2i
    //   1463: ldc_w 810691717
    //   1466: ixor
    //   1467: ldc2_w 885999682
    //   1470: l2i
    //   1471: ldc_w 1258259381
    //   1474: ixor
    //   1475: ixor
    //   1476: lookupswitch default -> 3092, 164465956 -> 1459, 1859686877 -> 1504
    //   1504: getfield field_72449_c : D
    //   1507: getstatic Perryc.c : I
    //   1510: iflt -> 1524
    //   1513: ldc2_w -1146440479
    //   1516: l2i
    //   1517: ldc_w 2053638731
    //   1520: ixor
    //   1521: goto -> 1532
    //   1524: ldc2_w 758067332
    //   1527: l2i
    //   1528: ldc_w -231213562
    //   1531: ixor
    //   1532: ldc2_w -1544581221
    //   1535: l2i
    //   1536: ldc_w -918381758
    //   1539: ixor
    //   1540: ixor
    //   1541: lookupswitch default -> 1568, -1418745229 -> 3052, 1788588365 -> 1524
    //   1568: goto -> 1572
    //   1571: athrow
    //   1572: invokevirtual func_177963_a : (DDD)Lnet/minecraft/util/math/BlockPos;
    //   1575: goto -> 1579
    //   1578: athrow
    //   1579: getstatic Perryc.c : I
    //   1582: iflt -> 1596
    //   1585: ldc2_w -1265438930
    //   1588: l2i
    //   1589: ldc_w 697184989
    //   1592: ixor
    //   1593: goto -> 1604
    //   1596: ldc2_w -1378375698
    //   1599: l2i
    //   1600: ldc_w 1727437032
    //   1603: ixor
    //   1604: ldc2_w 1305229533
    //   1607: l2i
    //   1608: ldc_w 1094353690
    //   1611: ixor
    //   1612: ixor
    //   1613: lookupswitch default -> 3086, -1846909388 -> 1596, -942177087 -> 1640
    //   1640: astore #8
    //   1642: getstatic Perryc.0 : I
    //   1645: ifle -> 1659
    //   1648: ldc2_w 2108744878
    //   1651: l2i
    //   1652: ldc_w -1671736400
    //   1655: ixor
    //   1656: goto -> 1667
    //   1659: ldc2_w -945133655
    //   1662: l2i
    //   1663: ldc_w 146346066
    //   1666: ixor
    //   1667: ldc2_w -1960455132
    //   1670: l2i
    //   1671: ldc_w 1565267068
    //   1674: ixor
    //   1675: ixor
    //   1676: lookupswitch default -> 1704, 931297094 -> 3068, 1537269209 -> 1659
    //   1704: getstatic bigname/zprestige/webhack/util/WurstPlusThree/WurstplusThreeEntityUtil.mc : Lnet/minecraft/client/Minecraft;
    //   1707: getstatic Perryc.0 : I
    //   1710: ifle -> 1724
    //   1713: ldc2_w 14270028
    //   1716: l2i
    //   1717: ldc_w 853313807
    //   1720: ixor
    //   1721: goto -> 1732
    //   1724: ldc2_w -1760669556
    //   1727: l2i
    //   1728: ldc_w -152877268
    //   1731: ixor
    //   1732: ldc2_w 890510996
    //   1735: l2i
    //   1736: ldc_w -782363729
    //   1739: ixor
    //   1740: ixor
    //   1741: lookupswitch default -> 1768, -1933822959 -> 1724, -699450760 -> 3076
    //   1768: getfield field_71441_e : Lnet/minecraft/client/multiplayer/WorldClient;
    //   1771: getstatic Perryc.0 : I
    //   1774: ifle -> 1788
    //   1777: ldc2_w 845006393
    //   1780: l2i
    //   1781: ldc_w -1990143710
    //   1784: ixor
    //   1785: goto -> 1796
    //   1788: ldc2_w -26363670
    //   1791: l2i
    //   1792: ldc_w -1363911970
    //   1795: ixor
    //   1796: ldc2_w 1334198966
    //   1799: l2i
    //   1800: ldc_w 866003049
    //   1803: ixor
    //   1804: ixor
    //   1805: lookupswitch default -> 1832, -953844284 -> 3040, 1347708629 -> 1788
    //   1832: aload #8
    //   1834: getstatic Perryc.0 : I
    //   1837: ifle -> 1851
    //   1840: ldc2_w -1543735148
    //   1843: l2i
    //   1844: ldc_w 689380986
    //   1847: ixor
    //   1848: goto -> 1859
    //   1851: ldc2_w -511907372
    //   1854: l2i
    //   1855: ldc_w 314831667
    //   1858: ixor
    //   1859: ldc2_w 1340744605
    //   1862: l2i
    //   1863: ldc_w 1490301343
    //   1866: ixor
    //   1867: ixor
    //   1868: lookupswitch default -> 3098, -1646955284 -> 1851, -461305627 -> 1896
    //   1896: goto -> 1900
    //   1899: athrow
    //   1900: invokevirtual func_180495_p : (Lnet/minecraft/util/math/BlockPos;)Lnet/minecraft/block/state/IBlockState;
    //   1903: goto -> 1907
    //   1906: athrow
    //   1907: getstatic Perryc.1 : I
    //   1910: ifeq -> 1924
    //   1913: ldc2_w -1072543279
    //   1916: l2i
    //   1917: ldc_w -663931291
    //   1920: ixor
    //   1921: goto -> 1932
    //   1924: ldc2_w 757792536
    //   1927: l2i
    //   1928: ldc_w 1203813923
    //   1931: ixor
    //   1932: ldc2_w -1409863528
    //   1935: l2i
    //   1936: ldc_w 823867931
    //   1939: ixor
    //   1940: ixor
    //   1941: lookupswitch default -> 3112, -2104265417 -> 1924, -268022856 -> 1968
    //   1968: goto -> 1972
    //   1971: athrow
    //   1972: invokeinterface func_177230_c : ()Lnet/minecraft/block/Block;
    //   1977: goto -> 1981
    //   1980: athrow
    //   1981: getstatic Perryc.0 : I
    //   1984: ifle -> 1998
    //   1987: ldc2_w -1061612138
    //   1990: l2i
    //   1991: ldc_w -2127902648
    //   1994: ixor
    //   1995: goto -> 2006
    //   1998: ldc2_w -399029276
    //   2001: l2i
    //   2002: ldc_w 1151266888
    //   2005: ixor
    //   2006: ldc2_w -454683519
    //   2009: l2i
    //   2010: ldc_w 509975031
    //   2013: ixor
    //   2014: ixor
    //   2015: lookupswitch default -> 2040, -1156558680 -> 3096, -570853831 -> 1998
    //   2040: astore #9
    //   2042: getstatic Perryc.1 : I
    //   2045: ifeq -> 2059
    //   2048: ldc2_w -2111563066
    //   2051: l2i
    //   2052: ldc_w 905297609
    //   2055: ixor
    //   2056: goto -> 2067
    //   2059: ldc2_w -822416499
    //   2062: l2i
    //   2063: ldc_w -1586869440
    //   2066: ixor
    //   2067: ldc2_w 379324871
    //   2070: l2i
    //   2071: ldc_w 922310631
    //   2074: ixor
    //   2075: ixor
    //   2076: lookupswitch default -> 2104, -1749747153 -> 3070, -1426216847 -> 2059
    //   2104: aload #9
    //   2106: instanceof net/minecraft/block/BlockAir
    //   2109: ifne -> 2123
    //   2112: ldc2_w -1687997459
    //   2115: l2i
    //   2116: ldc_w 2050322791
    //   2119: ixor
    //   2120: goto -> 2131
    //   2123: ldc2_w -1866273447
    //   2126: l2i
    //   2127: ldc_w 1905569748
    //   2130: ixor
    //   2131: ldc2_w -1617658979
    //   2134: l2i
    //   2135: ldc_w -1076876916
    //   2138: ixor
    //   2139: ixor
    //   2140: tableswitch default -> 2112, -1055780709 -> 2164, -1055780708 -> 2767
    //   2164: getstatic Perryc.1 : I
    //   2167: ifeq -> 2181
    //   2170: ldc2_w -1287445169
    //   2173: l2i
    //   2174: ldc_w -1176380250
    //   2177: ixor
    //   2178: goto -> 2189
    //   2181: ldc2_w -76589944
    //   2184: l2i
    //   2185: ldc_w -593029375
    //   2188: ixor
    //   2189: ldc2_w 2060872285
    //   2192: l2i
    //   2193: ldc_w -632330523
    //   2196: ixor
    //   2197: ixor
    //   2198: lookupswitch default -> 3056, -2024714447 -> 2224, -1438911151 -> 2181
    //   2224: aload #9
    //   2226: instanceof net/minecraft/block/BlockLiquid
    //   2229: ifne -> 2243
    //   2232: ldc2_w -129587049
    //   2235: l2i
    //   2236: ldc_w -2144205914
    //   2239: ixor
    //   2240: goto -> 2251
    //   2243: ldc2_w -1933283440
    //   2246: l2i
    //   2247: ldc_w -189741918
    //   2250: ixor
    //   2251: ldc2_w 1028221907
    //   2254: l2i
    //   2255: ldc_w -1406699045
    //   2258: ixor
    //   2259: ixor
    //   2260: tableswitch default -> 2232, -384124615 -> 2284, -384124614 -> 2767
    //   2284: getstatic Perryc.1 : I
    //   2287: ifeq -> 2301
    //   2290: ldc2_w 1627591796
    //   2293: l2i
    //   2294: ldc_w 1214223001
    //   2297: ixor
    //   2298: goto -> 2309
    //   2301: ldc2_w 1192497501
    //   2304: l2i
    //   2305: ldc_w -1439494871
    //   2308: ixor
    //   2309: ldc2_w -726382238
    //   2312: l2i
    //   2313: ldc_w 538778064
    //   2316: ixor
    //   2317: ixor
    //   2318: lookupswitch default -> 2344, -571091361 -> 3058, -61437092 -> 2301
    //   2344: aload #9
    //   2346: instanceof net/minecraft/block/BlockTallGrass
    //   2349: ifne -> 2363
    //   2352: ldc2_w 2025857037
    //   2355: l2i
    //   2356: ldc_w -1861074481
    //   2359: ixor
    //   2360: goto -> 2371
    //   2363: ldc2_w 922841468
    //   2366: l2i
    //   2367: ldc_w -556592961
    //   2370: ixor
    //   2371: ldc2_w 1579960952
    //   2374: l2i
    //   2375: ldc_w -455773110
    //   2378: ixor
    //   2379: ixor
    //   2380: tableswitch default -> 2352, 1395351536 -> 2404, 1395351537 -> 2767
    //   2404: getstatic Perryc.c : I
    //   2407: iflt -> 2421
    //   2410: ldc2_w 1876725475
    //   2413: l2i
    //   2414: ldc_w -40661818
    //   2417: ixor
    //   2418: goto -> 2429
    //   2421: ldc2_w -1227568267
    //   2424: l2i
    //   2425: ldc_w 239845860
    //   2428: ixor
    //   2429: ldc2_w -1003916241
    //   2432: l2i
    //   2433: ldc_w 2089440032
    //   2436: ixor
    //   2437: ixor
    //   2438: lookupswitch default -> 2464, -348784683 -> 2421, 720119082 -> 3088
    //   2464: aload #9
    //   2466: instanceof net/minecraft/block/BlockFire
    //   2469: ifne -> 2483
    //   2472: ldc2_w 742484690
    //   2475: l2i
    //   2476: ldc_w -1990747437
    //   2479: ixor
    //   2480: goto -> 2491
    //   2483: ldc2_w -756840131
    //   2486: l2i
    //   2487: ldc_w 2012576061
    //   2490: ixor
    //   2491: ldc2_w -717015337
    //   2494: l2i
    //   2495: ldc_w 750262012
    //   2498: ixor
    //   2499: ixor
    //   2500: tableswitch default -> 2472, 1559089194 -> 2524, 1559089195 -> 2767
    //   2524: getstatic Perryc.1 : I
    //   2527: ifeq -> 2541
    //   2530: ldc2_w 414442819
    //   2533: l2i
    //   2534: ldc_w 1054259717
    //   2537: ixor
    //   2538: goto -> 2549
    //   2541: ldc2_w -1248918328
    //   2544: l2i
    //   2545: ldc_w 1768825726
    //   2548: ixor
    //   2549: ldc2_w -1455234431
    //   2552: l2i
    //   2553: ldc_w -1447589239
    //   2556: ixor
    //   2557: ixor
    //   2558: lookupswitch default -> 2584, 381287777 -> 2541, 646985550 -> 3072
    //   2584: aload #9
    //   2586: instanceof net/minecraft/block/BlockDeadBush
    //   2589: ifne -> 2603
    //   2592: ldc2_w -517664828
    //   2595: l2i
    //   2596: ldc_w -467727888
    //   2599: ixor
    //   2600: goto -> 2611
    //   2603: ldc2_w -251132894
    //   2606: l2i
    //   2607: ldc_w -198049263
    //   2610: ixor
    //   2611: ldc2_w 333859231
    //   2614: l2i
    //   2615: ldc_w 163639064
    //   2618: ixor
    //   2619: ixor
    //   2620: tableswitch default -> 2592, 521969843 -> 2644, 521969844 -> 2767
    //   2644: getstatic Perryc.c : I
    //   2647: iflt -> 2661
    //   2650: ldc2_w -870055534
    //   2653: l2i
    //   2654: ldc_w 849420889
    //   2657: ixor
    //   2658: goto -> 2669
    //   2661: ldc2_w 283932988
    //   2664: l2i
    //   2665: ldc_w 431855878
    //   2668: ixor
    //   2669: ldc2_w -265022443
    //   2672: l2i
    //   2673: ldc_w 1190244769
    //   2676: ixor
    //   2677: ixor
    //   2678: lookupswitch default -> 3036, -1080801906 -> 2704, 1212188287 -> 2661
    //   2704: aload #9
    //   2706: instanceof net/minecraft/block/BlockSnow
    //   2709: ifne -> 2723
    //   2712: ldc2_w -937216501
    //   2715: l2i
    //   2716: ldc_w -763077598
    //   2719: ixor
    //   2720: goto -> 2731
    //   2723: ldc2_w -1879701017
    //   2726: l2i
    //   2727: ldc_w -1789828145
    //   2730: ixor
    //   2731: ldc2_w -568576520
    //   2734: l2i
    //   2735: ldc_w 642849443
    //   2738: ixor
    //   2739: ixor
    //   2740: tableswitch default -> 2712, -487963278 -> 2764, -487963277 -> 2767
    //   2764: goto -> 2964
    //   2767: getstatic Perryc.c : I
    //   2770: iflt -> 2784
    //   2773: ldc2_w -334544337
    //   2776: l2i
    //   2777: ldc_w 1273340268
    //   2780: ixor
    //   2781: goto -> 2792
    //   2784: ldc2_w -1169592147
    //   2787: l2i
    //   2788: ldc_w -778473673
    //   2791: ixor
    //   2792: ldc2_w -1702104594
    //   2795: l2i
    //   2796: ldc_w 627770948
    //   2799: ixor
    //   2800: ixor
    //   2801: lookupswitch default -> 3044, -734992336 -> 2828, 403313897 -> 2784
    //   2828: aload_3
    //   2829: getstatic Perryc.1 : I
    //   2832: ifeq -> 2846
    //   2835: ldc2_w -1031768643
    //   2838: l2i
    //   2839: ldc_w 1071283547
    //   2842: ixor
    //   2843: goto -> 2854
    //   2846: ldc2_w -2040211286
    //   2849: l2i
    //   2850: ldc_w 584985022
    //   2853: ixor
    //   2854: ldc2_w -1695332712
    //   2857: l2i
    //   2858: ldc_w 1627943824
    //   2861: ixor
    //   2862: ixor
    //   2863: lookupswitch default -> 3078, 111230446 -> 2846, 1598145564 -> 2888
    //   2888: aload #7
    //   2890: getstatic Perryc.1 : I
    //   2893: ifeq -> 2907
    //   2896: ldc2_w 541954945
    //   2899: l2i
    //   2900: ldc_w -325420013
    //   2903: ixor
    //   2904: goto -> 2915
    //   2907: ldc2_w -1503553227
    //   2910: l2i
    //   2911: ldc_w 396656735
    //   2914: ixor
    //   2915: ldc2_w 151208702
    //   2918: l2i
    //   2919: ldc_w 2130872163
    //   2922: ixor
    //   2923: ixor
    //   2924: lookupswitch default -> 2952, -1160369649 -> 3080, 1043941818 -> 2907
    //   2952: goto -> 2956
    //   2955: athrow
    //   2956: invokevirtual add : (Ljava/lang/Object;)Z
    //   2959: goto -> 2963
    //   2962: athrow
    //   2963: pop
    //   2964: iinc #6, 1
    //   2967: goto -> 614
    //   2970: getstatic Perryc.0 : I
    //   2973: ifle -> 2987
    //   2976: ldc2_w -650082038
    //   2979: l2i
    //   2980: ldc_w -78669395
    //   2983: ixor
    //   2984: goto -> 2995
    //   2987: ldc2_w 1789027571
    //   2990: l2i
    //   2991: ldc_w 641893348
    //   2994: ixor
    //   2995: ldc2_w -959687525
    //   2998: l2i
    //   2999: ldc_w -566633240
    //   3002: ixor
    //   3003: ixor
    //   3004: lookupswitch default -> 3032, -847766161 -> 2987, 989501652 -> 3074
    //   3032: aload_3
    //   3033: areturn
    //   3034: aconst_null
    //   3035: athrow
    //   3036: aconst_null
    //   3037: athrow
    //   3038: aconst_null
    //   3039: athrow
    //   3040: aconst_null
    //   3041: athrow
    //   3042: aconst_null
    //   3043: athrow
    //   3044: aconst_null
    //   3045: athrow
    //   3046: aconst_null
    //   3047: athrow
    //   3048: aconst_null
    //   3049: athrow
    //   3050: aconst_null
    //   3051: athrow
    //   3052: aconst_null
    //   3053: athrow
    //   3054: aconst_null
    //   3055: athrow
    //   3056: aconst_null
    //   3057: athrow
    //   3058: aconst_null
    //   3059: athrow
    //   3060: aconst_null
    //   3061: athrow
    //   3062: aconst_null
    //   3063: athrow
    //   3064: aconst_null
    //   3065: athrow
    //   3066: aconst_null
    //   3067: athrow
    //   3068: aconst_null
    //   3069: athrow
    //   3070: aconst_null
    //   3071: athrow
    //   3072: aconst_null
    //   3073: athrow
    //   3074: aconst_null
    //   3075: athrow
    //   3076: aconst_null
    //   3077: athrow
    //   3078: aconst_null
    //   3079: athrow
    //   3080: aconst_null
    //   3081: athrow
    //   3082: aconst_null
    //   3083: athrow
    //   3084: aconst_null
    //   3085: athrow
    //   3086: aconst_null
    //   3087: athrow
    //   3088: aconst_null
    //   3089: athrow
    //   3090: aconst_null
    //   3091: athrow
    //   3092: aconst_null
    //   3093: athrow
    //   3094: aconst_null
    //   3095: athrow
    //   3096: aconst_null
    //   3097: athrow
    //   3098: aconst_null
    //   3099: athrow
    //   3100: aconst_null
    //   3101: athrow
    //   3102: aconst_null
    //   3103: athrow
    //   3104: aconst_null
    //   3105: athrow
    //   3106: aconst_null
    //   3107: athrow
    //   3108: aconst_null
    //   3109: athrow
    //   3110: aconst_null
    //   3111: athrow
    //   3112: aconst_null
    //   3113: athrow
    //   3114: pop
    //   3115: goto -> 24
    //   3118: pop
    //   3119: aconst_null
    //   3120: goto -> 3114
    //   3123: dup
    //   3124: ifnull -> 3114
    //   3127: checkcast java/lang/Throwable
    //   3130: athrow
    //   3131: dup
    //   3132: ifnull -> 3118
    //   3135: checkcast java/lang/Throwable
    //   3138: athrow
    //   3139: aconst_null
    //   3140: athrow
    // Local variable table:
    //   start	length	slot	name	descriptor
    //   1642	1322	8	targetPos	Lnet/minecraft/util/math/BlockPos;
    //   2042	922	9	block	Lnet/minecraft/block/Block;
    //   986	1978	7	vector	Lnet/minecraft/util/math/Vec3d;
    //   24	3010	0	pos	Lnet/minecraft/util/math/Vec3d;
    //   24	3010	1	height	I
    //   24	3010	2	floor	Z
    //   161	2873	3	vec3ds	Ljava/util/ArrayList;
    // Local variable type table:
    //   start	length	slot	name	signature
    //   161	2873	3	vec3ds	Ljava/util/ArrayList<Lnet/minecraft/util/math/Vec3d;>;
    // Exception table:
    //   from	to	target	type
    //   8	20	3123	finally
    //   91	98	98	finally
    //   91	98	91	finally
    //   91	98	3	finally
    //   91	98	98	finally
    //   91	98	3	java/lang/NullPointerException
    //   344	350	350	finally
    //   344	350	350	java/lang/IllegalStateException
    //   344	350	3	java/lang/ArrayIndexOutOfBoundsException
    //   344	350	350	java/lang/EnumConstantNotPresentException
    //   344	350	350	java/lang/RuntimeException
    //   1115	1122	1122	finally
    //   1115	1122	1115	finally
    //   1115	1122	3	finally
    //   1116	1122	1122	finally
    //   1116	1122	3	java/lang/EnumConstantNotPresentException
    //   1571	1578	1578	finally
    //   1571	1578	1578	java/lang/StringIndexOutOfBoundsException
    //   1571	1578	1578	finally
    //   1572	1578	1578	java/lang/EnumConstantNotPresentException
    //   1572	1578	1571	java/lang/ArithmeticException
    //   1899	1906	1906	finally
    //   1899	1906	1906	finally
    //   1900	1906	1899	finally
    //   1900	1906	1906	java/util/NoSuchElementException
    //   1900	1906	1899	finally
    //   1971	1980	1980	finally
    //   1971	1980	1971	finally
    //   1972	1980	1971	java/lang/RuntimeException
    //   1972	1980	1971	finally
    //   1972	1980	1980	java/lang/ClassCastException
    //   2955	2962	2962	finally
    //   2955	2962	2955	java/lang/IllegalArgumentException
    //   2955	2962	2962	finally
    //   2956	2962	2955	finally
    //   2956	2962	3	finally
    //   3123	3131	3123	finally
    //   3139	3141	3	finally
  }
  
  public static BlockPos getRoundedBlockPos(Entity entity) {
    if (Perryc.0 <= 0) {
      null;
    } else {
      if (null != null)
        throw (Throwable)null; 
      null;
    } 
    if (null != null)
      throw (Throwable)null; 
    null;
  }
  
  public static void attackEntity(Entity entity, boolean packet) {
    // Byte code:
    //   0: goto -> 8
    //   3: dup
    //   4: ifnull -> 983
    //   7: athrow
    //   8: aconst_null
    //   9: getstatic Perryc.1 : I
    //   12: ifgt -> 975
    //   15: pop
    //   16: aconst_null
    //   17: goto -> 967
    //   20: nop
    //   21: nop
    //   22: nop
    //   23: athrow
    //   24: getstatic Perryc.c : I
    //   27: iflt -> 41
    //   30: ldc2_w -949752838
    //   33: l2i
    //   34: ldc_w -588741892
    //   37: ixor
    //   38: goto -> 49
    //   41: ldc2_w 63103497
    //   44: l2i
    //   45: ldc_w 753745636
    //   48: ixor
    //   49: ldc2_w 1272880570
    //   52: l2i
    //   53: ldc_w 1272025661
    //   56: ixor
    //   57: ixor
    //   58: lookupswitch default -> 934, 461661825 -> 41, 790680426 -> 84
    //   84: iload_1
    //   85: ifeq -> 99
    //   88: ldc2_w -957346403
    //   91: l2i
    //   92: ldc_w 806606005
    //   95: ixor
    //   96: goto -> 107
    //   99: ldc2_w -245966271
    //   102: l2i
    //   103: ldc_w 129303402
    //   106: ixor
    //   107: ldc2_w 1258796853
    //   110: l2i
    //   111: ldc_w -905999716
    //   114: ixor
    //   115: ixor
    //   116: tableswitch default -> 88, 1947985025 -> 140, 1947985026 -> 542
    //   140: getstatic Perryc.1 : I
    //   143: ifeq -> 157
    //   146: ldc2_w 577260135
    //   149: l2i
    //   150: ldc_w 842887422
    //   153: ixor
    //   154: goto -> 165
    //   157: ldc2_w 858304539
    //   160: l2i
    //   161: ldc_w -1095837193
    //   164: ixor
    //   165: ldc2_w 438704815
    //   168: l2i
    //   169: ldc_w 1992072248
    //   172: ixor
    //   173: ixor
    //   174: lookupswitch default -> 944, -518197381 -> 200, 2093988878 -> 157
    //   200: getstatic bigname/zprestige/webhack/util/WurstPlusThree/WurstplusThreeEntityUtil.mc : Lnet/minecraft/client/Minecraft;
    //   203: getstatic Perryc.c : I
    //   206: iflt -> 220
    //   209: ldc2_w 1008101725
    //   212: l2i
    //   213: ldc_w -628580071
    //   216: ixor
    //   217: goto -> 228
    //   220: ldc2_w 1899121535
    //   223: l2i
    //   224: ldc_w 438982806
    //   227: ixor
    //   228: ldc2_w 2070620288
    //   231: l2i
    //   232: ldc_w -1965198743
    //   235: ixor
    //   236: ixor
    //   237: lookupswitch default -> 954, -1699854080 -> 264, 388534957 -> 220
    //   264: getfield field_71439_g : Lnet/minecraft/client/entity/EntityPlayerSP;
    //   267: getstatic Perryc.0 : I
    //   270: ifle -> 284
    //   273: ldc2_w -2010517042
    //   276: l2i
    //   277: ldc_w 225095975
    //   280: ixor
    //   281: goto -> 292
    //   284: ldc2_w 179266885
    //   287: l2i
    //   288: ldc_w 1896819220
    //   291: ixor
    //   292: ldc2_w -641584807
    //   295: l2i
    //   296: ldc_w -530299930
    //   299: ixor
    //   300: ixor
    //   301: lookupswitch default -> 328, -1125830058 -> 950, -512381989 -> 284
    //   328: getfield field_71174_a : Lnet/minecraft/client/network/NetHandlerPlayClient;
    //   331: new net/minecraft/network/play/client/CPacketUseEntity
    //   334: dup
    //   335: getstatic Perryc.1 : I
    //   338: ifeq -> 352
    //   341: ldc2_w -1803504346
    //   344: l2i
    //   345: ldc_w -1122368149
    //   348: ixor
    //   349: goto -> 360
    //   352: ldc2_w -1682862733
    //   355: l2i
    //   356: ldc_w -443447138
    //   359: ixor
    //   360: ldc2_w 1215545085
    //   363: l2i
    //   364: ldc_w 2069828830
    //   367: ixor
    //   368: ixor
    //   369: lookupswitch default -> 396, 448141934 -> 946, 450665462 -> 352
    //   396: aload_0
    //   397: getstatic Perryc.0 : I
    //   400: ifle -> 414
    //   403: ldc2_w 2073126650
    //   406: l2i
    //   407: ldc_w 58164654
    //   410: ixor
    //   411: goto -> 422
    //   414: ldc2_w 1886898325
    //   417: l2i
    //   418: ldc_w -1494837788
    //   421: ixor
    //   422: ldc2_w 1536679922
    //   425: l2i
    //   426: ldc_w -1790871420
    //   429: ixor
    //   430: ixor
    //   431: lookupswitch default -> 948, -1238350814 -> 414, 407370247 -> 456
    //   456: goto -> 460
    //   459: athrow
    //   460: invokespecial <init> : (Lnet/minecraft/entity/Entity;)V
    //   463: goto -> 467
    //   466: athrow
    //   467: getstatic Perryc.c : I
    //   470: iflt -> 484
    //   473: ldc2_w -2030735014
    //   476: l2i
    //   477: ldc_w -1195095572
    //   480: ixor
    //   481: goto -> 492
    //   484: ldc2_w -767772062
    //   487: l2i
    //   488: ldc_w 1376015230
    //   491: ixor
    //   492: ldc2_w -1033536389
    //   495: l2i
    //   496: ldc_w 1960047531
    //   499: ixor
    //   500: ixor
    //   501: lookupswitch default -> 938, -2004371610 -> 484, 915302092 -> 528
    //   528: goto -> 532
    //   531: athrow
    //   532: invokevirtual func_147297_a : (Lnet/minecraft/network/Packet;)V
    //   535: goto -> 539
    //   538: athrow
    //   539: goto -> 931
    //   542: getstatic Perryc.c : I
    //   545: iflt -> 559
    //   548: ldc2_w 1848367058
    //   551: l2i
    //   552: ldc_w -1503859348
    //   555: ixor
    //   556: goto -> 567
    //   559: ldc2_w 1113345586
    //   562: l2i
    //   563: ldc_w 681370194
    //   566: ixor
    //   567: ldc2_w -2075662397
    //   570: l2i
    //   571: ldc_w -469236501
    //   574: ixor
    //   575: ixor
    //   576: lookupswitch default -> 604, -1472669290 -> 952, 915067355 -> 559
    //   604: getstatic bigname/zprestige/webhack/util/WurstPlusThree/WurstplusThreeEntityUtil.mc : Lnet/minecraft/client/Minecraft;
    //   607: getstatic Perryc.0 : I
    //   610: ifle -> 624
    //   613: ldc2_w 1127589996
    //   616: l2i
    //   617: ldc_w -94167210
    //   620: ixor
    //   621: goto -> 632
    //   624: ldc2_w 76595990
    //   627: l2i
    //   628: ldc_w 84705503
    //   631: ixor
    //   632: ldc2_w -1012196168
    //   635: l2i
    //   636: ldc_w 1544441857
    //   639: ixor
    //   640: ixor
    //   641: lookupswitch default -> 936, -1640427664 -> 668, 653523843 -> 624
    //   668: getfield field_71442_b : Lnet/minecraft/client/multiplayer/PlayerControllerMP;
    //   671: getstatic Perryc.c : I
    //   674: iflt -> 688
    //   677: ldc2_w 650516109
    //   680: l2i
    //   681: ldc_w -1083054232
    //   684: ixor
    //   685: goto -> 696
    //   688: ldc2_w 377974769
    //   691: l2i
    //   692: ldc_w 216416380
    //   695: ixor
    //   696: ldc2_w -1564111468
    //   699: l2i
    //   700: ldc_w -2046185765
    //   703: ixor
    //   704: ixor
    //   705: lookupswitch default -> 940, -1115958614 -> 688, 1051528386 -> 732
    //   732: getstatic bigname/zprestige/webhack/util/WurstPlusThree/WurstplusThreeEntityUtil.mc : Lnet/minecraft/client/Minecraft;
    //   735: getstatic Perryc.c : I
    //   738: iflt -> 752
    //   741: ldc2_w -1253590071
    //   744: l2i
    //   745: ldc_w -358426359
    //   748: ixor
    //   749: goto -> 760
    //   752: ldc2_w 865579828
    //   755: l2i
    //   756: ldc_w -671109698
    //   759: ixor
    //   760: ldc2_w -649211326
    //   763: l2i
    //   764: ldc_w 1750163983
    //   767: ixor
    //   768: ixor
    //   769: lookupswitch default -> 932, -285617523 -> 752, 1433710279 -> 796
    //   796: getfield field_71439_g : Lnet/minecraft/client/entity/EntityPlayerSP;
    //   799: getstatic Perryc.1 : I
    //   802: ifeq -> 816
    //   805: ldc2_w -1859232605
    //   808: l2i
    //   809: ldc_w 2107232357
    //   812: ixor
    //   813: goto -> 824
    //   816: ldc2_w -756135179
    //   819: l2i
    //   820: ldc_w 1544296467
    //   823: ixor
    //   824: ldc2_w -495650016
    //   827: l2i
    //   828: ldc_w -1960563329
    //   831: ixor
    //   832: ixor
    //   833: lookupswitch default -> 956, -2048435559 -> 816, -407731015 -> 860
    //   860: aload_0
    //   861: getstatic Perryc.c : I
    //   864: iflt -> 878
    //   867: ldc2_w -2105075266
    //   870: l2i
    //   871: ldc_w 1922186753
    //   874: ixor
    //   875: goto -> 886
    //   878: ldc2_w 844414501
    //   881: l2i
    //   882: ldc_w -1298502988
    //   885: ixor
    //   886: ldc2_w 1289379818
    //   889: l2i
    //   890: ldc_w -856969776
    //   893: ixor
    //   894: ixor
    //   895: lookupswitch default -> 920, 1223040178 -> 878, 1881462149 -> 942
    //   920: goto -> 924
    //   923: athrow
    //   924: invokevirtual func_78764_a : (Lnet/minecraft/entity/player/EntityPlayer;Lnet/minecraft/entity/Entity;)V
    //   927: goto -> 931
    //   930: athrow
    //   931: return
    //   932: aconst_null
    //   933: athrow
    //   934: aconst_null
    //   935: athrow
    //   936: aconst_null
    //   937: athrow
    //   938: aconst_null
    //   939: athrow
    //   940: aconst_null
    //   941: athrow
    //   942: aconst_null
    //   943: athrow
    //   944: aconst_null
    //   945: athrow
    //   946: aconst_null
    //   947: athrow
    //   948: aconst_null
    //   949: athrow
    //   950: aconst_null
    //   951: athrow
    //   952: aconst_null
    //   953: athrow
    //   954: aconst_null
    //   955: athrow
    //   956: aconst_null
    //   957: athrow
    //   958: pop
    //   959: goto -> 24
    //   962: pop
    //   963: aconst_null
    //   964: goto -> 958
    //   967: dup
    //   968: ifnull -> 958
    //   971: checkcast java/lang/Throwable
    //   974: athrow
    //   975: dup
    //   976: ifnull -> 962
    //   979: checkcast java/lang/Throwable
    //   982: athrow
    //   983: aconst_null
    //   984: athrow
    // Local variable table:
    //   start	length	slot	name	descriptor
    //   24	908	0	entity	Lnet/minecraft/entity/Entity;
    //   24	908	1	packet	Z
    // Exception table:
    //   from	to	target	type
    //   8	20	967	java/lang/StringIndexOutOfBoundsException
    //   460	466	466	finally
    //   460	466	3	finally
    //   460	466	466	java/lang/ClassCastException
    //   460	466	466	finally
    //   460	466	466	finally
    //   531	538	538	finally
    //   531	538	531	finally
    //   532	538	538	finally
    //   532	538	3	finally
    //   532	538	3	java/lang/NegativeArraySizeException
    //   923	930	930	finally
    //   923	930	3	java/lang/AssertionError
    //   924	930	930	java/lang/NegativeArraySizeException
    //   924	930	3	java/lang/NegativeArraySizeException
    //   924	930	923	java/lang/NullPointerException
    //   967	975	967	java/lang/StringIndexOutOfBoundsException
    //   983	985	3	java/lang/UnsupportedOperationException
  }
  
  public static boolean is32k(ItemStack paramItemStack) {
    return Perry1.0B(null, (int)-889878816L ^ 0xF5D53638, paramItemStack);
  }
  
  public static BlockPos getPlayerPosWithEntity() {
    if (Perryc.1 <= 0) {
      null;
    } else {
      if (null != null)
        throw (Throwable)null; 
      null;
    } 
    if (null != null)
      throw (Throwable)null; 
    null;
  }
  
  public static void resetTimer() {
    Perry1.3n(null, (int)271279498L ^ 0x5B51D293);
  }
  
  public static Vec3d[] getUnsafeBlockArray(Entity paramEntity, int paramInt, boolean paramBoolean) {
    return Perry1.0j(null, (int)376316934L ^ 0x2463DDA, paramEntity, paramInt, paramBoolean);
  }
  
  public static List getOffsetList(int y, boolean floor) {
    if (Perryc.c < 0) {
      null;
    } else {
      if (null != null)
        throw (Throwable)null; 
      null;
    } 
    if (null != null)
      throw (Throwable)null; 
    null;
  }
  
  public static Vec3d getInterpolatedAmount(Entity entity, double x, double y, double z) {
    if (Perryc.0 <= 0) {
      null;
    } else {
      if (null != null)
        throw (Throwable)null; 
      null;
    } 
    if (null != null)
      throw (Throwable)null; 
    null;
  }
  
  public static Block isColliding(double posX, double posY, double posZ) {
    // Byte code:
    //   0: goto -> 8
    //   3: dup
    //   4: ifnull -> 3974
    //   7: athrow
    //   8: aconst_null
    //   9: getstatic Perryc.0 : I
    //   12: ifgt -> 3966
    //   15: pop
    //   16: aconst_null
    //   17: goto -> 3958
    //   20: nop
    //   21: nop
    //   22: nop
    //   23: athrow
    //   24: aconst_null
    //   25: getstatic Perryc.0 : I
    //   28: ifle -> 42
    //   31: ldc2_w 1548802862
    //   34: l2i
    //   35: ldc_w 391591228
    //   38: ixor
    //   39: goto -> 50
    //   42: ldc2_w -1198732786
    //   45: l2i
    //   46: ldc_w -1855942430
    //   49: ixor
    //   50: ldc2_w 1427580699
    //   53: l2i
    //   54: ldc_w -25690108
    //   57: ixor
    //   58: ixor
    //   59: lookupswitch default -> 84, -530003699 -> 3865, 2022593179 -> 42
    //   84: astore #6
    //   86: getstatic Perryc.1 : I
    //   89: ifeq -> 103
    //   92: ldc2_w 676793658
    //   95: l2i
    //   96: ldc_w 908018110
    //   99: ixor
    //   100: goto -> 111
    //   103: ldc2_w -120565515
    //   106: l2i
    //   107: ldc_w 320704155
    //   110: ixor
    //   111: ldc2_w -2076209474
    //   114: l2i
    //   115: ldc_w 791765519
    //   118: ixor
    //   119: ixor
    //   120: lookupswitch default -> 148, -1253662667 -> 3857, 1577373821 -> 103
    //   148: getstatic bigname/zprestige/webhack/util/WurstPlusThree/WurstplusThreeEntityUtil.mc : Lnet/minecraft/client/Minecraft;
    //   151: getstatic Perryc.0 : I
    //   154: ifle -> 168
    //   157: ldc2_w 1862800802
    //   160: l2i
    //   161: ldc_w -1788958248
    //   164: ixor
    //   165: goto -> 176
    //   168: ldc2_w -1070608174
    //   171: l2i
    //   172: ldc_w 301470924
    //   175: ixor
    //   176: ldc2_w 1949487103
    //   179: l2i
    //   180: ldc_w -54958285
    //   183: ixor
    //   184: ixor
    //   185: lookupswitch default -> 3887, 1499229394 -> 212, 1927091382 -> 168
    //   212: getfield field_71439_g : Lnet/minecraft/client/entity/EntityPlayerSP;
    //   215: ifnull -> 229
    //   218: ldc2_w 1364879448
    //   221: l2i
    //   222: ldc_w 1875401695
    //   225: ixor
    //   226: goto -> 237
    //   229: ldc2_w 434205439
    //   232: l2i
    //   233: ldc_w 661864831
    //   236: ixor
    //   237: ldc2_w -2005332339
    //   240: l2i
    //   241: ldc_w 1298766937
    //   244: ixor
    //   245: ixor
    //   246: tableswitch default -> 218, -75325101 -> 268, -75325100 -> 3778
    //   268: getstatic Perryc.0 : I
    //   271: ifle -> 285
    //   274: ldc2_w 613036397
    //   277: l2i
    //   278: ldc_w 2097188724
    //   281: ixor
    //   282: goto -> 293
    //   285: ldc2_w 246915938
    //   288: l2i
    //   289: ldc_w 1053947407
    //   292: ixor
    //   293: ldc2_w 584571132
    //   296: l2i
    //   297: ldc_w -1141882410
    //   300: ixor
    //   301: ixor
    //   302: lookupswitch default -> 328, -1626592292 -> 285, -1062394061 -> 3877
    //   328: getstatic bigname/zprestige/webhack/util/WurstPlusThree/WurstplusThreeEntityUtil.mc : Lnet/minecraft/client/Minecraft;
    //   331: getstatic Perryc.c : I
    //   334: iflt -> 348
    //   337: ldc2_w -1424495143
    //   340: l2i
    //   341: ldc_w 1975487480
    //   344: ixor
    //   345: goto -> 356
    //   348: ldc2_w -1248173754
    //   351: l2i
    //   352: ldc_w -1046952709
    //   355: ixor
    //   356: ldc2_w 1269209078
    //   359: l2i
    //   360: ldc_w 1138898583
    //   363: ixor
    //   364: ixor
    //   365: lookupswitch default -> 3869, -689125568 -> 348, 2084963548 -> 392
    //   392: getfield field_71439_g : Lnet/minecraft/client/entity/EntityPlayerSP;
    //   395: getstatic Perryc.0 : I
    //   398: ifle -> 412
    //   401: ldc2_w -1623471781
    //   404: l2i
    //   405: ldc_w -1609622544
    //   408: ixor
    //   409: goto -> 420
    //   412: ldc2_w -1472751675
    //   415: l2i
    //   416: ldc_w -1590680441
    //   419: ixor
    //   420: ldc2_w 1196836421
    //   423: l2i
    //   424: ldc_w 1874767661
    //   427: ixor
    //   428: ixor
    //   429: lookupswitch default -> 456, 400309187 -> 3945, 1465961954 -> 412
    //   456: goto -> 460
    //   459: athrow
    //   460: invokevirtual func_184187_bx : ()Lnet/minecraft/entity/Entity;
    //   463: goto -> 467
    //   466: athrow
    //   467: ifnull -> 481
    //   470: ldc2_w 1200631288
    //   473: l2i
    //   474: ldc_w 1521466378
    //   477: ixor
    //   478: goto -> 489
    //   481: ldc2_w -236974208
    //   484: l2i
    //   485: ldc_w -320889231
    //   488: ixor
    //   489: ldc2_w -1924129221
    //   492: l2i
    //   493: ldc_w 516528100
    //   496: ixor
    //   497: ixor
    //   498: tableswitch default -> 470, -1901717459 -> 520, -1901717458 -> 1162
    //   520: getstatic Perryc.c : I
    //   523: iflt -> 537
    //   526: ldc2_w 1292412053
    //   529: l2i
    //   530: ldc_w 602165871
    //   533: ixor
    //   534: goto -> 545
    //   537: ldc2_w 130834592
    //   540: l2i
    //   541: ldc_w 600568570
    //   544: ixor
    //   545: ldc2_w 1336582204
    //   548: l2i
    //   549: ldc_w -390456048
    //   552: ixor
    //   553: ixor
    //   554: lookupswitch default -> 580, -906212394 -> 3895, 1251824744 -> 537
    //   580: getstatic bigname/zprestige/webhack/util/WurstPlusThree/WurstplusThreeEntityUtil.mc : Lnet/minecraft/client/Minecraft;
    //   583: getstatic Perryc.0 : I
    //   586: ifle -> 600
    //   589: ldc2_w 1246700684
    //   592: l2i
    //   593: ldc_w 811311987
    //   596: ixor
    //   597: goto -> 608
    //   600: ldc2_w -1893167343
    //   603: l2i
    //   604: ldc_w 721094690
    //   607: ixor
    //   608: ldc2_w 1802927896
    //   611: l2i
    //   612: ldc_w 877346043
    //   615: ixor
    //   616: ixor
    //   617: lookupswitch default -> 644, 623494172 -> 3847, 746037797 -> 600
    //   644: getfield field_71439_g : Lnet/minecraft/client/entity/EntityPlayerSP;
    //   647: getstatic Perryc.0 : I
    //   650: ifle -> 664
    //   653: ldc2_w 1938388612
    //   656: l2i
    //   657: ldc_w -824494112
    //   660: ixor
    //   661: goto -> 672
    //   664: ldc2_w 1280235352
    //   667: l2i
    //   668: ldc_w -1378617763
    //   671: ixor
    //   672: ldc2_w -1610172665
    //   675: l2i
    //   676: ldc_w 1171194846
    //   679: ixor
    //   680: ixor
    //   681: lookupswitch default -> 3919, 72652252 -> 708, 1486615997 -> 664
    //   708: goto -> 712
    //   711: athrow
    //   712: invokevirtual func_184187_bx : ()Lnet/minecraft/entity/Entity;
    //   715: goto -> 719
    //   718: athrow
    //   719: getstatic Perryc.c : I
    //   722: iflt -> 736
    //   725: ldc2_w 375009752
    //   728: l2i
    //   729: ldc_w 1014700765
    //   732: ixor
    //   733: goto -> 744
    //   736: ldc2_w -173798793
    //   739: l2i
    //   740: ldc_w 122987916
    //   743: ixor
    //   744: ldc2_w -2076398410
    //   747: l2i
    //   748: ldc_w -1425841947
    //   751: ixor
    //   752: ixor
    //   753: lookupswitch default -> 3885, -573611096 -> 780, 85911382 -> 736
    //   780: goto -> 784
    //   783: athrow
    //   784: invokevirtual func_174813_aQ : ()Lnet/minecraft/util/math/AxisAlignedBB;
    //   787: goto -> 791
    //   790: athrow
    //   791: ldc2_w 1.1433600632520196E308
    //   794: invokestatic doubleToLongBits : (D)J
    //   797: ldc2_w 9215589953129833209
    //   800: lxor
    //   801: invokestatic longBitsToDouble : (J)D
    //   804: ldc2_w 7.953810131792039E307
    //   807: invokestatic doubleToLongBits : (D)J
    //   810: ldc2_w 9213328025649122025
    //   813: lxor
    //   814: invokestatic longBitsToDouble : (J)D
    //   817: ldc2_w 1.0676894387930642E308
    //   820: invokestatic doubleToLongBits : (D)J
    //   823: ldc2_w 9215210811451526310
    //   826: lxor
    //   827: invokestatic longBitsToDouble : (J)D
    //   830: getstatic Perryc.0 : I
    //   833: ifle -> 847
    //   836: ldc2_w 1922281138
    //   839: l2i
    //   840: ldc_w 2027584187
    //   843: ixor
    //   844: goto -> 855
    //   847: ldc2_w 903082957
    //   850: l2i
    //   851: ldc_w -1012521070
    //   854: ixor
    //   855: ldc2_w 886442920
    //   858: l2i
    //   859: ldc_w -609117166
    //   862: ixor
    //   863: ixor
    //   864: lookupswitch default -> 892, -449952845 -> 3903, 285489818 -> 847
    //   892: goto -> 896
    //   895: athrow
    //   896: invokevirtual func_191195_a : (DDD)Lnet/minecraft/util/math/AxisAlignedBB;
    //   899: goto -> 903
    //   902: athrow
    //   903: getstatic Perryc.0 : I
    //   906: ifle -> 920
    //   909: ldc2_w 881167852
    //   912: l2i
    //   913: ldc_w -763289293
    //   916: ixor
    //   917: goto -> 928
    //   920: ldc2_w 1584040596
    //   923: l2i
    //   924: ldc_w 708508621
    //   927: ixor
    //   928: ldc2_w 788918039
    //   931: l2i
    //   932: ldc_w 966469646
    //   935: ixor
    //   936: ixor
    //   937: lookupswitch default -> 964, -1886038953 -> 920, -258315322 -> 3917
    //   964: dload_0
    //   965: getstatic Perryc.c : I
    //   968: iflt -> 982
    //   971: ldc2_w -628281485
    //   974: l2i
    //   975: ldc_w -940553714
    //   978: ixor
    //   979: goto -> 990
    //   982: ldc2_w -1508200678
    //   985: l2i
    //   986: ldc_w 2079753265
    //   989: ixor
    //   990: ldc2_w -357139541
    //   993: l2i
    //   994: ldc_w -662169657
    //   997: ixor
    //   998: ixor
    //   999: lookupswitch default -> 1024, -1619393991 -> 982, 792922385 -> 3913
    //   1024: dload_2
    //   1025: getstatic Perryc.c : I
    //   1028: iflt -> 1042
    //   1031: ldc2_w 1372651396
    //   1034: l2i
    //   1035: ldc_w -1309304344
    //   1038: ixor
    //   1039: goto -> 1050
    //   1042: ldc2_w -1461743832
    //   1045: l2i
    //   1046: ldc_w -914851301
    //   1049: ixor
    //   1050: ldc2_w 865499663
    //   1053: l2i
    //   1054: ldc_w 1390422129
    //   1057: ixor
    //   1058: ixor
    //   1059: lookupswitch default -> 1084, -2125253614 -> 3853, 758856482 -> 1042
    //   1084: dload #4
    //   1086: getstatic Perryc.0 : I
    //   1089: ifle -> 1103
    //   1092: ldc2_w 986577587
    //   1095: l2i
    //   1096: ldc_w -1529655251
    //   1099: ixor
    //   1100: goto -> 1111
    //   1103: ldc2_w -1026743717
    //   1106: l2i
    //   1107: ldc_w 1101538043
    //   1110: ixor
    //   1111: ldc2_w 1991148402
    //   1114: l2i
    //   1115: ldc_w 1722762719
    //   1118: ixor
    //   1119: ixor
    //   1120: lookupswitch default -> 1148, -1910543309 -> 3883, -899003743 -> 1103
    //   1148: goto -> 1152
    //   1151: athrow
    //   1152: invokevirtual func_72317_d : (DDD)Lnet/minecraft/util/math/AxisAlignedBB;
    //   1155: goto -> 1159
    //   1158: athrow
    //   1159: goto -> 1731
    //   1162: getstatic Perryc.c : I
    //   1165: iflt -> 1179
    //   1168: ldc2_w 1307855970
    //   1171: l2i
    //   1172: ldc_w 908537053
    //   1175: ixor
    //   1176: goto -> 1187
    //   1179: ldc2_w -1103614923
    //   1182: l2i
    //   1183: ldc_w 794140562
    //   1186: ixor
    //   1187: ldc2_w -588191179
    //   1190: l2i
    //   1191: ldc_w 1522124427
    //   1194: ixor
    //   1195: ixor
    //   1196: lookupswitch default -> 3881, -40219647 -> 1179, 388275993 -> 1224
    //   1224: getstatic bigname/zprestige/webhack/util/WurstPlusThree/WurstplusThreeEntityUtil.mc : Lnet/minecraft/client/Minecraft;
    //   1227: getstatic Perryc.c : I
    //   1230: iflt -> 1244
    //   1233: ldc2_w 2132989939
    //   1236: l2i
    //   1237: ldc_w -257383880
    //   1240: ixor
    //   1241: goto -> 1252
    //   1244: ldc2_w -347875719
    //   1247: l2i
    //   1248: ldc_w 13862798
    //   1251: ixor
    //   1252: ldc2_w -1381907389
    //   1255: l2i
    //   1256: ldc_w -10668966
    //   1259: ixor
    //   1260: ixor
    //   1261: lookupswitch default -> 1288, -579435054 -> 3875, 545874253 -> 1244
    //   1288: getfield field_71439_g : Lnet/minecraft/client/entity/EntityPlayerSP;
    //   1291: getstatic Perryc.1 : I
    //   1294: ifeq -> 1308
    //   1297: ldc2_w 1245366476
    //   1300: l2i
    //   1301: ldc_w 1472731577
    //   1304: ixor
    //   1305: goto -> 1316
    //   1308: ldc2_w 1072456641
    //   1311: l2i
    //   1312: ldc_w 1598817292
    //   1315: ixor
    //   1316: ldc2_w -1812167281
    //   1319: l2i
    //   1320: ldc_w -633520982
    //   1323: ixor
    //   1324: ixor
    //   1325: lookupswitch default -> 3925, 694279912 -> 1352, 1412655184 -> 1308
    //   1352: goto -> 1356
    //   1355: athrow
    //   1356: invokevirtual func_174813_aQ : ()Lnet/minecraft/util/math/AxisAlignedBB;
    //   1359: goto -> 1363
    //   1362: athrow
    //   1363: ldc2_w 8.550422200305123E307
    //   1366: invokestatic doubleToLongBits : (D)J
    //   1369: ldc2_w 9213925881164578739
    //   1372: lxor
    //   1373: invokestatic longBitsToDouble : (J)D
    //   1376: ldc2_w 5.199484319174815E306
    //   1379: invokestatic doubleToLongBits : (D)J
    //   1382: ldc2_w 9195679753404494207
    //   1385: lxor
    //   1386: invokestatic longBitsToDouble : (J)D
    //   1389: ldc2_w 1.7005546997608748E307
    //   1392: invokestatic doubleToLongBits : (D)J
    //   1395: ldc2_w 9203166834938003439
    //   1398: lxor
    //   1399: invokestatic longBitsToDouble : (J)D
    //   1402: getstatic Perryc.c : I
    //   1405: iflt -> 1419
    //   1408: ldc2_w -752759502
    //   1411: l2i
    //   1412: ldc_w 302819650
    //   1415: ixor
    //   1416: goto -> 1427
    //   1419: ldc2_w 89019693
    //   1422: l2i
    //   1423: ldc_w 888177122
    //   1426: ixor
    //   1427: ldc2_w -1245281677
    //   1430: l2i
    //   1431: ldc_w 453430369
    //   1434: ixor
    //   1435: ixor
    //   1436: lookupswitch default -> 1464, 223080265 -> 1419, 1877813858 -> 3851
    //   1464: goto -> 1468
    //   1467: athrow
    //   1468: invokevirtual func_191195_a : (DDD)Lnet/minecraft/util/math/AxisAlignedBB;
    //   1471: goto -> 1475
    //   1474: athrow
    //   1475: getstatic Perryc.0 : I
    //   1478: ifle -> 1492
    //   1481: ldc2_w 1490088907
    //   1484: l2i
    //   1485: ldc_w 1048110313
    //   1488: ixor
    //   1489: goto -> 1500
    //   1492: ldc2_w 1444711329
    //   1495: l2i
    //   1496: ldc_w 2141253131
    //   1499: ixor
    //   1500: ldc2_w -1808387428
    //   1503: l2i
    //   1504: ldc_w 180636935
    //   1507: ixor
    //   1508: ixor
    //   1509: lookupswitch default -> 1536, -1606157788 -> 1492, -128292679 -> 3863
    //   1536: dload_0
    //   1537: getstatic Perryc.1 : I
    //   1540: ifeq -> 1554
    //   1543: ldc2_w -156383104
    //   1546: l2i
    //   1547: ldc_w -1890585753
    //   1550: ixor
    //   1551: goto -> 1562
    //   1554: ldc2_w -1448047646
    //   1557: l2i
    //   1558: ldc_w -874036294
    //   1561: ixor
    //   1562: ldc2_w -944403098
    //   1565: l2i
    //   1566: ldc_w -1867143040
    //   1569: ixor
    //   1570: ixor
    //   1571: lookupswitch default -> 1596, -1758228980 -> 1554, 786570753 -> 3849
    //   1596: dload_2
    //   1597: getstatic Perryc.0 : I
    //   1600: ifle -> 1614
    //   1603: ldc2_w 1483866372
    //   1606: l2i
    //   1607: ldc_w -297978617
    //   1610: ixor
    //   1611: goto -> 1622
    //   1614: ldc2_w -1867604878
    //   1617: l2i
    //   1618: ldc_w -1082899665
    //   1621: ixor
    //   1622: ldc2_w -1137453247
    //   1625: l2i
    //   1626: ldc_w 2045345727
    //   1629: ixor
    //   1630: ixor
    //   1631: lookupswitch default -> 3897, -369068125 -> 1656, 1939184893 -> 1614
    //   1656: dload #4
    //   1658: getstatic Perryc.c : I
    //   1661: iflt -> 1675
    //   1664: ldc2_w -741674385
    //   1667: l2i
    //   1668: ldc_w 395746426
    //   1671: ixor
    //   1672: goto -> 1683
    //   1675: ldc2_w 545953711
    //   1678: l2i
    //   1679: ldc_w 1051310719
    //   1682: ixor
    //   1683: ldc2_w -167343699
    //   1686: l2i
    //   1687: ldc_w 1326877793
    //   1690: ixor
    //   1691: ixor
    //   1692: lookupswitch default -> 3891, -1489819620 -> 1720, 2102160345 -> 1675
    //   1720: goto -> 1724
    //   1723: athrow
    //   1724: invokevirtual func_72317_d : (DDD)Lnet/minecraft/util/math/AxisAlignedBB;
    //   1727: goto -> 1731
    //   1730: athrow
    //   1731: getstatic Perryc.0 : I
    //   1734: ifle -> 1748
    //   1737: ldc2_w 1327532400
    //   1740: l2i
    //   1741: ldc_w 1449348742
    //   1744: ixor
    //   1745: goto -> 1756
    //   1748: ldc2_w 466639153
    //   1751: l2i
    //   1752: ldc_w 1140969696
    //   1755: ixor
    //   1756: ldc2_w -1160724501
    //   1759: l2i
    //   1760: ldc_w -886199944
    //   1763: ixor
    //   1764: ixor
    //   1765: lookupswitch default -> 3923, 774676290 -> 1792, 1757335909 -> 1748
    //   1792: astore #7
    //   1794: getstatic Perryc.0 : I
    //   1797: ifle -> 1811
    //   1800: ldc2_w -349592497
    //   1803: l2i
    //   1804: ldc_w -1485312410
    //   1807: ixor
    //   1808: goto -> 1819
    //   1811: ldc2_w 434730090
    //   1814: l2i
    //   1815: ldc_w 2135443391
    //   1818: ixor
    //   1819: ldc2_w 1440332682
    //   1822: l2i
    //   1823: ldc_w 1798685043
    //   1826: ixor
    //   1827: ixor
    //   1828: lookupswitch default -> 3871, 1481460012 -> 1856, 1924280528 -> 1811
    //   1856: aload #7
    //   1858: getstatic Perryc.1 : I
    //   1861: ifeq -> 1875
    //   1864: ldc2_w -1442165249
    //   1867: l2i
    //   1868: ldc_w -1550943738
    //   1871: ixor
    //   1872: goto -> 1883
    //   1875: ldc2_w -926705587
    //   1878: l2i
    //   1879: ldc_w 742978849
    //   1882: ixor
    //   1883: ldc2_w -1709067994
    //   1886: l2i
    //   1887: ldc_w -611897620
    //   1890: ixor
    //   1891: ixor
    //   1892: lookupswitch default -> 1920, 1210230835 -> 3879, 1684330244 -> 1875
    //   1920: getfield field_72338_b : D
    //   1923: d2i
    //   1924: getstatic Perryc.1 : I
    //   1927: ifeq -> 1941
    //   1930: ldc2_w 227683028
    //   1933: l2i
    //   1934: ldc_w -1672519461
    //   1937: ixor
    //   1938: goto -> 1949
    //   1941: ldc2_w 1422936129
    //   1944: l2i
    //   1945: ldc_w -1426943872
    //   1948: ixor
    //   1949: ldc2_w -1969008097
    //   1952: l2i
    //   1953: ldc_w 1587495710
    //   1956: ixor
    //   1957: ixor
    //   1958: lookupswitch default -> 3899, 706660800 -> 1984, 1172396814 -> 1941
    //   1984: istore #8
    //   1986: getstatic Perryc.1 : I
    //   1989: ifeq -> 2003
    //   1992: ldc2_w -2054218466
    //   1995: l2i
    //   1996: ldc_w 2084357772
    //   1999: ixor
    //   2000: goto -> 2011
    //   2003: ldc2_w -723163214
    //   2006: l2i
    //   2007: ldc_w 1913715316
    //   2010: ixor
    //   2011: ldc2_w -753461170
    //   2014: l2i
    //   2015: ldc_w 969199807
    //   2018: ixor
    //   2019: ixor
    //   2020: lookupswitch default -> 3889, 325063523 -> 2003, 1277580599 -> 2048
    //   2048: aload #7
    //   2050: getstatic Perryc.0 : I
    //   2053: ifle -> 2067
    //   2056: ldc2_w 2090528198
    //   2059: l2i
    //   2060: ldc_w 742897628
    //   2063: ixor
    //   2064: goto -> 2075
    //   2067: ldc2_w -32739640
    //   2070: l2i
    //   2071: ldc_w 1510231459
    //   2074: ixor
    //   2075: ldc2_w -1287459658
    //   2078: l2i
    //   2079: ldc_w -539631603
    //   2082: ixor
    //   2083: ixor
    //   2084: lookupswitch default -> 2112, 220196766 -> 2067, 1011504801 -> 3901
    //   2112: getfield field_72340_a : D
    //   2115: getstatic Perryc.1 : I
    //   2118: ifeq -> 2132
    //   2121: ldc2_w -318558484
    //   2124: l2i
    //   2125: ldc_w 1325137072
    //   2128: ixor
    //   2129: goto -> 2140
    //   2132: ldc2_w -625815298
    //   2135: l2i
    //   2136: ldc_w 294493638
    //   2139: ixor
    //   2140: ldc2_w 1256662743
    //   2143: l2i
    //   2144: ldc_w 1712162007
    //   2147: ixor
    //   2148: ixor
    //   2149: lookupswitch default -> 3867, -1894616996 -> 2132, -405409992 -> 2176
    //   2176: goto -> 2180
    //   2179: athrow
    //   2180: invokestatic func_76128_c : (D)I
    //   2183: goto -> 2187
    //   2186: athrow
    //   2187: getstatic Perryc.1 : I
    //   2190: ifeq -> 2204
    //   2193: ldc2_w -911240685
    //   2196: l2i
    //   2197: ldc_w 369309968
    //   2200: ixor
    //   2201: goto -> 2212
    //   2204: ldc2_w 1459064195
    //   2207: l2i
    //   2208: ldc_w 779045863
    //   2211: ixor
    //   2212: ldc2_w -649718358
    //   2215: l2i
    //   2216: ldc_w 395956762
    //   2219: ixor
    //   2220: ixor
    //   2221: lookupswitch default -> 2248, 292777139 -> 3935, 988602697 -> 2204
    //   2248: istore #9
    //   2250: getstatic Perryc.1 : I
    //   2253: ifeq -> 2267
    //   2256: ldc2_w 1559220037
    //   2259: l2i
    //   2260: ldc_w -1605393035
    //   2263: ixor
    //   2264: goto -> 2275
    //   2267: ldc2_w 59335248
    //   2270: l2i
    //   2271: ldc_w -1138452297
    //   2274: ixor
    //   2275: ldc2_w -2032328111
    //   2278: l2i
    //   2279: ldc_w -1902032397
    //   2282: ixor
    //   2283: ixor
    //   2284: lookupswitch default -> 2312, -186908270 -> 3941, 1526787011 -> 2267
    //   2312: iload #9
    //   2314: getstatic Perryc.1 : I
    //   2317: ifeq -> 2331
    //   2320: ldc2_w 1906265908
    //   2323: l2i
    //   2324: ldc_w -348307289
    //   2327: ixor
    //   2328: goto -> 2339
    //   2331: ldc2_w 293386621
    //   2334: l2i
    //   2335: ldc_w 799679388
    //   2338: ixor
    //   2339: ldc2_w 1190214883
    //   2342: l2i
    //   2343: ldc_w -1905118916
    //   2346: ixor
    //   2347: ixor
    //   2348: lookupswitch default -> 2376, 1377894988 -> 3859, 1782559827 -> 2331
    //   2376: aload #7
    //   2378: getstatic Perryc.1 : I
    //   2381: ifeq -> 2395
    //   2384: ldc2_w 1096670589
    //   2387: l2i
    //   2388: ldc_w -580132103
    //   2391: ixor
    //   2392: goto -> 2403
    //   2395: ldc2_w -112902102
    //   2398: l2i
    //   2399: ldc_w -315209255
    //   2402: ixor
    //   2403: ldc2_w -260013472
    //   2406: l2i
    //   2407: ldc_w 1765574438
    //   2410: ixor
    //   2411: ixor
    //   2412: lookupswitch default -> 3915, -1915810635 -> 2440, 92945090 -> 2395
    //   2440: getfield field_72336_d : D
    //   2443: getstatic Perryc.c : I
    //   2446: iflt -> 2460
    //   2449: ldc2_w -1404439465
    //   2452: l2i
    //   2453: ldc_w -1139837511
    //   2456: ixor
    //   2457: goto -> 2468
    //   2460: ldc2_w -923662244
    //   2463: l2i
    //   2464: ldc_w -1771308587
    //   2467: ixor
    //   2468: ldc2_w -662245437
    //   2471: l2i
    //   2472: ldc_w 1760623115
    //   2475: ixor
    //   2476: ixor
    //   2477: lookupswitch default -> 3943, -1607429082 -> 2460, -286268351 -> 2504
    //   2504: goto -> 2508
    //   2507: athrow
    //   2508: invokestatic func_76128_c : (D)I
    //   2511: goto -> 2515
    //   2514: athrow
    //   2515: ldc2_w 373466087
    //   2518: l2i
    //   2519: ldc_w 373466086
    //   2522: ixor
    //   2523: iadd
    //   2524: if_icmpge -> 2538
    //   2527: ldc2_w 1882467220
    //   2530: l2i
    //   2531: ldc_w 741454583
    //   2534: ixor
    //   2535: goto -> 2546
    //   2538: ldc2_w 262461101
    //   2541: l2i
    //   2542: ldc_w 1403080653
    //   2545: ixor
    //   2546: ldc2_w 1465650828
    //   2549: l2i
    //   2550: ldc_w 942642034
    //   2553: ixor
    //   2554: ixor
    //   2555: tableswitch default -> 2527, 863372445 -> 2576, 863372446 -> 3778
    //   2576: getstatic Perryc.1 : I
    //   2579: ifeq -> 2593
    //   2582: ldc2_w -1649825377
    //   2585: l2i
    //   2586: ldc_w -174686607
    //   2589: ixor
    //   2590: goto -> 2601
    //   2593: ldc2_w -391963220
    //   2596: l2i
    //   2597: ldc_w 1047767357
    //   2600: ixor
    //   2601: ldc2_w -958862971
    //   2604: l2i
    //   2605: ldc_w 1777552898
    //   2608: ixor
    //   2609: ixor
    //   2610: lookupswitch default -> 2636, -954961815 -> 3911, 565358345 -> 2593
    //   2636: aload #7
    //   2638: getstatic Perryc.c : I
    //   2641: iflt -> 2655
    //   2644: ldc2_w -1512712755
    //   2647: l2i
    //   2648: ldc_w 1392252993
    //   2651: ixor
    //   2652: goto -> 2663
    //   2655: ldc2_w -1742005215
    //   2658: l2i
    //   2659: ldc_w -553986765
    //   2662: ixor
    //   2663: ldc2_w -1074282132
    //   2666: l2i
    //   2667: ldc_w 1250323576
    //   2670: ixor
    //   2671: ixor
    //   2672: lookupswitch default -> 3927, -1281334266 -> 2700, 39346328 -> 2655
    //   2700: getfield field_72339_c : D
    //   2703: getstatic Perryc.c : I
    //   2706: iflt -> 2720
    //   2709: ldc2_w 606248341
    //   2712: l2i
    //   2713: ldc_w 82049346
    //   2716: ixor
    //   2717: goto -> 2728
    //   2720: ldc2_w 1488506795
    //   2723: l2i
    //   2724: ldc_w 864987935
    //   2727: ixor
    //   2728: ldc2_w 992728710
    //   2731: l2i
    //   2732: ldc_w -1294030985
    //   2735: ixor
    //   2736: ixor
    //   2737: lookupswitch default -> 3843, -1456204506 -> 2720, -490531515 -> 2764
    //   2764: goto -> 2768
    //   2767: athrow
    //   2768: invokestatic func_76128_c : (D)I
    //   2771: goto -> 2775
    //   2774: athrow
    //   2775: getstatic Perryc.c : I
    //   2778: iflt -> 2792
    //   2781: ldc2_w -1555252464
    //   2784: l2i
    //   2785: ldc_w -940155971
    //   2788: ixor
    //   2789: goto -> 2800
    //   2792: ldc2_w 597879117
    //   2795: l2i
    //   2796: ldc_w -1146800237
    //   2799: ixor
    //   2800: ldc2_w -1195750845
    //   2803: l2i
    //   2804: ldc_w -1924944400
    //   2807: ixor
    //   2808: ixor
    //   2809: lookupswitch default -> 2836, -282938908 -> 2792, 1363347230 -> 3921
    //   2836: istore #10
    //   2838: getstatic Perryc.1 : I
    //   2841: ifeq -> 2855
    //   2844: ldc2_w 1587822074
    //   2847: l2i
    //   2848: ldc_w 1828477237
    //   2851: ixor
    //   2852: goto -> 2863
    //   2855: ldc2_w 2122555070
    //   2858: l2i
    //   2859: ldc_w 1746649112
    //   2862: ixor
    //   2863: ldc2_w -1727383748
    //   2866: l2i
    //   2867: ldc_w 882862392
    //   2870: ixor
    //   2871: ixor
    //   2872: lookupswitch default -> 2900, -1613940021 -> 3931, 1849341977 -> 2855
    //   2900: iload #10
    //   2902: getstatic Perryc.1 : I
    //   2905: ifeq -> 2919
    //   2908: ldc2_w -1615458251
    //   2911: l2i
    //   2912: ldc_w -1480213145
    //   2915: ixor
    //   2916: goto -> 2927
    //   2919: ldc2_w -875706134
    //   2922: l2i
    //   2923: ldc_w -2064883097
    //   2926: ixor
    //   2927: ldc2_w 1361934080
    //   2930: l2i
    //   2931: ldc_w -1551710831
    //   2934: ixor
    //   2935: ixor
    //   2936: lookupswitch default -> 2964, -891543613 -> 3909, 359898861 -> 2919
    //   2964: aload #7
    //   2966: getstatic Perryc.0 : I
    //   2969: ifle -> 2983
    //   2972: ldc2_w 555607445
    //   2975: l2i
    //   2976: ldc_w -117524481
    //   2979: ixor
    //   2980: goto -> 2991
    //   2983: ldc2_w 41233868
    //   2986: l2i
    //   2987: ldc_w -167727951
    //   2990: ixor
    //   2991: ldc2_w 266042484
    //   2994: l2i
    //   2995: ldc_w 400673843
    //   2998: ixor
    //   2999: ixor
    //   3000: lookupswitch default -> 3933, -1042685395 -> 2983, -330354374 -> 3028
    //   3028: getfield field_72334_f : D
    //   3031: getstatic Perryc.0 : I
    //   3034: ifle -> 3048
    //   3037: ldc2_w 1549245774
    //   3040: l2i
    //   3041: ldc_w 625055210
    //   3044: ixor
    //   3045: goto -> 3056
    //   3048: ldc2_w -483818993
    //   3051: l2i
    //   3052: ldc_w -61312589
    //   3055: ixor
    //   3056: ldc2_w 2120000871
    //   3059: l2i
    //   3060: ldc_w -30281736
    //   3063: ixor
    //   3064: ixor
    //   3065: lookupswitch default -> 3855, -1625507549 -> 3092, -109362629 -> 3048
    //   3092: goto -> 3096
    //   3095: athrow
    //   3096: invokestatic func_76128_c : (D)I
    //   3099: goto -> 3103
    //   3102: athrow
    //   3103: ldc2_w 1467909359
    //   3106: l2i
    //   3107: ldc_w 1467909358
    //   3110: ixor
    //   3111: iadd
    //   3112: if_icmpge -> 3126
    //   3115: ldc2_w 2143055718
    //   3118: l2i
    //   3119: ldc_w -1105060614
    //   3122: ixor
    //   3123: goto -> 3134
    //   3126: ldc2_w -1635332886
    //   3129: l2i
    //   3130: ldc_w 1595457397
    //   3133: ixor
    //   3134: ldc2_w 302530760
    //   3137: l2i
    //   3138: ldc_w 1992833437
    //   3141: ixor
    //   3142: ixor
    //   3143: tableswitch default -> 3115, -1520563511 -> 3164, -1520563510 -> 3772
    //   3164: getstatic Perryc.1 : I
    //   3167: ifeq -> 3181
    //   3170: ldc2_w 1156718194
    //   3173: l2i
    //   3174: ldc_w 243870690
    //   3177: ixor
    //   3178: goto -> 3189
    //   3181: ldc2_w -409734760
    //   3184: l2i
    //   3185: ldc_w 1914011872
    //   3188: ixor
    //   3189: ldc2_w 1356789274
    //   3192: l2i
    //   3193: ldc_w -1450584963
    //   3196: ixor
    //   3197: ixor
    //   3198: lookupswitch default -> 3873, -1288955913 -> 3181, 1825657631 -> 3224
    //   3224: getstatic bigname/zprestige/webhack/util/WurstPlusThree/WurstplusThreeEntityUtil.mc : Lnet/minecraft/client/Minecraft;
    //   3227: getstatic Perryc.1 : I
    //   3230: ifeq -> 3244
    //   3233: ldc2_w -883208664
    //   3236: l2i
    //   3237: ldc_w -1575315048
    //   3240: ixor
    //   3241: goto -> 3252
    //   3244: ldc2_w -459097933
    //   3247: l2i
    //   3248: ldc_w -1268945026
    //   3251: ixor
    //   3252: ldc2_w 1464294475
    //   3255: l2i
    //   3256: ldc_w -1387740695
    //   3259: ixor
    //   3260: ixor
    //   3261: lookupswitch default -> 3907, -1823585774 -> 3244, -1427092881 -> 3288
    //   3288: getfield field_71441_e : Lnet/minecraft/client/multiplayer/WorldClient;
    //   3291: new net/minecraft/util/math/BlockPos
    //   3294: dup
    //   3295: getstatic Perryc.1 : I
    //   3298: ifeq -> 3312
    //   3301: ldc2_w 813617836
    //   3304: l2i
    //   3305: ldc_w 1379961247
    //   3308: ixor
    //   3309: goto -> 3320
    //   3312: ldc2_w 449561576
    //   3315: l2i
    //   3316: ldc_w -921062858
    //   3319: ixor
    //   3320: ldc2_w -294315344
    //   3323: l2i
    //   3324: ldc_w 1455372294
    //   3327: ixor
    //   3328: ixor
    //   3329: lookupswitch default -> 3845, -621512315 -> 3312, 1796756328 -> 3356
    //   3356: iload #9
    //   3358: getstatic Perryc.c : I
    //   3361: iflt -> 3375
    //   3364: ldc2_w -51896000
    //   3367: l2i
    //   3368: ldc_w 551746314
    //   3371: ixor
    //   3372: goto -> 3383
    //   3375: ldc2_w 1123244494
    //   3378: l2i
    //   3379: ldc_w 1039890250
    //   3382: ixor
    //   3383: ldc2_w -9425969
    //   3386: l2i
    //   3387: ldc_w -1481643618
    //   3390: ixor
    //   3391: ixor
    //   3392: lookupswitch default -> 3905, -2066409445 -> 3375, 668462293 -> 3420
    //   3420: iload #8
    //   3422: getstatic Perryc.1 : I
    //   3425: ifeq -> 3439
    //   3428: ldc2_w 822490331
    //   3431: l2i
    //   3432: ldc_w -1367526561
    //   3435: ixor
    //   3436: goto -> 3447
    //   3439: ldc2_w -218714313
    //   3442: l2i
    //   3443: ldc_w -2106818449
    //   3446: ixor
    //   3447: ldc2_w 2067985819
    //   3450: l2i
    //   3451: ldc_w -2030963563
    //   3454: ixor
    //   3455: ixor
    //   3456: lookupswitch default -> 3929, -1926681002 -> 3484, 1657276042 -> 3439
    //   3484: iload #10
    //   3486: getstatic Perryc.1 : I
    //   3489: ifeq -> 3503
    //   3492: ldc2_w -1835238804
    //   3495: l2i
    //   3496: ldc_w -1177726971
    //   3499: ixor
    //   3500: goto -> 3511
    //   3503: ldc2_w -45495720
    //   3506: l2i
    //   3507: ldc_w -2048335582
    //   3510: ixor
    //   3511: ldc2_w 1883822969
    //   3514: l2i
    //   3515: ldc_w 211978251
    //   3518: ixor
    //   3519: ixor
    //   3520: lookupswitch default -> 3548, -33689260 -> 3503, 1471904027 -> 3861
    //   3548: goto -> 3552
    //   3551: athrow
    //   3552: invokespecial <init> : (III)V
    //   3555: goto -> 3559
    //   3558: athrow
    //   3559: getstatic Perryc.0 : I
    //   3562: ifle -> 3576
    //   3565: ldc2_w -1161782885
    //   3568: l2i
    //   3569: ldc_w -1925957592
    //   3572: ixor
    //   3573: goto -> 3584
    //   3576: ldc2_w -737631731
    //   3579: l2i
    //   3580: ldc_w 370969100
    //   3583: ixor
    //   3584: ldc2_w 403522421
    //   3587: l2i
    //   3588: ldc_w 101458364
    //   3591: ixor
    //   3592: ixor
    //   3593: lookupswitch default -> 3620, 703972218 -> 3939, 1023264390 -> 3576
    //   3620: goto -> 3624
    //   3623: athrow
    //   3624: invokevirtual func_180495_p : (Lnet/minecraft/util/math/BlockPos;)Lnet/minecraft/block/state/IBlockState;
    //   3627: goto -> 3631
    //   3630: athrow
    //   3631: getstatic Perryc.c : I
    //   3634: iflt -> 3648
    //   3637: ldc2_w -997344531
    //   3640: l2i
    //   3641: ldc_w -977238314
    //   3644: ixor
    //   3645: goto -> 3656
    //   3648: ldc2_w -311484110
    //   3651: l2i
    //   3652: ldc_w 1993158688
    //   3655: ixor
    //   3656: ldc2_w 1278615737
    //   3659: l2i
    //   3660: ldc_w 561872861
    //   3663: ixor
    //   3664: ixor
    //   3665: lookupswitch default -> 3937, -152482186 -> 3692, 1812357983 -> 3648
    //   3692: goto -> 3696
    //   3695: athrow
    //   3696: invokeinterface func_177230_c : ()Lnet/minecraft/block/Block;
    //   3701: goto -> 3705
    //   3704: athrow
    //   3705: getstatic Perryc.1 : I
    //   3708: ifeq -> 3722
    //   3711: ldc2_w -1871214339
    //   3714: l2i
    //   3715: ldc_w -1708343147
    //   3718: ixor
    //   3719: goto -> 3730
    //   3722: ldc2_w 520505270
    //   3725: l2i
    //   3726: ldc_w -1091098503
    //   3729: ixor
    //   3730: ldc2_w 2100409454
    //   3733: l2i
    //   3734: ldc_w -1084020109
    //   3737: ixor
    //   3738: ixor
    //   3739: lookupswitch default -> 3764, -1320781657 -> 3722, -938879371 -> 3893
    //   3764: astore #6
    //   3766: iinc #10, 1
    //   3769: goto -> 2838
    //   3772: iinc #9, 1
    //   3775: goto -> 2250
    //   3778: getstatic Perryc.1 : I
    //   3781: ifeq -> 3795
    //   3784: ldc2_w 1142333226
    //   3787: l2i
    //   3788: ldc_w -243027310
    //   3791: ixor
    //   3792: goto -> 3803
    //   3795: ldc2_w -1206316514
    //   3798: l2i
    //   3799: ldc_w 877493918
    //   3802: ixor
    //   3803: ldc2_w 1531875258
    //   3806: l2i
    //   3807: ldc_w 1934939953
    //   3810: ixor
    //   3811: ixor
    //   3812: lookupswitch default -> 3947, -1651542733 -> 3795, -1538378741 -> 3840
    //   3840: aload #6
    //   3842: areturn
    //   3843: aconst_null
    //   3844: athrow
    //   3845: aconst_null
    //   3846: athrow
    //   3847: aconst_null
    //   3848: athrow
    //   3849: aconst_null
    //   3850: athrow
    //   3851: aconst_null
    //   3852: athrow
    //   3853: aconst_null
    //   3854: athrow
    //   3855: aconst_null
    //   3856: athrow
    //   3857: aconst_null
    //   3858: athrow
    //   3859: aconst_null
    //   3860: athrow
    //   3861: aconst_null
    //   3862: athrow
    //   3863: aconst_null
    //   3864: athrow
    //   3865: aconst_null
    //   3866: athrow
    //   3867: aconst_null
    //   3868: athrow
    //   3869: aconst_null
    //   3870: athrow
    //   3871: aconst_null
    //   3872: athrow
    //   3873: aconst_null
    //   3874: athrow
    //   3875: aconst_null
    //   3876: athrow
    //   3877: aconst_null
    //   3878: athrow
    //   3879: aconst_null
    //   3880: athrow
    //   3881: aconst_null
    //   3882: athrow
    //   3883: aconst_null
    //   3884: athrow
    //   3885: aconst_null
    //   3886: athrow
    //   3887: aconst_null
    //   3888: athrow
    //   3889: aconst_null
    //   3890: athrow
    //   3891: aconst_null
    //   3892: athrow
    //   3893: aconst_null
    //   3894: athrow
    //   3895: aconst_null
    //   3896: athrow
    //   3897: aconst_null
    //   3898: athrow
    //   3899: aconst_null
    //   3900: athrow
    //   3901: aconst_null
    //   3902: athrow
    //   3903: aconst_null
    //   3904: athrow
    //   3905: aconst_null
    //   3906: athrow
    //   3907: aconst_null
    //   3908: athrow
    //   3909: aconst_null
    //   3910: athrow
    //   3911: aconst_null
    //   3912: athrow
    //   3913: aconst_null
    //   3914: athrow
    //   3915: aconst_null
    //   3916: athrow
    //   3917: aconst_null
    //   3918: athrow
    //   3919: aconst_null
    //   3920: athrow
    //   3921: aconst_null
    //   3922: athrow
    //   3923: aconst_null
    //   3924: athrow
    //   3925: aconst_null
    //   3926: athrow
    //   3927: aconst_null
    //   3928: athrow
    //   3929: aconst_null
    //   3930: athrow
    //   3931: aconst_null
    //   3932: athrow
    //   3933: aconst_null
    //   3934: athrow
    //   3935: aconst_null
    //   3936: athrow
    //   3937: aconst_null
    //   3938: athrow
    //   3939: aconst_null
    //   3940: athrow
    //   3941: aconst_null
    //   3942: athrow
    //   3943: aconst_null
    //   3944: athrow
    //   3945: aconst_null
    //   3946: athrow
    //   3947: aconst_null
    //   3948: athrow
    //   3949: pop
    //   3950: goto -> 24
    //   3953: pop
    //   3954: aconst_null
    //   3955: goto -> 3949
    //   3958: dup
    //   3959: ifnull -> 3949
    //   3962: checkcast java/lang/Throwable
    //   3965: athrow
    //   3966: dup
    //   3967: ifnull -> 3953
    //   3970: checkcast java/lang/Throwable
    //   3973: athrow
    //   3974: aconst_null
    //   3975: athrow
    // Local variable table:
    //   start	length	slot	name	descriptor
    //   2838	934	10	z	I
    //   2250	1528	9	x	I
    //   1794	1984	7	bb	Lnet/minecraft/util/math/AxisAlignedBB;
    //   1986	1792	8	y	I
    //   24	3819	0	posX	D
    //   24	3819	2	posY	D
    //   24	3819	4	posZ	D
    //   86	3757	6	block	Lnet/minecraft/block/Block;
    // Exception table:
    //   from	to	target	type
    //   8	20	3958	finally
    //   459	466	466	finally
    //   459	466	3	finally
    //   460	466	3	finally
    //   460	466	3	finally
    //   460	466	459	finally
    //   711	718	718	finally
    //   711	718	3	finally
    //   712	718	718	finally
    //   712	718	711	finally
    //   712	718	3	java/lang/UnsupportedOperationException
    //   783	790	790	finally
    //   783	790	3	finally
    //   784	790	783	finally
    //   784	790	790	finally
    //   784	790	3	java/util/ConcurrentModificationException
    //   895	902	902	finally
    //   895	902	3	java/lang/NumberFormatException
    //   895	902	3	java/lang/IllegalStateException
    //   896	902	895	finally
    //   896	902	902	java/lang/RuntimeException
    //   1151	1158	1158	finally
    //   1151	1158	1158	finally
    //   1151	1158	1158	java/lang/NumberFormatException
    //   1152	1158	1151	finally
    //   1152	1158	1151	finally
    //   1356	1362	1362	finally
    //   1356	1362	1362	finally
    //   1356	1362	3	finally
    //   1356	1362	3	finally
    //   1356	1362	1362	finally
    //   1467	1474	1474	finally
    //   1467	1474	1467	java/lang/ArithmeticException
    //   1467	1474	1474	java/lang/NullPointerException
    //   1468	1474	3	java/lang/IndexOutOfBoundsException
    //   1468	1474	1467	finally
    //   1724	1730	1730	finally
    //   1724	1730	1730	java/lang/NullPointerException
    //   1724	1730	1730	java/lang/NegativeArraySizeException
    //   1724	1730	3	finally
    //   1724	1730	3	finally
    //   2179	2186	2186	finally
    //   2179	2186	3	finally
    //   2179	2186	2186	finally
    //   2179	2186	2186	java/lang/ArithmeticException
    //   2180	2186	2179	finally
    //   2508	2514	2514	finally
    //   2508	2514	3	java/lang/StringIndexOutOfBoundsException
    //   2508	2514	2514	java/lang/RuntimeException
    //   2508	2514	3	finally
    //   2508	2514	3	finally
    //   2767	2774	2774	finally
    //   2767	2774	2774	java/util/NoSuchElementException
    //   2767	2774	2767	finally
    //   2768	2774	2774	finally
    //   2768	2774	2774	java/lang/NumberFormatException
    //   3095	3102	3102	finally
    //   3095	3102	3	java/util/ConcurrentModificationException
    //   3096	3102	3	finally
    //   3096	3102	3102	finally
    //   3096	3102	3095	finally
    //   3551	3558	3558	finally
    //   3551	3558	3	finally
    //   3552	3558	3	java/lang/NumberFormatException
    //   3552	3558	3558	finally
    //   3552	3558	3551	java/lang/ArrayIndexOutOfBoundsException
    //   3624	3630	3630	finally
    //   3624	3630	3630	finally
    //   3624	3630	3	java/lang/IllegalStateException
    //   3624	3630	3	java/lang/UnsupportedOperationException
    //   3624	3630	3	finally
    //   3695	3704	3704	finally
    //   3695	3704	3	finally
    //   3695	3704	3704	finally
    //   3695	3704	3695	finally
    //   3696	3704	3695	finally
    //   3958	3966	3958	java/lang/UnsupportedOperationException
    //   3974	3976	3	java/lang/IllegalArgumentException
  }
  
  public static boolean isLiving(Entity paramEntity) {
    return Perry1.5T(null, (int)-882025182L ^ 0xFA4F1B48, paramEntity);
  }
  
  public static boolean checkForLiquid(Entity entity, boolean b) {
    if (Perryc.1 <= 0) {
      null;
    } else {
      if (null != null)
        throw (Throwable)null; 
      null;
    } 
    if (null != null)
      throw (Throwable)null; 
    null;
  }
  
  public static boolean isOnLiquid(double offset) {
    // Byte code:
    //   0: goto -> 8
    //   3: dup
    //   4: ifnull -> 4235
    //   7: athrow
    //   8: aconst_null
    //   9: getstatic Perryc.c : I
    //   12: ifge -> 4227
    //   15: pop
    //   16: aconst_null
    //   17: goto -> 4219
    //   20: nop
    //   21: nop
    //   22: nop
    //   23: athrow
    //   24: getstatic Perryc.c : I
    //   27: iflt -> 41
    //   30: ldc2_w 1981705614
    //   33: l2i
    //   34: ldc_w -168408804
    //   37: ixor
    //   38: goto -> 49
    //   41: ldc2_w 1255018650
    //   44: l2i
    //   45: ldc_w -577369666
    //   48: ixor
    //   49: ldc2_w 59587018
    //   52: l2i
    //   53: ldc_w -1383760816
    //   56: ixor
    //   57: ixor
    //   58: lookupswitch default -> 4128, 769679624 -> 41, 961567934 -> 84
    //   84: getstatic bigname/zprestige/webhack/util/WurstPlusThree/WurstplusThreeEntityUtil.mc : Lnet/minecraft/client/Minecraft;
    //   87: getstatic Perryc.1 : I
    //   90: ifeq -> 104
    //   93: ldc2_w -448869275
    //   96: l2i
    //   97: ldc_w 521089864
    //   100: ixor
    //   101: goto -> 112
    //   104: ldc2_w 1798919110
    //   107: l2i
    //   108: ldc_w -19306324
    //   111: ixor
    //   112: ldc2_w 726708127
    //   115: l2i
    //   116: ldc_w -780302991
    //   119: ixor
    //   120: ixor
    //   121: lookupswitch default -> 148, -1546040413 -> 104, 1889731 -> 4158
    //   148: getfield field_71439_g : Lnet/minecraft/client/entity/EntityPlayerSP;
    //   151: getstatic Perryc.c : I
    //   154: iflt -> 168
    //   157: ldc2_w -232764042
    //   160: l2i
    //   161: ldc_w -601736625
    //   164: ixor
    //   165: goto -> 176
    //   168: ldc2_w 1105993852
    //   171: l2i
    //   172: ldc_w -1597705455
    //   175: ixor
    //   176: ldc2_w -1664551463
    //   179: l2i
    //   180: ldc_w 1116083697
    //   183: ixor
    //   184: ixor
    //   185: lookupswitch default -> 212, -1145488543 -> 168, -263416047 -> 4206
    //   212: getfield field_70143_R : F
    //   215: ldc_w 0.8867967
    //   218: invokestatic floatToIntBits : (F)I
    //   221: ldc_w 2133001500
    //   224: ixor
    //   225: invokestatic intBitsToFloat : (I)F
    //   228: fcmpl
    //   229: iflt -> 243
    //   232: ldc2_w -1074402498
    //   235: l2i
    //   236: ldc_w 845624059
    //   239: ixor
    //   240: goto -> 251
    //   243: ldc2_w -1727463591
    //   246: l2i
    //   247: ldc_w 345646751
    //   250: ixor
    //   251: ldc2_w 1466569137
    //   254: l2i
    //   255: ldc_w -415941487
    //   258: ixor
    //   259: ixor
    //   260: tableswitch default -> 232, 1036907749 -> 284, 1036907750 -> 293
    //   284: ldc2_w -2011948918
    //   287: l2i
    //   288: ldc_w -2011948918
    //   291: ixor
    //   292: ireturn
    //   293: getstatic Perryc.0 : I
    //   296: ifle -> 310
    //   299: ldc2_w -169242138
    //   302: l2i
    //   303: ldc_w -229452264
    //   306: ixor
    //   307: goto -> 318
    //   310: ldc2_w -1107577182
    //   313: l2i
    //   314: ldc_w 1529936540
    //   317: ixor
    //   318: ldc2_w -1230239666
    //   321: l2i
    //   322: ldc_w -1700093368
    //   325: ixor
    //   326: ixor
    //   327: lookupswitch default -> 352, 733867512 -> 4196, 989091659 -> 310
    //   352: getstatic bigname/zprestige/webhack/util/WurstPlusThree/WurstplusThreeEntityUtil.mc : Lnet/minecraft/client/Minecraft;
    //   355: getstatic Perryc.0 : I
    //   358: ifle -> 372
    //   361: ldc2_w 436089532
    //   364: l2i
    //   365: ldc_w 339218537
    //   368: ixor
    //   369: goto -> 380
    //   372: ldc2_w 1756252701
    //   375: l2i
    //   376: ldc_w 1402147029
    //   379: ixor
    //   380: ldc2_w -2134609559
    //   383: l2i
    //   384: ldc_w 1010638841
    //   387: ixor
    //   388: ixor
    //   389: lookupswitch default -> 416, -1321251771 -> 4162, 170120303 -> 372
    //   416: getfield field_71439_g : Lnet/minecraft/client/entity/EntityPlayerSP;
    //   419: getstatic Perryc.0 : I
    //   422: ifle -> 436
    //   425: ldc2_w 839980089
    //   428: l2i
    //   429: ldc_w -1248942411
    //   432: ixor
    //   433: goto -> 444
    //   436: ldc2_w -529315952
    //   439: l2i
    //   440: ldc_w -1585540403
    //   443: ixor
    //   444: ldc2_w -1517868781
    //   447: l2i
    //   448: ldc_w -2124526216
    //   451: ixor
    //   452: ixor
    //   453: lookupswitch default -> 480, -1555638553 -> 4208, -1408515732 -> 436
    //   480: goto -> 484
    //   483: athrow
    //   484: invokevirtual func_184187_bx : ()Lnet/minecraft/entity/Entity;
    //   487: goto -> 491
    //   490: athrow
    //   491: ifnull -> 505
    //   494: ldc2_w 1039055673
    //   497: l2i
    //   498: ldc_w 1453556103
    //   501: ixor
    //   502: goto -> 513
    //   505: ldc2_w 164731260
    //   508: l2i
    //   509: ldc_w 1654432707
    //   512: ixor
    //   513: ldc2_w -264320873
    //   516: l2i
    //   517: ldc_w -956320559
    //   520: ixor
    //   521: ixor
    //   522: tableswitch default -> 494, 1569474296 -> 544, 1569474297 -> 1090
    //   544: getstatic Perryc.1 : I
    //   547: ifeq -> 561
    //   550: ldc2_w 1435285702
    //   553: l2i
    //   554: ldc_w -153204207
    //   557: ixor
    //   558: goto -> 569
    //   561: ldc2_w 1341534494
    //   564: l2i
    //   565: ldc_w -347529965
    //   568: ixor
    //   569: ldc2_w -1430896751
    //   572: l2i
    //   573: ldc_w 1391626867
    //   576: ixor
    //   577: ixor
    //   578: lookupswitch default -> 4176, 1528186677 -> 561, 1559992815 -> 604
    //   604: getstatic bigname/zprestige/webhack/util/WurstPlusThree/WurstplusThreeEntityUtil.mc : Lnet/minecraft/client/Minecraft;
    //   607: getstatic Perryc.0 : I
    //   610: ifle -> 624
    //   613: ldc2_w -931737384
    //   616: l2i
    //   617: ldc_w 351881103
    //   620: ixor
    //   621: goto -> 632
    //   624: ldc2_w -2099324680
    //   627: l2i
    //   628: ldc_w 32968239
    //   631: ixor
    //   632: ldc2_w 1601168160
    //   635: l2i
    //   636: ldc_w -232091528
    //   639: ixor
    //   640: ixor
    //   641: lookupswitch default -> 4170, 778872207 -> 668, 1909122063 -> 624
    //   668: getfield field_71439_g : Lnet/minecraft/client/entity/EntityPlayerSP;
    //   671: getstatic Perryc.c : I
    //   674: iflt -> 688
    //   677: ldc2_w -243803965
    //   680: l2i
    //   681: ldc_w -227447887
    //   684: ixor
    //   685: goto -> 696
    //   688: ldc2_w -695906788
    //   691: l2i
    //   692: ldc_w -895722526
    //   695: ixor
    //   696: ldc2_w -1523125898
    //   699: l2i
    //   700: ldc_w 901956468
    //   703: ixor
    //   704: ixor
    //   705: lookupswitch default -> 4150, -1930614788 -> 732, -1812823696 -> 688
    //   732: goto -> 736
    //   735: athrow
    //   736: invokevirtual func_184187_bx : ()Lnet/minecraft/entity/Entity;
    //   739: goto -> 743
    //   742: athrow
    //   743: getstatic Perryc.0 : I
    //   746: ifle -> 760
    //   749: ldc2_w 1864921363
    //   752: l2i
    //   753: ldc_w 1569232537
    //   756: ixor
    //   757: goto -> 768
    //   760: ldc2_w -642292012
    //   763: l2i
    //   764: ldc_w 1737893966
    //   767: ixor
    //   768: ldc2_w -1471810127
    //   771: l2i
    //   772: ldc_w -290200888
    //   775: ixor
    //   776: ixor
    //   777: lookupswitch default -> 804, -2076006604 -> 760, 1951854835 -> 4134
    //   804: goto -> 808
    //   807: athrow
    //   808: invokevirtual func_174813_aQ : ()Lnet/minecraft/util/math/AxisAlignedBB;
    //   811: goto -> 815
    //   814: athrow
    //   815: ldc2_w 2.7450289380489815E306
    //   818: invokestatic doubleToLongBits : (D)J
    //   821: ldc2_w 9191642040440356223
    //   824: lxor
    //   825: invokestatic longBitsToDouble : (J)D
    //   828: ldc2_w 1.372283694136678E308
    //   831: invokestatic doubleToLongBits : (D)J
    //   834: ldc2_w 9216736956874526722
    //   837: lxor
    //   838: invokestatic longBitsToDouble : (J)D
    //   841: ldc2_w 2.8700300834779683E307
    //   844: invokestatic doubleToLongBits : (D)J
    //   847: ldc2_w 9206606062203503783
    //   850: lxor
    //   851: invokestatic longBitsToDouble : (J)D
    //   854: getstatic Perryc.c : I
    //   857: iflt -> 871
    //   860: ldc2_w 2092883937
    //   863: l2i
    //   864: ldc_w 659284895
    //   867: ixor
    //   868: goto -> 879
    //   871: ldc2_w 459836744
    //   874: l2i
    //   875: ldc_w -1677394719
    //   878: ixor
    //   879: ldc2_w 1017435884
    //   882: l2i
    //   883: ldc_w 2143603869
    //   886: ixor
    //   887: ixor
    //   888: lookupswitch default -> 4188, -1005818920 -> 916, 412427791 -> 871
    //   916: goto -> 920
    //   919: athrow
    //   920: invokevirtual func_191195_a : (DDD)Lnet/minecraft/util/math/AxisAlignedBB;
    //   923: goto -> 927
    //   926: athrow
    //   927: ldc2_w 1.0147263089487148E308
    //   930: invokestatic doubleToLongBits : (D)J
    //   933: ldc2_w 9214945443878823580
    //   936: lxor
    //   937: invokestatic longBitsToDouble : (J)D
    //   940: getstatic Perryc.1 : I
    //   943: ifeq -> 957
    //   946: ldc2_w 542177245
    //   949: l2i
    //   950: ldc_w -2032080609
    //   953: ixor
    //   954: goto -> 965
    //   957: ldc2_w 1109575750
    //   960: l2i
    //   961: ldc_w 819811939
    //   964: ixor
    //   965: ldc2_w 836197770
    //   968: l2i
    //   969: ldc_w -1312759833
    //   972: ixor
    //   973: ixor
    //   974: lookupswitch default -> 1000, 648518831 -> 4166, 1508604372 -> 957
    //   1000: dload_0
    //   1001: dneg
    //   1002: ldc2_w 1.8341487043805791E307
    //   1005: invokestatic doubleToLongBits : (D)J
    //   1008: ldc2_w 9203702324692294847
    //   1011: lxor
    //   1012: invokestatic longBitsToDouble : (J)D
    //   1015: getstatic Perryc.0 : I
    //   1018: ifle -> 1032
    //   1021: ldc2_w 1732726355
    //   1024: l2i
    //   1025: ldc_w -1315864492
    //   1028: ixor
    //   1029: goto -> 1040
    //   1032: ldc2_w 1614684351
    //   1035: l2i
    //   1036: ldc_w -585757226
    //   1039: ixor
    //   1040: ldc2_w 1694919128
    //   1043: l2i
    //   1044: ldc_w -606997733
    //   1047: ixor
    //   1048: ixor
    //   1049: lookupswitch default -> 4102, 67090346 -> 1076, 1744917700 -> 1032
    //   1076: goto -> 1080
    //   1079: athrow
    //   1080: invokevirtual func_72317_d : (DDD)Lnet/minecraft/util/math/AxisAlignedBB;
    //   1083: goto -> 1087
    //   1086: athrow
    //   1087: goto -> 1563
    //   1090: getstatic Perryc.1 : I
    //   1093: ifeq -> 1107
    //   1096: ldc2_w -810742455
    //   1099: l2i
    //   1100: ldc_w 62517769
    //   1103: ixor
    //   1104: goto -> 1115
    //   1107: ldc2_w 1980746637
    //   1110: l2i
    //   1111: ldc_w 1486726615
    //   1114: ixor
    //   1115: ldc2_w 1005728633
    //   1118: l2i
    //   1119: ldc_w -598448791
    //   1122: ixor
    //   1123: ixor
    //   1124: lookupswitch default -> 1152, 567718379 -> 1107, 733129040 -> 4136
    //   1152: getstatic bigname/zprestige/webhack/util/WurstPlusThree/WurstplusThreeEntityUtil.mc : Lnet/minecraft/client/Minecraft;
    //   1155: getstatic Perryc.1 : I
    //   1158: ifeq -> 1172
    //   1161: ldc2_w -1873117734
    //   1164: l2i
    //   1165: ldc_w 2099671673
    //   1168: ixor
    //   1169: goto -> 1180
    //   1172: ldc2_w -1048761034
    //   1175: l2i
    //   1176: ldc_w -1947146693
    //   1179: ixor
    //   1180: ldc2_w -1226635517
    //   1183: l2i
    //   1184: ldc_w -1513927547
    //   1187: ixor
    //   1188: ixor
    //   1189: lookupswitch default -> 4192, -27507675 -> 1172, 1504542859 -> 1216
    //   1216: getfield field_71439_g : Lnet/minecraft/client/entity/EntityPlayerSP;
    //   1219: getstatic Perryc.0 : I
    //   1222: ifle -> 1236
    //   1225: ldc2_w 698895890
    //   1228: l2i
    //   1229: ldc_w 132123364
    //   1232: ixor
    //   1233: goto -> 1244
    //   1236: ldc2_w -500434422
    //   1239: l2i
    //   1240: ldc_w -2062413850
    //   1243: ixor
    //   1244: ldc2_w -981626946
    //   1247: l2i
    //   1248: ldc_w -631792431
    //   1251: ixor
    //   1252: ixor
    //   1253: lookupswitch default -> 1280, -1097767925 -> 1236, 828528537 -> 4198
    //   1280: goto -> 1284
    //   1283: athrow
    //   1284: invokevirtual func_174813_aQ : ()Lnet/minecraft/util/math/AxisAlignedBB;
    //   1287: goto -> 1291
    //   1290: athrow
    //   1291: ldc2_w 8.118156442756338E307
    //   1294: invokestatic doubleToLongBits : (D)J
    //   1297: ldc2_w 9213492714487381447
    //   1300: lxor
    //   1301: invokestatic longBitsToDouble : (J)D
    //   1304: ldc2_w 6.083854975077044E307
    //   1307: invokestatic doubleToLongBits : (D)J
    //   1310: ldc2_w 9211454173169260119
    //   1313: lxor
    //   1314: invokestatic longBitsToDouble : (J)D
    //   1317: ldc2_w 5.585461404896374E307
    //   1320: invokestatic doubleToLongBits : (D)J
    //   1323: ldc2_w 9210954740857166113
    //   1326: lxor
    //   1327: invokestatic longBitsToDouble : (J)D
    //   1330: getstatic Perryc.0 : I
    //   1333: ifle -> 1347
    //   1336: ldc2_w 1247607995
    //   1339: l2i
    //   1340: ldc_w -148329569
    //   1343: ixor
    //   1344: goto -> 1355
    //   1347: ldc2_w -1839800377
    //   1350: l2i
    //   1351: ldc_w -1197804081
    //   1354: ixor
    //   1355: ldc2_w -669828415
    //   1358: l2i
    //   1359: ldc_w -348567613
    //   1362: ixor
    //   1363: ixor
    //   1364: lookupswitch default -> 4180, -1906431450 -> 1347, 434525962 -> 1392
    //   1392: goto -> 1396
    //   1395: athrow
    //   1396: invokevirtual func_191195_a : (DDD)Lnet/minecraft/util/math/AxisAlignedBB;
    //   1399: goto -> 1403
    //   1402: athrow
    //   1403: ldc2_w 5.328775939603725E307
    //   1406: invokestatic doubleToLongBits : (D)J
    //   1409: ldc2_w 9210697520413159259
    //   1412: lxor
    //   1413: invokestatic longBitsToDouble : (J)D
    //   1416: getstatic Perryc.c : I
    //   1419: iflt -> 1433
    //   1422: ldc2_w 1411524555
    //   1425: l2i
    //   1426: ldc_w -139298469
    //   1429: ixor
    //   1430: goto -> 1441
    //   1433: ldc2_w -1117319155
    //   1436: l2i
    //   1437: ldc_w -200728634
    //   1440: ixor
    //   1441: ldc2_w 595566771
    //   1444: l2i
    //   1445: ldc_w -363431064
    //   1448: ixor
    //   1449: ixor
    //   1450: lookupswitch default -> 1476, 876077343 -> 1433, 1790543179 -> 4148
    //   1476: dload_0
    //   1477: dneg
    //   1478: ldc2_w 1.2445647265726582E308
    //   1481: invokestatic doubleToLongBits : (D)J
    //   1484: ldc2_w 9216097031090114670
    //   1487: lxor
    //   1488: invokestatic longBitsToDouble : (J)D
    //   1491: getstatic Perryc.c : I
    //   1494: iflt -> 1508
    //   1497: ldc2_w -2048829183
    //   1500: l2i
    //   1501: ldc_w -1849628694
    //   1504: ixor
    //   1505: goto -> 1516
    //   1508: ldc2_w 22622511
    //   1511: l2i
    //   1512: ldc_w -1955188825
    //   1515: ixor
    //   1516: ldc2_w -1475545603
    //   1519: l2i
    //   1520: ldc_w -1853495920
    //   1523: ixor
    //   1524: ixor
    //   1525: lookupswitch default -> 4194, -1280962843 -> 1552, 766029446 -> 1508
    //   1552: goto -> 1556
    //   1555: athrow
    //   1556: invokevirtual func_72317_d : (DDD)Lnet/minecraft/util/math/AxisAlignedBB;
    //   1559: goto -> 1563
    //   1562: athrow
    //   1563: getstatic Perryc.0 : I
    //   1566: ifle -> 1580
    //   1569: ldc2_w -1537852559
    //   1572: l2i
    //   1573: ldc_w -792632200
    //   1576: ixor
    //   1577: goto -> 1588
    //   1580: ldc2_w 1231891338
    //   1583: l2i
    //   1584: ldc_w -1920278743
    //   1587: ixor
    //   1588: ldc2_w 1782378996
    //   1591: l2i
    //   1592: ldc_w -35296664
    //   1595: ixor
    //   1596: ixor
    //   1597: lookupswitch default -> 4146, -481377131 -> 1580, 1396600639 -> 1624
    //   1624: astore_2
    //   1625: ldc2_w -9617704
    //   1628: l2i
    //   1629: ldc_w -9617704
    //   1632: ixor
    //   1633: getstatic Perryc.c : I
    //   1636: iflt -> 1650
    //   1639: ldc2_w 534517304
    //   1642: l2i
    //   1643: ldc_w -1710365816
    //   1646: ixor
    //   1647: goto -> 1658
    //   1650: ldc2_w 2112911439
    //   1653: l2i
    //   1654: ldc_w 554543823
    //   1657: ixor
    //   1658: ldc2_w 1889081290
    //   1661: l2i
    //   1662: ldc_w -210150940
    //   1665: ixor
    //   1666: ixor
    //   1667: lookupswitch default -> 1692, -1315487592 -> 1650, 103922590 -> 4124
    //   1692: istore_3
    //   1693: getstatic Perryc.c : I
    //   1696: iflt -> 1710
    //   1699: ldc2_w -308639126
    //   1702: l2i
    //   1703: ldc_w -580637372
    //   1706: ixor
    //   1707: goto -> 1718
    //   1710: ldc2_w -944090964
    //   1713: l2i
    //   1714: ldc_w -1598103142
    //   1717: ixor
    //   1718: ldc2_w -1236712901
    //   1721: l2i
    //   1722: ldc_w 1477648604
    //   1725: ixor
    //   1726: ixor
    //   1727: lookupswitch default -> 4142, -1990274095 -> 1752, -559626807 -> 1710
    //   1752: aload_2
    //   1753: getstatic Perryc.1 : I
    //   1756: ifeq -> 1770
    //   1759: ldc2_w 1254490003
    //   1762: l2i
    //   1763: ldc_w 1485951451
    //   1766: ixor
    //   1767: goto -> 1778
    //   1770: ldc2_w -1001402772
    //   1773: l2i
    //   1774: ldc_w 2104599565
    //   1777: ixor
    //   1778: ldc2_w 291955533
    //   1781: l2i
    //   1782: ldc_w -575465999
    //   1785: ixor
    //   1786: ixor
    //   1787: lookupswitch default -> 1812, -851620101 -> 1770, -561915660 -> 4138
    //   1812: getfield field_72338_b : D
    //   1815: d2i
    //   1816: getstatic Perryc.1 : I
    //   1819: ifeq -> 1833
    //   1822: ldc2_w 1682210172
    //   1825: l2i
    //   1826: ldc_w -1472231229
    //   1829: ixor
    //   1830: goto -> 1841
    //   1833: ldc2_w 627691738
    //   1836: l2i
    //   1837: ldc_w 946184871
    //   1840: ixor
    //   1841: ldc2_w 1385499946
    //   1844: l2i
    //   1845: ldc_w 417999824
    //   1848: ixor
    //   1849: ixor
    //   1850: lookupswitch default -> 4132, -2046504123 -> 1833, 1467176071 -> 1876
    //   1876: istore #4
    //   1878: getstatic Perryc.1 : I
    //   1881: ifeq -> 1895
    //   1884: ldc2_w 1410830794
    //   1887: l2i
    //   1888: ldc_w -588624241
    //   1891: ixor
    //   1892: goto -> 1903
    //   1895: ldc2_w 772590430
    //   1898: l2i
    //   1899: ldc_w 1112206728
    //   1902: ixor
    //   1903: ldc2_w 578616343
    //   1906: l2i
    //   1907: ldc_w 1013534748
    //   1910: ixor
    //   1911: ixor
    //   1912: lookupswitch default -> 1940, -1763151026 -> 4200, -1406174316 -> 1895
    //   1940: aload_2
    //   1941: getstatic Perryc.c : I
    //   1944: iflt -> 1958
    //   1947: ldc2_w 663504811
    //   1950: l2i
    //   1951: ldc_w 1657555149
    //   1954: ixor
    //   1955: goto -> 1966
    //   1958: ldc2_w 70933297
    //   1961: l2i
    //   1962: ldc_w 1849074090
    //   1965: ixor
    //   1966: ldc2_w 1285029611
    //   1969: l2i
    //   1970: ldc_w 800088044
    //   1973: ixor
    //   1974: ixor
    //   1975: lookupswitch default -> 2000, -418182499 -> 1958, 644329057 -> 4204
    //   2000: getfield field_72340_a : D
    //   2003: getstatic Perryc.1 : I
    //   2006: ifeq -> 2020
    //   2009: ldc2_w -551612633
    //   2012: l2i
    //   2013: ldc_w -1336374141
    //   2016: ixor
    //   2017: goto -> 2028
    //   2020: ldc2_w -1610348466
    //   2023: l2i
    //   2024: ldc_w 1145407411
    //   2027: ixor
    //   2028: ldc2_w -1719250356
    //   2031: l2i
    //   2032: ldc_w -1387139404
    //   2035: ixor
    //   2036: ixor
    //   2037: lookupswitch default -> 2064, -957852240 -> 2020, 1536180060 -> 4202
    //   2064: goto -> 2068
    //   2067: athrow
    //   2068: invokestatic func_76128_c : (D)I
    //   2071: goto -> 2075
    //   2074: athrow
    //   2075: getstatic Perryc.1 : I
    //   2078: ifeq -> 2092
    //   2081: ldc2_w -2143669888
    //   2084: l2i
    //   2085: ldc_w -2138297637
    //   2088: ixor
    //   2089: goto -> 2100
    //   2092: ldc2_w -234816631
    //   2095: l2i
    //   2096: ldc_w -1755926596
    //   2099: ixor
    //   2100: ldc2_w -196072981
    //   2103: l2i
    //   2104: ldc_w -1944212437
    //   2107: ixor
    //   2108: ixor
    //   2109: lookupswitch default -> 2136, 556412060 -> 2092, 2029756059 -> 4130
    //   2136: istore #5
    //   2138: getstatic Perryc.0 : I
    //   2141: ifle -> 2155
    //   2144: ldc2_w 538734573
    //   2147: l2i
    //   2148: ldc_w 1107221248
    //   2151: ixor
    //   2152: goto -> 2163
    //   2155: ldc2_w 369508941
    //   2158: l2i
    //   2159: ldc_w -343523590
    //   2162: ixor
    //   2163: ldc2_w -674178080
    //   2166: l2i
    //   2167: ldc_w -560698590
    //   2170: ixor
    //   2171: ixor
    //   2172: lookupswitch default -> 2200, 423556681 -> 2155, 1755710511 -> 4182
    //   2200: iload #5
    //   2202: getstatic Perryc.c : I
    //   2205: iflt -> 2219
    //   2208: ldc2_w -753388546
    //   2211: l2i
    //   2212: ldc_w -919557136
    //   2215: ixor
    //   2216: goto -> 2227
    //   2219: ldc2_w -1480859054
    //   2222: l2i
    //   2223: ldc_w 2082313466
    //   2226: ixor
    //   2227: ldc2_w 854768679
    //   2230: l2i
    //   2231: ldc_w -1908504846
    //   2234: ixor
    //   2235: ixor
    //   2236: lookupswitch default -> 2264, -1494965541 -> 4112, 27218610 -> 2219
    //   2264: aload_2
    //   2265: getstatic Perryc.1 : I
    //   2268: ifeq -> 2282
    //   2271: ldc2_w 370148340
    //   2274: l2i
    //   2275: ldc_w 1501075810
    //   2278: ixor
    //   2279: goto -> 2290
    //   2282: ldc2_w 420629276
    //   2285: l2i
    //   2286: ldc_w -135132945
    //   2289: ixor
    //   2290: ldc2_w 2104755504
    //   2293: l2i
    //   2294: ldc_w -1616889123
    //   2297: ixor
    //   2298: ixor
    //   2299: lookupswitch default -> 4174, -1380145797 -> 2282, 204766238 -> 2324
    //   2324: getfield field_72336_d : D
    //   2327: ldc2_w 40.04197821978004
    //   2330: invokestatic doubleToLongBits : (D)J
    //   2333: ldc2_w 9201985846533983423
    //   2336: lxor
    //   2337: invokestatic longBitsToDouble : (J)D
    //   2340: dadd
    //   2341: getstatic Perryc.0 : I
    //   2344: ifle -> 2358
    //   2347: ldc2_w 1067207079
    //   2350: l2i
    //   2351: ldc_w 1055982758
    //   2354: ixor
    //   2355: goto -> 2366
    //   2358: ldc2_w -1473305034
    //   2361: l2i
    //   2362: ldc_w -1962888973
    //   2365: ixor
    //   2366: ldc2_w -660187790
    //   2369: l2i
    //   2370: ldc_w 1280117495
    //   2373: ixor
    //   2374: ixor
    //   2375: lookupswitch default -> 2400, -1786375548 -> 4154, 1988509051 -> 2358
    //   2400: goto -> 2404
    //   2403: athrow
    //   2404: invokestatic func_76128_c : (D)I
    //   2407: goto -> 2411
    //   2410: athrow
    //   2411: if_icmpge -> 2425
    //   2414: ldc2_w 368119239
    //   2417: l2i
    //   2418: ldc_w -1697359230
    //   2421: ixor
    //   2422: goto -> 2433
    //   2425: ldc2_w -7258142
    //   2428: l2i
    //   2429: ldc_w 1890871462
    //   2432: ixor
    //   2433: ldc2_w 571384494
    //   2436: l2i
    //   2437: ldc_w 1964164433
    //   2440: ixor
    //   2441: ixor
    //   2442: tableswitch default -> 2414, -667340614 -> 2464, -667340613 -> 4041
    //   2464: getstatic Perryc.0 : I
    //   2467: ifle -> 2481
    //   2470: ldc2_w -1289355804
    //   2473: l2i
    //   2474: ldc_w 996311897
    //   2477: ixor
    //   2478: goto -> 2489
    //   2481: ldc2_w -2030220822
    //   2484: l2i
    //   2485: ldc_w -1153904177
    //   2488: ixor
    //   2489: ldc2_w -323769052
    //   2492: l2i
    //   2493: ldc_w -1777577739
    //   2496: ixor
    //   2497: ixor
    //   2498: lookupswitch default -> 2524, -2038118569 -> 2481, -218594452 -> 4164
    //   2524: aload_2
    //   2525: getstatic Perryc.1 : I
    //   2528: ifeq -> 2542
    //   2531: ldc2_w 518673091
    //   2534: l2i
    //   2535: ldc_w 429898842
    //   2538: ixor
    //   2539: goto -> 2550
    //   2542: ldc2_w 1464027562
    //   2545: l2i
    //   2546: ldc_w 81180294
    //   2549: ixor
    //   2550: ldc2_w -1217926559
    //   2553: l2i
    //   2554: ldc_w 1066646567
    //   2557: ixor
    //   2558: ixor
    //   2559: lookupswitch default -> 4144, -1887323937 -> 2542, -614356630 -> 2584
    //   2584: getfield field_72339_c : D
    //   2587: getstatic Perryc.1 : I
    //   2590: ifeq -> 2604
    //   2593: ldc2_w -1871590676
    //   2596: l2i
    //   2597: ldc_w 590844611
    //   2600: ixor
    //   2601: goto -> 2612
    //   2604: ldc2_w 1784030911
    //   2607: l2i
    //   2608: ldc_w -968047868
    //   2611: ixor
    //   2612: ldc2_w 2071244047
    //   2615: l2i
    //   2616: ldc_w 65261317
    //   2619: ixor
    //   2620: ixor
    //   2621: lookupswitch default -> 2648, -875480539 -> 4186, 1923139956 -> 2604
    //   2648: goto -> 2652
    //   2651: athrow
    //   2652: invokestatic func_76128_c : (D)I
    //   2655: goto -> 2659
    //   2658: athrow
    //   2659: getstatic Perryc.1 : I
    //   2662: ifeq -> 2676
    //   2665: ldc2_w -220633316
    //   2668: l2i
    //   2669: ldc_w -812954626
    //   2672: ixor
    //   2673: goto -> 2684
    //   2676: ldc2_w 983700932
    //   2679: l2i
    //   2680: ldc_w 245275138
    //   2683: ixor
    //   2684: ldc2_w -2142761717
    //   2687: l2i
    //   2688: ldc_w 1868199086
    //   2691: ixor
    //   2692: ixor
    //   2693: lookupswitch default -> 2720, -767535801 -> 4106, -479294743 -> 2676
    //   2720: istore #6
    //   2722: getstatic Perryc.0 : I
    //   2725: ifle -> 2739
    //   2728: ldc2_w -1561402426
    //   2731: l2i
    //   2732: ldc_w -1801340315
    //   2735: ixor
    //   2736: goto -> 2747
    //   2739: ldc2_w -1582417881
    //   2742: l2i
    //   2743: ldc_w 1642914797
    //   2746: ixor
    //   2747: ldc2_w -1602395959
    //   2750: l2i
    //   2751: ldc_w -1611049538
    //   2754: ixor
    //   2755: ixor
    //   2756: lookupswitch default -> 2784, -1078888947 -> 2739, 164326612 -> 4168
    //   2784: iload #6
    //   2786: getstatic Perryc.c : I
    //   2789: iflt -> 2803
    //   2792: ldc2_w 1972938693
    //   2795: l2i
    //   2796: ldc_w -1392733214
    //   2799: ixor
    //   2800: goto -> 2811
    //   2803: ldc2_w -133292267
    //   2806: l2i
    //   2807: ldc_w -1265254696
    //   2810: ixor
    //   2811: ldc2_w -108407735
    //   2814: l2i
    //   2815: ldc_w 1491784203
    //   2818: ixor
    //   2819: ixor
    //   2820: lookupswitch default -> 2848, -449661882 -> 2803, 2013737573 -> 4114
    //   2848: aload_2
    //   2849: getstatic Perryc.c : I
    //   2852: iflt -> 2866
    //   2855: ldc2_w 1971783505
    //   2858: l2i
    //   2859: ldc_w -2107367179
    //   2862: ixor
    //   2863: goto -> 2874
    //   2866: ldc2_w 1685744874
    //   2869: l2i
    //   2870: ldc_w 319447144
    //   2873: ixor
    //   2874: ldc2_w 1024386697
    //   2877: l2i
    //   2878: ldc_w 393297139
    //   2881: ixor
    //   2882: ixor
    //   2883: lookupswitch default -> 4172, -576913954 -> 2866, 1561319160 -> 2908
    //   2908: getfield field_72334_f : D
    //   2911: ldc2_w 4.738398720249445
    //   2914: invokestatic doubleToLongBits : (D)J
    //   2917: ldc2_w 9215196200650376379
    //   2920: lxor
    //   2921: invokestatic longBitsToDouble : (J)D
    //   2924: dadd
    //   2925: getstatic Perryc.c : I
    //   2928: iflt -> 2942
    //   2931: ldc2_w 36791647
    //   2934: l2i
    //   2935: ldc_w -2076873000
    //   2938: ixor
    //   2939: goto -> 2950
    //   2942: ldc2_w 1413804642
    //   2945: l2i
    //   2946: ldc_w -30885522
    //   2949: ixor
    //   2950: ldc2_w -657032174
    //   2953: l2i
    //   2954: ldc_w 2115880383
    //   2957: ixor
    //   2958: ixor
    //   2959: lookupswitch default -> 4190, 212333217 -> 2984, 550482474 -> 2942
    //   2984: goto -> 2988
    //   2987: athrow
    //   2988: invokestatic func_76128_c : (D)I
    //   2991: goto -> 2995
    //   2994: athrow
    //   2995: if_icmpge -> 3009
    //   2998: ldc2_w 990351269
    //   3001: l2i
    //   3002: ldc_w -107324352
    //   3005: ixor
    //   3006: goto -> 3017
    //   3009: ldc2_w 525700287
    //   3012: l2i
    //   3013: ldc_w -574070949
    //   3016: ixor
    //   3017: ldc2_w -1007111034
    //   3020: l2i
    //   3021: ldc_w 138063917
    //   3024: ixor
    //   3025: ixor
    //   3026: tableswitch default -> 2998, 157275982 -> 3048, 157275983 -> 4035
    //   3048: getstatic Perryc.0 : I
    //   3051: ifle -> 3065
    //   3054: ldc2_w 1503720456
    //   3057: l2i
    //   3058: ldc_w -36200906
    //   3061: ixor
    //   3062: goto -> 3073
    //   3065: ldc2_w -825079574
    //   3068: l2i
    //   3069: ldc_w 1752510159
    //   3072: ixor
    //   3073: ldc2_w -1071387956
    //   3076: l2i
    //   3077: ldc_w 1261096360
    //   3080: ixor
    //   3081: ixor
    //   3082: lookupswitch default -> 4108, 766394689 -> 3108, 796806490 -> 3065
    //   3108: getstatic bigname/zprestige/webhack/util/WurstPlusThree/WurstplusThreeEntityUtil.mc : Lnet/minecraft/client/Minecraft;
    //   3111: getstatic Perryc.1 : I
    //   3114: ifeq -> 3128
    //   3117: ldc2_w 2111064148
    //   3120: l2i
    //   3121: ldc_w 1033919415
    //   3124: ixor
    //   3125: goto -> 3136
    //   3128: ldc2_w 5372095
    //   3131: l2i
    //   3132: ldc_w 1008677863
    //   3135: ixor
    //   3136: ldc2_w -13340935
    //   3139: l2i
    //   3140: ldc_w -680606793
    //   3143: ixor
    //   3144: ixor
    //   3145: lookupswitch default -> 3172, 1719913873 -> 3128, 1747893933 -> 4178
    //   3172: getfield field_71441_e : Lnet/minecraft/client/multiplayer/WorldClient;
    //   3175: new net/minecraft/util/math/BlockPos
    //   3178: dup
    //   3179: getstatic Perryc.1 : I
    //   3182: ifeq -> 3196
    //   3185: ldc2_w 1181704268
    //   3188: l2i
    //   3189: ldc_w -193512724
    //   3192: ixor
    //   3193: goto -> 3204
    //   3196: ldc2_w -337204874
    //   3199: l2i
    //   3200: ldc_w -1383772666
    //   3203: ixor
    //   3204: ldc2_w -459343957
    //   3207: l2i
    //   3208: ldc_w -418592180
    //   3211: ixor
    //   3212: ixor
    //   3213: lookupswitch default -> 4120, -1316329657 -> 3196, 1173478039 -> 3240
    //   3240: iload #5
    //   3242: getstatic Perryc.c : I
    //   3245: iflt -> 3259
    //   3248: ldc2_w -1805322584
    //   3251: l2i
    //   3252: ldc_w 1701045559
    //   3255: ixor
    //   3256: goto -> 3267
    //   3259: ldc2_w -1217724742
    //   3262: l2i
    //   3263: ldc_w 966210433
    //   3266: ixor
    //   3267: ldc2_w 1211519342
    //   3270: l2i
    //   3271: ldc_w 1581976170
    //   3274: ixor
    //   3275: ixor
    //   3276: lookupswitch default -> 3304, -411416421 -> 4160, 1753188263 -> 3259
    //   3304: iload #4
    //   3306: getstatic Perryc.c : I
    //   3309: iflt -> 3323
    //   3312: ldc2_w -196881749
    //   3315: l2i
    //   3316: ldc_w -2037079184
    //   3319: ixor
    //   3320: goto -> 3331
    //   3323: ldc2_w -710092592
    //   3326: l2i
    //   3327: ldc_w 504740384
    //   3330: ixor
    //   3331: ldc2_w -1581229218
    //   3334: l2i
    //   3335: ldc_w -755834151
    //   3338: ixor
    //   3339: ixor
    //   3340: lookupswitch default -> 4126, -1198793865 -> 3368, 31836252 -> 3323
    //   3368: iload #6
    //   3370: getstatic Perryc.1 : I
    //   3373: ifeq -> 3387
    //   3376: ldc2_w 1368240429
    //   3379: l2i
    //   3380: ldc_w -616922683
    //   3383: ixor
    //   3384: goto -> 3395
    //   3387: ldc2_w 1859112011
    //   3390: l2i
    //   3391: ldc_w -879795373
    //   3394: ixor
    //   3395: ldc2_w -1735554125
    //   3398: l2i
    //   3399: ldc_w -1537822386
    //   3402: ixor
    //   3403: ixor
    //   3404: lookupswitch default -> 3432, -2020291657 -> 3387, -1234433515 -> 4140
    //   3432: goto -> 3436
    //   3435: athrow
    //   3436: invokespecial <init> : (III)V
    //   3439: goto -> 3443
    //   3442: athrow
    //   3443: getstatic Perryc.c : I
    //   3446: iflt -> 3460
    //   3449: ldc2_w 1316632866
    //   3452: l2i
    //   3453: ldc_w -762912628
    //   3456: ixor
    //   3457: goto -> 3468
    //   3460: ldc2_w -457035556
    //   3463: l2i
    //   3464: ldc_w -209077550
    //   3467: ixor
    //   3468: ldc2_w -1889621952
    //   3471: l2i
    //   3472: ldc_w 1796547487
    //   3475: ixor
    //   3476: ixor
    //   3477: lookupswitch default -> 4184, -218103343 -> 3504, 2025280113 -> 3460
    //   3504: goto -> 3508
    //   3507: athrow
    //   3508: invokevirtual func_180495_p : (Lnet/minecraft/util/math/BlockPos;)Lnet/minecraft/block/state/IBlockState;
    //   3511: goto -> 3515
    //   3514: athrow
    //   3515: getstatic Perryc.c : I
    //   3518: iflt -> 3532
    //   3521: ldc2_w -377338240
    //   3524: l2i
    //   3525: ldc_w 1446747399
    //   3528: ixor
    //   3529: goto -> 3540
    //   3532: ldc2_w -1807858388
    //   3535: l2i
    //   3536: ldc_w -776643822
    //   3539: ixor
    //   3540: ldc2_w -1350846465
    //   3543: l2i
    //   3544: ldc_w 123221202
    //   3547: ixor
    //   3548: ixor
    //   3549: lookupswitch default -> 3576, -1823940366 -> 3532, 395991210 -> 4118
    //   3576: goto -> 3580
    //   3579: athrow
    //   3580: invokeinterface func_177230_c : ()Lnet/minecraft/block/Block;
    //   3585: goto -> 3589
    //   3588: athrow
    //   3589: getstatic Perryc.0 : I
    //   3592: ifle -> 3606
    //   3595: ldc2_w -1724400166
    //   3598: l2i
    //   3599: ldc_w 641593728
    //   3602: ixor
    //   3603: goto -> 3614
    //   3606: ldc2_w -485937972
    //   3609: l2i
    //   3610: ldc_w 668585941
    //   3613: ixor
    //   3614: ldc2_w 1701975180
    //   3617: l2i
    //   3618: ldc_w -663147402
    //   3621: ixor
    //   3622: ixor
    //   3623: lookupswitch default -> 3648, 33649824 -> 4116, 373652090 -> 3606
    //   3648: astore #7
    //   3650: getstatic Perryc.1 : I
    //   3653: ifeq -> 3667
    //   3656: ldc2_w 497637970
    //   3659: l2i
    //   3660: ldc_w -1916941198
    //   3663: ixor
    //   3664: goto -> 3675
    //   3667: ldc2_w -1525998832
    //   3670: l2i
    //   3671: ldc_w 1874123072
    //   3674: ixor
    //   3675: ldc2_w -474281737
    //   3678: l2i
    //   3679: ldc_w -1596794240
    //   3682: ixor
    //   3683: ixor
    //   3684: lookupswitch default -> 4104, -1982459865 -> 3712, -746765225 -> 3667
    //   3712: aload #7
    //   3714: getstatic Perryc.c : I
    //   3717: iflt -> 3731
    //   3720: ldc2_w 1393361326
    //   3723: l2i
    //   3724: ldc_w -1668927351
    //   3727: ixor
    //   3728: goto -> 3739
    //   3731: ldc2_w 1911920523
    //   3734: l2i
    //   3735: ldc_w 954949676
    //   3738: ixor
    //   3739: ldc2_w -1784880605
    //   3742: l2i
    //   3743: ldc_w 1528088165
    //   3746: ixor
    //   3747: ixor
    //   3748: lookupswitch default -> 3776, 16979297 -> 4152, 1815912736 -> 3731
    //   3776: getstatic net/minecraft/init/Blocks.field_150350_a : Lnet/minecraft/block/Block;
    //   3779: if_acmpeq -> 3793
    //   3782: ldc2_w 965272528
    //   3785: l2i
    //   3786: ldc_w 1654780680
    //   3789: ixor
    //   3790: goto -> 3801
    //   3793: ldc2_w 345622612
    //   3796: l2i
    //   3797: ldc_w 1336989837
    //   3800: ixor
    //   3801: ldc2_w -2039548159
    //   3804: l2i
    //   3805: ldc_w -1923499845
    //   3808: ixor
    //   3809: ixor
    //   3810: tableswitch default -> 3782, 1344167778 -> 3832, 1344167779 -> 4029
    //   3832: getstatic Perryc.0 : I
    //   3835: ifle -> 3849
    //   3838: ldc2_w 1266685490
    //   3841: l2i
    //   3842: ldc_w 1944183292
    //   3845: ixor
    //   3846: goto -> 3857
    //   3849: ldc2_w 2022071393
    //   3852: l2i
    //   3853: ldc_w -1314290353
    //   3856: ixor
    //   3857: ldc2_w -1369193970
    //   3860: l2i
    //   3861: ldc_w -340211225
    //   3864: ixor
    //   3865: ixor
    //   3866: lookupswitch default -> 3892, -931060688 -> 3849, 2109406247 -> 4122
    //   3892: aload #7
    //   3894: instanceof net/minecraft/block/BlockLiquid
    //   3897: ifne -> 3911
    //   3900: ldc2_w 1548379378
    //   3903: l2i
    //   3904: ldc_w 2106631753
    //   3907: ixor
    //   3908: goto -> 3919
    //   3911: ldc2_w -10175808
    //   3914: l2i
    //   3915: ldc_w -557942662
    //   3918: ixor
    //   3919: ldc2_w 1425239974
    //   3922: l2i
    //   3923: ldc_w 1353555093
    //   3926: ixor
    //   3927: ixor
    //   3928: tableswitch default -> 3900, 629420424 -> 3952, 629420425 -> 3961
    //   3952: ldc2_w 108697160
    //   3955: l2i
    //   3956: ldc_w 108697160
    //   3959: ixor
    //   3960: ireturn
    //   3961: ldc2_w 316510291
    //   3964: l2i
    //   3965: ldc_w 316510290
    //   3968: ixor
    //   3969: getstatic Perryc.1 : I
    //   3972: ifeq -> 3986
    //   3975: ldc2_w 659028635
    //   3978: l2i
    //   3979: ldc_w -1325976320
    //   3982: ixor
    //   3983: goto -> 3994
    //   3986: ldc2_w 386134020
    //   3989: l2i
    //   3990: ldc_w 1248555735
    //   3993: ixor
    //   3994: ldc2_w 1380671926
    //   3997: l2i
    //   3998: ldc_w -1332201383
    //   4001: ixor
    //   4002: ixor
    //   4003: lookupswitch default -> 4156, -1078207684 -> 4028, 1969460852 -> 3986
    //   4028: istore_3
    //   4029: iinc #6, 1
    //   4032: goto -> 2722
    //   4035: iinc #5, 1
    //   4038: goto -> 2138
    //   4041: getstatic Perryc.0 : I
    //   4044: ifle -> 4058
    //   4047: ldc2_w -358887718
    //   4050: l2i
    //   4051: ldc_w 768168398
    //   4054: ixor
    //   4055: goto -> 4066
    //   4058: ldc2_w 1601052023
    //   4061: l2i
    //   4062: ldc_w -1070330809
    //   4065: ixor
    //   4066: ldc2_w -826387662
    //   4069: l2i
    //   4070: ldc_w -1655857600
    //   4073: ixor
    //   4074: ixor
    //   4075: lookupswitch default -> 4100, -1801366938 -> 4110, 327812547 -> 4058
    //   4100: iload_3
    //   4101: ireturn
    //   4102: aconst_null
    //   4103: athrow
    //   4104: aconst_null
    //   4105: athrow
    //   4106: aconst_null
    //   4107: athrow
    //   4108: aconst_null
    //   4109: athrow
    //   4110: aconst_null
    //   4111: athrow
    //   4112: aconst_null
    //   4113: athrow
    //   4114: aconst_null
    //   4115: athrow
    //   4116: aconst_null
    //   4117: athrow
    //   4118: aconst_null
    //   4119: athrow
    //   4120: aconst_null
    //   4121: athrow
    //   4122: aconst_null
    //   4123: athrow
    //   4124: aconst_null
    //   4125: athrow
    //   4126: aconst_null
    //   4127: athrow
    //   4128: aconst_null
    //   4129: athrow
    //   4130: aconst_null
    //   4131: athrow
    //   4132: aconst_null
    //   4133: athrow
    //   4134: aconst_null
    //   4135: athrow
    //   4136: aconst_null
    //   4137: athrow
    //   4138: aconst_null
    //   4139: athrow
    //   4140: aconst_null
    //   4141: athrow
    //   4142: aconst_null
    //   4143: athrow
    //   4144: aconst_null
    //   4145: athrow
    //   4146: aconst_null
    //   4147: athrow
    //   4148: aconst_null
    //   4149: athrow
    //   4150: aconst_null
    //   4151: athrow
    //   4152: aconst_null
    //   4153: athrow
    //   4154: aconst_null
    //   4155: athrow
    //   4156: aconst_null
    //   4157: athrow
    //   4158: aconst_null
    //   4159: athrow
    //   4160: aconst_null
    //   4161: athrow
    //   4162: aconst_null
    //   4163: athrow
    //   4164: aconst_null
    //   4165: athrow
    //   4166: aconst_null
    //   4167: athrow
    //   4168: aconst_null
    //   4169: athrow
    //   4170: aconst_null
    //   4171: athrow
    //   4172: aconst_null
    //   4173: athrow
    //   4174: aconst_null
    //   4175: athrow
    //   4176: aconst_null
    //   4177: athrow
    //   4178: aconst_null
    //   4179: athrow
    //   4180: aconst_null
    //   4181: athrow
    //   4182: aconst_null
    //   4183: athrow
    //   4184: aconst_null
    //   4185: athrow
    //   4186: aconst_null
    //   4187: athrow
    //   4188: aconst_null
    //   4189: athrow
    //   4190: aconst_null
    //   4191: athrow
    //   4192: aconst_null
    //   4193: athrow
    //   4194: aconst_null
    //   4195: athrow
    //   4196: aconst_null
    //   4197: athrow
    //   4198: aconst_null
    //   4199: athrow
    //   4200: aconst_null
    //   4201: athrow
    //   4202: aconst_null
    //   4203: athrow
    //   4204: aconst_null
    //   4205: athrow
    //   4206: aconst_null
    //   4207: athrow
    //   4208: aconst_null
    //   4209: athrow
    //   4210: pop
    //   4211: goto -> 24
    //   4214: pop
    //   4215: aconst_null
    //   4216: goto -> 4210
    //   4219: dup
    //   4220: ifnull -> 4210
    //   4223: checkcast java/lang/Throwable
    //   4226: athrow
    //   4227: dup
    //   4228: ifnull -> 4214
    //   4231: checkcast java/lang/Throwable
    //   4234: athrow
    //   4235: aconst_null
    //   4236: athrow
    // Local variable table:
    //   start	length	slot	name	descriptor
    //   3650	379	7	block	Lnet/minecraft/block/Block;
    //   2722	1313	6	z	I
    //   2138	1903	5	x	I
    //   24	4078	0	offset	D
    //   1625	2477	2	bb	Lnet/minecraft/util/math/AxisAlignedBB;
    //   1693	2409	3	onLiquid	Z
    //   1878	2224	4	y	I
    // Exception table:
    //   from	to	target	type
    //   8	20	4219	java/lang/ClassCastException
    //   484	490	490	finally
    //   484	490	490	finally
    //   484	490	490	finally
    //   484	490	3	finally
    //   484	490	490	java/lang/ArithmeticException
    //   735	742	742	finally
    //   735	742	735	finally
    //   735	742	735	java/lang/StringIndexOutOfBoundsException
    //   736	742	742	finally
    //   736	742	735	java/lang/NegativeArraySizeException
    //   807	814	814	finally
    //   807	814	807	java/lang/NumberFormatException
    //   808	814	3	finally
    //   808	814	814	finally
    //   808	814	807	finally
    //   919	926	926	finally
    //   919	926	919	finally
    //   919	926	926	java/util/NoSuchElementException
    //   920	926	919	java/util/NoSuchElementException
    //   920	926	926	finally
    //   1080	1086	1086	finally
    //   1080	1086	1086	java/lang/EnumConstantNotPresentException
    //   1080	1086	1086	finally
    //   1080	1086	3	finally
    //   1080	1086	1086	java/lang/ArithmeticException
    //   1284	1290	1290	finally
    //   1284	1290	3	finally
    //   1284	1290	1290	finally
    //   1284	1290	1290	finally
    //   1284	1290	3	java/util/NoSuchElementException
    //   1395	1402	1402	finally
    //   1395	1402	1402	java/lang/IndexOutOfBoundsException
    //   1396	1402	3	java/lang/ClassCastException
    //   1396	1402	1402	java/lang/NegativeArraySizeException
    //   1396	1402	1395	finally
    //   1555	1562	1562	finally
    //   1555	1562	1555	java/lang/NullPointerException
    //   1555	1562	1562	java/lang/NumberFormatException
    //   1555	1562	3	java/lang/NegativeArraySizeException
    //   1556	1562	1555	java/lang/NullPointerException
    //   2067	2074	2074	finally
    //   2067	2074	2074	finally
    //   2067	2074	2067	finally
    //   2067	2074	3	finally
    //   2068	2074	3	java/lang/ArrayIndexOutOfBoundsException
    //   2403	2410	2410	finally
    //   2404	2410	2410	finally
    //   2404	2410	2410	java/lang/AssertionError
    //   2404	2410	2403	finally
    //   2404	2410	3	java/lang/UnsupportedOperationException
    //   2651	2658	2658	finally
    //   2651	2658	2651	java/lang/ArithmeticException
    //   2652	2658	3	java/lang/StringIndexOutOfBoundsException
    //   2652	2658	3	java/lang/EnumConstantNotPresentException
    //   2652	2658	2651	finally
    //   2987	2994	2994	finally
    //   2987	2994	2987	java/lang/IndexOutOfBoundsException
    //   2987	2994	2994	java/lang/NullPointerException
    //   2988	2994	2994	finally
    //   2988	2994	3	java/lang/UnsupportedOperationException
    //   3435	3442	3442	finally
    //   3435	3442	3	finally
    //   3436	3442	3442	finally
    //   3436	3442	3	java/lang/IllegalStateException
    //   3436	3442	3435	finally
    //   3508	3514	3514	finally
    //   3508	3514	3	java/util/NoSuchElementException
    //   3508	3514	3	finally
    //   3508	3514	3514	java/lang/ArrayIndexOutOfBoundsException
    //   3508	3514	3514	java/lang/UnsupportedOperationException
    //   3579	3588	3588	finally
    //   3579	3588	3	java/lang/UnsupportedOperationException
    //   3580	3588	3	finally
    //   3580	3588	3579	java/util/NoSuchElementException
    //   3580	3588	3	finally
    //   4219	4227	4219	finally
    //   4235	4237	3	finally
  }
  
  public static void attackEntity(Entity entity, boolean packet, boolean swingArm) {
    if (Perryc.0 <= 0) {
      null;
    } else {
      if (null != null)
        throw (Throwable)null; 
      null;
    } 
    if (null != null)
      throw (Throwable)null; 
    null;
  }
  
  public static boolean isAboveLiquid(Entity entity) {
    if (Perryc.0 <= 0) {
      null;
    } else {
      if (null != null)
        throw (Throwable)null; 
      null;
    } 
    if (null != null)
      throw (Throwable)null; 
    null;
  }
  
  public static boolean canEntityFeetBeSeen(Entity entityIn) {
    // Byte code:
    //   0: goto -> 8
    //   3: dup
    //   4: ifnull -> 1691
    //   7: athrow
    //   8: aconst_null
    //   9: getstatic Perryc.1 : I
    //   12: ifgt -> 1683
    //   15: pop
    //   16: aconst_null
    //   17: goto -> 1675
    //   20: nop
    //   21: nop
    //   22: nop
    //   23: athrow
    //   24: getstatic Perryc.c : I
    //   27: iflt -> 41
    //   30: ldc2_w 1278840829
    //   33: l2i
    //   34: ldc_w 1509527932
    //   37: ixor
    //   38: goto -> 49
    //   41: ldc2_w -1347213760
    //   44: l2i
    //   45: ldc_w -582515101
    //   48: ixor
    //   49: ldc2_w -1287244181
    //   52: l2i
    //   53: ldc_w 663760310
    //   56: ixor
    //   57: ixor
    //   58: lookupswitch default -> 1662, -2129263268 -> 41, -433931266 -> 84
    //   84: getstatic bigname/zprestige/webhack/util/WurstPlusThree/WurstplusThreeEntityUtil.mc : Lnet/minecraft/client/Minecraft;
    //   87: getstatic Perryc.0 : I
    //   90: ifle -> 104
    //   93: ldc2_w -889705606
    //   96: l2i
    //   97: ldc_w 332683661
    //   100: ixor
    //   101: goto -> 112
    //   104: ldc2_w -1213987328
    //   107: l2i
    //   108: ldc_w -32957876
    //   111: ixor
    //   112: ldc2_w 1972103653
    //   115: l2i
    //   116: ldc_w 1586463608
    //   119: ixor
    //   120: ixor
    //   121: lookupswitch default -> 148, -900370868 -> 104, -232253334 -> 1636
    //   148: getfield field_71441_e : Lnet/minecraft/client/multiplayer/WorldClient;
    //   151: new net/minecraft/util/math/Vec3d
    //   154: dup
    //   155: getstatic Perryc.0 : I
    //   158: ifle -> 172
    //   161: ldc2_w 1563131735
    //   164: l2i
    //   165: ldc_w 1430511097
    //   168: ixor
    //   169: goto -> 180
    //   172: ldc2_w 1247998432
    //   175: l2i
    //   176: ldc_w 592300499
    //   179: ixor
    //   180: ldc2_w -49313954
    //   183: l2i
    //   184: ldc_w -776202645
    //   187: ixor
    //   188: ixor
    //   189: lookupswitch default -> 1638, 618345371 -> 172, 1167894790 -> 216
    //   216: getstatic bigname/zprestige/webhack/util/WurstPlusThree/WurstplusThreeEntityUtil.mc : Lnet/minecraft/client/Minecraft;
    //   219: getstatic Perryc.1 : I
    //   222: ifeq -> 236
    //   225: ldc2_w 98093981
    //   228: l2i
    //   229: ldc_w 1719639565
    //   232: ixor
    //   233: goto -> 244
    //   236: ldc2_w -674231542
    //   239: l2i
    //   240: ldc_w -1262285489
    //   243: ixor
    //   244: ldc2_w -115539681
    //   247: l2i
    //   248: ldc_w -438234969
    //   251: ixor
    //   252: ixor
    //   253: lookupswitch default -> 1628, 2136687656 -> 236, 2146375677 -> 280
    //   280: getfield field_71439_g : Lnet/minecraft/client/entity/EntityPlayerSP;
    //   283: getstatic Perryc.0 : I
    //   286: ifle -> 300
    //   289: ldc2_w -1328050310
    //   292: l2i
    //   293: ldc_w 985123929
    //   296: ixor
    //   297: goto -> 308
    //   300: ldc2_w 293686282
    //   303: l2i
    //   304: ldc_w 538650231
    //   307: ixor
    //   308: ldc2_w 37742136
    //   311: l2i
    //   312: ldc_w -1622328086
    //   315: ixor
    //   316: ixor
    //   317: lookupswitch default -> 344, 387095025 -> 1634, 1392238923 -> 300
    //   344: getfield field_70165_t : D
    //   347: getstatic Perryc.0 : I
    //   350: ifle -> 364
    //   353: ldc2_w 1874981423
    //   356: l2i
    //   357: ldc_w -1832324157
    //   360: ixor
    //   361: goto -> 372
    //   364: ldc2_w -1161562756
    //   367: l2i
    //   368: ldc_w -558124806
    //   371: ixor
    //   372: ldc2_w -2069919994
    //   375: l2i
    //   376: ldc_w 560819018
    //   379: ixor
    //   380: ixor
    //   381: lookupswitch default -> 408, -1652852211 -> 364, 1492905376 -> 1620
    //   408: getstatic bigname/zprestige/webhack/util/WurstPlusThree/WurstplusThreeEntityUtil.mc : Lnet/minecraft/client/Minecraft;
    //   411: getstatic Perryc.0 : I
    //   414: ifle -> 428
    //   417: ldc2_w -977433021
    //   420: l2i
    //   421: ldc_w -1218137708
    //   424: ixor
    //   425: goto -> 436
    //   428: ldc2_w 1236449604
    //   431: l2i
    //   432: ldc_w -1638933010
    //   435: ixor
    //   436: ldc2_w 1300204283
    //   439: l2i
    //   440: ldc_w 882207335
    //   443: ixor
    //   444: ixor
    //   445: lookupswitch default -> 1642, -1374190538 -> 472, 187948875 -> 428
    //   472: getfield field_71439_g : Lnet/minecraft/client/entity/EntityPlayerSP;
    //   475: getstatic Perryc.c : I
    //   478: iflt -> 492
    //   481: ldc2_w 923115587
    //   484: l2i
    //   485: ldc_w 709617942
    //   488: ixor
    //   489: goto -> 500
    //   492: ldc2_w 1823477948
    //   495: l2i
    //   496: ldc_w 812740293
    //   499: ixor
    //   500: ldc2_w -132709804
    //   503: l2i
    //   504: ldc_w 1908038742
    //   507: ixor
    //   508: ixor
    //   509: lookupswitch default -> 1646, -1797056681 -> 492, -714334085 -> 536
    //   536: getfield field_70165_t : D
    //   539: getstatic Perryc.0 : I
    //   542: ifle -> 556
    //   545: ldc2_w 1683274574
    //   548: l2i
    //   549: ldc_w 926575563
    //   552: ixor
    //   553: goto -> 564
    //   556: ldc2_w -1652578944
    //   559: l2i
    //   560: ldc_w -142747365
    //   563: ixor
    //   564: ldc2_w 1192223545
    //   567: l2i
    //   568: ldc_w 2015888300
    //   571: ixor
    //   572: ixor
    //   573: lookupswitch default -> 1626, 1428528142 -> 600, 1816735760 -> 556
    //   600: getstatic bigname/zprestige/webhack/util/WurstPlusThree/WurstplusThreeEntityUtil.mc : Lnet/minecraft/client/Minecraft;
    //   603: getstatic Perryc.1 : I
    //   606: ifeq -> 620
    //   609: ldc2_w -402896037
    //   612: l2i
    //   613: ldc_w -419913863
    //   616: ixor
    //   617: goto -> 628
    //   620: ldc2_w -1460780914
    //   623: l2i
    //   624: ldc_w 682103776
    //   627: ixor
    //   628: ldc2_w 1034824873
    //   631: l2i
    //   632: ldc_w 511220530
    //   635: ixor
    //   636: ixor
    //   637: lookupswitch default -> 664, -413740448 -> 620, 584213433 -> 1660
    //   664: getfield field_71439_g : Lnet/minecraft/client/entity/EntityPlayerSP;
    //   667: getstatic Perryc.1 : I
    //   670: ifeq -> 684
    //   673: ldc2_w 1896498291
    //   676: l2i
    //   677: ldc_w -941034393
    //   680: ixor
    //   681: goto -> 692
    //   684: ldc2_w -2012787476
    //   687: l2i
    //   688: ldc_w -1809671643
    //   691: ixor
    //   692: ldc2_w 814488884
    //   695: l2i
    //   696: ldc_w 322397505
    //   699: ixor
    //   700: ixor
    //   701: lookupswitch default -> 728, -1789278111 -> 1656, -1340450265 -> 684
    //   728: goto -> 732
    //   731: athrow
    //   732: invokevirtual func_70047_e : ()F
    //   735: goto -> 739
    //   738: athrow
    //   739: f2d
    //   740: dadd
    //   741: getstatic Perryc.c : I
    //   744: iflt -> 758
    //   747: ldc2_w -237613061
    //   750: l2i
    //   751: ldc_w -1346743477
    //   754: ixor
    //   755: goto -> 766
    //   758: ldc2_w -1119096192
    //   761: l2i
    //   762: ldc_w -741240178
    //   765: ixor
    //   766: ldc2_w 900340784
    //   769: l2i
    //   770: ldc_w 1230056764
    //   773: ixor
    //   774: ixor
    //   775: lookupswitch default -> 1648, 308367618 -> 800, 580332988 -> 758
    //   800: getstatic bigname/zprestige/webhack/util/WurstPlusThree/WurstplusThreeEntityUtil.mc : Lnet/minecraft/client/Minecraft;
    //   803: getstatic Perryc.0 : I
    //   806: ifle -> 820
    //   809: ldc2_w -679608628
    //   812: l2i
    //   813: ldc_w -1058345059
    //   816: ixor
    //   817: goto -> 828
    //   820: ldc2_w 1856840297
    //   823: l2i
    //   824: ldc_w -3761426
    //   827: ixor
    //   828: ldc2_w 1139732465
    //   831: l2i
    //   832: ldc_w 1469617415
    //   835: ixor
    //   836: ixor
    //   837: lookupswitch default -> 864, -833783046 -> 820, 65104807 -> 1652
    //   864: getfield field_71439_g : Lnet/minecraft/client/entity/EntityPlayerSP;
    //   867: getstatic Perryc.1 : I
    //   870: ifeq -> 884
    //   873: ldc2_w 967713737
    //   876: l2i
    //   877: ldc_w -769829461
    //   880: ixor
    //   881: goto -> 892
    //   884: ldc2_w -836630040
    //   887: l2i
    //   888: ldc_w 216313326
    //   891: ixor
    //   892: ldc2_w -801283320
    //   895: l2i
    //   896: ldc_w 748286179
    //   899: ixor
    //   900: ixor
    //   901: lookupswitch default -> 1630, 387442057 -> 884, 1046624237 -> 928
    //   928: getfield field_70161_v : D
    //   931: getstatic Perryc.1 : I
    //   934: ifeq -> 948
    //   937: ldc2_w 1696827280
    //   940: l2i
    //   941: ldc_w -871230205
    //   944: ixor
    //   945: goto -> 956
    //   948: ldc2_w 1779835995
    //   951: l2i
    //   952: ldc_w 1096863655
    //   955: ixor
    //   956: ldc2_w -1040234210
    //   959: l2i
    //   960: ldc_w -1635929941
    //   963: ixor
    //   964: ixor
    //   965: lookupswitch default -> 1632, -156013786 -> 948, 1962152521 -> 992
    //   992: goto -> 996
    //   995: athrow
    //   996: invokespecial <init> : (DDD)V
    //   999: goto -> 1003
    //   1002: athrow
    //   1003: new net/minecraft/util/math/Vec3d
    //   1006: dup
    //   1007: getstatic Perryc.c : I
    //   1010: iflt -> 1024
    //   1013: ldc2_w 1637288196
    //   1016: l2i
    //   1017: ldc_w 2031165295
    //   1020: ixor
    //   1021: goto -> 1032
    //   1024: ldc2_w 1326032677
    //   1027: l2i
    //   1028: ldc_w 1155425720
    //   1031: ixor
    //   1032: ldc2_w 1519721195
    //   1035: l2i
    //   1036: ldc_w -2110221065
    //   1039: ixor
    //   1040: ixor
    //   1041: lookupswitch default -> 1650, -1070884745 -> 1024, -746959743 -> 1068
    //   1068: aload_0
    //   1069: getstatic Perryc.c : I
    //   1072: iflt -> 1086
    //   1075: ldc2_w -921055430
    //   1078: l2i
    //   1079: ldc_w 1838465566
    //   1082: ixor
    //   1083: goto -> 1094
    //   1086: ldc2_w -549922462
    //   1089: l2i
    //   1090: ldc_w 949860475
    //   1093: ixor
    //   1094: ldc2_w 1749815071
    //   1097: l2i
    //   1098: ldc_w -286365049
    //   1101: ixor
    //   1102: ixor
    //   1103: lookupswitch default -> 1644, 573532348 -> 1086, 1627849857 -> 1128
    //   1128: getfield field_70165_t : D
    //   1131: getstatic Perryc.0 : I
    //   1134: ifle -> 1148
    //   1137: ldc2_w -816997006
    //   1140: l2i
    //   1141: ldc_w 1268970333
    //   1144: ixor
    //   1145: goto -> 1156
    //   1148: ldc2_w -1338735300
    //   1151: l2i
    //   1152: ldc_w -1547819406
    //   1155: ixor
    //   1156: ldc2_w -1585187556
    //   1159: l2i
    //   1160: ldc_w 1400583788
    //   1163: ixor
    //   1164: ixor
    //   1165: lookupswitch default -> 1192, 468813221 -> 1148, 1981263199 -> 1654
    //   1192: aload_0
    //   1193: getstatic Perryc.1 : I
    //   1196: ifeq -> 1210
    //   1199: ldc2_w -1814080298
    //   1202: l2i
    //   1203: ldc_w 511068150
    //   1206: ixor
    //   1207: goto -> 1218
    //   1210: ldc2_w -52085152
    //   1213: l2i
    //   1214: ldc_w -385742369
    //   1217: ixor
    //   1218: ldc2_w -1721079983
    //   1221: l2i
    //   1222: ldc_w -167518713
    //   1225: ixor
    //   1226: ixor
    //   1227: lookupswitch default -> 1252, -490689930 -> 1640, 192480427 -> 1210
    //   1252: getfield field_70163_u : D
    //   1255: getstatic Perryc.1 : I
    //   1258: ifeq -> 1272
    //   1261: ldc2_w 230381546
    //   1264: l2i
    //   1265: ldc_w -984580079
    //   1268: ixor
    //   1269: goto -> 1280
    //   1272: ldc2_w 1553350035
    //   1275: l2i
    //   1276: ldc_w 619229938
    //   1279: ixor
    //   1280: ldc2_w 1316407180
    //   1283: l2i
    //   1284: ldc_w -803462827
    //   1287: ixor
    //   1288: ixor
    //   1289: lookupswitch default -> 1624, -434869832 -> 1316, 1451307298 -> 1272
    //   1316: aload_0
    //   1317: getstatic Perryc.1 : I
    //   1320: ifeq -> 1334
    //   1323: ldc2_w 1494750523
    //   1326: l2i
    //   1327: ldc_w -863174877
    //   1330: ixor
    //   1331: goto -> 1342
    //   1334: ldc2_w 1128468550
    //   1337: l2i
    //   1338: ldc_w -2144203793
    //   1341: ixor
    //   1342: ldc2_w 1683503738
    //   1345: l2i
    //   1346: ldc_w 1935081847
    //   1349: ixor
    //   1350: ixor
    //   1351: lookupswitch default -> 1376, -2103717611 -> 1664, 315378496 -> 1334
    //   1376: getfield field_70161_v : D
    //   1379: getstatic Perryc.1 : I
    //   1382: ifeq -> 1396
    //   1385: ldc2_w -522247753
    //   1388: l2i
    //   1389: ldc_w 2067602351
    //   1392: ixor
    //   1393: goto -> 1404
    //   1396: ldc2_w 1905589888
    //   1399: l2i
    //   1400: ldc_w 2135241483
    //   1403: ixor
    //   1404: ldc2_w 2087002843
    //   1407: l2i
    //   1408: ldc_w 1945084485
    //   1411: ixor
    //   1412: ixor
    //   1413: lookupswitch default -> 1440, -1805075834 -> 1658, 287265567 -> 1396
    //   1440: goto -> 1444
    //   1443: athrow
    //   1444: invokespecial <init> : (DDD)V
    //   1447: goto -> 1451
    //   1450: athrow
    //   1451: ldc2_w 1643746916
    //   1454: l2i
    //   1455: ldc_w 1643746916
    //   1458: ixor
    //   1459: ldc2_w -1343078503
    //   1462: l2i
    //   1463: ldc_w -1343078504
    //   1466: ixor
    //   1467: ldc2_w -1875361840
    //   1470: l2i
    //   1471: ldc_w -1875361840
    //   1474: ixor
    //   1475: getstatic Perryc.1 : I
    //   1478: ifeq -> 1492
    //   1481: ldc2_w 1912208722
    //   1484: l2i
    //   1485: ldc_w 1523887821
    //   1488: ixor
    //   1489: goto -> 1500
    //   1492: ldc2_w 330085052
    //   1495: l2i
    //   1496: ldc_w 697209709
    //   1499: ixor
    //   1500: ldc2_w 137009897
    //   1503: l2i
    //   1504: ldc_w -935519918
    //   1507: ixor
    //   1508: ixor
    //   1509: lookupswitch default -> 1536, -348467164 -> 1622, 2110321814 -> 1492
    //   1536: goto -> 1540
    //   1539: athrow
    //   1540: invokevirtual func_147447_a : (Lnet/minecraft/util/math/Vec3d;Lnet/minecraft/util/math/Vec3d;ZZZ)Lnet/minecraft/util/math/RayTraceResult;
    //   1543: goto -> 1547
    //   1546: athrow
    //   1547: ifnonnull -> 1561
    //   1550: ldc2_w -52224610
    //   1553: l2i
    //   1554: ldc_w -701542117
    //   1557: ixor
    //   1558: goto -> 1569
    //   1561: ldc2_w -1077466470
    //   1564: l2i
    //   1565: ldc_w -1794415076
    //   1568: ixor
    //   1569: ldc2_w 1906259863
    //   1572: l2i
    //   1573: ldc_w 275558759
    //   1576: ixor
    //   1577: ixor
    //   1578: tableswitch default -> 1550, 1262471797 -> 1600, 1262471798 -> 1611
    //   1600: ldc2_w 1542143273
    //   1603: l2i
    //   1604: ldc_w 1542143272
    //   1607: ixor
    //   1608: goto -> 1619
    //   1611: ldc2_w 1535926711
    //   1614: l2i
    //   1615: ldc_w 1535926711
    //   1618: ixor
    //   1619: ireturn
    //   1620: aconst_null
    //   1621: athrow
    //   1622: aconst_null
    //   1623: athrow
    //   1624: aconst_null
    //   1625: athrow
    //   1626: aconst_null
    //   1627: athrow
    //   1628: aconst_null
    //   1629: athrow
    //   1630: aconst_null
    //   1631: athrow
    //   1632: aconst_null
    //   1633: athrow
    //   1634: aconst_null
    //   1635: athrow
    //   1636: aconst_null
    //   1637: athrow
    //   1638: aconst_null
    //   1639: athrow
    //   1640: aconst_null
    //   1641: athrow
    //   1642: aconst_null
    //   1643: athrow
    //   1644: aconst_null
    //   1645: athrow
    //   1646: aconst_null
    //   1647: athrow
    //   1648: aconst_null
    //   1649: athrow
    //   1650: aconst_null
    //   1651: athrow
    //   1652: aconst_null
    //   1653: athrow
    //   1654: aconst_null
    //   1655: athrow
    //   1656: aconst_null
    //   1657: athrow
    //   1658: aconst_null
    //   1659: athrow
    //   1660: aconst_null
    //   1661: athrow
    //   1662: aconst_null
    //   1663: athrow
    //   1664: aconst_null
    //   1665: athrow
    //   1666: pop
    //   1667: goto -> 24
    //   1670: pop
    //   1671: aconst_null
    //   1672: goto -> 1666
    //   1675: dup
    //   1676: ifnull -> 1666
    //   1679: checkcast java/lang/Throwable
    //   1682: athrow
    //   1683: dup
    //   1684: ifnull -> 1670
    //   1687: checkcast java/lang/Throwable
    //   1690: athrow
    //   1691: aconst_null
    //   1692: athrow
    // Local variable table:
    //   start	length	slot	name	descriptor
    //   24	1596	0	entityIn	Lnet/minecraft/entity/Entity;
    // Exception table:
    //   from	to	target	type
    //   8	20	1675	java/lang/RuntimeException
    //   732	738	738	finally
    //   732	738	3	finally
    //   732	738	738	java/lang/IllegalArgumentException
    //   732	738	3	java/lang/NegativeArraySizeException
    //   732	738	3	finally
    //   995	1002	1002	finally
    //   995	1002	3	finally
    //   996	1002	995	java/lang/RuntimeException
    //   996	1002	3	finally
    //   996	1002	3	java/util/NoSuchElementException
    //   1443	1450	1450	finally
    //   1443	1450	3	finally
    //   1443	1450	3	finally
    //   1444	1450	1443	finally
    //   1444	1450	1450	java/lang/AssertionError
    //   1539	1546	1546	finally
    //   1539	1546	3	java/util/ConcurrentModificationException
    //   1539	1546	1539	java/lang/ArrayIndexOutOfBoundsException
    //   1540	1546	1539	finally
    //   1540	1546	1546	finally
    //   1675	1683	1675	java/lang/NullPointerException
    //   1691	1693	3	java/lang/ArithmeticException
  }
  
  public static boolean isBothHole(BlockPos paramBlockPos) {
    return Perry1.6r(null, (int)-703694589L ^ 0xF3586097, paramBlockPos);
  }
  
  public static boolean isAboveBlock(Entity paramEntity, BlockPos paramBlockPos) {
    return Perry1.2k(null, (int)-674329825L ^ 0xDE56E3D5, paramEntity, paramBlockPos);
  }
  
  public static boolean stopSneaking(boolean isSneaking) {
    if (Perryc.0 <= 0) {
      null;
    } else {
      if (null != null)
        throw (Throwable)null; 
      null;
    } 
    if (null != null)
      throw (Throwable)null; 
    null;
  }
  
  static {
    throw SYNTHETIC_LOCAL_VARIABLE_0;
  }
  
  public static boolean isSafe(Entity paramEntity, int paramInt, boolean paramBoolean) {
    return Perry1.t(null, (int)-1916595974L ^ 0xDA55425B, paramEntity, paramInt, paramBoolean);
  }
  
  public static boolean isObbyHole(BlockPos paramBlockPos) {
    return Perry1.6s(null, (int)1302660522L ^ 0x70FEA0ED, paramBlockPos);
  }
  
  public static boolean isntValid(Entity paramEntity, double paramDouble) {
    return Perry1.14(null, (int)2029576613L ^ 0x135C1626, paramEntity, paramDouble);
  }
  
  public static Vec3d interpolateEntity(Entity entity, float time) {
    if (Perryc.c < 0) {
      null;
    } else {
      if (null != null)
        throw (Throwable)null; 
      null;
    } 
    if (null != null)
      throw (Throwable)null; 
    null;
  }
  
  public static boolean holding32k(EntityPlayer paramEntityPlayer) {
    return Perry1.0e(null, (int)1132203351L ^ 0x7DEDB18A, paramEntityPlayer);
  }
  
  public static boolean checkCollide() {
    return Perry1.4v(null, (int)625128661L ^ 0x18A14166);
  }
  
  public static float getHealth(Entity paramEntity) {
    return Perry1.6d(null, (int)-775117855L ^ 0xEF10A80A, paramEntity);
  }
  
  public static boolean isInHole(Entity entity) {
    if (Perryc.1 <= 0) {
      null;
    } else {
      if (null != null)
        throw (Throwable)null; 
      null;
    } 
    if (null != null)
      throw (Throwable)null; 
    null;
  }
  
  public static double predictPos(double motion, double threshold) {
    if (Perryc.c < 0) {
      null;
    } else {
      if (null != null)
        throw (Throwable)null; 
      null;
    } 
    if (null != null)
      throw (Throwable)null; 
    null;
  }
  
  public static Vec3d getInterpolatedPos(Entity entity, float partialTicks) {
    if (Perryc.c < 0) {
      null;
    } else {
      if (null != null)
        throw (Throwable)null; 
      null;
    } 
    if (null != null)
      throw (Throwable)null; 
    null;
  }
}


/* Location:              C:\Users\alex\Desktop\webhack\WebHack-0.8-obf_sussy_1.jar!\bigname\zprestige\webhac\\util\WurstPlusThree\WurstplusThreeEntityUtil.class
 * Java compiler version: 8 (52.0)
 * JD-Core Version:       1.1.3
 */