package bigname.zprestige.webhack.util.WurstPlusThree;

import Perryc;
import net.minecraft.util.math.BlockPos;

public class WurstplusThreeCrystalPos {
  public Double damage;
  
  public BlockPos pos;
  
  public BlockPos getPos() {
    if (Perryc.1 <= 0) {
      null;
    } else {
      if (null != null)
        throw (Throwable)null; 
      null;
    } 
    if (null != null)
      throw (Throwable)null; 
    null;
  }
  
  static {
    throw SYNTHETIC_LOCAL_VARIABLE_0;
  }
  
  public WurstplusThreeCrystalPos(BlockPos pos, Double damage) {
    // Byte code:
    //   0: getstatic Perryc.c : I
    //   3: iflt -> 16
    //   6: ldc2_w -703985337
    //   9: l2i
    //   10: ldc 1484740197
    //   12: ixor
    //   13: goto -> 23
    //   16: ldc2_w -130164513
    //   19: l2i
    //   20: ldc -540296916
    //   22: ixor
    //   23: ldc2_w -1887753562
    //   26: l2i
    //   27: ldc 1253024361
    //   29: ixor
    //   30: ixor
    //   31: lookupswitch default -> 488, -501028548 -> 56, 1268897773 -> 16
    //   56: aload_0
    //   57: getstatic Perryc.0 : I
    //   60: ifle -> 73
    //   63: ldc2_w 136371119
    //   66: l2i
    //   67: ldc 19514066
    //   69: ixor
    //   70: goto -> 80
    //   73: ldc2_w 1601947386
    //   76: l2i
    //   77: ldc 1239990625
    //   79: ixor
    //   80: ldc2_w -560314901
    //   83: l2i
    //   84: ldc -651125958
    //   86: ixor
    //   87: ixor
    //   88: lookupswitch default -> 116, 245614508 -> 484, 2105094945 -> 73
    //   116: invokespecial <init> : ()V
    //   119: getstatic Perryc.c : I
    //   122: iflt -> 135
    //   125: ldc2_w 265614632
    //   128: l2i
    //   129: ldc -2029936563
    //   131: ixor
    //   132: goto -> 142
    //   135: ldc2_w -1948038150
    //   138: l2i
    //   139: ldc -2130720867
    //   141: ixor
    //   142: ldc2_w -1292383021
    //   145: l2i
    //   146: ldc 218248915
    //   148: ixor
    //   149: ixor
    //   150: lookupswitch default -> 486, -1259768217 -> 176, 924888933 -> 135
    //   176: aload_0
    //   177: getstatic Perryc.1 : I
    //   180: ifeq -> 193
    //   183: ldc2_w 611116344
    //   186: l2i
    //   187: ldc -1185958666
    //   189: ixor
    //   190: goto -> 200
    //   193: ldc2_w -626204300
    //   196: l2i
    //   197: ldc 1796580357
    //   199: ixor
    //   200: ldc2_w -742498782
    //   203: l2i
    //   204: ldc -605479203
    //   206: ixor
    //   207: ixor
    //   208: lookupswitch default -> 236, -1787555535 -> 490, 1680185765 -> 193
    //   236: aload_1
    //   237: getstatic Perryc.1 : I
    //   240: ifeq -> 253
    //   243: ldc2_w 1814677283
    //   246: l2i
    //   247: ldc -670964900
    //   249: ixor
    //   250: goto -> 260
    //   253: ldc2_w 62026490
    //   256: l2i
    //   257: ldc 867882445
    //   259: ixor
    //   260: ldc2_w -462505895
    //   263: l2i
    //   264: ldc -1048503632
    //   266: ixor
    //   267: ixor
    //   268: lookupswitch default -> 492, -1849194858 -> 253, 367461854 -> 296
    //   296: putfield pos : Lnet/minecraft/util/math/BlockPos;
    //   299: getstatic Perryc.c : I
    //   302: iflt -> 315
    //   305: ldc2_w -1533335987
    //   308: l2i
    //   309: ldc 894549659
    //   311: ixor
    //   312: goto -> 322
    //   315: ldc2_w -1197717302
    //   318: l2i
    //   319: ldc 329051973
    //   321: ixor
    //   322: ldc2_w 348140757
    //   325: l2i
    //   326: ldc 380483267
    //   328: ixor
    //   329: ixor
    //   330: lookupswitch default -> 480, -1817765184 -> 315, -1452464743 -> 356
    //   356: aload_0
    //   357: getstatic Perryc.c : I
    //   360: iflt -> 373
    //   363: ldc2_w 1678564901
    //   366: l2i
    //   367: ldc 2100024633
    //   369: ixor
    //   370: goto -> 380
    //   373: ldc2_w 621513019
    //   376: l2i
    //   377: ldc -2007429754
    //   379: ixor
    //   380: ldc2_w 222635427
    //   383: l2i
    //   384: ldc -819085412
    //   386: ixor
    //   387: ixor
    //   388: lookupswitch default -> 416, -615542493 -> 482, 1162748081 -> 373
    //   416: aload_2
    //   417: getstatic Perryc.1 : I
    //   420: ifeq -> 433
    //   423: ldc2_w -1226568510
    //   426: l2i
    //   427: ldc 1549885120
    //   429: ixor
    //   430: goto -> 440
    //   433: ldc2_w 767295181
    //   436: l2i
    //   437: ldc 223558890
    //   439: ixor
    //   440: ldc2_w 1054360030
    //   443: l2i
    //   444: ldc -849434595
    //   446: ixor
    //   447: ixor
    //   448: lookupswitch default -> 494, -747754524 -> 476, 419675073 -> 433
    //   476: putfield damage : Ljava/lang/Double;
    //   479: return
    //   480: aconst_null
    //   481: athrow
    //   482: aconst_null
    //   483: athrow
    //   484: aconst_null
    //   485: athrow
    //   486: aconst_null
    //   487: athrow
    //   488: aconst_null
    //   489: athrow
    //   490: aconst_null
    //   491: athrow
    //   492: aconst_null
    //   493: athrow
    //   494: aconst_null
    //   495: athrow
    // Local variable table:
    //   start	length	slot	name	descriptor
    //   0	480	0	this	Lbigname/zprestige/webhack/util/WurstPlusThree/WurstplusThreeCrystalPos;
    //   0	480	1	pos	Lnet/minecraft/util/math/BlockPos;
    //   0	480	2	damage	Ljava/lang/Double;
  }
  
  public Double getDamage() {
    if (Perryc.1 <= 0) {
      null;
    } else {
      if (null != null)
        throw (Throwable)null; 
      null;
    } 
    if (null != null)
      throw (Throwable)null; 
    null;
  }
}


/* Location:              C:\Users\alex\Desktop\webhack\WebHack-0.8-obf_sussy_1.jar!\bigname\zprestige\webhac\\util\WurstPlusThree\WurstplusThreeCrystalPos.class
 * Java compiler version: 8 (52.0)
 * JD-Core Version:       1.1.3
 */