package bigname.zprestige.webhack.features.modules.Player;

import Perry1;
import bigname.zprestige.webhack.features.modules.Module;

public class FastExp extends Module {
  public void onUpdate() {
    Perry1.3D(this, (int)1595699301L ^ 0x39CA614A);
  }
  
  public FastExp() {
    // Byte code:
    //   0: getstatic Perryc.c : I
    //   3: iflt -> 16
    //   6: ldc2_w 1896811883
    //   9: l2i
    //   10: ldc 264172429
    //   12: ixor
    //   13: goto -> 23
    //   16: ldc2_w -295198332
    //   19: l2i
    //   20: ldc -1488008047
    //   22: ixor
    //   23: ldc2_w -1583119235
    //   26: l2i
    //   27: ldc -692747429
    //   29: ixor
    //   30: ixor
    //   31: lookupswitch default -> 328, 162003392 -> 16, 1044343347 -> 56
    //   56: aload_0
    //   57: ldc '㫇㌒㪠㶣衣푅๩'
    //   59: getstatic Perryc.0 : I
    //   62: ifle -> 75
    //   65: ldc2_w -69483232
    //   68: l2i
    //   69: ldc 502507376
    //   71: ixor
    //   72: goto -> 82
    //   75: ldc2_w 737207395
    //   78: l2i
    //   79: ldc 508015910
    //   81: ixor
    //   82: ldc2_w 1866480362
    //   85: l2i
    //   86: ldc 1432115171
    //   88: ixor
    //   89: ixor
    //   90: lookupswitch default -> 324, -600567975 -> 75, 262880332 -> 116
    //   116: invokestatic 0 : (Ljava/lang/String;)Ljava/lang/String;
    //   119: ldc '㫠㌛㪲㷷血표๪䝠蹦풽舿'
    //   121: getstatic Perryc.0 : I
    //   124: ifle -> 137
    //   127: ldc2_w 1981025050
    //   130: l2i
    //   131: ldc -190622130
    //   133: ixor
    //   134: goto -> 144
    //   137: ldc2_w 1971130742
    //   140: l2i
    //   141: ldc 364852622
    //   143: ixor
    //   144: ldc2_w -2134123998
    //   147: l2i
    //   148: ldc -1056595710
    //   150: ixor
    //   151: ixor
    //   152: lookupswitch default -> 332, -1015470476 -> 137, 554459096 -> 180
    //   180: invokestatic 0 : (Ljava/lang/String;)Ljava/lang/String;
    //   183: getstatic Perryc.1 : I
    //   186: ifeq -> 199
    //   189: ldc2_w -74137213
    //   192: l2i
    //   193: ldc 1745811576
    //   195: ixor
    //   196: goto -> 206
    //   199: ldc2_w 1931339202
    //   202: l2i
    //   203: ldc -1444592990
    //   205: ixor
    //   206: ldc2_w 1209480349
    //   209: l2i
    //   210: ldc -1499156012
    //   212: ixor
    //   213: ixor
    //   214: lookupswitch default -> 240, -119911013 -> 199, 2099887282 -> 330
    //   240: getstatic bigname/zprestige/webhack/features/modules/Module$Category.PLAYER : Lbigname/zprestige/webhack/features/modules/Module$Category;
    //   243: ldc2_w -1634982721
    //   246: l2i
    //   247: ldc -1634982722
    //   249: ixor
    //   250: ldc2_w 29050216
    //   253: l2i
    //   254: ldc 29050216
    //   256: ixor
    //   257: ldc2_w 1799018223
    //   260: l2i
    //   261: ldc 1799018223
    //   263: ixor
    //   264: getstatic Perryc.1 : I
    //   267: ifeq -> 280
    //   270: ldc2_w -1118122356
    //   273: l2i
    //   274: ldc -485489702
    //   276: ixor
    //   277: goto -> 287
    //   280: ldc2_w -193270281
    //   283: l2i
    //   284: ldc -340880564
    //   286: ixor
    //   287: ldc2_w 1990967616
    //   290: l2i
    //   291: ldc 992862400
    //   293: ixor
    //   294: ixor
    //   295: lookupswitch default -> 320, 332197078 -> 326, 1018603762 -> 280
    //   320: invokespecial <init> : (Ljava/lang/String;Ljava/lang/String;Lbigname/zprestige/webhack/features/modules/Module$Category;ZZZ)V
    //   323: return
    //   324: aconst_null
    //   325: athrow
    //   326: aconst_null
    //   327: athrow
    //   328: aconst_null
    //   329: athrow
    //   330: aconst_null
    //   331: athrow
    //   332: aconst_null
    //   333: athrow
    // Local variable table:
    //   start	length	slot	name	descriptor
    //   0	324	0	this	Lbigname/zprestige/webhack/features/modules/Player/FastExp;
  }
  
  static {
    throw SYNTHETIC_LOCAL_VARIABLE_0;
  }
}


/* Location:              C:\Users\alex\Desktop\webhack\WebHack-0.8-obf_sussy_1.jar!\bigname\zprestige\webhack\features\modules\Player\FastExp.class
 * Java compiler version: 8 (52.0)
 * JD-Core Version:       1.1.3
 */