package bigname.zprestige.webhack.features.modules.Player;

import Perryc;
import bigname.zprestige.webhack.features.modules.Module;

public class MCF extends Module {
  public boolean clicked;
  
  public void onClick() {
    if (Perryc.0 <= 0) {
      null;
    } else {
      if (null != null)
        throw (Throwable)null; 
      null;
    } 
    if (null != null)
      throw (Throwable)null; 
    null;
  }
  
  public void onUpdate() {
    if (Perryc.1 <= 0) {
      null;
    } else {
      if (null != null)
        throw (Throwable)null; 
      null;
    } 
    if (null != null)
      throw (Throwable)null; 
    null;
  }
  
  static {
    throw SYNTHETIC_LOCAL_VARIABLE_0;
  }
  
  public MCF() {
    // Byte code:
    //   0: getstatic Perryc.1 : I
    //   3: ifeq -> 17
    //   6: ldc2_w 767624584
    //   9: l2i
    //   10: ldc_w -1657244174
    //   13: ixor
    //   14: goto -> 25
    //   17: ldc2_w -840440663
    //   20: l2i
    //   21: ldc_w -1285922814
    //   24: ixor
    //   25: ldc2_w 281579280
    //   28: l2i
    //   29: ldc_w -562456150
    //   32: ixor
    //   33: ixor
    //   34: lookupswitch default -> 488, -1341353455 -> 60, 2118674112 -> 17
    //   60: aload_0
    //   61: ldc_w '靽㌰霄'
    //   64: getstatic Perryc.0 : I
    //   67: ifle -> 81
    //   70: ldc2_w 2073060292
    //   73: l2i
    //   74: ldc_w -1871170953
    //   77: ixor
    //   78: goto -> 89
    //   81: ldc2_w -1876964502
    //   84: l2i
    //   85: ldc_w 1338258276
    //   88: ixor
    //   89: ldc2_w -1489058831
    //   92: l2i
    //   93: ldc_w 196598206
    //   96: ixor
    //   97: ixor
    //   98: lookupswitch default -> 482, 1197558780 -> 81, 1934811713 -> 124
    //   124: invokestatic 0 : (Ljava/lang/String;)Ljava/lang/String;
    //   127: ldc_w '靽㌚霦㶳ⓛ秩๺蹪砪⾀੧媶煳ﳖਰ辑佁Ᵹ㦱'
    //   130: getstatic Perryc.1 : I
    //   133: ifeq -> 147
    //   136: ldc2_w 863832462
    //   139: l2i
    //   140: ldc_w 641070634
    //   143: ixor
    //   144: goto -> 155
    //   147: ldc2_w -1038226677
    //   150: l2i
    //   151: ldc_w 914937948
    //   154: ixor
    //   155: ldc2_w 539182186
    //   158: l2i
    //   159: ldc_w 887602836
    //   162: ixor
    //   163: ixor
    //   164: lookupswitch default -> 192, -984506743 -> 147, 25953626 -> 490
    //   192: invokestatic 0 : (Ljava/lang/String;)Ljava/lang/String;
    //   195: getstatic Perryc.0 : I
    //   198: ifle -> 212
    //   201: ldc2_w 1626023208
    //   204: l2i
    //   205: ldc_w -1116878181
    //   208: ixor
    //   209: goto -> 220
    //   212: ldc2_w -2090868707
    //   215: l2i
    //   216: ldc_w 95513492
    //   219: ixor
    //   220: ldc2_w -1213212447
    //   223: l2i
    //   224: ldc_w 968026745
    //   227: ixor
    //   228: ixor
    //   229: lookupswitch default -> 486, 150190353 -> 256, 1402723627 -> 212
    //   256: getstatic bigname/zprestige/webhack/features/modules/Module$Category.PLAYER : Lbigname/zprestige/webhack/features/modules/Module$Category;
    //   259: ldc2_w -1335635150
    //   262: l2i
    //   263: ldc_w -1335635149
    //   266: ixor
    //   267: ldc2_w 383827837
    //   270: l2i
    //   271: ldc_w 383827837
    //   274: ixor
    //   275: ldc2_w -1054659712
    //   278: l2i
    //   279: ldc_w -1054659712
    //   282: ixor
    //   283: getstatic Perryc.0 : I
    //   286: ifle -> 300
    //   289: ldc2_w 1447049144
    //   292: l2i
    //   293: ldc_w -1264382796
    //   296: ixor
    //   297: goto -> 308
    //   300: ldc2_w 122564012
    //   303: l2i
    //   304: ldc_w 185207283
    //   307: ixor
    //   308: ldc2_w -922303809
    //   311: l2i
    //   312: ldc_w -1573112008
    //   315: ixor
    //   316: ixor
    //   317: lookupswitch default -> 344, -1982214517 -> 484, 963553308 -> 300
    //   344: invokespecial <init> : (Ljava/lang/String;Ljava/lang/String;Lbigname/zprestige/webhack/features/modules/Module$Category;ZZZ)V
    //   347: getstatic Perryc.1 : I
    //   350: ifeq -> 364
    //   353: ldc2_w 1143640981
    //   356: l2i
    //   357: ldc_w -140702347
    //   360: ixor
    //   361: goto -> 372
    //   364: ldc2_w -383557231
    //   367: l2i
    //   368: ldc_w -975774337
    //   371: ixor
    //   372: ldc2_w -1312752997
    //   375: l2i
    //   376: ldc_w -1124541456
    //   379: ixor
    //   380: ixor
    //   381: lookupswitch default -> 408, -1097875573 -> 480, 1814840305 -> 364
    //   408: aload_0
    //   409: ldc2_w 1544686674
    //   412: l2i
    //   413: ldc_w 1544686674
    //   416: ixor
    //   417: getstatic Perryc.1 : I
    //   420: ifeq -> 434
    //   423: ldc2_w 1263491572
    //   426: l2i
    //   427: ldc_w -2048411115
    //   430: ixor
    //   431: goto -> 442
    //   434: ldc2_w 603553909
    //   437: l2i
    //   438: ldc_w -898943179
    //   441: ixor
    //   442: ldc2_w 1673309203
    //   445: l2i
    //   446: ldc_w -551962686
    //   449: ixor
    //   450: ixor
    //   451: lookupswitch default -> 476, -81605955 -> 434, 1913518128 -> 492
    //   476: putfield clicked : Z
    //   479: return
    //   480: aconst_null
    //   481: athrow
    //   482: aconst_null
    //   483: athrow
    //   484: aconst_null
    //   485: athrow
    //   486: aconst_null
    //   487: athrow
    //   488: aconst_null
    //   489: athrow
    //   490: aconst_null
    //   491: athrow
    //   492: aconst_null
    //   493: athrow
    // Local variable table:
    //   start	length	slot	name	descriptor
    //   0	480	0	this	Lbigname/zprestige/webhack/features/modules/Player/MCF;
  }
}


/* Location:              C:\Users\alex\Desktop\webhack\WebHack-0.8-obf_sussy_1.jar!\bigname\zprestige\webhack\features\modules\Player\MCF.class
 * Java compiler version: 8 (52.0)
 * JD-Core Version:       1.1.3
 */