package bigname.zprestige.webhack.features.modules.Player;

public class Speedmine$1 {
  public static int[] $SwitchMap$bigname$zprestige$webhack$features$modules$Player$Speedmine$Mode;
  
  static {
    // Byte code:
    //   0: getstatic Perryc.c : I
    //   3: iflt -> 16
    //   6: ldc2_w 1449912446
    //   9: l2i
    //   10: ldc -76798146
    //   12: ixor
    //   13: goto -> 23
    //   16: ldc2_w -1103202417
    //   19: l2i
    //   20: ldc 1638079247
    //   22: ixor
    //   23: ldc2_w 732582683
    //   26: l2i
    //   27: ldc 1371379548
    //   29: ixor
    //   30: ixor
    //   31: lookupswitch default -> 884, -1517639481 -> 56, -686814457 -> 16
    //   56: invokestatic values : ()[Lbigname/zprestige/webhack/features/modules/Player/Speedmine$Mode;
    //   59: arraylength
    //   60: newarray int
    //   62: getstatic Perryc.c : I
    //   65: iflt -> 78
    //   68: ldc2_w -557053816
    //   71: l2i
    //   72: ldc 35087005
    //   74: ixor
    //   75: goto -> 85
    //   78: ldc2_w -1290522588
    //   81: l2i
    //   82: ldc -290491134
    //   84: ixor
    //   85: ldc2_w 821576425
    //   88: l2i
    //   89: ldc -1344086381
    //   91: ixor
    //   92: ixor
    //   93: lookupswitch default -> 890, -1029580452 -> 120, 1136785007 -> 78
    //   120: putstatic bigname/zprestige/webhack/features/modules/Player/Speedmine$1.$SwitchMap$bigname$zprestige$webhack$features$modules$Player$Speedmine$Mode : [I
    //   123: getstatic Perryc.c : I
    //   126: iflt -> 139
    //   129: ldc2_w -2137173922
    //   132: l2i
    //   133: ldc 1616777166
    //   135: ixor
    //   136: goto -> 146
    //   139: ldc2_w 1957016387
    //   142: l2i
    //   143: ldc -1693289342
    //   145: ixor
    //   146: ldc2_w -1168165197
    //   149: l2i
    //   150: ldc 1387914046
    //   152: ixor
    //   153: ixor
    //   154: lookupswitch default -> 878, 122753612 -> 180, 136677917 -> 139
    //   180: getstatic bigname/zprestige/webhack/features/modules/Player/Speedmine$1.$SwitchMap$bigname$zprestige$webhack$features$modules$Player$Speedmine$Mode : [I
    //   183: getstatic Perryc.1 : I
    //   186: ifeq -> 199
    //   189: ldc2_w 1739901021
    //   192: l2i
    //   193: ldc 1090267456
    //   195: ixor
    //   196: goto -> 206
    //   199: ldc2_w -1127110437
    //   202: l2i
    //   203: ldc 1608223118
    //   205: ixor
    //   206: ldc2_w 296361950
    //   209: l2i
    //   210: ldc -406572956
    //   212: ixor
    //   213: ixor
    //   214: lookupswitch default -> 898, -785985881 -> 199, 358878959 -> 240
    //   240: getstatic bigname/zprestige/webhack/features/modules/Player/Speedmine$Mode.PACKET : Lbigname/zprestige/webhack/features/modules/Player/Speedmine$Mode;
    //   243: getstatic Perryc.1 : I
    //   246: ifeq -> 259
    //   249: ldc2_w -1091259159
    //   252: l2i
    //   253: ldc -1626945141
    //   255: ixor
    //   256: goto -> 266
    //   259: ldc2_w -1924948021
    //   262: l2i
    //   263: ldc -241256279
    //   265: ixor
    //   266: ldc2_w -1570861147
    //   269: l2i
    //   270: ldc -582636207
    //   272: ixor
    //   273: ixor
    //   274: lookupswitch default -> 300, 1592352662 -> 880, 1961498786 -> 259
    //   300: invokevirtual ordinal : ()I
    //   303: ldc2_w 878194768
    //   306: l2i
    //   307: ldc 878194769
    //   309: ixor
    //   310: iastore
    //   311: goto -> 373
    //   314: getstatic Perryc.1 : I
    //   317: ifeq -> 330
    //   320: ldc2_w 1829169084
    //   323: l2i
    //   324: ldc -973146492
    //   326: ixor
    //   327: goto -> 337
    //   330: ldc2_w -1935544207
    //   333: l2i
    //   334: ldc 660835347
    //   336: ixor
    //   337: ldc2_w 114252372
    //   340: l2i
    //   341: ldc -631878086
    //   343: ixor
    //   344: ixor
    //   345: lookupswitch default -> 372, -1678427872 -> 330, 1952515414 -> 886
    //   372: astore_0
    //   373: getstatic Perryc.1 : I
    //   376: ifeq -> 389
    //   379: ldc2_w -1586826056
    //   382: l2i
    //   383: ldc -974264646
    //   385: ixor
    //   386: goto -> 396
    //   389: ldc2_w 1666957169
    //   392: l2i
    //   393: ldc -330334682
    //   395: ixor
    //   396: ldc2_w 1355483880
    //   399: l2i
    //   400: ldc 1058202249
    //   402: ixor
    //   403: ixor
    //   404: lookupswitch default -> 432, 190773859 -> 892, 1209708303 -> 389
    //   432: getstatic bigname/zprestige/webhack/features/modules/Player/Speedmine$1.$SwitchMap$bigname$zprestige$webhack$features$modules$Player$Speedmine$Mode : [I
    //   435: getstatic Perryc.c : I
    //   438: iflt -> 451
    //   441: ldc2_w 2019074205
    //   444: l2i
    //   445: ldc 2004939277
    //   447: ixor
    //   448: goto -> 458
    //   451: ldc2_w 670804845
    //   454: l2i
    //   455: ldc 139784080
    //   457: ixor
    //   458: ldc2_w 1315986891
    //   461: l2i
    //   462: ldc -731910611
    //   464: ixor
    //   465: ixor
    //   466: lookupswitch default -> 900, -1778917002 -> 451, -1249839333 -> 492
    //   492: getstatic bigname/zprestige/webhack/features/modules/Player/Speedmine$Mode.DAMAGE : Lbigname/zprestige/webhack/features/modules/Player/Speedmine$Mode;
    //   495: getstatic Perryc.c : I
    //   498: iflt -> 511
    //   501: ldc2_w -1799630830
    //   504: l2i
    //   505: ldc 912651882
    //   507: ixor
    //   508: goto -> 518
    //   511: ldc2_w -844738171
    //   514: l2i
    //   515: ldc 483357113
    //   517: ixor
    //   518: ldc2_w 1172678205
    //   521: l2i
    //   522: ldc -60483218
    //   524: ixor
    //   525: ixor
    //   526: lookupswitch default -> 552, 459184427 -> 896, 1935480405 -> 511
    //   552: invokevirtual ordinal : ()I
    //   555: ldc2_w 416413102
    //   558: l2i
    //   559: ldc 416413100
    //   561: ixor
    //   562: iastore
    //   563: goto -> 625
    //   566: getstatic Perryc.1 : I
    //   569: ifeq -> 582
    //   572: ldc2_w -1262239109
    //   575: l2i
    //   576: ldc 680001454
    //   578: ixor
    //   579: goto -> 589
    //   582: ldc2_w -597273182
    //   585: l2i
    //   586: ldc -1820966500
    //   588: ixor
    //   589: ldc2_w -1619340592
    //   592: l2i
    //   593: ldc 1857328470
    //   595: ixor
    //   596: ixor
    //   597: lookupswitch default -> 624, 1262369154 -> 582, 1837791827 -> 882
    //   624: astore_0
    //   625: getstatic Perryc.0 : I
    //   628: ifle -> 641
    //   631: ldc2_w -1039086940
    //   634: l2i
    //   635: ldc 528798061
    //   637: ixor
    //   638: goto -> 648
    //   641: ldc2_w -435907923
    //   644: l2i
    //   645: ldc -1457565835
    //   647: ixor
    //   648: ldc2_w 1040478512
    //   651: l2i
    //   652: ldc 1451652721
    //   654: ixor
    //   655: ixor
    //   656: lookupswitch default -> 684, -1256842104 -> 888, 1956173339 -> 641
    //   684: getstatic bigname/zprestige/webhack/features/modules/Player/Speedmine$1.$SwitchMap$bigname$zprestige$webhack$features$modules$Player$Speedmine$Mode : [I
    //   687: getstatic Perryc.1 : I
    //   690: ifeq -> 703
    //   693: ldc2_w -1640981945
    //   696: l2i
    //   697: ldc 1642829224
    //   699: ixor
    //   700: goto -> 710
    //   703: ldc2_w -85812179
    //   706: l2i
    //   707: ldc -1116144753
    //   709: ixor
    //   710: ldc2_w -1515537204
    //   713: l2i
    //   714: ldc -204597834
    //   716: ixor
    //   717: ixor
    //   718: lookupswitch default -> 744, -1447057771 -> 894, -507710722 -> 703
    //   744: getstatic bigname/zprestige/webhack/features/modules/Player/Speedmine$Mode.INSTANT : Lbigname/zprestige/webhack/features/modules/Player/Speedmine$Mode;
    //   747: getstatic Perryc.1 : I
    //   750: ifeq -> 763
    //   753: ldc2_w -2082388642
    //   756: l2i
    //   757: ldc -135927799
    //   759: ixor
    //   760: goto -> 770
    //   763: ldc2_w 852898724
    //   766: l2i
    //   767: ldc -1935360377
    //   769: ixor
    //   770: ldc2_w -883387678
    //   773: l2i
    //   774: ldc 433285293
    //   776: ixor
    //   777: ixor
    //   778: lookupswitch default -> 904, -1500555496 -> 763, 1828288364 -> 804
    //   804: invokevirtual ordinal : ()I
    //   807: ldc2_w 716752654
    //   810: l2i
    //   811: ldc 716752653
    //   813: ixor
    //   814: iastore
    //   815: goto -> 877
    //   818: getstatic Perryc.1 : I
    //   821: ifeq -> 834
    //   824: ldc2_w -1582921362
    //   827: l2i
    //   828: ldc -1772084695
    //   830: ixor
    //   831: goto -> 841
    //   834: ldc2_w 808475257
    //   837: l2i
    //   838: ldc 1811311047
    //   840: ixor
    //   841: ldc2_w 669414926
    //   844: l2i
    //   845: ldc -539630795
    //   847: ixor
    //   848: ixor
    //   849: lookupswitch default -> 876, -806011268 -> 902, 1084718413 -> 834
    //   876: astore_0
    //   877: return
    //   878: aconst_null
    //   879: athrow
    //   880: aconst_null
    //   881: athrow
    //   882: aconst_null
    //   883: athrow
    //   884: aconst_null
    //   885: athrow
    //   886: aconst_null
    //   887: athrow
    //   888: aconst_null
    //   889: athrow
    //   890: aconst_null
    //   891: athrow
    //   892: aconst_null
    //   893: athrow
    //   894: aconst_null
    //   895: athrow
    //   896: aconst_null
    //   897: athrow
    //   898: aconst_null
    //   899: athrow
    //   900: aconst_null
    //   901: athrow
    //   902: aconst_null
    //   903: athrow
    //   904: aconst_null
    //   905: athrow
    // Exception table:
    //   from	to	target	type
    //   123	311	314	java/lang/NoSuchFieldError
    //   373	563	566	java/lang/NoSuchFieldError
    //   625	815	818	java/lang/NoSuchFieldError
  }
}


/* Location:              C:\Users\alex\Desktop\webhack\WebHack-0.8-obf_sussy_1.jar!\bigname\zprestige\webhack\features\modules\Player\Speedmine$1.class
 * Java compiler version: 8 (52.0)
 * JD-Core Version:       1.1.3
 */