package bigname.zprestige.webhack.features.gui.components.items.buttons;

import Perry1;
import Perryc;
import bigname.zprestige.webhack.features.setting.Setting;

public class BindButton extends Button {
  public Setting setting;
  
  public boolean isListening;
  
  public void onKeyTyped(char typedChar, int keyCode) {
    if (Perryc.c < 0) {
      null;
    } else {
      if (null != null)
        throw (Throwable)null; 
      null;
    } 
    if (null != null)
      throw (Throwable)null; 
    null;
  }
  
  public int getHeight() {
    return Perry1.36(this, (int)863594414L ^ 0x351503C1);
  }
  
  public void toggle() {
    Perry1.3W(this, (int)-843476085L ^ 0xB9CD7B54);
  }
  
  public void drawScreen(int mouseX, int mouseY, float partialTicks) {
    if (Perryc.1 <= 0) {
      null;
    } else {
      if (null != null)
        throw (Throwable)null; 
      null;
    } 
    if (null != null)
      throw (Throwable)null; 
    null;
  }
  
  public void update() {
    Perry1.3m(this, (int)-447336050L ^ 0x80BF168C);
  }
  
  public BindButton(Setting setting) {
    // Byte code:
    //   0: getstatic Perryc.1 : I
    //   3: ifeq -> 17
    //   6: ldc2_w 811543713
    //   9: l2i
    //   10: ldc_w -1716444689
    //   13: ixor
    //   14: goto -> 25
    //   17: ldc2_w -1453679638
    //   20: l2i
    //   21: ldc_w -654389602
    //   24: ixor
    //   25: ldc2_w -784585978
    //   28: l2i
    //   29: ldc_w 1040740015
    //   32: ixor
    //   33: ixor
    //   34: lookupswitch default -> 60, -1784063940 -> 17, 1188710631 -> 572
    //   60: aload_0
    //   61: getstatic Perryc.1 : I
    //   64: ifeq -> 78
    //   67: ldc2_w 851088455
    //   70: l2i
    //   71: ldc_w -43911668
    //   74: ixor
    //   75: goto -> 86
    //   78: ldc2_w -2002029348
    //   81: l2i
    //   82: ldc_w 1564806891
    //   85: ixor
    //   86: ldc2_w -2114552053
    //   89: l2i
    //   90: ldc_w -1072044777
    //   93: ixor
    //   94: ixor
    //   95: lookupswitch default -> 580, -1909131177 -> 78, -1811816405 -> 120
    //   120: aload_1
    //   121: getstatic Perryc.c : I
    //   124: iflt -> 138
    //   127: ldc2_w -243353162
    //   130: l2i
    //   131: ldc_w 1693230950
    //   134: ixor
    //   135: goto -> 146
    //   138: ldc2_w -1017757291
    //   141: l2i
    //   142: ldc_w -610243030
    //   145: ixor
    //   146: ldc2_w -614780314
    //   149: l2i
    //   150: ldc_w 1058326470
    //   153: ixor
    //   154: ixor
    //   155: lookupswitch default -> 180, -1461218608 -> 138, 1910369136 -> 574
    //   180: invokevirtual getName : ()Ljava/lang/String;
    //   183: getstatic Perryc.0 : I
    //   186: ifle -> 200
    //   189: ldc2_w -633014125
    //   192: l2i
    //   193: ldc_w 2127373176
    //   196: ixor
    //   197: goto -> 208
    //   200: ldc2_w -567701348
    //   203: l2i
    //   204: ldc_w 1298958460
    //   207: ixor
    //   208: ldc2_w -1519124525
    //   211: l2i
    //   212: ldc_w 338949082
    //   215: ixor
    //   216: ixor
    //   217: lookupswitch default -> 566, 365549538 -> 200, 570758377 -> 244
    //   244: invokespecial <init> : (Ljava/lang/String;)V
    //   247: getstatic Perryc.c : I
    //   250: iflt -> 264
    //   253: ldc2_w 1199670111
    //   256: l2i
    //   257: ldc_w 1033726046
    //   260: ixor
    //   261: goto -> 272
    //   264: ldc2_w -1875806632
    //   267: l2i
    //   268: ldc_w -202652302
    //   271: ixor
    //   272: ldc2_w 788685690
    //   275: l2i
    //   276: ldc_w 2105462911
    //   279: ixor
    //   280: ixor
    //   281: lookupswitch default -> 308, -643207324 -> 264, 677402628 -> 570
    //   308: aload_0
    //   309: getstatic Perryc.1 : I
    //   312: ifeq -> 326
    //   315: ldc2_w -1092190548
    //   318: l2i
    //   319: ldc_w -1060964512
    //   322: ixor
    //   323: goto -> 334
    //   326: ldc2_w 1885290107
    //   329: l2i
    //   330: ldc_w -629742607
    //   333: ixor
    //   334: ldc2_w -323016655
    //   337: l2i
    //   338: ldc_w 1551925845
    //   341: ixor
    //   342: ixor
    //   343: lookupswitch default -> 368, -837082200 -> 578, 1769543145 -> 326
    //   368: aload_1
    //   369: getstatic Perryc.c : I
    //   372: iflt -> 386
    //   375: ldc2_w -1193525013
    //   378: l2i
    //   379: ldc_w 2099680506
    //   382: ixor
    //   383: goto -> 394
    //   386: ldc2_w -1526953880
    //   389: l2i
    //   390: ldc_w 122633972
    //   393: ixor
    //   394: ldc2_w 1166719493
    //   397: l2i
    //   398: ldc_w -880949876
    //   401: ixor
    //   402: ixor
    //   403: lookupswitch default -> 428, -1663106596 -> 386, 1259187096 -> 564
    //   428: putfield setting : Lbigname/zprestige/webhack/features/setting/Setting;
    //   431: getstatic Perryc.1 : I
    //   434: ifeq -> 448
    //   437: ldc2_w 134131405
    //   440: l2i
    //   441: ldc_w -1294382374
    //   444: ixor
    //   445: goto -> 456
    //   448: ldc2_w -1842131987
    //   451: l2i
    //   452: ldc_w -845262203
    //   455: ixor
    //   456: ldc2_w -1319035950
    //   459: l2i
    //   460: ldc_w -866207288
    //   463: ixor
    //   464: ixor
    //   465: lookupswitch default -> 576, -937933299 -> 448, 580041586 -> 492
    //   492: aload_0
    //   493: ldc2_w 137395650
    //   496: l2i
    //   497: ldc_w 137395661
    //   500: ixor
    //   501: getstatic Perryc.0 : I
    //   504: ifle -> 518
    //   507: ldc2_w -405548845
    //   510: l2i
    //   511: ldc_w 642860917
    //   514: ixor
    //   515: goto -> 526
    //   518: ldc2_w 1400316193
    //   521: l2i
    //   522: ldc_w 2039506904
    //   525: ixor
    //   526: ldc2_w 190951756
    //   529: l2i
    //   530: ldc_w 340055634
    //   533: ixor
    //   534: ixor
    //   535: lookupswitch default -> 560, -2130403973 -> 518, -559419208 -> 568
    //   560: putfield width : I
    //   563: return
    //   564: aconst_null
    //   565: athrow
    //   566: aconst_null
    //   567: athrow
    //   568: aconst_null
    //   569: athrow
    //   570: aconst_null
    //   571: athrow
    //   572: aconst_null
    //   573: athrow
    //   574: aconst_null
    //   575: athrow
    //   576: aconst_null
    //   577: athrow
    //   578: aconst_null
    //   579: athrow
    //   580: aconst_null
    //   581: athrow
    // Local variable table:
    //   start	length	slot	name	descriptor
    //   0	564	0	this	Lbigname/zprestige/webhack/features/gui/components/items/buttons/BindButton;
    //   0	564	1	setting	Lbigname/zprestige/webhack/features/setting/Setting;
  }
  
  public boolean getState() {
    return Perry1.4r(this, (int)1545133657L ^ 0x3253CFBF);
  }
  
  public void mouseClicked(int mouseX, int mouseY, int mouseButton) {
    if (Perryc.1 <= 0) {
      null;
    } else {
      if (null != null)
        throw (Throwable)null; 
      null;
    } 
    if (null != null)
      throw (Throwable)null; 
    null;
  }
  
  static {
    throw SYNTHETIC_LOCAL_VARIABLE_0;
  }
}


/* Location:              C:\Users\alex\Desktop\webhack\WebHack-0.8-obf_sussy_1.jar!\bigname\zprestige\webhack\features\gui\components\items\buttons\BindButton.class
 * Java compiler version: 8 (52.0)
 * JD-Core Version:       1.1.3
 */