package bigname.zprestige.webhack.features.gui.components.items.buttons;

import Perry1;
import Perryc;
import bigname.zprestige.webhack.features.setting.Setting;

public class EnumButton extends Button {
  public Setting setting;
  
  public void mouseClicked(int mouseX, int mouseY, int mouseButton) {
    if (Perryc.c < 0) {
      null;
    } else {
      if (null != null)
        throw (Throwable)null; 
      null;
    } 
    if (null != null)
      throw (Throwable)null; 
    null;
  }
  
  public int getHeight() {
    return Perry1.2T(this, (int)-455081187L ^ 0xC28AD458);
  }
  
  public void update() {
    Perry1.3L(this, (int)-1251971066L ^ 0xA45768CB);
  }
  
  public boolean getState() {
    return Perry1.4H(this, (int)823285636L ^ 0x42D4CFCB);
  }
  
  public EnumButton(Setting setting) {
    // Byte code:
    //   0: getstatic Perryc.1 : I
    //   3: ifeq -> 17
    //   6: ldc2_w -1649218447
    //   9: l2i
    //   10: ldc_w -573150826
    //   13: ixor
    //   14: goto -> 25
    //   17: ldc2_w 1261178
    //   20: l2i
    //   21: ldc_w -391696645
    //   24: ixor
    //   25: ldc2_w 55767746
    //   28: l2i
    //   29: ldc_w -1999992797
    //   32: ixor
    //   33: ixor
    //   34: lookupswitch default -> 572, -872612090 -> 17, 1663855200 -> 60
    //   60: aload_0
    //   61: getstatic Perryc.1 : I
    //   64: ifeq -> 78
    //   67: ldc2_w -1011715957
    //   70: l2i
    //   71: ldc_w 1608630344
    //   74: ixor
    //   75: goto -> 86
    //   78: ldc2_w 1838086410
    //   81: l2i
    //   82: ldc_w 816491529
    //   85: ixor
    //   86: ldc2_w 625946966
    //   89: l2i
    //   90: ldc_w 846758714
    //   93: ixor
    //   94: ixor
    //   95: lookupswitch default -> 576, -1956379985 -> 78, 1242818415 -> 120
    //   120: aload_1
    //   121: getstatic Perryc.1 : I
    //   124: ifeq -> 138
    //   127: ldc2_w 1504577590
    //   130: l2i
    //   131: ldc_w -1108335247
    //   134: ixor
    //   135: goto -> 146
    //   138: ldc2_w 1776764197
    //   141: l2i
    //   142: ldc_w -2077618797
    //   145: ixor
    //   146: ldc2_w -1005611903
    //   149: l2i
    //   150: ldc_w 1495091788
    //   153: ixor
    //   154: ixor
    //   155: lookupswitch default -> 578, 1893701243 -> 180, 2035086218 -> 138
    //   180: invokevirtual getName : ()Ljava/lang/String;
    //   183: getstatic Perryc.1 : I
    //   186: ifeq -> 200
    //   189: ldc2_w 1667167309
    //   192: l2i
    //   193: ldc_w 1949601265
    //   196: ixor
    //   197: goto -> 208
    //   200: ldc2_w 21063770
    //   203: l2i
    //   204: ldc_w 643870976
    //   207: ixor
    //   208: ldc2_w 2147117086
    //   211: l2i
    //   212: ldc_w 1778324209
    //   215: ixor
    //   216: ixor
    //   217: lookupswitch default -> 244, 24052563 -> 570, 1325427461 -> 200
    //   244: invokespecial <init> : (Ljava/lang/String;)V
    //   247: getstatic Perryc.0 : I
    //   250: ifle -> 264
    //   253: ldc2_w -1698846895
    //   256: l2i
    //   257: ldc_w -1091186420
    //   260: ixor
    //   261: goto -> 272
    //   264: ldc2_w -711529318
    //   267: l2i
    //   268: ldc_w 1308095987
    //   271: ixor
    //   272: ldc2_w -1916831065
    //   275: l2i
    //   276: ldc_w -840246585
    //   279: ixor
    //   280: ixor
    //   281: lookupswitch default -> 574, -667633399 -> 308, 1679676989 -> 264
    //   308: aload_0
    //   309: getstatic Perryc.c : I
    //   312: iflt -> 326
    //   315: ldc2_w -2134078497
    //   318: l2i
    //   319: ldc_w -102086460
    //   322: ixor
    //   323: goto -> 334
    //   326: ldc2_w 356684580
    //   329: l2i
    //   330: ldc_w 1005887616
    //   333: ixor
    //   334: ldc2_w 955122631
    //   337: l2i
    //   338: ldc_w -930896689
    //   341: ixor
    //   342: ixor
    //   343: lookupswitch default -> 368, -1991547885 -> 566, 1820524970 -> 326
    //   368: aload_1
    //   369: getstatic Perryc.1 : I
    //   372: ifeq -> 386
    //   375: ldc2_w 342174461
    //   378: l2i
    //   379: ldc_w -481136652
    //   382: ixor
    //   383: goto -> 394
    //   386: ldc2_w 1219662458
    //   389: l2i
    //   390: ldc_w 769191736
    //   393: ixor
    //   394: ldc2_w -980389847
    //   397: l2i
    //   398: ldc_w 1799346220
    //   401: ixor
    //   402: ixor
    //   403: lookupswitch default -> 428, -927104923 -> 386, 1503194380 -> 580
    //   428: putfield setting : Lbigname/zprestige/webhack/features/setting/Setting;
    //   431: getstatic Perryc.1 : I
    //   434: ifeq -> 448
    //   437: ldc2_w 1994654756
    //   440: l2i
    //   441: ldc_w -1502050367
    //   444: ixor
    //   445: goto -> 456
    //   448: ldc2_w -367145647
    //   451: l2i
    //   452: ldc_w 1907640484
    //   455: ixor
    //   456: ldc2_w 1373176288
    //   459: l2i
    //   460: ldc_w -201887941
    //   463: ixor
    //   464: ixor
    //   465: lookupswitch default -> 564, 965208878 -> 492, 1924328766 -> 448
    //   492: aload_0
    //   493: ldc2_w -288374872
    //   496: l2i
    //   497: ldc_w -288374873
    //   500: ixor
    //   501: getstatic Perryc.1 : I
    //   504: ifeq -> 518
    //   507: ldc2_w -1698358083
    //   510: l2i
    //   511: ldc_w 1785339010
    //   514: ixor
    //   515: goto -> 526
    //   518: ldc2_w 1683458361
    //   521: l2i
    //   522: ldc_w -1279715957
    //   525: ixor
    //   526: ldc2_w -1468009536
    //   529: l2i
    //   530: ldc_w 642620945
    //   533: ixor
    //   534: ixor
    //   535: lookupswitch default -> 560, 1438169240 -> 518, 2124246510 -> 568
    //   560: putfield width : I
    //   563: return
    //   564: aconst_null
    //   565: athrow
    //   566: aconst_null
    //   567: athrow
    //   568: aconst_null
    //   569: athrow
    //   570: aconst_null
    //   571: athrow
    //   572: aconst_null
    //   573: athrow
    //   574: aconst_null
    //   575: athrow
    //   576: aconst_null
    //   577: athrow
    //   578: aconst_null
    //   579: athrow
    //   580: aconst_null
    //   581: athrow
    // Local variable table:
    //   start	length	slot	name	descriptor
    //   0	564	0	this	Lbigname/zprestige/webhack/features/gui/components/items/buttons/EnumButton;
    //   0	564	1	setting	Lbigname/zprestige/webhack/features/setting/Setting;
  }
  
  public void toggle() {
    Perry1.3N(this, (int)458887773L ^ 0x100BBECC);
  }
  
  public void drawScreen(int mouseX, int mouseY, float partialTicks) {
    if (Perryc.1 <= 0) {
      null;
    } else {
      if (null != null)
        throw (Throwable)null; 
      null;
    } 
    if (null != null)
      throw (Throwable)null; 
    null;
  }
  
  static {
    throw SYNTHETIC_LOCAL_VARIABLE_0;
  }
}


/* Location:              C:\Users\alex\Desktop\webhack\WebHack-0.8-obf_sussy_1.jar!\bigname\zprestige\webhack\features\gui\components\items\buttons\EnumButton.class
 * Java compiler version: 8 (52.0)
 * JD-Core Version:       1.1.3
 */