package bigname.zprestige.webhack.features.gui.components.items.buttons;

import Perry1;
import Perryc;
import bigname.zprestige.webhack.features.gui.components.items.Item;
import bigname.zprestige.webhack.features.modules.Module;
import java.util.List;

public class ModuleButton extends Button {
  public Module module;
  
  public boolean subOpen;
  
  public List<Item> items;
  
  public Module getModule() {
    if (Perryc.1 <= 0) {
      null;
    } else {
      if (null != null)
        throw (Throwable)null; 
      null;
    } 
    if (null != null)
      throw (Throwable)null; 
    null;
  }
  
  public void mouseClicked(int mouseX, int mouseY, int mouseButton) {
    if (Perryc.1 <= 0) {
      null;
    } else {
      if (null != null)
        throw (Throwable)null; 
      null;
    } 
    if (null != null)
      throw (Throwable)null; 
    null;
  }
  
  public int getHeight() {
    if (Perryc.1 <= 0) {
      null;
    } else {
      if (null != null)
        throw (Throwable)null; 
      null;
    } 
    if (null != null)
      throw (Throwable)null; 
    null;
  }
  
  public boolean getState() {
    return Perry1.4I(this, (int)-1207685778L ^ 0xC132B295);
  }
  
  public static void drawCompleteImage(float posX, float posY, int width, int height) {
    if (Perryc.0 <= 0) {
      null;
    } else {
      if (null != null)
        throw (Throwable)null; 
      null;
    } 
    if (null != null)
      throw (Throwable)null; 
    null;
  }
  
  public ModuleButton(Module module) {
    // Byte code:
    //   0: getstatic Perryc.1 : I
    //   3: ifeq -> 17
    //   6: ldc2_w -1410312889
    //   9: l2i
    //   10: ldc_w -1486823843
    //   13: ixor
    //   14: goto -> 25
    //   17: ldc2_w -606330540
    //   20: l2i
    //   21: ldc_w -2098665719
    //   24: ixor
    //   25: ldc2_w 1021032683
    //   28: l2i
    //   29: ldc_w -701583194
    //   32: ixor
    //   33: ixor
    //   34: lookupswitch default -> 756, -1279144432 -> 60, -429554857 -> 17
    //   60: aload_0
    //   61: getstatic Perryc.0 : I
    //   64: ifle -> 78
    //   67: ldc2_w 175280841
    //   70: l2i
    //   71: ldc_w -2088479474
    //   74: ixor
    //   75: goto -> 86
    //   78: ldc2_w -971484574
    //   81: l2i
    //   82: ldc_w 2121323897
    //   85: ixor
    //   86: ldc2_w -1461045269
    //   89: l2i
    //   90: ldc_w 1954008273
    //   93: ixor
    //   94: ixor
    //   95: lookupswitch default -> 120, 516453246 -> 78, 1433091325 -> 748
    //   120: aload_1
    //   121: getstatic Perryc.0 : I
    //   124: ifle -> 138
    //   127: ldc2_w -752076162
    //   130: l2i
    //   131: ldc_w 1194113452
    //   134: ixor
    //   135: goto -> 146
    //   138: ldc2_w -393897346
    //   141: l2i
    //   142: ldc_w -1756800832
    //   145: ixor
    //   146: ldc2_w -1446031823
    //   149: l2i
    //   150: ldc_w 1723753580
    //   153: ixor
    //   154: ixor
    //   155: lookupswitch default -> 768, -1329731357 -> 180, 1534175631 -> 138
    //   180: invokevirtual getName : ()Ljava/lang/String;
    //   183: getstatic Perryc.1 : I
    //   186: ifeq -> 200
    //   189: ldc2_w -113751642
    //   192: l2i
    //   193: ldc_w -1084131997
    //   196: ixor
    //   197: goto -> 208
    //   200: ldc2_w -102755837
    //   203: l2i
    //   204: ldc_w -1510697052
    //   207: ixor
    //   208: ldc2_w -1730264701
    //   211: l2i
    //   212: ldc_w -1022625914
    //   215: ixor
    //   216: ixor
    //   217: lookupswitch default -> 244, -43793662 -> 200, 495749824 -> 750
    //   244: invokespecial <init> : (Ljava/lang/String;)V
    //   247: getstatic Perryc.0 : I
    //   250: ifle -> 264
    //   253: ldc2_w -1428335206
    //   256: l2i
    //   257: ldc_w 285127840
    //   260: ixor
    //   261: goto -> 272
    //   264: ldc2_w -2005453004
    //   267: l2i
    //   268: ldc_w -1985316424
    //   271: ixor
    //   272: ldc2_w 219494825
    //   275: l2i
    //   276: ldc_w -1809614819
    //   279: ixor
    //   280: ixor
    //   281: lookupswitch default -> 770, -1729425608 -> 308, 588619918 -> 264
    //   308: aload_0
    //   309: new java/util/ArrayList
    //   312: dup
    //   313: getstatic Perryc.0 : I
    //   316: ifle -> 330
    //   319: ldc2_w -673775917
    //   322: l2i
    //   323: ldc_w 1741049154
    //   326: ixor
    //   327: goto -> 338
    //   330: ldc2_w -1816294013
    //   333: l2i
    //   334: ldc_w -1918128258
    //   337: ixor
    //   338: ldc2_w 1985205907
    //   341: l2i
    //   342: ldc_w -1902087045
    //   345: ixor
    //   346: ixor
    //   347: lookupswitch default -> 762, -421167083 -> 372, 1222840697 -> 330
    //   372: invokespecial <init> : ()V
    //   375: getstatic Perryc.0 : I
    //   378: ifle -> 392
    //   381: ldc2_w 1574791071
    //   384: l2i
    //   385: ldc_w 117385745
    //   388: ixor
    //   389: goto -> 400
    //   392: ldc2_w -234542027
    //   395: l2i
    //   396: ldc_w 1772160689
    //   399: ixor
    //   400: ldc2_w 271757884
    //   403: l2i
    //   404: ldc_w 1498239524
    //   407: ixor
    //   408: ixor
    //   409: lookupswitch default -> 436, -71757665 -> 392, 308129174 -> 758
    //   436: putfield items : Ljava/util/List;
    //   439: getstatic Perryc.c : I
    //   442: iflt -> 456
    //   445: ldc2_w 156120776
    //   448: l2i
    //   449: ldc_w 2123432966
    //   452: ixor
    //   453: goto -> 464
    //   456: ldc2_w -1770278298
    //   459: l2i
    //   460: ldc_w -1340073860
    //   463: ixor
    //   464: ldc2_w 2143633532
    //   467: l2i
    //   468: ldc_w -455784442
    //   471: ixor
    //   472: ixor
    //   473: lookupswitch default -> 764, -1119116704 -> 500, -321963340 -> 456
    //   500: aload_0
    //   501: getstatic Perryc.c : I
    //   504: iflt -> 518
    //   507: ldc2_w 556084882
    //   510: l2i
    //   511: ldc_w -1015476238
    //   514: ixor
    //   515: goto -> 526
    //   518: ldc2_w 1274682560
    //   521: l2i
    //   522: ldc_w -561444059
    //   525: ixor
    //   526: ldc2_w 728737792
    //   529: l2i
    //   530: ldc_w 508033447
    //   533: ixor
    //   534: ixor
    //   535: lookupswitch default -> 560, -680234809 -> 766, 38367156 -> 518
    //   560: aload_1
    //   561: getstatic Perryc.1 : I
    //   564: ifeq -> 578
    //   567: ldc2_w -522956411
    //   570: l2i
    //   571: ldc_w -1027310931
    //   574: ixor
    //   575: goto -> 586
    //   578: ldc2_w -1439681579
    //   581: l2i
    //   582: ldc_w -1405904472
    //   585: ixor
    //   586: ldc2_w 724896470
    //   589: l2i
    //   590: ldc_w -224510881
    //   593: ixor
    //   594: ixor
    //   595: lookupswitch default -> 620, -1039383180 -> 578, -71623263 -> 760
    //   620: putfield module : Lbigname/zprestige/webhack/features/modules/Module;
    //   623: getstatic Perryc.0 : I
    //   626: ifle -> 640
    //   629: ldc2_w 1884026873
    //   632: l2i
    //   633: ldc_w 1564581293
    //   636: ixor
    //   637: goto -> 648
    //   640: ldc2_w -1298184009
    //   643: l2i
    //   644: ldc_w 1975596093
    //   647: ixor
    //   648: ldc2_w 1247686318
    //   651: l2i
    //   652: ldc_w -1678522043
    //   655: ixor
    //   656: ixor
    //   657: lookupswitch default -> 684, -56128065 -> 752, 1189857823 -> 640
    //   684: aload_0
    //   685: getstatic Perryc.c : I
    //   688: iflt -> 702
    //   691: ldc2_w 627850811
    //   694: l2i
    //   695: ldc_w 1279701243
    //   698: ixor
    //   699: goto -> 710
    //   702: ldc2_w 782082486
    //   705: l2i
    //   706: ldc_w 268791470
    //   709: ixor
    //   710: ldc2_w 1349301314
    //   713: l2i
    //   714: ldc_w 1095452037
    //   717: ixor
    //   718: ixor
    //   719: lookupswitch default -> 744, 1122778622 -> 702, 2014150407 -> 754
    //   744: invokevirtual initSettings : ()V
    //   747: return
    //   748: aconst_null
    //   749: athrow
    //   750: aconst_null
    //   751: athrow
    //   752: aconst_null
    //   753: athrow
    //   754: aconst_null
    //   755: athrow
    //   756: aconst_null
    //   757: athrow
    //   758: aconst_null
    //   759: athrow
    //   760: aconst_null
    //   761: athrow
    //   762: aconst_null
    //   763: athrow
    //   764: aconst_null
    //   765: athrow
    //   766: aconst_null
    //   767: athrow
    //   768: aconst_null
    //   769: athrow
    //   770: aconst_null
    //   771: athrow
    // Local variable table:
    //   start	length	slot	name	descriptor
    //   0	748	0	this	Lbigname/zprestige/webhack/features/gui/components/items/buttons/ModuleButton;
    //   0	748	1	module	Lbigname/zprestige/webhack/features/modules/Module;
  }
  
  public void drawScreen(int mouseX, int mouseY, float partialTicks) {
    if (Perryc.c < 0) {
      null;
    } else {
      if (null != null)
        throw (Throwable)null; 
      null;
    } 
    if (null != null)
      throw (Throwable)null; 
    null;
  }
  
  static {
    throw SYNTHETIC_LOCAL_VARIABLE_0;
  }
  
  public void initSettings() {
    if (Perryc.c < 0) {
      null;
    } else {
      if (null != null)
        throw (Throwable)null; 
      null;
    } 
    if (null != null)
      throw (Throwable)null; 
    null;
  }
  
  public void onKeyTyped(char typedChar, int keyCode) {
    if (Perryc.1 <= 0) {
      null;
    } else {
      if (null != null)
        throw (Throwable)null; 
      null;
    } 
    if (null != null)
      throw (Throwable)null; 
    null;
  }
  
  public void toggle() {
    Perry1.43(this, (int)910813032L ^ 0xCBCB631);
  }
}


/* Location:              C:\Users\alex\Desktop\webhack\WebHack-0.8-obf_sussy_1.jar!\bigname\zprestige\webhack\features\gui\components\items\buttons\ModuleButton.class
 * Java compiler version: 8 (52.0)
 * JD-Core Version:       1.1.3
 */