/*   */ package bigname.zprestige.webhack.features.gui.components.items.buttons;
/*   */ import bigname.zprestige.webhack.features.modules.Module;
/*   */ 
/*   */ public class SliderButton extends Module {
/*   */   public static boolean IdentifyBlockLimit() {
/* 6 */     return true;
/*   */   }
/*   */   
/*   */   static {
/*   */     throw SYNTHETIC_LOCAL_VARIABLE_0;
/*   */   }
/*   */   
/*   */   public SliderButton() {
/*   */     // Byte code:
/*   */     //   0: getstatic Perryc.1 : I
/*   */     //   3: ifeq -> 16
/*   */     //   6: ldc2_w -276577825
/*   */     //   9: l2i
/*   */     //   10: ldc -2016122687
/*   */     //   12: ixor
/*   */     //   13: goto -> 23
/*   */     //   16: ldc2_w 1175708150
/*   */     //   19: l2i
/*   */     //   20: ldc -2139761771
/*   */     //   22: ixor
/*   */     //   23: ldc2_w 1787836512
/*   */     //   26: l2i
/*   */     //   27: ldc 117101719
/*   */     //   29: ixor
/*   */     //   30: ixor
/*   */     //   31: lookupswitch default -> 56, 71124457 -> 324, 918430449 -> 16
/*   */     //   56: aload_0
/*   */     //   57: ldc '螂㌟蟊㶳㌳椟๛﨑蹷濜㽥਩'
/*   */     //   59: getstatic Perryc.1 : I
/*   */     //   62: ifeq -> 75
/*   */     //   65: ldc2_w 990866350
/*   */     //   68: l2i
/*   */     //   69: ldc -1324404117
/*   */     //   71: ixor
/*   */     //   72: goto -> 82
/*   */     //   75: ldc2_w 698007517
/*   */     //   78: l2i
/*   */     //   79: ldc -1121587062
/*   */     //   81: ixor
/*   */     //   82: ldc2_w 539245575
/*   */     //   85: l2i
/*   */     //   86: ldc 140005164
/*   */     //   88: ixor
/*   */     //   89: ixor
/*   */     //   90: lookupswitch default -> 328, -1568920850 -> 75, -1128055684 -> 116
/*   */     //   116: invokestatic 0 : (Ljava/lang/String;)Ljava/lang/String;
/*   */     //   119: ldc '螂㌟蟊㶳㌳椟๛﨑蹷濜㽥਩'
/*   */     //   121: getstatic Perryc.1 : I
/*   */     //   124: ifeq -> 137
/*   */     //   127: ldc2_w 926996128
/*   */     //   130: l2i
/*   */     //   131: ldc -1888050756
/*   */     //   133: ixor
/*   */     //   134: goto -> 144
/*   */     //   137: ldc2_w -1454192771
/*   */     //   140: l2i
/*   */     //   141: ldc -1193425973
/*   */     //   143: ixor
/*   */     //   144: ldc2_w -1647630396
/*   */     //   147: l2i
/*   */     //   148: ldc 1437078236
/*   */     //   150: ixor
/*   */     //   151: ixor
/*   */     //   152: lookupswitch default -> 180, 717520400 -> 137, 1884635652 -> 330
/*   */     //   180: invokestatic 0 : (Ljava/lang/String;)Ljava/lang/String;
/*   */     //   183: getstatic Perryc.c : I
/*   */     //   186: iflt -> 199
/*   */     //   189: ldc2_w 942078659
/*   */     //   192: l2i
/*   */     //   193: ldc -1371811995
/*   */     //   195: ixor
/*   */     //   196: goto -> 206
/*   */     //   199: ldc2_w -316447774
/*   */     //   202: l2i
/*   */     //   203: ldc -1763250886
/*   */     //   205: ixor
/*   */     //   206: ldc2_w -946799111
/*   */     //   209: l2i
/*   */     //   210: ldc 935204050
/*   */     //   212: ixor
/*   */     //   213: ixor
/*   */     //   214: lookupswitch default -> 332, -1947506701 -> 240, 1714674829 -> 199
/*   */     //   240: getstatic bigname/zprestige/webhack/features/modules/Module$Category.MISC : Lbigname/zprestige/webhack/features/modules/Module$Category;
/*   */     //   243: ldc2_w -1066127611
/*   */     //   246: l2i
/*   */     //   247: ldc -1066127612
/*   */     //   249: ixor
/*   */     //   250: ldc2_w 343079931
/*   */     //   253: l2i
/*   */     //   254: ldc 343079930
/*   */     //   256: ixor
/*   */     //   257: ldc2_w 1916667031
/*   */     //   260: l2i
/*   */     //   261: ldc 1916667031
/*   */     //   263: ixor
/*   */     //   264: getstatic Perryc.1 : I
/*   */     //   267: ifeq -> 280
/*   */     //   270: ldc2_w 751058715
/*   */     //   273: l2i
/*   */     //   274: ldc 2010925642
/*   */     //   276: ixor
/*   */     //   277: goto -> 287
/*   */     //   280: ldc2_w -572560209
/*   */     //   283: l2i
/*   */     //   284: ldc -1316184827
/*   */     //   286: ixor
/*   */     //   287: ldc2_w -241592189
/*   */     //   290: l2i
/*   */     //   291: ldc -779598168
/*   */     //   293: ixor
/*   */     //   294: ixor
/*   */     //   295: lookupswitch default -> 320, -574184484 -> 280, 2064231290 -> 326
/*   */     //   320: invokespecial <init> : (Ljava/lang/String;Ljava/lang/String;Lbigname/zprestige/webhack/features/modules/Module$Category;ZZZ)V
/*   */     //   323: return
/*   */     //   324: aconst_null
/*   */     //   325: athrow
/*   */     //   326: aconst_null
/*   */     //   327: athrow
/*   */     //   328: aconst_null
/*   */     //   329: athrow
/*   */     //   330: aconst_null
/*   */     //   331: athrow
/*   */     //   332: aconst_null
/*   */     //   333: athrow
/*   */     // Local variable table:
/*   */     //   start	length	slot	name	descriptor
/*   */     //   0	324	0	this	Lbigname/zprestige/webhack/features/gui/components/items/buttons/SliderButton;
/*   */   }
/*   */ }


/* Location:              C:\Users\alex\Desktop\webhack\WebHack-0.8-obf_sussy_1.jar!\bigname\zprestige\webhack\features\gui\components\items\buttons\SliderButton.class
 * Java compiler version: 8 (52.0)
 * JD-Core Version:       1.1.3
 */