package bigname.zprestige.webhack.features.gui.components.items.buttons;

import Perry1;

public class StringButton$CurrentString {
  public String string;
  
  static {
    throw SYNTHETIC_LOCAL_VARIABLE_0;
  }
  
  public StringButton$CurrentString(String string) {
    // Byte code:
    //   0: getstatic Perryc.1 : I
    //   3: ifeq -> 16
    //   6: ldc2_w -587161319
    //   9: l2i
    //   10: ldc -1190358656
    //   12: ixor
    //   13: goto -> 23
    //   16: ldc2_w -1343800840
    //   19: l2i
    //   20: ldc 2066648561
    //   22: ixor
    //   23: ldc2_w -2059976520
    //   26: l2i
    //   27: ldc -1541510949
    //   29: ixor
    //   30: ixor
    //   31: lookupswitch default -> 56, -1475547173 -> 16, 1160059130 -> 300
    //   56: aload_0
    //   57: getstatic Perryc.c : I
    //   60: iflt -> 73
    //   63: ldc2_w -1756645722
    //   66: l2i
    //   67: ldc 985336636
    //   69: ixor
    //   70: goto -> 80
    //   73: ldc2_w -492467826
    //   76: l2i
    //   77: ldc 556810551
    //   79: ixor
    //   80: ldc2_w -547386168
    //   83: l2i
    //   84: ldc 686505386
    //   86: ixor
    //   87: ixor
    //   88: lookupswitch default -> 116, -1020894839 -> 73, 1514409208 -> 304
    //   116: invokespecial <init> : ()V
    //   119: getstatic Perryc.1 : I
    //   122: ifeq -> 135
    //   125: ldc2_w -1098486557
    //   128: l2i
    //   129: ldc 1474300599
    //   131: ixor
    //   132: goto -> 142
    //   135: ldc2_w 1469451720
    //   138: l2i
    //   139: ldc -1484653428
    //   141: ixor
    //   142: ldc2_w 1943985286
    //   145: l2i
    //   146: ldc -1168094029
    //   148: ixor
    //   149: ixor
    //   150: lookupswitch default -> 308, 551089761 -> 135, 967401841 -> 176
    //   176: aload_0
    //   177: getstatic Perryc.1 : I
    //   180: ifeq -> 193
    //   183: ldc2_w 926956778
    //   186: l2i
    //   187: ldc 698215694
    //   189: ixor
    //   190: goto -> 200
    //   193: ldc2_w -1983347266
    //   196: l2i
    //   197: ldc 559998556
    //   199: ixor
    //   200: ldc2_w -318008899
    //   203: l2i
    //   204: ldc 237029352
    //   206: ixor
    //   207: ixor
    //   208: lookupswitch default -> 302, -34175055 -> 193, 1266890167 -> 236
    //   236: aload_1
    //   237: getstatic Perryc.c : I
    //   240: iflt -> 253
    //   243: ldc2_w -1718416680
    //   246: l2i
    //   247: ldc -1563574156
    //   249: ixor
    //   250: goto -> 260
    //   253: ldc2_w 58960994
    //   256: l2i
    //   257: ldc -1586504877
    //   259: ixor
    //   260: ldc2_w -1996136873
    //   263: l2i
    //   264: ldc 897588800
    //   266: ixor
    //   267: ixor
    //   268: lookupswitch default -> 306, -2015655237 -> 253, 510211878 -> 296
    //   296: putfield string : Ljava/lang/String;
    //   299: return
    //   300: aconst_null
    //   301: athrow
    //   302: aconst_null
    //   303: athrow
    //   304: aconst_null
    //   305: athrow
    //   306: aconst_null
    //   307: athrow
    //   308: aconst_null
    //   309: athrow
    // Local variable table:
    //   start	length	slot	name	descriptor
    //   0	300	0	this	Lbigname/zprestige/webhack/features/gui/components/items/buttons/StringButton$CurrentString;
    //   0	300	1	string	Ljava/lang/String;
  }
  
  public String getString() {
    return Perry1.3(this, (int)1935360424L ^ 0x516DF894);
  }
}


/* Location:              C:\Users\alex\Desktop\webhack\WebHack-0.8-obf_sussy_1.jar!\bigname\zprestige\webhack\features\gui\components\items\buttons\StringButton$CurrentString.class
 * Java compiler version: 8 (52.0)
 * JD-Core Version:       1.1.3
 */